{"id":"8ee3e8ab-abbb-4310-82ca-8b130bcf21aa","key":"05","link":"https://indra.ai/rigveda/books/05.html","hymns":[{"id":"d28c9d1a-134a-4aef-a2c7-baa368d83a91","key":"05001","book":"05","title":"HYMN I. Agni","link":"https://indra.ai/rigveda/hymns/05001.html","text":"p: Agni is wakened by the people's fuel to meet the Dawn who cometh like a MilchCow. Like young trees shooting up on high their branches, his flames are rising to the vault of heaven.\n\np: For worship of the Devas the Monk was wakened: at morning gracious Agni hath arisen. Kindled, his radiant might is made apparent, and the great Deity set free from darkness.\n\np: When he hath stirred the line of his attendants, with the pure milk pure Agni is anointed. The strength-bestowing gift is then made ready, which spread in front, with tongues, erect, he drinketh.\n\np: The spirits of the pious turn together to Agni, as the eyes of all to Surya. He, when both Dawns of different hues have borne him, springs up at daybreak as a strong white charger.\n\np: The noble One was born at days' beginning, laid red in colour mid the well-laid fuel. Yielding in every house his seven rich treasure.s, Agni is seated, Monk most skilled in worship.\n\np: Agni hath sat him down, a Monk most skilful, on a sweet-smelling place, his Mother's bosom. Young, faithful, sage, preeminent o’er many, kindled among the folk whom he sustaineth.\n\np: This Singer excellent at offers, Agni the Monk, they glorify with homage. Him who spread out both worlds by Law Eternal they balm with oil, strong Steed who never faileth.\n\np:  He, worshipful House-Friend, in his home is worshipped, our own auspicious guest, lauded by sages. That strength the Bull with thousand horns possesses. In might, O Agni, thou excellest others.\n\np: Thou quickly passest by all others, Agni, for him to whom thou hast appeared most lovely, Wondrously fair, adorable, effulgent, the guest of men, the darling of the people.\n\np: To thee, most Youthful Deva. to thee, O Agni from near and far the people bring their tribute. Mark well the prayer of him who best extols thee. Great, high, auspicious, Agni, is thy shelter.\n\np: Ascend to-day thy splendid car, O Agni, in splendour, with the Holy Ones around it. Knowing the paths by mid-air's spacious region bring hither Devas to feast on our oblation.\n\np: To him adorable, sage, strong and mighty we have sung forth our song of praise and homage. Gavisthira hath raised with prayer to Agni this laud far-reaching, like gold light to heaven.","people":["Agni","Deva","Surya","Attendants","Dawn"],"places":["Heaven","Mid-Air"],"things":["Worship","Holy Ones","Milk","Born","Law Eternal","Singer","Light","Air","Treasure","Men","Might","Song","Gold","Home","Strong","Mighty","Car","Praise","Gift","Ascend","Adorable","Splendour","Offers","Excellent","People","Tribute","Friend","Sage","Morning","MilchCow"],"groups":["Devas","Dawns","Mother"],"concepts":["Splendid Car","House-Friend","Holy","Strength","Worshipped","Auspicious","Noble"],"hash":"md5-MmgnDy9NmMy0g3mwDVX3lw==","created":"Monday, April 8, 2024 - 10:51:52 PM"},{"id":"1216af43-99bf-4feb-9362-71dc7e858c41","key":"05002","book":"05","title":"HYMN II. Agni.","link":"https://indra.ai/rigveda/hymns/05002.html","text":"p: THE youthful Mother keeps the Boy in secret pressed to her close, nor yields him to the Father. But, when he lies upon the arm, the people see his unfading countenance before them.\n\np: What child is this thou carriest as handmaid, O Youthful One? The Consort-Queen hath borne him. The Babe unborn increased through many autumns. I s w him born what time his Mother bare him.\n\np: I s w him from afar gold-toothed, bright-coloured, hurling his weapons from his habitation, what time I gave him Amrta free from mixture. How can the Indraless, the hymnless harm me?\n\np: I s w him moving from the place he dwells in, even as with a herd, brilliantly shining. These seized him not: he had been born already. They who were grey with age again grow youthful.\n\np: Who separate my young bull from the cattle, they whose protector was in truth no stranger? Let those whose hands have seized upon them free them. May he, observant, drive the herd to us ward.\n\np: Mid mortal men godless have secreted the King of all who live, home of the people. May the prayers of Atri give him freedom. Reproached in turn be those who now reproach him.\n\np: Thou from the stake didst loose e’en Sunaḥsepa bound for a thousand; for he prayed with fervour. So, Agni, loose from us the bonds that bind us, when thou art seated here, O Monk who knowest.\n\np: Thou hast sped from me, Agni, in thine anger: this the protector of Devas’ Laws hath told me. Indra who knoweth bent his eye upon thee: by him instructed am I come, O Agni.\n\np: Agni shines far and wide with lofty splendour, and by his greatness makes all things apparent. He conquers godless and malign enchantments, and sharpens both his horns to gore the Raksas.\n\np: Loud in the heaven above be Agni's roarings with keen-edged weapons to destroy the demons. Forth burst his splendours in the Soma's rapture. The godless bands press round but cannot stay him.\n\np: As a skilled craftsman makes a car, a singer I, Mighty One! this hymn for thee have fashioned. If thou, O Agni, Deva, accept it gladly. May we obtain thereby the heavenly Waters.\n\np: May he, the strong-necked Steer, waxing in vigour, gather the foeman's wealth with none to check him. Thus to this Agni have the Immortals spoken. To man who spreads the gras. May he grant shelter, grant shelter to the man who brings oblation.","people":["Indra","Soma","Agni","Atri","Deva"],"places":["Heaven"],"things":["Born","Soma","Waters","Singer","Wealth","Men","Gold","Home","Strong","Mighty","Car","Hymn","Splendour","People","King","Cattle","Amrta"],"groups":["Devas","Father","Mother","Child","Man"],"concepts":["Heavenly","Truth"],"hash":"md5-OlABbUjaN3SVpKRlKdzPog==","created":"Monday, April 8, 2024 - 10:51:52 PM"},{"id":"f5ca05d1-9b3f-44c9-9767-304e20ceaa8b","key":"05003","book":"05","title":"HYMN III. Agni.","link":"https://indra.ai/rigveda/hymns/05003.html","text":"p: THOU at thy birth art Varuna, O Agni; when thou art kindled thou becomest Mitra. In thee, O Son of Strength, all Devas are centred. Indra art thou to man who brings oblation.\n\np: Aryaman art thou as regardeth maidens mysterious, is thy name, O Self-sustainer. As a kind friend with streams of milk they balm thee what time thou makest wife and lord one-minded.\n\np: The Maruts deck their beauty for thy glory, yea, Rudra! for thy birth fair, brightly-coloured. That which was fixed as Visnu's loftiest station—therewith the secret of the Cows thou guardest.\n\np: Devas through thy glory, Deva who art so lovely! granting abundant gifts gained life immortal. As their own Monk have men established Agni; and serve him fain for praise from him who liveth.\n\np: There is no priest more skilled than thou in worship; none Self-sustainer pass thee in wisdom. The man within whose house as guest thou dwellest, O Deva, by offering shall conquer mortals.\n\np: Aided by thee, O Agni. May we conquer through our oblation, fain for wealth, awakened: May we in battle, in the days’ assemblies, O Son of Strength, by riches conquer mortals.\n\np: He shall bring evil on the evil-plotter whoever turns against us sin and outrage. Destroy this calumny of him, O Agni, whoever injures us with double-dealing.\n\np: At this dawn's flushing, Deva. our ancient fathers served thee with offerings, making thee their envoy, when, Agni, to the store of wealth thou goest, a Deva.enkindled with good things by mortals.\n\np: Save, thou who knowest, draw thy father near thee, who counts as thine own son, O Child of Power. O sapient Agni, when wilt thou regard us? When, skilled in holy Law, wilt thou direct us?\n\np: Adoring thee he gives thee many a title, when thou, Good Lord! acceptest this as Father. And doth not Agni, glad in strength of Deva.ead, gain splendid bliss when he hath waxen mighty?\n\np: Most Youthful Agni, verily thou bearest thy praiser safely over all his troubles. Thieves have been seen by us and open foemen: unknown have been the plottings of the wicked.\n\np: To thee these eulogies have been directed: or to the Vasu hath this sin been spoken. But this our Agni, flaming high, shall never yield us to calumny, to him who wrongs us.","people":["Indra","Agni","Visnu","Mitra","Varuna","Deva","Dawn","Aryaman","Vasu"],"places":[],"things":["Worship","Milk","Lord","Glory","Offering","Wealth","Men","Streams","Beauty","Mighty","Praise","Offerings","Bliss","Friend","Riches","Life","Gifts"],"groups":["Devas","Maruts","Fathers","Father","Son","Child","Wife","Immortal","Man"],"concepts":["Good","Evil","Birth","Life","Immortal","Holy","Strength","Wisdom","Offering","Offerings"],"hash":"md5-dgAAaV1fuEAt2yDlZKMHuA==","created":"Monday, April 8, 2024 - 10:51:52 PM"},{"id":"32806b75-3713-4ab6-8de8-939ed0b95817","key":"05004","book":"05","title":"HYMN IV. Agni.","link":"https://indra.ai/rigveda/hymns/05004.html","text":"p: O AGNI, King and Lord of wealth and treasure.s, in thee is my delight at offers. Through the, may we obtain the strength we long for, and overcome the fierce attacks of mortals.\n\np: Agni, Eternal Father, offering-bearer, fair to behold, far-reaching, far-refulgent, From well-kept household fire beam food to feed us, and measure out to us abundant glory.\n\np: The Sage of men, the Lord of human races, pure, purifying Agni, balmed with butterhim the Omniscient as your Monk ye stablish: he wins among the Devas things worth the choosing.\n\np: Agni, enjoy, of one accord with Ila, striving in rivalry with beams of Surya, Enjoy, O Jatavedas, this our fuel, and bring the Devas to us to taste oblations.\n\np: As dear House-Friend, guest welcome in the dwelling, to this  'our offering come thou who knowest. And, Agni, having scattered all assailants, bring to us the possessions of our foemen.\n\np: Drive thou away the Dasyu with thy weapon. As, gaining vital power for thine own body, O Son of Strength, the Devas thou satisfiest, so in fight save us, most heroic Agni.\n\np: May we, O Agni, with our lauds adore thee, and with our gifts, fair-beaming Purifier! Send to us wealth containing all things precious: bestow upon us every sort of riches.\n\np: Son of Strength, Agni, dweller in three regions, accept  'our offering and our oblation. Among the Deva. May we be counted pious: protect us with a triply-guarding shelter.\n\np: Over all woes and dangers, Jatavedas, bear us as in a boat across a river. Praised with our homage even as Atri praised thee, O Agni, be the guardian of our bodies.\n\np: As I, remembering thee with grateful spirit, a mortal, call with might on thee Immortal, vouchsafe us high renown, O Jatavedas, an. May I be immortal by my children.\n\np: The pious man, O Jatavedas Agni, to whom thou grantest ample room and pleasure, Gaineth abundant wealth with sons and horses, with heroes and with kine for his well-being.","people":["Agni","Atri","Deva","Surya","Ila"],"places":[],"things":["Lord","Glory","Offering","Treasure","Wealth","Food","Men","River","Might","Delight","Heroes","Offers","Friend","King","Sage","Horses","call","Riches","Spirit","Gifts"],"groups":["Devas","Dasyu","Jatavedas","Sons","Human","Father","Son","Immortal","Man"],"concepts":["Heroic","House-Friend","Immortal","Strength","Offering"],"hash":"md5-7zT+J0LuElV3r4XDSkvAaA==","created":"Monday, April 8, 2024 - 10:51:52 PM"},{"id":"7e1907d8-1677-4b81-83f2-512c196c4811","key":"05005","book":"05","title":"HYMN V. Apris.","link":"https://indra.ai/rigveda/hymns/05005.html","text":"p: To Agni, Jatavedas, to the flame, the well-enkindled Deva, Offer thick offerings oil.\n\np: He, Narasamsa, ne’er beguiled, inspiriteth this offering: For sage is he, with sweets in hand.\n\np: Adored, O Agni, hither bring Indra the Wonderful, the Friend, On lightly-rolling car to aid.\n\np: Spread thyself out, thou soft as wool The holy hymns have sung to thee. Bring gain to us, O beautiful!\n\np: Open yourselves, ye Doors Divine, easy of access for our aid: Fill, more and more,  'the offering.\n\np: Fair strengtheners of vital power, young Mothers of eternal Law, Morning and Night we supplicate.\n\np: On the wind's flight come, glorified, ye two celestial Monks of man Come ye to this  'our offering.\n\np: Ila, Sarasvati, Mahi, three Devas who bring us weal, be seated harmless on the grass.\n\np: Rich in all plenty, Tvastar, come auspicious of thine own accord Help us in every offering.\n\np: Vanaspati, wherever thou knowest the Devas’ mysterious names, Send our oblations thitherward.\n\np: To Agni and to Varuna, indra, the Maruts, and the Devas, with Svaha be oblation brought.","people":["Indra","Agni","Varuna","Narasamsa","Tvastar","Svaha","Sarasvati","Deva","Ila","Vanaspati","Mahi"],"places":[],"things":["Offering","Help","Grass","Car","Offerings","Friend","Sage","Morning"],"groups":["Devas","Maruts","Jatavedas","Man","Monks"],"concepts":["Celestial","Divine","Beautiful","Holy","Offering","Offerings","Auspicious","Eternal Law"],"hash":"md5-gpe6LYFSfYAy/pLpyH6Xlg==","created":"Monday, April 8, 2024 - 10:51:52 PM"},{"id":"3ae0d410-a018-4c07-9707-ebace0bcedb8","key":"05006","book":"05","title":"HYMN VI. Agni.","link":"https://indra.ai/rigveda/hymns/05006.html","text":"p: I VALUE Agni that good Lord, the home to which the kine return: Whom fleet-foot coursers seek as home, and stron enduring steeds as home. Bring food to those who sing thy praise.\n\np: ’Tis Agni whom we laud as good, to whom the milch-kine come in herds, to whom the chargers swift of foot, to whom our well-born princes come. Bring food to those who sing thy praise.\n\np: Agni the Deva.of all mankind, gives, verily, a steed to man. Agni gives precious gear for wealth, treasure. he gives when he is pleased. Bring food to those who sing thy praise.\n\np: Deva, Agni, we will kindle thee, rich in thy splendour, fading not, So that this glorious fue. May send forth by day its light for thee. Bring food to those who sing thy praise.\n\np: To thee the splendid, Lord of flame, bright, wondrous, prince of men, is brought. Oblation with the holy verse, O Agni, bearer of our gifts. Bring food to those who sing thy praise.\n\np: These Agnis in the seats of the fire nourish each thing most excellent. They give delight, they spread abroad, they move themselves continually. Bring food to those who sing thy praise.\n\np: Agni, these brilliant flames of thine wax like strong chargers mightily, who with the treadings of their hoofs go swiftly to the stalls of kine. Bring food to those who sing thy praise.\n\np: To us who laud thee, Agni, bring fresh food and safe and happy homes. May we who have sung hymns to thee have thee for envoy in each house. Bring food to those who sing thy praise.\n\np: Thou, brilliant Deva, within thy mouth warmest both ladles of the oil. So fill us also, in our hymns, abundantly, O Lord of Strength. Bring food to those who sing thy praise.\n\np: Thus Agni have we duly served with offers and with hymns. May he give us what we crave, store of brave sons and fleet-foot steeds. Bring food to those who sing thy praise.","people":["Agni","Deva"],"places":[],"things":["Mankind","Steeds","Lord","Born","Glorious","Light","Treasure","Wealth","Food","Men","Home","Strong","Praise","Brave","Delight","Splendour","Offers","Excellent","Gifts"],"groups":["Sons","Man"],"concepts":["Good","Holy","Strength","Glorious","Swift","Pleased"],"hash":"md5-IqLWGCnS+rYZc0JNKyO4Eg==","created":"Monday, April 8, 2024 - 10:51:52 PM"},{"id":"ba72f428-4553-4549-8989-0101b2425a60","key":"05007","book":"05","title":"HYMN VII. Agni.","link":"https://indra.ai/rigveda/hymns/05007.html","text":"p: OFFER to Agni, O my friends, your seemly food, your seemly praise; To him supremest o’er the folk, the Son of Strength, the mighty Lord:\n\np: Him in whose presence, when they meet in full assembly, men rejoice; Even him whom worthy ones inflame, and living creatures bring to life.\n\np: When we present to him the food and offerings gifts of men. He by the might of splendour grasps the holy Ordinance's rein.\n\np: He gives a signal in the night even to him who is afar, when he, the Bright, unchanged by eld, consumes the sovrans of the wood.\n\np: He in whose service on the ways they offer up their drops of sweat, On him is their high kin have they mounted, as ridges on the earth.\n\np: Whom, sought of many, mortal man hath found to be the Stay of all; He who gives flavour to our food, the home of every man that lives.\n\np: Even as a herd that crops the grass he shears the field and wilderness, with flashing teeth and beard of gold, deft with his unabated might.\n\np: For him, to whom, bright as an axe he, as to Atri, hath flashed forth, Hath the well-bearing Mother borne, producing when her time is come.\n\np: Agni to whom the oil is shed by him thou lovest to support, bestow upon these mortals fame and splendour and intelligence.\n\np: Such zeal hath he, resistless one: he gained the cattle given by thee. Agni. May Atri overcome the Dasyus who bestow no gifts, subdue the men who give no food.","people":["Agni","Atri"],"places":["Earth"],"things":["Lord","Food","Men","Might","Gold","Home","Mighty","Grass","Praise","Splendour","Offerings","Friends","Drops","Cattle","Life","Gifts"],"groups":["Dasyus","Mother","Son","Man"],"concepts":["Life","Holy","Strength","Offerings","Intelligence"],"hash":"md5-+yymLJuT0MvFE4KZeu1GUg==","created":"Monday, April 8, 2024 - 10:51:52 PM"},{"id":"580c26fa-edc7-48d3-9800-5fd0c5b03f1a","key":"05008","book":"05","title":"HYMN VIII. Agni.","link":"https://indra.ai/rigveda/hymns/05008.html","text":"p: O AGNI urged to strength, the men of old who loved the Law enkindled thee, the Ancient, for their aid, thee very bright, and holy, nourisher of all, most excellent, the Friend and Master of the home.\n\np: Thee, Agni, men have stablished as their guest of old, as Master of the household, thee, with hair of flame; High-bannered, multiform, distributor of wealth, kind helper, good protector, drier of the floods.\n\np: The tribes of men praise thee, Agni, who knowest well burnt offerings, the Discerner, lavishest of wealth, Dwelling in secret, Blest One! visible to all, loud-roaring, skilled in worship, glorified with oil.\n\np: Ever to thee, O Agni, as exceeding strong have we drawn nigh with songs and reverence singing hymns. So be thou pleased with us, Angiras! as a Deva.enkindled by the noble with man's goodly light.\n\np: Thou, Agni! multiform, Deva who art lauded much! givest in every house subsistence as of old. Thou rulest by thy might o’er food of many a sort: that light of thine when blazin. May not be opposed.\n\np: The Devas, most Youthful Agni, have made thee, inflamed, the bearer of oblations and the messenger. Thee, widely-reaching, homed in sacred oil, invoked, effulgent, have they made the Eye that stirs the thought.\n\np: Men seeking joy have lit thee worshipped from of old, O Agni, with good fuel and with sacred oil. So thou, bedewed and waxing mighty by the plants, spreadest thyself abroad over the realms of earth.","people":["Agni","Angiras","Deva"],"places":["Earth"],"things":["Worship","Master","Reverence","Light","Wealth","Food","Men","Might","Joy","Home","Strong","Mighty","Praise","Excellent","Offerings","Songs","Friend"],"groups":["Devas","Man"],"concepts":["Good","Holy","Sacred","Strength","Offerings","Worshipped","Pleased","Noble"],"hash":"md5-C1+w3hx3u8MtLv5manantg==","created":"Monday, April 8, 2024 - 10:51:52 PM"},{"id":"481127b9-e756-448c-bd07-3bbb4991ead0","key":"05009","book":"05","title":"HYMN IX. Agni.","link":"https://indra.ai/rigveda/hymns/05009.html","text":"p: BEARING; oblations mortal men, O Agni, worship thee the Deva. I deem thee Jatavedas: bear our offerings unceasingly.\n\np: In the man's home who offers gifts, where grass is trimmed, Agni is Monk, to whom all offers come and strengthenings that win renown.\n\np: Whom, as an infant newly-born, the kindling-sticks have brought to life, Sustainer of the tribes of men, skilled in well-ordered offering.\n\np: Yea, very hard art thou to grasp, like offspring of the wriggling snakes, when thou consumest many woods like an ox, Agni, in the mead.\n\np: Whose flames, when thou art sending forth the smoke, completely reach the mark, when Trta in the height of heaven, like as a smelter fanneth thee, e’en as a smelter sharpeneth thee.\n\np: O Agni, by thy assist and by Mitra's friendly furtherance, may we, averting hate, subdue the wickedness of mortal men.\n\np: O Agni, to our heroes bring such riches, thou victorious Deva. May he protect and nourish us, and help in gaining strength: be thou near us in fight for our success.","people":["Agni","Mitra","Deva","Trta"],"places":["Heaven"],"things":["Worship","Born","Offering","Men","Help","Home","Offspring","Grass","Heroes","Offers","Offerings","Riches","Life","Gifts"],"groups":["Jatavedas","Man"],"concepts":["Life","Strength","Offering","Offerings"],"hash":"md5-0YzuGNF1Xn816uVZ8nZ8+w==","created":"Monday, April 8, 2024 - 10:51:52 PM"},{"id":"80901113-58ca-46e1-96e9-9a439aa2ce31","key":"05010","book":"05","title":"HYMN X. Agni.","link":"https://indra.ai/rigveda/hymns/05010.html","text":"p: BRING us most mighty splendour thou, Agni, resistless on thy way. With overflowing store of wealth mark out for us a path to strength.\n\np: Ours art thou, wondrous Agni, by wisdom and bounteousness of power. The might of Asuras rests on thee, like Mitra worshipful in act.\n\np: Agni, increase our means of life, increase the house and home of these, the men, the princes who have won great riches through our hymns of praise.\n\np: Bright Agni, they who deck their songs for thee have horses as their meed. The men are mighty in their might, they whose high laud, as that of heaven, awakes thee of its own accord.\n\np: O Agni, those resplendent flames of thine go valorously forthlike lightnings flashing round us, like a rattling car that seeks the spoil.\n\np: Now, Agni, come to assist us; let monks draw nigh to offer gifts; And let the patrons of our rites subdue all regions of the earth.\n\np: Bring to us, Agni, Angiras, lauded of old and lauded now, invoker! wealth to quell the strong, that singer. May extol thee. Be near us in fight for our success.","people":["Agni","Angiras","Mitra"],"places":["Earth","Heaven"],"things":["Singer","Wealth","Men","Might","Home","Strong","Mighty","Car","Praise","Splendour","Songs","Horses","spoil","Riches","Life","Gifts"],"groups":["Asuras","Monks"],"concepts":["Life","Strength","Wisdom"],"hash":"md5-aYvypykKB9Kd18YIiLxmJQ==","created":"Monday, April 8, 2024 - 10:51:52 PM"},{"id":"90f97341-ded6-4bfd-8f8a-bb45319f2fd8","key":"05011","book":"05","title":"HYMN XI. Agni.","link":"https://indra.ai/rigveda/hymns/05011.html","text":"p: THE watchful Guardian of the people hath been born, Agni, the very strong, for fresh prosperity. With oil upon his face, with high heaven-touching flame, he shineth splendidly, pure, for the Bharatas.\n\np: Ensign of offering, the earliest Household-Monk, the men have kindled Agni in his threefold seat, with Indra and the Devas together on the grass let the wise Monk sit to complete  'the offering.\n\np: Pure , unadorned, from thy two Mothers art thou born: thou camest from Vivasvan as a charming Sage. With oil they strengthened thee, O Agni, worshipped Deva. thy banner was the smoke that mounted to the sky.\n\np: May Agni graciously come to  'our offering. The men bear Agni here and there in every house. He hath become an envoy, bearer of our gifts: electing Agni, men choose on exceeding wise.\n\np: For thee, O Agni, is this sweetest prayer of mine: dear to thy spirit be this product of my thought. As great streams fill the river so our song of praise fill thee, and make thee yet more mighty in thy strength.\n\np: O Agni, the Angirases discovered thee what time thou layest hidden, fleeing back from wood to wood. Thou by attrition art produced as conquering might, and men, O Angiras, call thee the Son of Strength.","people":["Indra","Agni","Angiras","Vivasvan","Deva"],"places":["Heaven","Sky"],"things":["Born","Offering","Men","River","Streams","Might","Song","Wise","Strong","Mighty","Grass","Praise","People","Sage","call","Spirit","Gifts"],"groups":["Devas","Bharatas","Son","Angirases"],"concepts":["Strength","Offering","Worshipped"],"hash":"md5-zv6Z8sidq8sb5sr8MhGZFg==","created":"Monday, April 8, 2024 - 10:51:52 PM"},{"id":"eb773f2e-8ea9-4a57-ba96-0d4e9b765a67","key":"05012","book":"05","title":"HYMN XII. Agni.","link":"https://indra.ai/rigveda/hymns/05012.html","text":"p: To Agni, lofty Asura, meet for worship, Steer of eternal Law, my meditation I offer; I bring my song directed to the Mighty like pure oil for his mouth at offeringss.\n\np: Mark the Law, thou who knowest, yea, observe it: send forth the full streams of eternal Order. I use no sorcery with might or falsehood the sacred Law of the Red Steer I follow.\n\np: How hast thou, follower of the Law eternal, become the knower of a new song, Agni? The Deva, the Guardian of the seasons, knows me: the Lord of him who won this wealth I know not.\n\np: Who, Agni, in alliance with thy foeman, what splendid helpers won for them their riches? Agni, who guard the dwelling-place of falsehood? Who are protectors of the speech of liars?\n\np: Agni, those friends of thine have turned them from thee: gracious of old, they have become ungracious. They have deceived themselves by their own speeches, uttering wicked words against the righteous.\n\np: He who pays offering to thee with homage, O Agni, keeps the Red Steer's Law eternal; Wide is his dwelling. May the noble offspring of Nahusa who wandered forth come hither.","people":["Agni","Deva"],"places":[],"things":["Worship","Lord","Seasons","Meditation","Law Eternal","Offering","Wealth","Streams","Might","Song","Offspring","Mighty","Friends","Riches","Order"],"groups":["Asura"],"concepts":["Sacred","Offering","Noble","Eternal Law","Speech"],"hash":"md5-CnyKF3jeMG2HbGGtmXsRgQ==","created":"Monday, April 8, 2024 - 10:51:52 PM"},{"id":"64bc2716-2724-49cf-af57-75d92597df56","key":"05013","book":"05","title":"HYMN XIII. Agni.","link":"https://indra.ai/rigveda/hymns/05013.html","text":"p: WITH songs of praise we call on thee, we kindle thee with songs of praise, Agni, with songs of praise, for help.\n\np: Eager for wealth, we meditate Agni's effectual praise to-day, praise of the Deva who touches heaven.\n\np: May Agni, Monk among mankind, take pleasure in our songs of praise, and worship the Celestial Folk.\n\np: Thou, Agni, art spread widely forth, Monk dear and excellent; through thee Men make  'the offering complete.\n\np: Singers exalt thee, Agni, well lauded, best giver of our strength: So grant thou us heroic might.\n\np: Thou Agni, as the felly rings the spokes, encompassest the Devas. I yearn for bounty manifold.","people":["Agni","Deva"],"places":["Heaven"],"things":["Worship","Mankind","Offering","Wealth","Men","Might","Help","Praise","Excellent","Songs","call"],"groups":["Devas"],"concepts":["Celestial","Heroic","Strength","Offering","Giver"],"hash":"md5-EOdr8gYp0trmhjQXkFtWAw==","created":"Monday, April 8, 2024 - 10:51:52 PM"},{"id":"6c2c7798-1a59-4f5a-a4f3-7116d4eab9e6","key":"05014","book":"05","title":"HYMN XIV. Agni.","link":"https://indra.ai/rigveda/hymns/05014.html","text":"p: ENKINDLING the Immortal, wake Agni with song of praise. May he bear our oblations to the Devas.\n\np: At high solemnities mortal men glorify him the Immortal, best At offering among mankind.\n\np: That h. May bear their gifts to heaven, all glorify him Agni, Deva, with ladle that distilleth oil.\n\np: Agni shone bright when born, with light killing the Dasyus and the dark: He found the Kine, the Floods, the Sun.\n\np: Serve Agni, Deva.adorable, the Sage whose back is balmed with oil: Let him approach, and hear my call.\n\np: They have exalted Agni, Deva.of all mankind, with oil and hymns Of praise, devout and eloquent.","people":["Agni","Deva"],"places":["Heaven"],"things":["Mankind","Born","Offering","Light","Sun","Men","Song","Praise","Adorable","Sage","call","Gifts"],"groups":["Devas","Dasyus","Immortal"],"concepts":["Immortal","Devout","Offering"],"hash":"md5-gy9X+AmYtoStlCkEWZ8C3w==","created":"Monday, April 8, 2024 - 10:51:52 PM"},{"id":"8c351029-499f-4ba4-a19d-c4bdad85d173","key":"05015","book":"05","title":"HYMN XV. Agni.","link":"https://indra.ai/rigveda/hymns/05015.html","text":"p: To him, the far-renowned, the wise Ordainer, ancient and glorious, a song I offer. Enthroned in oil, the Asura, bliss-giver, is Agni, firm support of noble, riches.\n\np: By holy Law they kept supporting Order, by help of offering, in loftiest heaven. They who attained with born men to the unborn, men seated on that stay, heaven's firm sustainer.\n\np: Averting woe, they labour hard to bring him, the ancient, plenteous food as power resistless. May he, born newly, conquer his assailants: round him they stand as round an angry lion.\n\np: When, like a mother, spreading forth to nourish, to cherish and regard each man that liveth. Consuming all the strength that thou hast gotten, thou wanderest round, thyself, in varied fashion.\n\np: May strength preserve the compass of thy vigour, Deva. that broad stream of thine that beareth riches. Thou, like a thief who keeps his refuge secret, hast holpen Atri to great wealth, by teaching.","people":["Agni","Atri","Deva"],"places":["Heaven"],"things":["Born","Glorious","Offering","Wealth","Food","Men","Stream","Song","Help","Wise","Bliss","Riches","Order"],"groups":["Asura","Mother","Man"],"concepts":["Holy","Strength","Offering","Giver","Glorious","Noble"],"hash":"md5-2Zn7netvljAZj4vNB2IKxA==","created":"Monday, April 8, 2024 - 10:51:52 PM"},{"id":"0611db24-d378-4c64-bcb8-64f752ec16d5","key":"05016","book":"05","title":"HYMN XVI. Agni.","link":"https://indra.ai/rigveda/hymns/05016.html","text":"p: GREAT power is in the beam of light, sing praise to, Agni, to the Deva.Whom men have set in foremost place like Mitra with their eulogies.\n\np: He by the splendour of his arms is Monk of every able man. Agni conveys oblation straight, and deals, as Bhaga deals, his boons.\n\np: All rests upon the laud and love of him the rich, high-flaming Deva, On whom, loud-roaring, men have laid great strength as on a faithful friend.\n\np: So, Agni, be the Friend of these with liberal gift of hero strength. Yea. Heaven and Earth have not surpassed this Youthful One in glorious fame.\n\np: O Agni, quickly come to us, and, glorified, bring precious wealth. So we and these our princes will assemble for the good of all. Be near in fight to prosper us.","people":["Agni","Mitra","Bhaga","Deva"],"places":["Earth","Heaven"],"things":["Glorious","Light","Wealth","Men","Praise","Gift","Splendour","Friend","Hero"],"groups":["Man"],"concepts":["Good","Love","Strength","Glorious"],"hash":"md5-3ZGbvCCX5ilRNtQAFXNzfg==","created":"Monday, April 8, 2024 - 10:51:52 PM"},{"id":"61f957ee-1d69-49ad-91a8-1f1a153c90fe","key":"05017","book":"05","title":"HYMN XVII. Agni.","link":"https://indra.ai/rigveda/hymns/05017.html","text":"p: GOD. May a mortal call the Strong hither, with solemn rites, to aid, a man call Agni to protect when offering is well prepared.\n\np: Near him thou seemest mightier still in native glory, set to hold Apart yon flame-hued vault of heaven, lovely beyond the thought of man.\n\np: Yea, this is by the light of him whom powerful song hath bound to act, whose beams of splendour flash on high as though they sprang from heavenly seed.\n\np: Wealth loads the Wonder-Worker's car through his, the very wise One's power. Then, meet to be invoked among all tribes, is Agni glorified.\n\np: Now, too, the princes shall obtain excellent riches by our lips. Protect us for our welfare: lend thy assist, O thou Son of Strength. Be near in fight to prosper us.","people":["Agni"],"places":["Heaven"],"things":["Glory","Offering","Light","Wealth","Song","Wise","Strong","Car","Splendour","Excellent","call","Riches"],"groups":["Son","Man"],"concepts":["Heavenly","Strength","Offering","Powerful"],"hash":"md5-kmdmOyi4W0ERxaYyRYNffQ==","created":"Monday, April 8, 2024 - 10:51:52 PM"},{"id":"78997e5b-f72e-456e-b6b0-6dabe0bb8f38","key":"05018","book":"05","title":"HYMN XVIII. Agni.","link":"https://indra.ai/rigveda/hymns/05018.html","text":"p: AT dawn let Agni, much-beloved guest of the house, be glorified; Immortal who delights in all oblations brought by mortal men.\n\np: For Dvita who receives through wealth of native strength maimed offerings, Thy praiser even gains at once the Soma-drops, Immortal Devas!\n\np: Nobles, with song I call that car of yours that shines with lengthened life, for, Deva who givest steeds! that car hither and thither goes unharmed.\n\np: They who have varied ways of thought, who guard the lauds within their lips, and strew the grass before the light, have decked themselves with high renown.\n\np: Immortal Agni, give the chiefs, heroes who institute the rite. Heroes’ illustrious, lofty fame, who at the synod met for praise presented me with fifty steeds.","people":["Soma","Agni","Deva","Dawn"],"places":[],"things":["Steeds","Soma","Light","Wealth","Men","Song","Grass","Car","Praise","Heroes","Offerings","Drops","call","Life"],"groups":["Devas","Immortal"],"concepts":["Life","Immortal","Strength","Offerings"],"hash":"md5-YnjpInh80AtisPHlXZg7Cw==","created":"Monday, April 8, 2024 - 10:51:53 PM"},{"id":"d24fce6f-f325-4d12-b96b-0df7f8c59360","key":"05019","book":"05","title":"HYMN XIX. Agni.","link":"https://indra.ai/rigveda/hymns/05019.html","text":"p: ONE state begets another state: husk is made visible from husk: Within his Mother's side he speaks.\n\np: Discerning, have they offered gifts: they guard the strength that never wastes. To a strong fort have they pressed in.\n\np: Svaitreya's people, all his men, have gloriously increased in might. A gold chain Brhaduktha wears, as, through this Soma, seeking spoil.\n\np: I bring, as ’twere, the longed-for milk, the dear milk of the Sister-Pair. Like to a caldron filled with food is he, unconquered, conquering all.\n\np: Beam of light, come to us in sportive fashion, finding thyself close to the wind that fans thee. These flames of his are wasting flames, like arrows keen-pointed, sharpened, on his breast.","people":["Soma"],"places":[],"things":["Milk","Soma","Light","Food","Men","Might","Gold","Strong","People","spoil","Gifts","Caldron"],"groups":["Mother","Sister"],"concepts":["Strength"],"hash":"md5-008dpifhRGuC5f9I1nvv7w==","created":"Monday, April 8, 2024 - 10:51:53 PM"},{"id":"98764cd9-8ea9-4f77-b0b9-bd846ea7ad63","key":"05020","book":"05","title":"HYMN XX. Agni.","link":"https://indra.ai/rigveda/hymns/05020.html","text":"p: AGNI, best winner of the spoil, cause us to praise before the Devas As our associate meet for lauds, wealth which thou verily deemest wealth.\n\np: Agni, the great who ward not off the anger of thy power and might Stir up the wrath and hatred due to one who holds an alien creed.\n\np: Thee, Agni, would we choose as Monk, the perfecter of strength and skill; We who bring sacred food invoke with song thee Chief at holy rites.\n\np: Here as is needful for thine aid we toil, O Conqueror, day by day, for wealth, for Lawe may we rejoice, most Wise One! at the feast, with kine, rejoice, with heroes, at the feast.","people":["Agni"],"places":[],"things":["Wealth","Food","Might","Song","Wise","Chief","Praise","Heroes","spoil"],"groups":["Devas"],"concepts":["Holy","Sacred","Strength","Winner"],"hash":"md5-kZ/6IPkn2qKiFJmtNYHU4A==","created":"Monday, April 8, 2024 - 10:51:53 PM"},{"id":"5d657a51-dd70-4bbb-a195-a16553599a6f","key":"05021","book":"05","title":"HYMN XXI. Agni.","link":"https://indra.ai/rigveda/hymns/05021.html","text":"p: WE stablish thee as Manus used, as Manus used we kindle thee. Like Manus, for the pious man , Angiras, Agni, worship Devas.\n\np: For well, O Agni, art thou pleased when thou art kindled mid mankind. Straight go the ladles unto thee, thou highborn Deva whose food is oil.\n\np: Thee have all Devas of one accord established as their messenger. Serving at offers men adore thee as a Deva, O Sage.\n\np: Let mortal man adore your Deva, Agni, with worship due to Devas. Shine forth enkindled, Radiant One. Sit in the chamber of the Law, sit in the chamber of the food.","people":["Agni","Angiras","Deva"],"places":[],"things":["Worship","Mankind","Shine","Food","Men","Offers","Sage"],"groups":["Devas","Man"],"concepts":["Pleased"],"hash":"md5-DQ6DGRYACESbQr21bNnUjQ==","created":"Monday, April 8, 2024 - 10:51:53 PM"},{"id":"42f3ad7a-4d51-4913-8efd-7a004de99c7b","key":"05022","book":"05","title":"HYMN XXII. Agni.","link":"https://indra.ai/rigveda/hymns/05022.html","text":"p: LIKE Atri, Visvasaman! sing to him of purifying light, who must be praised in holy rites, the Monk most welcome in the house.\n\np: Set Jatavedas in his place, Agni the Deva.and Minister. Let offering proceed to-day duly, comprising all the Devas.\n\np: All mortals come to thee for aid, the Deva.of most observant mind. Of thine excelling favour we bethink us as we long for it.\n\np: Mark with attention this our speech, O Agni, thou victorious One. Thee, Strong-jawed! as the homestead's Lord, the Atris with their lauds exalt, the Atris beautify with songs.","people":["Agni","Atri","Deva"],"places":[],"things":["Lord","Offering","Light","Strong","Songs"],"groups":["Devas","Jatavedas","Atris"],"concepts":["Holy","Offering","Speech"],"hash":"md5-u2c3SKB54zSuOL2077vvrQ==","created":"Monday, April 8, 2024 - 10:51:53 PM"},{"id":"2503c432-01e1-48e6-8ed1-5f75a108ea1f","key":"05023","book":"05","title":"HYMN XXIII. Agni.","link":"https://indra.ai/rigveda/hymns/05023.html","text":"p: By thy fair splendour's mighty power, O Agni, bring victorious wealth, Wealth that o’ercometh all mankind, and, near us, conquereth in fight.\n\np: Victorious Agni, bring to us the wealth that vanquisheth in war; For thou art wonderful and true, giver of strength in herds of kine.\n\np: For all the folk with one accord, whose sacred grass is trimmed and strewn, invite thee to their worship-halls, as a dear Monk, for choicest wealth.\n\np: For he, the Deva.of all men, hath gotten him might that quelleth foes. O Agni, in these homes shine forth, bright Deva. for our prosperity, shine, purifier! splendidly.","people":["Agni","Deva"],"places":[],"things":["Worship","Mankind","Shine","Wealth","Men","Might","Mighty","Grass","Splendour"],"groups":[],"concepts":["Sacred","Strength","Giver"],"hash":"md5-Gu+Z7bsjWBFZ//ThRI5OZA==","created":"Monday, April 8, 2024 - 10:51:53 PM"},{"id":"2dfed14c-1f73-4b8d-8d12-ca1777e21ec8","key":"05024","book":"05","title":"HYMN XXIV. Agni.","link":"https://indra.ai/rigveda/hymns/05024.html","text":"p: O AGNI, be our nearest Friend, be thou a kind deliverer and a gracious Friend.\n\np: Excellent Agni, come thou nigh to us, and give us wealth most splendidly renowned.\n\np: So hear us, listen to this call of ours, and keep us far from every sinful man.\n\np: To thee then, O Most Bright, O Radiant Deva, we come with prayer for happiness for our friends.","people":["Agni","Deva"],"places":[],"things":["Wealth","Excellent","Friends","Friend","call"],"groups":["Man"],"concepts":[],"hash":"md5-/PBW+SvSfFckqNGIw8xZLA==","created":"Monday, April 8, 2024 - 10:51:53 PM"},{"id":"385d1a59-dab4-46e5-95c3-fc3e14df2585","key":"05025","book":"05","title":"HYMN XXV. Agni.","link":"https://indra.ai/rigveda/hymns/05025.html","text":"p: I WILL sing near, for grace, your Deva.Agni, for he is good to us. Son of the Brands. May he give gifts, and, righteous, save us from the foe.\n\np: For he is true, whom men of old enkindled, and the Devas themselves, the Monk with the delicious tongue, rich with the light of glorious beams.\n\np: With wisdom that surpasseth all, with gracious will most excellent, O Agni, worthy of our choice, shine wealth on us through hymns of praise.\n\np: Agni is King, for he extends to mortals and to Devas alike. Agni is bearer of our gifts. Worship ye Agni with your thoughts.\n\np: Agni gives to the worshipper a son, the best, of mightiest fame, Of deep devotion, ne’er subdued, bringer of glory to his sire.\n\np: Agni bestows the hero-lord who conquers with the men in fight. Agni bestows the fleet-foot steed, the victor never overcome.\n\np: The mightiest song is Agni's: shine on high, thou who art rich in light. Like the Chief Consort of a King, riches and strength proceed from thee.\n\np: Resplendent are thy rays of light: loud is thy voice like pressing-stones. Yea, of itself thy thunder goes forth like the roaring of the heaven.\n\np: Thus, seeking riches, have we paid homage to Agni Conqueror. May he, most wise, as with a ship, carry us over all our foes.","people":["Agni","Deva"],"places":["Heaven"],"things":["Worship","Lord","Glory","Glorious","Shine","Light","Wealth","Men","Song","Wise","Chief","Praise","Voice","Worshipper","Excellent","Pressing-Stones","Hero","King","Riches","Gifts"],"groups":["Devas","Son"],"concepts":["Good","Strength","Wisdom","Glorious"],"hash":"md5-zuFX+Sso417iCwXxszYANQ==","created":"Monday, April 8, 2024 - 10:51:53 PM"},{"id":"d2304dc7-ded3-4f6a-9b25-819f5c3361d2","key":"05026","book":"05","title":"HYMN XXVI. Agni.","link":"https://indra.ai/rigveda/hymns/05026.html","text":"p: O AGNI, Holy and Divine, with splendour and thy pleasant tongue Bring hither and adore the Devas.\n\np: We meditate thee, thou who droppest oil, bright-rayed! who lookest on the Sun, Bring the Devas hither to the feast.\n\np: We have enkindled thee, O Sage, bright caller of the Devas to feast. O Agni, great in Offering.\n\np: O Agni, come with all the Devas, come to our offerings gift: We choose thee as Invoking Monk.\n\np: Bring, Agni, to the worshipper who pours the juice, heroic strength: Sit with the Devas upon the grass.\n\np: Victor of thousands, Agni enkindled, cherishest the laws, Laud-worthy, envoy of the Devas.\n\np: Set Agni Jatavedas down, the bearer of our sacred gifts, mostYouthful, Deva.and Minister.\n\np: Duly proceed  'our offering, comprising all the Devas, to-day: Strew holy grass to be their seat.\n\np: May the Maruts sit thereon, the Asvins, Mitra, Varuna: The Devas with all their company.","people":["Agni","Mitra","Varuna","Asvins","Deva"],"places":[],"things":["Offering","Sun","Juice","Grass","Worshipper","Gift","Splendour","Offerings","Sage","Gifts"],"groups":["Devas","Maruts","Jatavedas"],"concepts":["Divine","Heroic","Holy","Sacred","Strength","Offering","Offerings"],"hash":"md5-nXYI/kJghQ3PEnnXFwWWjA==","created":"Monday, April 8, 2024 - 10:51:53 PM"},{"id":"1d985b04-26f9-4902-bf30-a91e22077e8c","key":"05027","book":"05","title":"HYMN XXVII. Agni.","link":"https://indra.ai/rigveda/hymns/05027.html","text":"p: THE Deva like hero, famousest of nobles, hath granted me two oxen with a wagon. Trvrsan's son Tryaruna hath distinguished himself, Vaisvanara Agni! with ten thousands.\n\np: Protect Tryaruna, as thou art waxing strong and art highly praised, Vaisvanara Agni! Who granteth me a hundred kine and twenty, and two bay horses, good at draught, and harnessed.\n\np: So Trasadasyu served thee, Deva.Most Youthful, craving thy favour for the ninth time, Agni, Tryaruya who with attentive spirit accepteth many a song from me the mighty.\n\np: He who declares his wish to me, to Asvamedha, to the Prince, pays him who with his verse seeks gain, gives power to him who keeps the Law.\n\np: From whom a hundred oxen, all of speckled hue, delight my heart, the gifts of Asvamedha, like thrice-mingled draughts of Soma juice.\n\np: To Asvamedha who bestows a hundred gifts grant hero power, O Indra and Agni! lofty rule like the unwasting Sun in heaven.","people":["Indra","Soma","Agni","Deva","Vaisvanara"],"places":["Heaven"],"things":["Soma","Sun","Juice","Song","Strong","Mighty","Delight","Bay Horses","Hero","Horses","Spirit","Gifts"],"groups":["Son"],"concepts":["Good"],"hash":"md5-Fj+g4/4HOz+EY94/KVNoDQ==","created":"Monday, April 8, 2024 - 10:51:53 PM"},{"id":"3f6c2078-2b19-4ece-a783-3e2e169ae1a6","key":"05028","book":"05","title":"HYMN XXVIII. Agni.","link":"https://indra.ai/rigveda/hymns/05028.html","text":"p: AGNI inflamed hath sent to heaven his lustre: he shines forth widely turning unto Morning. Eas ward the ladle goes that brings all blessing, praising the Deva with homage and oblation.\n\np: Enkindled, thou art King of the immortal world: him who brings offerings thou attendest for his weal. He whom thou urgest on makes all possessions his: he sets before thee, Agni, gifts that guest. May claim.\n\np: Show thyself strong for mighty bliss, O Agni, most excellent be thine effulgent splendours. Make easy to maintain our household lordship, and overcome the might of those who hate us.\n\np: Thy glory, Agni, I adore, kindled, exalted in thy strength. A Steer of brilliant splendour, thou art lighted well at sacred rites.\n\np: Agni, invoked and kindled, serve the Devas, thou skilled in offering: For thou art bearer of our gifts.\n\np: Invoke and worship Agni while the offerings rite proceeds: For offering-bearer choose ye him.","people":["Agni","Deva"],"places":["Heaven"],"things":["Worship","Glory","Offering","Might","Strong","Mighty","Blessing","Splendour","Excellent","Offerings","Bliss","King","Morning","Gifts"],"groups":["Devas","Immortal"],"concepts":["Immortal","Sacred","Strength","Offering","Offerings"],"hash":"md5-cB6Tcv8rofThYTBpsPs/IA==","created":"Monday, April 8, 2024 - 10:51:53 PM"},{"id":"007c72d5-eef3-499c-af57-c631006706f6","key":"05029","book":"05","title":"HYMN XXIX. Agni.","link":"https://indra.ai/rigveda/hymns/05029.html","text":"p: MAN'S worship of the Devas hath three great lustres, and three celestial lights have they established The Maruts gifted with pure strength adore thee, for thou, O Indra, art their sapient Rsi.\n\np: What time the Maruts sang their song to Indra, joyous when he had drunk of Soma juices. He grasped his thunderbolt to subdue the Dragon, and loosed, that they might flow, the youthful Waters.\n\np: And, O ye Brahmans, Maruts, s. May Indra drink draughts of this my carefully pressed Soma; For this oblation found for man the cattle, and Indra, having quaffed it, slew the Dragon.\n\np: Then heaven and earth he sundered and supported: wrapped even in these he struck the Beast with terror. So Indra forced the Engulfer to disgorgement, and slew the Danava. panting against him.\n\np: Thus all the Devas delivered to thee of their free will the draught of Soma; When thou for Etasa didst cause to tarry the flying mares of Surya racing forward.\n\np: When Maghavan with the thunderbolt demolished his nine-and-ninety castles all together, the Maruts, where they met, glorified Indra: ye with the Trstup hymn obstructed heaven.\n\np: As friend to aid a friend, Agni dressed quickly three hundred buffaloes, even as he willed it. And Indra, from man's gift, for Vrtra's slaughter, drank ofr at once three lakes of pressed-out Soma.\n\np: When thou three hundred buffaloes' flesh hadst eaten, and drunk, as Maghavan, three lakes of Soma, All the Devas raised as ’twere a shout of triumph to Indra praise because.\n\np: What time ye came with strong steeds swiftly speeding, O Usana and Indra, to the dwelling, Thou camest thither -conquering together with Kutsa and the Devas: thou slewest Susna.\n\np: One car-wheel of the Sun thou rolledst forward, and one thou settest free to move for Kutsa. Thou slewest noseless Dasyus with thy weapon, and in their home o’erthrewest hostile speakers.\n\np: The lauds of Gauriviti made thee mighty to Vidathin's son, as prey, thou gavest Pipru. Rjisivan drew thee into friendship dressing the sacred food, and thou hast drunk his Soma.\n\np: Navagvas and Dasgvas with libations of Soma juice sing hymns of praise to Indra. Labouring at their task the men laid open the stall of Kine though firmly closed and fastened.\n\np: How shall I serve thee, Maghavan, though knowing full well what hero deeds thou hast accomplished? And the fresh deeds which thou wilt do, most Mighty! these, too, will we tell forth in sacred synods.\n\np: Resistless from of old through hero courage, thou hast done all these many acts, O Indra. What thou wilt do in bravery, Thunder-wielder! none is there wh. May hinder this thy prowess.\n\np: Indra, accept the prayers which now are offered, accept the new prayers, Mightiest! which we utter. Like fair and well-made robes, I, seeking riches, as a deft craftsman makes a car, have wrought them.","people":["Indra","Soma","Vrtra","Agni","Maghavan","Susna","Usana","Kutsa","Etasa","Surya"],"places":["Earth","Heaven"],"things":["Worship","Steeds","Triumph","Soma","Waters","Sun","Food","Men","Flow","Might","Juice","Song","Home","Strong","Mighty","Car","Praise","Hymn","Gift","Libations","Friend","Hero","Riches","Cattle","Wheel"],"groups":["Devas","Danava","Dasyus","Maruts","Brahmans","Son","Navagvas","Man"],"concepts":["Celestial","Friendship","Sacred","Strength","Libations"],"hash":"md5-Z9bqytnGLjWuehSOXRr67Q==","created":"Monday, April 8, 2024 - 10:51:53 PM"},{"id":"a78f8ded-e082-43cf-9e5a-a759ff6c1a4d","key":"05030","book":"05","title":"HYMN XXX. Indra.","link":"https://indra.ai/rigveda/hymns/05030.html","text":"p: WHERE is that Hero? Who hath looked on Indra borne on light-rolling car by Tawny Coursers, who, Thunderer, seeks with wealth we, and to his house goes, much-invoked, to aid him?\n\np: I have beheld his strong and secret dwelling, longing have sought the Founder's habitation. I asked of others, and they said in answer, may we, awakened men, attain to Indra.\n\np: We will tell, indra, when we pour libation, what mighty deeds thou hast performed to please us. Let him who knows not learn, who knows them listen: hither rides Maghavan with all his army.\n\np: Indra, when born, thou madest firm thy spirit: alone thou seekest war to fight with many. With might thou clavest e’en the rock asunder, and foundest out the stable of the Milch-kine.\n\np: When thou wast born supremest at a distance, bearing a name renowned in far-off regions, Since then e’en Devas have been afraid of Indra: he conquered all the floods which served the Dasa.\n\np: These blissful Maruts sing their psalm to praise thee, and pour to thee libation of the Soma. Indra with wondrous powers subdued the Dragon, the guileful lurker who beset the waters.\n\np: Thou, Maghavan, from the first didst scatter foemen, speeding, while joying in the milk, the Giver. There, seeking man's prosperity, thou torest away the head of Namuci the Dasa.\n\np: Pounding the head of Namuci the Dasa, me, too thou madest thine associate, indra! Yea, and the rolling stone that is in heaven both worlds, as on a car, brought to the Maruts.\n\np: Women for weapons hath the Dasa taken, what injury can his feeble armies To me? Well he distinguished his two different voices, and Indra then advanced to fight the Dasyu.\n\np: Divided from their calves the Cows went lowing around, on every side, hither and thither. These Indra re-united with his helpers, what time the well-pressed Soma made him joyful.\n\np: What time the Somas mixed by Babhru cheered him, loud the Steer bellowed in his habitations. So Indra drank thereof, the Fort-destroyer, and gave him guerdon, in return, of milch-kine.\n\np: This good deed have the Rusamas done, Agni! that they have granted me four thousand cattle. We have received Rnancaya's wealth, of heroes the most heroic, which was freely offered.\n\np: The Rusamas, O Agni, sent me homeward with fair adornment and with kine in thousands. The strong libations have made Indra joyful, when night, whose course was ending, changed to morning.\n\np: Night, well-nigh ended, at Rnancaya's coming, King of the Rusamas, was changed to morning. Like a strong courser, fleet of foot, urged onward, Babhru hath gained four thousand as his guerdon.\n\np: We have received four thousand head of cattle presented by the Rusamas, O Agni. And we, the singers, have received the caldron of metal which was heated for Pravargya.","people":["Indra","Soma","Agni","Maghavan","Namuci"],"places":["Heaven"],"things":["Milk","Tawny Coursers","Born","Soma","Waters","Light","Wealth","Men","Might","Strong","Mighty","Car","Armies","Praise","Heroes","Powers","Libations","Hero","King","Morning","Cattle","Spirit","Caldron"],"groups":["Devas","Dasyu","Maruts","Man"],"concepts":["Good","Heroic","Giver","Libations"],"hash":"md5-1QSFe4POVYg7Ro92bvzi9Q==","created":"Monday, April 8, 2024 - 10:51:53 PM"},{"id":"d59c2a16-f0c9-4507-83df-5e7df5bfd125","key":"05031","book":"05","title":"HYMN XXXI. Indra.","link":"https://indra.ai/rigveda/hymns/05031.html","text":"p: MAGHAVAN Indra turns his chariot downward, the strength-displaying car which he hath mounted. Even as a herdsman driveth forth his cattle, he goeth, first, uninjured, fain for treasure..\n\np:  Haste to us, Lord of Bays; be not ungracious: visit us, lover of gold-hued oblation. There is naught else better than thou art, indra: e’en to the wifeless hast thou given spouses.\n\np: When out of strength arose the strength that conquers, indra displayed all powers that he possesses. Forth from the cave he drove the milky mothers, and with the light laid bare investing darkness.\n\np:  Anus have wrought a chariot for thy Courser, and Tvastar, Much-invoked! thy bolt that glitters. The Brahmans with their songs exalting Indra increased his strength that he might slaughter Ahi.\n\np: When heroes sang their laud to thee the Hero, indra! and stones and Aditi accordant, without or steed or chariot were the fellies which, sped by Indra, rolled upon the Dasytis.\n\np: I will declare thine exploits wrought aforetime, and, Maghavan, thy deeds of late achievement, when, Lord of Might, thou sunderedst earth and heaven, winning for man the moistly-gleaming waters.\n\np: This is thy deed, e’en this, Wonderful! Singer! that, subduing Ahi, here thy strength thou showedst, Didst check and stay e’en gusna's wiles and magic, and, drawing nigh, didst chase away the Dasytis.\n\np: Thou, indra, on the farther bank forYadu and Turvaga didst stay the gushing waters. Ye both assailed the fierce: thou barest Kutsa: when Devas and Usana came to you together.\n\np: Let the steeds bring you both, indra and Kutsa, borne on the chariot within hearing-distance. Ye blew him from the waters, from his dwelling, and chased the darkness from the noble's spirit.\n\np: Even this sage hath come looking for assist even to Vata's docile harnessed horses. Here are the Maruts, all, thy dear companions: prayers have increased thy power and might, O Indra.\n\np: When night was near its close he carried forward e’en the Sun's chariot backward in its running. Etaga brought his wheel and firmly stays it: setting it eas ward he shall give us courage.\n\np: This Indra, O ye men, hath come to see you, seeking a friend who hath expressed the Soma. The creaking stone is laid upon the altar, and the Adhvaryus come to turn it quickly.\n\np: Let mortals who were happy still be happy; let them not come to sorrow, O Immortal. Love thou the pious, and to these thy people-with who. May we be numbered-give thou vigour.","people":["Indra","Soma","Maghavan","Tvastar","Usana","Kutsa","Vata","Aditi","Ahi","Turvaga"],"places":["Earth","Heaven"],"things":["Steeds","Lord","Soma","Waters","Singer","Light","Sun","Treasure","Men","Might","Gold","Car","Heroes","People","Lord of Bays","Powers","Songs","Friend","Hero","Sage","Horses","Winning","Cattle","Spirit","Wheel"],"groups":["Devas","Maruts","Brahmans","Immortal","Man","Spouses"],"concepts":["Love","Immortal","Strength","Noble"],"hash":"md5-tenQzQMHD6g93WuL8jrkEA==","created":"Monday, April 8, 2024 - 10:51:53 PM"},{"id":"cc84553f-7a60-40f2-a277-05c9ad4750e5","key":"05032","book":"05","title":"HYMN XXXII. Indra.","link":"https://indra.ai/rigveda/hymns/05032.html","text":"p: ṬHE well thou clavest, settest free the fountains, and gavest rest to floods that were obstructed. Thou, indra, laying the great mountain open, subduing the Danava, didst loose the torrents.\n\np: The fountain-depths obstructed in their seasons Thunderer! madest flow, the mountain's udder. Strong Indra, thou by subduing e’en the Dragon that lay extended there hast shown thy vigour.\n\np: Indra with violence smote down the weapon, yea, even of that wild and mighty creature.. Although he deemed himself alone unequalled, another had been born e’en yet more potent.\n\np: Him, whom the heavenly food of these delighted, child of the mist, strong waxing, couched in darknesshim the bolt-hurling Thunderer with his lightning smote down and slew, the Danava's wrath-fire, Susna.\n\np: Though he might ne’er be wounded still his vitals felt that, the Deva's bolt, which his powers supported, when, after offered draughts, Strong Lord, thou laidest him, fain to battle, in the pit in darkness.\n\np: Him as he lay there huge in length extended, still waxing in the gloom which no sun lightenedhim, after loud-voiced threats, the Hero Indra, rejoicing in the poured libation, slaughtered.\n\np: When 'gainst the mighty Danava his weapon Indra uplifted, power which none could combat, when at the hurling of his bolt he smote him, he made him lower than all living creatures.\n\np: The fierce Deva.seized that huge and restless coiler, insatiate, drinker of the sweets, recumbent, and with his mighty weapon in his dwelling smote down the footless evil-speaking ogre.\n\np: Wh. May arrest his strength or cheek his vigour? Alone, resistless, he bears off all riches. Even these Twain, these Devas, through terror of Indra's might, retire from his dominion.\n\np: E’en the Celestial Axe bows down before him, and the Earth, lover-like, gives way to Indra. As he imparts all vigour to these people, straightway the folk bend them to him the Deva like.\n\np: I hear that thou wast born sole Lord of heroes of the Five Races, famed among the people. As such my wishes have most lately grasped him, invoking Indra both at eve and morning.\n\np: So, too, I hear of thee as in due season urging to action and enriching singers. What have thy friends received from thee, the Brahmans who, faithful, rest their hopes on thee, O Indra?","people":["Indra","Susna","Deva"],"places":["Earth"],"things":["Lord","Seasons","Born","Sun","Food","Flow","Might","Strong","Mighty","Heroes","People","Powers","Friends","Hero","Riches","Morning"],"groups":["Devas","Danava","Brahmans","Child"],"concepts":["Celestial","Evil","Heavenly","Strength"],"hash":"md5-G4NadKYGy6tURc0u4Qn5KA==","created":"Monday, April 8, 2024 - 10:51:53 PM"},{"id":"503785e7-7693-41ef-848a-34adac67f281","key":"05033","book":"05","title":"HYMN XXXIII. Indra.","link":"https://indra.ai/rigveda/hymns/05033.html","text":"p: GREAT praise to Indra, great and strong mid heroes, I ponder thus, the feeble to the Mighty, who with his band shows favour to this people, when lauded, in the fight where spoil is gathered.\n\np: So made attentive by our hymns, Steer! Indra! thou fastenedst the girth of thy Bay Coursers, Which, Maghavan, at thy will thou drivest hither. With these subdue for us the men who hate us.\n\np: They were not turned to us wtrd, lofty Indra! while yet through lack of prayer they stood unharnessed. Ascend this chariot, thou whose hand wields thunder, and draw the rein, O Lord of noble horses.\n\np: Thou, because many lauds are thine, O Indra, wast active warring in the fields for cattle. For Surya in his own abode thou. Hero, formedst in fights even a Dasa's nature.\n\np: Thine are we, indra; thine are all these people, conscious of might, whose cars are set in motion. Some hero come to us, O Strong as Ahi beauteous in war, to be invoked like Bhaga.\n\np: Strength much to be desired is in thee, indra: the Immortal dances forth his hero exploits. Such, Lord of Treasure, give us splendid riches. I praise the Friend's gift, his whose wealth is mighty.\n\np: Thus favour us, O Indra, with ihy assist; Hero, protect the bards who sing thy praises. Be friendly in the fray to those who offer the skin of beautiful and well-pressed Soma.\n\np: And these ten steeds which Trasadasyu gives me, the goldrich chief, the son of Purukutsa, Resplendent in their brightness shall convey me. Gairiksita willed it and so came I hither.\n\np: And these, bestowed as offerings guerdon, the powerful tawny steeds of Marutasva; And thousands which kind Cyavatana gave me, abundantly bestowed for my adornment.\n\np: And these commended horses, bright and active, by Dhvanya son of Laksmana presented, Came unto me, as cows into the Rsi Samvarana's stall, with magnitude of riches.","people":["Indra","Soma","Maghavan","Bhaga","Surya","Ahi"],"places":[],"things":["Steeds","Lord","Soma","Treasure","Wealth","Men","Might","Strong","Mighty","Chief","Praise","Heroes","Gift","Ascend","People","Offerings","Friend","Hero","Horses","spoil","Riches","Cars","Cattle"],"groups":["Son","Immortal"],"concepts":["Beautiful","Cars","Immortal","Strength","Offerings","Powerful","Noble"],"hash":"md5-Sx3Axogn98Wl7EQYQD2H1Q==","created":"Monday, April 8, 2024 - 10:51:53 PM"},{"id":"698d30bc-aa96-44e1-bbc2-5716933cea5b","key":"05034","book":"05","title":"HYMN XXXIV. Indra.","link":"https://indra.ai/rigveda/hymns/05034.html","text":"p: BOUNDLESS and wasting not, the heavenly food of Devas goes to the foeless One, doer of wondrous deeds. Press out, make ready, offer gifts with special zeal to him whom many laud, accepter of the prayer.\n\np: He who filled full his belly with the Soma's juice, Maghavan, was delighted with the meath's sweet draught, when Usana, that he might subdue the monstrous beast, gave him the mighty weapon with a thousand points.\n\np: Illustrious is the man whoever presseth out Soma for him in sunshine or in cloud and rain. The mighty Maghavan who is the sage's Friend advanceth more and more his beauteous progeny.\n\np: The Strong Deva.doth not flee away from him whose sire, whose mother or whose brother he hath done to death. He, the Avenger, seeketh this man's offered gifts: this Deva, the source of riches, doth not flee from sin.\n\np: He seeks no enterprise with five or ten to aid, nor stays with him who pours no juice though prospering well. The Shaker conquers or subdues in this way or that, and to the pious gives a stable full of kine.\n\np: Exceeding strong in war he stays the chariot wheel, and, hating him who pours not, prospers him who pours. Indra, tamer of every man, as Arya leads away the Dasa at his will.\n\np: He gathers up for plunder all the niggard’s gear: excellent wealth he gives to him who offers gifts. Not even in wide stronghol. May all the folk stand firm who have provoked to anger his surpassing might.\n\np: When Indra Maghavan hath marked two wealthy men fighting for beauteous cows with all their followers. He who stirs all things takes one as his close ally, and, Shaker, with his Heroes, sends the kine to him.\n\np: Agni! I laud the liberal Agnivesi, Satri the type and standard of the pious. May the collected waters yield him plenty, and his be powerful and bright dominion.","people":["Indra","Soma","Agni","Maghavan","Usana","Deva"],"places":[],"things":["Meath","Soma","Waters","Wealth","Food","Men","Might","Juice","Rain","Strong","Mighty","Heroes","Offers","Excellent","Friend","Sage","Riches","Death","Gifts","Wheel"],"groups":["Devas","Mother","Brother","Progeny","Man"],"concepts":["Death","Heavenly","Special","Powerful"],"hash":"md5-iwPzDtkhrSCHJMfLGEfh9w==","created":"Monday, April 8, 2024 - 10:51:53 PM"},{"id":"8b314d77-711d-45d7-bccd-3f7d61f8c705","key":"05035","book":"05","title":"HYMN XXXV. Indra.","link":"https://indra.ai/rigveda/hymns/05035.html","text":"p: INDRA, for our assistance bring that most effectual power of thine, Which conquers men for us, and wins the spoil, invincible in fight.\n\np: Indra, whatever aids be thine, four be they, or, O Hero, three, or those of the Five Tribes of men, bring quickly all that help to us.\n\np: The aid most excellent of thee the Mightiest hitherward we call, for thou wast born with hero might, conquering, indra, with the Strong.\n\np: Mighty to prosper us wast thou born, and mighty is the strength thou hast. In native power thy soul is firm: thy valour, indra, subdues a host.\n\np: O Satakratu, Lord of Strength, O Indra, Caster of the Stone. With all thy chariot's force assail the man who shows himself thy foe.\n\np: For, Mightiest Vrtra conquerer, thee, fierce, foremost among many, folk Whose sacred grass is trimmed invite to battle where the spoil is won.\n\np: Indra, do thou protect our car that mingles foremost in the fights, that bears its part in every fray, invincible and seeking spoil.\n\np: Come to us, indra, and protect our car with thine intelligence. May we, O Mightiest One, obtain excellent fame at break of day, and meditate our hymn at dawn.","people":["Indra","Vrtra","Satakratu","Dawn"],"places":[],"things":["Lord","Born","Men","Might","Help","Strong","Mighty","Grass","Car","Hymn","Excellent","Hero","call","spoil"],"groups":["Man"],"concepts":["Sacred","Strength","Intelligence"],"hash":"md5-rpTCr3R+2eEEDi1vp0TlIQ==","created":"Monday, April 8, 2024 - 10:51:53 PM"},{"id":"d6314608-c5b3-45ec-a811-e2b0c77af0b2","key":"05036","book":"05","title":"HYMN XXXVI. Indra.","link":"https://indra.ai/rigveda/hymns/05036.html","text":"p: MAY Indra come to us, he who knows rightly to give forth treasure.s from his store of riches. Even as a thirsty steer who roams the desert. May he drink eagerly the milked-out Soma.\n\np: Lord of Bay Horses. Hero. May the Soma rise to thy cheeks and jaws like mountain-ridges. May we, O King, as he who driveth coursers, all joy in thee with hymns, invoked of many!\n\np: Invoked of many, Caster of the Stone my heart quakes like a rolling wheel for fear of penury. Shall not Puruvasu the singer give thee praise, O ever-prospering Maghavan, mounted on thy car?\n\np: Like the press-stone is this thy praiser, indra. Loudly he lifts his voice with stron endeavour. With thy left hand give us riches: with thy right, Lord of Bays, be not reluctant.\n\np: May the strong Heaven make thee the Strong wax stronger: Strong, thou art borne by thy two strong Bay Horses. So, fair of cheek, with mighty chariot, mighty, uphold us, strong-willed, thunderarmed, in battle.\n\np: Maruts, let all the people in obeisance bow down before this youthful Srutaratha, who, rich in steeds, gave me two dark red horses together with three hundred head of cattle.","people":["Indra","Soma","Maghavan"],"places":["Heaven"],"things":["Steeds","Lord","Soma","Singer","Treasure","Joy","Strong","Mighty","Car","Praise","Voice","People","Bay Horses","Lord of Bays","Hero","King","Horses","Riches","Cattle","Wheel"],"groups":["Maruts"],"concepts":[],"hash":"md5-TSAzFI6i5LaKbdeMc1YfAA==","created":"Monday, April 8, 2024 - 10:51:53 PM"},{"id":"6e798f8f-6c9e-47dc-a37c-fd9e97296d1a","key":"05037","book":"05","title":"HYMN XXXVII. Indra.","link":"https://indra.ai/rigveda/hymns/05037.html","text":"p: BEDEWED with holy oil and meetly worshipped, the Swift One vies with Surya's beam in splendour. For hi. May mornings dawn without cessation who saith, Let us press Soma out for Indra.\n\np: With kindled fire and strewn grass let him worship, and, Soma-presser, sing with stones adjusted: And let the Sage whose press-stones ring forth loudly, go down with his oblation to the river.\n\np: This wife is coming near who loves her husband who carries to his home a vigorous consort. Her. May his car seek fame, here loudly thunder, and his wheel make a thousand revolutions.\n\np: No troubles vex that King in whose home Indra drinks the sharp Soma juice with milk commingled. With heroes he drives near, he subdues the foeman: Blest, cherishing that name, he guards his people.\n\np: May he support in peace and win in battle: he masters both the hosts that meet together. Dear shall he be to Surya, dear to Agni, who with pressed Soma offers gifts to India.","people":["Indra","Soma","Agni","Surya","Dawn"],"places":[],"things":["Worship","Masters","Milk","Soma","River","Juice","Home","Grass","Car","Heroes","Splendour","Offers","People","King","Sage","Gifts","Wheel"],"groups":["Wife","Husband"],"concepts":["Holy","Worshipped","Swift"],"hash":"md5-4gIAYc5QpmM/sGFEGav6ng==","created":"Monday, April 8, 2024 - 10:51:53 PM"},{"id":"f1ec17b1-73ab-45d4-8e1b-f924c4c5218e","key":"05038","book":"05","title":"HYMN XXXVIII. Indra.","link":"https://indra.ai/rigveda/hymns/05038.html","text":"p: WIDE, indra Satakratu, spreads the bounty of thine ample grace: So, Lord of fair dominion, Friend of all men, give us splendid wealth.\n\np: The food which, Mightiest Indra, thou possessest worthy of renown Is bruited as most widely famed, invincible, O Golden-hued!\n\np: O Darter of the Stone, the powers which readily obey thy will. Divinities, both thou and they, ye rule, to guard them, earth and heaven.\n\np: And from whatever power of thine, O Vrtra conquerer, i. May be, Bring thou to us heroic strength: thou hast a man's regard for us.\n\np: In thy protection, with these aids of thine, O Lord of Hundred Powers, indra, may we be guarded well. Hero. May we be guarded well.","people":["Indra","Vrtra","Satakratu"],"places":["Earth","Heaven"],"things":["Lord","Wealth","Food","Men","Powers","Friend","Hero"],"groups":["Man"],"concepts":["Heroic","Strength"],"hash":"md5-HGSuHKzWSZ9I9U3FG7C2XA==","created":"Monday, April 8, 2024 - 10:51:53 PM"},{"id":"cd9cb345-b7b3-49e0-ad2f-6e01cc2ab460","key":"05039","book":"05","title":"HYMN XXXIX. Indra.","link":"https://indra.ai/rigveda/hymns/05039.html","text":"p: STONE-DARTING Indra. Wondrous One, what wealth is richly given from thee, that bounty, Treasure-Finder! bring filling both thy hands, to us.\n\np: Bring what thou deemest worth the wish, O Indra, that which is in heaven. May we know thee as thou art, boundless in thy munificence.\n\np: Thy lofty spirit, far-renowned as fain to give and prompt to win. With this thou rendest e’en the firm, Stone-Darter! so to gain thee strength.\n\np: Singers with many songs have made Indra propitious to their famehim who is King of human kind, most liberal of your wealthy ones.\n\np: To him, to Indra must be sung the poet's word, the hymn of praise. To him, accepter of the prayer, the Atris raise their songs on high, the Atris beautify their songs.","people":["Indra"],"places":["Heaven"],"things":["Treasure","Wealth","Praise","Hymn","Songs","King","Spirit"],"groups":["Atris","Human"],"concepts":["Strength"],"hash":"md5-7XY1vpq8KRaDComulbeDTw==","created":"Monday, April 8, 2024 - 10:51:54 PM"},{"id":"140e30f0-f257-4607-916d-c84ce2a1f3b5","key":"05040","book":"05","title":"HYMN XL. Indra. Surya. Atri.","link":"https://indra.ai/rigveda/hymns/05040.html","text":"p: COME thou to what the stones have pressed, drink Soma, O thou Soma's Lord, indra best Vrtra conquerer Strong One, with the Strong.\n\np: Strong is the stone, the draught is strong, strong is this Soma that is pressed, indra, best Vrtra conquerer, Strong One with the Strong.\n\np: As strong I call on thee the Strong, O Thunder-armed, with various aids, indra, best Vrtra conquerer, Strong One with the Strong.\n\np: Impetuous, Thunderer, Strong, quelling the mighty, King, potent, Vrtra conquerer, Soma-drinker, may he come hither with his yoked Bay Horses. May Indra gladden him at the noon libation.\n\np: O Surya, when the Asura's descendant Svarbhanu, pierced thee through and through with darkness, All creatures looked like one who is bewildered, who knoweth not the place where he is standing.\n\np: What time thou smotest down Svarbhanu's magic that spread itself beneath the sky, O Indra, by his fourth sacred prayer Atri disoovered Surya concealed in gloom that stayed his function.\n\np: Let not the oppressor with this dread, through anger swallow me up, for I am thine, O Atri. Mitra art thou, the sender of true blessings: thou and King Varuna be both my helpers.\n\np: The Brahman Atri, as he set the press-stones, serving the Devas with praise and adoration, Established in the heaven the eye of Surya, and caused Svarbhanu's magic arts to vanish.\n\np: The Atris found the Sun again, him whom Svarbhanu of the brood Of Asuras had pierced with gloom. This none besides had power to do.","people":["Indra","Soma","Vrtra","Mitra","Varuna","Atri","Surya"],"places":["Heaven","Sky"],"things":["Lord","Soma","Sun","Strong","Mighty","Praise","Bay Horses","King","Horses","call"],"groups":["Devas","Asura","Asuras","Atris"],"concepts":["Blessings","Sacred"],"hash":"md5-W9IBXaGNeiohFEtBa3c01A==","created":"Monday, April 8, 2024 - 10:51:54 PM"},{"id":"ba7cb784-898c-490e-b897-f4ee6303671a","key":"05041","book":"05","title":"HYMN XLI. Devas","link":"https://indra.ai/rigveda/hymns/05041.html","text":"p: WHO, Mitra and Varuna, is your pious servant to give you gifts from earth or mighty heaven? Preserve us in the seat of holy Order, and give the offerer power that winneth cattle.\n\np: May Mitra, Varuna, Aryaman, and Ayu, indra Rbhuksan, and the Maruts, love us, and they who of one mind with bounteous Rudra accept the hymn and laud with adorations.\n\np: You will I call to feed the car-horse, Asvins, with the wind's flight swiftest of those who travel: Or also to the Asura of heavenworshipful, bring a hymn as ’twere libation.\n\np: The heavenly Victor, he whose priest is Kanva, Trta with Dyaus accordant, Vata, Agni, All-feeding Pusan, Bhaga sought the oblation, as they whose steeds are fleetest seek the contest.\n\np: Bring ye your riches forward borne on horses: let thought be framed for help and gain of treasure.. Blest he the Sage of Ausija through courses, the courses which are yours the fleet, O Maruts.\n\np: Bring hither him who yokes the car, your Vayu, who praises with his songs, the Deva.and Singer; And, praying and devout, noble and prudent. May the Deva Spouses in their thoughts retain us.\n\np: I speed to you with powers that should be honoured, with songs distinguishing Heaven's mighty Daughters, Morning and Night, the Two, as ’twere all-knowing: these bring  'the offering unto the mortal.\n\np: You I extol, the nourishers of heroes bringing you gifts, Vastospati and Tvastar- Rich Dhisana accords through our obeisance - andTrees and Plants, for the swift gain of riches.\n\np: Ours be the Parvatas, even they, for offspring, free-moving, who are Heroes like the Vasus. May holy Aptya, Friend of man, exalted, strengthen our word forever and be near us.\n\np: Trta praised him, germ of the earthly hero, with pure songs him the Offspring of the Waters. Agn; with might neighs loudly like a charger: he of the flaming hair destroys the forests.\n\np: How shall we speak to the great might of Rudra? How speak to Bhaga who takes thought for riches? May Plants, the Waters, and the Sky preserve us, and Woods and Mountains with their trees for tresses.\n\np: May the swift Wanderer, Lord of refreshments listen to our songs, who speeds throuih cloudy heaven: An. May the Waters, bright like castles, hear us, as they flow onward from the cloven mountain.\n\np: We know your ways, ye MightyOnes receiving choice meed, ye Wonderful, we will proclaim it. Even strong birds descend not to the mortal who strives to reach them with swift blow and weapons.\n\np: Celestial and terrestrial generations, and Waters will I summon to the feasting. May days with bright dawns cause my songs to prosper, an. May the conquered streams increase their waters.\n\np: Duly to each one hath my laud been offered. Strong be Varutri with her powers to assist. May the great Mother Rasa here befriend us, straight-handed, with the princes, striving forward.\n\np: Ho. May we serve the Liberal Ones with worship, the Maruts swift of course in invocation, the Maruts far-renowned in invocation? Let not the Dragon of the Deep annoy us, and gladl. May he welcome our addresses.\n\np: Thus thinking, O ye Devas, the mortal wins you to give him increase of his herds of cattle: the mortal wins him, O ye Devas, your favour. Here he wins wholesome food to feed this body: as for mine old age, Nirrti consume it\n\np: O Devas. May we obtain from you this favour, strengthening food through the Cow's praise, ye Vasus. May she who gives good gifts, the gracious Deva.es. s, come speeding nigh to us for our well-being.\n\np: May Ila, Mother of the herds of cattle, and Urvasi with all the streams accept us; May Urvasi in lofty heaven accepting, as she partakes the oblation of the living,\n\np: Visit us while she shares Urjavya's food.","people":["Indra","Agni","Vayu","KanVa","Mitra","Varuna","Asvins","Tvastar","Varutri","Dhisana","Pusan","Bhaga","Deva","Urvasi","Ila","Vata","Urjavya","Trta","Aptya","Rasa","Ayu","Aryaman","Rbhuksan"],"places":["Earth","Heaven","Sky"],"things":["Worship","Steeds","Lord","Mountains","Waters","Singer","Offering","Treasure","Food","Streams","Flow","Might","Help","Offspring","Strong","Mighty","Car","Praise","Hymn","Heroes","Powers","Songs","Friend","Hero","Sage","Cow","Horses","Horse","call","Riches","Order","Morning","Cattle","Gifts"],"groups":["Devas","Asura","Dyaus","Maruts","Dawns","Parvatas","Mother","MightyOnes","Man","Vasus","Spouses"],"concepts":["Celestial","Good","Heavenly","Love","Holy","Devout","Offering","Swift","Dragon of the Deep","Noble"],"hash":"md5-H3Auhjifx9edquFyf+lDmQ==","created":"Monday, April 8, 2024 - 10:51:54 PM"},{"id":"fc778ead-75b6-474b-85bb-37dbf70af93e","key":"05042","book":"05","title":"HYMN XLII, Devas.","link":"https://indra.ai/rigveda/hymns/05042.html","text":"p: No. May our sweetest song with deep devotion reach Varuna, Mitra, Aditi, and Bhaga. May the Five Monks' Lord, dwelling in oblations, bliss-giving Asura, hear, whose paths are open.\n\np: May Aditi welcome, even as a mother her dear heart-gladdening son, my song that lauds her. The prayer they love, bliss-giving, Deva.appointed, I offer unto Varuna and Mitra.\n\np: In spirit him, the Sagest of the Sages; with offerings oil and meath bedew him  So then let him, Deva.Savitar, provide us excellent, ready, and resplendent treasure.s.\n\np: With willing mind, indra, vouchsafe us cattle, prosperity, Lord of Bays! and pious patrons; And, with the sacred prayer by Devas appointed, give us the holy Deities' lovingkindness.\n\np: Deva.Bhaga, Savitar who deals forth riches, indra, and they who conquer Vrtra's treasure.s, and Vaja and Rbhuksan and Purandhi, the Mighty and Immortal Ones, protect us!\n\np: Let us declare his deeds, the undecaying unrivalled Victor whom the Maruts follow. None of old times nor later, none of these days hath reached thy hero prowess.\n\np: Praise him the Chief who gives the boon of riches, Narasamsa distributor of treasure.s, who, blessing most the man who sings and praises, comes with abundant wealth to his invoker.\n\np: Tended, Narasamsa, with thy protections, the princes are unharmed and girt by heroes. Wealth that brings bliss is found among the givers of horses and of cattle and of raiment.\n\np: Make their wealth flee who, through our hymns enjoying their riches, yield us not an ample guerdon. Far from the sun keep those who hate devotion, the godless, prospering in their vocation.\n\np: With wheelless chariots drive down him, O Maruts, who at the feasts of Devas regards the demons. May he, though bathed in sweat, form empty wishes, who blames his sacred rite who toils to serve you.\n\np: Praise him whose bow is strong and sure his arrow, him who is Lord of every balm that bealeth. Worship thou Rudra for his great good favour: adore the Asura, Deva, with salutations.\n\np: May the House-friends, the cunning-handed Artists. May the Steer's Wives, the streams carved out by Vibhvan, an. May the fair Ones honour and befriend us, Sarasvati, Brhaddiva, and Raka.\n\np: My newest song, thought that now springs within me, I offer to the Great, the Sure Protector, who made for us this All, in fond love laying each varied form within his Daughter's bosom.\n\np: Now, even nowe may thy fair praise, O Singer, attain Idaspati who roars and thunders, who, rich in clouds and waters with his lightning speeds forth bedewing both the earth and heaven.\n\np: May this my laud attain the troop of Maruts, those who are youths in act, the Sons of Rudra. The wish calls me to riches and well-being: praise the unwearied Ones whose steeds are dappled.\n\np: May this my laud reach earth and air's mid-region, and forest trees and plants to win me riches. May every Deity be swift to listen, and Mother Earth with no ill thought regard me.\n\np: Devas. May we dwell in free untroubled bliss.\n\np: May we obtain the Asvins' newest favour, and gain their health-bestowing happy guidance. Bring riches hither unto us, and heroes, and all felicity and joy, Immortals!","people":["Indra","Vrtra","Mitra","Varuna","Asvins","Narasamsa","Savitar","Sarasvati","Bhaga","Deva","Aditi","Vibhvan","Vaja","Purandhi","Rbhuksan"],"places":["Earth","Heaven"],"things":["Worship","Meath","Steeds","Lord","Waters","Chariots","Singer","Air","Sun","Treasure","Wealth","Boon","Streams","Song","Joy","Strong","Mighty","Blessing","Chief","Praise","Heroes","Form","Excellent","Lord of Bays","Offerings","Friends","Bliss","Hero","Horses","Riches","Cattle","Spirit"],"groups":["Devas","Asura","Maruts","Sons","Deities","Mother","Son","Immortal","Man","Monks"],"concepts":["Good","Love","Immortal","Holy","Sacred","Offerings","Swift"],"hash":"md5-nMiPdBesVs7NdH/iGC30Rg==","created":"Monday, April 8, 2024 - 10:51:54 PM"},{"id":"7e977ff1-a65c-4667-9a04-4e27eba097cc","key":"05043","book":"05","title":"HYMN XLIII, Devas.","link":"https://indra.ai/rigveda/hymns/05043.html","text":"p: MAY the Milch-cows who hasten to their object come harmless unto us with liquid sweetness. The Singer, lauding, calls, for ample riches, the Seven MightyOnes who bring enjoyment.\n\np: With reverence and fair praise will I bring hither, for sake of strength, exhaustless Earth and Heaven. Father and Mother, sweetof speech, fairhanded. May they, far-famed, in every fight protect us.\n\np: Adhvaryus, make the sweet libations ready, and bring the beautiful bright juice to Vayu. Deva, as our Monk, be thou the first to drink it: we give thee of the mead to make thee joyful.\n\np: Two arms-the Soma's dexterous immo. lators-and the ten fingers set and fix the press-stone. The stalk hath poured, fair with its spreading branches, the mead's bright glittering juice that dwells on mountains.\n\np: The Soma hath been pressed for thee, its lover, to give thee power and might and high enjoyment. Invoked, turn hither in thy car, O Indra, at need, thy two well-trained and dear Bay Horses.\n\np: Bring by Deva.traversed paths, accordant, Agni, the great Aramati, Celestial Lady, Exalted, worshipped with our gifts and homage, who knoweth holy Law, to drink sweet Soma.\n\np: As on his father's lap the son, the darling, so on the fire is set the sacred caldron, Which holy singers deck, as if extending and heating that which holds the fatty membrane.\n\np: Hither, as herald to invite the Asvins, come the great lofty song, most sweet and pleasant! Come in one car, joy-givers! to the banquet, like the bolt binding pole and nave, come hither.\n\np: I have declared this speech of adoration to mightiest Pusan and victorious Vayu, who by their bounty are the hymns' inspirers, and of themselves give power as a possession.\n\np: Invoked by us bring hither, jatavedas the Maruts all under their names and figures. Come to  'the offering with aid all Maruts, all to the songs and praises of the singer!\n\np: From high heave. May Sarasvati the Holy visit  'our offering, and from the mountain. Eager, propitious. May the balmy Deva hear our effectual speech, our invocation.\n\np: Set in his seat the Deva whose back is dusky, Narasamsa the lofty, the Disposer. Him let us worship, set within the dwelling, the red, the golden-hued, the allresplendent.\n\np: May the Sustainer, high in heaven, come hither, the Bounteous One, invoked, with all his favours, Dweller with Dames divine, with plants, unwearied, the Steer with triple horn, the life-bestower.\n\np: The tuneful eloquent monks of him who liveth have sought the Mother's bright and loftiest station. As living men, with offered gifts and homage they deck the most auspicious Child to clothe him.\n\np: Agni, great vital power is thine, the mighty: pairs waxing old in their devotion seek thee. May every Deity be swift to listen, and Mother Earth with no ill thought regard me.\n\np: Devas. May we dwell in free untroubled bliss.\n\np: May we obtain the Asvins' newest favour, and gain their health-bestowing happy guidance. Bring riches hither unto us, and heroes, and all felicity and joy, Immortals!","people":["Indra","Soma","Agni","Vayu","Asvins","Narasamsa","Pusan","Sarasvati","Deva"],"places":["Earth","Heaven"],"things":["Worship","Mountains","Reverence","Soma","Singer","Offering","Men","Might","Juice","Song","Joy","Mighty","Car","Banquet","Praise","Heroes","Bay Horses","Libations","Bliss","Songs","Horses","Riches","Life","Gifts","Caldron"],"groups":["Devas","Maruts","Jatavedas","Dames","Father","Mother","Son","Child","MightyOnes","Monks"],"concepts":["Celestial","Life","Divine","Beautiful","Holy","Sacred","Strength","Offering","Worshipped","Auspicious","Libations","Swift","Speech"],"hash":"md5-8PFb0vgBme+c4I/dMxENlg==","created":"Monday, April 8, 2024 - 10:51:54 PM"},{"id":"4b00cb5a-874a-4fd1-808c-6a5cd5813bec","key":"05044","book":"05","title":"HYMN XLIV, Devas.","link":"https://indra.ai/rigveda/hymns/05044.html","text":"p: As in the first old times, as all were wont, as now, he draweth forth the power turned hitherward with song, the Princedom throned on holy grass, who findeth light, swift, conquering in the' plants wherein he waxeth strong.\n\np: Shining to him who leaves heaven's regions undisturbed, which to his sheen who is beneath show fair in light, Good guardian art thou, not to be deceived, most Wise! Far from deceits thy name dwelleth in holy Law.\n\np: Truth waits upon oblation present and to come: naught checks him in his way, this vic tory- bringing Monk: The Mighty Child who glides along the sacred grass, the undecaying Youth set in the midst of plants.\n\np: These come, well-yoked, to you for furtherance in the rite: down come the twinborn strengtheners of Law for him, with reins easily guided and commanding all. In the deep fall the hide stealeth away their names.\n\np: Thou, moving beauteously in visibly pregnant ones, snatching with trees the branching plant that grasps the juice. Shinest, true Singer! mid the upholders of the voice. Increase thy Consorts thou, lively at offering.\n\np: Like as he is beheld such is he said to be. They with effectual splendour in the floods have made Earth yield us room enough and amply wide extent, great might invincible, with store of hero sons.\n\np: Surya the Sage, as if unwedded, with a Spouse, in battle-loving spirit moveth o’er the foes. May he, self-excellent, grant us a sheltering home, a house that wards the fierce heat off on every side.\n\np: Thy name, sung forth by Rsis in these hymns of ours, goes to the loftier One with this swift mover's light. By skill he wins the boon whereon his heart is set: he who bestirs himself shall bring the thing to pass.\n\np: The chief and best of these abideth in the sea, nor doth libation fail wherein it is prolonged. The heart of him who praiseth trembleth not in fear there where the hymn is found connected with the pure.\n\np: For it is he: with though to of Ksatra, Manasa, of Yajata, and Sadhri, and Evavada, with Avatsara's sweet songs will we strive to win the mightiest strength which even he who knows should gain.\n\np: The Hawk is their full source, girth-stretching rapturous drink of Visvavara, of Mayin, and Yajata. They ever seek a fresh draught so that the, may come, know when thy time to halt and drink thy fill is near.\n\np: Sadaprna the holy, Tarya, Srutavit, and Bahuvrkta, joined with you, have slain the foes. He gains his wish in both the worlds and brightly shines when he adores the host with well-advancing steeds.\n\np: The worshipper's defender is Sutambhara, producer and uplifter of all holy thoughts. The MilchCow brought, sweet-flavoured milk was dealt around. Who speaks the bidding text knows this, not he who sleeps.\n\np: The sacred hymns love him who wakes and watches: to him who watches come the Sama verses. This Soma saith unto the man who watches, I rest and have my dwelling in thy friendship.\n\np: Agni is watchful, and the gcas love him; Agni is watchful, Sama verses seek him. Agni is watchful, to him saith this Soma, I rest and have my dwelling in thy friendship.","people":["Soma","Agni","Surya"],"places":["Earth","Heaven"],"things":["Milk","Steeds","Soma","Singer","Offering","Light","Boon","Might","Juice","Song","Home","Wise","Strong","Mighty","Grass","Chief","Voice","Worshipper","Hymn","Splendour","Excellent","Songs","Hero","Sage","Spouse","Spirit","MilchCow"],"groups":["Sons","Child","Rsis","Man"],"concepts":["Good","Friendship","Love","Holy","Sacred","Strength","Offering","Truth","Swift"],"hash":"md5-anCaGwryYafeX4+NB2PUzw==","created":"Monday, April 8, 2024 - 10:51:54 PM"},{"id":"0f1e482a-1839-4c6b-a129-582e344485d5","key":"05045","book":"05","title":"HYMN XLV, Devas.","link":"https://indra.ai/rigveda/hymns/05045.html","text":"p: BARDS of approaching Dawn who know the heavens are come with hymns to throw the mountain open. The Sun hath risen and oped the stable portals: the doors of men, too, hath the Deva.thrown open.\n\np: Surya hath spread his light as splendour: hither came the Cows' Mother, conscious, from the stable, to streams that flow with biting waves to deserts; and heaven is stablished like a firm-set pillar.\n\np: This laud hath won the burden of the mountain. To aid the ancient birth of mighty waters The mountain parted. Heaven performed his office. The worshippers were worn with constant serving.\n\np: With hymns and Deva.loved words will I invoke you, indra and Agni, to obtain your favour, for verily sages, skilled in sacrificing, worship the Maruts and with lauds invite them.\n\np: This day approach us. May our thoughts be holy, far from us let us cast away misfortune. Let us keep those who hate us at a distance, and haste to meet the man who offers.\n\np: Come, let us carry out, O friends, the purpose wherewith the Mother threw the Cow's stall open, that wherewith Manu conquered Visisipra, wherewith the wandering merchant gained heaven's water.\n\np: Here, urged by hands, loudly hath rung the press-stone wherewith Navagvas through ten months sang praises. Sarama went aright and found the cattle. Angiras gave effect to all their labours.\n\np: When at the dawning of this mighty Deva, Angirases all sang forth with the cattle. Their spring is in the loftiest place of meeting.Sarama found the kine by Order's pathway.\n\np: Borne by his Coursers Seve. May Surya visit the field that spreadeth wide for his long journey. Down on the Soma swooped the rapid Falcon. Bright was the young Sage moving mid his cattle.\n\np: Surya hath mounted to the shining ocean when he hath yoked his fair-backed Tawny Horses. The wise have drawn him like a ship through water: the floods obedient have descended hither.\n\np: I lay upon the Floods your hymn, lightwinning, wherewith Navagvas their ten months completed. Through this our hym. May we have Devas to guard us: through this our hymn pass safe beyond affliction.","people":["Indra","Soma","Agni","Angiras","Deva","Surya","Dawn","Sarama"],"places":["Ocean","Heaven"],"things":["Worship","Journey","Soma","Waters","Water","Light","Sun","Men","Streams","Flow","Wise","Mighty","Hymn","Splendour","Offers","Friends","Sage","Cow","Horses","Order","Cattle"],"groups":["Devas","Maruts","Worshippers","Mother","Angirases","Navagvas","Man"],"concepts":["Birth","Holy"],"hash":"md5-pet7OrZWjouocc058hfyXw==","created":"Monday, April 8, 2024 - 10:51:54 PM"},{"id":"689bd0ea-b577-4e46-9f49-5e7f7148ec64","key":"05046","book":"05","title":"HYMN XLVI, Devas.","link":"https://indra.ai/rigveda/hymns/05046.html","text":"p: WELL knowing I have bound me, horselike, to the pole: I carry that which bears as on and gives us help. I seek for no release, no turning back therefrom. May he who knows the way, the Leader, guide me straight.\n\np: O Agni, indra, Varuna, and Mitra, give, O ye Devas, and Marut host, and Visnu. May both Nasatyas, Rudra, heavenly Matrons, pusan, Sarasvati, Bhaga, accept us.\n\np: Indra and Agni, Mitra, Varuna, Aditi, the Waters, Mountains, Maruts, Sky, and Earth and Heaven, Visnu I call, pusan, and Narasamsa, and Bhaga, Samsa, Savitar that the, may help.\n\np: May Visnu also and Vata who injures none, and Soma granter of possessions give us joy; An. May the Rbhus and the Asvins, Tvastar and Vibhvan remember us so that we may have wealth.\n\np: May the band of Maruts dwelling in the sky, the holy, come to us to sit on sacred grass; Narasamsa and Pusan grant us sure defence, Varuna, Mitra, Aryaman guard and shelter us.\n\np: An. May the Mountains famed in noble eulogies, and the fair-gleaming Rivers keep us safe from harm. May Bhaga the Dispenser come with power and grace, and far-pervading Aditi listen to my call.\n\np: May the Deva Spouses aid us of their own freewill, aid us to offspring and the winning of the spoil. Grant us protection, O ye gracious Devas, ye who are on the earth or in the waters' realm.\n\np: May the Dames, wives of Devas, enjoy our presents, Rat, Asvini, Agnayi, and Indrani. May Rodasi and Varunani hear us, and Devas come at the Matrons' season.","people":["Indra","Soma","Agni","Visnu","Mitra","Varuna","Asvins","Nasatyas","Narasamsa","Tvastar","Savitar","Pusan","Sarasvati","Bhaga","Deva","Varunani","Indrani","Agnayi","Vata","Aditi","Rat","Asvini","Rodasi","Vibhvan","Aryaman"],"places":["Earth","Heaven","Sky"],"things":["Leader","Mountains","Rivers","Soma","Waters","Wealth","Joy","Help","Offspring","Grass","Winning","Dispenser","call","spoil"],"groups":["Devas","Maruts","Marut","Dames","Spouses","Rbhus"],"concepts":["Heavenly","Holy","Sacred","Noble"],"hash":"md5-vMkGkz8XmY0bNHa3/SgDBw==","created":"Monday, April 8, 2024 - 10:51:54 PM"},{"id":"b448c502-1e0a-434f-80f3-69d15cfb7400","key":"05047","book":"05","title":"HYMN XLVII, Devas.","link":"https://indra.ai/rigveda/hymns/05047.html","text":"p: URGING to toil and making proclamation, seeking Heaven's Daughter comes the Mighty Mother: She comes, the youthful Hymn, unto the Fathers, inviting to her home and loudly calling.\n\np: Swift in their motion, hasting to their duty, reaching the central point of life immortal, On every side about the earth and heaven go forth the spacious paths without a limit.\n\np: Steer, Sea, Red Bird with strong wings, he hath entered the dwelling-place of the Primeval Father. A gay-hued Stone set in the midst of heaven, he hath gone forth and guards mid-air's two limits.\n\np: Four bear him up and give him rest and quiet, and ten invigorate the Babe for travel. His kine most excellent, of threefold nature, pass swiftly round the boundaries of heaven.\n\np: Wondrous, O people, is the mystic knowledge that while the waters stand the streams are flowing: That, separate from his Mother, Two support him, closely-united, twins, here made apparent.\n\np: For him they lenghten prayers and acts of worship: the Mothers weave garments for him their offspring. Rejoicing, for the Steer's impregning contact, his Spouses move on paths or heaven to meet him.\n\np: Be this our praise, O Varuna and Mitr. May this be health and force to us, O Agni. May we obtain firm ground and room for resting: Glory to Heaven, the lofty habitation!","people":["Agni","Varuna"],"places":["Earth","Heaven","Mid-Air"],"things":["Worship","Waters","Glory","Air","Streams","Home","Offspring","Strong","Mighty","Praise","Hymn","Excellent","People","Wings","Bird","Life"],"groups":["Fathers","Father","Mother","Immortal","Spouses"],"concepts":["Life","Immortal","Swift"],"hash":"md5-ZPFrQsGUhGfHH15bR5w5fg==","created":"Monday, April 8, 2024 - 10:51:54 PM"},{"id":"f22981f4-e32d-4ecf-8d0d-4490ae514258","key":"05048","book":"05","title":"HYMN XLVIII, Devas.","link":"https://indra.ai/rigveda/hymns/05048.html","text":"p: WHA. May we meditate for the beloved Power, mighty in native strength and glorious in itself, Which as a magic energy seeking waters spreads even to theimmeasurable middle region's cloud?\n\np: O'er all the region with their uniform advance these have spread out the lore that giveth heroes strength. Back, with their course reversed, the others pass away: the pious lengthens life with those that are before.\n\np: With pressing-stones and with the bright beams of the day he hurls his broadest bolt against the Guileful One. Even he whose hundred wander in his own abode, driving the days afar and bringing them again.\n\np: I, to enjoy the beauty of his form, behold that rapid rush of his as ’twere an axe's edge, what time he gives the man who calls on him in fight wealth like a dwelling-house filled full with store of food.\n\np: Four-faced and nobly clad, Varuna, urging on the pious to his task, stirs himself with the tongue. Naught by our human nature do we know of him, him from whom Bhaga Savitar bestows the boon.","people":["Varuna","Savitar","Bhaga"],"places":[],"things":["Waters","Glorious","Wealth","Boon","Food","Beauty","Mighty","Heroes","Form","Pressing-Stones","Life"],"groups":["Human","Man"],"concepts":["Life","Strength","Glorious"],"hash":"md5-CCsUYIaJAqjI6tOwYdrAlA==","created":"Monday, April 8, 2024 - 10:51:54 PM"},{"id":"e2169041-1ef5-4fbd-b381-98323b2c4ae0","key":"05049","book":"05","title":"HYMN XLIX, Devas.","link":"https://indra.ai/rigveda/hymns/05049.html","text":"p: THIS day I bring Deva.Savitar to meet you, and Bhaga who allots the wealth of mortals. You, Asvins. Heroes rich in treasure.s, daily seeking your friendship fain would I turn hither.\n\np: Knowing full well the Asura's time of coming, worship Deva.Savitar with hymns and praises. Let him who rightly knoweth speak with homage to him who dealeth out man's noblest treasure..\n\np: Not for reward doth Pusan send his blessings, Bhaga, or Aditi: his garb is splendour. May Indra, Visniu, Varuna, Mitra, Agni produce auspicious days, the Wonder-Workers.\n\np: Sending the shelter which we ask, the foeless Savitar and the Rivers shall approach us. When I,  'the offering's priest, invite them. May we he lords of wealth and rich possessions.\n\np: They who devote such worship to the Vasus, singing their hymns to Varuna and Mitra, vouchsafe them ample room, far off be danger. Through grace of Heaven and Eart. May we be happy.","people":["Indra","Agni","Mitra","Varuna","Asvins","Savitar","Pusan","Bhaga","Deva","Aditi"],"places":["Heaven"],"things":["Worship","Rivers","Offering","Treasure","Wealth","Heroes","Splendour"],"groups":["Asura","Man","Vasus"],"concepts":["Wonder-Workers","Friendship","Blessings","Offering","Auspicious"],"hash":"md5-aNPyaFJ8eDDtH9rcv+dFsw==","created":"Monday, April 8, 2024 - 10:51:54 PM"},{"id":"9e3e829b-486b-4c02-bf5f-48dfb7ed4575","key":"05050","book":"05","title":"HYMN L, Devas.","link":"https://indra.ai/rigveda/hymns/05050.html","text":"p: LET every mortal man elect the friendship of the guiding Deva. Each one solicits him for wealth and seeks renown to prosper him.\n\np: These, leading Deva, are thine, and these here ready to speak after us. As suc. May we attain to wealth and wait with services on thee.\n\np: So further honour as our guests the Hero Devas and then the Dames. May he remove and keep afar our foes and all who block our path.\n\np: Where fire is set, and swiftly runs the victim dwelling in the trough. He wins, with heroes in his home, friendly to man, like constant streams.\n\np: May these thy riches, Leader Deva. that rule the car, be blest to us, Yea, blest to us for wealth and weal. This will we ponder praising strength, this ponder as we praise the Deva.","people":["Deva"],"places":[],"things":["Leader","Wealth","Streams","Home","Car","Praise","Heroes","Hero","Riches"],"groups":["Devas","Dames","Man"],"concepts":["Friendship","Strength"],"hash":"md5-eE2/KF+Xhme8RsLwbsSXPw==","created":"Monday, April 8, 2024 - 10:51:54 PM"},{"id":"795b058a-ccc7-47f5-a257-f7f10b71cbed","key":"05051","book":"05","title":"HYMN LI, Devas.","link":"https://indra.ai/rigveda/hymns/05051.html","text":"p: WITH all assistants, Agni, come hither to drink the Soma-juice; With Devas unto our sacred gifts.\n\np: Come to  'the offering, O ye whose ways are right, whose laws are true, and drink the draught with Agni's tongue.\n\np: O Singer, with the singers, O Gracious, with those who move at dawn, Come to the Soma-draught with Devas.\n\np: To Indra and to Vayu dear, this Soma, by the mortar pressed, is now poured forth to fill the jar.\n\np: Vayu, come hither to the feast, wellpleased unto our sacred gifts: Drink of the Soma juice effused come to the food.\n\np: Ye, indra, Vayu, well deserve to drink the juices pressed by us. Gladly accept them, spotless Pair come to the food.\n\np: For Indra and for Vayu pressed are Soma juices blent with curd, as rivers to the lowland flow: come to the food.\n\np: Associate with all the Devas, come, with the Asvins and with Dawn, Agni, as erst with Atri, so enjoy the juice.\n\np: Associate with Varuna, with Mitra, Soma, Visnu, come, Agni, as ers with Atri, so enjoy the juice.\n\np: Associate with Vasus, with Adityas, indra, Viyu, come, Agni as erst with Atri, so enjoy the juice.\n\np: May Bhaga and the Asvins grant us health and wealth, and Deva Adid and he whom none resist. The Asura Pusan grant us all prosperity, and Heaven and Earth most wise vouchsafe us happiness.\n\np: Let us solicit Vayu for prosperity, and Soma who is Lord of all the world for weal; For weal Narasamsa with all his company. May the Adityas bring us health and happiness.\n\np: May all the Devas. May Agni the beneficent, Deva.of all men, this day be with us for our weal. Help us the Rbhus, the Divine Ones, for our good. May Rudra bless and keep us from calamity.\n\np: Prosper us, Mitra, Varuna. O wealthy Pathya, prosper us. Indra and Agni, prosper us; prosper us thou, O Aditi.\n\np: Like Sun and Moo. May we pursue in full prosperity our path, and meet with one who gives again, -who knows us well and subdues us not.","people":["Indra","Soma","Agni","Vayu","Visnu","Mitra","Varuna","Asvins","Narasamsa","Pusan","Bhaga","Atri","Deva","Dawn","Aditi"],"places":["Earth","Heaven"],"things":["Lord","Rivers","Soma","Singer","Offering","Sun","Wealth","Food","Men","Flow","Juice","Help","Wise","Gifts"],"groups":["Devas","Asura","Vasus","Adityas","Rbhus"],"concepts":["Good","Divine","Sacred","Offering"],"hash":"md5-e9LpEDcQ6fHqzcPybNVBXg==","created":"Monday, April 8, 2024 - 10:51:54 PM"},{"id":"248145fc-90a5-48a1-9341-59a2e7370f4b","key":"05052","book":"05","title":"HYMN LII Maruts.","link":"https://indra.ai/rigveda/hymns/05052.html","text":"p: SING boldly forth, Syavasva, with the Maruts who are loud in song, who, holy, as their wont is, joy in glory that is free from guile.\n\np: For in their boldness they are friends of firm and sure heroic strength. They in their course, bold-spirited, guard all men of their own accord.\n\np: Like steers in rapid motion they advance and overtake the nights; And thus the Maruts’ power in heaven and on the earth we celebrate.\n\np: With boldness to your Maruts let us offer laud and offering: Who all, through ages of mankind, guard mortal man from injury.\n\np: Prais worthy, givers of good gifts. Heroes with full and perfect strength - To Maruts, Holy Ones of heaven, will I extol  'the offering.\n\np: The lofty Heroes cast their spears and weapons bright with gleaming gold. After these Maruts followed close, like laughing lightning from the sky, a splendour of its own accord.\n\np: They who waxed mighty, of the earth, they who are in the wide mid-air, or in the rivers’ compass, or in the abode of ample heaven.\n\np: Praise thou the Maruts’ company, the valorous and truly strong, the Heroes, hasting, by themselves have yoked their deer for victory.\n\np: Fair-gleaming, on Parusni they have clothed themselves in robes of wool, and with their chariot tires they cleave the rock asunder in their might.\n\np: Whether as wanderers from the way or speeders on or to the path, Under these names the spreading band tend well  'the offering for me.\n\np: To this the Heroes well attend, well do their teams attend to this. Visible are their varied forms. Behold, they are Paravatas.\n\np: Hymn-singing, seeking water, they, praising, have danced about the spring. What are they unto me? No thieves, but helpers, splendid to behold.\n\np: Sublime, with lightnings for their spears, Sages and Orderers are they. Rsi, adore that Marut host, and make them happy with thy song.\n\np: Rsi, invite the Marut band with offerings, as a maid her friend. From heaven, too, Bold Ones, in your might haste hither glorified with songs.\n\np: Thinking of these now let him come, as with the escort of the Devas, and with the splendid Princes, famed for rapid courses, to the gifts.\n\np: Princes, who, when I asked their kin, named Prsni as their Mother-cow, and the impetuous Rudra they, the MightyOnes, declared their Sire.\n\np: The mighty ones, the seven times seven, have singly given me hundred gifts. I have obtained on Yamuna famed wealth in kine and wealth in steeds.","people":[],"places":["Earth","Heaven","Mid-Air","Sky"],"things":["Mankind","Holy Ones","Victory","Steeds","Rivers","Water","Glory","Offering","Air","Wealth","Men","Might","Song","Joy","Gold","Strong","Mighty","Praise","Hymn","Heroes","Splendour","Offerings","Friends","Songs","Friend","Cow","Gifts"],"groups":["Devas","Maruts","Marut","Maid","Steers","Mother","MightyOnes","Man"],"concepts":["Good","Heroic","Holy","Strength","Offering","Offerings"],"hash":"md5-IpWBVoVYSNSqc6qPFBWuug==","created":"Monday, April 8, 2024 - 10:51:54 PM"},{"id":"74281ca5-7924-475b-8727-3fd4c309f953","key":"05053","book":"05","title":"HYMN LIII. Maruts.","link":"https://indra.ai/rigveda/hymns/05053.html","text":"p: Who knows the birth of these, or who lived in the Maruts’ favour in the days of old What time their spotted deer were yoked?\n\np: Who, when they stood upon their cars, hath heard them tell the way they went? Who was the bounteous man to whom their kindred rains flowed down with food of offering?\n\np: To me they told it, and they came with winged steeds radiant to the draught, Youths. Heroes free from spot or stain: Behold us here and praise thou us;\n\np: Who shine self-luminous with ornaments and swords, with breastplates, armlets, and with wreaths, Arrayed on chariots and with bows.\n\np: O swift to pour your bounties down, ye Maruts, with delight I look upon your carslike splendours coming through the rain.\n\np: Munificent Heroes, they have cast heaven's treasure. down for the worshipper's behoof: They set the storm-cloud free to stream through both the worlds, and rainfloods flow o’er desert spots.\n\np: The bursting streams m billowy flood have spread abroad, like milch-kine, o’er the firmament. Like swift steeds hasting to their journey's resting-place, to every side run glittering brooks.\n\np: Hither, O Maruts, come from heaven, from mid-air, or from near at hand Tarry not far away from us.\n\np: So let not Rasa, Krumu, or Anitabha, Kubha, or Sindhu hold you back. Let not the watery Sarayti obstruct your way. With us be all the bliss ye give.\n\np: That brilliant gathering of your cars, the company of Maruts, of the Youthful Ones, the rain-showers, speeding on, attend.\n\np: With eulogies and hymn. May we follow your army, troop by troop, and band by band, and company by company.\n\np: To what oblation-giver, sprung of noble ancestry, have sped The Maruts on this course to-day?\n\np: Vouchsafe to us the bounty, that which we implore, through which, for child and progeny, Ye give the seed of corn that wasteth not away, and bliss that reacheth to all life.\n\np: May we in safety pass by those who slander us, leaving behind disgrace and hate. Maruts. May we be there when ye, at dawn, in rest and toil, rain waters down and balm.\n\np: Favoured by Devas shall he the man, O Heroes, Marutr! and possessed of noble sons, whom ye protect. Suc. May we be.\n\np: Praise the Free-givers. At this liberal patron's rite they joy like cattle in the mead. So call thou unto them who come as ancient Friends: hymn those who love thee with a song.","people":["Dawn","Rasa","Sindhu"],"places":["Heaven","Firmament","Mid-Air"],"things":["Journey","Steeds","Waters","Chariots","Offering","Shine","Air","Treasure","Food","Streams","Stream","Flow","Rain","Song","Joy","Praise","Worshipper","Delight","Hymn","Heroes","Friends","Bliss","call","Cars","Cattle","Life"],"groups":["Devas","Maruts","Sons","Child","Progeny","Man"],"concepts":["Birth","Life","Cars","Love","Offering","Giver","Swift","Noble"],"hash":"md5-txnq4QbRpYtsGqfQnShfXA==","created":"Monday, April 8, 2024 - 10:51:54 PM"},{"id":"d5e24244-2705-4a4d-b466-8529c9ccd221","key":"05054","book":"05","title":"HYMN LIV. Maruts.","link":"https://indra.ai/rigveda/hymns/05054.html","text":"p: THIS hymn will I make for the Marut host who bright in native splendour cast the mountains down. Sing the great strength of those illustrious in renown, who stay the heat, who offering on heights of heaven.\n\np: O Maruts, rich in water, strengtheners of life are your strong bands with harnessed steeds, that wander far. Trita roars out at him who aims the lightning-flash. The waters sweeping round are thundering on their way.\n\np: They gleam with lightning. Heroes, Casters of the Stone, wind-rapid Maruts, overthrowers of the bills, Oft through desire to rain coming with storm of hail, roaring in onset, violent and exceeding strong.\n\np: When, mighty Rudras, through the nights and through the days, when through the sky and realms of air, shakers of all, when over the broad fields ye drive along like ships, e’en to strongholds ye come, Maruts, but are not harmed.\n\np: Maruts, this hero strength and majesty of yours hath, like the Sun, extended o’er a lengthened way, when in your course like deer with splendour unsubdued ye bowed the hill that gives imperishable rain.\n\np: Bright shone your host, ye Sages, Maruts, when ye smote the waving tree as when the worm consumeth it. Accordant, as the eye guides him who walks, have ye led our devotion onward by an easy path.\n\np: Never is he, O Maruts, slain or overcome, never doth he decay ne’er is distressed or harmed; His treasure.s, his resources, never waste away, whom. whether he be prince or Rsi, ye direct.\n\np: With harnessed team like heroes overcoming troops, the friendly Maruts, laden with their water-casks, Let the spring flow, and when impetuous' they roar they inundate the earth with floods of pleasant meath.\n\np: Free for the Maruts is the earth with sloping ways, free for the rushing Ones is heaven with steep descents. The paths of air's mid-region are precipitous, precipitous the mountains with their running streams.\n\np: When, as the Sun hath risen up, ye take delight, O bounteous radiant Maruts. Heroes of the sky, Your coursers weary not when speeding ontheir way, and rapidly ye reach the end of this your path.\n\np: Lances are on your shoulders, anklets on your feet, gold chains are on your breasts, gems, Maruts, on your car. Lightnings aglow with flame are flashing in your hands, and visors wroughtof gold are laid upon your heads.\n\np: Maruts, in eager stir ye shake the vault of heaven, splendid beyond conception, for its shining fruit. They gathered when they let their deeds of might flash forth. The Pious Ones send forth a far-resounding shout.\n\np: Sage Maruts. May we be the drivers of the car of riches ful I of life that have been given by you. O Maruts, let that wealth in thousands dwell with us which never vanishes like Tisya from the sky.\n\np: Maruts, ye further wealth with longedfor heroes, further the Rsi skilled in chanted verses. Ye give the Bharata as his strength, a charger, and ye bestow a king who quickly listens.\n\np: Of you, most swift to assist! I solicit wealth wherewith we may spread forth mid men like as the Sun. Accept, O Maruts, graciously this hymn of mine that we may live a hundred winters through its power.","people":["Bharata","Trita"],"places":["Earth","Heaven","Sky"],"things":["Meath","Steeds","Mountains","Waters","Water","Offering","Air","Sun","Treasure","Wealth","Men","Streams","Flow","Might","Rain","Gold","Strong","Mighty","Car","Delight","Hymn","Heroes","Splendour","Hero","King","Sage","Riches","Life"],"groups":["Maruts","Marut","Rudras"],"concepts":["Life","Strength","Offering","Swift"],"hash":"md5-qq84hY9TZxey9meUgpxZUA==","created":"Monday, April 8, 2024 - 10:51:54 PM"},{"id":"bf58dc02-2cae-486a-ab99-6666e1453c7b","key":"05055","book":"05","title":"HYMN LV. Maruts.","link":"https://indra.ai/rigveda/hymns/05055.html","text":"p: WITH gleaming lances, with their breasts adorned with gold, the Maruts, rushing onward, hold high power of life. They hasten with swift steeds easy to be controlled. Their cars moved onward as they went to victory.\n\np: Ye, as ye wist, have gained of your own selves your power: high, O ye MightyOnes, and wide ye shine abroad. They with their strength have even measured out the sky. Their cars moved onward as they went to victory.\n\np: Strong, born together, they together have waxed great: the Heroes more and more have grown to majesty Resplendent as the Sun's beams in their light are they. Their cars moved onward as they went to victory.\n\np: Maruts, your mightiness deserves to be adored, sight to be longed for like the shining of the Sun. So lead us with your aid to immortality. Their cars moved onward as they went to victory.\n\np: O Maruts, from the Ocean ye uplift the rain, and fraught with vaporous moisture pour the torrents down. Never, ye Wonder-Workers, are your Milch-kine dry. Their cars moved onward as they went to victory.\n\np: When to your carpoles ye have yoked your spotted deer to be your steeds, and put your golden mantles on, O Maruts, ye disperse all enemies abroad. Their cars moved onward as they went to victory.\n\np: Neither the mountains nor the rivers keep you back: whither ye have resolved thither ye, Maruts, go. Ye compass round about even the heaven and earth. Their cars moved onward as they went to victory. Whate’er is ancient, Maruts, what of recent time, whate’er is spoken, Vasus, what is chanted forth, they who take cognizance of all of this are ye. Their cars moved onward as they went to victory.\n\np: Be gracious unto us, ye Maruts, subdue us not extend ye unto us shelter of many a sort. Pay due regard unto our friendship and our praise. Their cars moved onward as they went to victory.\n\np: O Maruts, lead us on to higher fortune deliver us, when lauded, from afflictions. Accept, ye Holy Ones, the gifts we bring you. May we be masters of abundant riches.","people":[],"places":["Ocean","Earth","Heaven","Sky"],"things":["Holy Ones","Victory","Masters","Steeds","Born","Mountains","Rivers","Shine","Light","Sun","Rain","Gold","Strong","Praise","Heroes","Riches","Cars","Life","Gifts"],"groups":["Maruts","MightyOnes","Vasus"],"concepts":["Life","Wonder-Workers","Friendship","Immortality","Cars","Holy","Strength","Swift"],"hash":"md5-7WQJc+mFiRLSLdg8pU//Yw==","created":"Monday, April 8, 2024 - 10:51:54 PM"},{"id":"220ca341-7c24-4d5f-bb21-1781f65139ac","key":"05056","book":"05","title":"HYMN LVI. Maruts.","link":"https://indra.ai/rigveda/hymns/05056.html","text":"p: AGNI, that valorous company adorned with ornaments of gold, the people of the Maruts, I call down to-day even from the luminous realm of heaven.\n\np: Even as thou thinkest in thy heart, thither my wishes also tend. Those who have come most near to thine invoking calls, strengthen them fearful to behold.\n\np: Earth, like a bounteous lady, liberal of her gifts, struck down and shaken, yet exultant, comes to us. Impetuous as a bear, O Maruts, is youi rush terrible as a dreadful bull..\n\np: They who with mighty strength o’erthrow like oxen difficult to yoke, Cause e’en the heavenly stone to shake ' yea, shake the rocky mountain as they race along.\n\np: Rise up! even now with lauds I call the very numerous company, Unequalled, of these Maruts, like a herd of kine, grown up together in their strength.\n\np: Bind to your car the bright red mares, yoke the red coursers to your car. Bind to the pole, to draw, the fleet-foot tawny steeds, the best at drawing, to the pole.\n\np: Yea, and this loudly-neighing bright red vigorous horse who hath been sutioned, fair to see, Let him not cause delay, O Maruts, in your course, urge ye him onward in your cars.\n\np: The Maruts’ chariot, ever fain to gather glory, we invoke, Which Rodasi hath mounted, bringing pleasant gifts, with Maruts in her company.\n\np: I call that brilliant band of yours, adorable, rapid on the car Whereon the bounteous Dame, auspicious, nobly born, shows glorious with the Marut host.","people":["Agni","Rodasi"],"places":["Earth","Heaven"],"things":["Steeds","Born","Glory","Glorious","Gold","Mighty","Car","Adorable","People","Horse","call","Cars","Gifts"],"groups":["Maruts","Marut"],"concepts":["Heavenly","Cars","Strength","Auspicious","Glorious"],"hash":"md5-3ETyhDX1wrBTxwrZ+IK3Gw==","created":"Monday, April 8, 2024 - 10:51:54 PM"},{"id":"c59e4e01-0687-409a-9a05-e8c10bcf1f5b","key":"05057","book":"05","title":"HYMN LVII. Maruts.","link":"https://indra.ai/rigveda/hymns/05057.html","text":"p: OF one accord, with Indra, O ye Rudras, come borne on your golden car for our prosperity. An offering from us, this hymn is brought to you, as, unto one who th irsts for water, heavenly springs.\n\np: Armed with your daggers, full of wisdom, armed with spears, armed with your quivers, armed with arrows, with good bows, Good horses and good cars have ye, O Prsni's Sons: ye, Maruts, with good weapons go to victory.\n\np: From hills and heaven ye shake wealth for the worshipper: in terror at your coming low the woods bow down. Ye make the earth to tremble, Sons of Prsni, when for victory ye have yoked, fierce Ones! your spotted deer.\n\np: Bright with the blasts of wind, wrapped in their robes of rain, like twins of noble aspect and of lovely form, the Maruts, spotless, with steeds tawnyhued and red, strong in their mightiness and spreading wide like heaven.\n\np: Rich in adornment, rich in drops, munificent, bright in their aspect, yielding bounties that endure, Noble by birth, adorned with gold upon their breasts, the Singers of the sky have won immortal fame.\n\np: Borne on both shoulders, O ye Maruts, are your spears: within your arms is laid your energy and 3trength. Bold thoughts are in your heads, your weapons in your cars, all glorious majesty is moulded on your forms.\n\np: Vouchsafe to us, O Maruts, splendid bounty in steeds, in cars and heroes. Children of Rudra, give us high distinction. May I enjoy your Deva like help and favour.\n\np: Ho! Maruts. Heroes, skilled in Law, immortal, be gracious unto us, ye rich in treasure.s, Ye hearers of the truth, ye sage and youthful, grown mighty, dwelling on the lofty mountains.","people":["Indra","Deva"],"places":["Earth","Heaven","Sky"],"things":["Victory","Steeds","Mountains","Water","Glorious","Offering","Treasure","Wealth","Rain","Gold","Help","Strong","Mighty","Car","Worshipper","Hymn","Heroes","Form","Drops","Sage","Horses","Cars"],"groups":["Maruts","Rudras","Sons","Immortal"],"concepts":["Good","Birth","Heavenly","Golden Car","Cars","Immortal","Wisdom","Offering","Truth","Glorious","Noble"],"hash":"md5-uVrym0ZbOcoXDQqIFDl8JQ==","created":"Monday, April 8, 2024 - 10:51:54 PM"},{"id":"6b541a2b-e817-4ef4-81ef-15f07e98cd2a","key":"05058","book":"05","title":"HYMN LVIII. Maruts.","link":"https://indra.ai/rigveda/hymns/05058.html","text":"p: Now do I glorify their mighty cohort, the company of these the youthful Maruts, who ride impetuous on with rapid horses, and radiant in themselves, are Lords of Amrta.\n\np: The mighty glittering band, arm-bound with bracelets, givers of bliss, unmeasured in their greatness, with magical powers, bountiful, ever-roaring.these, liberal Heroes, venerate thou singer.\n\np: This da. May all your water-bringers, Maruts, they who impel the falling rain, approach us. This fire, O Maruts, hath been duly kindled; let it find favour with you, youthful Sages.\n\np: Ye raise up for the folk an active ruler whom, Holy Ones! a Master's hand hath fashioned. Ye send the fighter hand to hand, armmighty, and the brave hero, Maruts with good horses.\n\np: They spring forth more and more, strong in their glories, like days, like spokes where none are last in order. Highest and mightiest are the Sons of Prsni. Firm to their own intention cling the Maruts.\n\np: When ye have hastened on with spotted coursers, O Maruts, on your cars with strong-wrought fellies, the waters are disturbed, the woods are shattered. Let Dyaus the Red Steer send his thunder downward.\n\np: Even Earth hath spread herself wide at their coming, and they as husbands have with power impregned her. They to the pole have yoked the winds for coursers: their sweat have they made rain, these Sons of Rudra.\n\np: Ho! Maruts. Heroes, skilled in Law, immortal, be gracious unto us, ye rich in treasure.s, Ye hearers of the truth, ye sage and youthful, grown mighty, dwelling on the lofty mountains.","people":[],"places":["Earth"],"things":["Holy Ones","Master","Mountains","Waters","Water","Singer","Treasure","Rain","Strong","Mighty","Brave","Heroes","Powers","Bliss","Hero","Sage","Horses","Cars","Order","Amrta"],"groups":["Dyaus","Maruts","Sons","Immortal"],"concepts":["Good","Cars","Immortal","Holy","Truth"],"hash":"md5-KNzERvntpHgYMSAyEmitZA==","created":"Monday, April 8, 2024 - 10:51:54 PM"},{"id":"ce871680-65a5-49f5-8a7c-61f7d3c95c50","key":"05059","book":"05","title":"HYMN LIX. Maruts.","link":"https://indra.ai/rigveda/hymns/05059.html","text":"p: YOUR spy hath called to you to give prosperity. I sing to Heaven and Earth and offer offering. They bathe their steeds and hasten through the firmament: they spread abroad their radiance through the sea of cloud.\n\np: Earth shakes and reels in terror at their onward rush, like a full ship which, quivering, lets the water in. Marked on their ways are they, visible from afar: the Heroes press between in mighty armament.\n\np: As the exalted horn of bulls for splendid might, as the Sun's eye set in the firmament's expanselike vigorous horses ye are beauteous to behold, and for your glory show like bridegrooms, O ye Men.\n\np: Who, O ye Maruts. May attain the mighty lore of you the mighty, wh. May reach your manly deeds? Ye, verily, make earth tremble like a ray of light what time ye bring your boons to give prosperity,\n\np: Like steeds of ruddy colour, scions of one race, as foremost champions they have battled in the van. The Heroes have waxed strong like we.1grown manly youths; with floods of rain they make the Sun's eye fade away,\n\np: Having no eldest and no youngest in their band, no middlomost, preeminent they have waxed in might, these Sons of Prsni, sprung of noble ancestry: come hitberward to us, ye bridegrooms of the sky.\n\np: Like birds of air they flew with might in lengthened lines from heaven's high ridges to the borders of the sky. The steeds who carry them, as Devas and mortals know, have caused the waters of the mounuains to desGend.\n\np: May Dyaus, the Infinite, roar for our banquet. May Dawns toil for us, glittering with moisture. Lauded by thee, these Maruts, Sons o Rudra, O Rsi, have sent down the heavenly treasure..","people":[],"places":["Earth","Heaven","Firmament","Sky"],"things":["Steeds","Waters","Water","Glory","Offering","Light","Air","Sun","Treasure","Men","Might","Rain","Strong","Mighty","Banquet","Heroes","Horses"],"groups":["Devas","Dyaus","Maruts","Sons","Dawns"],"concepts":["Heavenly","Offering","Noble"],"hash":"md5-dKvEkwlmfEcjoVssphqH/Q==","created":"Monday, April 8, 2024 - 10:51:54 PM"},{"id":"217f2a70-66cc-47a5-bfb5-89c3a914ea8b","key":"05060","book":"05","title":"HYMN LX. Maruts.","link":"https://indra.ai/rigveda/hymns/05060.html","text":"p: I LAUD with reverence the gracious Agni: her. May he sit and part our meed among us. As with spoil-seeking cars I bring oblation: turned rightward I will swell the Marut's, praise-song.\n\np: The Maruts, yea, the Rudras, who have mounted their famous spotted deer and cars swift-moving. Before you, fierce Ones! woods bow down in terror: Earth, even the mountain, trembles at your coming.\n\np: Though vast and tall, the mountain is affrighted, the height of heaven is shaken at your roaring When, armed with lances, ye are sporting, Maruts, and rush along together like the waters.\n\np: They, like young suitors, sons of wealthy houses, have with their golden natures decked their bodies. Strong on their cars, the lordly Ones, for glory, have set their splendours on their forms forever.\n\np: None being eldest, none among them youngest, as brothers they have grown to happy fortune. May their Sire Rudra, young and deft, and Prsni pouring much milk, bring fair days to the Maruts.\n\np: Whether, O blessed Maruts, ye be dwelling in highest, midmost, or in lowest heaven, thence, O ye Rudras, and thou also, Agni, notice the sacred food we offer.\n\np: O Maruts, Lords of all, when Agni and when ye drive downward from sublimest heaven along the heights, Shakers of all, rejoicing, slayers of the foe, give riches to the Soma-pressing worshipper.\n\np: O Agni, with the Maruts as they gleam and sing, gathered in troop, rejoicing drink the Soma juice; With these the living ones who cleanse and further all, joined with thy banner, O Vaisvanara, from of old.","people":["Soma","Agni","Vaisvanara"],"places":["Earth","Heaven"],"things":["Milk","Reverence","Soma","Waters","Glory","Food","Juice","Song","Strong","Praise","Worshipper","spoil","Riches","Cars"],"groups":["Maruts","Marut","Rudras","Sons"],"concepts":["Cars","Sacred","Swift"],"hash":"md5-y/zWvEwuUTghxGRxS6xiaA==","created":"Monday, April 8, 2024 - 10:51:54 PM"},{"id":"19e6f0f3-4790-4509-b287-99ae893a5179","key":"05061","book":"05","title":"HYMN LXI. Maruts.","link":"https://indra.ai/rigveda/hymns/05061.html","text":"p: O HEROES lordliest of all, who are ye that have singly come Forth from a region most remote?\n\np:  Where are your horses, where the reins? How came ye? how had ye the power? Rein was on nose and seat on back.\n\np: The whip is laid upon the flank. The heroes stretch their thighs apartlike women when the babe is born.\n\np: Go ye, O Heroes, far away, ye bridegrooms with a lovely Spouse That y. May warm you at the fire.\n\np: May she gain cattle for her meed, hundreds of sheep and steeds and kine, who threw embracing arms around the hero whom gyavaiva praised.\n\np: Yea, many a woman is more firm and better than the man who turns Away from Devas, andoffers not.\n\np: She who discerns the weak and worn, the man who thirsts and is in want She sets her mind upon the Devas.\n\np: And yet full many a one, unpraised, mean niggard, is entitled man: Only in weregild is he such.\n\np: And she, the young, the joyous-spirited, divulged the path to Syava, yea, to me. Two red steeds carried me to Purumilha's side, that sage of far-extended fame,\n\np: Him who, like Vaidadasvi, like Taranta, hath bestowed on me A hundred cows in liberal gift.\n\np: They who are borne by rapid steeds, drinking the meath that gives delight, they have attained high glories here.\n\np: They by whose splendour both the worlds are over-spread they shine on cars As the gold gleams above in heaven.\n\np: That Marut band is ever young, borne on bright cars, unblamable, Moving to victory, checked by none.\n\np: Who knoweth, verily, of these where the All-shakers take delight, Born, spotless, after sacred Law?\n\np: Guides are ye, lovers of the song to mortal man through holy hymn, and hearers when he cries for help.\n\np: Do ye, destroyers of the foe, worshipful and exceeding bright, Send down the treasure.s that we crave.\n\np: OUrmya, bear thou far away to Darbhya this my hymn of praise, Songs, Deva, as if chariot-borne.\n\np: From me to Rathaviti say, when he hath pressed the Soma juice, the wish I had departeth not.\n\np: This wealthy Rathaviti dwells among the people rich in kine, Among the mountains, far withdrawn.","people":["Soma","Deva"],"places":["Heaven"],"things":["Meath","Victory","Steeds","Born","Mountains","Soma","Shine","Treasure","Juice","Song","Gold","Help","Praise","Delight","Hymn","Heroes","Gift","Splendour","People","Songs","Hero","Sage","Horses","Spouse","Cars","Cattle"],"groups":["Devas","Marut","Man","Woman"],"concepts":["Cars","Holy","Sacred"],"hash":"md5-gvlaZMAwpGGwPibhaS+J1A==","created":"Monday, April 8, 2024 - 10:51:54 PM"},{"id":"b4030ad9-70f8-46a8-9963-e45145ff3dfd","key":"05062","book":"05","title":"HYMN LXII. Mitra and Varuna","link":"https://indra.ai/rigveda/hymns/05062.html","text":"p: BY your high Law firm order is established there where they loose for travel Surya's horses. Ten hundred stood together: there I looked on this the most marvellous Deities' one chief glory.\n\np: This, Mitra and Varuna, is your special greatness: floods that stood there they with the days attracted. Ye cause to flow all voices of the cowpen: your single chariotfelly hath rolled hither.\n\np: O Mitra and Varuna, ye by your greatness, both Kings, have firmly stablished earth and heaven, Ye caused the cows to stream, the plants to flourish, and, scattering swift drops, sent down the rain-flood.\n\np: Let your well-harnessed horses bear you hither: hitherward let them come with reins drawn tightly. A covering cloud of sacred oil attends you, and your streams flow to us from days aforetime.\n\np: To make the lustre wider and more famous, guarding the sacred grass with veneration, Ye, Mitra and Varuna, firm, strong, awe-inspiring, are seated on a throne amid oblations.\n\np: With hands that shed no blood, guarding the pious, whom, Varuni3, ye save amid oblations. Ye Twain, together, Kings of willing spirit, uphold dominion based on thousand pillars.\n\np: Adorned with gold, its columns are of iron. in heaven it glitters like a whip for horses; Or stablished on a field deep-spoiled and fruitful. May we share the meath that loads your car-seat.\n\np: Ye mount your car gold-hued at break of morning, and iron-pillared when the Sun is setting, and from that place, O Varuna and Mitra, behold infinity and limit~tion.\n\np: Bountiful guardians of the world! the shelter that is impenetrable, strongest, flawless, Aid us with that, O Varuna and Mitra, and when we long to wi. May we be victors.","people":["Mitra","Varuna","Surya"],"places":["Earth","Heaven"],"things":["Meath","Glory","Sun","Streams","Stream","Flow","Rain","Gold","Strong","Grass","Car","Chief","Drops","Horses","Order","Morning","Spirit"],"groups":["Deities","Kings"],"concepts":["Special","Sacred","Swift"],"hash":"md5-cOgKO9uW2pfNkI472mIKww==","created":"Monday, April 8, 2024 - 10:51:54 PM"},{"id":"22795d35-8af9-43f0-bc77-dc2eb4cba919","key":"05063","book":"05","title":"HYMN LXIII. Mitra and Varuna.","link":"https://indra.ai/rigveda/hymns/05063.html","text":"p: GUARDIANS of Order, ye whose Laws are ever true, in the sublimest heaven your chariot ye ascend. O Mitra and Varuna whomsoe’er ye: favour, here, to him the rain with sweetness streameth down from heaven.\n\np: This world's imperial Kings, O Mitra and Varuna, ye rule in holy synod, looking on the light. We meditate for rain, your boon, and immortality. Through heaven and over earth the thunderers take their way.\n\np: Imperial Kings, strong. Heroes, Lords of earth and heaven, Mitra and Varuna, ye ever active Ones, Ye wait on thunder with the many-tinted clouds, and by the Asura's magic power cause Heaven to rain.\n\np: Your magic, Mitra and Varuna, resteth in the heaven. The Sun, the wondrous weapon, cometh forth as light. Ye hide him in the sky with cloud and flood of rain, and water-drops, parjanya! full of sweetness flow.\n\np: The Maruts yoke their easy car for victory, O Mitra and Varuna, as a hero in the wars. The thunderers roam through regions varied in their hues. Imperial Kings, bedew us with the milk of heaven.\n\np: Refreshing is your voice, O Mitra and Varuna: Parjanya sendeth out a wondrous mighty voice. With magic power the Maruts clothe them with the clouds. Ye Two cause Heaven to rain, the red, the spotless One.\n\np: Wise, with your Law and through the Asura's magic power ye guard the ordinances, Mitra and Varuna. Ye by eternal Order govern all the world. Ye set the Sun in heaven as a refulgent car.","people":["Mitra","Varuna","Parjanya"],"places":["Earth","Heaven","Sky"],"things":["Victory","Milk","Water","Light","Sun","Boon","Flow","Rain","Wise","Strong","Mighty","Car","Voice","Heroes","Ascend","Drops","Hero","Order"],"groups":["Asura","Maruts","Kings"],"concepts":["Immortality","Holy"],"hash":"md5-YQZUCi7lkJ2ycVW6Zj1riw==","created":"Monday, April 8, 2024 - 10:51:55 PM"},{"id":"56484270-7b70-4c3c-98ed-617784934a06","key":"05064","book":"05","title":"HYMN LX1V. Mitra and Varuna","link":"https://indra.ai/rigveda/hymns/05064.html","text":"p: You, foeman-subduing Varuna and Mitra, we invoke with song, who, as with penfold of your arms, encompass round the realm of light.\n\np: Stretch out your arms with favouring love unto this man who singeth hymns, for in all places is sung forth your evergracious friendliness.\n\np: That . May gain a refuge nowe may my steps be on Mitra's path. Men go protected in the charge of this dear Friend who harms us not.\n\np: Mitra and Varuna, from yo. May I, by song, win noblest meed. That shall stir envy in the homes of wealthy chiefs and those who praise.\n\np: With your fair splendours, Varuna and Mitra, to our gathering come, that in their homes the wealthy chiefs and they who are your friend. May thrive.\n\np: With those, moreover, among whom ye hold your high supremacy, vouchsafe us room that we may win strength for prosperity and wealth.\n\np: When morning flushes, Holy Ones! in the Devas’ realm where white Cows shine, Supporting Arcananas, speed, ye Heroes, with your active feet hither to my pressed Soma juice.","people":["Soma","Mitra","Varuna"],"places":[],"things":["Holy Ones","Soma","Shine","Light","Wealth","Men","Juice","Song","Praise","Heroes","Friend","Morning"],"groups":["Devas","Man"],"concepts":["Love","Holy","Strength"],"hash":"md5-n1YIdTcueLkUpywl9XLooA==","created":"Monday, April 8, 2024 - 10:51:55 PM"},{"id":"032287d4-e0b8-4d93-acfb-c783a145323c","key":"05065","book":"05","title":"HYMN LXV Mitra and Varuna.","link":"https://indra.ai/rigveda/hymns/05065.html","text":"p: FULL wise is he who hath discerned: let him speak to us of the Devas. The man whose praise-songs Varuna the beautiful, or Mitra, loves.\n\np: For they are Kings of noblest might, of glorious fame most widely spread; Lords of the brave, who strengthen Law, the Holy Ones with every race.\n\np: Approaching you with prayer for aid, together I address you first We who have good steeds call on you, most Sage, to give us strength besides.\n\np: E’en out of misery Mitra gives a way to dwelling at our case, for he who worships hath the grace of Mitra, fighter in the van. '\n\np: In Mitra's shelter that extends to utmost distanc. May we dwell, Unmenaced, guarded by the care, ever as sons of Varuna.\n\np: Ye, Mitra, urge this people on, and to on end direct their ways. Neglect not ye the wealthy chiefs, neglect not us the Rsis: be our guardians when ye quaff the milk.","people":["Mitra","Varuna"],"places":[],"things":["Holy Ones","Milk","Steeds","Glorious","Might","Wise","Praise","Brave","People","Songs","Sage","call"],"groups":["Devas","Sons","Kings","Rsis","Man"],"concepts":["Good","Beautiful","Holy","Strength","Glorious"],"hash":"md5-/nzYUUzbGLnvIXVDAVhqbw==","created":"Monday, April 8, 2024 - 10:51:55 PM"},{"id":"0d8749f1-3e78-4179-81ec-56ec33d828ce","key":"05066","book":"05","title":"HYMN LXVI. Mitra and Varuna.","link":"https://indra.ai/rigveda/hymns/05066.html","text":"p: O SAPIENT man, call the Two Devas, the very wise, who subdue the foe. For Varuna, whose form is Law, place offerings for his great delight.\n\np: For they have won unbroken sway in full perfection, power divine. And, like high laws, the world of man hath been made beautiful as light.\n\np: Therefore we praise you that your car. May travel far in front of ours- You who accept the eulogy of Ratahavya with his hymns.\n\np: And ye show wMom, Wondrous Devas with fulness of intellIgence. By men's discernment are Ve marked, O ye whose might is purified.\n\np: This is the Law sublime, O Earth: to aid the Rsis’ toil for fame The Two, wide-spreading, are prepared. They come with ample overflow.\n\np: Mitra, ye Devas with wandering eyes, would that the worshippers and we Might strive to reach the realm ye rule, most spacious and protected well,","people":["Mitra","Varuna"],"places":["Earth"],"things":["Light","Men","Might","Wise","Car","Praise","Delight","Form","Offerings","call"],"groups":["Devas","Worshippers","Rsis","Man"],"concepts":["Divine","Beautiful","Offerings","Intelligence"],"hash":"md5-Stiev0d9y4hfEbgagqu5WQ==","created":"Monday, April 8, 2024 - 10:51:55 PM"},{"id":"9e22bccc-6045-443b-bce2-836a18024d73","key":"05067","book":"05","title":"HYMN LXVII. Mitra and Varuna.","link":"https://indra.ai/rigveda/hymns/05067.html","text":"p: YE Devas, Adityas, Varuna, Aryaman, Mitra, verily Have here obtained supremest sway, high, holy, set apart for you.\n\np: When, Varuna and Mitra, ye sit in your golden dwelling-place, Ye Twain, supporters of mankind, foeslayers, give felicity.\n\np: All these, possessors of all wealth, Varuna, Mitra, Aryaman, Follow their ways, as if with feet, and guard from injury mortal man.\n\np: For they are true, they cleave to Law, held holy amon every race, Good leaders, bounteous in their gifts, deliverers even from distress.\n\np: Which of your persons, Varuna or Mitra, merits not our praise? Therefore our thought is turned to you, the Atris' thought is turned to you.","people":["Mitra","Varuna","Aryaman"],"places":[],"things":["Mankind","Wealth","Praise","Gifts"],"groups":["Devas","Atris","Man","Adityas"],"concepts":["Good","Holy"],"hash":"md5-2owcLde9GH9jUYIH9IZpow==","created":"Monday, April 8, 2024 - 10:51:55 PM"},{"id":"486a2001-d23e-441b-8d18-29e14b911525","key":"05068","book":"05","title":"HYMN LXVIII. Mitra and Varuna.","link":"https://indra.ai/rigveda/hymns/05068.html","text":"p: SING forth unto your Varuna and Mitra with a song inspired. They, Mighty Lords, are lofty Law\n\np: Full springs of fatness, Sovran Kings, Mitra. and Varuna, the Twain, Devas glorified among the Devas.\n\np: So help ye us to riches, great terrestrial and celestial wealth: Vast is your sway among the Devas.\n\np: Carefully tending Law with Law they have attained their vigorous might. The two Devas wax devoid of guile.\n\np: With rainy skies and streaming floods, Lords of the strength that bringeth gifts, a lofty seat have they attained.","people":["Mitra","Varuna"],"places":[],"things":["Wealth","Might","Song","Help","Mighty","Riches","Gifts"],"groups":["Devas","Kings"],"concepts":["Celestial","Strength"],"hash":"md5-orLeStV0mx4e+RSZXf8DlA==","created":"Monday, April 8, 2024 - 10:51:55 PM"},{"id":"01106f32-fc07-4783-87e8-741c72ece417","key":"05069","book":"05","title":"HYMN LXIX. Mitra and Varuna.","link":"https://indra.ai/rigveda/hymns/05069.html","text":"p: THREE spheres of light, O Varuna, three heavens, three firmaments ye comprehend, O Mitra: Waxed strong, ye keep the splendour of dominion, guarding the Ordinance that lasts forever.\n\np: Ye, Varuna, have kine who yield refreshment; Mitra, your floods pour water full of sweetness. There stand the Three Steers, splendid in their brightness, who fill the three world-bowls with genial moisture.\n\np: I call at dawn on Aditi the Deva, I call at noon and when the Sun is setting. I pray, O Mitra and Varuna, for safety, for wealth and progeny, in rest and trouble.\n\np: Ye who uphold the region, sphere of brightness, ye who support earth's realm Divine Adityas, the Immortal Devas, O Varuna and Mitra, never impair your everlasting statutes.","people":["Mitra","Varuna","Deva","Dawn","Aditi"],"places":["Earth"],"things":["Water","Light","Sun","Wealth","Strong","Splendour","call"],"groups":["Devas","Steers","Immortal","Progeny","Adityas"],"concepts":["Divine","Immortal"],"hash":"md5-zC1QHKNR4DZ7F5OXSTbWhw==","created":"Monday, April 8, 2024 - 10:51:55 PM"},{"id":"164c5319-344d-47c4-8e31-8d0306cc163d","key":"05070","book":"05","title":"HYMN LXX. Mitra and Varuna.","link":"https://indra.ai/rigveda/hymns/05070.html","text":"p: EVEN far and wide, O Varuna and Mitra, doth your grace extend. May I obtain your kind good-will.\n\np: From you, benignant Devas. May we gain fully food for sustenance. Such, O ye Rudras, my we be.\n\np: Guard us, O Rudras. with your guar4 save us, ye skilled to save, my we Subdue the Dasyus, we ourselves,\n\np: Or ne’e. May we, O Wondrous Strong, enjoy another's solemn feast, Ourselves, our sons, or progeny.","people":["Mitra","Varuna"],"places":[],"things":["Food","Strong"],"groups":["Devas","Dasyus","Rudras","Sons","Progeny"],"concepts":["Good"],"hash":"md5-g7YLlTEXsBlfI28x1VaZ0A==","created":"Monday, April 8, 2024 - 10:51:55 PM"},{"id":"63669b4f-f303-40ff-b067-8adf15185d5a","key":"05071","book":"05","title":"HYMN LXXI. Mitra and Varuna.","link":"https://indra.ai/rigveda/hymns/05071.html","text":"p: O Varuna and Mitra, ye who subdue the foemen, come with might To this our goodly offerings.\n\np: For, Varuna and Mitra, ye Sages are Rulers over all. Fill full our songs, for this ye can.\n\np: Come to the juice that we have pressed. Varuna, Mitra, come to drink This Soma of the worshipper.","people":["Soma","Mitra","Varuna"],"places":[],"things":["Soma","Might","Juice","Worshipper","Offerings","Songs"],"groups":[],"concepts":["Offerings"],"hash":"md5-QOilpTIf0HyygxKp1ktC2Q==","created":"Monday, April 8, 2024 - 10:51:55 PM"},{"id":"2a23dd4e-f43a-436a-9765-44935534c2dc","key":"05072","book":"05","title":"HYMN LXXII. Mitra and Varuna.","link":"https://indra.ai/rigveda/hymns/05072.html","text":"p: To Varuna and Mitra we offer with songs, as Atri did. Sit on the sacred grass to drink the Soma juice.\n\np: By Ordinance and Law ye dwell in peace secure, bestirring men. Sit on the sacred grass to drink the Soma juice.\n\np: May Varuna and Mitra, for our help, accept  'the offering. Sit on the sacred grass to drink the Soma juice.","people":["Soma","Mitra","Varuna","Atri"],"places":[],"things":["Soma","Offering","Men","Juice","Help","Grass","Songs"],"groups":[],"concepts":["Sacred","Offering"],"hash":"md5-d4CJIk4wwMlpt/wgY4vEpw==","created":"Monday, April 8, 2024 - 10:51:55 PM"},{"id":"fa9d750a-7c9a-49a2-a7cc-de6b0b8e5540","key":"05073","book":"05","title":"HYMN LXXIII. Asvins.","link":"https://indra.ai/rigveda/hymns/05073.html","text":"p: WHETHER, O Asvins, ye this day be far remote or near at hand, in many spots or in mid-air, come hither, Lords of ample wealth.\n\np: These here, who show o’er widest space, bringing full many a wondrous act, Resistless, lovingly I seek, I call the Mightiest to enjoy.\n\np: Another beauteous wheel have ye fixed there to decorate your car. With others through the realms ye roam in might unto the neighbouring tribes.\n\np: That deed of yours that is extolled, Visvas! hath all been done with this. Born otherwise, and spotless, ye have entered kinship's bonds with us.\n\np: When Surya mounted on your car that rolls forever rapidly, Birds of red hue were round about and burning splendours compassed you.\n\np: Atri bethinks himself of you, O Heroes, with a friendly mind, what time, Nasatyas, with his mouth he stirs the spotless flame for you.\n\np: Strong is your swiftly moving steed, famed his exertion in the course When by your great deeds, Asvins, Chiefs, Atri is brought to us again.\n\np: Lovers of sweetness, Rudras, she who streams with sweetness waits on you. When ye have travelled through the seas men bring you gifts of well-dressed food.\n\np: Asvins, with truth they call you Twain bestowers of felicity; At offering most prompt to hear, most gracious ye at offering.\n\np: Most pleasing to the Asvins be these prayers which magnify their might, Which we have fashioned, even as cars high reverence have we spoken forth.","people":["Asvins","Nasatyas","Atri","Surya"],"places":["Mid-Air"],"things":["Born","Reverence","Offering","Air","Wealth","Food","Men","Streams","Might","Strong","Car","Heroes","call","Cars","Gifts","Wheel"],"groups":["Rudras"],"concepts":["Cars","Offering","Truth"],"hash":"md5-MncBpBKfo3lwNrpAEbOR9A==","created":"Monday, April 8, 2024 - 10:51:55 PM"},{"id":"1386579f-1af0-4852-a0e2-c06af4f98919","key":"05074","book":"05","title":"HYMN LXXIV. Asvins.","link":"https://indra.ai/rigveda/hymns/05074.html","text":"p: WHERE in the heavens are ye to-day, Devas, Asvins, rich in constancy? Hear this, ye excellent as Steers: Atri inviteth you to come.\n\np: Where are they now? Where are the Twain, the famed Nasatyas, Devas in heaven? Who is the man ye strive to reach? Who of your suppliants is with you?\n\np: Whom do ye visit, whom approach? to whom direct your harnessed car? With whose devotions are ye pleased? We long for you to further us.\n\np: Ye, Strengtheners, for Paura stir the filler swimming in the flood, Advancing to be captured like a lion to the ambuscade.\n\np: Ye from cyavana worn with age removed his skin as ’twere a robe. So, when ye made him young again, he stirred the longing of a dame.\n\np: Here is the man who lauds you both: to see your glory are we here. Now bear me, come with saving help, ye who are rich in store of wealth.\n\np: Who among many mortal men this day hath won you to himself? What bard, accepters of the bard? Who, rich in wealth! with offering?\n\np: O Asvins. May your car approach, most excellent of cars for speed. Through many region. May our praise pass onward among mortal men.\n\np: May our laudation of you Twain, lovers of meath! be sweet to you. Fly hitherward, ye wise of heart, like falcons with your winged steeds.\n\np: O Asvins, when at any time ye listen to this call of mine, for you is dainty food prepared: they mix refreshing food for you.","people":["Asvins","Nasatyas","Atri"],"places":["Heaven"],"things":["Meath","Steeds","Glory","Offering","Wealth","Food","Men","Help","Wise","Car","Praise","Excellent","call","Cars"],"groups":["Devas","Steers","Man"],"concepts":["Cars","Offering","Pleased"],"hash":"md5-qMSH/wwdNa+pcN72y9rsdQ==","created":"Monday, April 8, 2024 - 10:51:55 PM"},{"id":"cdb4b081-3d6f-4021-bc71-c1bea02f725b","key":"05075","book":"05","title":"HYMN LXXV. Asvins.","link":"https://indra.ai/rigveda/hymns/05075.html","text":"p: To meet your treasure.-bringing car, the mighty car most dear to us, Asvins, the Rsi is prepared, your raiser, with his song of praise. Lovers of sweetness, hear my call.\n\np: Pass, O ye Asvins, pass away beyond all tribes of selfish men, Wonderful, with your golden paths, most gracious, bringers of the flood. Lovers of sweetness, hear my call.\n\np: Come to us, O ye Asvin Pair, bringing your precious treasure.s, come Ye Rudras, on your paths of gold, rejoicing, rich in store of wealth. Lovers of sweetness, hear my call.\n\np: O strong and Good, the voice of him who lauds you well cleaves to your car. And that great beast, your chariot-steed, fair, wonderful, makes dainty food. Lovers of sweetness, hear my call.\n\np: Watchful in spirit, born on cars, impetuous, listing to his cry, Asvins, with winged steeds ye speed down to cyavana void of guile. Lovers of sweetness, hear my call.\n\np: Hither, O Heroes, let your steeds, of dappled hue, yoked at the thought, Your flying steeds, O Asvins, bring you hitherward, with bliss, to drink. Lovers of sweetness, hear my call.\n\np: O Asvins, hither come to us; Nasatyas, be not disinclined. Through longing for the pious turn out of the way to reach our home. Lovers of sweetness, bear my call.\n\np: Ye Lords of Splendour, free from guile, come, stand at this  'our offering. Beside the singer, Asvins, who longs for your grace and lauds you both. Lovers of sweetness, hear my call.\n\np: Dawn with her white herd hath appeared, and in due time hath fire been placed. Harnessed is your immortal car, O WonderWorkers, strong and kind. Lovers of sweetness, bear my call.","people":["Asvins","Nasatyas","Dawn"],"places":[],"things":["Steeds","Born","Singer","Offering","Treasure","Wealth","Food","Men","Song","Gold","Home","Strong","Mighty","Car","Praise","Voice","Heroes","Splendour","Bliss","call","Cars","Spirit"],"groups":["Rudras","Immortal"],"concepts":["Good","Cars","Immortal","Offering"],"hash":"md5-CyzOG6+2jXgQVid1KERLkQ==","created":"Monday, April 8, 2024 - 10:51:55 PM"},{"id":"d5ab92d0-7e33-48c0-837e-f0f4d49f88e3","key":"05076","book":"05","title":"HYMN LXXVI. Asvins","link":"https://indra.ai/rigveda/hymns/05076.html","text":"p: AGNI, the bright face of the Dawns, is shining; the singers' pious voices have ascended. Borne on your chariot, Asvins, turn you hither and come unto our full and rich libation.\n\np: Most frequent guests, they scorn not what is ready: even now the lauded Asvins are beside us. With promptest aid they come at morn and evening, the worshipper's most blessed guards from trouble.\n\np: Yea, come at milking-time, at early morning, at noon of day and when the Sun is setting, by day, by night, with favour most auspicious. Not only now the draught hath drawn the Asvins.\n\np: For this place, Asvins, was of old your dwelling, these were your houses, this your habitation. Come to us from high heaven and from the mountain. Come from the waters bringing food and vigour.\n\np: May we obtain the Asvins' newest favour, and gain their health-bestowing happy guidance. Bring riches hither unto us, and heroes, and all felicity and joy, Immortals!","people":["Agni","Asvins"],"places":["Heaven"],"things":["Waters","Sun","Food","Joy","Worshipper","Heroes","Riches","Morning"],"groups":["Dawns"],"concepts":["Auspicious"],"hash":"md5-MR+kdat/yjsI28Si0qm5Cg==","created":"Monday, April 8, 2024 - 10:51:55 PM"},{"id":"aad069ed-3a73-4813-af3e-63fe57c9debf","key":"05077","book":"05","title":"HYMN LXXVII. Asvins.","link":"https://indra.ai/rigveda/hymns/05077.html","text":"p: FIRST worship those who come at early morning: let the Twain drink before the giftless niggard. The Asvins claim  'the offering at daybreak: the sages yielding the first share extol them.\n\np: Worship at dawn and instigate the Asvins: nor is the worshipper at eve rejected. Besides ourselves another craves and worships: each first in worship is most highly favoured.\n\np: Covered with gold, meath-tinted, dropping fatness, your chariot with its freight of food comes hither, Swift as thought, Asvins, rapid as the tempest, wherewith ye travel over all obstructions.\n\np: He who hath served most often the Nasatyas, and gives the sweetest food at distribution, Furthers with his own holy works his offspring, and ever passes those whose flames ascend not.\n\np: May we obtain the Asvins' newest favour, and gain their health-bestowing happy guidance. Bring riches hither unto us, and heroes, and all felicity and joy, Immortals!","people":["Asvins","Nasatyas","Dawn"],"places":[],"things":["Worship","Meath","Offering","Food","Joy","Gold","Offspring","Worshipper","Heroes","Ascend","Riches","Morning"],"groups":[],"concepts":["Holy","Offering","Swift"],"hash":"md5-YgL3Yf/nDcqC9fLfvpwZyA==","created":"Monday, April 8, 2024 - 10:51:55 PM"},{"id":"a67c318d-8a5f-4f3f-9897-ac72302d4d65","key":"05078","book":"05","title":"HYMN LXXVIII. Asvins.","link":"https://indra.ai/rigveda/hymns/05078.html","text":"p: YE Asvins, hither come to us: Nasatyas, be not disinclined. Fly hither like two swans unto the juice we shed.\n\np: O Asvins, like a pair of deer, like two wild cattle to the mead: Fly hither like two swans unto the juice we shed.\n\np: O Asvins rich in gifts, accept  'our offering to prosper it: Fly hither like two swans unto the juice we shed.\n\np: As Atri when descending to the cavern called on you loudly like a wailing woman. Ye came to him, O Asvins, with the freshest and most auspicious fleetness of a falcon.\n\np: Tree, part asunder like the side of her who bringeth forth a child. Ye Asvins, listen to my call: loose Saptavadhri from his bonds.\n\np: For Saptavadhri, for the seer affrighted when he wept and wailed, Ye, Asvins, with your magic powers rent up the tree and shattered it.\n\np: Like as the wind on every side ruffles a pool of lotuses, So stir in thee the babe unborn, s. May the ten-month babe descend.\n\np: Like as the wind, like as the wood, like as the sea is set astir, So also, ten-month babe, descend together with the after-birth.\n\np: The child who hath for ten months' time been lying in his mother's side. May he come forth alive, unharmed, yea, living from the living dame.","people":["Asvins","Nasatyas","Atri"],"places":[],"things":["Offering","Juice","Powers","Swans","call","Cattle","Gifts"],"groups":["Mother","Child","Woman"],"concepts":["Birth","Offering","Auspicious"],"hash":"md5-VDKr3pA/sB9wktC07zJJmg==","created":"Monday, April 8, 2024 - 10:51:55 PM"},{"id":"cc74e560-6ad1-4764-8302-c75610238fc6","key":"05079","book":"05","title":"HYMN LXXIX. Dawn.","link":"https://indra.ai/rigveda/hymns/05079.html","text":"p: O HEAVENLY Dawn, awaken us to ample opulence to-day Even as thou hast wakened us with Satyasravas, Vayya's son, high-born! delightful with thy steeds!\n\np: Daughter of Heaven, thou dawnedst on Sunitha Sucadratha's son, So dawn thou on one mightier still, on Satyasravas, Vayya's son, high-born! delightful with thy steeds!\n\np: So, bringing treasure., dawn to-day on us thou Daughter of the Sky, as thou, O mightier yet. didst shine for Satyatravas, Vayya's son, high-born! delightful with thy steeds!\n\np: Here round about thee are the monks who laud thee, Bright One, with their hymns, and men with gifts, O Bounteous Dame, splendid with wealth and offering much, high-born! delightful with thy steeds!\n\np: Whatever these thy bands perform to please thee or to win them wealth, E’en fain they gird us round and give rich gifts which ne’er are reft away, high-born! delightful with thy steeds!\n\np: Give to these wealthy patrons fame, O affluent Dawn, with hero sons, to these our princes who have brought rich gifts ne’er to be reft away, highborn! delightful with thy steeds!\n\np: Bring lofty and resplendent fame, O thou munificent Dawn, to these Our wealthy patrons who bestow rich gifts on us of steeds and kine, high-born! delightful with thy steeds!\n\np: Bring us, O Deva of the sky, subsistence in our herds of kine, together with the sunbeams, with the shine of pure refulgent flames, highborn! delightful with thy steeds!\n\np: O Daughter of the Sky, shine forth; delay not to perform thy task. Let not the Sun with fervent heat consume thee like a robber foe, high-born! delightful with the steeds!\n\np: So much, and more exceedingly, O Dawn, it suits thee to bestow, Thou Radiant One who ceasest not to shine for those who sing thy praise, highborn! delightful with thy steeds!","people":["Deva","Dawn","Vayya"],"places":["Heaven","Sky"],"things":["Steeds","Born","Offering","Shine","Sun","Treasure","Wealth","Men","Praise","Hero","Gifts"],"groups":["Sons","Son","Monks"],"concepts":["Heavenly","Offering"],"hash":"md5-dB7erd9ZWAuE+Hmd+POL1A==","created":"Monday, April 8, 2024 - 10:51:55 PM"},{"id":"542e7187-337e-4894-93ff-345e9141cf28","key":"05080","book":"05","title":"HYMN LXXX. Dawn.","link":"https://indra.ai/rigveda/hymns/05080.html","text":"p: THE singers welcome with their hymns and praises the Deva Dawn who bringeth in the sunlight, Sublime, by Law true to eternal Order, bright on her path, red-tinted, far-refulgent.\n\np: She comes in front, fair, rousing up the people, making the pathways easy to be travelled. High, on her lofty chariot, all-impelling, Dawn gives her splendour at the days' beginning.\n\np: She, harnessing her car with purple oxen. injuring none, hath brought perpetual riches. Opening paths to happiness, the Deva shines, praised by all, giver of every blessing.\n\np: With changing tints she gleams in double splendour while from the eas ward she displays her body. She travels perfectly the path of Order, nor fails to reach, as one who knows, the quarters.\n\np: As conscious that her limbs are bright with bathing, she stands, as ’twere, erect that we may see her. Driving away malignity and darkness, Dawn, Child of Heaven, hath come to us with lustre.\n\np: The Daughter of the Sky, like some chaste woman, bends, opposite to men, her forehead downward. The Maid, disclosing boons to him who worships, hath brought again the daylight as aforetime.","people":["Deva","Dawn"],"places":["Heaven","Sky"],"things":["Men","Car","Blessing","Splendour","People","Riches","Order"],"groups":["Maid","Child","Woman"],"concepts":["Giver"],"hash":"md5-bJKGoffThzkrwPUvsgIeWg==","created":"Monday, April 8, 2024 - 10:51:55 PM"},{"id":"a552fb7f-04f9-4b34-b75d-171c63473828","key":"05081","book":"05","title":"HYMN LXXXI. Savitar.","link":"https://indra.ai/rigveda/hymns/05081.html","text":"p: THE monks of him the lofty Monk well-skilled in hymns harness their spirit, yea, harness their holy thoughts. He only knowing works assigns their priestly tasks. Yea, lofty is the praise of Savitar the Deva.\n\np: The Sapient One arrays himself in every form: for quadruped and biped he hath brought forth good. Excellent Savitar hath looked on heaven's high vault, and shineth after the outgoing of the Dawn.\n\np: Even he, the Deva whose going-forth and majesty the other Deities have followed with their might. He who hath measured the terrestrial regions out by his great power, he is the Courser Savitar.\n\np: To the three spheres of light thou goest, Savitar, and with the rays of Sidrya thou combinest thee. Around, on both sides thou encompassest the night: yea O Deva, art Mitra through thy righteous laws.\n\np: Over all generation thou art Lord alone: Pusan art thou, O Deva, in all thy goings-forth. Yea, thou hast domination over all this world. Syavasva hath brought praise to thee, O Savitar,","people":["Mitra","Savitar","Pusan","Deva","Dawn"],"places":["Heaven"],"things":["Lord","Light","Might","Praise","Form","Excellent","Spirit"],"groups":["Deities","Monks"],"concepts":["Good","Holy"],"hash":"md5-K5XiVg2iNAlOedYGrDlfdQ==","created":"Monday, April 8, 2024 - 10:51:55 PM"},{"id":"8a281c67-0cf1-4491-ba9a-49ea9b8ddf61","key":"05082","book":"05","title":"HYMN LXXXII. Savitar.","link":"https://indra.ai/rigveda/hymns/05082.html","text":"p: WE crave of Savitar the Deva.this treasure. much to be enjoyed. The best, all-yielding, conquering gift of Bhaga we would gladly win.\n\np: Savitar's own supremacy, most glorious and beloved of all, No one diminisheth in aught.\n\np: For Savitar who is Bhaga shall send riches to his worshipper. That wondrous portion we implore.\n\np: Send us this day, Deva.Savitar, prosperity with progeny. Drive thou the evil dream away.\n\np: Savitar, Deva, send far away all sorrows and calamities, and send us only what is good.\n\np: Sinless in sight of Aditi through the Deva.Savitar's influence, may we obtain all lovely things.\n\np: We with our hymns this day elect the general Deva, Lord of the good, Savitar whose decrees are true.\n\np: He who forever vigilant precedes these Twain, the Day and Night, is Savitar the thoughtful Deva.\n\np: He who gives glory unto all these living creatures with the song, and brings them forth, is Savitar.","people":["Savitar","Bhaga","Deva","Aditi"],"places":[],"things":["Lord","Glory","Glorious","Treasure","Song","Worshipper","Gift","Riches"],"groups":["Progeny"],"concepts":["Good","Evil","Glorious"],"hash":"md5-G9EDHIm9tC12npMWYCoNIQ==","created":"Monday, April 8, 2024 - 10:51:55 PM"},{"id":"921a0763-f0c1-48ea-85c9-8aab69120a8b","key":"05083","book":"05","title":"HYMN LXXXIII. Parjanya.","link":"https://indra.ai/rigveda/hymns/05083.html","text":"p: SING with these songs thy welcome to the Mighty, with adoration praise and call Parjanya. The Bull, loud roaring, swift to send his bounty, lays in the plants the seed. for germination.\n\np: He smites the trees apart, he subdues the demons: all life fears him who wields the mighty weapon. From him exceeding strong fices e’en the guiltless, when thundering Parjanya smites the wicked.\n\np: Like a car-driver whipping on his horses, he makes the messengers of rain spring forward. Far off resounds the roaring of the lion, what time Parjanya fills the sky with rain-cloud.\n\np: Forth burst the winds, down come the lightning-flashes: the plants shoot up, the realm of light is streaming. Food springs abundant for all living creatures, what time Parjanya quickens earth with moisture.\n\np: Thou at whose bidding earth bows low before thee, at whose command hoofed cattle fly in terror, At whose behest the plants assume all colours, even thou Parjanya, yield us great protection.\n\np: Send down for us the rain of heaven, ye Maruts, and let the Stallion's flood descend in torrents. Come hither with this thunder while thou pourest the waters down, our heavenly Lord and Father.\n\np: Thunder and roar: the germ of life deposit. Fly round us on thy chariot waterladen. Thine opened water-skin draw with thee downward, and let the hollows and the heights be level.\n\np: Lift up the mighty vessel, pour down water, and let the liberated streams rush forward. Saturate both the earth and heaven with fatness, and for the cows let there be drink abundant.\n\np: When thou, with thunder and with roar, parjanya, smitest sinners down, This universe exults thereat, yea, all that is upon the earth.\n\np: Thou hast poured down the rain-flood now withhold it. Thou hast made desert places fit for travel. Thou hast made herbs to grow for our enjoyment: yea, thou hast won thee praise from living creatures.","people":["Parjanya"],"places":["Earth","Heaven","Sky"],"things":["Lord","Waters","Water","Light","Food","Streams","Rain","Strong","Mighty","Car","Praise","Songs","Horses","call","Cattle","Life"],"groups":["Maruts","Father"],"concepts":["Life","Heavenly","Swift"],"hash":"md5-Xw7FtDbd4eCSdo7o5UWdeQ==","created":"Monday, April 8, 2024 - 10:51:55 PM"},{"id":"3b3be1a2-65f8-44d3-878f-86ea574a800b","key":"05084","book":"05","title":"HYMN LXXXIV. Prthivi.","link":"https://indra.ai/rigveda/hymns/05084.html","text":"p: THOU, of a truth,O Prthivi, bearest the tool that rends the hills: Thou rich in torrents, who with might quickenest earth, O Mighty One.\n\np: To thee, O wanderer at will, ring out the lauds with beams of day, who drivest, like a neighing steed, the swelling cloud, O bright of hue.\n\np: Who graspest with thy might on earth. e’en the strong sovrans of the wood, when from the lightning of thy cloud the rain-floods of the heaven descend.","people":["Prthivi"],"places":["Earth","Heaven"],"things":["Might","Rain","Strong","Mighty"],"groups":[],"concepts":["Truth"],"hash":"md5-vZfSvyQKi3PfwPwdg72vVw==","created":"Monday, April 8, 2024 - 10:51:55 PM"},{"id":"f42a1285-25fc-45dc-8b72-c8801a4dcc5b","key":"05085","book":"05","title":"HYMN LXXXV. Varuna.","link":"https://indra.ai/rigveda/hymns/05085.html","text":"p: SING forth a hymn sublime and solemn, grateful to glorious. Varuna, imperial Ruler, who hath struck out, like one who subdues the victim, earth as a skin to spread in front of Surya.\n\np: In the tree-tops the air he hath extended, put milk in kine and vigorous speed in horses, Set intellect in hearts, fire in the waters, Siurya in heaven and Soma on the mountain.\n\np: Varuna lets the big cask, opening downward, flow through the heaven and earth and air's mid-region. Therewith the universe's Sovran waters earth as the shower of rain bedews the barley.\n\np: When Varuna is fain for milk he moistens the sky, the land, and earth to her foundation. Then straight the mountains clothe them in the rain-cloud: the Heroes, putting forth their vigour, loose them.\n\np: I will declare this mighty deed of magic, of glorious Varuna the Lord Immortal, who standing in the firmament hath meted the earth out with the Sun as with a measure.\n\np: None, verily, hath ever let or hindered this the most wise Deva's mighty deed of magic, Whereby with all their flood, the lucid rivers fill not one sea wherein they pour their waters.\n\np: If we have sinned against the man who loves us, have ever wronged a brother, friend, or comrade, the neighbour ever with us, or a stranger, O Varuna, remove from us the trespass.\n\np: If we, as gamesters cheat at play, have cheated, done wrong unwittingly or sinned of purpose, Cast all these sins away like loosened fetters, and, Varuna let us be thine own beloved.","people":["Soma","Varuna","Deva","Surya"],"places":["Earth","Heaven","Firmament","Sky"],"things":["Milk","Lord","Mountains","Rivers","Soma","Waters","Glorious","Air","Sun","Flow","Rain","Wise","Mighty","Hymn","Heroes","Friend","Horses"],"groups":["Brother","Immortal","Man"],"concepts":["Immortal","Glorious"],"hash":"md5-JQS+UG4BsXaMqxU4xcOKHA==","created":"Monday, April 8, 2024 - 10:51:55 PM"},{"id":"81b73a69-04d7-4409-be80-c39d94d8aff5","key":"05086","book":"05","title":"HYMN LXXXVI. Indra and Agni.","link":"https://indra.ai/rigveda/hymns/05086.html","text":"p: THE mortal man whom ye, the Twain, indra and Agni, help in fight, Breaks through e’en strongly-guarded wealth as Trta burst his way through reeds.\n\np: The Twain invincible in war, worthy to be renowned in frays, Lords of the Fivefold. People, these, indra and Agni, we invoke.\n\np: Impetuous is their strength, and keen the lightning of the mighty Pair, Which from their arms speeds with the car to Vrtra's slayer for the kine.\n\np: Indra and Agni, we invoke you both, as such, to send your cars: Lords of quick-coming bounty, ye who know, chief lovers of the song.\n\np: These who give increase day by day, Devas without guile for mortal man, Worthy themselves, I honour most, Two Devas as partners, for my horse.\n\np: The strength-bestowing offering thus to Indra and Agni hath been paid, as butter, purified by stones. Deal to our princes high renown, deal wealth to those who sing your praise, deal food to those who sing your praise.","people":["Indra","Vrtra","Agni","Trta"],"places":[],"things":["Offering","Wealth","Food","Song","Help","Mighty","Car","Chief","Praise","People","Horse","Cars"],"groups":["Devas","Man"],"concepts":["Cars","Strength","Offering"],"hash":"md5-AbsDzyj44tIfI3b8ia6nlQ==","created":"Monday, April 8, 2024 - 10:51:55 PM"},{"id":"899d3601-fa6c-47e7-b818-0758246f1f33","key":"05087","book":"05","title":"HYMN LXXXVII. Maruts.","link":"https://indra.ai/rigveda/hymns/05087.html","text":"p: To Visnu, to the Mighty whom the Maruts follow let your hymns born in song go forth, Evayamarut; To the impetuous, strong band, adorned with bracelets, that rushes on in joy and ever roars for vigour.\n\np: They who with might were manifest, and who willingly by their own knowledge told it forth, Evayamarut. Maruts, this strength of yours no wisdom comprehendeth: through their gifts' greatness they are moveless as the mountains.\n\np: Who by the psalm they sing are heard, from lofty heaven, the strong, the brightly shining Ones, Evayamarut; In whose abode there is no mightier one to move them, whose lightnings are as fires, who urge the roaring rivers.\n\np: He of the Mighty Stride forth strode, Evayamarut, out of the spacious dwelling-place, their home in common. When he, himself, hath yoked his emulous strong horses on heights, he cometh forth, joy-giving, with the Heroes.\n\np: Like your tremendous roar, the rainer with light flashing, strong, speeding, hath made all tremble, Evayamarut, Wherewith victorious ye, self-luminous, press onward, with strong reins, decked with gold, impetuous and well-weaponed.\n\np: Unbounded is your greatness, ye of mighty power. May your bright vigour be our aid, Evayamarut; For ye are visible helpers in the time of trouble: like fires, aglow with light, save us from shame and insult.\n\np: May the Rudras, mighty warriors, Evayamarut, with splendid brilliancy, like fires, be our protectors; They whose terrestrial dwelling-place is wide-extended, whom none suspect of sin, whose bands have lofty courage.\n\np: Come in a friendly spirit, come to us, O Maruts, and hear his call who praises you, Evayamarut. Like car-borne men, one-minded with the mighty Visnu, keep enmity far from us with your deeds of wonder.\n\np: Come to  'our offering, ye Hnly Ones, to bless it, and, free from demons, hear our call, Evayamarut.","people":["Visnu"],"places":["Heaven"],"things":["Born","Mountains","Rivers","Offering","Light","Men","Might","Song","Joy","Gold","Home","Strong","Mighty","Car","Heroes","Horses","call","Spirit","Gifts"],"groups":["Maruts","Rudras"],"concepts":["Strength","Wisdom","Offering"],"hash":"md5-dhrBOWaGiGhGLgTGlnAL5A==","created":"Monday, April 8, 2024 - 10:51:55 PM"}],"copyright":"©2023 Quinn Michaels (indra.ai). All rights reserved.","created":"Monday, April 8, 2024 - 10:51:52 PM"}