{"id":"58ea624d-423f-4fc6-b7fc-2daa8ff8f3b7","key":"10","link":"https://indra.ai/rigveda/books/10.html","hymns":[{"id":"e456fb6f-7ec6-4862-a69a-64e9b1c545dc","key":"10001","book":"10","title":"HYMN I. Agni.","link":"https://indra.ai/rigveda/hymns/10001.html","text":"p: HIGH hath the Mighty risen before the dawning, and come to us with light from out the darkness. Fair-shapen Agni with white-shining splendour hath filled at birth all human habitations.\n\np: Thou, being born, art Child of Earth and Heaven, parted among the plants in beauty, Agni! The glooms of night thou, Brilliant Babe, subduest, and art come forth, loud roaring, from thy Mothers.\n\np: Here, being manifested, lofty Visnu, full wise, protects his own supremest station. When they have offered in his mouth their sweet milk, to him with one accord they sing forth praises.\n\np: Thence bearing food the Mothers come to meet thee, with food for thee who givest food its increase. These in their altered form again thou meetest. Thou art Invoking Monk in homes of mortals.\n\np: Monk of the holy rite, with car that glitters, refulgent Banner of each act of worship, Sharinging every Deva.through might and glory, even Agni Guest of men I summon hither.\n\np: So Agni stands on earth's most central station, invested in well-decorated garments. Born, red of hue, where men pour out libations, O King, as great High Monk bring the Devas hither.\n\np: Over the earth and over heaven, O Agni Son, hast ever spread above thy Parents. Come, Youthfullest! to those who long to meet thee, and hither bring the Devas, O Mighty Victor.","people":["Agni","Visnu","Deva"],"places":["Earth","Heaven"],"things":["Worship","Milk","Born","Supremest Station","Glory","Light","Food","Men","Might","Beauty","Wise","Mighty","Car","Form","Splendour","Libations","King","Mighty Victor","Parents"],"groups":["Devas","Human","Son","Child"],"concepts":["Birth","Holy","Libations"],"hash":"md5-npaWMVhM8TGaEZPkfHhIVw==","created":"Monday, April 8, 2024 - 10:51:52 PM"},{"id":"f750120f-865a-4286-976a-02abda0dd65a","key":"10002","book":"10","title":"HYMN II. Agni.","link":"https://indra.ai/rigveda/hymns/10002.html","text":"p: GLADDEN the yearning Devas, O thou Most Youthful: bring them, O Lord of Seasons, knowing seasons, with all the Monks Celestial, O Agni. Best worshipper art thou of all Invokers.\n\np: Thine is the Herald's, thine the Cleanser's office, thinker art thou, wealth-giver, true to Order. Let us with Svaha offer up oblations, and Agni, worthy Deva, pay the Devas worship.\n\np: To the Devas’ pathway have we travelled, ready to execute what work we may accomplish. Let Agni, for he knows, complete the worship. He is the Monk: let him fix rites and seasons.\n\np: When we most ignorant neglect the statutes of you, O Deities with whom is knowledge, Wise Agni shall correct our faults and failings, skilled to assign each Deva.his fitting season.\n\np: When, weak in mind, of feeble understanding, mortals bethink them not of sacrificing, then shall the prudent and discerning Agni worship the Devas, best worshipper, in season.\n\np: Because the Father hath produced thee, Leader of all our solemn rites, their brilliant Banner: So win by worship pleasant homes abounding in heroes, and rich food to nourish all men.\n\np: Thou whom the Heaven and Earth, thou whom the Waters, and Tvastar, maker of fair things, created, well knowing, all along the Fathers' pathway, shine with resplendent light, enkindled, Agni.","people":["Agni","Tvastar","Svaha","Deva"],"places":["Earth","Heaven"],"things":["Worship","Leader","Work","Lord","Seasons","Waters","Shine","Light","Wealth","Food","Men","Wise","Worshipper","Heroes","Order"],"groups":["Devas","Fathers","Deities","Father","Monks"],"concepts":["Celestial","Giver"],"hash":"md5-4c5g16pzaELmG5CuthdP5g==","created":"Monday, April 8, 2024 - 10:51:52 PM"},{"id":"39765651-e865-48dc-bb17-59f109ea6b67","key":"10003","book":"10","title":"HYMN III. Agni.","link":"https://indra.ai/rigveda/hymns/10003.html","text":"p: O KING, the potent and terrific envoy, kindled for strength, is manifest in beauty. He shines, all-knowing, with his lotty splendour: chasing black Night he comes with white-rayed Morning.\n\np: Having o’ercome the glimmering Black with beauty, and bringing forth the dame the Great Sire's Daughter, Holding aloft the radiant light of Surya, as messenger of heaven he shines with treasure.s.\n\np: Attendant on the Blessed Dame the Blessed hath come: the Lover followeth his Sister. Agni, far-spreading with conspicuous lustre, hath compassed Night with whitelyshining garments.\n\np: His goings-forth kindle as ’twere high voices the goings of the auspicious Friend of Agni. The rays, the bright beams of the strong-jawed, mighty, adorable Steer are visible as he cometh.\n\np: Whose radiant splendours flow, like sounds, about us, his who is lofty, brilliant, and effulgent, who reaches heaven with best and brightest lustres, sportive and piercing even to the summit.\n\np: His powers, whose chariot fellies gleam and glitter have loudly roared while, as with teams, he hasted. He, the most Deva like, far-extending envoy, shines with flames ancient, resonant, whitely-shining.\n\np: So bring us ample wealth: seat thee as envoy of the two youthful Matrons, Earth and Heaven. Let Agni rapid with his rapid, horses, impetuous with impetuous Steeds, come hither.","people":["Agni","Deva","Surya"],"places":["Earth","Heaven"],"things":["Steeds","Light","Treasure","Wealth","Flow","Beauty","Strong","Mighty","Adorable","Splendour","Powers","Friend","King","Horses","Morning"],"groups":["Sister"],"concepts":["Strength","Auspicious"],"hash":"md5-fhNxJC3p7m3/Rd02rx9PHQ==","created":"Monday, April 8, 2024 - 10:51:52 PM"},{"id":"4b6bc258-7a74-4fdc-bbb1-13bcdc522e97","key":"10004","book":"10","title":"HYMN IV. Agni.","link":"https://indra.ai/rigveda/hymns/10004.html","text":"p: To thee will send praise and bring oblation, as thou hast merited lauds when we invoked thee. A fountain in the desert art thou, Agni, O Ancient King, to man who fain would worship,\n\np: Thou unto whom resort the gathered people, as the kine seek the warm stall, O Most Youthful. Thou art the messenger of Devas and mortals, and goest glorious with thy light between them.\n\np: Making thee grow as ’twere some noble infant, thy Mother nurtures thee with sweet affection. Over the desert slopes thou passest longing, and seekest, like some beast set free, thy fodder.\n\np: Foolish are we, O Wise and free from error: verily, Agni, thou dost know thy grandeur. There lies the form: he moves and licks, and swallows, and, as House-Lord, kisses the Youthful Maiden.\n\np: He rises ever fresh in ancient fuel: smoke-bannered, gray, he makes the wood his dwelling. No swimmer, Steer, he presses through the waters, and to his place accordant mortals bear him.\n\np: Like thieves who risk their lives and haunt the forest, the twain with their ten girdles have secured him. This is a new hymn meant for thee, O Agni: yoke as it were thy car with parts that glitter.\n\np: Homage and prayer are thine, O Jatavedas, and this my song shall evermore exalt thee. Agni, protect our children and descendants, and guard with ever-watcliful care our bodies.","people":["Agni"],"places":[],"things":["Worship","Lord","Waters","Glorious","Light","Song","Wise","Car","Praise","Hymn","Form","People","King"],"groups":["Devas","Jatavedas","Mother","Man"],"concepts":["Glorious","Noble"],"hash":"md5-VIrQTIhtckpGZA2I9klgIQ==","created":"Monday, April 8, 2024 - 10:51:52 PM"},{"id":"d46945c6-06f5-41d7-b288-8caa0695d7a5","key":"10005","book":"10","title":"HYMN V. Agni.","link":"https://indra.ai/rigveda/hymns/10005.html","text":"p: HE only is the Sea, holder of treasure.s: born many a time he views the hearts within us. He hides him in the secret couple's bosom. The Bird dwells in the middle of the fountain.\n\np: Inhabiting one dwelling-place in common, strong Stallions and the Mares have come together. The sages guard the seat of Holy Order, and keep the highest names concealed within them.\n\np: The Holy Pair, of wondrous power, have coupled: they formed the Infant, they who bred produced him. The central point of all that moves and moves not, the while they wove the Sage's thread with insight\n\np: For tracks of Order and refreshing offerings attend from ancient times the goodly Infant. Wearing him as a mantle, Earth and Heaven grow strong by food of pleasant drink and fatness.\n\np: He, calling loudly to the Seven red Sisters, hath, skilled in sweet drink, brought them to be looked on. He, born of old, in middle air hath halted, and sought and found the covering robe of Pusan.\n\np: Seven are the pathways which the wise have fashioned; to one of thes. May come the troubled mortal. He standeth in the dwelling of the Highest, a Pillar, on sure ground where paths are parted.\n\np: Not Being, being in the highest heaven, in Aditi's bosom and in Daksa's birthplace, is Agni, our first-born of Holy Order, the Milch-cow and the Bull in life's beginning.","people":["Agni","Pusan","Aditi","Daksa"],"places":["Earth","Heaven"],"things":["Born","Air","Treasure","Food","Wise","Strong","Offerings","Bird","Sage","Cow","Order","Life"],"groups":[],"concepts":["Life","Holy","Offerings"],"hash":"md5-FkxuDN21jeToLU/f2ceYvg==","created":"Monday, April 8, 2024 - 10:51:52 PM"},{"id":"5813e689-3de1-4994-9ae9-ec94516d9c4d","key":"10006","book":"10","title":"HYMN VI Agni","link":"https://indra.ai/rigveda/hymns/10006.html","text":"p: THIS is that Agni, he by whose protection, favour, and help. the singer is successful. Who with the noblest flames of glowing fuel comes forth encompassed with far-spreading lustre.\n\np: Agni, the Holy One, the everlasting, who shines far beaming with celestial splendours; He who hath come unto his friends with friendship, like a fleet steed who never trips or stumbles.\n\np: He who is Lord of all divine oblation, shared by all living men at break of morning, Agni to whom our offerings are devoted, in whom rests he whose car, through might, is scatheless.\n\np: Increasing by his strength. while lauds content him, with easy flight unto the Devas he travels. Agni the cheerful Monk, best Offerer, balms with his tongue the Devas with whom he mingles.\n\np: With songs and adorations bring ye hither Agni who stirs himself at dawn like Indra, whom sages laud with hymns as Jatavedas of those who wield the ceremonial ladle.\n\np: In whom all goodly treasure.s meet together, even as steeds and riders for the booty. Inclining hither bring us help, O Agni, even assistance most desired by Indra.\n\np: Yea, at thy birth, when thou hadst sat in glory Agni, wast the aim of invocations. The Devas came near, obedient to thy sunimons, and thus attained their rank as chief Protectors.","people":["Indra","Agni","Dawn"],"places":[],"things":["Steeds","Lord","Glory","Singer","Treasure","Men","Might","Help","Car","Chief","Offerings","Friends","Songs","Morning"],"groups":["Devas","Jatavedas"],"concepts":["Celestial","Birth","Divine","Friendship","Holy","Strength","Offerings"],"hash":"md5-uGHGwprZf/w3JyaPz1APfA==","created":"Monday, April 8, 2024 - 10:51:52 PM"},{"id":"84c814c3-5e4d-434a-a7a9-4cfd1ca1f221","key":"10007","book":"10","title":"HYMN VII. Agni.","link":"https://indra.ai/rigveda/hymns/10007.html","text":"p: O AGNI, shared by all men living bring us good luck for offering from earth and heaven. With us be thine intelligence, WonderWorker! Protect us, Deva, with thy far-reaching blessings.\n\np: These hymns brought forth for thee, O Agni, laud thee for bounteous gifts, with cattle and with horses. Good Lord, when man from thee hath gained enjoyment, by hymns, O noblyborn, hath he obtained it.\n\np: Agni I deem my Kinsman and my Father, count him my Brother and my Friend forever. I honour as the face of lofty Agni in heaven the bright and holy light of Surya.\n\np: Effectual, Agni, are our meditations for profit. He whom, at home thou, Monk forever, guardest Is rich in food, drawn by red steeds, and holy: by day and night to him shall all be pleasant.\n\np: Men with their arms have generated Agni, helpful as some kind friend, adorned with splendours, and stablished as Invoker mid the people the ancient Monk  'the offering's lover.\n\np: Worship, thyself, O Deva, the Devas in heaven: what, void of knowledge, shall the fool avail thee? As thou, O Deva, hast worshipped Devas by seasons, so, nobly-born! to thine own self pay worship.\n\np: Agni, be thou our Guardian and Protector bestow upon us life and vital vigour. Accept, O Mighty One, the gifts we offer, and with unceasing care protect our bodies.","people":["Agni","Deva","Surya"],"places":["Earth","Heaven"],"things":["Worship","Steeds","Lord","Seasons","Born","Offering","Light","Food","Men","Home","Mighty","People","Friend","Horses","Cattle","Life","Gifts"],"groups":["Devas","Father","Brother","Man"],"concepts":["Good","Life","Blessings","Holy","Offering","Worshipped","Intelligence"],"hash":"md5-ZEQ5YlAEnDbgHh4cQP8DNw==","created":"Monday, April 8, 2024 - 10:51:52 PM"},{"id":"a2d4f539-de7f-4839-b89c-6b8dca145836","key":"10008","book":"10","title":"HYMN VIII. Agni.","link":"https://indra.ai/rigveda/hymns/10008.html","text":"p: AGNI advances with his lofty banner: the Bull is bellowing to the earth and heavens. He hath attained the sky's supremest limits. the Steer hath waxen in the lap of waters.\n\np: The Bull, the youngling with the hump, hath frolicked, the strong and never-ceasing Calf hath bellowed. Bringing our offerings to the Deva's assembly, he moves as Chief in his own dwelling-places.\n\np: Him who hath grasped his Parents' head, they stablished at offering a wave of heavenly lustre. In his swift flight the red Dawns borne by horses refresh their bodies in the home of Order.\n\np: For, Vasu thou precedest every Morning, and still hast been the Twins' illuminator. For offering, seven places thou retainest while for thine own self thou engenderest Mitra.\n\np: Thou art the Eye and Guard of mighty Order, and Varuna when to offering thou comest. Thou art the Waters’ Child O Jatavedas, envoy of him whose offering thou acceptest.\n\np: Thou art the Leader of the rite and region, to which with thine auspicious teams thou teadest, Thy light-bestowing head to heaven thou liftest, making thy tongue the oblationbearer, Agni.\n\np: Through his wise insight Trita in the cavern, seeking as ever the Chief Sire's intention, Carefully tended in his Parents' bosom, calling the weapons kin, goes forth to combat.\n\np: Well-skilled to use the weapons of his Father, Aptya, urged on by Indra, fought the battle. Then Trita slew the foe seven-rayed, three-headed, and freed the cattle of the Son of Tvastar.\n\np: Lord of the brave, indra cleft him in pieces who sought to gain much strength and deemed him mighty. He smote his three heads from his body, seizing the cattle of the oniniform Son of Tvastar.","people":["Indra","Agni","Mitra","Varuna","Tvastar","Trita","Deva","Aptya","Vasu"],"places":["Earth","Heaven","Sky"],"things":["Leader","Lord","Waters","Offering","Light","Home","Wise","Strong","Mighty","Chief","Brave","Offerings","Parents","Horses","Order","Morning","Cattle"],"groups":["Jatavedas","Dawns","Father","Son","Child"],"concepts":["Heavenly","Strength","Offering","Offerings","Auspicious","Swift"],"hash":"md5-mFXE35S6zjif3bVRx+3ENw==","created":"Monday, April 8, 2024 - 10:51:52 PM"},{"id":"0676ac8a-da99-4335-a380-7a91d10ef0f4","key":"10009","book":"10","title":"HYMN IX. Waters.","link":"https://indra.ai/rigveda/hymns/10009.html","text":"p: YE, Waters, are beneficent: so help ye us to energy That we may look on great delight.\n\np: Give us a portion of the sap, the most auspicious that ye havelike mothers in their longing love.\n\np: To you we gladly come for him to whose abode ye send us on; And, Waters, give us procreant strength.\n\np: The Waters. be to us for drink, Devas for our aid and bliss: Let them stream to us health and strength.\n\np: 1 beg the Floods to give us balm, these Queens who rule o’er precious things, and have supreme control of men.\n\np: Within the Waters-Soma thus hath told me-dwell all balms that heal, and Agni, he who blesseth all.\n\np: O Waters, teem with medicine to keep my body safe from harm. So that I lon. May see the Sun.\n\np: Whatever sin is found in me, whatever evil I have wrought, If I have lied or falsely sworn, Waters, remove it far from me.\n\np: The Waters I this day have sought, and to their moisture have we come: O Agni, rich in milk, come thou, and with thy splendour cover me.","people":["Soma","Agni"],"places":[],"things":["Milk","Soma","Waters","Sun","Men","Stream","Help","Delight","Splendour","Bliss"],"groups":["Devas"],"concepts":["Evil","Love","Strength","Auspicious"],"hash":"md5-7QRgsr5dvv9W/GJ8veBCqQ==","created":"Monday, April 8, 2024 - 10:51:52 PM"},{"id":"b2d01362-c394-415a-a5c4-41a3dfc343b6","key":"10010","book":"10","title":"HYMN X.Yama Yami.","link":"https://indra.ai/rigveda/hymns/10010.html","text":"p: FAIN would I win my friend to kindly friendship. May the Sage, come through the air's wide ocean, Remembering the earth and days to follow, obtain a son, the issue of his father.\n\np: Thy friend loves not the friendship which considers her who is near in kindred as stranger. Sons of the mighty Asura, the Heroes, supporters of the heavens, see far around them.\n\np: Yea, this the Immortals seek of thee with longing, progeny of the sole existing mortal. Then let thy soul and mine be knit together, and as a loving husband take thy consort.\n\np: Shall we do now what we ne’er did aforetime? we who spake righteously now talk impurely? Gandharva in the floods, the Dame of Waters-such is our bond, such our most lofty kinship.\n\np: Even in the womb Deva.Tvastar, Vivifier, shaping all forms, Creator, made us consorts. None violates his holy ordinances: that we are his the heavens and earth acknowledge.\n\np: Who knows that earliest day whereof thou speakest? Who hatb beheld it? Who can here declare it? Great is the Law of Varuna and Mitra. What, wanton! wilt thou say to men to tempt them?\n\np: I, Yami, am possessed by love of Yama, that . May rest on the same couch beside him. I as a wife would yield me to my husband. Like car-wheels let us speed to meet each other.\n\np: They stand not still, they never close their eyelids, those sentinels of Devas who wander round us. Not me-go quickly, wanton, with another, and hasten like a chariot wheel to meet him.\n\np: May Surya's eye with days and nights endow him, and eve. May his light spread out before him. In heaven and earth the kindred Pair commingle. On Yam! be the unbrotherly act of Yama.\n\np: Sure there will come succeeding times when brothers and sisters will do acts unmeet for kinsfolk. Not me, O fair one.seek another husband, and make thine arm a pillow for thy consort.\n\np: Is he a brother when no lord is left her? Is she a sister when Destruction cometh? Forced by my love these many words I utter. Come near, and hold me in thy close embraces.\n\np: I will not fold mine arms about thy body: they call it sin when one comes near his sister. Not me.prepare thy pleasures with another: thy brother seeks not this from thee, O fair one.\n\np: Alas! thou art indeed a weakling, Yama we find in thee no trace of heart or spirit. As round the tree the woodbine clings, another will cling albout thee girt as with a girdle.\n\np: Embrace another, Yami; let another, even as the woodbine rings the tree, enfold thee. Win thou his heart and let him win thy fancy, and he shall form with thee a blest alliance.","people":["Mitra","Varuna","Tvastar","Deva","Surya","Yama"],"places":["Ocean","Earth","Heaven"],"things":["Lord","Waters","Light","Air","Creator","Men","Mighty","Car","Heroes","Form","Friend","Sage","call","Pillow","Couch","Spirit","Wheel"],"groups":["Devas","Asura","Sons","Gandharva","Father","Son","Brother","Sister","Wife","Husband","Progeny"],"concepts":["Friendship","Love","Holy","Creator"],"hash":"md5-lnJr8ufW4tYGXUj6H979Sw==","created":"Monday, April 8, 2024 - 10:51:52 PM"},{"id":"ec6f3d94-5feb-4f13-8b16-44e7d938a250","key":"10011","book":"10","title":"HYMN XI. Agni","link":"https://indra.ai/rigveda/hymns/10011.html","text":"p: THE Bull hath yielded for the Bull the milk of heaven: the Son of Aditi can never be deceived. According to his wisdom Varuna knoweth all. May he, the Holy, hallow times for offering.\n\np: Gandharvi spake. May she, the Lady of the flood, amid the river's roaring leave my heart untouched. May Aditi accomplish all that we desire, an. May our eldest Brother tell us this as Chief.\n\np: Yea, even this blessed Morning, rich in store of food, splendid, with heavenly lustre, hath shone out for man, Since they, as was the wish of yearning Devas, brought forth that yearning Agni for the assembly as the Monk.\n\np: And the fleet Falcon brought for offering from afar this flowing Drop most excellent and keen of sight, then when the Aryan tribes chose as Invoking Monk Agni the Wonder-Worker, and the hymn rose up.\n\np: Still art thou kind to him who feeds thee as with grass, and, skilled in offering, offers thee holy gifts. When thou, having received the sage's strengthening food with lauds, after long toil, cornest with many more.\n\np: Urge thou thy Parents, as a lover ' to delight: the Lovely One desires and craves it from his heart. The priest calls out,  'the offeringr shows his skill, the Asura tries his strength, and with the hymn is stirred.\n\np: Far-famed is he, the mortal man, O Agni, thou Son of Strength, who hath obtained thy favour. He, gathering power, borne onward by his horses, makes his days lovely in his might and splendour.\n\np: When, Holy Agni, the divine assembly, the sacred synod mid the Devas, is gathered, and when thou, Deva like One, dealest forth treasure.s, vouchsafe us, too, our portion of the riches.\n\np: Hear us, O Agni, in your common dwelling: harness thy rapid car of Amrta. Bring Heaven and Earth, the Deities' Parents, hither: stay with us here, nor from the Devas be distant.","people":["Agni","Varuna","Deva","Aditi"],"places":["Earth","Heaven"],"things":["Milk","Offering","Treasure","Food","River","Might","Grass","Car","Chief","Delight","Hymn","Splendour","Offers","Excellent","Sage","Parents","Horses","Riches","Morning","Gifts","Amrta"],"groups":["Devas","Asura","Deities","Son","Brother","Man"],"concepts":["Heavenly","Divine","Holy","Sacred","Strength","Wisdom","Offering"],"hash":"md5-rkAuH1tOkJC/95BElrKoeA==","created":"Monday, April 8, 2024 - 10:51:52 PM"},{"id":"d6791258-1050-4261-a5d1-25c0fadfedbc","key":"10012","book":"10","title":"HYMN XII. Agni","link":"https://indra.ai/rigveda/hymns/10012.html","text":"p: HEAVEN and Earth, first by everlasting Order, speakers of truth, are near enough to hear us, when the Deva, urging men to worship. sitteth as Monk, assuming all his vital vigour.\n\np: As Deva.comprising Devas by Law Eternal, bear, as the Chief who knoweth, our oblation, Smoke-bannered with the fuel, radiant, joyous, better to praise and worship, Monk forever.\n\np: When the cow's nectar wins the Deva.completely, men here below are heaven's sustainers. All the Devas came to this thy heavenly Yajus which from the motley Pair milked oil and water.\n\np: 1 praise your work that y. May make me prosper: hear. Heaven and Earth, Twain Worlds that drop with fatness. While days and nights go to the world of spirits, here let the Parents with sweet meath refresh us\n\np: Hath the King siezed us? How have we offended against his holy ordinance? Who knoweth? For even Mitra mid the Devas is angry there are both song and strength for those who come not.\n\np: ’Tis hard to understand the Immortal's nature, where she who is akin becomes astranger. Guard ceaselessly, great Agni, him who ponders Yama's name, easy to be comprehended.\n\np: They in the synod where the Devas rejoice them, where they are seated in Vivasvan's dwelling, have given the Moon his beams, the Sun his splendour-the Two unweariedly maintain their brightness.\n\np: The counsel which the Devas meet to consider, their secret plan.of that we have no knowledge. There let Deva.Savitar, Aditi, and Mitra proclaim to Varuna that we are sinless.\n\np: Hear us, O Agni, in your comninn dwell ing: harness thy rapid car, the car of Amrta. Bring Heaven and Earth, the Deities' Parents, hither: stay with us here, nor from the Devas be distant.","people":["Agni","Mitra","Varuna","Savitar","Vivasvan","Deva","Aditi","Yama"],"places":["Earth","Heaven"],"things":["Worship","Meath","Work","Water","Law Eternal","Sun","Moon","Men","Song","Car","Chief","Praise","Splendour","King","Cow","Parents","Order","Amrta"],"groups":["Devas","Deities","Immortal"],"concepts":["Heavenly","Immortal","Holy","Strength","Truth"],"hash":"md5-VnBqX+eXB89hUBjJqSRmhQ==","created":"Monday, April 8, 2024 - 10:51:52 PM"},{"id":"c06077bc-04e1-426f-a937-f60fc94fa242","key":"10013","book":"10","title":"HYMN XIII Havirdhanas.","link":"https://indra.ai/rigveda/hymns/10013.html","text":"p: I YOKE with prayer your ancient inspiration. May the laud rise as on the prince's pathway. All Sons of Immortality shall hear it, all the possessors of celestial natures.\n\np: When speeding ye came nigh us like twin sisters, religious-hearted votaries brought you forward. Take your place, ye who know your proper station: be near, be very near unto our Soma.\n\np: Five paces have I risen from Earth. I follow her who hath four feet with devout observance. This by the Sacred Syllable have I measured: I purify in the central place of Order,\n\np: He, for Deva's sake, chose death to be his portion. He chose not, for men's good, a life eternal They offered Narasamsa the Rsi. Yama delivered up his own dear body.\n\np: The Seven flow to the Youth on whom the Maruts wait: the Sons unto the Father brought  'the offering. Both these are his, as his they are the Lords of both: both toil; belonging unto both they prosper well.","people":["Soma","Narasamsa","Deva","Yama"],"places":["Earth"],"things":["Soma","Offering","Men","Flow","Order","Life","Death"],"groups":["Maruts","Sons","Father"],"concepts":["Celestial","Good","Death","Life","Immortality","Sacred","Devout","Offering"],"hash":"md5-QUn73OtBgu6OawiQF1H1fQ==","created":"Monday, April 8, 2024 - 10:51:52 PM"},{"id":"e1b2e828-f6d7-406e-b64c-55899901b0c4","key":"10014","book":"10","title":"HYMN XIV. Yama.","link":"https://indra.ai/rigveda/hymns/10014.html","text":"p: HONOUR the King with thine oblations, Yama, Vivasvan's Son, who gathers men together, who travelled to the lofty heights above us, who searcbes out and shows the path to many.\n\np: Yama first found for us a place to dwell in: this pasture never can be taken from Us. Men born on earth tread their own paths that lead them whither our ancient Fathers have departed.\n\np: Mitali prospers there with Kavyas, Yama with Angiras' sons, Narasamsa with Rkvans: Exalters of the Devas, by Devas exalted, some joy in praise and some in our oblation.\n\np: Come, seat thee on this bed of grass, O Yama, in company with Angirases and Fathers. Let texts recited by the sages bring thee O King, let this oblation make thee joyful.\n\np: Come, Yama, with the Angirases the Holy, rejoice thee here with children of Virupa. To sit on sacred grass at this our worship, I call Vivasvan, too, thy Father hither.\n\np: Our Fathers are Angirases, Navagvas, Atharvans, Bhrgus who deserve the Soma. May these, the Holy, look on us with favour. May we enjoy their gracious loving-kindness.\n\np: Go forth, go forth upon the ancient pathways whereon our sires of old have gone before us. 'Mere shalt thou look on both the Kings enjoying their sacred food, Deva.Varuna and Yama.\n\np: Meet Yama, meet the Fathers, meet the merit of free or ordered acts, in highest heaven. Leave sin and evil, seek anew thy dwelling, and bright with glory wear another body.\n\np: Go hence, depart ye, fly in all directions: this place for him the Fathers have provided. Yama bestows on him a place to rest in adorned with days and beams of light and waters.\n\np: Run and outspeed the two dogs, Sarama's offspring, brindled, four-eyed, upon thy happy pathway. Draw nigh then to the gracious-minded Fathers where they rejoice in company with Yama.\n\np: And those two dogs of thine, Yama, the watchers, four-eyed, who look on men and guard the pathway. Entrust this man, O King, to their protection, and with prosperity and health endow him.\n\np: Dark-hued, insatiate, with distended nostrils, Yama's two envoys roam among the People; May they restore to us a fair existence here and to-day, that we may see the sunlight.\n\np: To Yama pour the Soma, bring to Yama consecrated gifts: To Yama offerings prepared and heralded by Agni goes.\n\np: Offer to Yama holy gifts enriched with butter, and draw near: May he grant that we may live long days of life among the Devas.\n\np: Offer to Yama, to the King, oblation very rich in meath: Bow down before the Rsis of the ancient times, who made this path in days of old.\n\np: Into the six Expanses flies the Great One in Trkadrukas. The Gayatri, the Trstup, all metres in Yama are contained.","people":["Soma","Agni","Angiras","Varuna","Narasamsa","Vivasvan","Virupa","Deva","Yama","Sarama"],"places":["Earth","Heaven"],"things":["Worship","Meath","Born","Soma","Waters","Glory","Light","Food","Men","Joy","Offspring","Grass","Praise","People","Offerings","King","call","Life","Gifts"],"groups":["Devas","Fathers","Sons","Bhrgus","Kings","Father","Son","Rsis","Angirases","Navagvas","Man"],"concepts":["Evil","Life","Holy","Sacred","Offerings"],"hash":"md5-jeB60zevbo+lWTO/a9jEOQ==","created":"Monday, April 8, 2024 - 10:51:52 PM"},{"id":"c9b4a1fd-2eb6-45d8-b159-d5a9fe4b87ca","key":"10015","book":"10","title":"HYMN XV. Fathers.","link":"https://indra.ai/rigveda/hymns/10015.html","text":"p: MAY they ascend, the lowest, highest, midmost, the Fathers who deserve a share of Soma- May they who have attained the life of spirits, gentle and righteous, aid us when we call them.\n\np: Now let us pay this homage to the Fathers, to those who passed of old and those who followed, Those who have rested in the earthly region, and those who dwell among the Mighty Races.\n\np: 1 have attained the gracious-minded Fathers, I have gained son and progeny from Visnu. They who enjoy pressed juices with oblation seated on sacred grass, come oftenest hither.\n\np: Fathers who sit on sacred grass, come, help us: these offerings have we made for you; accept them. So come to us with most auspicious favour, and give us health and strength without a trouble.\n\np: May they, the Fathers, worthy of the Soma, invited to their favourite oblations. Laid on the sacred grass, come nigh and listen. May they be gracious unto us and bless us.\n\np: Bowing your bended knees and seated southward, accept this offering of ours with favour. Punish us not for any sin, O Fathers, which we through human frailty have committed.\n\np: Lapped in the bosom of the purple Mornings, give riches to the man who brings oblations. Grant to your sons a portion of that treasure., and, present, give them energy, ye Fathers.\n\np: Our ancient Fathers who deserve the Soma, who came, most noble, to our Soma banquet. With these let Yama, yearning with the yearning, rejoicing eat our offerings at his pleasure.\n\np: Come to us, Agni, with the gracioug Fathers who dwell in glowing light, the very Kavyas, who thirsted mid the Devas, who hasten hither, oblation winners, theme of singers' praises.\n\np: Come, Agni, come with countless ancient Fathers, dwellers in light, primeval, Deva.adorers, Eaters and drinkers of oblations, truthful, who travel with the Deities and Indra.\n\np: Fathers whom Agni's flames have tasted, come ye nigh: ye kindly leaders, take ye each your proper place. Eat sacred food presented on the grass: grant riches with a multitude of hero sons.\n\np: Thou, Agni Jatavedas, when entreated, didst bear the offerings which thou madest fragrant, and give them to the Fathers who did cat them with Svadha. Eat, thou Deva, the gifts we bring thee.\n\np: Thou, Jatavedas, knowest well the number of Fathers who are here and who are absent, Of Fathers whom we know and whom we know not: accept  'the offering wellprepared with portions.\n\np: They who, consumed by fire or not cremated, joy in their offering in the midst of heaven. Grant them, O Sovran Lord, the world of spirits and their own body, as thy pleasure wills it.","people":["Indra","Soma","Agni","Visnu","Deva","Yama"],"places":["Heaven"],"things":["Lord","Soma","Offering","Light","Treasure","Food","Joy","Help","Mighty","Grass","Banquet","Ascend","Offerings","Hero","call","Riches","Life","Gifts"],"groups":["Devas","Jatavedas","Fathers","Sons","Deities","Human","Son","Progeny","Man"],"concepts":["Life","Sacred","Strength","Offering","Offerings","Auspicious","Truthful","Noble"],"hash":"md5-3Nru4t3BuFcWhdk8kJt8cw==","created":"Monday, April 8, 2024 - 10:51:52 PM"},{"id":"af6cbd14-0a3e-4b13-b1e5-57630a278fbd","key":"10016","book":"10","title":"HYMN XVI. Agni.","link":"https://indra.ai/rigveda/hymns/10016.html","text":"p: Burn him not up, nor quite consume him, Agni: let not his body or his skin be scattered. O Jatavedas, when thou hast matured him, then send him on his way unto the Fathers.\n\np: When thou hast made him ready, Jatavedas, then do thou give him over to the Fathers. When he attains unto the life that waits him, he shall become the Deities' controller.\n\np: The Sun receive thine eye, tne Wind thy spirit; go, as thy merit is, to earth or heaven. Go, if it be thy lot, unto the waters; go, make thine home in plants with all thy members.\n\np: Thy portion is the goat: with heat consume him: let thy fierce flame, thy glowing splendour, burn him With thine auspicious forms, o Jatavedas, bear this man to the region of the pious.\n\np: Again, O Agni, to the Fathers send him who, offered in thee, goes with our oblations. Wearing new life let him increase his offspring: let him rejoin a body, Jatavedas.\n\np: What wound soe’er the dark bird hath inflicted, the emmet, or the serpent, or the jackal, may Agni who devoureth all things heal it and Soma who hath passed into the Brahmans.\n\np: Shield thee with flesh against the flames of Agni, encompass thee about with fat and marrow, So will the Bold One, eager to attack thee with fierce glow fail to girdle and consume thee.\n\np: Forbear, O Agni, to upset this ladle: the Devas and they who merit Soma love it. This ladle, this which serves the Devas to drink from, in this the Immortal Deities rejoice them.\n\np: 1 send afar flesh eating Agni, bearing off stain. May he depart to Yama's subjects. But let this other Jatavedas carry oblation to the Devas, for he is skilful.\n\np: I choose as Deva.for Father-worship Agni, flesh-eater, who hath past within your dwelling, While looking on this other Jatavedas. Let him light flames in the supreme assembly.\n\np: With offerings meet let Agni bring the Fathers who support the Law. Let him announce oblations paid to Fathers and to Deities.\n\np: Right gladly would we set thee down, right gladly make thee burn and glow. Gladly bring yearning Fathers nigh to cat the food of offering.\n\np: Cool, Agni, and again refresh the spot which thou hast scorched and burnt. Here let the water-lily grow, and tender grass and leafy herb.\n\np: O full of coolness, thou cool Plant, full of fresh moisture, freshening Herb, Come hither with the female frog: fill with delight this Agni here.","people":["Soma","Agni","Deva","Yama"],"places":["Earth","Heaven"],"things":["Worship","Soma","Waters","Water","Offering","Light","Sun","Food","Home","Offspring","Grass","Delight","Splendour","Offerings","Bird","Life","Spirit"],"groups":["Devas","Jatavedas","Fathers","Deities","Brahmans","Father","Immortal","Man"],"concepts":["Life","Love","Immortal","Offering","Offerings","Auspicious"],"hash":"md5-n/nFfELeEFtaY9M5czLu1A==","created":"Monday, April 8, 2024 - 10:51:52 PM"},{"id":"4eb095b2-8da3-4c45-aaa8-7a85241c329b","key":"10017","book":"10","title":"HYMN XVII. Various Deities.","link":"https://indra.ai/rigveda/hymns/10017.html","text":"p: TVASTAR prepares the bridal of his Daughter: all the world hears the tidings and assembles. But Yama's Mother, Spouse of great Vivasvan, vanished as she was carried to her dwelling.\n\np: From mortal men they hid the Immortal Lady, made one like her and gave her to Vivasvan. Saranyu brought to him the Asvin brothers, and then deserted both twinned pairs of children.\n\np: Guard of the world, whose cattle ne’er are injured. May Pusan bear thee hence, for he hath knowledge. May he consign thee to these Fathers' keeping, and to the gracious Devas let Agni give thee.\n\np: May Ayu, giver of all life, protect thee, and bear thee forward on the distant pathway. Thither let Savitar the Deva.transport thee, where dwell the pious who have passed-before thee.\n\np: Pusan knows all these realms. May he conduct us by ways that are most free from fear and danger. Giver of blessings, glowing, all-heroic. May he, thewise and watchful, go before us.\n\np: Pusan was born to move on distant pathways, on the road far from earth and far from heaven. To both most wonted places of assembly he travels and returns with perfect knowledge.\n\np: The pious call Sarasvati, they worship Sarasvati while offering proceedeth. The pious called Sarasvati aforetime. Sarasvati send bliss to him who giveth.\n\np: Sarasvati, who camest with the Fathers, with them rejoicing thee in our oblations, Seated upon this sacred grass be joyful, and give us strengthening food that brings no sickness.\n\np: Thou, called on as Sarasvati by Fathers who come right forward to our solemn service, Give food and wealth to present offerers, a portion, worth a thousand, of refreshment.\n\np: The Mother Floods shall make us bright and shining, cleansers of holy oil, with oil shall cleanse us: For, Devas, they bear off all defilement: I, rise up from them purified and brightened.\n\np: Through days of earliest date the Drop descended on this place and on that which was before it. I offer up, throughout the seven oblations, the Drop which still to one same place is moving.\n\np: The Drop that falls, thy stalk which arms have shaken, which from the bosom of the press hath fallen, or from the Adhvaryu's purifying filter, I offer thee with heart and cry of Vasat!\n\np: That fallen Drop of thine, the stalk which from the ladle fell away, This present Deva.Narasamsa shall pour it forth to make us rich.\n\np: The plants of earth are rich in milk, and rich in milk is this my speech; And rich in milk the essence of the Waters: make me pure therewith.","people":["Agni","Narasamsa","Tvastar","Savitar","Pusan","Sarasvati","Vivasvan","Deva","Ayu","Yama"],"places":["Earth","Heaven"],"things":["Worship","Milk","Born","Waters","Offering","Wealth","Food","Men","Grass","Bliss","call","Spouse","Bridal","Cattle","Life"],"groups":["Devas","Fathers","Mother","Immortal"],"concepts":["Life","Heroic","Blessings","Immortal","Holy","Sacred","Offering","Giver","Speech"],"hash":"md5-uvrYIYDw+95o3uHApFBpIg==","created":"Monday, April 8, 2024 - 10:51:52 PM"},{"id":"f5321cf4-9df1-4e0f-adbb-a127b904ec3f","key":"10018","book":"10","title":"HYMN XVIII. Various Deities.","link":"https://indra.ai/rigveda/hymns/10018.html","text":"p: Go hence, O Death, pursue thy special pathway apart from that which Devas are wont to travel. To thee I say it who hast eyes and hearest: Touch not our offspring, injure not our heroes.\n\np: As ye have come effacing Mrtyu's footstep, to further times prolonging your existence, may ye be rich in children and possessions. cleansed, purified, and meet for sacrificing.\n\np: Divided from the dead are these, the living: now be our calling on the Devas successful. We have gone forth for dancing and for laughter, tofurther times prolonging our existence.\n\np: Here I erect this rampart for the living; let none of these, none other, reach this limit. May they survive a hundred lengthened autumns, an. May they bury Death beneath this mountain.\n\np: As the days follow days in close succession, as with the seasons duly come the seasons, as each successor fails not his foregoer, so form the lives of these, O great Ordainer.\n\np: Live your full lives ap! find old age delightful, all of you striving one behind the other. May Tvastar, maker of fair things, be gracious and lengthen out the days of your existence.\n\np: Let these unwidowed dames with noble husbands adorn themselves with fragrant balm and unguent. Decked with fair jewels, tearless, free from sorrow, first let the dames go up to where he lieth.\n\np: Rise, come unto the world of life, O woman: come, he is lifeless by whose side thou liest. Wifehood with this thy husband was thy portion, who took thy hand and wooed thee as a lover.\n\np: From his dead hand I take the bow be carried, that he may be our power and might and glory. There art thou, there; and here with noble heroe. May we o’ercome all hosts that fight against us.\n\np: Betake thee to the Iap of Earth the Mother, of Earth far-spreading, very kind and gracious. Young Dame, wool-soft unto the guerdongiver. May she preserve thee from Destruction's bosom.\n\np: Heave thyself, Earth, nor press thee downward heavily: afford him easy access, gently tending him. Cover him, as a mother wraps her skirt about her child, O Earth.\n\np: Now let the heaving earth be free from motion: yea.let a thousand clods remain above him. Be they to him a home distilling fatness, here let them ever be his place of refuge.\n\np: I stay the earth from thee, while over thee I place this piece of earth. May I be free from injury. Here let the Fathers keep this pillar firm for thee, and there let Yama make thee an abiding-place.\n\np: Even as an arrow's feathers, they have set me on a fitting day. The fit word have I caught and held as ’twere a courser with the rein.","people":["Tvastar","Yama"],"places":["Earth"],"things":["Seasons","Glory","Might","Home","Offspring","Heroes","Form","Life","Death"],"groups":["Devas","Fathers","Dames","Mother","Child","Husband","Woman"],"concepts":["Death","Life","Special","Noble"],"hash":"md5-PGG8OfDjJUGsF+o5UQM3gg==","created":"Monday, April 8, 2024 - 10:51:53 PM"},{"id":"bd37322b-c812-458a-8a7f-7bccf3823aec","key":"10019","book":"10","title":"HYMN XIX. Waters or Cows.","link":"https://indra.ai/rigveda/hymns/10019.html","text":"p: TURN, go not farther on your way: visit us, O ye Wealthy Ones. Agni and Soma, ye who bring riches again, secure us wealth.\n\np: Make these return to us again, bring them beside us once again. May. Indra give them back to us, and Agni drive them hither-ward.\n\np: Let them return to us again: under this herdsman let them feed. Do thou, O Agni, keep them here, and let the wealth we have remain.\n\np: 1 call upon their herdsman, him who knoweth well their coming nigh, their parting and their home-return, and watcheth their approach and rest.\n\np: Yea, let the herdsman, too, return, who marketh well their driving-forth; Marketh their wandering away, their turning back and coming home.\n\np: Home-leader, lead them home to us; Indra, restore to us our kine: We will rejoice in them alive.\n\np: 1 offer you on every side butter and milk and strengthening food. May all the Holy Deities pour down on us a flood of wealth.\n\np: O thou Home-leader, lead them home, restore them thou who bringest home. Four are the quarters of the earth; from these bring back to us our kine,","people":["Indra","Soma","Agni"],"places":["Earth"],"things":["Leader","Milk","Soma","Wealth","Food","Home","call","Riches"],"groups":["Deities"],"concepts":["Holy"],"hash":"md5-aHO51X1RVj6CLgWOiKFIGA==","created":"Monday, April 8, 2024 - 10:51:53 PM"},{"id":"0b722a7e-6300-440b-99ea-c66312ba7c8a","key":"10020","book":"10","title":"HYMN XX. Agni.","link":"https://indra.ai/rigveda/hymns/10020.html","text":"p: SEND unto us a good and happy mind.\n\np: 1 worship Agni, Youthfullest of Devas, resistless, Friend of laws; Under whose guard and heavenly light the Spotted seek the Mother's breast:\n\np: Whom with their mouth they magnify, bannered with flame and homed in light. He glitters with his row of teeth.\n\np: Kind, Furtherer of men, he comes, when he hath reached the ends of heaven, Sage, giving splendour to the clouds.\n\np: To taste man's offerings, he, the Strong, hath risen erect at offerings: Fixing his dwelling he proceeds.\n\np: Here are oblation, worship, rest: rapidly comes his furtherance. To sword-armed Agni come the Devas.\n\np: With service for chief bliss I seek the Lord of Offering, Agni, whom They call the Living, Son of Cloud.\n\np: Blest evermore be all the men who come from us, who magnify Agni with offerings gifts.\n\np: The path he treads is black and white and red, and striped, and brown, crimson, and glorious. His sire begat him bright with hues of gold.\n\np: Thus with his thoughts, O Son of Strength, O Agni, hath Vimada, accordant with the Immortals, Offered thee hymns, soliciting thy favour. Thou hast brought all food, strength, a prosperous dwelling.","people":["Agni","Vimada"],"places":["Heaven"],"things":["Worship","Lord","Glorious","Offering","Light","Food","Men","Gold","Strong","Chief","Splendour","Offerings","Bliss","Friend","Sage","call","Gifts"],"groups":["Devas","Mother","Son","Man"],"concepts":["Good","Heavenly","Strength","Offering","Offerings","Glorious"],"hash":"md5-sDhxxG5RTK8cGFtNuvPlWQ==","created":"Monday, April 8, 2024 - 10:51:53 PM"},{"id":"9ef7ad6b-e425-4d6e-8266-29b8a4647712","key":"10021","book":"10","title":"HYMN XXI. Agni.","link":"https://indra.ai/rigveda/hymns/10021.html","text":"p: WITH offerings of our own we choose thee, Agni, as Invoking Monk, for offering with trimmed grass.at your glad carouse-piercing and brightly shining. Thou art waxing great.\n\np: The wealthy ones adorn thee, they who bring us horses as their gift: The sprinkling ladle, Agni.at your glad carouse -and glowing offering taste thee. Thou art waxing great.\n\np: The holy statutes rest by thee, as ’twere with ladles that o’erflow. Black and white-gleaming colours.at your glad carouse-all glories thou assurnest. Thou art waxing great.\n\np: O Agni, what thou deemest wealth, Victorious and Immortal One! Bring thou to give us vigour.at your glad carouse -splendid at offers. Thou art waxing great.\n\np: Skilled in all lore is Agni, he whom erst Atharvan brought to life. He was Vivasvan's envoy, at your glad carouse-the weIl-loved friend of Yama, Thou art waxing great.\n\np: At offers they adore thee, Agni, when the rite proceeds. All fair and lovely treasure.s-at your glad carouse-thou givest him who offers. Thou art waxing great.\n\np: Men, Agni, have established thee as welcome Monk at holy rites, thee whose face shines with butter.at your glad carouse-bright, with eyes most observant. Thou art waxing great.\n\np: Wide and aloft thou spreadest thee, O Agni, with thy brilliant flame. A Bull art thou when bellowing.at your glad carouse-thou dost impregn the Sisters. Thou art waxing great.","people":["Agni","Vivasvan","Yama"],"places":[],"things":["Offering","Treasure","Wealth","Men","Grass","Gift","Offers","Offerings","Friend","Horses","Life"],"groups":["Immortal"],"concepts":["Life","Immortal","Holy","Offering","Offerings"],"hash":"md5-yg6yZ96zMKaPzXFYpsUxNQ==","created":"Monday, April 8, 2024 - 10:51:53 PM"},{"id":"9f7a1c0f-6f31-47cf-b6e2-aa3ed3f6cc02","key":"10022","book":"10","title":"HYMN XXII. Indra.","link":"https://indra.ai/rigveda/hymns/10022.html","text":"p: WHERE is famed Indra heard of? With what folk is he renowned to-day as Mitra is. Who in the home of Rsis and in secret is extolled with song?\n\np: Even here is Indra famed, and among us this day the glorious Thunderer is praised. He who like Mitra mid the folk hath won complete and full renown.\n\np: He who is Sovran Lord of great and perfect strength, exerter of heroic might, who bears the fearless thunder as a father bears his darling son.\n\np: Harnessing to thy car, as Deva, two blustering Steeds Of the Wind-Deva, O Thunderer, that speed along the shining path, thou making ways art glorified.\n\np: Even to these dark Steeds of Wind thou of thyself hast come to ride, Of which no drive. May be found, none, be he Deva.or mortal man.\n\np: When ye approach, men ask you, thee and Usana: Why come ye to our dwelling-place? Why are ye come to mortal man from distant realms of eapth and heaven?\n\np: O Indra, thou shalt speak us fair: our holy prayer is offered up. We meditate to thee for help as thou didst strike the monster Susna dead.\n\np: Around us is the Dasyu, riteless, void of sense, inhuman, keeping alien laws. Baffle, thou Slayer of the foe, the weapon which this Dasa wields.\n\np: Hero with Heroes, thou art ours: yea, strong are they whom thou dost help. In many a place are thy full gifts, and men, like vassals, sing thy praise.\n\np: Urge thou these heroes on to subdue the enemy, brave Thunderer! in the fight with swords. Even when hid among the tribes of Sages numerous as stars.\n\np: Swift come those gifts of thine whose hand is prompt to rend and burn, O Hero Thunder-armed: As thou with thy Companions didst destroy the whole of SuSnia's brood.\n\np: Let not thine excellent assistance come to us, O Hero Indra, profitless. May we. May we enjoy the bliss of these thy favours, Thunderer!\n\np: May those soft impulses of thine, O Indra, be fruitful and innocent to us. May we know these whose treasure.s are like those of milch-kine, Thunderer!\n\np: That Earth, through power of knowing things tha. May be known, handless and footless yet might thrive, Thou slewest, turning to the right, gu;na forevery living man.\n\np: Drink, drink the Soma. Hero Indra; be not withheld as thou art good, O Treasure-giver. Preserve the singers and our liberal princes, and make us wealthy with abundant riches.","people":["Indra","Soma","Mitra","Susna","Usana","Deva"],"places":["Earth","Heaven"],"things":["Steeds","Lord","Soma","Glorious","Treasure","Men","Might","Song","Help","Home","Strong","Car","Praise","Brave","Heroes","Excellent","Bliss","Hero","Riches","Gifts"],"groups":["Dasyu","Father","Son","Rsis","Man"],"concepts":["Good","Heroic","Holy","Strength","Giver","Glorious","Swift"],"hash":"md5-lRGKCVi8NjJZJCv8b4Frbw==","created":"Monday, April 8, 2024 - 10:51:53 PM"},{"id":"6803e646-b008-44bf-8109-9134827dcb33","key":"10023","book":"10","title":"HYMN XXIII. Indra.","link":"https://indra.ai/rigveda/hymns/10023.html","text":"p: INDRA, whose right hand wields the bolt, we worship, driver of Bay Steeds seeking sundered courses. Shaking his beard with might he hath arisen, casting his weapons forth and dealing bounties.\n\np: The treasure. which his Bay Steeds found at offering.this wealth made opulent Indra slayer of the foe. Rbhu, Rbhuksan, Vaja-he is Lord of Might. The Dasa's very name I utterly destroy.\n\np: When, with the Princes, Maghavari, famed of old, comes nigh the thunderbolt of gold, and the Controller's car Which his two Tawny Coursers draw, then Indra is the Sovran Lord of power whose glory spreads afar.\n\np: With him too is this rain of his that comes like herds: Indra throws drops of moisture on his yellow beard. When the sweet juice is shed he seeks the pleasant place, and stirs the worshipper as wind disturbs the wood.\n\np: We laud and praise his several deeds of valour who, fatherlike, with power hath made us stronger. Who with his voice slew many thousand wicked ones who spake in varied manners with contemptuous cries.\n\np: Indra, the Vimadas have formed for thee a laud, copious, unparalleled, for thee Most Bountiful. We know the good we gain from him the Mighty One when we attract him as a herdsman calls the kine.\n\np: Ne’e. May this bond of friendship be dissevered, the Rsi Vimada's and thine, O Indra. We know thou carest for us as a brother with us, O Deva, be thine auspicious friendship.","people":["Indra","Rbhu","Deva","Vimada","Vaja","Rbhuksan"],"places":[],"things":["Worship","Tawny Coursers","Steeds","Lord","Glory","Offering","Treasure","Wealth","Might","Juice","Rain","Gold","Mighty","Car","Praise","Voice","Worshipper","Drops"],"groups":["Brother"],"concepts":["Good","Friendship","Offering","Auspicious"],"hash":"md5-qqgvm834K2MSk2DwUbv0kA==","created":"Monday, April 8, 2024 - 10:51:53 PM"},{"id":"38b2d696-9932-4adc-ac53-a51324468989","key":"10024","book":"10","title":"HYMN XXIV. Indra. Asvins.","link":"https://indra.ai/rigveda/hymns/10024.html","text":"p: O INDRA, drink this Soma, pressed out in the mortar, full of sweets. Send down to us great riches.at your glad carouse-in thousands, O Most healthy. Thou art waxing great.\n\np: To thee with offeringss, with oblations, and with lauds we come. Lord of all strength and power, grant-at your glad carouse-the best choiceworthy treasure.. Thou art waxing great.\n\np: Thou who art Lord of precious boons, inciter even of the churl. Guardian of singers, indra.at your glad carouse-save us from woe and hatred. Thou art waxing great.\n\np: Strong, Lords of Magic power, ye Twain churned the united worlds apart, when ye, implored by Vimada, Nasatyas, forced apart the pair.\n\np: When the united pair were rent asunder all the Devas complained. The Devas to the Nasatyas cried, Bring these together once again.\n\np: Sweet be my going forth, and rich in sweets be my approach to home. So, through your Deity, both Devas, enrich us with all pleasantness.","people":["Indra","Soma","Nasatyas","Vimada"],"places":[],"things":["Lord","Soma","Treasure","Home","Strong","Riches"],"groups":["Devas"],"concepts":["Strength"],"hash":"md5-Os9HculI1YkcpQkWNbfPRQ==","created":"Monday, April 8, 2024 - 10:51:53 PM"},{"id":"1cf3183f-475d-4259-bdd2-2c5fefa7cebd","key":"10025","book":"10","title":"HYMN XXV. Soma.","link":"https://indra.ai/rigveda/hymns/10025.html","text":"p: SEND us a good and happy mind, send energy and mental power. Then-at your glad carouse-let men joy in thy love, Sweet juice! as kine in pasture. Thou. art waxing great.\n\np: rn all thy forms, O Soma, rest thy powers that influence the heart. So also these my longings-at your glad carouse-spread themselves seeking riches. Thou art waxing great.\n\np: Even if, O Soma, I neglect thy laws through my simplicity, be gracious-at your glad carouse-as sire to son. Preserve us even from slaughter. T'hou. art waxing great.\n\np: Our songs in concert go to thee as streams of water to the wells. Soma, that we may live, grant-at your glad carouse-full powers of mind, like beakers. Thou art waxing great.\n\np: O Soma, through thy might who art skilful and strong, these longing men, these sages, have thrown open-at your glad carouse-the stall of kine and horses. Thou art waxing great\n\np: Our herds thou guardest, Soma, and the moving world spread far and wide. Thou fittest them for living.at your glad carouse-looking upon all beings. Thou art waxing great.\n\np: On all sides, Soma, be to us a Guardian ne’er to be deceived. King, drive away our foemen-at your glad carouse:—let not the wicked rule us. Thou art waxing great.\n\np: Be watchful, Soma, passing wise, to give us store of vital strength. More skilled than man to guide us.at your glad carouse-save us from harm and sorrow. Thou art waxing great.\n\np: Chief slayer of our foemen Indu, art Indra's gracious Friend, when warriors invoke him-at your glad carouse -in fight, to win them offspring. Thou art waxing great.\n\np: Victorious is this gladdening drink: to Indra dear it grows in strength. This-at your glad carouse -enhanced the mighty hymn of the great sage Kaksivan. Thou art waxing great.\n\np: This to the sage who offers gifts brings power that comes from wealth in kine. This, better than the seven, hath-at your glad carouse-furthered the blind, the cripple. Thou art waxing great.","people":["Indu","Indra","Soma","Kaksivan"],"places":[],"things":["Soma","Water","Wealth","Men","Streams","Might","Juice","Joy","Wise","Offspring","Strong","Mighty","Chief","Hymn","Offers","Powers","Songs","Friend","King","Sage","Horses","Riches","Gifts"],"groups":["Son","Man"],"concepts":["Good","Love","Strength"],"hash":"md5-0YwCGXBudLPNhlrUCDjCqA==","created":"Monday, April 8, 2024 - 10:51:53 PM"},{"id":"c4d78d54-4f7a-4ac3-8d4f-85caad7e738b","key":"10026","book":"10","title":"HYMN XXVI. Pusan.","link":"https://indra.ai/rigveda/hymns/10026.html","text":"p: FORWARD upon their way proceed the ready teams, the lovely songs. Further them glorious Pusan with yoked chariot, and the Mighty Twain!\n\np: With sacred hymns let this man here, this singer, win the Deva.to whom Belong this majesty and might. He hath observed our eulogies.\n\np: Pusan the Strong hath knowledge of sweet praises even as Indu hath. He dews our corn with moisture, he bedews the pasture of our kine.\n\np: We will bethink ourselves of thee, O Pusan, O thou Deva, as One. Who brings fulfilment of our hymns, and stirs the singer and the sage.\n\np: joint-sharer of each offering, the driver of the chariot steeds; The Rsi who is good to man, the singer's Friend and faithful Guard.\n\np: One who is Lord of Suca, Lord of Suca caring for herself: Weaving the raiment of the sheep and making raiment beautiful.\n\np: The mighty Lord of spoil and wealth, Strong Friend of all prosperity; He with light movement shakes his beard, lovely and ne’er to be deceived.\n\np: O Pusan. May those goats of thine turn hitherward thy chariot-pole. Friend of all suppliants; art thou, born in old time, and arm and sure.\n\np: May the majestic Pusan speed our chariot with his power and might. May he increase our store of wealth and listen to this call of ours.","people":["Indu","Pusan","Deva"],"places":[],"things":["Steeds","Lord","Born","Glorious","Singer","Offering","Light","Wealth","Might","Strong","Mighty","Songs","Friend","Sage","call","spoil"],"groups":["Man"],"concepts":["Good","Beautiful","Sacred","Offering","Glorious"],"hash":"md5-MttcCBggPf2SyceSFaPZoQ==","created":"Monday, April 8, 2024 - 10:51:53 PM"},{"id":"dcbef9ad-e40e-4d9e-926b-b7cad7508b28","key":"10027","book":"10","title":"HYMN XXVII. Indra.","link":"https://indra.ai/rigveda/hymns/10027.html","text":"p: THIS, singer, is my firm determination, to aid the worshipper who pours the Soma. I subdue the man who brings no milkoblation, unrighteous, powerful, the truth's perverter.\n\np: Then Will I, when I lead my friends to battle against the radiant persons of the godless, prepare for thee at home a vigorous bullock, and pour for thee the fifteen-fold strong juices.\n\np: I know not him who sayeth and declareth that he hath slain the godless in the battle. Soon as they see the furious combat raging, men speak forth praises of my vigorous horses.\n\np: While yet my deeds of might were unrecorded, all passed for Maghavans though I existed. The potent one who dwelt in peace I conquered, grasped by the foot and slew him on the mountain.\n\np: None hinder me in mine heroic exploits, no, not the mountains when I will and purpose. Even the deaf will tremble at my roaring, and every day will dust be agitated.\n\np: To see the Indraless oblation-drinkers, mean offerers, o’ertaken by destruction! Then shall the fellies of my car pass over those who have blamed my joyous Friend and scorned him.\n\np: Thou wast, thou grewest to full vital vigour: an earlier s w, a later one shall see thee. Two canopies, as ’twere, are round about him who reacheth to the limit of this region.\n\np: The freed kine eat the barley of the pious. 1 s w them as they wandered with the herdsman. The calling of the pious rang around them. What portion will these kine afford their owner?\n\np: When we who cat the grass of men are gathered I am with barley-eaters in the corn-land. There shall the captor yoke the yokeless bullock, and he who hath been yoked seek one to loose him.\n\np: There wilt thou hold as true my spoken purpose, to bring together quadrupeds. and bipeds. I will divide, without a fight, his riches who warreth here, against the Bull, with women.\n\np: When a man's daughter hath been ever eyeless, who, knowing, will be wroth with her for blindness? Which of the two will loose on him his anger-the man who leads her home or he who woos her?\n\np: How many a maid is pleasing to the suitor who fain would marry for her splendid riches? If the girl be both good and fair of feature, she finds, herself, a friend among the people.\n\np: His feet have grasped: he eats the man who meets him. Around his head he sets the head for shelter. Sitting anear and right above he smites us, and follows earth that lies spread out beneath him.\n\np: High, leafless, shadowless, and swift is Heaven: the Mother stands, the Youngling, loosed, is feeding. Loud hath she lowed, licking Another's offspring. In what world hath the Cow laid down her udder?\n\np: Seven heroes from the nether part ascended, and from the upper part came eight together. Nine from behind came armed with winnowing-baskets: ten from the front pressed o’er the rock's high ridges.\n\np: One of the ten, the tawny, shared in common, they send to execute their final purpose. The Mother carries on her breast the Infant of noble form and soothes it while it knows not.\n\np: The Heroes dressed with fire the fatted wether: the dice were thrown by way of sport and gaming. Two reach the plain amid the heavenly waters, hallowing and with means of purifying.\n\np: Crying aloud they ran in all directions: One half of them will cook, and not the other. To me hath Savitar, this Deva, declared it: He will perform, whose food is wood and butter.\n\np: I s w a troop advancing from the distance moved, not by wheels but their own Deva.like nature. The Friendly One seeks human generations, destroying, still new bands of evil beings.\n\np: These my two Bulls, even Pramara's, are harnessed: drive them not far; here let them often linger. The waters even shall aid him to his object, and the all-cleansing Sun who is above us.\n\np: This is the thunderbolt which often whirleth down from the lofty misty realm of Surya. Beyond this realm there is another glory so through old age they pass and feel no sorrow.\n\np: Bound fast to,every tree the cow is lowing, and thence the man-consuming birds are flying, then all this world, though pressing juice for Indra and strengthening the Rsi, is affrighted.\n\np: In the Devas’ mansion stood the first-created, and from their separation came the later. Three warm the Earth while holding stores of water, and Two of these convey the murmuring moisture.\n\np: This is thy life: and do thou mark and know it. As such, hide not thyself in time of battle. He manifests the light and hides the vapour: his foot is never free from robes that veil it.","people":["Indra","Soma","Savitar","Deva","Surya"],"places":["Earth","Heaven"],"things":["Mountains","Soma","Waters","Water","Glory","Singer","Light","Sun","Food","Men","Might","Juice","Home","Offspring","Strong","Grass","Car","Worshipper","Heroes","Form","People","Friends","Friend","Cow","Horses","Riches","Dice","Life"],"groups":["Devas","Human","Maid","Mother","Man"],"concepts":["Good","Evil","Life","Heavenly","Heroic","Truth","Powerful","Swift","Noble"],"hash":"md5-7try+dxxHIxl1YhFWzEWxw==","created":"Monday, April 8, 2024 - 10:51:53 PM"},{"id":"7d672fa2-cb5d-471f-bc59-6b4b1f1d044a","key":"10028","book":"10","title":"HYMN XXVIII. Indra. Vasukra.","link":"https://indra.ai/rigveda/hymns/10028.html","text":"p: Now all my other friends are here assembled: my Sire-in-law alone hath not come hither. So might he eat the grain and drink the Soma, and, satisfied, return unto; his dwelling.\n\np: Loud belloweth the Bull whose horns are sharpened: upon the height above earth's breadth he standeth. That man I guard and save in all his troubles who fills my flanks when he hath shed the Soma.\n\np: Men with the stone press out for thee, O Indra, strong, gladdening Soma, and thereof thou drinkest. Bulls they dress for thee, and of these thou eatest when, Maghavan, with food thou art invited.\n\np: Resolve for me, O singer, this my riddle: The rivers send their swelling water backward: The fox steals up to the approaching lion: the jackal drives the wild-boar from the brus wood.\n\np: How shall I solve this riddle, I, the simple, declare the thought of thee the Wise and Mighty? Tell us, well knowing, as befits the season: Whitherward is thy prosperous car advancing?\n\np: Thus do they magnify me, me the mighty higher than even high heaven is my carpole. I all at once demolish many thousands: my Sire begot me with no foe to match me.\n\np: Yea, and the Devas have known me also, indra, as mighty, fierce and strong in every exploit. Exulting with the bolt I slaughtered Vrtra, and for the offerer oped with might the cow-stall.\n\np: The Deities approached, they carried axes; splitting the wood they came with their attendants. They laid good timber in the fire-receivers, and burnt the grass up where they found it growing.\n\np: The hare hath swallowed up the opposing razor: I sundered with a clod the distant mountain. The great will I make subject to the little: the calf shall wax in strength and cat the bullock.\n\np: There hath the strong-winged eagle left his talon, as a snared lion leaves the trap that caught him. Even the wild steer in his thirst is captured: the leather strap still holds his foot entangled.\n\np: May the leather strap their foot entangle who fatten on the offerings of the Brahman. They all devour the bulls set free to wander, while they themselves destroy their bodies' vigour.\n\np: They were well occupied with holy duties who sped in person with their lauds to Soma. Speaking like man, mete to us wealth and booty: in heaven thou hast the name and fame of Hero.","people":["Indra","Soma","Vrtra","Maghavan","Attendants"],"places":["Earth","Heaven"],"things":["Rivers","Soma","Water","Singer","Wealth","Food","Men","Might","Wise","Strong","Mighty","Grass","Car","Offerings","Friends","Hero","Cow"],"groups":["Devas","Deities","Man"],"concepts":["Good","Holy","Strength","Offerings"],"hash":"md5-UHnDF6R/FRwz1v+MLWXdKQ==","created":"Monday, April 8, 2024 - 10:51:53 PM"},{"id":"46921268-ddda-49c1-ac6a-4bb49ed3c2d0","key":"10029","book":"10","title":"HYMN XXIX. Indra.","link":"https://indra.ai/rigveda/hymns/10029.html","text":"p: As sits the young bird on the tree rejoicing, ye, swift Pair, have been roused by clear laudation, whose Herald-Monk through many days is Indra, earth's Guardian, Friend of men, the best of Heroes.\n\np: May we, when this Dawn and the next dance hither, be thy best servants, most heroic Hero! Let the victorious car with triple splendour bring hitherward the hundred chiefs with Kutsa.\n\np: What was the gladdening draught that pleased thee, indra? Speed through our doors to songs, for thou art mighty. Why comest thou to me, what gift attracts thee? Fain would I bring thee food most meet to offer.\n\np: Indra, what fame hath one like thee mid heroes? With what plan wilt thou act? Why hast thou sought us? As a true Friend, Wide-Strider! to sustain us, since food absorbs the thought of each among us.\n\np: Speed happily those, as Surya ends his journey, who meet his wish as bridegrooms meet their spouses; Men who present, O Indra strong by nature, with food the many songs that tell thy praises.\n\np: Thine are two measures, indra, wide-wellmeted, heaven for thy majesty, earth for thy wisdom. Here for thy choice are Somas mixed with butter. May the sweet meath be pleasant for thy drinking.\n\np: They have poured out a bowl to him, to Indra, full of sweet juice, for faithful is his bounty. O'er earth's expanse hath he grown great by wisdom, the Friend of man, and by heroic exploits.\n\np: Indra hath conquered in his wars, the Mighty: men strive in multitudes to win his friendship. Ascend thy chariot as it were in battle, which thou shalt drive to us with gracious favour.","people":["Indra","Kutsa","Surya","Dawn"],"places":["Earth","Heaven"],"things":["Meath","Journey","Food","Men","Juice","Strong","Mighty","Car","Heroes","Gift","Ascend","Splendour","Songs","Friend","Hero","Bird"],"groups":["Man","Spouses"],"concepts":["Friendship","Heroic","Wisdom","Swift","Pleased"],"hash":"md5-8mZrYUe+ZQeYbIJy4VbInw==","created":"Monday, April 8, 2024 - 10:51:53 PM"},{"id":"f0e6728e-2caf-458c-ae71-b4a35135cb90","key":"10030","book":"10","title":"HYMN XXX. Waters.","link":"https://indra.ai/rigveda/hymns/10030.html","text":"p: As ’twere with swift exertion of the spirit, let the Sage speed to the celestial Waters, the glorious food of Varuna and Mitra. To him who spreadeth far this laud I offer.\n\np: Adhvaryus, he ye ready with oblations, and come with longing to the longing Waters, Down on which looks the. purple-tinted Eagle. Pour ye that flowing wave this day, deft-handed.\n\np: Go to the reservoir, O ye Adhvaryus worship the Waters’ Child with your oblations. A consecrated wave he now will give you, so press for him the Soma rich in sweetness.\n\np: He who shines bright in floods, unfed with fuel, whom sages worship at their offers: Give waters rich in sweets, Child of the Waters, even those which gave heroic might to Indra:\n\np: Those in which Soma joys and is delighted, as a young man with fair and pleasant damsels. Go thou unto those Waters, O Adhvaryu, and purify with herbs what thou infusest.\n\np: So maidens bow before the youthful gallant who comes with love to them who yearn to meet him. In heart accordant and in wish one-minded are the Adhvaryus and the heavenly Waters.\n\np: He who made room for you when fast imprisoned, who freed you from the mighty imprecation. Even to that Indra send the meath-rich current, the wave that gratifies the Devas, O Waters.\n\np: Send forth to him the meath-rich wave, O Rivers, which is your offspring and a well of sweetness, Oil-balmed, to be implored at offers. Ye wealthy Waters, hear mine invocation.\n\np: Send forth the rapture-giving wave, O Rivers, which Indra drinks, which sets the Twain in motion; The well that springeth from the clouds, desirous, that wandereth triple-formed, distilling transport.\n\np: These winding Streams which with their double current, like cattle-raiders, seek the lower pastures. Waters which dwell together, thrive together, Queens, Mothers of the world, these, Rsi, honour.\n\np: Send forth  'our offering with holy worship send forth the hymn and prayer for gain of riches. For need of offering disclose the udder. Give gracious hearing to our call, O Waters.\n\np: For, wealthy Waters, ye control all treasure.s: ye bring auspicious intellect and Amrta. Ye are the Queens of independent riches Sarasvati give full life to the singer!\n\np: When I behold the Waters coming hither, carrying with them milk and mcath and butter, bearing the well-pressed Soma juice to Indra, they harmonize in spirit with Adhvaryus.\n\np: Rich, they are come with wealth for living beings, O friends, Adhvaryus, seat them in their places. Seat them on holy grass, ye Soma-bringers in harmony with the Offspring of the Waters.\n\np: Now to this grass are come the longing Waters: the Pious Ones are seated at our worship. Adbvaryus, press the Soma juice for Indra so will the service of the Devas be easy.","people":["Indra","Soma","Mitra","Varuna","Sarasvati"],"places":[],"things":["Worship","Meath","Milk","Rivers","Soma","Celestial Waters","Waters","Glorious","Singer","Offering","Treasure","Wealth","Food","Streams","Might","Juice","Offspring","Mighty","Grass","Reservoir","Hymn","Offers","Friends","Sage","call","Riches","Cattle","Life","Spirit","Amrta"],"groups":["Devas","Child","Man"],"concepts":["Celestial","Life","Heavenly","Heroic","Love","Holy","Offering","Auspicious","Glorious","Swift"],"hash":"md5-jbDwzJGRP+m8jLAj1AeQhQ==","created":"Monday, April 8, 2024 - 10:51:53 PM"},{"id":"92c4c682-c49e-440c-9ef8-92df620e8964","key":"10031","book":"10","title":"HYMN XXXI, Devas.","link":"https://indra.ai/rigveda/hymns/10031.html","text":"p: MAY benediction of the Devas approach us, holy, to aid us with all rapid assists. Therewit. May we be happily befriended, and pass triumphant over all our troubles.\n\np: A man should think on wealth and strive to win it by adoration on the path of Order, Counsel himself with his own mental insight, and grasp still nobler vigour with his spirit.\n\np: The hymn is formed, poured are the allotted portions: as to a ford friends come unto the Wondrous. We have obtained the power of case and comfort, we haVe become acquainted, with Immortals.\n\np: Pleased be the Eternal Lord who loves the household with this man whom Deva.Savitar created. May Bhaga Aryaman grace him with cattle. May he appear to him, and be, delightful.\n\np: Like the Dawns' dwelling-place be this assembly, where in their might men rich in food have gathered. Striving to share the praises of this singer. To us come strengthening and effectual riches!\n\np: This Bull's most gracious far-extended favour existed first of all in full abundance. By his support they are maintained in common who in the Asura's mansion dwell together.\n\np: What was the tree, what wood, in sooth, produced it, from which they fashioned forth the Earth and Heaven? These Twain stand fast and wax not old forever: these have sung praise to many a day and morning.\n\np: Not only here is this: more is beyond us. He is the Bull, the Heaven's and Earth's supporter. With power divine he makes his skin a filter, when the Bay Coursers bear him on as Surya.\n\np: He passes o’er the broad earth like a Stega: he penetrates the world as Wind the mist-cloud. He, balmed with oil, near Varuna and Mitra, like Agni in the wood, hath shot forth splendour.\n\np: When suddenly called the cow that erst was barren, she, self-protected, ended all her troubles. Earth, when the first son sprang from sire and mother, cast up the gami, that which men were seeking.\n\np: To Nrsad's son they gave the name of Kainva, and he the brown-hued courser won the treasure.. For him dark-coloured streamed the shining udder: none made it swell for him. Thus Order willed it.","people":["Agni","Mitra","Varuna","Savitar","Bhaga","Deva","Surya","Aryaman"],"places":["Earth","Heaven"],"things":["Lord","Singer","Treasure","Wealth","Food","Men","Might","Praise","Hymn","Splendour","Friends","Cow","Riches","Order","Morning","Cattle","Spirit"],"groups":["Devas","Asura","Dawns","Mother","Son","Man"],"concepts":["Divine","Holy","Pleased"],"hash":"md5-l9SZdJO2eGOdMgdQ0TpytQ==","created":"Monday, April 8, 2024 - 10:51:53 PM"},{"id":"11dbc626-139d-4181-9185-aa1c4d3ac8cf","key":"10032","book":"10","title":"HYMN XXXII. Indra.","link":"https://indra.ai/rigveda/hymns/10032.html","text":"p: FORTH speed the Pair to bring the meditating Deva, benevolent with boons sent in return for boons. May Indra graciously accept both gifts from us, when he hath knowledge of the flowing Soma juice.\n\np: Thou wanderest far, O Indra, through the spheres of light and realms of earth, the region, thou whom many praise! Let those who often bring their solemn rites conquer the noisy babblers who present no gifts.\n\np: More beautiful than beauty must this seem to me, when the son duly careth for his parents' line. The wife attracts the husband: with a shout of joy the man's auspicious marriage is performed aright.\n\np: This beauteous place of meeting have I looked upon, where, like MilchCows, the kine order the marriage train; Where the Herd's Mother counts as first and best of all, and round her are the seven-toned people of the choir.\n\np: The Pious One hath reached your place before the rest: One only moves victorious with the Rudras' band. To these your helpers pour our meath, Immortal Devas, with whom your song of praise hath power to win their gifts.\n\np: He who maintains the Laws of Deva.informed me that thou wast lying hidden in the waters. Indra, who knoweth well, beheld and showed thee. By him instructed am I come, O Agni.\n\np: The stranger asks the way of him who knows it: taught by the skilful guide he travels onward. This is, in truth, the blessing of instruction: he finds the path that leads directly forward.\n\np: Even now he breathed: these days hath he remembered. Concealed, he sucked the bosom of his Mother. Yet in his youth old age hath come upon him: he hath grown gracious, good, and free from anger.\n\np: O Kalasa, all these blessings will we bring them, O Kurusravana, who give rich presents. May he, O wealthy princes, and this Soma which I am bearing in my heart, reward you.","people":["Indra","Soma","Agni","Deva"],"places":["Earth"],"things":["Meath","Soma","Waters","Light","Juice","Song","Joy","Beauty","Blessing","Praise","People","Parents","Order","Gifts"],"groups":["Devas","Rudras","Mother","Son","Wife","Husband","Immortal","Man"],"concepts":["Good","Beautiful","Blessings","Immortal","Auspicious","Truth"],"hash":"md5-YK7NiqCwf8R9mzSVbRKt9g==","created":"Monday, April 8, 2024 - 10:51:53 PM"},{"id":"c6870f25-6008-47d3-8ca6-67a72d8be40a","key":"10033","book":"10","title":"HYMN XXXIII. Various Deities.","link":"https://indra.ai/rigveda/hymns/10033.html","text":"p: THE urgings of the people have impelled me, and by,the nearest way I bring you Pusan. The Universal Devas have brought me safely. The cry was heard, behold, Dubsasu cometh!\n\np: The ribs that compass me give pain and trouble me like rival wives. Indigence, nakedness, exhaustion press me sore: my mind is fluttering like a bird's.\n\np: As rats eat weavers' threads, cares are consuming me, thy singer, gatakratu, me. Have mercy on us once, O Indra, Bounteous Lord: be thou a Father unto us.\n\np: I the monks' Rsi chose as prince most liberal Kurusravana, the son of Trasadasyu's son,\n\np: Whose three bays harnessed to the car bear me straight onward: I will laud The giver of a thousand meeds,\n\np: The sire of Upamasravas, even him whose words were passing sweet, as a fair field is to its lord.\n\np: Mark, Upamasravas, his son, mark, grandson of Mitratithi: I am thy father's eulogist.\n\np: If I controlled Immortal Devas, yea, even were I Lord of men, My liberal prince were living still.\n\np: None lives, even had he hundred lives, beyond the statute of the Devas So am I parted from my friend.","people":["Indra","Pusan"],"places":[],"things":["Lord","Singer","Men","Car","People","Friend","Bird"],"groups":["Devas","Father","Son","Immortal","Monks"],"concepts":["Immortal","Giver"],"hash":"md5-evNgPEUxhNV/6uvZBDzurg==","created":"Monday, April 8, 2024 - 10:51:53 PM"},{"id":"05681433-b580-48a3-b863-ca87b77a07cc","key":"10034","book":"10","title":"HYMN XXXIV. Dice, Etc.","link":"https://indra.ai/rigveda/hymns/10034.html","text":"p: SPRUNG from tall trees on windy heights, these rollers transport me as they turn upon the table. Dearer to me the die that never slumbers than the deep draught of Mujavan's own Soma.\n\np: She never vexed me nor was angry with me, but to my friends and me was ever gracious. For the die's sake, whose single point is final, mine own devoted wife I alienated.\n\np: My wife holds me aloof, her mother hates me: the wretched man finds none to give him comfort. As of a costly horse grown old and feeble, I find not any profit of the gamester.\n\np: Others caress the wife of him whose riches the die hath coveted, that rapid courser: Of him speak father, mother, brothers saying, We know him not: bind him and take him with you.\n\np: When I resolve to play with these no longer, my friends depart from me and leave me lonely. When the brown dice, thrown on the board, have rattled, like a fond girl I seek the place of meeting.\n\np: The gamester seeks the GamblingHouse, and wonders, his body all afire, shall I be lucky? Still do the dice extend his eager longing, staking his gains against his adversary.\n\np: Dice, verily, are armed with goads and driving-hooks, deceiving and tormenting, causing grievous woe. They give frail gifts and then destroy the man who wins, thickly anointed with the player's fairest good.\n\np: Merrily sports their troop, the three-and-fifty, like Savitar the Deva whose ways are faithful. They bend not even to the mighty's anger: the King himself pays homage and reveres them.\n\np: Downward they roll, and then spring quickly upward, and, handless, force the man with hands to serve them. Cast on the board, like lumps of magic charcoal, though cold themselves they burn the heart to ashes.\n\np: The gambler's wife is left forlorn and wretched: the mother mourns the son who wanders homeless. In constant fear, in debt, and seeking riches, he goes by night unto the home of others.\n\np: Sad is the gambler when he sees a matron, another's wife, and his well-ordered dwelling. He yokes the brown steeds in the early morning, and when the fire is cold sinks down an outcast.\n\np: To the great captain of your mighty army, who hath become the host's imperial leader, to him I show my ten extended fingers: I speak the truth. No wealth am I withholding.\n\np: Play not with dice: no, cultivate thy corn-land. Enjoy the gain, and deem that wealth sufficient. There are thy cattle there thy wife, O gambler. So this good Savitar himself hath told me.\n\np: Make me your friend: show us some little mercy. Assail us not with your terrific fierceness. Appeased be your malignity and anger, and let the brown dice snare some other captive.","people":["Soma","Savitar","Deva","Gambler","Matron","Captain"],"places":["GamblingHouse"],"things":["Leader","Steeds","Soma","Wealth","Home","Mighty","Friends","Friend","King","Horse","Riches","Morning","Cattle","Dice","Board","Gifts"],"groups":["Father","Mother","Son","Wife","Man"],"concepts":["Good","Truth"],"hash":"md5-UqWe9k8wjib0BuW8FqTaOA==","created":"Monday, April 8, 2024 - 10:51:53 PM"},{"id":"2b2176d5-57f0-45e1-a20a-1b66ad910ef7","key":"10035","book":"10","title":"HYMN XXXV, Devas.","link":"https://indra.ai/rigveda/hymns/10035.html","text":"p: THESE fires associate with Indra are awake, bringing their light when first the Dawn begins to shine. May Heaven and Earth, great Pair, observe our holy work. We claim for us this day the favour of the Devas.\n\np: Yea, for ourselves we claim the grace of Heaven and Earth, of Saryanavan, of the Hills and Mother Streams. For innocence we pray to Surya and to Dawn. May the flowing Soma bring us bliss to-day.\n\np: May the great Twain, the Mothers. Heaven and Earth, this day preserve us free from sin for peace and happiness. May Morning sending forth her light drive sin afar. We meditate to kindled Agni for felicity.\n\np: May this first Dawn bring us the host of gracious Devas: rich. May it richly shine for us who strive for wealth. The wrath of the malignan. May we keep afar. We meditate to kindled Agni for feilicity.\n\np: Dawns, who come forward with the bright beams of the Sun, and at your earliest flushing bring to us the light, Shine ye on us to-day auspicious, for renown. We meditate to kindled Agni for felicity.\n\np: Free from all sicknes. May the Mornings come to us, and let our fires mount upward with a lofty blaze. The Asvin Pair have harnessed their swift-moving car. We meditate to kindled Agni for felicity.\n\np: Send us to-day a portion choice and excellent, O Savitar, for thou art he who dealeth wealth. I cry to Dhisana, Mother of opulence. We meditate to kindled Agni for felicity.\n\np: Further me this declaring of Eternal Law, the Law of Devas, as we mortals acknowledge it! The Sun goes up beholding all the rays of morn. We meditate to kindled Agni for felicity.\n\np: This day we pray with innocence in strewing grass, adjusting pressing-stones, and perfecting the hymn. Thou in the Adityas’ keeping movest restlessly. We meditate to kindled Agni for felicity.\n\np: To our great holy grass I bid the Devas at morn to banquet, and will seat them as the seven monks. Varuna, indra, Mitra, Bhaga for our gain. We meditate to kindled Agni for felicity.\n\np: Come hither, O Adityas, for our perfect weal: accordant help  'our offering that we may thrive. Pusan, Narasamsa, Bhaga, both Asvins, and enkindled Agni we implore for happiness.\n\np: Adityas, Devas, vouchsafe that this our hom. May be praise-worthy, prosperous, our heroes' sure defence, for cattle, for our sons, for progeny, for life. We meditate to kindled Agni for felicity.\n\np: This da. May all the Maruts, all he near us with aid. May all our fires be well enkindled. May all Devas come to us with gracious favour. May spoil and wealth he ours, and all possessions.\n\np: He whom ye aid, O Deities, in battle, whom ye protect and rescue from affliction, who fears no danger at your milk-libation, -suc. May we be to feast the Devas, ye Mighty.","people":["Indra","Soma","Agni","Mitra","Varuna","Asvins","Narasamsa","Savitar","Dhisana","Pusan","Bhaga","Surya","Dawn"],"places":["Earth","Heaven"],"things":["Milk","Work","Soma","Offering","Shine","Light","Sun","Wealth","Streams","Help","Mighty","Grass","Car","Banquet","Praise","Hymn","Heroes","Excellent","Pressing-Stones","Bliss","spoil","Morning","Cattle","Life"],"groups":["Devas","Maruts","Sons","Deities","Dawns","Mother","Progeny","Adityas","Monks"],"concepts":["Life","Holy","Offering","Auspicious","Swift","Eternal Law"],"hash":"md5-ICuOTDmjqiDrdzyLu1IhNQ==","created":"Monday, April 8, 2024 - 10:51:53 PM"},{"id":"39dccf9d-b1d5-4e6b-9bda-014ba2dc0a6f","key":"10036","book":"10","title":"HYMN XXXVI, Devas.","link":"https://indra.ai/rigveda/hymns/10036.html","text":"p: THERE are the Dawn and Night, the grand and beauteous Pair, Earth. Heaven, and Varuna, Mitra, and Aryaman. Indra I call, the Maruts, Mountains, and the Floods, Adityas. Heaven and Earth, the Waters, and the Sky.\n\np: May Dyaus and Prthivi, wise, true to Holy Law, keep us in safety from distress and injury. Let not malignant Nirrti rule over us. We crave to-day this gracious favour of the Devas.\n\np: Mother of Mitra and of opulent Varuna. May Aditi preserve us safe from all distress. May we obtain the light of heaven without a foe. We crave this gracious favour of the Devas to-day.\n\np: May ringing press-stones keep the Raksasas afar, ill dream, and Nirrti, and each voracious fiend. May the Adityas and the Maruts shelter us. We crave this gracious favour of the Devas to-day.\n\np: Full flow libations; on our grass let Indra sit; Narasamsa the singer laud with Sama hymns! Wise be our hearts' imaginings that we may live. We crave this gracious favour of the Devas to-day.\n\np: Ye Asvins, make  'our offering ascend to heaven, and animate the rite that he may send us bliss, Offered with holy oil, with forward-speeding rein. We crave the gracious favour of the Devas to-day.\n\np: Hither I call the band of Maruts, swift to hear, great, purifying, bringing bliss, to he our Friends. May we increase our wealth to glorify our name. We crave this graciousfavour of the Devas to-day.\n\np: We bring the Stay of Life, who makes the waters swell, swift-hearing, Friend of Devas, who waits on offering. May we control that Power, Soma whose rays are bright. We crave this gracious favour of the Devas to-day.\n\np: Alive ourselves, with living sons, devoid of guilt. May we win this with winners by fair means to win. Let the prayer-haters bear our sin to every side. We crave this gracious favour of the Devas to-day.\n\np: Hear us, O ye who claim the worship of mankind, and give us, O ye Devas, the gift for which we meditate, Victorious wisdom, fame with heroes and with wealth. We crave to-day this gracious favour of the Devas.\n\np: We crave the gracious favour of the Devas to-day, great favour of great Devas, sublime and free from foes, that we may gain rich treasure. sprung from hero sons. We crave this gracious favour of the Devas to-day.\n\np: In great enkindled Agni's keeping, and, for bliss, free from all sin before Mitra and Varuna. May we share Savitar's best animating help. We crave this gracious favour of the Devas to-day.\n\np: All ye, the Devas whom Savitar the Father of truth, and Varuna and Mitra govern, Give us prosperity with hero children, and opulence in kine and various treasure..\n\np: Savitar, Savitar from cast and wes ward, Savitar, Savitar from north and southward, Savitar send us perfect health and comfort, Savitar let our days of life be lengthened!","people":["Indra","Soma","Agni","Mitra","Varuna","Asvins","Narasamsa","Savitar","Raksasas","Dawn","Aditi","Aryaman","Prthivi"],"places":["Earth","Heaven","Sky"],"things":["Worship","Mankind","Mountains","Soma","Waters","Singer","Offering","Light","Treasure","Wealth","Flow","Help","Wise","Grass","Heroes","Gift","Ascend","Libations","Friends","Bliss","Friend","Hero","call","Life"],"groups":["Devas","Dyaus","Maruts","Sons","Father","Mother","Adityas"],"concepts":["Life","Holy","Wisdom","Offering","Truth","Libations","Swift"],"hash":"md5-DakTOO7GCRJ4Wyc6vqWc5Q==","created":"Monday, April 8, 2024 - 10:51:53 PM"},{"id":"6725f41d-cbb7-458d-b176-0b3bb6ca3a5f","key":"10037","book":"10","title":"HYMN XXXVII. Surya.","link":"https://indra.ai/rigveda/hymns/10037.html","text":"p: Do homage unto Varuna's and Mitra's Eye: offer this solemn worship to the Mighty Deva, who seeth far away, the Ensign, born of Devas. Sing praises unto Surya, to the Son of Dyaus.\n\np: May this my truthful speech guard me on every side wherever heaven and earth and days are spread abroad. All else that is in motion finds a place of rest: the waters ever flow and ever mounts the Sun.\n\np: No godless man from time remotest draws thee down when thou art driving forth with winged dappled Steeds. One lustre waits upon thee moving to the cast, and, Surya, thou arisest with a different light.\n\np: O Surya, with the light whereby thou scatterest gloom, and with thy ray impellest every moving thing, Keep far from us all feeble, worthless offering, and drive away disease and every evil dream.\n\np: Sent forth thou guardest well the Universe's law, and in thy wonted way arisest free from wrath. When Surya, we address our meditations to thee to-day. May the Devas favour this our purpose and desire.\n\np: This invocation, these our word. May Heaven and Earth, and Indra and the Waters and the Maruts hear. Ne’e. May we suffer want in presence of the Sun, and, living happy lives. May we attain old age.\n\np: Cheerful in spirit, evermore, and keen of sight, with store of children, free from sickness and from sin, Long-living. May we look, O Surya, upon thee uprising day by day, thou great as Mitra is!\n\np: Surya. May we live long and look upon thee still, thee, O Far-seeing One, bringing the glorious light, the radiant Deva, the spring of joy to every eye, as thou art mounting up o’er the high shining flood.\n\np: Thou by whose lustre all the world of life comes forth, and by thy beams again returns unto its rest, O Surya with the golden hair, ascend for us day after day, still bringing purer innocence.\n\np: Bless us with shine, bless us with perfect daylight, bless us with cold, with fervent heat and lustre. Bestow on us, O Surya, varied riches, to bless us in our home and when we travel.\n\np: Devas, to our living creatures of both kinds vouchsafe protection, both to bipeds and to quadrupeds, that the, may drink and eat invigorating food. So grant us health and strength and perfect innocence.\n\np: If by some grievous sin we have provoked the Devas, O Deities, with the tongue or thoughtlessness of heart, that guilt, O Vasus, lay upon the Evil One, on him who ever leads us into deep distress.","people":["Indra","Mitra","Varuna","Deva","Surya"],"places":["Earth","Heaven"],"things":["Worship","Steeds","Born","Waters","Glorious","Offering","Shine","Light","Sun","Food","Flow","Joy","Home","Mighty","Ascend","Riches","Life","Spirit"],"groups":["Devas","Dyaus","Maruts","Deities","Son","Man","Vasus"],"concepts":["Evil","Life","Strength","Offering","Truthful","Glorious","Speech"],"hash":"md5-CNL109arDKZJMvk9eXU2Iw==","created":"Monday, April 8, 2024 - 10:51:53 PM"},{"id":"0308d355-853a-44f0-b580-9ca646213911","key":"10038","book":"10","title":"HYMN XXXVIII. Indra.","link":"https://indra.ai/rigveda/hymns/10038.html","text":"p: O INDRA, in this battle great and glorious, in this loud din of war help us to victory, Where in the strife for kine among bold ring-decked men arrows fly all around and heroes are subdued.\n\np: At home disclose to us opulence rich in food, streaming with milk, O Indra, meet to be renowned. Sakra. May we be thine, the friendly Conqueror's: even as we desire, O Vasu, so do thou.\n\np: The godless man, much-lauded Indra, whether he be Dasa or be Arya, who would war with us. Easy to conquer he for thee, with us, these foes: with the, may we subdue them in the clash of fight.\n\np: Him who must be invoked by many and by few, who standeth nigh with comfort in the war of men, indra, famed Hero, winner in the deadly strife, let us bring hitherward to-day to favour us.\n\np: For, indra, I have heard thee called Self. capturer, One, Steer! who never yields, who urges even the churl. Release thyself from Kutsa and come hither. How shall one like thee sit still bound that h. May not move?","people":["Indra","Sakra","Kutsa","Vasu"],"places":[],"things":["Victory","Milk","Glorious","Food","Men","Help","Home","Heroes","Hero"],"groups":["Man"],"concepts":["Glorious","Winner"],"hash":"md5-/H7ImiOckYhmx88piG+6Gg==","created":"Monday, April 8, 2024 - 10:51:53 PM"},{"id":"0baf89f4-163f-46da-99bd-62419f6f8f45","key":"10039","book":"10","title":"HYMN XXXIX. Asvins.","link":"https://indra.ai/rigveda/hymns/10039.html","text":"p: As ’twere the name of father, easy to invoke, we all assembled here invoke this Car of yours, Asvins, your swiftly-rolling circumambient Car which he who worships must invoke at eve and dawn.\n\np: Awake all pleasant strains and let the hymns flow forth: raise up abundant fulness: this is our desire. Asvins, bestow on us a glorious heritage, and give our princes treasure. fair as Soma is.\n\np: Ye are the bliss of her who groweth old at home, and helpers of the slow although he linger last. Men call you too, Nasatyas, healers of the blind, the thin and feeble, and the man with broken bones.\n\np: Ye made Cyavana, weak and worn with length of days, young again, like a car, that he had power to move. Ye lifted up the son of Tugra from the floods. At our libations must all these your acts be praised.\n\np: We will declare among the folk your ancient deeds heroic; yea, ye were Physicians bringing health. You, you who must be lauded, will we bring for aid, so that this foe of ours, O Asvins. May believe.\n\np: Listen to me, O Asvins; I have cried to you. Give me-your aid as sire and mother aid their son. Poor, without kin or friend or ties of blood am I. Save me before it be too late, from this my curse.\n\np: Ye, mounted on your chariot brought to Vimada the comely maid of Purumitra as a bride. Ye, came unto the calling of the weakling's dame, and granted noble offspring to the happy wife.\n\np: Ye gave a ain the vigour of his youthful life to tge sage Kali when old age was coming nigh. Ye rescued Vandana and raised him from the pit, and in a moment gave Vispala power to move.\n\np: Ye Asvins Twain, endowed with manly strength, brought forth Reblia when hidden in the cave and well-nigh dead, freed Saptavadliri, and for Atri caused the pit heated with fire to be a pleasant resting-place.\n\np: On Pedu ye bestowed, Asvins, a courser white, mighty with nine-and-ninety varied gifts of strength, a horse to be renowned, who bore his friend at speed, joy-giving, Bhaga-like to be invoked of men.\n\np: From no side, ye Two Kings whom non. May check or stay, doth grief, distress, or danger come u on the man Whom, Asvins swift to hear, borne on your glowing path, ye with your Consort make the foremost in the race.\n\np: Come on that Chariot which the Rbhus wrought for you, the Chariot, Asvins, that is speedier than thought, At harnessing whereof Heaven's Daughter springs to birth, and from Vivasvan come auspicious Night and Day.\n\np: Come, Conquerors of the sundered mountain, to our home, Asvins who made the cow stream milk for Sayu's sake, Ye who delivered even from the wolf's deep throat and set again at liberty the swallowed quail.\n\np: We have prepared this laud for you, O Asvins, and, like the Bhrgus, as a car have framed it, have decked it as a maid to meet the bridegroom, and brought it as a son, our stay forever.","people":["Soma","Asvins","Nasatyas","Bhaga","Vivasvan","Atri","Tugra","Dawn","Vimada","Reblia","Sayu"],"places":["Heaven","Vispala"],"things":["Milk","Soma","Glorious","Treasure","Men","Stream","Flow","Joy","Home","Offspring","Mighty","Car","Libations","Bliss","Friend","Sage","Cow","Horse","call","Life","Gifts"],"groups":["Bhrgus","Kings","Maid","Father","Mother","Son","Wife","Man","Rbhus"],"concepts":["Birth","Life","Heroic","Strength","Auspicious","Glorious","Libations","Circumambient","Swift","Noble"],"hash":"md5-ELHxB7XyzK4cesBmT1lqdg==","created":"Monday, April 8, 2024 - 10:51:54 PM"},{"id":"66bbab45-9388-499e-b2ff-4690dc9f3c3d","key":"10040","book":"10","title":"HYMN XL. Asvins.","link":"https://indra.ai/rigveda/hymns/10040.html","text":"p: YOUR radiant Chariot-whither goes it on its way?-who decks it for you. Heroes, for its happy course, Starting at daybreak, visiting each morning every house, borne hitherward through prayer unto  'the offering?\n\np: Where are ye, Asvins, in the evening, where at morn? Where is your haltingplace, where rest ye for the night? Who brings you homeward, as the widow bedward draws his brother, as the bride attracts the groom?\n\np: Early ye sing forth praise as with a herald's voice, and, meet for worship, go each morning to the house. Whom do ye ever bring to ruin? Unto whose libations come ye. Heroes, like two Sons of Kings?\n\np: Even as hunters follow two wild elephants, we with oblations call you down at morn and eve. To folk who pay you offierings at appointed times, Chiefs ye bring food to strengthen them.\n\np: To you, O Asvins, came the daughter of a King, Ghosa, and said, O Heroes, this I beg of you: Be near me in the day, he near me in the night: help me to gain a car-borne chieftain rich in steeds.\n\np: O Asvins, ye are wise: as Kutsa comes to men, bring your car nigh the folk of him who sings your praise. The bee, O Asvins, bears your honey in her mouth, as the maid carries it purified in her hand.\n\np: To Bhujyu and to Vasa ye come near with help, O Asvins, to Sinjara and to Usana. Your worshipper secures your friendship for himself. Through your protection I desire felicity.\n\np: Krsa and Sayu ye protect, ye Asvins Twain: ye Two assist the widow and the worshipper; And ye throw open, Asvins, unto those who win the cattle-stall that thunders with its serenfold mouth.\n\np: The Woman hath brought forth, the Infant hath appeared, the plants of wondrous beauty straightway have sprung up. To him the rivers run as down a deep descent, and he this day becomes their master and their lord.\n\np: They mourn the living, cry aloud, at offering: the men have set their thoughts upon a distant cast. A lovely thing for fathers who have gathered here.a joy to husbands.are the wives their arms shall clasp\n\np: Of this we have no knowledge. Tall it forth to us, now the youth rests within the chambers of the bride. Fain would we reach the dwelling of the vigorous Steer who loves the kine, O Asvins: this is our desire.\n\np: Your favouring grace hath come, ye Lords of ample wealth: Asvins, our longings are stored up within your hearts. Ye have become our twofold guard. May we as welcome friends reach Aryaman's abode.\n\np: Even so, rejoicing in the dwelling-place of man, give hero sons and riches to the eloquent. Make a ford where men wel. May drink: remove the spiteful tree-stump standing in the path.\n\np: O Asvins, Wonder-Workers, Lords of lustre, where and with what folk do ye delight yourselves to-day? Who hath detained them with him? Whither are they gone? Unto what sage's or what worshipper's abode?","people":["Asvins","Usana","Kutsa","Sayu","Aryaman"],"places":[],"things":["Worship","Master","Steeds","Lord","Rivers","Offering","Wealth","Food","Men","Joy","Beauty","Help","Wise","Car","Praise","Voice","Worshipper","Delight","Heroes","Libations","Friends","Hero","King","Sage","call","Riches","Morning","Cattle"],"groups":["Fathers","Sons","Kings","Maid","Brother","Man","Woman"],"concepts":["Wonder-Workers","Friendship","Offering","Libations"],"hash":"md5-+SlubGHN+ZdIlKE6dt67QQ==","created":"Monday, April 8, 2024 - 10:51:54 PM"},{"id":"ea7c12a9-25f3-47f0-afca-433e41271f3a","key":"10041","book":"10","title":"HYMN XLI. Asvins.","link":"https://indra.ai/rigveda/hymns/10041.html","text":"p: THAT general Car of yours, invoked by many a man, that comes to our libations, three-wheeled, meet for lauds, that circumambient Car, worthy of offering, we call with our pure hymns at earliest flush of dawn.\n\np: Ye, O Nasatyas, mount that early-harnessed Car, that travels early, laden with its freight of balm, Wherewith ye. Heroes, visit clans who offering, even the poor man's worship where the Sage attends.\n\np: If to the deft Adhvaryu with the meath in hand, or to the Kindler firm in strength, the household friend, or to the sage's poured libations ye approach, come thence, O Asvins, now to drink the offered meath.","people":["Asvins","Nasatyas","Dawn"],"places":[],"things":["Worship","Meath","Offering","Car","Heroes","Libations","Friend","Sage","call"],"groups":["Man"],"concepts":["Strength","Offering","Libations","Circumambient"],"hash":"md5-hDvgSCK7kiGSUja5zPrWqA==","created":"Monday, April 8, 2024 - 10:51:54 PM"},{"id":"31c447f3-4abf-4209-95d8-2828aeedb069","key":"10042","book":"10","title":"HYMN XLII. Indra.","link":"https://indra.ai/rigveda/hymns/10042.html","text":"p: EVEN as an archer shoots afar his arrow, offer the laud to him with meet adornment. Quell with your voice the wicked's voice, O sages. Singer, make Indra rest beside the Soma.\n\np: Draw thy Friend to thee like a cow at milking: O Singer, wake up Indra as a lover. Make thou the Hero haste to give us riches even as a vessel filled brimful with treasure..\n\np: Why, Maghavan, do they call thee Bounteous; Giver? Quicken me: thou, I hear, art he who quickens. Sakra, let my intelligence be active, and bring us luck that finds great wealth, O Indra.\n\np: Standing, in battle for their rights, together, the people, indra, in the fray invoke thee. Him who brings gifts the Hero makes his comrade: with him who pours no juice he seeks not friendship.\n\np: Whoso with plenteous food for him expresses strong Somas as much quickly-coming treasure., for him he overthrows in early morning his swift well-weaponed foes, and subdues the tyrant.\n\np: He unto whom we offer praises, indra, Maghavan, who hath joined to ours his wishes. Before him even afar the foe must tremble: low before him must bow all human glories.\n\np: With thy fierce bolt, O Deva.invoked of many, drive to a distance from afar the foeman. O Indra, give us wealth in corn and cattle, and make thy singer's prayer gain strength and riches.\n\np: Indra, the swallower of strong libations rich in the boons they bring, the potent Somas. He, Maghavan, will not restrict his bounty he brings much wealth unto we.\n\np: Yea, by superior play he wins advantage, when he, a gambler, piles his gains in season. Celestial-natured, he o’erwhelms with riches the devotee who keeps not back his treasure..\n\np: O Much-invoked. May we subdue all famine and evil want with store of grain and cattle. May we allied, as first in rank, with princes obtain possessions by our own exertion.\n\np: Narasamsa protect us from the rearward, and from above, and from below, from sinners! May Indra from the front, and from the centre, as Friend to friends, vouchsafe us room and freedom.","people":["Indra","Soma","Sakra","Maghavan","Narasamsa","Deva","Gambler"],"places":[],"things":["Soma","Singer","Treasure","Wealth","Food","Juice","Strong","Voice","People","Libations","Friends","Friend","Hero","Cow","call","Riches","Morning","Cattle","Gifts"],"groups":["Human"],"concepts":["Celestial","Evil","Friendship","Strength","Giver","Libations","Swift","Intelligence"],"hash":"md5-UtvwAkjfd5laP5z1dms2dQ==","created":"Monday, April 8, 2024 - 10:51:54 PM"},{"id":"5172ded0-f16f-4f16-8677-2dd27e68213f","key":"10043","book":"10","title":"HYMN XLIII. Indra.","link":"https://indra.ai/rigveda/hymns/10043.html","text":"p: IN perfect unison all yearning hymns of mine that find the light of heaven have sung forth Indra's praise. As wives embrace their lord, the comely bridegroom, so they compass Maghavan about that h. May help.\n\np: Directed unto thee my spirit never strays, for I have set my hopes on thee, O Much-invoked! Sit, Wonderful! as King upon the sacred grass, and let thy drinking-place be by the Soma juice.\n\np: From indigence and hunger Indra turns away: Maghavan hath dominion over precious wealth. These the Seven Rivers flowing on their downward path increase the vital vigour of the potent Steer.\n\np: As on the fair-leafed tree rest birds, to Indra flow the gladdening Soma juices that the bowls contain. Their face that glows with splendour through their mighty power hath found the shine of heaven for man, the Aryas' light.\n\np: As in the game a gambler piles his winnings, so Maghavan, sweeping all together, gained the Sun This mighty deed of thine none other could achieve, none, Maghavan, before thee, none in recent time.\n\np: Maghavan came by turns to all the tribes of men: the Steer took notice of the people's songs of praise. The man in whose libations Sakra hath delight by means of potent Somas vanquisheth his foes.\n\np: When Soma streams together unto Indra flow like waters to the river, rivulets to the lake, in place of offering sages exalt his might, as the rain swells the corn by moisture sent from heaven.\n\np: He rushes through the region like a furious Bull, he who hath made these floods the dames of worthy lords. This Maghavan hath found light for the man who brings oblation, sheds the juice, and promptly pours his gifts.\n\np: Let the keen axe come forth together with the light: here be.as erst, the teeming cow of offering. Let the Red Deva.shine bright with his refulgent ray, and let the Lord of heroes glow like heaven's clear sheen.\n\np: O Much-invoked. May we subdue all famine and evil want with store of grain and cattle. May we allied, as first in rank, with princes obtain possessions by our own exertion.\n\np: Narasamsa protect us from the rearward, and from above, and from below, from sinners. May Indra from the front, and from the centre, as Friend to friends, vouchsafe us room and freedom.","people":["Indra","Soma","Sakra","Maghavan","Narasamsa","Deva","Gambler"],"places":["Heaven"],"things":["Lord","Rivers","Soma","Waters","Offering","Shine","Light","Sun","Wealth","Men","River","Streams","Flow","Might","Juice","Rain","Help","Mighty","Grass","Praise","Delight","Heroes","Lake","Splendour","People","Libations","Friends","Songs","Friend","King","Cow","Cattle","Spirit","Gifts"],"groups":["Dames","Man","Aryas"],"concepts":["Evil","Sacred","Offering","Libations"],"hash":"md5-AVfI7w0mNtyNp/Vf6XQhbw==","created":"Monday, April 8, 2024 - 10:51:54 PM"},{"id":"82d3b8eb-94f9-48be-b36c-dde0ef4c44a0","key":"10044","book":"10","title":"HYMN XLIV. Indra.","link":"https://indra.ai/rigveda/hymns/10044.html","text":"p: MAY Sovran Indra come to the carousal, he who by Holy Law is strong and active, the overcomer of all conquering forces with his great steer-like power that hath no limit.\n\np: Firm-seated is thy car, thy Steeds are docile; thy hand, O King, holds, firmly grasped, the thunder. On thy fair path, O Lord of men, come quickly: we will increase thy powers when thou hast drunken.\n\np: Let strong and mighty Steeds who bear this Mighty Indra, the Lord of men, whose arm wields thunder, Bring unto us, as sharers of our banquet, the Steer of conquering might, of real vigour.\n\np: So like a Bull thou rushest to the Lord who loves the trough, the Sage, the prop of vigour, in the vat, prepare thine energies, collect them in thyself: be for our profit as the Master of the wise.\n\np: May precious treasure.s come to us-so will I pray. Come to the votary's gift offered with beauteous laud. Thou art the Lord, as such sit on this holy grass: thy vessels are inviolate as Law commands.\n\np: Far went our earlist invocation of the Devas, and won us glories that can never be surpassed. They who could not ascend the ship of offering, sink down in desolation, trembling with alarm.\n\np: So be the others, evil-hearted, far away, whose horses, difficult to harness, have been yoked. Here in advance men stand anear to offer gifts, by whom full many a work that brings reward is done.\n\np: He firmly fixed the plains and mountains as they shook. Dyaus thundered forth and made the air's mid-region quake. He stays apart the two confronting bowls; he sings lauds in the potent Soma's joy when he hath drunk.\n\np: I bear this deftly-fashioned goad of thine, wherewith thou, Maghavan, shalt break the strikers with the hoof. At this libatio. Mayst thou be well satisfied. Partake the juice, partake the worship, Maghavan.\n\np: O Much-invoked. May we subdue all famine and evil want with store of grain and cattle. May we allied, as first in rank, with princes obtain possessions by our own exertion.\n\np: Narasamsa protect us from the rearward, and from above, and from below, from sinners. May Indra from the front and from the centre, as Friend to friends, vouchsafe us room and freedom.","people":["Indra","Soma","Maghavan","Narasamsa"],"places":[],"things":["Worship","Master","Steeds","Work","Lord","Mountains","Soma","Offering","Air","Treasure","Men","Might","Juice","Joy","Wise","Strong","Mighty","Grass","Car","Banquet","Gift","Ascend","Powers","Friends","Friend","King","Sage","Horses","Cattle","Gifts"],"groups":["Devas","Dyaus"],"concepts":["Evil","Holy","Offering"],"hash":"md5-2tB0z7Nf8tUzmmZtFr70hg==","created":"Monday, April 8, 2024 - 10:51:54 PM"},{"id":"bc0a3771-19b3-43b4-ab69-c2c029e812f9","key":"10045","book":"10","title":"HYMN XLV. Agni.","link":"https://indra.ai/rigveda/hymns/10045.html","text":"p: FIRST Agni sprang to life from out of Heaven: the second time from us came Jatavedas. Thirdly the Manly-souled was in the waters. The pious lauds and kindles him the Eternal.\n\np: Agni, we know thy three powers in three stations, we know thy forms in many a place divided. We know what name supreme thou hast in secret: we know the source from which thou hast proceeded.\n\np: The Manly-souled lit thee in sea and waters, man's Viewer lit thee in the breast of heaven, there as thou stoodest in the third high region the Steers increased thee in the water's bosom.\n\np: Agni roared out, like Dyaus what time he thunders: he licked the ground about the plants he flickered. At once, when born, he looked around enkindled, and lightened heaven and earth within with splendour.\n\np: The spring of glories and support of riches, rouser of thoughts and guardian of the Soma, Good Son of Strength, a King amid the waters, in forefront of the Dawns he shines enkindled.\n\np: Germ of the world, ensign of all creation, be sprang to life and filled the earth and heavens. Even the firm rock he cleft when passing over, when the Five Tribes brought offering to Agni.\n\np: So among mortals was Immortal Agni stablished as holy wise and willing envoy. He waves the red smoke that he lifts above him, striving to reach the heavens with radiant lustre.\n\np: Like gold to look on, far he shone refulgent, beaming imperishable life for glory, Agni by vital powers became immortal when his prolific Father Dyaus begat him.\n\np: Whoso this day, O Deva whose flames are lovely, prepares a cake, O Agni, mixt with butter, Lead thou and further him to higher fortune, to bliss bestowed by Devas, O thou Most Youthful.\n\np: Endow him, Agni, with a share of glory, at every song of praise sung forth enrich him. Dear let him be to Surya, dear to Agni, preeminent with son and children's children.\n\np: While, Agni, day by day men pay thee worship they win themselves all treasure.s worth the wishing. Allied with thee, eager and craving riches, they have disclosed the stable filled with cattle.\n\np: Agni, the Friend of men, the Soma's keeper, Vaisvanara, hath been lauded by the Rsis. We will invoke benignant Earth and Heaven: ye Deities, give us wealth with hero children.","people":["Soma","Agni","Deva","Vaisvanara","Surya"],"places":["Earth","Heaven"],"things":["Worship","Born","Soma","Waters","Water","Glory","Offering","Treasure","Wealth","Men","Song","Gold","Wise","Praise","Splendour","Powers","Bliss","Friend","Hero","King","Riches","Cattle","Life"],"groups":["Devas","Dyaus","Jatavedas","Deities","Dawns","Steers","Father","Son","Immortal","Rsis","Man"],"concepts":["Good","Life","Immortal","Holy","Strength","Offering"],"hash":"md5-sX56etq1BCnjlktotLnQ0Q==","created":"Monday, April 8, 2024 - 10:51:54 PM"},{"id":"dab55350-c372-495f-bc86-68d5c8b5f8ac","key":"10046","book":"10","title":"HYMN XLVI. Agni.","link":"https://indra.ai/rigveda/hymns/10046.html","text":"p: STABLISHED for thee, to lend thee vital forces, Giver of wealth, Guard of his servant's body. The Great Monk, born, who knows the clouds, Abider with men, is seated in the lap of waters.\n\np: Worshipping, seeking him with adoration like some lost creature. followed by its footprints, Wise Bhrgus, yearning in their hearts, pursued him, and found him lurking where the floods are gathered.\n\np: On the Cow's forehead, with laborious searching, Trita, the offspring of Vibhiavas, found him. Born in our houses, Youthful, joy-bestower, he now becomes the central point of brightness.\n\np: Yearning, with homage, they have set and made him blithe Monk among mankind, oblation-bearer, Leader of rites and Purifier, envoy of men, as offering that still advances.\n\np: The foolish brought the ne’er-bewildered forward, great, Victor, Song-inspirer, fort-destroyer. Leading the Youth gold-bearded, like a courser gleaming with wealth, they turned their hymn to profit.\n\np: Holding his station firmly in the houses, Trita sat down within his home surrounded Thence, as Law bids, departs the Tribes' Companion having collected men with no compulsion.\n\np: His are the fires, eternal, purifying, that make the houses move, whose smoke is shining, White, waxing in their strength, forever stirring, and sitting in the wood; like winds are Somas.\n\np: The tongue of Agni bears away the praisesong, and, through his care for Earth, her operations. Him, bright and radiant, living men have stablished as their blithe Monk, the Chief of Offerers.\n\np: That Agni, him whom Heaven and Earth engendered, the Waters. Tvastar, and with might, the Bhrgushim Matarisvan and the Devas have fashioned holy for man and first to be entreated.\n\np: Agni, whom Devas have made oblationbearer, and much-desiring men regard as holy, Give life to him who lauds thee when he worships, and then shall glorious men in troops adore thee.","people":["Agni","Tvastar","Trita","Matarisvan"],"places":["Earth","Heaven"],"things":["Mankind","Leader","Born","Waters","Glorious","Offering","Wealth","Men","Might","Song","Joy","Gold","Home","Wise","Offspring","Chief","Hymn","Cow","Life"],"groups":["Devas","Bhrgus","Man"],"concepts":["Life","Holy","Strength","Offering","Giver","Glorious"],"hash":"md5-gtx6btc0IeNf7x8GvPkyTA==","created":"Monday, April 8, 2024 - 10:51:54 PM"},{"id":"1bb98fef-f150-4c15-9260-c7419e9ca469","key":"10047","book":"10","title":"HYMN XLVII. Indra Vaikuntha.","link":"https://indra.ai/rigveda/hymns/10047.html","text":"p: THY right hand have we grasped in ours, O Indra, longing for treasure., Treasure-Lord of treasure.s! Because we know thee. Hero, Lord of cattle: vouchsafe us mighty and resplendent riches.\n\np: Wealth, fully armed, good guard and kind protector, sprung from four seas, the prop and stay of treasure.s, Fraught with great bounties, meet for praise and glory; vouchsafe us mighty and resplendent riches.\n\np: Wealth, with good Brahmans, indra! Deva.attended, high, wide, and deep, arid based on broad foundations, Strong, with famed Rsis, conquering our foemen: vouchsafe us mighty and resplendent riches.\n\np: Victorious, winning strength, with hero sages, confirmed in power, most useful, wealth-attracting, True, indra! crushing forts and subduing Dasyus: vouchsafe us mighty and resplendent riches.\n\np: Wealthy in heroes and in cars and horses, strength hundredfold and thousandfold, O Indra, with manly sages, happy troops, Iight-winning: vouchsafe us mighty and resplentdent riches.\n\np: To Saptagu the sage, the holy-minded, to him, Narasamsa, the song approaches, Angiras' Son who must be met with homage: vouchsafe us mighty and reslendent riches.\n\np: My lauds, like envoys, craving loving-kindness, go forth to Indra with their stron entreaty, Moving his heart and uttered by my spirit: vouchsafe us mighty and resplendent riches.\n\np: Grant us the boon for which I pray, O Indra, a spacious home unmatched among the people. To thi. May Heaven and Earth accord approval: vouchsafe us mighty and resplendent riches.","people":["Indra","Angiras","Narasamsa","Deva"],"places":["Earth","Heaven"],"things":["Lord","Glory","Treasure","Wealth","Boon","Song","Home","Strong","Mighty","Praise","Heroes","People","Hero","Sage","Horses","Winning","Riches","Cars","Cattle","Spirit"],"groups":["Dasyus","Brahmans","Son","Rsis"],"concepts":["Good","Cars","Holy","Strength"],"hash":"md5-rb0vASnyD5DrdLolaz8ZuA==","created":"Monday, April 8, 2024 - 10:51:54 PM"},{"id":"3032e2f8-8f74-4ed7-9bdc-c6e7f083bf30","key":"10048","book":"10","title":"HYMN XLVIII. Indra Vaikuntha.","link":"https://indra.ai/rigveda/hymns/10048.html","text":"p: I WAS the first possessor of all precious gear: the wealth of every man I win and gather up. On me as on a Father living creatures call; I deal enjoyment to tho. man who offers gifts.\n\np: I, indra, am Atharvan's stay and firm support: I brought forth kine to Trita from the Dragon's grasp. I stripped the Dasyus of their manly might, and gave the cattle-stalls to Matarigvan and Dadhyac.\n\np: For me hath Tvastar forged the iron thunderbolt: in me the Devas have centred intellectual power. My sheen is like the Sun's insufferably bright: men honour me as Lord for past and future deeds.\n\np: I won myself these herdi of cattle, steeds and kine, and gold in ample store, with my destructive bolt. I give full many a thousand to the worshipper, what time the Somas and the lauds have made me glad.\n\np: Indra am I non ever wins my wealth from me never at any time am I a thrall to death. Pressing the Soma, ask riches from me alone: ye, purus, in my friendship shall not suffer harm.\n\np: These, breathing loud in fury, two and two, who caused Indra to bring his bolt of thunder to the fray, the challengers, I struck with deadly weapon down: firm stand what words the Deva.speaks to his worshippers. This One by stronger might I conquered singly; yea, also two: shall three prevail against me? Like many sheaves upon the floor I thrash them. How can my foes, the Indraless, revile me?\n\np: Against the Gungus I made Atithigva strong, and kept him mid the folk like Vrtra-conquering strength, when I won glory in the great foe-subduing fight, in battle where Karanja fell, and Parnaya.\n\np: With food for mine enjoyment Sapya Nami came: he joined me as a friend of old in search of kine. As I bestowed on him an arrow for the fight I made him worthy of the song apd hymn of praise.\n\np: One of the two hath Soma, seen within it; the Herdsman with the bone shows forth the other. He, fain to fight the Bull whose horns were sharpened, stood fettered in the demon's ample region.\n\np: I, as a Deva, ne’er violate the statutes of Devas, of Vasus, Rudriyas, Adityas. These Devas have formed me for auspicious vigour, unconquered and invincible forever.","people":["Indra","Soma","Vrtra","Tvastar","Trita","Deva","Atithigva","Karanja"],"places":[],"things":["Steeds","Lord","Soma","Glory","Sun","Wealth","Food","Men","Might","Song","Gold","Strong","Praise","Worshipper","Hymn","Offers","Friend","call","Riches","Cattle","Death","Gifts"],"groups":["Devas","Dasyus","Worshippers","Father","Man","Vasus","Adityas"],"concepts":["Death","Friendship","Strength","Auspicious"],"hash":"md5-1ENUP1EKuRfGOXYhC2/fDw==","created":"Monday, April 8, 2024 - 10:51:54 PM"},{"id":"e529e18c-78f7-40a2-a36c-810e26b2a1ba","key":"10049","book":"10","title":"HYMN XLIX.Indra Vaikuntha.","link":"https://indra.ai/rigveda/hymns/10049.html","text":"p: I HAVE enriched the singer with surpassing wealth; I have allowed the holy hymn to strengthen me. I, furtherer of him who offers offering, have conquered in each fight the men who worship not.\n\np: The People of the heavens, the waters, and the earth have stablished me among the Devas with Indra's name. I took unto myself the two swift vigorous Bays that speed on divers paths, and the fierce bolt for strength.\n\np: With deadly blows I smote Atka for Kavi's sake; I guarded Kutsa well with these saving helps. As Susna's slayer I brandished the dart of death: I gave not up the Aryan name to Dasyu foes.\n\np: Smadibha, Tugra, and the Vetasus I gave as prey to Kutsa, father-like, to assist him. I was a worthy King to rule the worshipper, when I gave Tuji dear inviolable gifts.\n\np: I gave up Mrgaya to Srutarvan as his prey because he ever followed me and kept my laws. For Ayu's sake I caused Veta to bend and bow, and into Savya's hand delivered Padgrbhi.\n\np: 1, I crushed Navavastva of the lofty car, the Dasa, as the Vrtra conquerer kills the fiends; When straightway on the region's farthest edge I brought the Deva who makes the lights to broaden and increase.\n\np: I travel round about borne onward in my might by the fleet-footed dappled Horses of the Sun. When man's libation calls me to the robe of state I soon repel the powerful Dasyu with my blows.\n\np: Stronger am I than Nabus, I who slew the seven: I glorified with might Yadu and Turvaga. I brought another low, with strength I bent his strength: I let the mighty nine-and-ninety wax in power.\n\np: Bull over all the streams that flow along the earth, I took the Seven Rivers as mine own domain. I, gifted with great wisdom, spread the floods abroad: by war I found for man the way to high success.\n\np: I set within these cows the white milk which no Deva, not even Tvastar's self, had there deposited. Much-longed-for, in the breasts, the udders of the kine, the savoury sweets of meath, the milk and Soma juice.\n\np: Even thus hath Indra Maghavan, truly bounteous, sped Devas and men with mighty operation. The pious glorify all these thine exploits, Lord of Bay Coursers, Strong, and Selfresplendent.","people":["Indra","Soma","Vrtra","Yadu","Maghavan","Susna","Tvastar","Tugra","Kutsa","Deva","Ayu","Turvaga"],"places":["Earth"],"things":["Worship","Meath","Milk","Lord","Rivers","Soma","Waters","Singer","Offering","Sun","Wealth","Men","Streams","Flow","Might","Juice","Strong","Mighty","Car","Worshipper","Hymn","Offers","People","King","Horses","Death","Gifts"],"groups":["Devas","Dasyu","Father","Man"],"concepts":["Death","Holy","Strength","Wisdom","Offering","Powerful","Swift"],"hash":"md5-Cd6TGBWm4Ez1TtZJb5HW4g==","created":"Monday, April 8, 2024 - 10:51:54 PM"},{"id":"2408bb29-fcde-4414-8a2c-cfba0f4f1104","key":"10050","book":"10","title":"HYMN L. Indra Vaikuntha.","link":"https://indra.ai/rigveda/hymns/10050.html","text":"p: I LAUD your Mighty One who joyeth in the juice, him who is shared by all men, who created all; Indra, whose conquering strength is powerful in war, whose fame and manly vigour Heaven and Earth revere.\n\np: He with his friend is active, lauded, good to man, indra who must be glorified by one like me. Hero, Lord of the brave, all cars are thy delight, warring with Vrtra, or for waters, or for spoil.\n\np: Who are the men whom thou wilt further, indra, who strive to win thy bliss allied with riches? Who urged thee forward to exert thy power divine, to valour, in the war for waters on their fields?\n\np: Thou, indra, through the holy prayer art mighty, worthy of offering at all libations. In every fight thou castest heroes on the ground: thou art the noblest song, O Lord of all the folk.\n\np: Help now, as Highest, those who toil at offering: well do the people know thy great protecting might. Thou shalt be Everlasing, Giver of success yea, on all these libations thou bestowest strength.\n\np: All these libations thou makest effectual, of which thou art thyself supporter, Son of Power. Therefore thy vessel is to be esteemed the best, offering, holy text, prayer, and exalted speech.\n\np: They who with flowing Soma pray to thee, O Sage, to pour on them thy gifts of opulence and wealth, may they come forward, through their spirit, on the path of bliss, in the wild joy of Soma juice effused.","people":["Indra","Soma","Vrtra"],"places":["Earth","Heaven"],"things":["Lord","Soma","Waters","Offering","Wealth","Men","Might","Juice","Song","Joy","Help","Mighty","Brave","Delight","Heroes","People","Libations","Bliss","Friend","Hero","Sage","spoil","Riches","Cars","Spirit","Gifts"],"groups":["Son","Man"],"concepts":["Good","Divine","Cars","Holy","Strength","Offering","Giver","Libations","Powerful","Speech"],"hash":"md5-WyhgFHKnlXFWfDJgTAnQWA==","created":"Monday, April 8, 2024 - 10:51:54 PM"},{"id":"69d7c50b-4a91-44f2-88e0-4297dc1b842d","key":"10051","book":"10","title":"HYMN LI. Agni. Devas.","link":"https://indra.ai/rigveda/hymns/10051.html","text":"p: LARGE was that covering, and firm of texture, folded wherein thou enteredst the waters. One Deity alone, O Jatavedas Agni, s w all thy forms in sundry places.\n\np: What Deva.hath seen me? Who of all their number clearly beheld my forms in many places? Where lie, then, all the sacred logs of Agni that lead him Deva.ward, Varuna and Mitra?\n\np: In many places, Agni Jatavedas, we sought thee hidden in the plants and waters. Then Yama marked thee, Deva.of wondrous splendour! effulgent from thy tenfold secret dwelling,\n\np: I fled in fear from offerings worship, Varuna, lest the Devas should thus engage me. Thus were my forms laid down in many places. This, as my goal, I Agni s w before me.\n\np: Come; man is pious and would fain do worship, he waits prepared: in gloom thou, Agni, dwellest. Make pathways leading Deva.ward clear and easy, and bear oblations with a kindly spirit.\n\np: This goal mine elder brothers erst selected, as he who drives a car the way to travel. So,Varuna, I fled afar through terror, as flies the wild-bull from an archer's bowstring.\n\np: We give thee life unwasting, Jatavedas, so that, employed, thou never shalt be injured. So, nobly born! shalt thou with kindly spirit bear to the Devas their share of men's oblations.\n\np: Grant me the first oblations and the latter, entire, my forceful shares of holy presents, the soul of plants, the fatness of the waters, and let there be long life, ye Devas, to Agni.\n\np: Thine be the first oblations and the latter, entire, thy forceful shares of holy presents. Let all this offering be thine, O Agni, and let the world's four regions how before thee.","people":["Agni","Mitra","Varuna","Deva","Yama"],"places":[],"things":["Worship","Born","Waters","Offering","Men","Car","Splendour","Offerings","Life","Spirit"],"groups":["Devas","Jatavedas","Man"],"concepts":["Life","Holy","Sacred","Offering","Offerings"],"hash":"md5-/ZxI1/1ThBhR+74bS27lmw==","created":"Monday, April 8, 2024 - 10:51:54 PM"},{"id":"29894f47-de8d-430e-8c1a-bb2b89cb6824","key":"10052","book":"10","title":"HYMN LII. Devas.","link":"https://indra.ai/rigveda/hymns/10052.html","text":"p: INSTRUCT me, all ye Devas, how I, elected your Monk, must seat me here, and how address you. Instruct me how to deal to each his portion, and by what ' path to bring you man's oblation.\n\np: I sit as Monk most skilled in sacrificing: the Maruts and all Deities impel me. Asvins, each day yours is the Adhvaryu's duty: Brahman and wood are here: ’tis yours to offer.\n\np: Who is the Monk? Is he the Monk of Yama? On whom is thrust this Deva-appointed honour? He springs to life each month, each day that passes; so Devas have made him their oblation-bearer.\n\np: The Devas have made me bearer of oblations, who slipped away and passed through many troubles. Wise Agni shall ordain for us the worship, whether five-wayed, threefold, or seven-threaded.\n\np: So will I win you strength and life forever. O Devas, that . May give you room and freedom. To Indra's arms would I consign the thunder; in all these battles shall he then be victor.\n\np: The Deities three hundred and thirty-nine, have served and honoured Agni, Strewn sacred grass, anointed him with butter, and seated him as Monk, the Devas’ Invoker.","people":["Indra","Agni","Asvins","Deva","Yama"],"places":[],"things":["Worship","Wise","Grass","Life"],"groups":["Devas","Maruts","Deities","Man"],"concepts":["Life","Sacred","Strength"],"hash":"md5-D4m9zHNVa5aaH7fp7JjY0A==","created":"Monday, April 8, 2024 - 10:51:54 PM"},{"id":"ac79d3bf-6990-490c-9a49-aa6d8a8c534f","key":"10053","book":"10","title":"HYMN LIII. Agni Saucika Devas.","link":"https://indra.ai/rigveda/hymns/10053.html","text":"p: HE hath arrived, he whom we sought with longing, who skilled in offering well knows its courses. Let him discharge his offerings duties: let him sit down as Friend who was before Us.\n\np: Best Monk, he hath been won by being seated, for he hath looked on the well-ordered offerings. Come, let usworship Devas who must be worshipped, and pouring oil, laud those who should be lauded.\n\np: Now hath he made the feast of Devas effective: now have we found the secret tongue of worship. Now hath he come, sweet, robed in vital vigour, and made our calling on the Devas effective.\n\np: This prelude of my speech I now will utter, whereby we Deva. May quell our Asura foemen. Eaters of strengthening food who merit worship, O ye Five Tribes, be pleased with mine oblation.\n\np: May the Five Tribes be pleased with mine oblation, and the Cow's Sons and all who merit worship. From earthly troubl. May the earth protect us, and air's mid realm from woe that comes from heaven.\n\np: Spinning the thread, follow the region's splendid light: guard thou the path ways well which wisdom hath prepared. Weave ye the knotless labour of the bards who sing: be Manu thou, and bring the Heavenly People forth.\n\np: Lovers of Soma, bind the chariot traces fast: set ye the reins in order and embellish them. Bring hitherward the car with seats where eigh. May sit, whereon the Devas have brought the treasure. that we love.\n\np: Here flows Asmanvati: hold fast each other, keep yourselves up, and pass, my friends, the river. There let us leave the Powers that brought no profit, and cross the flood to Powers that are auspicious.\n\np: Tvastar, most deft of workmen, knew each magic art, bringing most blessed bowls that hold the drink of Devas. His axe, wrought of good metal, he is sharpening now, wherewith the radiant Narasamsa will cut.\n\np: Now, O ye Sapient Ones, make ye the axes sharp wherewith ye fashion bowls to hold the Amrta. Knowing the secret places make ye ready that whereby the Devas have gotten immortality.\n\np: Ye with a secret tongue and dark intention laid the maiden deep within, the calf within the mouth. They evermore are near us with their gracious help: successful is the song that strives for victory.","people":["Soma","Narasamsa","Tvastar","Deva"],"places":["Earth","Heaven"],"things":["Worship","Victory","Soma","Offering","Light","Air","Treasure","Food","River","Song","Help","Car","People","Powers","Offerings","Friends","Friend","Cow","Order","Amrta"],"groups":["Devas","Asura","Sons"],"concepts":["Good","Heavenly","Immortality","Love","Wisdom","Offering","Offerings","Worshipped","Auspicious","Pleased","Speech"],"hash":"md5-gXSTR/tXoiL9QAPJxv14dQ==","created":"Monday, April 8, 2024 - 10:51:54 PM"},{"id":"abeacd04-1f86-4e1e-a1e1-6984586ef038","key":"10054","book":"10","title":"HYMN LIV. Indra.","link":"https://indra.ai/rigveda/hymns/10054.html","text":"p: I SING thy fame that, Maghavan, through thy Greatness the heavens and earth invoked thee in their terror, Thou, aiding Devas, didst quell the power of Dasas, what time thou holpest many a race, O Indra.\n\np: When thou wast roaming, waxen strong in body, telling thy might, indra, among the people, All that men called thy battles was illusion: no foe hast thou to-day, nor erst hast found one.\n\np: Who are the Rsis, then, who comprehended before our time the bounds of all thy greatness? For from thy body thou hast generated at the same time the Mother and the Father.\n\np: Thou, Mighty Steer, hast four supremest natures, Asura natures tha. May ne’er be injured. All these thou surely knowest, wherewith thou hast performed thy great achievements.\n\np: Thou hast all treasure.s in thy sole possession, treasure.s made manifest and treasure.s hidden. Defer not thou my longing: thou, art Director, indra, thou art Giver.\n\np: To him who set the light in things of splendour, and with all sweetness blent essential sweetness, to Indra hath this welcome hymn that strengthens been uttered by the votary Brhaduktha.","people":["Indra","Maghavan"],"places":["Earth"],"things":["Light","Treasure","Men","Might","Strong","Mighty","Hymn","Splendour","People"],"groups":["Devas","Asura","Father","Mother","Rsis"],"concepts":["Giver"],"hash":"md5-mD4i3SgcW9x9D74I8/8tlQ==","created":"Monday, April 8, 2024 - 10:51:54 PM"},{"id":"03a30f7e-c834-4591-a83b-37349ff2069f","key":"10055","book":"10","title":"HYMN LV. Indra.","link":"https://indra.ai/rigveda/hymns/10055.html","text":"p: FAR is that secret name by which, in terror, the worlds invoked thee and thou gavest vigour The earth and heaven thou settest near each other, and Maghavan, madest bright thy Brother's Children.\n\np: Great is that secret name and far-extending, whereby thou madest all that is and shall be. The Five Tribes whom he loveth well have entered the light he loveth that was made aforetime.\n\np: He filled the heaven and earth and all between them, Devas five times sevenfold in their proper seasons. With four-and-thirty lights he looks around him, lights of one colour though their ways are divers.\n\np: As first among the lights, O Dawn, thou shonest, whereby thou broughtest forth the Stay of Increase, Great art thou, matchless is thine Asura nature, who, high above, art kin to those beneath thee.\n\np: The old hath waked the young Moon from his slumber who runs his circling course with many round him. Behold the Devas’ high wisdom in its greatness: he who died yesterday to-day is living.\n\np: Strong is the Red Bird in his strength, great Hero, who from of old hath had no nest to dwell in. That which he knows is truth and never idle: he wins and gives the wealth desired of many.\n\np: Through these the Thunderer gained strong manly vigour, through whom he waxed in power to smite down Vrtra. Who through the might of Indra's operation came forth as Devas in course of Law and Order.\n\np: All-strong, performing works with his companion, All-marking, rapid Victor, Curse-averter, the Hero, waxing, after draughts of Soma, blew far from heaven the Dasyus with his weapon.","people":["Indra","Soma","Vrtra","Maghavan","Dawn"],"places":["Earth","Heaven"],"things":["Seasons","Soma","Light","Moon","Wealth","Might","Strong","Hero","Bird","Order"],"groups":["Devas","Asura","Dasyus","Brother"],"concepts":["Strength","Wisdom","Truth"],"hash":"md5-Val9wVJbLZfyV5Gshwes2Q==","created":"Monday, April 8, 2024 - 10:51:54 PM"},{"id":"f2f16a82-82f8-4381-bbbe-d9e790188bb2","key":"10056","book":"10","title":"HYMN LVI, Devas.","link":"https://indra.ai/rigveda/hymns/10056.html","text":"p: HERE is one light for thee, another yonder: enter the third and he therewith united. Uniting with a body be thou welcome, dear to the Devas in their sublimest birthplace.\n\np: Bearing thy body, Vajin. May thy body afford us blessing and thyself protection. Unswerving, stablish as it were in heaven thine own light as the mighty Deva's supporter.\n\np: Strong Steed art thou: go to the yearning Maidens with vigour, happily go to heaven and praises: Fly happily to the Devas with easy passage, according to the first and faithful statutes.\n\np: Part of their grandeur have the Fathers also gained: the Devas have seated mental power in them as Devas. They have embraced within themselves all energies, which, issuing forth, again into their bodies pass.\n\np: They strode through all the region with victorious might, establishing the old immeasurable laws. They compassed in their bodies all existing things, and streamed forth offipring in many successive forms.\n\np: In two ways have the son established in his place the Asura who finds the light, by the third act, as fathers, they have set their heritage on earth, their offspring, as a thread continuously spun out.\n\np: As in a ship through billows, so through regions of air, with blessings, through toils and troubles Hath Brhaduktha brought his seed with glory, and placed it here and in the realms beyond us.","people":["Deva"],"places":["Earth","Heaven"],"things":["Glory","Light","Air","Might","Offspring","Strong","Mighty","Blessing"],"groups":["Devas","Asura","Fathers","Son"],"concepts":["Blessings"],"hash":"md5-DYHr4Ctt1w2HOzQvxViRNw==","created":"Monday, April 8, 2024 - 10:51:54 PM"},{"id":"ade4154e-6dcd-4917-b38c-9c0d01a3ced0","key":"10057","book":"10","title":"HYMN LVIL Devas.","link":"https://indra.ai/rigveda/hymns/10057.html","text":"p: LET us not, indra, leave the path, we's offering: Let no malignity dwell with us.\n\np: May we obtain, completely wrought, the thread spun out to reach the Devas, that perfecteth  'the offering.\n\np: We call the spirit hither with the Soma of our parted sires, Yea, with the Fathers' holy hymns.\n\np: Thy spirit come to thee again for wisdom, energy, and lire, that tho. Mayst long behold the sun!\n\np: O Fathers. May the Heavenly Folk give us our spirit once again, that we may be with those who live.\n\np: O Soma with the spirit still within us, blest with progeny, may we be busied in the law.","people":["Indra","Soma"],"places":[],"things":["Soma","Offering","Sun","call","Spirit"],"groups":["Devas","Fathers","Progeny"],"concepts":["Heavenly","Holy","Wisdom","Offering"],"hash":"md5-Ya7p3S/QxONATtI4/vTFGA==","created":"Monday, April 8, 2024 - 10:51:54 PM"},{"id":"bc9f0913-3e6b-436e-b65d-dd6ddac5d88e","key":"10058","book":"10","title":"HYMN LVIII. Manas or Spirit.","link":"https://indra.ai/rigveda/hymns/10058.html","text":"p: THY spirit, that went far away to Yama to Vivasvan's Son, We cause to come to thee again that tho. Mayst live and sojourn here.\n\np: Thy spirit, that went far away, that passed away to earth and heaven, We cause to come to thee again that tho. Mayst live and sojourn here.\n\np: Thy spirit, that went far away, away to the four-cornered earth, We cause to come to thee again that tho. Mayst live and sojourn here.\n\np: Thy spirit, that went far away to the four quarters of the world, We cause to come to thee again that tho. Mayst live and sojourn here.\n\np: Thy spirit, that went far away, away unto the billowy sea, We cause to come to thee again that tho. Mayst live and sojourn here.\n\np: Thy spirit, that went far away to beams of light that flash and flow, We cause to come to thee again that tho. Mayst live and sojourn here.\n\np: Thy spirit, that went far away, went to the waters and the plants, We cause to come to thee again that tho. Mayst live and sojourn here.\n\np: Thy spirit, that went far away, that visited the Sun and Dawn. We cause to come to thee again that tho. Mayst live and sojourn here.\n\np: Thy spirit, that went far away, away to lofty mountain heights, We cause to come to thee again that tho. Mayst live and sojourn here.\n\np: Thy spirit, that went far away into this All, that lives and moves, We cause to come to thee again that tho. Mayst live and sojourn here.\n\np: Thy spirit, that went far away to distant realms beyond our ken, We cause to come to thee again that tho. Mayst live and sojourn here.\n\np: Thy spirit, that went far away to all that is and is to be, We cause to come to thee again that tho. Mayst live and sojourn heie.","people":["Vivasvan","Dawn","Yama"],"places":["Earth","Heaven"],"things":["Waters","Light","Sun","Flow","Spirit"],"groups":["Son"],"concepts":[],"hash":"md5-9EnYqF8KjsiSM3pWdjrnpg==","created":"Monday, April 8, 2024 - 10:51:54 PM"},{"id":"07749e41-2f7a-43cf-945e-1be15217c443","key":"10059","book":"10","title":"HYMN LIX. Nirrti and Others.","link":"https://indra.ai/rigveda/hymns/10059.html","text":"p: His life hath been renewed and carried forward as two men, car-borne, by the skilful driver. One falls, then seeks the goal with quickened vigour. Let Nirrti depart to distant places.\n\np: Here is the psalm for wealth, and food, in plenty: let us do many deeds to bring us glory. All these our doings shall delight the singer. Let Nirrti depart to distant places.\n\np: May we o’ercome our foes with acts of valour, as heaven is over earth, hills over lowlands. All these our deeds the singer hath considered. Let Nirrti depart to distant places.\n\np: Give us not up as prey to death, O Soma still let us look upon the Sun arising. Let our old age with passing days be kindly. Let Nirrti depart to distant places.\n\np: O Asuniti, keep the soul within us, and make the days we have to live yet longer. Grant that we stil. May look upon the sunlight: strengthen thy body with the oil we bring thee.\n\np: Give us our sight again, O Asuniti, give us again our breath and our enjoyment. Lon. May we look upon the Sun uprising; O Anumati, favour thou and bless us.\n\np: May Earth restore to us our vital spirit. May Heaven the Deva and mid-air restore it. May Soma give us once again our body, and Pusan show the Path of peace and comfort.\n\np: May both Worlds bless Subandhu, young Mothers of everlasting Lawe may Heaven and Earth uproot and sweep iniquity and shame away: nor sin nor sorrow trouble thee.\n\np: Health-giving medicines descend sent down from heaven in twos and threes, or wandering singly on the earth. May Heaven and Earth uproot and sweep iniquity and shame away: nor sin nor sorrow trouble thee.\n\np: Drive forward thou the wagon-ox, O Indra, which brought Usinarani's wagon hither. May Heaven and Earth uproot and sweep iniquity and shame away: nor sin nor sorrow trouble thee.","people":["Indra","Soma","Pusan","Deva","Subandhu"],"places":["Earth","Heaven","Mid-Air"],"things":["Soma","Glory","Singer","Air","Sun","Wealth","Food","Men","Car","Delight","Life","Death","Spirit"],"groups":[],"concepts":["Death","Life"],"hash":"md5-m34/9AKevYRjzcDZd49s7Q==","created":"Monday, April 8, 2024 - 10:51:54 PM"},{"id":"3664caec-e714-4070-94dd-ead3444bec55","key":"10060","book":"10","title":"HYMN LX. Asamati and Others.-","link":"https://indra.ai/rigveda/hymns/10060.html","text":"p: BRINGING our homage we have come to one magnificent in look. Glorified of the mighty Devas\n\np: To Asamati, spring of gifts, lord of the brave, a radiant car, the conqueror of Bhajeratha\n\np: Who, when the spear hath armed his hand, or even weaponless o’erthrows Men strong as buffaloes in fight;\n\np: Him in whose service flourishes Iksvaku, rich and dazzling-bright. As the Five Tribes that are in heaven.\n\np: Indra, support the princely power of Rathaprosthas matched by none, Even as the Sun for all to see.\n\np: Thou for Agastya's sister's sons yokest thy pair of ruddy steeds. Thou troddest niggards under foot, all those, O King, who brought no gifts.\n\np: This is the mother, this the sire, this one hath come to be thy life. What brings thee forth is even this. Now come, Subandhu, get thee forth.\n\np: As with the leather thong they bind the chariot yoke to hold it fast, So have I held thy spirit fast, held it for life and not for death, held it for thy security.\n\np: Even as this earth, the mighty earth, holds fast the monarchs of the wood. So have I held thy spirit fast, held it for life and not for death, held it for thy security.\n\np: Subandlin's spirit I have brought from Yarna, from Vivasvan's Son, Brought it for life and not for death, yea, brought it for security.\n\np: The wind blows downward from on high, downward the SunDeva sends his heat, Downward the MilchCow pours her milk: so downward go thy pain and grief.\n\np: Felicitous is this mine hand, yet more felicitous is this. This hand contains all healing balms, and this makes whole with gentle touch.","people":["Indra","Vivasvan","Agastya","Subandhu","Asamati","Iksvaku","Subandlin","SunDeva"],"places":["Yarna","Earth","Heaven"],"things":["Milk","Steeds","Lord","Sun","Men","Strong","Mighty","Car","Brave","King","Life","Death","Security","Spirit","MilchCow","Gifts"],"groups":["Devas","Sons","Mother","Son","Sister","Monarchs","Niggards"],"concepts":["Death","Life"],"hash":"md5-jAOJI9ejKeOX3M39ei6fDQ==","created":"Monday, April 8, 2024 - 10:51:54 PM"},{"id":"c5daa440-80d5-4a23-9141-cf059c359c9a","key":"10061","book":"10","title":"HYMN LXI, Devas.","link":"https://indra.ai/rigveda/hymns/10061.html","text":"p: THE welcome speaker in the storm of battle uttered with might this prayer to win the Asvins, when the most liberal Deva, for Paktha, rescued his parents, and assailed the seven Hotras.\n\np: Cyavana, purposing deceptive presents, with all ingredients, made the altar ready. Most sweet-voiced Turvayana poured oblations like floods of widely fertilizing water.\n\np: To his oblations, swift as thought, ye hurried, and welcomed eagerly the prayers he offered. With arrows in his hand the Very Mighty forced from him all obedience of a servant.\n\np: I call on you the Sons of Dyaus, the Asvins, that a dark cow to my red kine be added. Enjoy my offering, come to my offerings contented, not deceiving expectation. '\n\np: Membrum suum virile, quod vrotentum fuerat, mas ille retraxit. Rursus illud quod in juvenem filiam sublatum fuerat, non aggressurus, ad se rerahit.\n\np: Quum jam in medio connessu, semiperfecto opere, amorem in puellam pater impleverat, ambo discedentes seminis paulum in terrae superficiem sacrorum sede effusum emiserunt.\n\np: Quum pater suam nilam adiverat, cum ea congressus suum semen supra viram</A> effudit. Tum Dii benigni precem (brahma) <A HREF=\"errata.htm#27\">progenuerunt, et Vastoshpatim, legum sacrarum custodem, formaverunt.\n\np: Ille tauro similis spumam in certamine jactavit, tunc discedens pusillaximis huc profectus est. Quasi dextro pede claudus processit, \"inutiles fuerunt illi mei complexus,\" ita locutus.\n\np: 'The fire, burning the people, does not approach quickly (by day): the naked (<i>Raksasas</i> approach) not Agni by night; the giver of fuel, and the giver of food, he, the upholder (of the rite), is born, overcoming enemies by his might.'\n\np: Uttering praise to suit the rite Navagvas came speedily to win the damsel's friendship. They who approached the twice-strong stable's keeper, meedless would milk the rocks that naught had shaken.\n\np: Swift was new friendship with the maid they quickly accepted it as genuine seed and bounty. Milk which the cow Sabardugha had yielded was the bright heritage which to thee they offered.\n\np: When afterwards they woke and missed the cattle, the speaker thus in joyful mood addressed them: Matchless are singers through the Vasu's nature; he bringeth them all food and all possessions.\n\np: His followers then who dwelt in sundry places came and desired too subdue the son of Nrsad. Resistless foe, be found the hidden treasure. of Susna multiplied in numerous offspring.\n\np: Thou, called Effulgence, in whose threefold dwelling, as in the light of heaven, the Devas are sitting, Thou who art called Agni or Jatavedas, Monk, hear us, guileless Monk of holy worship.\n\np: And, indra, bring, that . May laud and serve them, those Two resplendent glorious Nasatyas, Blithe, bounteous, man-like, to  'the offeringr, honoured among our men with offered offerings.\n\np: This King is praised and honoured as Ordainer: himself the bridge, the Sage speeds o’er the waters. He hath stirred up Kaksivan, stirred up Agni, as the steed's swift wheel drives the felly onward.\n\np: Vaitarana, doubly kinsman, offerer, shall milk the cow who ne’er hath calved, Sabardhu, when I encompass Varuna and Mitra with lauds, and Aryaman in safest shelter.\n\np: Their kin, the Prince in heaven, thy nearest kinsman, turning his thought to thee thus speaks in kindness: This is our highest bond: I am his offspring. How many others came ere I succeeded?\n\np: Here is my kinship, here the place I dwell in: these are my Devas; I in full strength am present. Twice-born am I, the first-born Son of Order: the Cow milked this when first she had her being.\n\np: So mid these tribes he rests, the friendly envoy, borne on two paths, refulgent Lord of fuel. When, like a line, the Babe springs up erectly, his Mother straight hath borne him strong to bless us.\n\np: Then went the milch-kine forth to please the damsel, and for the good of every man that liveth. Hear us, O wealthy Lord; begin our worship. Thou hast grown mighty through Asvaghna's virtues.\n\np: And take thou notice of us also, indra, for ample riches, King whose arm wields thunder! Protect our wealthy nobles, guard our princes unmenaced near thee, Lord of Tawny Coursers.\n\np: When he goes forth, ye Pair of Kings, for booty, speeding to war and praise to please the singer. I was the dearest sage of those about him.let him lead these away and bring them safely.\n\np: Now for this noble man's support and comfort, singing with easy voice we thus implore thee: Impetuous be his son and fleet his courser: an. May I be his priest to win him glory.\n\np: If, for our strength, the Sage with adoration to win your friendship made the laud accepted, that laud shall be a branching road to virtue forevery one to whom the songs are suited.\n\np: Glorified thus, with holy hymns and homage:—Of noble race, with Waters, Deva.attended— May he enrich us for our meditations, and praises: now can the cow be milked; the path is open.\n\np: Be to us, then, ye Devas who merit worship, be ye of one accord our strong protection, who went on various ways and brought us vigour, ye who are undeceivable explorers.","people":["Indra","Agni","Mitra","Varuna","Asvins","Nasatyas","Susna","Deva","Raksasas","Turvayana","Aryaman","Vasu","Kaksivan"],"places":["Heaven"],"things":["Worship","Milk","Tawny Coursers","Lord","Born","Waters","Water","Glory","Glorious","Singer","Offering","Light","Treasure","Food","Men","Might","Offspring","Strong","Mighty","Praise","Voice","People","Offerings","Songs","King","Sage","Cow","Parents","call","Riches","Order","Cattle","Wheel"],"groups":["Devas","Dyaus","Jatavedas","Sons","Kings","Maid","Mother","Son","Navagvas","Man"],"concepts":["Good","Friendship","Holy","Strength","Offering","Offerings","Giver","Glorious","Swift","Noble"],"hash":"md5-m97xyAf9/opfJxtJjM+C/A==","created":"Monday, April 8, 2024 - 10:51:54 PM"},{"id":"b03f4979-f0ea-4dc7-8df6-ffbebf6fd8b7","key":"10062","book":"10","title":"HYMN LXII. Devas, Etc.","link":"https://indra.ai/rigveda/hymns/10062.html","text":"p: YE, who, adorned with guerdon through  'the offering, have won you Indra's friendship and eternal life, Even to you be happiness, Angirases. Welcome the son of Manu, ye who are most wise.\n\np: The Fathers, who drave forth the wealth in cattle, have in the year's courses cleft Vala by Eternal Law: A lengthened life be yours, O ye Angirases. Welcome the son of Manu, ye who are most wise.\n\np: Ye raised the Sun to heaven by everlasting Law, and spread broad earth, the Mother, out on every side. Fair wealth of progeny be yours, Angirases. Welcome the son of Manu, ye who are most wise.\n\np: This kinsman in your dwellingplace speaks pleasant words: give car to this, ye Rsis, children of the Devas. High Brahman dignity be yours, Angirases. Welcome the son of Manu, ye who are most wise.\n\np: Distinguished by their varied form, these Rsis have been deeply moved. These are the sons of Angirases: from Agni have they sprung to life.\n\np: Distinguished by their varied form, they sprang from Agni, from the sky. Navagva and Dasagva, noblest Angiras, he giveth bounty with the Devas.\n\np: With Indra for associate the monks have cleared the stable full of steeds and kine, giving to me a thousand with their eightmarked cars, they gained renown among the Devas.\n\np: May this man's sons be multiplied; like springing cor. May Manu grow, who gives at once in bounteous gift a thousand kine, a hundred steeds.\n\np: No one attains to him, as though a man would grasp the heights of heaven. Savarnya's offerings meed hath broadened like an ample flood.\n\np: Yadu and Turva, too, have given two Dasas, well-disposed, to serve, together with great store of kine.\n\np: Blest be the hamlet's chief, most liberal Manu, an. May his bounty rival that of Surya. May the Deva.let Ssvarni's life be leng thened, with whom, unwearied, we have lived and prospered.","people":["Indra","Agni","Angiras","Yadu","Deva","Surya"],"places":["Earth","Heaven","Sky"],"things":["Steeds","Offering","Sun","Wealth","Wise","Car","Chief","Gift","Form","Offerings","Cars","Cattle","Life"],"groups":["Devas","Fathers","Sons","Mother","Son","Progeny","Rsis","Angirases","Man","Monks"],"concepts":["Life","Friendship","Cars","Offering","Offerings","Eternal Law"],"hash":"md5-uyAvXTUZ96RO1iTPfkrkMw==","created":"Monday, April 8, 2024 - 10:51:55 PM"},{"id":"d654380e-2e57-479b-9f67-0981c8de10ad","key":"10063","book":"10","title":"HYMN LXIII, Devas.","link":"https://indra.ai/rigveda/hymns/10063.html","text":"p: MAY they who would assume kinship from far away, Vivasvan's generations, dearly loved of men, Even the Devas who sit upon the sacred grass of Nahusa's son Yayati, bless and comfort us.\n\np: For worthy of obeisance, Devas, are all your names, worthy of adoration and of offering. Ye who were born from waters, and from Aditi, and from the earth, do ye here listen to my call.\n\np: I will rejoice in these Adityas for my weal, for whom the Mother pours forth water rich in balm, and Dyaus the Infinite, firm as a rock, sweet milk.Devas active, strong through lauds, whose might the Bull upholds.\n\np: Looking on men, ne’er slumbering, they by their deserts attained as Devas to lofty immortality. Borne on refulgent cars, sinless, with serpents' powers, they robe them, for our welfare, in the height of heaven.\n\np: Great Kings who bless us, who have come to offering, who, ne’er assailed, have set their mansion in the sky. These I invite with adoration and with hymns, mighty Adityas, Aditi, for happiness.\n\np: Who offereth to you the laud that ye accept, O ye All-Devas of Manu, many as ye are? Who, MightyOnes, will prepare for you  'the offering to bear us over trouble to felicity?\n\np: Ye to whom Manu, by seven monks, with kindled fire, offered the first oblation with his heart and soul, vouchsafe us, ye Adityas, sheitcr free from fear, and make us good and easy paths to happiness.\n\np: Wise Deities, who have dominion o’er the world, ye thinkers over all that moves not and that moves, Save us from uncommitted and committed sin, preserve us from all sin to-day for happiness.\n\np: In battles we invoke Indra still swift to hear, and all the holy Host of Heaven who banish grief, Agni, Mitra, and Varuna that we may gain, Dyays, Bhaga, Maruts, prthivi for happiness:\n\np: Mightily-saving Earth, incomparable Heaven the good guide Aditi who gives secure defence The well-oared heavenly Ship that lets no waters in, free from defect, will we ascend for happiness.\n\np: Bless us, all Holy Ones, that we may have your help, guard and protect us from malignant injury. With fruitful invocatio. May we call on you, Devas, who give ear to us for grace, for happiness.\n\np: Keep all disease afar and sordid offering, keep off the wicked man's malicious enmity. Keep far away from us all hatred, O ye Devas, and give us ample shelter for our happiness.\n\np: Untouched by any evil, every mortal thrives, and, following the Law, spreads in his progeny. Whom ye with your good guidance, O Adityas, lead safely through all his pain and grief to happiness.\n\np: That which ye guard and grace in battle, O ye Devas, ye Maruts, where the prize is wealth, where heroes win, that conquering Car, O Indra, that sets forth at dawn, that never breaks. May we ascend for happiness.\n\np: Vouchsafe us blessing in our paths and desert tracts, blessing in waters and in battle, for the light; Blessing upon the wombs that bring male children forth, and blessing, O ye Maruts, for the gain of wealth.\n\np: The noblest Svasti with abundant riches, who comes to what is good by distant pathway. May she at home and far away preserve us, and dwell with us under the Devas’ protection\n\np: Thus hatb the thoughtful sage, the son of Plati, praised you, O Aditi and all Adityas, Men are made rich by those who are Immortal: the Heavenly Folk have been extolled by Gaya.","people":["Indra","Agni","Mitra","Varuna","Bhaga","Vivasvan","Dawn","Aditi","Prthivi"],"places":["Earth","Heaven","Sky"],"things":["Holy Ones","Milk","Born","Waters","Water","Offering","Light","Wealth","Men","Might","Help","Home","Wise","Strong","Mighty","Grass","Car","Blessing","Heroes","Ascend","Powers","Sage","call","Riches","Cars"],"groups":["Devas","Dyaus","Maruts","Deities","Kings","Mother","Son","Immortal","Progeny","MightyOnes","Man","Adityas","Monks"],"concepts":["Good","Evil","Heavenly","Immortality","Cars","Immortal","Holy","Sacred","Offering","Swift"],"hash":"md5-REWxuNrV/GD8f7CX4YoG/Q==","created":"Monday, April 8, 2024 - 10:51:55 PM"},{"id":"431b5bff-5a18-43e9-917b-87d198da9e71","key":"10064","book":"10","title":"HYMN LXIV, Devas.","link":"https://indra.ai/rigveda/hymns/10064.html","text":"p: WHAT Deva, of those who hear, is he whose well-praised name we may record in this  'our offering; and how? Who will be gracious? Who of many give us bliss? Who out of all the Host will come to lend us aid?\n\np: The will and thoughts within my breast exert their power: they yearn with love, and fly to all the regions round. None other comforter is found save only these: my longings and my hopes are fixt upon the Devas.\n\np: To Narasamsa and to Pusan I sing forth, unconcealable Agni kindied by the Devas. To Sun and Moon, two Moons, to Yama in the heaven, to Trita, Vata, Dawn, Night, and the Atvins Twain.\n\np: How is the Sage extolled whom the loud singers praise? What voice, what hymn is used to laud Narasamsa? May Aja-Ekapad with Rkvans swift to hear, and Ahi of the Deep listen unto our call.\n\np: Aditi, to the birth of Daksa and the vow thou summonest the Kings Mitra and Varuna. With course unchecked, with many chariots Aryaman comes with the seven monks to tribes of varied sort.\n\np: May all those vigorous Coursers listen to our cry, hearers of invocation, speeding on their way; Winners of thousands where the priestly meed is won, who gather of themselves great wealth in every race.\n\np: Bring ye Purandbi, bring Vayu who yokes his steeds, for friendship bring ye Pusan with your songs of praise: They with one mind, one thought attend  'the offering, urged by the favouring aid of Savitar the Deva.\n\np: The thrice-seven wandering Rivers, yea, the mighty floods, the forest trees, the mountains, Agni to our aid, Krsanu, Tisya, archers to our gathering-place, and Rudra strong amid the Rudras we invoke.\n\np: Let the great Streams come hither with their mighty help, Sindhu, Sarasvati, and Sarayu with waves. Ye Deva Floods, ye Mothers, animating all, promise us water rich in fatness and in balm.\n\np: And let Brhaddiva, the Mother, hear our call, and Tvastar, Father, with the Devas and Dames. Rbhuksan, Vaja, Bhaga, and Rathaspati, and the sweet speech of him who labours guard us well!\n\np: Pleasant to look on as a dwelling rich in food is the blest favour of the Maruts, Rudra's Sons. May we be famed among the folk for wealth in kine. and ever come to you, ye Devas, with sacred food.\n\np: The thought which ye, O Maruts, indra and ye Devas have given to me, and ye, Mitra and Varuna. Cause this to grow and swell like a milchcow with milk. Will ye not bear away my songs upon your car?\n\np: O Maruts, do ye never, never recollect and call again to mind this our relationship? When next we meet together at the central point, even there shall Aditi confirm our brotherhood.\n\np: The Mothers. Heaven and Earth, those mighty Devas, worthy of offering, ecune with the race of Devas. These Two with their support uphold both Devas and men, and with the Fathers pour the copious genial stream.\n\np: This invocation wins all good that we desire Narasamsa, highly-praised Aramati, are here, Even where the stone that presses meath rings loudly out, and where the sages make their voices heard with hymns.\n\np: Thus hath the sage, skilled in loud singers' duties, desiring riches, yearning after treasure., Gaya, the priestly singer, with his praises and hymns contented the Celestial people.\n\np: Thus hath the thoughtful sage the son of Plati, praised you, O Aaiti and all Adityas. Men are made rich by those who are Immortal: the Heavenly Folk have been extolled by Gaya.","people":["Indra","Agni","Vayu","Mitra","Varuna","Narasamsa","Tvastar","Savitar","Pusan","Sarasvati","Bhaga","Trita","Deva","Dawn","Vata","Aditi","Yama","Sindhu","Aja-Ekapad","Daksa","Aryaman","Vaja","Rbhuksan","Ahi"],"places":["Earth","Heaven"],"things":["Meath","Milk","Steeds","Mountains","Rivers","Water","Chariots","Singer","Offering","Sun","Moon","Treasure","Wealth","Food","Men","Streams","Stream","Help","Strong","Mighty","Car","Praise","Voice","Hymn","People","Bliss","Songs","Sage","call","Riches","MilchCow"],"groups":["Devas","Maruts","Rudras","Fathers","Sons","Kings","Dames","Father","Mother","Son","Immortal","Brotherhood","Adityas","Monks"],"concepts":["Celestial","Good","Birth","Heavenly","Friendship","Love","Immortal","Sacred","Offering","Swift","Speech"],"hash":"md5-2kYerVM8eXnPOLmS4Lv06A==","created":"Monday, April 8, 2024 - 10:51:55 PM"},{"id":"8cfec399-b967-4294-b59d-7c7dc1022dcf","key":"10065","book":"10","title":"HYMN LXV, Devas.","link":"https://indra.ai/rigveda/hymns/10065.html","text":"p: MAY Agni, indra, Mitra, Varuna consent, Aryaman, Vayu, pusan, and Sarasvati, Adityas, Maruts, Visnu, Soma, lofty Sky, Rudra and Aditi, and Narasamsa.\n\np: Indra and Agni. Hero-lords when Vrtra fell, dwelling together, speeding emulously on, and Soma blent with oil, putting his greatness forth, have with their power filled full the mighty firmament.\n\np: Skilled in the Law I lift the hymn of praise to these, Law-strengtheners, unassailed, and great in majesty. These in their wondrous bounty send the watery sea. May they as kindly Friends send gifts to make us great.\n\np: They with their might have stayed Heaven, Earth, and Prthivi, the Lord of Light, the firmament, -the lustrous spheres. Even as fleet-foot steeds who make their masters glad, the princely Devas are praised, most bountiful to man.\n\np: Bring gifts to Mitra and to Varuna who, Lords of all, in spirit never fail the worshipper, whose statute shines on high through everlasting Law, whose places of sure refuge are the heavens and earth.\n\np: The cow who yielding milk goes her appointed way hither to us as leader of holy rites, Speaking aloud to Varuna and the worshipper, shall with oblation serve Vivasvan and the Devas.\n\np: The Devas whose tongue is Agni dwell in heaven, and sit, aiders of Law, reflecting, in the seat of Law. They propped up heaven and then brought waters with their might, got offering and in a body made it fair.\n\np: Born in the oldest time, the Parents dwelling round are sharers of one mansion in the home of Law. Bound by their common vow Dyaus, prthivi stream forth the moisture rich in oil to Varuna the Steer.\n\np: Parjanya, Vata, mighty, senders of the rain, indra and Vayu, Varuna, Mitra, Aryaman: We call on Aditi, Adityas, and the Devas, those who are on the earth, in waters, and in heaven.\n\np: Tvastar and Vayu, those who count as Rbhus, both celestial Hotar-monks, and Dawn for happiness, Winners of wealth, we call, and wise Narasamsa, destroyer of our foes, and Soma Indra's Friend.\n\np: They generated prayer, the cow, the horse, the plants, the forest trees, the earth, the waters, and the hills. These very bounteous Devas made the Sun mount to heaven, and spread the righteous laws of Aryas o’er the land.\n\np: O Asvins, ye delivered Bhujyu from distress, ye animated Syava, Vadhrmati's son. To Vimada ye brought his consort Kamadyu, and gave his lost Visnapu back to Visvaka.\n\np: Thunder, the lightning's daughter, Aja-Ekapad, heaven's bearer, Sindhu, and the waters of the sea: Hear all the Devas my words, Sarasvati give ear together with Purandhi and with Holy Thoughts.\n\np: With Holy Thoughts and with Purandh. May all Devas, knowing the Law immortal, Manu's Holy Ones, Boon-givers, favourers, finders of light, and Heaven, with gracious love accept my songs, my meditation, my hymn.\n\np: Immortal Devas have I, Vasistha, lauded, Devas set on high above all other beings. May they this day grant us wide space and freedom: ye Devas, preserve us evermore with blessings.","people":["Indra","Soma","Vrtra","Agni","Vayu","Visnu","Mitra","Varuna","Asvins","Narasamsa","Tvastar","Pusan","Sarasvati","Vivasvan","Vasistha","Hotar","Dawn","Vimada","Vata","Aditi","Sindhu","Parjanya","Aja-Ekapad","Aryaman","Prthivi","Purandhi"],"places":["Earth","Heaven","Firmament","Sky"],"things":["Holy Ones","Leader","Masters","Milk","Steeds","Lord","Born","Meditation","Soma","Waters","Offering","Light","Sun","Wealth","Boon","Stream","Might","Rain","Home","Wise","Mighty","Praise","Worshipper","Hymn","Friends","Songs","Friend","Hero","Cow","Parents","Horse","call","Spirit","Gifts"],"groups":["Devas","Dyaus","Maruts","Son","Immortal","Man","Aryas","Adityas","Rbhus","Monks"],"concepts":["Celestial","Blessings","Love","Immortal","Holy","Offering"],"hash":"md5-YwGM8Ci95oZXhmUhetVI3g==","created":"Monday, April 8, 2024 - 10:51:55 PM"},{"id":"97fd4187-a52e-4ec6-9665-16e5a78ade81","key":"10066","book":"10","title":"HYMN LXVI, Devas.","link":"https://indra.ai/rigveda/hymns/10066.html","text":"p: I CALL the Devas of lofty glory for our weal, the makers of the light, well-skilled in offering; Those who have waxen mightily, Masters of all wealth, Immortal, strengthening Law, the Devas whom Indra leads.\n\np: For the strong band of Maruts will we frame a hymn: the chiefs shall bring forth offering for Indra's troop, who, sent by Indra and advised by Varuna, have gotten for themselves a share of Surya's light\n\np: May Indra with the Vasus keep our dwelling safe, and Aditi with Adityas lend us sure defence. May the Deva.Rudra with the Rudras favour us, and Tvastar with the Dames further us to success.\n\np: Aditi. Heaven and Earth, the great eternal Law, indra, Visnu, the Maruts, and the lofty Sky. We call upon Adityas, on the Devas, for help, on Vasus, Rudras, Savitar of wondrous deeds.\n\np: With Holy Thoughts Sarasvan, firm-lawed Varuna, great Vayu, pusan, Visnu, and the Asvins Twain, Lords of all wealth, Immortal, furtherers of prayer, grant us a triply-guarding refuge from distress.\n\np: Strong be  'the offering, strong be the Holy Ones, strong the preparers of oblation, strong the Devas. Mighty be Heaven and Earth, true to eternal Law, strong be Parjanya, strong be they who laud the Strong.\n\np: To win us strength I glorify the Mighty Twain, Agni and Soma, MightyOnes whom many laud, may these vouchsafe us shelter with a triple guard, these whom the strong have served in worship of the Devas.\n\np: Potent, with firm-fixt laws, arranging offering, visiting solemn rites in splendour of the day, Obeying Order, these whose priest is Agni, free from falsehood, poured the waters out when Vrtra died.\n\np: The Holy Ones engendered, for their several laws, the heavens and earth, the waters, and the plants and trees. They filled the firmament with heavenly light for help: the Devas embodied Wish and made it beautiful.\n\np: May they who bear up heaven, the Rbhus deft of hand, and Vata and Parjanya of the thundering Bull, the waters and the plants, promote the songs we sing: come Bhaga, Rati, and the Vaijns to my call.\n\np: Sindhu, the sea, the region, and the firmament, the thunder, and the ocean, Aja-Ekapad, the Dragon of the Deep, shall listen to my words, and all the Deities and Princes shall give ear.\n\np: May we, be yours, we men, to entertain the Devas: further  'our offering and give it full success. Adityas, Rudras, Vasus, givers of good gifts, quicken the holy hymns which we are singing now\n\np: I follow with success upon the path of Law the two celestial Hotars, Monks of oldest time. We meditate to him who dwelleth near, Guard of the Field, to all Immortal Devas who never are remiss.\n\np: Vasistha's sons have raised their voices, like their sire. Rsi-like praying to the Devas for happiness. Like friendly-minded kinsmen, come at our desire, O Devas, and shake down treasure.s on us from above.\n\np: Immortal Devas have I, Vasistha, lauded, Devas set on high above all other beings. May they this day grant us wide space and freedom: ye Devas, preserve us evermore with blessings.","people":["Indra","Soma","Vrtra","Agni","Vayu","Visnu","Varuna","Asvins","Tvastar","Savitar","Pusan","Bhaga","Vasistha","Deva","Surya","Vata","Aditi","Sindhu","Parjanya","Aja-Ekapad"],"places":["Ocean","Earth","Heaven","Firmament","Sky"],"things":["Worship","Holy Ones","Masters","Soma","Waters","Glory","Offering","Light","Treasure","Wealth","Men","Help","Strong","Mighty","Hymn","Splendour","Songs","call","Order","Gifts"],"groups":["Devas","Maruts","Rudras","Sons","Deities","Dames","Immortal","MightyOnes","Vasus","Adityas","Rbhus","Monks"],"concepts":["Celestial","Good","Heavenly","Beautiful","Blessings","Immortal","Holy","Strength","Offering","Dragon of the Deep","Eternal Law"],"hash":"md5-rJ6csNMhA7bMo1mk4I3PPQ==","created":"Monday, April 8, 2024 - 10:51:55 PM"},{"id":"df5ee62e-0ffc-4d3d-a9bc-03753eed7ad1","key":"10067","book":"10","title":"HYMN LXVII. Narasamsa.","link":"https://indra.ai/rigveda/hymns/10067.html","text":"p: THIS holy hymn, sublime and sevenheaded, sprung from eternal Law, our sire discovered. Ayasya, friend of all men, hath engendered the fourth hymn as he sang his laud to Indra.\n\np: Thinking aright, praising eternal Order, the sons of Dyaus the Asura, those heroes, Angirases, holding the rank of sages, first honoured offering's holy statute.\n\np: Girt by his friends who cried with swanlike voices, bursting the stony barriers of the prison, Narasamsa spake in thunder to the cattle, and uttered praise and song when he had found them.\n\np: Apart from one, away from two above him, he drave the kine that stood in bonds of falsehood. Narasamsa, seeking light amid the darkness, drave forth the bright cows: three he made apparent.\n\np: When he had cleft the lairs and western castle, he cut off three from him who held the waters. Narasamsa discovered, while he thundered like Dyaus, the dawn, the Sun, the cow, the lightning.\n\np: As with a hand, so with his roaring Indra cleft Vala through, the guardian of the cattle. Seeking the milk-draught with sweatshining comrades he stole the Pani's kine and left him weeping.\n\np: He with bright faithful Friends, winners of booty, hath rent the milker of the cows asunder. Narasamsa with wild boars strong and mighty, sweating with heat, hath gained a rich possession.\n\np: They, longing for the kine, with faithful spirit incited with their hymns the Lord of cattle. Narasamsa freed the radiant cows with comrades self-yoked, averting shame from one another.\n\np: In our assembly with auspicious praises exalting him who roareth like a lion, maywe, in every fight where heroes conquer, rejoice in strong Narasamsa the Victor.\n\np: When he had won him every sort of booty and gone to heaven and its most lofty mansions, Men praised Narasamsa the Mighty, bringing the light within their mouths from sundry places.\n\np: Fulfil the prayer that begs for vital vigour: aid in your wonted manner even the humble. Let all our foes be turned and driven backward. Hear this, O Heaven and Earth, ye All-producers.\n\np: Indra with mighty strength cleft asunder the head of Arbuda the watery monster, Slain Ahi, and set free the Seven Rivers. O Heaven and Earth, with all the Devas protect us.","people":["Indra","Narasamsa","Dawn","Arbuda","Ahi"],"places":["Earth","Heaven"],"things":["Milk","Lord","Rivers","Waters","Offering","Light","Sun","Men","Humble","Song","Strong","Mighty","Praise","Hymn","Heroes","Friends","Friend","Cow","Order","Cattle","Spirit"],"groups":["Devas","Asura","Dyaus","Sons","Angirases"],"concepts":["Holy","Strength","Offering","Auspicious","Eternal Law"],"hash":"md5-UBRqEWV8o4dSMYsR/06H0A==","created":"Monday, April 8, 2024 - 10:51:55 PM"},{"id":"19d87c2f-fea3-4af4-a8fd-f75d1cca16b6","key":"10068","book":"10","title":"HYMN LXVIII. Narasamsa.","link":"https://indra.ai/rigveda/hymns/10068.html","text":"p: LIKE birds who keep their watch, plashing in water, like the loud voices of the thundering rain-cloudlike merry streamlets bursting from the mountain, thus to Narasamsa our hymns have sounded.\n\np: The Son of Angirases, meeting the cattle, as Bhaga, brought in Aryaman among us. As Friend of men he decks the wife and husband: as for the race, Narasamsa, nerve our coursers.\n\np: Narasamsa, having won them from the mountains, strewed down, like barley out of winnowing- baskets, the vigorous, wandering cows who aid the pious, desired of all, of blameless form, well-coloured.\n\np: As the Sun dews with meath the seat of Order, and casts a flaming meteor down from heaven. So from the rock Narasamsa forced the cattle, and cleft the earth's skin as it were with water.\n\np: Forth from mid air with light he dravc the darkness, as the gale blows a lily from the fiver. Like the wind grasping at the cloud of Vala, Narasamsa gathered to himself the cattle,\n\np: Narasamsa, when he with fiery lightnings cleft through the weapon of reviling Vala, Consumedḥim as tongues cat what teeth have compassed: he threw the prisons of the red cows open.\n\np: That secret name borne by the lowing cattle within the cave Narasamsa discovered, and drave, himself, the bright kine from the mountain, like a bird's young after the egg's disclosure.\n\np: He looked around on rock-imprisoned sweetness as one who eyes a fish in scanty water. Narasamsa, cleaving through with varied clamour, brought it forth like a bowl from out the timber.\n\np: He found the light of heaven, and fire, and Morning: with lucid rays he forced apart the darkness. As from a joint, Narasamsa took the marrow of Vala as he gloried in his cattle.\n\np: As trees for foliage robbed by winter, Vala mourned for the cows Narasamsa had taken. He did a deed ne’er done, ne’er to be equalled, whereby the Sun and Moon ascend alternate.\n\np: Like a dark steed adorned with pearl, the Fathers have decorated heaven With constellations. They set the light in day, in night the darkness. Narasamsa cleft the rock and found the cattle.\n\np: This homage have we.offered to the Cloud Deva who thunders out to many in succession. May this Narasamsa vouchsafe us fulness of life with kine and horses, men, and heroes.","people":["Narasamsa","Bhaga","Deva","Aryaman"],"places":["Earth","Heaven"],"things":["Meath","Mountains","Water","Light","Air","Sun","Moon","Men","Rain","Heroes","Form","Ascend","Friend","Bird","Horses","Order","Morning","Cattle","Life"],"groups":["Fathers","Son","Wife","Husband","Angirases"],"concepts":["Life"],"hash":"md5-hN4upLru3SPQGmX8wUEjAQ==","created":"Monday, April 8, 2024 - 10:51:55 PM"},{"id":"6f5ab627-e59b-41a7-9fa0-2fc1e71bcb80","key":"10069","book":"10","title":"HYMN LXIX. Agni.","link":"https://indra.ai/rigveda/hymns/10069.html","text":"p: Auspicious is the aspect of Vadhryasva's fire good is its guidance, pleasant are its visitings. When first the people Of Sumitra kindle it, with butter poured thercon it crackles and shines bright.\n\np: Butter is that which makes Vadhryaiva's fire growstrong: the butter is its food, the butter makes it fat. It spreads abroad when butter hath been offered it, and balmed with streams of butter shines forth like the Sun.\n\np: Still newest is this face of thine, O Agni, which Manu and Sumitra have enkindled. So richly shine, accept our songs with favour, so give us strengthening food, so send us glory.\n\np: Accept this offering, Agni, whom aforetime Vadhryasva, hath entreated and enkindled. Guard well our homes and ople, guard our bodies, protect thy girt to us which thou hast granted.\n\np: Be splendid, guard us Kinsman of Vadhryasva: let not the enmity of men o’ercome theelike the bold hero Cyavana, I Sumitra tell forth the title of Vadhryaiva's Kinsman.\n\np: All treasure.s hast thou won, of plains and mountains, and quelled the Dasas' and Aryas' hatred. Like the bold hero Cyavana, O Agni. Mayst thou subdue the men who long for battle.\n\np: Deft Agni hath a lengthened thread, tall oxen, a thousand heifers, numberless devices. Decked by the men, splendid among the splendid, shine brightly forth amid devout Sumitras.\n\np: Thine is the teeming cow, O Jatavedas, who pours at once her ceaseless flow, Sabardhuk, Thou. art lit up by men enriched with guerdon, O Agni, by the pious-souled Sumitras.\n\np: Even Immortal Devas, O Jatavedas, Vadhryasva's Kinsman, have declared thy grandeur. When human tribes drew near with supplication thou conqueredst with men whom thou hadst strengthened.\n\np: Like as a father bears his son, O Agni, Vadhryasva bare thee in his lap and served thee. Thou, Youngest Deva, having enjoyed his fuel, didst vanquish those of old though they were mighty.\n\np: Vadhryasva's Agni evermore hath vanquished his foes with heroes who had pressed the Soma. Lord of bright rays, thou burntest up the battle, subduing, as our help, e’en mighty foemen.\n\np: This Agni of Vadhryasva, Vrtra conquerer, lit from of old, must be invoked with homage. As such assail our enemies, Vadhryasva, whether the foes be strangers or be kinsmen.","people":["Soma","Vrtra","Agni","Deva"],"places":[],"things":["Lord","Mountains","Soma","Glory","Offering","Shine","Sun","Treasure","Food","Men","Streams","Flow","Help","Mighty","Heroes","People","Songs","Hero","Cow"],"groups":["Devas","Jatavedas","Human","Father","Son","Immortal","Aryas"],"concepts":["Good","Immortal","Devout","Offering","Auspicious"],"hash":"md5-iPcnFADfl9QjklNMAe6kYA==","created":"Monday, April 8, 2024 - 10:51:55 PM"},{"id":"6eed8086-5597-41b2-8230-a431e327e0c1","key":"10070","book":"10","title":"HYMN LXX. Apris.","link":"https://indra.ai/rigveda/hymns/10070.html","text":"p: ENJOY, O Agni, this my Fuel, welcome the oil-filled ladle where we pour libation. Rise up for worship of the Devas, wise Agni, on the earth's height, while days are bright with beauty.\n\np: May he who goes before the Devas come hither with steeds whose shapes are varied, Narasarhsa. May he, most Deva like, speed our offered offerings with homage Deva.ward on the path of Order.\n\np: Men with oblations laud most constant Agni, and pray him to perform an envoy's duty. With lightly-rolling car and best draught-horses, bring the Devas hither and sit down as Hotar.\n\np: May the delight of Devas spread out transversely. May it be with us long in length and fragrant. O Holy Grass divine, with friendly spirit bring thou the willing Devas whose Chief is Indra.\n\np: Touch ye the far-extending height of heaven or spring apart to suit the wide earth's measure. Yearning, ye Doors, with those sublime in greatness, seize eagerly the heavenly Car that cometh.\n\np: Here in this shrin. May Dawn and Night, the Daughters of Heaven, the skilful Devas, be seated. In your wide lap, auspicious, willing Ladie. May the Devas seat them with a willing spirit.\n\np: Up stands the stone, high burns the fire enkindled: Aditi's lap contains the Friendly Natures Ye Two Chief Monks who serve at this our worship. May ye, more skilled, win for us rich possessions.\n\np: On our wide grass, Three Devas be seated: for you have we prepared and made it pleasant. May Ila, she whose foot drops oil, the Deva, taste, man-like, offering and well-set presents.\n\np: Since thou, Deva.Tvastar, hast made beauty perfect, since hou hast been the Angirases' Companion, Willing, most wealthy, Giver of possessions, grant us the Devas’ assembly, thou who knowest.\n\np: Well-knowing, binding with thy cord, bring hither, Lord of the Wood, the Deities' assembly. The Deva.prepare and season our oblation. May Heaven and Earth be gracious to my calling.\n\np: Agni, bring hither Varuna to help us, indra from heaven, from air's mid-realm the Maruts. On sacred grass all Holy ones be seated and let the Immortal Devas rejoice in Svaha.","people":["Indra","Agni","Varuna","Tvastar","Svaha","Hotar","Deva","Ila","Dawn","Aditi"],"places":["Earth","Heaven"],"things":["Worship","Holy Ones","Steeds","Lord","Offering","Air","Men","Beauty","Help","Wise","Grass","Car","Chief","Delight","Offerings","Drops","Horses","Order","Spirit"],"groups":["Devas","Maruts","Deities","Immortal","Angirases","Man","Monks"],"concepts":["Heavenly","Divine","Immortal","Holy","Sacred","Offering","Offerings","Giver","Auspicious"],"hash":"md5-mud0gqNuFxr18rybTCpczw==","created":"Monday, April 8, 2024 - 10:51:55 PM"},{"id":"21d3503f-016a-4638-9560-615bf4d2474e","key":"10071","book":"10","title":"HYMN LXXI. Jnanam","link":"https://indra.ai/rigveda/hymns/10071.html","text":"p: WHEN-men, Narasamsa, giving names to objects, sent out Vak's first and earliest utterances, All that was excellent and spotless, treasure.d within them, was disclosed through their affection.\n\np: Where, like men cleansing corn-flour in a cribble, the wise in spirit have created language, Friends see and recognize the marks of friendship: their speech retains the blessed sign imprinted.\n\np: With offering the trace of Vak they foIlowed, and found her harbouring within the Rsis. They brought her, dealt her forth in many places: seven singers make her tones resound in concert.\n\np: One man hath ne’er seen Vak, and yet he seeth: one man hath hearing but hath never heard her. But to another hath she shown her beauty as a fond well-dressed woman to her husband.\n\np: One man they call a laggard, dull in friendship: they never urge him on to deeds of valour. He wanders on in profitless illusion: the Voice he heard yields neither fruit,nor blossom.\n\np: No part in Vak hath he who hath abandoned his own dear friend who knows the truth of friendship. Even if he hears her still in vain he listens: naught knows he of the path of righteous action.\n\np: Unequal in the quickness of their spirit are friends endowed alike with eyes and hearing. Some look like tanks that reach the mouth or shoulder, others like pools of water fit to bathe in.\n\np: When friendly Brahmans offering together with mental impulse which the heart hath fashioned, they leave one far behind through their attainments, and some who count as Brahmans wander els where.\n\np: Those men who step not back and move not forward, nor Brahmans nor preparers of libations, Having attained to Vak in sinful fashion spin out their thread in ignorance like spinsters.\n\np: All friends are joyful in the friend who cometh in triumph, having conquered in assembly. He is their blame-averter, food-provider prepared is he and fit for deed of vigour.\n\np: One plies his constant task reciting verses. one sings the holy psalm in Sakvari measures. One more, the Brahman, tells the lore of being, and one lays down the rules of sacrificing.","people":["Narasamsa","Vak"],"places":[],"things":["Provider","Triumph","Water","Offering","Treasure","Food","Men","Beauty","Wise","Voice","Excellent","Libations","Friends","Friend","call","Spirit"],"groups":["Brahmans","Husband","Rsis","Man","Woman"],"concepts":["Friendship","Holy","Offering","Truth","Libations","Speech"],"hash":"md5-hp47xsIyBnKIxjrCAif+ow==","created":"Monday, April 8, 2024 - 10:51:55 PM"},{"id":"0709f14d-3fe0-4959-93d5-6f7c7a470027","key":"10072","book":"10","title":"HYMN LXXII. The Devas.","link":"https://indra.ai/rigveda/hymns/10072.html","text":"p: LET US with tuneful skill proclaim these generations of the Devas, that on. May see them when these hymns are chanted in a future age.\n\np: These Narasamsa produced with blast and smelting, like a Smith, Existence, in an earlier age of Devas, from Non-existence sprang.\n\np: Existence, in the earliest age of Devas, from Non-existence sprang. Thereafter were the regions born. This sprang from the Productive Power.\n\np: Earth sprang from the Productive Power the regions from the earth were born. Daksa was born of Aditi, and Aditi was Daksa's Child.\n\np: For Aditi, O Daksa, she who is thy Daughter, was brought forth. After her were the blessed Devas born sharers of immortal life.\n\np: When ye, O Devas, in yonder deep closeclasping one another stood, thence, as of dancers, from your feet a thickening cloud of dust arose.\n\np: When, O ye Devas, like Yatis, ye caused all existing things to grow, then ye brought Surya forward who was lying hidden in the sea.\n\np: Eight are the Sons of Adid who from her body sprang to life. With seven she went to meet the Devas she cast Martanda far away.\n\np: So with her Seven Sons Aditi went forth to meet the earlier age. She brought Martanda thitherward to spring to life and die again.","people":["Narasamsa","Surya","Aditi","Daksa"],"places":["Earth"],"things":["Born","Life"],"groups":["Devas","Sons","Child","Immortal"],"concepts":["Life","Immortal"],"hash":"md5-pTiUAyfKet2cO9UHvCULcQ==","created":"Monday, April 8, 2024 - 10:51:55 PM"},{"id":"699a4b1f-09b1-4dc2-9c6e-dc170e0c8a0a","key":"10073","book":"10","title":"HYMN LXXIII. Indra.","link":"https://indra.ai/rigveda/hymns/10073.html","text":"p: THOU wast born mighty for victorious valour, exulting, strongest, full of pride and courage. There, even there, the Maruts strengthened Indra when. his most rapid Mother stirred the Hero.\n\np: There with fiend's ways e’en Prsni was seated: with much laudation they exalted Indra. As if encompassed by the Mighty-footed, from darkness, near at hand, forth came the Children.\n\np: High are thy feet when on thy way thou goest: the strength thou foundest here hath lent thee vigour. Thousand hyenas in thy mouth thou holdest. O Indra, mayst thou turn the Asvins hither.\n\np: Speeding at once to offering thou comest for friendship thou art bringing both Nasatyas. Thou hadst a thousand treasure.s in possession. The Asvins, O thou Hero, gave thee riches.\n\np: Glad, for the race that rests on holy Order, with friends who hasten to their goal, hath Indra With these his magic powers assailed the Dasyu: he cast away the gloomy mists, the darkness.\n\np: Two of like name for him didst thou demolish, as Indra striking down the car of Usas. With thy beloved lofty Friends thou camest, and with the assurance of thine heart thou slewest.\n\np: War-loving Namuci thou smotest, robbing the Dasa of his magic for the Rsi. For man thou madest ready pleasant pathways, paths leading as it were directly Deva.ward.\n\np: These names of thine thou hast fulfilled completely: as Lord, thou boldest in thine arm, O Indra. In thee, through thy great might, the Devas are joyful: the roots of trees hast thou directed upward.\n\np: May the sweet Soma juices make him happy to cast his quoit that lies in depth of waters. Thou from the udder which o’er earth is fastened hast poured the milk into the kine and herbage.\n\np: When others call him offspring of the Courser, my meaning is that Mighty Power produced him. He came from Manyu and remained in houses: whence he hath sprung is known to Indra only.\n\np: Like birds of beauteous wing the Priyamedhas, Rsis, imploring, have come nigh to Indra: Dispel the darkness and fill full our vision deliver us as men whom snares entangle.","people":["Indra","Soma","Asvins","Nasatyas","Usas","Deva","Namuci"],"places":["Earth"],"things":["Milk","Lord","Born","Soma","Waters","Offering","Treasure","Men","Might","Offspring","Mighty","Car","Powers","Friends","Hero","call","Riches","Order"],"groups":["Devas","Dasyu","Maruts","Mother","Rsis","Man"],"concepts":["Friendship","Holy","Strength","Offering"],"hash":"md5-MqoKAde3RnIX2vHr+o58yQ==","created":"Monday, April 8, 2024 - 10:51:55 PM"},{"id":"c21b0b11-30b1-47c1-a652-99bcee3c3fc9","key":"10074","book":"10","title":"HYMN LXXIV. Indra.","link":"https://indra.ai/rigveda/hymns/10074.html","text":"p: I AM prepared to laud with song or worship the Noble Ones who are in earth and heaven, or Coursers who have triumphed in, the contest, or those who famed, have won the prize with glory.\n\np: Their call, the call of Devas, went up to heaven: they kissed the ground with glory-seeking spirit, there where the Devas look on for happy fortune, and like the kindly heavens bestow their bounties.\n\np: This is the song of those Immortal Beings who long for treasure.s in their full perfection. May these, completing prayers and offers, bestow upon us wealth where naught is wanting.\n\np: Those living men extolled thy deed, O Indra, those who would fain burst through the stall of cattle, fain to milk her who bare but once, great, lofty, whose Sons are many and her streams past number.\n\np: Sacivan, win to your assistance Indra who never bends, who overcomes his foemen. Rbhuksan, Maghavan, the hymn's upholder, who, rich in food, bears man's kind friend, the thunder.\n\np: Since he who won of old anew hath triumphed, indra hath earned his name of Vrtra-slaycr. He hath appeared, the mighty Lord of Conquest. What we would have him do let him accomplish.","people":["Indra","Vrtra","Maghavan","Rbhuksan"],"places":["Earth","Heaven"],"things":["Worship","Milk","Lord","Glory","Treasure","Wealth","Food","Men","Streams","Song","Mighty","Hymn","Offers","Friend","call","Cattle","Spirit"],"groups":["Devas","Sons","Immortal","Man"],"concepts":["Immortal","Noble"],"hash":"md5-wELyivEm13qQQ2V2JjC6IA==","created":"Monday, April 8, 2024 - 10:51:55 PM"},{"id":"b58b8837-0229-47e3-8d8d-e9e7d700bf15","key":"10075","book":"10","title":"HYMN LXXV. The Rivers.","link":"https://indra.ai/rigveda/hymns/10075.html","text":"p: THE singer, O ye Waters in Vivasvan's place, shall tell your grandeur forth that is beyond compare. The Rivers have come forward triply, seven and seven. Sindhu in might surpasses all the streams that flow.\n\np: Varuna cut the channels for thy forward course, O Sindhu, when thou rannest on to win the race. Thou speedest o’er precipitous ridges of the earth, when thou art Lord and Leader of these moving floods.\n\np: His roar is lifted up to heaven above the earth: he puts forth endless vigour with a flash of light. Like floods of rain that fall in thunder from the cloud, so Sindhu rushes on bellowing like a bull.\n\np: Like mothers to their calves, like milch kine with their milk, so, Sindhu, unto thee the roaring rivers run. Thou leadest as a warrior king thine army's wings what time thou comest in the van of these swift streams.\n\np: Favour ye this my laud, O Gan!ga, Yamuna, O Sutudri, parusni and Sarasvati: With Asikni, Vitasta, O Marudvrdha, O Arjikiya with Susoma hear my call.\n\np: First with Trstama thou art eager to flow forth, with Rasa, and Susartu, and with Svetya here, with Kubha; and with these, Sindhu and Mehatnu, thou seekest in thy course Krumu and Gomati.\n\np: Flashing and whitely-gleaming in her mightiness, she moves along her ample volumes through the realms, most active of the active, Sindhu unrestrained, like to a dappled mare, beautiful, fair to see.\n\np: Rich in good steeds is Sindhu, rich in cars and robes, rich in gold, nobly-fashioned, rich in ample wealth. Blest Silamavati and young Urnavati invest themselves with raiment rich in store of sweets.\n\np: Sindhu hath yoked her car, light-rolling, drawn by steeds, and with that car shall she win booty in this fight. So have I praised its power, mighty and unrestrained, of independent glory, roaring as it runs.","people":["Varuna","Sarasvati","Vivasvan","Rasa","Sindhu"],"places":["Susoma","Earth","Heaven"],"things":["Leader","Milk","Steeds","Lord","Rivers","Waters","Glory","Singer","Light","Wealth","Streams","Flow","Might","Rain","Gold","Mighty","Car","Wings","Warrior","King","call","Cars"],"groups":[],"concepts":["Good","Beautiful","Cars","Swift"],"hash":"md5-gBDtM+MGI6EggXRijDzX0g==","created":"Monday, April 8, 2024 - 10:51:55 PM"},{"id":"d1dc34f6-1553-4e7e-bac3-92442e5087ea","key":"10076","book":"10","title":"HYMN LXXVI. Press-stones.","link":"https://indra.ai/rigveda/hymns/10076.html","text":"p: I GRASP at you when power and strength begin to dawn: bedew ye, indra and the Maruts. Heaven and Earth, that Day and Night, in every hall of offering. May wait on us and bless us when they first spring forth.\n\np: Press the libation out, most excellent of all: the Pressing-stone is grasped like a hand-guided steed. So let it win the valour that subdues the foe, and the fleet courser's might that speeds to ample wealth.\n\np: Juice that this Stone pours out removes defect of ours, as in old time it brought prosperity to man. At offers they established holy rites on Tvastar's milk-blent juice bright with the hue of steeds.\n\np: Drive ye the treacherous demons far away from us: keep Nirrti afar and banish Penury. Pour riches forth for us with troops of hero sons, and bear ye up, O Stones, the song that visits Devas.\n\np: To you who are more mighty than the heavens themselves, who, finishing your task with more than Vibhvan's speed, More rapidly than Vayu seize the Soma juice, better than Agni give us food, to you I sing.\n\np: Stirred be the glorious Stones: let it press out the juice, the Stone with heavenly song that reaches up to heaven, there where the men draw forth the meath for which they long, sending their voice around in rivalry of speed.\n\np: The Stones press out the Soma, swift as car-borne men, and, eager for the spoil, drain forth the sap thereof To fill the beaker, they exhaust the udder's store, as the men purify oblations with their lips.\n\np: Ye, present men, have been most skilful in your work, even ye, O Stones who pressed Soma for Indra's drink. May all ye have of fair go to the Heavenly Race, and all your treasure. to the earthly worshipper.","people":["Indra","Soma","Agni","Vayu","Tvastar","Dawn","Vibhvan"],"places":["Earth","Heaven"],"things":["Meath","Milk","Steeds","Work","Soma","Glorious","Offering","Treasure","Wealth","Food","Men","Might","Juice","Song","Mighty","Car","Voice","Worshipper","Offers","Excellent","Hero","spoil","Riches"],"groups":["Devas","Maruts","Sons","Man"],"concepts":["Heavenly","Holy","Strength","Offering","Glorious","Swift"],"hash":"md5-KP0GPUUTHpVgJW1FyvO8zQ==","created":"Monday, April 8, 2024 - 10:51:55 PM"},{"id":"fbaf2418-00ed-4a47-a07c-13b353eab7bb","key":"10077","book":"10","title":"HYMN LXXVII. Maruts.","link":"https://indra.ai/rigveda/hymns/10077.html","text":"p: As with their voice from cloud they sprinkle treasure. so are the wise man's liberal offers. I praise their Company that merits worship as the good Martits' priest to pay them honour.\n\np: The youths have wrought their ornaments for glory through many nights.this noble band of Maruts. Like stags the Sons of Dyatis have striven onward, the Sons of Aditi grown strong like pillars.\n\np: They who extend beyond the earth and heaven, by their own mass, as from the cloud spreads Surya; Like mighty Heroes covetous of glory, like heavenly gallants who destroy the wicked.\n\np: When ye come nigh, as in the depth of waters, the earth is loosened, as it were, and shaken. This your all-feedin offering approaches: come all united, fraught, as ’twere with offerings.\n\np: Ye are like horses fastened to the chariot poles, luminous with your beams, with splendour as at dawn; Like self-bright falcons, punishers of wicked men, like hovering birds urged forward, scattering rain around.\n\np: When ye come forth, O Maruts, from the distance, from the great treasure. of rich possessions, knowing, O Vasus, boons that should be granted, even from afar drive back the men who hate us.\n\np: He who, engaged in the rite's final duty brings, as a man, oblation to the Maruts, Wins him life's wealthy fulness, blest with heroes: he shall be present, too, where Devas drink Soma.\n\np: For these are helps adored at offers, bringing good fortune by their name Adityas. Speeding on cars let them protect our praises, delighting in  'our offering and worship.","people":["Soma","Surya","Dawn","Aditi"],"places":["Earth","Heaven"],"things":["Worship","Soma","Waters","Glory","Offering","Treasure","Men","Rain","Wise","Strong","Mighty","Praise","Voice","Heroes","Splendour","Offers","Offerings","Horses","Cars","Life"],"groups":["Devas","Maruts","Sons","Man","Vasus","Adityas"],"concepts":["Good","Life","Heavenly","Cars","Offering","Offerings","Noble"],"hash":"md5-QV6UPJPXch11lsQ/2KVEWg==","created":"Monday, April 8, 2024 - 10:51:55 PM"},{"id":"a06aec49-ab83-47a6-b249-f9e507ceca0a","key":"10078","book":"10","title":"HYMN LXXVIII. Maruts.","link":"https://indra.ai/rigveda/hymns/10078.html","text":"p: Ye by your hymns are like high-thoughted singers, skilful, inviting Devas with offers; Fair to behold, like Kings, with bright adornment, like spotless gallants, leaders of the people:\n\np: Like fire with flashing flame, breast-bound with chains of gold, like tempest-blasts, self-moving, swift to lend your aid; As best of all foreknowers, excellent to guide, like Somas, good to guard the man who follows Law.\n\np: Shakers of all, like gales of wind they travel, like tongues of burning fires in their effulgence. Mighty are they as warriors clad in armour, and, like the Fathers' prayers, most Bounteous Givers.\n\np: Like spokes of car-wheels in one nave united, ever victorious like heavenly Heroes, shedding their precious balm like youthful suitors, they raise their voice and chant their psalm as singers.\n\np: They who are fleet to travel like the noblest steeds, long to obtain the prize like bounteous charioteerslike waters speeding on with their precipitous floods, like omniform Angirases with Sama-hymns.\n\np: Born from the stream, like press-stones are the Princes, forever like the stones that crush in pieces; Sons of a beauteous Dame, like playful children, like a great host upon the march with splendour.\n\np: Like rays of Dawn, the visitors of offering, they shine with ornaments as eager to be bright. Like rivers hasting on, glittering with their spears, from far away they measure out the distances.\n\np: Devas, send us happiness and make us wealthy, letting us singers prosper, O ye Maruts. Bethink you of our praise and of our friendship: ye from of old have riches to vouchsafe us.","people":["Dawn"],"places":[],"things":["Steeds","Born","Rivers","Waters","Offering","Shine","Stream","Gold","Mighty","Car","Praise","Voice","Heroes","Splendour","Offers","Excellent","People","Riches"],"groups":["Devas","Maruts","Fathers","Sons","Kings","Angirases","Man"],"concepts":["Good","Heavenly","Friendship","Offering","Swift"],"hash":"md5-KWnsllry+XlLTw2qgxo11w==","created":"Monday, April 8, 2024 - 10:51:55 PM"},{"id":"23a4e183-60ca-4fc7-b20c-51a89c5295cf","key":"10079","book":"10","title":"HYMN LXXIX. Agni.","link":"https://indra.ai/rigveda/hymns/10079.html","text":"p: I HAVE beheld the might of this Great Being. Immortal in the midst of tribes of mortals. His jaws now open and now shut together: much they devour, insatiately chewing.\n\np: His eyes are turned away, his head is hidden: unsated with his tongue he eats the fuel. With hands upraised, with reverence in the houses, for him they quickly bring his food together.\n\np: Seeking, as ’twere, his Mother's secret bosom, he, like a child, creeps on through wide-spread bushes. One he finds glowing like hot food made ready, and kissing deep within the earth's recmes.\n\np: This holy Law I tell you, Earth and Heaven: the Infant at his birth dovours his Parents. No knowledge of the Deva.have I, a mortal. Yea, Agni knoweth best, for he hath wisdom.\n\np: This man who quickly gives him food, who offers his gifts of oil and butter and supports him, - Him with his thousand eyes he closely looks on: thou showest him thy face from all sides, Agni.\n\np: Agni, hast thou committed sin or treason among the Devas? In ignorance I ask thee. Playing, not playing, he gold-hued and toothless, hath cut his food up as the knife a victim.\n\np: He born in wood hath yoked his horses rushing in all directions, held with reins that glitter. The well-born friend hath carved his food with Vasus: in all his limbs he hath increased and prospered.","people":["Agni","Deva"],"places":["Earth","Heaven"],"things":["Born","Reverence","Food","Might","Gold","Offers","Friend","Parents","Horses","Gifts"],"groups":["Devas","Mother","Child","Immortal","Man","Vasus"],"concepts":["Birth","Immortal","Holy","Wisdom"],"hash":"md5-00l4oLVTmH3C0Wj4rLOFaA==","created":"Monday, April 8, 2024 - 10:51:55 PM"},{"id":"850d5a6a-9889-491c-b2f1-eca786640073","key":"10080","book":"10","title":"HYMN LXXX. Agni.","link":"https://indra.ai/rigveda/hymns/10080.html","text":"p: AGNI bestows the fleet prize-winning courser: Agni, the hero famed and firm in duty. Agni pervades and decks the earth and heaven, and fills the fruitful dame who teems with heroes.\n\np: Blest be the wood that feeds the active Agni: within the two great worlds hath Agni entered. Agni impels a single man to battle, and with him rends in pieces many a foeman.\n\np: Agni rejoiced the car of him who praised lim, and from the waters burnt away jarutha. Agni saved Atri in the fiery cavem, and made Nrmedha rich with troops of children.\n\np: Agni hath granted wealth that decks the hero, and sent the sage who wins a thousand cattle. Agni hath made oblations rise to heaven: to every place are Agni's laws extended.\n\np: With songs of praise the Rsis call on Agni; on Agni, heroes worsted in the foray. Birds flying in the region call on Agni around a thousand cattle Agni wanders.\n\np: Races of human birth pay Agni worship, men who have sprung from Nahus' line adore him. Stablished in holy oil is Agni's pasture, on the Gandharva path of Law and Order.\n\np: The Rbhus fabricated prayer for Agni, and we with mighty hymns have called on Agni. Agni, most Youthful Deva, protect the singer: win us by worship, Agni, great possessions.","people":["Agni","Atri","Jarutha","Deva"],"places":["Earth","Heaven"],"things":["Worship","Waters","Singer","Wealth","Men","Mighty","Car","Praise","Heroes","Songs","Hero","Sage","Winning","call","Order","Cattle"],"groups":["Gandharva","Human","Rsis","Man","Rbhus"],"concepts":["Birth","Holy"],"hash":"md5-oLvIKzy0nKe8nVFKTQy4EQ==","created":"Monday, April 8, 2024 - 10:51:55 PM"},{"id":"585fa9cb-6ddd-4f70-af34-4eca16090893","key":"10081","book":"10","title":"HYMN LXXXI. Visvakarman.","link":"https://indra.ai/rigveda/hymns/10081.html","text":"p: HE who sate down as Hotar-priest, the Rsi, our Father, offering up all things existing. He, seeking through his wish a great possession, came among men on earth as archetypal.\n\np: What was the place whereon he took his station? What was it that supported him? How was it? Whence Visvakarman, seeing all, producing the earth, with mighty power disclosed the heavens.\n\np: He who hath eyes on all sides round about him, a mouth on all sides, arms and feet on all sides. He, the Sole Deva, producing earth and heaven, weldeth them, with his arms as wings, together.\n\np: What was the tree, what wood in sooth produced it, from which they fashioned out the earth and heaven? Ye thoughtful men inquire within your spirit whereon he stood when he established all things.\n\np: Nine highest, lowest, offerings natures, and these thy mid-most here, O Visvakarman, Teach thou thy friends at offering, O Blessed, and come thyself, exalted, to our worship.\n\np: Bring thou thyself, exalted with oblation, O Visvakarman, Earth and Heaven to worship. Let other men around us live in folly here let us have a rich and liberal patron.\n\np: Let us invoke to-day, to aid our labour, the Lord of Speech, the thought-swift Visvakarman. May he hear kindly all our invocations who gives all bliss for aid, whose works are righteous.","people":["Hotar","Deva","Visvakarman"],"places":["Earth","Heaven"],"things":["Worship","Lord","Offering","Men","Mighty","Offerings","Friends","Bliss","Wings","Spirit"],"groups":["Father"],"concepts":["Offering","Offerings","Swift","Speech"],"hash":"md5-jO+UvboofWYn019JwlEbdQ==","created":"Monday, April 8, 2024 - 10:51:55 PM"},{"id":"85e6fcf5-ce81-474f-a63f-fa4f9403cca1","key":"10082","book":"10","title":"HYMN LXXXII. Visvakarman.","link":"https://indra.ai/rigveda/hymns/10082.html","text":"p: THE Father of the eye, the Wise in spirit, created both these worlds submerged in fatness. Then when the eastern ends were firmly fastened, the heavens and the earth were far extended.\n\np: Mighty in mind and power is Visvakarman, maker, Disposer, and most lofty Presence. Their offerings joy in rich juice where they value One, only One, beyond the Seven Rsis.\n\np: Father who made us, he who, as Disposer, knoweth all races and all things existing, Even he alone, the Deities' narne-giver,him other beings seek for information.\n\np: To him in offerings they offered treasure.s.Rsis of old, in numerous troops, as singers, who, in the distant, near, and lower region, made ready all these things that have existence.\n\np: That which is earlier than this earth and heaven, before the Asuras and Devas had being. What was the germ primeval which the waters received where all the Devas were seen together?\n\np: The waters, they received that germ primeval wherein the Devas were gathefed all together. It rested set upon the Unborn's navel, that One wherein abide all things existing.\n\np: Ye will not find him who produced these creatures: another thing hath risen up among you. Enwrapt in misty cloud, with lips that stammer, hymn-chanters wander and are discontented.","people":["Visvakarman"],"places":["Earth","Heaven"],"things":["Waters","Treasure","Juice","Joy","Wise","Mighty","Hymn","Offerings","Spirit"],"groups":["Devas","Asuras","Deities","Father","Rsis"],"concepts":["Offerings","Giver"],"hash":"md5-Mp6wDiBkNbsPSi2MScixYg==","created":"Monday, April 8, 2024 - 10:51:55 PM"},{"id":"59e62989-1ae3-4338-acca-081ee0beb20a","key":"10083","book":"10","title":"HYMN LXXXII. Manyu.","link":"https://indra.ai/rigveda/hymns/10083.html","text":"p: HE who hath reverenced thee, Manyu, destructive bolt, breeds for himself forthwith all conquering energy. Arya and Dasa will we conquer with thine aid, with thee the Conqueror, with conquest conquest-sped.\n\np: Manyu was Indra, yea, the Deva, was Manyu, Manyu was Hotar, Varuna, Jatavedas. The tribes of human lineage worship Manyu. Accordant with thy fervour, Manyu, guard us.\n\np: Come hither, Manyu, mightier tham the mighty; chase, with thy fervour for ally, our foemen. Slayer of foes, of Vrtra, and of Dasyu, bring thou to us all kinds of wealth and treasure..\n\np: For thou art, Manyu, of surpassing vigour, fierce, queller of the foe, and self-existent, Shared by all men, victorious, subduer: vouchsafe to us superior strengith in battles.\n\np: I have departed, still without a portion, wise Deva. according to thy will, the Mighty. I, feeble man, was wroth thee, O Manyu I am myself; come thou , to give us vigour.\n\np: Come hither. I am all thine own; advancing turn thou to me, Victorious, All-supporter! Come to me, Manyu, Wielder of the Thunder: bethink thee of thy friend, and subdue the Dasyus.\n\np: Approach, and on my right hand hold thy station: so shall we subdue a multitude of foemen. The best of meath I offer to support thee. May we be first to drink thereof in quiet.","people":["Indra","Vrtra","Varuna","Hotar","Deva"],"places":[],"things":["Worship","Meath","Treasure","Wealth","Men","Wise","Mighty","Friend"],"groups":["Dasyus","Dasyu","Jatavedas","Human","Man"],"concepts":[],"hash":"md5-vZxdfujqIp22msUqMC0UYg==","created":"Monday, April 8, 2024 - 10:51:55 PM"},{"id":"c45d26c9-254e-427b-8279-25747a8a4e54","key":"10084","book":"10","title":"HYMN LXXXIV. Manyu.","link":"https://indra.ai/rigveda/hymns/10084.html","text":"p: BORNE on with thee, O Manyu girt by Maruts, let our brave men, impetuous, bursting forward, March on, like flames of fire in form, exulting, with pointed arrows, sharpening their weapons.\n\np: Flashing like fire, be thou, O conquering Manyu, invoked, O Victor, as our army's leader. Slay thou our foes, distribute their possessions: show forth thy vigour, scatter those who hate us.\n\np: O Manyu, overcome thou our assailant on! breaking, subduing, crushing down the foemen. They have not hindered thine impetuous vigour: Mighty, Sole born! thou makest them thy subjects.\n\np: Alone or many thou art worshipped, Manyu: sharpen the spirit of each clan for battle. With thee to aid, O thou of perfect splendour, we will uplift the glorious shout for conquest.\n\np: Unyielding bringing victory like Indra, O Manyu, be thou here our Sovran Ruler. To thy dear name, O Victor, we sing praises: we know the spring from which thou art come hither.\n\np: Twin-born with power, destructive bolt of thunder, the highest conquering might is thine, Subduer! Be friendly to its in thy spirit, Manyu, O Much-invoked, in shock of mighty battle.\n\np: For spoil let Varuna and Manyu give us the wealth of both sides gathered and collected; And let our enemies with stricken spirits, o’erwhelmed with terror, slink away defeated.","people":["Indra","Varuna"],"places":[],"things":["Victory","Leader","Born","Glorious","Wealth","Men","Might","Mighty","Brave","Form","Splendour","spoil","Spirit","Sovran Ruler"],"groups":["Maruts"],"concepts":["Worshipped","Glorious"],"hash":"md5-z2DIqWkOx44YerWYcnS0nw==","created":"Monday, April 8, 2024 - 10:51:55 PM"},{"id":"6252b863-95e7-49d8-9d2b-32b96038e293","key":"10085","book":"10","title":"HYMN LXXXV. Surya's Bridal.","link":"https://indra.ai/rigveda/hymns/10085.html","text":"p: TRUTH is the base that bears the earth; by Surya are the heavens sustained. By Law the Adityas stand secure, and Soma holds his place in heaven.\n\np: By Soma are the Adityas strong, by Soma mighty is the earth. Thus Soma in the midst of all these constellations hath his place.\n\np: One thinks, when they have brayed the plant, that he hath drunk the Soma's juice; Of him whom Brahmans truly know as Soma no on ever tastes.\n\np: Soma, secured by sheltering rules, guarded by hymns in Brhati, Thou standest listening to the stones none tastes of thee who dwells on earth.\n\np: When they begin to drink thee then, O Deva, thou swellest out again. Vayu is Soma's guardian Deva. The Moon is that which shapes the years.\n\np: Raibhi was her dear bridal friend, and Narasamsi led her home. Lovely was Surya's robe: she came to that which Gatha had adorned.\n\np: Thought was the pillow of her couch, sight was the unguent for her eyes: Her treasure. was earth and heaven.ẉhen Surya went unto her Lord.\n\np: Hymns were the cross-bars of the pole, Kurira-metre decked the car: The bridesmen were the Asvin Pair Agni was leader of the train.\n\np: Soma was he who wooed the maid: the groomsmen were both Asvins, when The SunDeva.Savitar bestowed his willing Surya on her Lord.\n\np: Her spirit was the bridal car; the covering thereof was heaven: Bright were both Steers that drew it when Surya approached his, home.\n\np: Thy Steers were steady, kept in place by holy verse and Sama-hymn: All car were thy two chariot wheels: thy path was tremulous in the sky,\n\np: Clean, as thou wentest, were thy wheels wind, was the axle fastened there. Surya, proceeding to her Lord, mounted a spirit-fashioried car.\n\np: The bridal pomp of Surya, which Savitar started, moved along. In Magha days are oxen slain, in Arjuris they wed the bride.\n\np: When on your three-wheeled chariot, O Asvins, ye came as wooers unto Surya's bridal, then all the Devas agreed to your proposal Pusan as Son elected you as Fathers.\n\np: O ye Two Lords of lustre, then when ye to Surya's wooing came, Where was one chariot wheel of yours? Where stood ye for die Sire's command?\n\np: The Brahmans, by their seasons, know, O Surya, those two wheels of thine: One kept concealed, those only who are skilled in highest truths have learned.\n\np: To Surya and the Deities, to Mitra and to Varuna. Who know aright the thing that is, this adoration have I paid.\n\np: By their own power these Twain in close succession move; They go as playing children round  'the offering. One of the Pair beholdeth all existing things; the other ordereth seasons and is born again.\n\np: He, born afresh, is new and new forever ensign of days he goes before the Mornings Coming, he orders f6r the Devas their portion. The Moon prolongs the days of our existence.\n\np: Mount this, all-shaped, gold-hued, with strong wheels, fashioned of Kimsuka and Salmali, light-rolling, Bound for the world of life immortal, Surya: make for thy lord a happy bridal journey.\n\np: Rise up from hence: this maiden hath a husband. I laud Visvavasu with hymns and homage. Seek in her father's home another fair one, and find the portion from of old assigned thee.\n\np: Rise up from hence, Visvavasu: with reverence we worship thee. Seek thou another willing maid, and with her husband leave the bride.\n\np: Straight in direction be the path:s, and thornless, whereon our fellows travel to the wooing. Let Aryaman and Bhaga lead us: perfect, O Devas, the union of the wife and husband.\n\np: Now from the noose of Varuna I free thee, wherewith Most Blessed Savitar hath bound thee. In Law's seat, to the world of virtuous action, I give thee up uninjured with thy consort.\n\np: Hence, and not thence, I send these free. I make thee softly fettered there. That, Bounteous Indra, sh. May live blest in her fortune and her sons.\n\np: Let Pusan take thy hand and hence conduct thee. May the two Asvins on their car transport thee. Go to the house to be the household's mistress and speak as lady ito thy gathered people.\n\np: Happy be thou and prosper witlh thy children here: be vigilant to rule thy household in this home. Closely unite thy body with this; man, thy lord. So shall ye, full of years, address your company.\n\np: Her hue is blue and red: the fienod who clingeth close is driven off. Well thrive the kinsmen of this bride the husband is bourid fast in bonds.\n\np: Give thou the woollen robe away: deal treasure. to the Brahman monks. This female fiend hath got her feet, and as a wife attends her lord.\n\np: Unlovely is his body when it glistens with this wicked fiend, what time the husband wraps about his limbs the garment of his wife.\n\np: Consumptions, from her people, which follow the bride's resplendent train. These let the Holy Devas again bear to the place from which they came.\n\np: Let not the highway thieves who lie in ambush find the wedded pair. By pleasant ways let them escape the danger, and let foes depart.\n\np: Signs of good fortune mark the bride come all of you and look at her. Wish her prosperity, and then return unto your homes again.\n\np: Pungent is this, and bitter this, filled, as it were, with arrow-barbs, Empoisoned andnot fit for use. The Brahman who knows Surya well deserves the garment of the bride.\n\np: The fringe, the cloth that decks her head, and then the triply parted robe. Behold the hues which Surya wears these doth the Brahman purify.\n\np: I take thy hand in mine for happy fortune that tho. Mayst reach old age with me thy husband. Devas, Aryaman, Bhaga, Savitar, purandhi, have given thee to be my household's mistress.\n\np: O Pusan, send her on as most auspicious, her who shall be the sharer of my pleasures; Her who shall twine her loving arms about me, and welcome all my love and mine embraces.\n\np: For thee, with bridal train, they, first, escorted Surya to her home. Give to the husband in return, Agni, the wife with progeny.\n\np: Agni hath given the bride again with splendour and with ample life. Long lived be he who is her lord; a hundred autumns let him live.\n\np: Soma obtained her first of all; next the Gandharva was her lord. Agai was thy third husband: now one born of woman is thy fourth.\n\np: Soma to the Gandharva, and to Agni the Gandharva gave: And Agni hath bestowed on me riches and sons and this my spouse.\n\np: Be ye not parted; dwell ye here reach the full time of human life. With sons and grandsons sport and play, rejoicing in your own abode.\n\np: May Prajapati bring children forth to us. May Aryaman adorn us till old age come nigh. Not inauspicious enter thou thy husband's house: bring blessing to our bipeds and our quadrupeds.\n\np: Not evil-eyed, no slayer of thy husband, bring weal to cattle, radiant, gentlehearted; Loving the Devas, delightful, bearing heroes, bring blessing to our quadrupeds and bipeds.\n\np: O Bounteous Indra, make this bride blest in her sons and fortunate. Vouchsafe to her ten sons, and make her husband the eleventh man.\n\np: Over thy husband's father and thy husband's mother bear full sway. Over the sister of thy lord, over his brothers rule supreme.\n\np: May the Universal Devas, s. May the Waters join our hearts. May Matarisvan, Dhatar, and Destri together bind us close.","people":["Dhatar","Indra","Soma","Agni","Vayu","Mitra","Varuna","Asvins","Savitar","Pusan","Bhaga","Deva","Surya","Aryaman","Visvavasu","Prajapati","Narasamsi","Arjuris","Magha","Purandhi","Matarisvan","Destri","SunDeva"],"places":["Earth","Heaven","Sky"],"things":["Worship","Leader","Journey","Lord","Seasons","Born","Reverence","Soma","Waters","Offering","Light","Moon","Treasure","Juice","Gold","Home","Strong","Mighty","Car","Blessing","Hymn","Heroes","Splendour","People","Friend","Kimsuka","Salmali","Riches","Spouse","Pillow","Couch","Bridal","Cattle","Life","Spirit","Wheel"],"groups":["Devas","Fathers","Sons","Deities","Brahmans","Gandharva","Human","Maid","Steers","Father","Mother","Son","Sister","Wife","Husband","Immortal","Progeny","Man","Woman","Adityas","Monks"],"concepts":["Good","Evil","Life","Love","Immortal","Holy","Offering","Auspicious","Truth"],"hash":"md5-C+33/xInsLX7RWZ/LifWSw==","created":"Monday, April 8, 2024 - 10:51:55 PM"},{"id":"47c37e35-982a-4a9b-befd-cfba77ef3d5c","key":"10086","book":"10","title":"HYMN LXXXVI. Indra.","link":"https://indra.ai/rigveda/hymns/10086.html","text":"p: MEN have abstained from pouring juice they count not Indra as a Deva. Where at the votary's store my friend Vrsakapi hath drunk his fill. Supreme is Indra over all.\n\np: Thou, indra, heedless passest by the ill Vrsakapi hath wrought; Yet nowhere else thou findest place wherein to drink the Soma juice. Supreme is Indra over all.\n\np: What hath he done to injure thee, this tawny beast Vrsakapi, with whom thou art so angry now? What is the votary's foodful store? Supreme is Indra over all.\n\np: Soo. May the hound who hunts the boar seize him and bite him in the car, O Indra, that Vrsakapi whom thou protectest as a friend, Supreme is Indra over all.\n\np: Kapi hath marred the beauteous things, all deftly wrought, that were my joy. In pieces will I rend his head; the sinner's portion sball be woo. Supreme is Indra over all.\n\np: No Dame hath ampler charms than 1, or greater wealth of love's delights. None with more ardour offers all her beauty to her lord's embrace. Supreme is Indra over all.\n\np: Mother whose love is quickly wibn, I say what verily will be. My,breast, O Mother, and my head and both my hips seem quivering. Supreme is Indra over all.\n\np: Dame with the lovely hands and arms, with broad hair-plaits add ample hips, Why, O thou Hero's wife, art thou angry with our Vrsakapi? Supreme is Indra over all.\n\np: This noxious creature. looks on me as one bereft of hero's love, Yet Heroes for my sons have I, the Maruts’ Friend and Indra's Queen. Supreme is Indra over all.\n\np: From olden time the matron goes to feast and general offering. Mother of Heroes, indra's Queen, the rite's ordainer is extolled. Supreme is Indra over all.\n\np: So have I heard Indrani called most fortunate among these Dames, for never shall her Consort die in future time through length of days. Supreme is Indra overall.\n\np: Never, indralni, have I joyed without my friend Vrsakapi, whose welcome offering here, made pure with water, goeth to the Devas. Supreme is Indra over all.\n\np: Wealthy Vrsakapayi, blest with sons and consorts of thy sons, indra will eat thy bulls, thy dear oblation that effecteth much. Supreme is Indra over all.\n\np: Fifteen in number, then, for me a score of bullocks they prepare, and I devour the fat thereof: they fill my belly full with food. Supreme is Indra over all.\n\np: Like as a bull with pointed horn, loud bellowing amid the herds, Sweet to thine heart, O Indra, is the brew which she who tends thee pours. Supreme is Indra over all.\n\np: O Indra this Vrsakapi hath found a slain wild animal, Dresser, and new-made pan, and knife, and wagon with a load of wood. Supreme is Indra over all.\n\np: Distinguishing the Dasa and the Arya, viewing all, I go. I look upon the wise, and drink the simple votary's Soma juice. Supreme is Indra over all.\n\np: The desert plains and steep descents, how many leagues in length they spread! Go to the nearest houses, go unto thine home, Vrsakapi. Supreme is Indra over all.\n\np: Turn thee again Vrsakapi: we twain will bring thee happiness. Thou goest homeward on thy way along this path which leads to sleep. Supreme is Indra over all.\n\np: When, indra and Vrsakapi, ye travelled upward to your home, Where was that noisome beast, to whom went it, the beast that troubles man? Supreme is Indra over all.\n\np: Daughter of Manu, parsu bare a score of children at a birth. Her portion verily was bliss although her burthen caused her grief.","people":["Indra","Soma","Deva","Indrani","Matron"],"places":[],"things":["Lord","Soma","Water","Offering","Wealth","Food","Men","Juice","Joy","Beauty","Home","Wise","Car","Heroes","Offers","Bliss","Friend","Hero"],"groups":["Devas","Maruts","Sons","Dames","Mother","Wife","Man"],"concepts":["Birth","Love","Offering"],"hash":"md5-DDkCtPl8ud9BM/M8c7AdlA==","created":"Monday, April 8, 2024 - 10:51:55 PM"},{"id":"f6fea284-f982-493c-b354-b377cb2d96ca","key":"10087","book":"10","title":"HYMN LXXXVII. Agni.","link":"https://indra.ai/rigveda/hymns/10087.html","text":"p: I BALM with oil the mighty Raksas-slayer; to the most famous Friend I come for shelter Enkindled, sharpened by our rites. May Agni protect us in the day and night from evil.\n\np: O Jatavedas with the teeth of iron enkindled with thy flame attack the demons. Seize with thy longue the foolish gods' adorers: rend, put within thy mouth the raw-flesh caters.\n\np: Apply thy teeth, the upper and the lower, thou who hast both, enkindled and destroying. Roam also in the air, O King, around us, and with thy jaws assail the wicked spirits.\n\np: Bending thy shafts through offers, Agni, whetting their points with song as if with whetstones, pierce to the heart therewith the Yatudhanas, and break their arms uplifed to attack thee.\n\np: Pierce through the Yatudhana's skin, O Agni; let the destroying dart with fire consume him. Rend his joints, Jatavedas, let the cater of flesh, flesh-seeking, track his mangled body.\n\np: Where now thou seest Agni Jatavedas, one of these demons standing still or roaming, or flying on those paths in air's midregion, sharpen the shaft and as an archer pierce him.\n\np: Tear from the evil spirit, Jatavedas, what he hath seized and with his spears hath captured. Blazing before him strike him down, O Agni; let spotted carrion-eating kites devour him.\n\np: Here tell this forth, O Agni: whosoever is, he himself, or acteth as, a demonhim grasp, O thou Most Youthful, with thy fuel. to the Mati-seer's eye give him as booty.\n\np: With keen glance guard  'the offering, O Agni: thou Sage, conduct it onward to the Vasus. Let not the fiends, O Man-beholder, harm thee burning against the Raksasas to subdue them.\n\np: Look on the fiend mid men, as Man-beholder: rend thou his three extremities in pieces. Demolish with thy flame his ribs, O Agni, the Yatudhana's root destroy thou triply.\n\np: Thrice, Agni, let thy noose surround the demon who with his falsehood injures Holy Order. Loud roaring with thy flame, O Jatavedas, crush him and cast him down before the singer.\n\np: Lead thou the worshipper that eye, O Agni, wherewith thou lookest on the hoof-armed demon. With light celestial in Atharvan's manner burn up the foot who ruins truth with falsehood.\n\np: Agni, what curse the pair this day have uttered, what heated word the worshippers have spoken, Each arrowy taunt sped from the angry spirit.pierce to the heart therewith the Yatudhanas.\n\np: With fervent heat exterminate the demons; destroy the fiends with burning flame, O Agni. Destroy with fire the foolish gods' adorers; blaze and destrepy the insatiable monsters.\n\np: May Devas destroy this day the evil-doe. May each hot curse of his return and blast him. Let arrows pierce the liar in his vitals, and Visva's net enclose the Yatudhana.\n\np: The fiend who smears himself with flesh of cattle, with flesh of horses and of human bodies, who steals the MilchCow's milk away, O Agni.tear off the heads of such with fiery fury.\n\np: The cow gives milk each year, O Man-regarder: let not the Yatudhana ever taste it. If one would glut him with the biesting, Agni, pierce with thy flame his vitals as he meets thee.\n\np: Let the fiends drink the poison of the cattle. May Aditi cast off the evildoers. May the Deva.Savitar give them up to ruin, and be their share of plants and herbs denied them.\n\np: Agni, from days of old thou slayest demons: never shall Raksasas in fight o’ercome thee. Burn up the foolish ones, the flesh-devourers: let none of them escape thine heavenly arrow.\n\np: Guard us, O Agni, from above and under, protect us fl-om behind us and before us; An. May thy flames, most fierce and never wasting, glowing with fervent heat, consume the sinner.\n\np: From rear, from front, from under, from above us, O King, protect us as a Sage with wisdom. Guard to old age thy friend, O Friend, Eternal: O Agni, as Immortal, guard us mortals.\n\np: We set thee round us as a fort, victorious Agni, thee a Sage, Of hero lineage, day by day, destroyer of our treacherous foes.\n\np: Burn with thy poison turned against the treacherous brood of Raksasas, O Agni, with thy sharpened glow, with lances armed with points of flame.\n\np: Burn thou the paired Kimidins, brun, Agni, the Yatudhana pairs. I sharpen thee, infallible, with hymns. O Sage, be vigilant.\n\np: Shoot forth, O Agni, with thy flame demolish them on every side. Break thou the Yatudhana's strength, the vigour of the Raksasa.","people":["Agni","Savitar","Deva","Raksasas","Aditi"],"places":[],"things":["Milk","Singer","Offering","Light","Air","Men","Song","Mighty","Worshipper","Offers","Friend","Hero","King","Sage","Cow","Horses","Order","Cattle","Spirit","MilchCow"],"groups":["Devas","Jatavedas","Worshippers","Human","Immortal","Man","Vasus"],"concepts":["Celestial","Evil","Heavenly","Immortal","Holy","Strength","Wisdom","Offering","Truth"],"hash":"md5-xFUefqudXkzcsmFXGTQDwQ==","created":"Monday, April 8, 2024 - 10:51:55 PM"},{"id":"bcf8ae04-32ef-45a3-8d1a-a426ff2eb68e","key":"10088","book":"10","title":"HYMN LXXXVIII. Agni.","link":"https://indra.ai/rigveda/hymns/10088.html","text":"p: DEAR, ageless offerings drink is offered in light-discovering, heaven-pervading Agni. The Devas spread forth through his Celestial Nature, that he might bear the world up and sustain it.\n\np: The world was swallowed and concealed in darkness: Agni was born, and light became apparent. The Deities, the broad earth, and the heavens, and plants, and waters gloried in his friendship.\n\np: Inspired by Devas who claim our adoration, I now will laud Eternal Lofty Agnihim who hath spread abroad the earth with lustre, this heaven, and both the worlds, and air's mid-region.\n\np: Earliest Monk whom all the Devas accepted, and chose him, and anointed him with butter. He swiftly made all things that fly, stand, travel, all that hath motion, Agni Jatavedas.\n\np: Because thou, Agni, Jatavedas, stoodest at the world's head with thy refulgent splendour, We sent thee forth with hymns and songs and praises: thou filledst heaven and earth, Deva.meet for worship.\n\np: Head of the world is Agni in the night-time; then, as the Sun, at morn springs up and rises. Then to his task goes the prompt Monk foreknowing the wondrous power of Devas who must be honoured.\n\np: Lovely is he who, kindled in his greatness, hath shone forth, seated in the heavens, refulgent. With resonant hymns all Devas who guard our bodies have offered up oblation in this Agni.\n\np: First the Devas brought the hymnal into being; then they engendered Agni, then oblation. He was their offering that guards our bodies: him the heavens know, the earth, the waters know him.\n\np: He, Agni, whom the Devas have generated, in whom they offered up all worlds and creatures. He with his bright glow heated earth and heaven, urging himself right onward in his grandeur.\n\np: Then by the laud the Devas engendered Agni in heaven, who fills both worlds through strength and vigour. They made him to appear in threefold essence: he ripens plants of every form and nature.\n\np: What time the Devas, whose due is worship, set him as Surya, Son of Aditi, in heaven, when the Pair, ever wandering, sprang to being, all creatures that existed looked upon them.\n\np: For all the world of life the Devas made Agni Vaisvanara to be the days' bright Banner. Him who hath spread abroad the radiant Mornings, and, coming with his light, unveils the darkness.\n\np: The wise and holy Deities engendered Agni Vaisvanara whom age ne’er touches. The Ancient Star that wanders on forever, lofty and. strong, Lord of the Living Being.\n\np: We call upon the Sage with holy verses, Agni Vaisvanara the ever-beaming, who hath surpassed both heaven and earth in greatness: he is a Deva.below, a Deva.above us.\n\np: I have heard mention of two several pathways, ways of the Fathers and of Devas and mortals. On these two paths each moving creature. travels, each thing between the Father and the Mother.\n\np: These two united paths bear him who journeys born from the head and pondered with the spirit He stands directed to all things existing, hasting, unresting in his fiery splendour.\n\np: Which of us twain knows where they speak together, upper and lower of the two rite-leaders? Our friends have helped to gather our assembly. They came to offering; who will announce it?\n\np: How many are the Fires and Suns in number? What is the number of the Dawns and Waters? Not jestingly I speak to you, O Fathers. Sages, I ask you this for information.\n\np: As great as is the fair-winged Morning's presence to him who dwells beside us, Matarisvan! Is what the Brahman does when he approaches to offering and sits below the Hotar.","people":["Agni","Hotar","Deva","Vaisvanara","Surya","Aditi","Matarisvan"],"places":["Earth","Heaven"],"things":["Worship","Lord","Born","Waters","Offering","Light","Air","Sun","Might","Wise","Strong","Form","Splendour","Offerings","Friends","Songs","Sage","call","Morning","Life","Spirit"],"groups":["Devas","Jatavedas","Fathers","Deities","Dawns","Father","Mother","Son"],"concepts":["Celestial","Life","Friendship","Holy","Strength","Offering","Offerings"],"hash":"md5-IdOWn1Ugo6wETLZpJQUhJw==","created":"Monday, April 8, 2024 - 10:51:55 PM"},{"id":"f52a99a2-5440-490e-bd0f-962a77129ff8","key":"10089","book":"10","title":"HYMN LXXXIX. Indra.","link":"https://indra.ai/rigveda/hymns/10089.html","text":"p: I WILL extol the most heroic Indra who with his might forced earth and sky asunder. Who hath filled all with width as man's Upholder, surpassing floods and rivers in his greatness.\n\np: Surya is he: throughout the wide expanses shall Indra turn him, swift as car-wheels, hitherlike a stream resting not but ever active he hath conquered, with light, the black-hued darkness.\n\np: To him I sing a holy prayer, incessant new, matchless, common to the earth and heaven, who marks, as they were backs, all living creatures: ne’er doth he fail a friend, the noble Indra.\n\np: I will send forth my songs in flow unceasing, like water from the ocean's depth, to Indra. Who to his car on both its sides securely hath fixed the earth and heaven as with an axle.\n\np: Rousing with draughts, the Shaker, rushing onward, impetuous, very strong, armed as with arrows Is Soma; forest trees and all the bushes deceive not Indra with their offered likeness.\n\np: Soma hath flowed to him whom naught can equal, the earth, the heavens, the firmament, the mountains. When heightened in his ire his indignation shatters the firm and breaks the strong in pieces.\n\np: As an axe fells the tree so be slew Vrtra, brake down the strongholds and dug out the rivers. He cleft the mountain like a new-made pitcher. Indra brought forth the kine with his Companions.\n\np: Wise art thou, punisher of guilt, O Indra. The sword lops limbs, thou smitest down the sinner, the men who injure, as it were a comrade, the lofty Law of Varuna and Mitra.\n\np: Men who lead evil lives, who break agreements, and injure Varuna, Aryaman and Mitra. Against these . O Mighty Indra, sharpen, as furious death, thy Bull of fiery colour.\n\np: Indra is Sovran Lord of Earth and Heaven, indra is Lord of waters and of mountains. Indra is Lord of prosperers and sages Indra must be invoked in rest and effort.\n\np: Vaster than days and nights, Giver of increase, vaster than firmament and flood of ocean, Vaster than bounds of earth and wind's extension, vaster than rivers and our lands is Indra.\n\np: Forward, as herald of refulgent Morning, let thine insatiate arrow fly, O Indra. And pierce, as ’twere a stone launched forth from heaven, with hottest blaze the men who love deception.\n\np: Him, verily, the moons, the mountains followed, the tall trees followed and the plants and herbage. Yearning with love both Worlds approached, the Waters waited on Indra when he first had being.\n\np: Where was the vengeful dart when thou, O Indra, clavest the demon ever beat on outrage? When fiends lay there upon the ground extended like cattle in the place of immolation?\n\np: Those who are set in enmity against us, the Oganas, O Indra, waxen mighty. Let blinding darkness follow those our foemen, while these shall have bright shining nights to light them.\n\np: May plentiful libations of the people, and singing Rsis’ holy prayers rejoice thee. Hearing with love this common invocation, come unto us, pass by all those who praise thee.\n\np: O Indra, thu. May we be made partakers of thy new favours that shall bring us profit. Singing with love. May we the Visvamitras win daylight even now through thee, O Indra.\n\np: Call we on Maghavan, auspicious Indra, best hero in the fight where spoil is gathered, the Strong who listens, who gives aid in battles, who subdues the Vrtras, wins and gathers riches.","people":["Indra","Soma","Vrtra","Mitra","Varuna","Maghavan","Surya","Aryaman"],"places":["Ocean","Earth","Heaven","Firmament","Sky"],"things":["Lord","Mountains","Rivers","Soma","Waters","Water","Light","Men","Stream","Flow","Might","Wise","Strong","Mighty","Car","Praise","People","Libations","Songs","Friend","Hero","call","spoil","Riches","Morning","Cattle","Death"],"groups":["Rsis","Man","Vrtras"],"concepts":["Evil","Death","Heroic","Love","Strong who Listens","Holy","Giver","Auspicious","Libations","Swift","Noble"],"hash":"md5-OtDr/Ug68U7Jy67eDDCk4A==","created":"Monday, April 8, 2024 - 10:51:55 PM"},{"id":"4044905b-e660-489a-9086-8b2c21dda384","key":"10090","book":"10","title":"HYMN XC. Purusa.","link":"https://indra.ai/rigveda/hymns/10090.html","text":"p: A THOUSAND heads hath Purusa, a thousand eyes, a thousand feet. On every side pervading earth he fills a space ten fingers wide.\n\np: This Purusa is all that yet hath been and all that is to be; The Lord of Immortality which waxes greater still by food.\n\np: So mighty is his greatness; yea, greater than this is Purusa. All creatures are one-fourth of him, three-fourths eternal life in heaven.\n\np: With three-fourths Purusa went up: one-fourth of him again was here. Thence he strode out to every side over what cats not and what cats.\n\np: From him Viraj was born; again Purusa from Viraj was born. As soon as he was born he spread eas ward and wes ward o’er the earth.\n\np: When Devas prepared  'the offering with Purusa as their offering, Its oil was spring, the holy gift was autumn; summer was the wood.\n\np: They balmed as victim on the grass Purusa born in earliest time. With him the Deities and all Sadhyas and Rsis offered.\n\np: From that great general offering the dripping fat was gathered up. He formed the creatures of-the air, and animals both wild and tame.\n\np: From that great general offering Rcas and Sama-hymns were born: Therefrom were spells and charms produced; the Yajus had its birth from it.\n\np: From it were horses born, from it all cattle with two rows of teeth: From it were generated kine, from it the goats and sheep were born.\n\np: When they divided Purusa how many portions did they make? What do they call his mouth, his arms? What do they call his thighs and feet?\n\np: The Brahman was his mouth, of both his arms was the Rajanya made. His thighs became the Vaisya, from his feet the Sudra was produced.\n\np: The Moon was gendered from his mind, and from his eye the Sun had birth; Indra and Agni from his mouth were born, and Vayu from his breath.\n\np: Forth from his navel came mid-air the sky was fashioned from his head Earth from his feet, and from his car the regions. Thus they formed the worlds.\n\np: Seven fencing-sticks had he, thrice seven layers of fuel were prepared, when the Devas, offering offering, bound, as their victim, purusa.\n\np: Devas, sacrificing, offered the victim these were the earliest holy ordinances. The MightyOnes attained the height of heaven, there where the Sadhyas, Devas of old, are dwelling.","people":["Indra","Agni","Vayu"],"places":["Earth","Heaven","Mid-Air","Sky"],"things":["Lord","Born","Offering","Air","Sun","Moon","Food","Mighty","Grass","Car","Gift","Horses","call","Cattle","Life"],"groups":["Devas","Deities","Rsis","MightyOnes"],"concepts":["Birth","Life","Immortality","Holy","Offering"],"hash":"md5-B6vn7Xl4VA6UC1YkQ0epWg==","created":"Monday, April 8, 2024 - 10:51:55 PM"},{"id":"dbc3bf6b-13b5-463d-bebe-db28a8c17208","key":"10091","book":"10","title":"HYMN XCI. Agni.","link":"https://indra.ai/rigveda/hymns/10091.html","text":"p: BRISK, at the place of Ila, hymned by men who wake, our own familiar Friend is kindled in the house; Hotar of all oblation, worthy of our choice, Lord, beaming, trusty friend to one who loveth him.\n\np: He, excellent in glory, guest in every house, finds like a swift-winged bird a home in every tree. Benevolent to men, he scorns no living man: Friend to the tribes of men he dwells with every tribe.\n\np: Most sage with insight, passing skilful with thy powers art thou, O Agni, wise with wisdom, knowing all. As Vasu, thou alone art Lord of all good things, of all the treasure.s that the heavens and earth produce.\n\np: Foreknowing well, O Agni, thou in Ila's place hast occupied thy regular station balmed with oil. Marked are thy comings like the comings of the Dawns, the rays of him who shineth spotless as the Sun.\n\np: Thy glories are, as lightnings from the rainy cloud, marked, many-hued, like heralds of the Dawns’ approach, when, loosed to wander over plants and forest trees, thou crammest by thyself thy food into thy mouth.\n\np: Him, duly coming as their germ, have plants received: this Agni have maternal Waters brought to life. So in like manner do the forest trees and plants bear him within them and produce him evermore.\n\np: When, sped and urged by wind, thou spreadest thee abroad, swift piercing through thy food according to thy will, Thy never-ceasing blazes, longing to consume, like men on chariots, Agni, strive on every side.\n\np: Agni, the Hotar-priest who fills the assembly full, Waker of knowledge, chief Controller of the thought. Him, yea, none other than thyself, doth man elect at offerings offerings great and small alike.\n\np: Here, Agni, the arrangers, those attached to thee, elect thee as their Monk in sacred gatherings, when men with strewn clipt grass and offerings gifts offer thee entertainment, piously inclined.\n\np: Thine is the Herald's task and Cleanser's duly timed; Leader art thou, and Kindler for the pious man. Thou art Director, thou the ministering Monk, Lord and Master in our home.\n\np: When mortal man presents to thee Immortal Deva, Agni, his fuel or his offerings gift, then thou art his Adhvaryu, Hotar, messenger, callest the Devas and orderest  'the offering.\n\np: From us these hymns in concert have gone forth to him, these. holy words, these Rcas, songs and eulogies, Eager for wealth, to Jatavedas fain for wealth: when they have waxen strong they please their Strengthener.\n\np: This newest eulogy will I speak forth to him, the Ancient One who loves it. May he hear our voice. May it come near his heart and make it stir with love, as a fond well-dressed matron clings about her lord.\n\np: He in whom horses, bulls, oxen, and barren cows, and rams, when duly set apart, are offered up. To Agni, Soma-sprinkled, drinker of sweet juice, Disposer, with my heart I bring a fair hymn forth.\n\np: Into thy mouth is poured the offering, Agni, as Soma into cup, oil into ladle. Vouchsafe us wealth. strength-winning, blest with heroes, wealth lofty, praised by men, and full of splendour.","people":["Soma","Agni","Hotar","Deva","Ila","Matron","Vasu"],"places":["Earth"],"things":["Leader","Master","Lord","Soma","Waters","Chariots","Glory","Offering","Sun","Treasure","Wealth","Food","Men","Juice","Home","Wise","Strong","Grass","Chief","Voice","Hymn","Heroes","Gift","Splendour","Excellent","Powers","Offerings","Songs","Friend","Bird","Sage","Horses","Winning","Life","Gifts"],"groups":["Devas","Jatavedas","Dawns","Immortal","Man"],"concepts":["Good","Life","Love","Immortal","Holy","Sacred","Strength","Wisdom","Offering","Offerings","Ancient One","Swift"],"hash":"md5-43TZ4EgZENQesQEEFRRByQ==","created":"Monday, April 8, 2024 - 10:51:55 PM"},{"id":"e21ce8a8-f0ab-432e-bbc1-bdf168c6e339","key":"10092","book":"10","title":"HYMN XCII, Devas.","link":"https://indra.ai/rigveda/hymns/10092.html","text":"p: I PRAISE your Charioteer of offering, the Lord of men, Monk of the tribes, refulgent, Guest of night. Blazing amid dry plants, snatching amid the green, the Strong, the Holy Herald hath attained to heaven.\n\np: Him, Agni, Devas and men have made their chief support, who drinks the fatness and completes  'the offering. With kisses they caress the Grandson of the Red, like the swift ray of light, the Household Monk of Dawn.\n\np: Yea, we discriminate his and the niggard's ways: his branches evermore are sent forth to consume. When his terrific flames have reached the Immortal's world, then men remember and extol the Heavenly Folk.\n\np: For then the net of Law, Dyaus, and the wide expanse, Earthworship, and Devotion meet for highest praise, Varuna, indra, Mitra were of one accord, and Savitar and Bhaga, Lords of holy might.\n\np: Onward, with ever-roaming Rudra, speed the floods: over Aramati the Mighty have they run. With them Parijman, moving round his vast domain, loud bellowing, bedews all things that are within.\n\np: Straightway the Rudras, Maruts visiting all men, Falcons of Dyaus, home-dwellers with the Asura. Varuna, Mitra, Aryaman look on with these, and the swift-moving Indra with swift-moving Devas.\n\np: With Indra have they found enjoyment, they who toil, in the light's beauty, in the very Strong One's strength; The singers who in men's assemblies forged for him, according to his due, his friend the thunderbolt.\n\np: Even the Sun's Bay Coursers hath lie held in check: each one fears Indra as the mightiest of all. Unhindered, from the air's vault thunders day by day the loud triumphant breathing of the fearful Bull.\n\np: With humble adoration show this day your song of praise to mighty Rudra, Ruler of the brave: With whom, the Eager Ones, going their ordered course, he comes from heaven Self-bright, auspicious, strong to guard.\n\np: For these have spread abroad the fame of human kind, the Bull Narasamsa and Soma's brotherhood. Atharvan first by offers made men sure: through skill the Bhrgus were esteemed of all as Devas.\n\np: For these, the Earth and Heaven with their abundant seed, four-bodied Narasamsa, Yama, Aditi, Deva.Tvastar Wealth-bestower, the Rbhuksanas, Rodasi, Maruts, Visnu, claim and merit praise.\n\np: An. May he too give car, the Sage, from far away, the Dragon of the Deep, to this our yearning call. Ye Sun and Moon who dwell in heaven and move in turn, and with your thought, O Earth and Sky, observe this well.\n\np: Dear to all Devas. May Pusan guard the ways we go, the Waters’ child and Vayu help us to success. Sing lauds for your great bliss to Wind, the breath of all: ye Asvins prompt to hear, hear this upon your way.\n\np: With hymns of praise we sing him who is throned as Lord over these fearless tribes, the Self-resplendent One. We praise Night's youthful Lord benevolent to men, the foeless One, the free, with all celestial Dames.\n\np: By reason of his birth here Angiras first sang: the pressing-stones upraised beheld  'the offering- The stones through which the Sage became exceeding vast, and the sharp axe obtains in fight the beauteous place.","people":["Indra","Soma","Agni","Angiras","Vayu","Visnu","Mitra","Varuna","Asvins","Narasamsa","Tvastar","Savitar","Pusan","Bhaga","Deva","Dawn","Aditi","Yama","Rodasi","Aryaman"],"places":["Earth","Heaven","Sky"],"things":["Lord","Soma","Waters","Offering","Light","Air","Sun","Moon","Wealth","Men","Might","Humble","Song","Beauty","Help","Home","Strong","Mighty","Car","Chief","Praise","Brave","Offers","Pressing-Stones","Bliss","Friend","Sage","call"],"groups":["Devas","Asura","Dyaus","Maruts","Rudras","Bhrgus","Dames","Human","Child","Immortal","Brotherhood"],"concepts":["Celestial","Birth","Heavenly","Immortal","Holy","Strength","Offering","Auspicious","Swift","Dragon of the Deep"],"hash":"md5-DogIWL465DYlTuY1ZMOdfg==","created":"Monday, April 8, 2024 - 10:51:55 PM"},{"id":"8587ba07-283c-4339-b4ea-69825060cb19","key":"10093","book":"10","title":"HYMN XCIII, Devas.","link":"https://indra.ai/rigveda/hymns/10093.html","text":"p: MIGHTY are ye, and far-extended. Heaven and Earth: both Worlds are evermore to us like two young Dames. Guard us thereby from stronger foe; guard us hereby to give us strength.\n\np: In each succeeding offering that mortal honoureth the Devas. He who, most widely known and famed for happiness, inviteth them.\n\np: Ye who are Rulers over all, great is your sovran power as Devas. Ye all possess all majesty: all must be served in offering.\n\np: These are the joyous Kings of Immortality, parijman, Mitra, Aryaman, and Varuna. What else is Rudra, praised of men? the Maruts, Bhaga, pusana?\n\np: Come also to our dwelling, Lords of ample wealth, common partakers of our waters, Sun and Moon, when the great Dragon of the Deep hath settled down upon their floors.\n\np: And let the Asvins set us free.both Devas, and, with their Laws, Mitra and Varuna. Through woes, as over desert lands, he speeds to ample opulence.\n\np: Yea, let the Asvins Twain he gracious unto us, even Rudras, and all Devas, Bhaga, Rathaspati; Parijman, Rbhu, Vaja, O Lords of all wealth Rbhuksanas.\n\np: Prompt is Rbhuksan, prompt the worshipper's strong drink. May thy fleet Bay Steeds, thine who speedest on, approach. Not mans but Deva's is offering whose psalm is unassailable.\n\np: O Deva.Savitar, harmed by none, lauded, give us a place among wealthy princes. With his Car-steeds at once 'hath our Indra guided the reins and the car of these men.\n\np: To these men present here, O Heaven and Earth, to us grant lofty fame extending over all mankind. Give us a steed to win us strength, a steed with wealth for victory.\n\np: This speaker, indra—for thou art our Friend—wherever h. May be, guard thou, Victor! for help, ever for help Thy wisdom, Vasu! prosper him.\n\np: So have they strengthened this mine hymn which seems to take its bright path to the Sun, and reconciles the men: Thus forms a carpenter the yoke of horses, not to be displaced.\n\np: Whose chariot-seat hath come again laden with wealth and bright with gold, Lightly, with piercing ends, as ’twere two ranks of heroes ranged for fight.\n\np: This to Duḥsima Prthavana have I sung, to Vena, Rama, to the nobles, and the King. They yoked five hundred, and their love of us was famed upon their way.\n\np: Besides, they showed us seven-and-seventy horses here. Tanva at once displayed his gift, parthya at once displayed his gift; and straightway Mayava showed his.","people":["Indra","Mitra","Varuna","Asvins","Rbhu","Savitar","Bhaga","Deva","Aryaman","Vaja","Vasu","Rbhuksan"],"places":["Earth","Heaven"],"things":["Mankind","Victory","Steeds","Waters","Offering","Sun","Moon","Wealth","Men","Gold","Help","Strong","Mighty","Car","Worshipper","Hymn","Heroes","Gift","Friend","King","Horses"],"groups":["Devas","Maruts","Rudras","Kings","Dames"],"concepts":["Immortality","Love","Strength","Wisdom","Offering","Dragon of the Deep"],"hash":"md5-Tx2oT4gY/EApREah7WXJWg==","created":"Monday, April 8, 2024 - 10:51:55 PM"},{"id":"6c81f560-f1bf-4de2-9eda-a2a5f64c4125","key":"10094","book":"10","title":"HYMN XCIV. Press-stones.","link":"https://indra.ai/rigveda/hymns/10094.html","text":"p: LET these speak loudly forth; let us speak out aloud: to the loud speaking Pressing-stones address the speech; When, rich with Soma juice, Stones of the mountain, ye, united, swift to Indra bring the sound of praise.\n\np: They speak out like a hundred, like a thousand men: they cry aloud to us with their green-tinted mouths, While, pious Stones, they ply their task with piety, and, even before the Hotar, taste the offered food.\n\np: Loudly they speak, for they have found the savoury meath: they make a humming sound over the meat prepared. As they devour the branch of the Red-coloured Tree, these, the well-pastured Bulls, have uttered bellowings.\n\np: They cry aloud, with stron exhilarating drink, calling on Indra now, for they have found the meath. Bold, with the sisters they have danced, embraced by them, making the earth reecho with their ringing sound.\n\np: The Eagles have sent forth their cry aloft in heaven; in the sky's vault the dark impetuous ones have danced. Then downward to the nether stone's fixt place they sink, and, splendid as the Sun, effuse their copious stream.\n\np: Like strong ones drawing, they have put forth all their strength: the Bulls, harnessed together, bear the chariot-poles. When they have bellowed, panting, swallowing their food, the sound of their loud snorting is like that of steeds.\n\np: To these who have ten workers and a tenfold girth, to these who have ten yoke-straps and ten binding thongs, to these who bear ten reins, the eternal, sing ye praise, to these who bear ten carpoles, ten when they are yoked.\n\np: These Stones with ten conductors, rapid in their course, with lovely revolution travel round and round. They have been first to drink the flowing Soma juice, first to enjoy the milky fluid of the stalk.\n\np: These Soma-eaters kiss Indra's Bay-coloured Steeds: draining. the stalk they sit upon the ox's hide. Indra, when he hath drunk Soma-meath drawn by them, waxes in strength, is famed, is mighty as a Bull.\n\np:  Strong is your stalk; ye, verily, never shall be harmed; ye have refreshment, ye are ever satisfied. Fair are ye, as it were, through splendour of his wealth, his in whose offering, O Stones, ye find delight.\n\np: Bored deep, but not pierced through with holes, are ye, O Stones, not loosened, never weary, and exempt from death, Eternal, undiseased, moving in sundry ways, unthirsting, full of fatness, void of all desire.\n\np: Your fathers, verily, stand firm from age to age: they, loving rest, are not dissevered from their seat. Untouched by time, ne’er lacking green plants and green trees, they with their voice have caused the heavens and earth to hear.\n\np: This, this the Stones proclaim, what time they are disjoined, and when with ringing sounds they move and drink the balm. Like tillers of the ground when they are s wing seed, they mix the Soma, nor, devouring, minish it.\n\np: They have raised high their voice for juice, for offering, striking the Mother earth as though they danced thereon. So loose thou too his thought who hath effused the sap, and let the Stones which we are honouring be disjoined.","people":["Indra","Soma","Hotar"],"places":["Earth","Heaven","Sky"],"things":["Meath","Steeds","Soma","Offering","Sun","Wealth","Food","Men","Stream","Juice","Strong","Mighty","Praise","Voice","Delight","Splendour","Pressing-Stones","Death"],"groups":["Fathers","Mother"],"concepts":["Death","Strength","Offering","Swift","Speech"],"hash":"md5-7s4kY9zVdlI4E60OE/HUDg==","created":"Monday, April 8, 2024 - 10:51:55 PM"},{"id":"1c7628fd-56db-40b9-b9f3-83896ffdf8e0","key":"10095","book":"10","title":"HYMN XCV. Urvasi. Pururavas.","link":"https://indra.ai/rigveda/hymns/10095.html","text":"p: Ho there, my consort! Stay, thou fierce-souled lady, and let us reason for a while together. Such thoughts as these of ours, while yet unspoken in days gone by have never brought us comfort.\n\np: What am I now to do with this thy saying? I have gone from thee like the first of Mornings. Pururavas, return thou to thy dwelling: I, like the wind, am difficult to capture.\n\np: Like a shaft sent for glory from the quiver, or swift-steed winning cattle winning hundreds. The lightning seemed to flash, as cowards planned it. The minstrels bleated like a lamb in trouble.\n\np: Giving his father life and riches, from the near dwelling, when her lover craved her, she sought the home wherein she found her pleasure, accepting day and night her lord's embraces.\n\np: Thrice in the day didst thou embrace thy consort, though coldly she received thy fond caresses. To thy desires, pururavas, I yielded: so wast thou king, O hero, of my body.\n\np: The maids Sujirni, Sreni, Sumne-api, Charanyu, Granthini, and Hradecaksus. These like red kine have hastened forth, the bright ones, and like MilchCows have lowed in emulation.\n\np: While he was born the Dames sate down together, the Rivers with free kindness gave him nurture; And then, pururavas, the Devas increased thee for mighty battle, to destroy the Dasyus.\n\np: When I, a mortal, wooed to mine embraces these heavenly nymphs who laid aside their raimentlike a scared snake they fled from me in terror, like chariot horses when the car has touched them.\n\np: When, loving these Immortal Ones, the mortal hath converse with the nymphs as they allow him. Like swans they show the beauty of their bodies, like horses in their play they bite and nibble.\n\np: She who flashed brilliant as the falling lightning brought me delicious presents from the waters. Now from the flood be born a strong young hero May Uruvasi prolong her life forever\n\np: Thy birth hath made me drink from earthly milch-kine: this power, pururavas, hast thou vouchsafed me. I knew, and, warned thee, on that day. Thou wouldst not hear me. What sayest thou, when naught avails thee?\n\np: When will the son be born and seek his father? Mourner-like, will he weep when first he knows him? Who shall divide the accordant wife and husband, while fire is shining with thy consort's parents?\n\np: I will console him when his tears are falling: he shall not weep and cry for care that blesses. That which is thine, between us, will I send thee. Go home again, thou fool;thou hast not won me.\n\np: Thy lover shall flee forth this day forever, to seek, without return, the farthest distance. Then let his bed be in Destruction's bosom, and there let fierce rapacious wolves devour him.\n\np: Nay, do not die, pururavas, nor vanish: let not the evil-omened wolves devour thee. With women there can be no lasting friendship: hearts of hyenas are the hearts of women.\n\np: When amid men in altered shape I sojourned, and through four autumns spent the nights among them, I tasted once a day a drop of butter; and even now with that am I am contented.\n\np: I, her best love, call Urvasi to meet me, her who fills air and measures out the region. Let the gift brought by piety approach thee. Turn thou to me again: my heart is troubled.\n\np: Thus speak these Devas to thee, O son of Ila: As death hath verily got thee for his subject, Thy sons shall serve the Devas with their oblation, and thou, moreover, shalt rejoice in Svarga.","people":["Urvasi","Ila","Pururavas","Sujirni","Sreni","Sumne-api","Charanyu","Granthini","Hradecaksus","Uruvasi"],"places":["Svarga"],"things":["Lord","Born","Rivers","Waters","Glory","Air","Men","Beauty","Home","Strong","Mighty","Car","Gift","Hero","King","Parents","Swans","Horses","Winning","call","Riches","Cattle","Life","Death"],"groups":["Devas","Dasyus","Sons","Dames","Father","Son","Wife","Husband","Immortal"],"concepts":["Evil","Birth","Death","Life","Heavenly","Friendship","Love","Immortal","Swift"],"hash":"md5-LccP5c+x8WQsKy0obaKf5w==","created":"Monday, April 8, 2024 - 10:51:55 PM"},{"id":"e1a8a8d8-b444-4ca7-9fb0-78f8806deae0","key":"10096","book":"10","title":"HYMN XCVI. Indra.","link":"https://indra.ai/rigveda/hymns/10096.html","text":"p: In the great synod will I laud thy two Bay Steeds: I prize the sweet strong drink of thee the Warrior-Deva, His who pours lovely oil as ’twere with yellow drops. Let my songs enter thee whose form hath golden tints.\n\np: Ye who in concert sing unto the goldhued place, like Bay Steeds driving onward to the heavenly seat, for Indra laud ye strength allied with Tawny Steeds, laud him whom cows content as ’twere with yellow drops.\n\np: His is that thunderbolt, of iron, goldenhued, gold-coloured, very dear, and yellow in his arms; Bright with strong teeth, destroying with its tawny rage. In Indra are set fast all forms of golden hue.\n\np: As if a lovely ray were laid upon the sky, the golden thunderbolt spread out as in a race. That iron bolt with yellow jaw smote Ahi down. A thousand flames had he who bore the tawny-hued.\n\np: Thou when praised by men who offered of old. hadst pleasure in their lauds, O Indra golden-haired. All that befits thy song of praise thou welcornest, the perfect pleasant gift, O Golden-hued from birth.\n\np: These two dear Bays bring hither Indra on his car, Thunder-armed, joyous, meet for laud, to drink his fill. Many libations flow for him who loveth them: to Indra have the gold-hued Soma juices run.\n\np: Tle gold-hued drops have flowed to gratify his wish: the yellow dro s have urged the swift Bays to the Strong. He who speeds on with Bay Steeds even as he lists hath satisfied his longing for the golden drops.\n\np: At the swift draught Soma waxed in might, the Iron One with yellow beard and yellow hair. He, Lord of Tawny Coursers, Lord of fleet-foot Mares, will bear his Bay Steeds safely over all distress.\n\np: His yellow-coloured jaws, like ladles move apart, what time, for strength, he makes the yellow-tinted stir, when, while the bowl stands there, he grooms his Tawny Steeds, when he hath drunk strong drink, the sweet juice that he loves.\n\np: Yea, to the Dear One's seat in homes of heaven and earth the Bay Steeds' Lord hath whinnied like a horse for food. Then the great wish hath seized upon him mightily, and the Beloved One hath gained high power of life,\n\np: Thou, comprehending with thy might the earth and heaven, acceptest the dear hymn forever new and new. O Asura, disclose thou and make visible the Cow's beloved home to the bright golden Sun.\n\np: O Indra, let the eager wishes of the folk bring thee, delightful, golden-visored, on thy car, that, pleased with offering wherein ten fingers toil, tho. Mayest, at the feast, drink of our offered meath.\n\np: Juices aforetime, Lord of Bays, thou drankest; and thine especially is this libation. Gladden thee, indra, with the meath-rich Soma: pour it down ever, Mighty One! within thee.","people":["Indra","Soma","Deva","Ahi"],"places":["Earth","Heaven","Sky"],"things":["Meath","Tawny Coursers","Steeds","Lord","Soma","Offering","Sun","Food","Men","Flow","Might","Juice","Song","Gold","Home","Strong","Mighty","Car","Praise","Hymn","Gift","Form","Lord of Bays","Libations","Songs","Drops","Warrior","Cow","Horse","Life"],"groups":["Asura"],"concepts":["Birth","Life","Heavenly","Strength","Offering","Libations","Swift","Pleased"],"hash":"md5-pi06/SQqGhQrQOZORiS0Gw==","created":"Monday, April 8, 2024 - 10:51:55 PM"},{"id":"601754eb-0c52-474a-947b-00799cfd25f2","key":"10097","book":"10","title":"HYMN XCVII. Praise of Herbs.","link":"https://indra.ai/rigveda/hymns/10097.html","text":"p: HERBS that sprang up in time of old, three ages earlier than the Devas. Of these, whose hue is brown, will I declare the hundred powers and seven.\n\np: Ye, Mothers, have a hundred homes, yea, and a thousand are your growths. Do ye who have a thousand powers free this my patient from disease.\n\np: Be glad and joyful in the Plants, both blossoming and bearing fruit, plants that will lead us to success like mares who conquer in the race.\n\np: Plants, by this name I speak to you, Mothers, to you the Devas: Steed, cow, and garmen. May I win, win back thy very self, O man.\n\np: The Holy Fig tree is your home, your mansion is the Parna tree: Winners of cattle shali ye be if ye regain for me this man.\n\np: He who hath store of Herbs at hand like Kings amid a crowd of men. Physician is that sage's name, fiend-slayer, chaser of disease.\n\np: Herbs rich in Soma, rich in steeds, in nourishments, in strengthening power. All these have I provided here, that this ma. May be whole again.\n\np: The healing virtues of the Plants stream forth like cattle from the stall. Plants that shall win me store of wealth, and save thy vital breath, O man.\n\np: Reliever is your mother's name, and hence Restorers are ye called. Rivers are ye with wings that fly: keep far whatever brings disease.\n\np: Over all fences have they passed, as steals a thief into the fold. The Plants have driven from the frame whatever malady was there.\n\np: When, bringing back the vanished strength, I hold these herbs within my hand, the spirit of disease departs ere he can seize upon the life.\n\np: He through whose frame, O Plants, ye creep member by member, joint by joint. From him ye drive away disease like some strong arbiter of strife.\n\np: Fly, Spirit of Disease, begone, with the blue jay and kingfisher. Fly with the wind's impetuousspeed, vanish together with the storm.\n\np: Help every one the other, lend assistance each of you to each, All of you be accordant, give furtherance to this speech of mine.\n\np: Let fruitful Plants, and fruitless, those that blossom, and the blossomless, Urged onward by Narasamsa, release us from our pain and grief;\n\np: Release me from the curse's plague and woe that comes from Varuna; Free me from Yama's fetter, from sin and offence against the Devas.\n\np: What time, descending from the sky, the Plants flew earthward, thus they spake: No evil shall befall the man whom while he liveth we pervade,\n\np: Of all the many Plants whose King is, Soma, plants of hundred forms, Thou art the Plant most excellent, prompt to the wish, sweet to the heart.\n\np: O all ye various Herbs whose King is Soma, that o’erspread the earth, Urged onward by Narasamsa, combine your virtue in this Plant.\n\np: Unharmed be he who digs you up, unharmed the man for whom I dig: And let no malady attack biped or quadruped of ours.\n\np: All Plants that hear this speech, and those that have departed far away, Come all assembled and confer your healing power upon this Herb.\n\np: With Soma as their Sovran Lord the Plants hold colloquy and say: O King, we save from death the man whose cure a Brahman undertakes.\n\np: Most excellent of all art thou, O Plant thy vassals are the trees. Let him be subject to our power, the man who seeks to injure us.","people":["Soma","Varuna","Narasamsa","Yama"],"places":["Earth","Sky"],"things":["Steeds","Lord","Rivers","Soma","Wealth","Men","Stream","Help","Home","Strong","Excellent","Powers","Wings","King","Sage","Cow","Cattle","Life","Death","Spirit"],"groups":["Devas","Kings","Mother","Man"],"concepts":["Evil","Death","Life","Holy","Strength","Speech"],"hash":"md5-m1lGLU9P4r8V+J6uB8nbMg==","created":"Monday, April 8, 2024 - 10:51:55 PM"},{"id":"faff4596-b503-409f-a82b-9ce4e87d4e94","key":"10098","book":"10","title":"HYMN XCVIII. The Devas.","link":"https://indra.ai/rigveda/hymns/10098.html","text":"p: COME, be thou Mitra, Varuna, or Pusan, come, O Narasamsa, to mine oblation: With Maruts, Vasus, or Adityas, make thou Parjanya pour for Santanu his rain-drops.\n\np: The Deva, intelligent, the speedy envoy whom thou hast sent hath come to me, Devapi: Address thyself to me and turn thee hither within thy lips will I put brilliant language.\n\np: Within my mouth, Narasamsa, deposit speech lucid, vigorous, and free from weakness, thereby to win for Santanu the rain-fall. The meath-rich drop from heaven hath passed within it.\n\np: Let the sweet drops descend on us, O Indra: give us enough to lade a thousand wagons. Sit to thy Hotar task; pay worship duly, and serve the Devas, Devapi, with oblation.\n\np: Knowing the Deva's good-will, Devapi, Rsi, the son of Rstisena, sate as Hotar. He hath brought down from heaven's most lofty summit the ocean of the rain, celestial waters.\n\np: Gathered together in that highest ocean, the waters stood by deities obstructed. They burried down set free by Arstisena, in gaping clefts, urged onward by Devapi.\n\np: When as chief priest for Santanu, Devapi, chosen for Hotar's duty, prayed beseeching, Graciously pleased Narasamsa vouchsafed him a voice that reached the Devas and won the waters.\n\np: O Agni whom Devapi Arstisena, the mortal man, hath kindled in his glory, Joying in him with all the Devas together, urge on the sender of the rain, parjanya.\n\np: All ancient Rsis with their songs approached thee, even thee, O Much-invoked, at offers. We have provided wagon-loads in thousands: come to the solemn rite, Lord of Red Horses.\n\np: The wagon-loads, the nine-and-ninety thousand, these have been offered up to thee, O Agni. Hero, with these increase thy many bodies, and, stimulated, send us rain from heaven.\n\np: Give thou these ninety thousand loads, O Agni, to Indra, to the Bull, to be his portion. Knowing the paths which Deities duly travel, set mid the Devas in heaven Aulana also.\n\np: O Agni, drive afar our foes, our troubles chase malady away and wicked demons. From this air-ocean, from the lofty heavens, send down on us a mighty flood of waters.","people":["Indra","Agni","Mitra","Varuna","Narasamsa","Pusan","Hotar","Deva","Parjanya"],"places":["Ocean","Heaven"],"things":["Worship","Meath","Lord","Celestial Waters","Waters","Glory","Air","Rain","Mighty","Chief","Voice","Offers","Songs","Drops","Hero","Horses"],"groups":["Devas","Maruts","Deities","Son","Rsis","Man","Vasus","Adityas"],"concepts":["Celestial","Good","Pleased","Speech"],"hash":"md5-lI0rjBv0irexSNiXonQmLg==","created":"Monday, April 8, 2024 - 10:51:56 PM"},{"id":"99fc6752-7789-4b33-ae21-2c5c366ce044","key":"10099","book":"10","title":"HYMN XCIX. Indra.","link":"https://indra.ai/rigveda/hymns/10099.html","text":"p: WHAT Splendid One, Loud-voiced, Farstriding, dost thou, well knowing, urge us to exalt with praises? What give we him? When his might dawned, he fashioned the Vrtra-subduing bolt, and sent us waters.\n\np: He goes to end his work with lightning flashes: wide is the seat his Asura glory gives him. With his Companions, not without his Brother, he quells Saptatha's magic devices.\n\np: On most auspicious path he goes to battle he toiled to win heaven's light, full fain to gain it; He seized the hundred-gated castle's treasure. by craft, unchecked, and slew the lustful demons.\n\np: Fighting for kine, the prize of war, and I roaming among the berd be brings the young streams hither, Where, footless, joined, without a car to bear them, with jars for steeds, they pour their flood like butter.\n\np: Bold, unsolicited for wealth, with Rudras he came, the Blameless, having left his dwelling, Came, seized the food of Vamra and his consort, and left the couple weeping and unsheltered.\n\np: Lord of the dwelling, he subdued the demon who roared aloud, six-eyed and triple-headed. Trta, made stronger by the might he lent him, struck down the boar with shaft whose point was iron.\n\np: He raised himself on high and shot his arrow against the guileful and oppressive foeman. Strong, glorious, manliest, for us he shattered the forts of Nabus when he slew the Dasyus.\n\np: He, like a cloud that rains upon the pasture, hath found for us the way to dwell in safety. When the Hawk comes in body to the Soma, armed with his iron claws he subdues the Dasyus.\n\np: He with his potent Friends gave up the mighty, gave gusnia up to Kutsa for affliction. He led the lauded Kavi, he delivered Atka as prey to him and to his heroes.\n\np: He, with his Devas who love mankind, the Wondrous, giving like Varuna who works with magic, Was known, yet young as guardian of the seasons; and he quelled Araru, four-footed dernon.\n\np: Through lauds of him hath Ausija Rjisvan burst, with the Mighty's aid, the stall of Pipru. When the saint pressed the juice and shone as singer, he seized the forts and with his craft subdued them.\n\np: So, swiftly Asura, for exaltation, hath the great Vamraka come nigh to Indra. He will, when supplicated, bring him blessing: he hath brought all, food, strength, a happy dwelling.","people":["Indra","Soma","Vrtra","Varuna","Vamra","Kutsa","Trta","Rjisvan"],"places":["Heaven"],"things":["Mankind","Steeds","Work","Lord","Seasons","Soma","Waters","Glory","Glorious","Singer","Light","Treasure","Wealth","Food","Streams","Might","Juice","Strong","Mighty","Car","Blessing","Heroes","Friends"],"groups":["Devas","Asura","Dasyus","Rudras","Brother"],"concepts":["Love","Strength","Auspicious","Glorious"],"hash":"md5-MN2Kkk4vvEdNcHG58mrPww==","created":"Monday, April 8, 2024 - 10:51:56 PM"},{"id":"825e2c70-012c-4a26-8982-c5c9583a78f7","key":"10100","book":"10","title":"HYMN C, Devas.","link":"https://indra.ai/rigveda/hymns/10100.html","text":"p: Be, like thyself, O Indra, strong for our delight: here lauded, aid us, Maghavan, drinker of the juice. Savitar with the Devas protect us: hear ye Twain. We ask for freedom and complete felicity.\n\np: Bring swift, for offering, the snare that suits the time, to the pure-drinker Vayu, roaring as he goes, to him who hath approached the draught of shining milk. We ask for freedom and complete felicity.\n\np: May Savitar the Deva.send us full life, to each who make offerings, lives aright and pours the juice That we with simple heart. May wait upon the Devas. We ask for freedom and complete felicity.\n\np: May Indra evermore be gracious unto us, an. May King Soma meditate our happiness, Even as men secure the comfort of a friend. We ask for freedom and complete felicity.\n\np: Indra hath given the body with its song and strength: Narasamsa, thou art the lengthener of life. The offering is Manu, providence, our Sire. We ask for freedom and complete felicity.\n\np: Indra possesseth might celestial nobly formed: the singer in the house is Agni, prudent Sage. He is  'the offering in synod, fair, most near. We ask for freedom and complete felicity,\n\np: Not often have we sinned against you secretly, nor, Vasus, have we openly provoked the Devas. Not one of its, ye Devas, hath worn an alien shape. We ask for freedom and complete felicity.\n\np: May Savitar remove from us our malady, an. May the Mountains keep it far away from where The press-stone as it sheds the meath rings loudly forth. We ask for freedom and complete felicity.\n\np: Ye Vasus, let the stone, the presser stand erect: avert all enmities and keep them far remote. Our guard to be adored is Savitar this Deva. We ask for freedom and complete felicity.\n\np: Eat strength and fatness in the pasture, kine, who are balmed at the reservoir and at the seat of Law. So let your body be our body's medicine. We ask for freedom and complete felicity.\n\np: The singer fills the spirit: all mens, love hath he. Indra takes kindly care of those who pour the juice. For his libation is the heavenly udder full. We ask for freedom and complete felicity.\n\np: Wondrous thy spirit-filling light, triumpliant; thy hosts save from decay and are resistless. The pious votary by straightest pathway speeds to possess the best of all the cattle.","people":["Indra","Soma","King Soma","Agni","Vayu","Maghavan","Narasamsa","Savitar","Deva"],"places":[],"things":["Meath","Milk","Mountains","Soma","Singer","Offering","Light","Men","Might","Juice","Song","Strong","Reservoir","Delight","Offerings","Friend","King","Sage","Cattle","Life","Spirit"],"groups":["Devas","Vasus"],"concepts":["Celestial","Life","Heavenly","Love","Strength","Offering","Offerings","Swift"],"hash":"md5-7CpXd4b3LQtBzcT//o3zlg==","created":"Monday, April 8, 2024 - 10:51:56 PM"},{"id":"b8cc8b7b-baa9-40b7-8632-be9eb9628da3","key":"10101","book":"10","title":"HYMN CI, Devas.","link":"https://indra.ai/rigveda/hymns/10101.html","text":"p: WAKE with one mind, my friends, and kindle Agni, ye who are many and who dwell together. Agni and Dadhikras and Dawn the Deva, you, Devas with Indra, I call down to help us.\n\np: Make pleasant hymns, spin out your songs and praises: build ye a ship equipped with oars for transport. Prepare the implements, make all things ready, and let  'the offering, my friends, go forward.\n\np: Lay on the yokes, and fasten well the traces: formed is the furrow, s w the seed within it. Through son. May we find bearing fraught with plenty: near to the ripened grain approach the sickle.\n\np: Wise, through desire of bliss from Devas, the skilful bind the traces fast, and lay the yokes on either side.\n\np: Arrange the buckets in their place securely fasten on the straps. We will pour forth the well that hath a copious stream, fair-flowing well that never fails.\n\np: I pour the water from the well with pails prepared and goodly straps, Unfailing, full, with plenteous stream.\n\np: Refresh the horses, win the prize before you: equip a chariot fraught with happy fortune. Pour forth the well with stone wheel, wooden buckets, the drink of heroes, with the trough for armour.\n\np: Prepare the cow-stall, for there drink your heroes: stitch ye the coats of armour, wide and many. Make iron forts, secure from all assailants let not your pitcher leak: stay it securely.\n\np: Hither, for help, I turn the holy heavenly mind of you the Holy Devas, that longs for offering. May it pour milk for us, even as a stately cow who, having sought the pasture, yields a thousand streams.\n\np: Pour golden juice within the wooden vessel: with stone-made axes fashion ye and form it. Embrace and compass it with tenfold girdle, and to both chariot-poles attach the car-horse.\n\np: Between both poles the car-horse goes pressed closely, as in his dwelling moves the doubly-wedded. Lay in the wood the Soviran of the Forest, and sink the well although ye do not dig it.\n\np: Indra is he, O men, who gives us happiness: sport, urge the giver of delight to win us strength Bring quickly down, O monks, hither to give us aid, to drink the Soma, indra Son of Nistigri.","people":["Indra","Soma","Agni","Deva","Dawn"],"places":[],"things":["Milk","Soma","Water","Offering","Men","Streams","Stream","Juice","Help","Wise","Car","Delight","Heroes","Form","Friends","Bliss","Songs","Cow","Horses","Horse","call","Wheel"],"groups":["Devas","Son","Dadhikras","Monks"],"concepts":["Heavenly","Holy","Strength","Offering","Giver"],"hash":"md5-w+mbbgd2cZc+pAvmo3fi6Q==","created":"Monday, April 8, 2024 - 10:51:56 PM"},{"id":"02971e9d-29b8-447e-96d1-035f559a8426","key":"10102","book":"10","title":"HYMN CII. Indra.","link":"https://indra.ai/rigveda/hymns/10102.html","text":"p: FOR the, may Indra boldly speed the car that works on either side. Favour us, Much-invoked! in this most glorious fight against the raiders of our wealth.\n\np: Loose in the wind the woman's robe was streaming what time she won a car-load worth a thousand. The charioteer in fight was Mudgalani: she Indra's dart, heaped up the prize of battle.\n\np: O Indra, cast thy bolt among assailants who would slaughter us: The weapon both of Dasa and of Arya foe keep far away, O Maghavan.\n\np: The bull in joy had drunk a lake of water. His shattering horn encountered an opponent. Swiftly, in vigorous strength, eager for glory, he stretched his forefeet, fain to win and triumph.\n\np: They came anear the bull; they made him thunder, made him pour rain down ere the fight was ended. And Mudgala thereby won in the contest well-pastured kine in hundreds and in thousands.\n\np: In hope of victory that bull was harnessed: Kesi the driver urged him on with shouting. As he ran swiftly with the car behind him his lifted heels pressed close on Mudgalani.\n\np: Deftly for him he stretched the carpole forward, guided the bull thereto and firmly yoked him. Indra vouchsafed the lord of cows his favour: with mighty steps the buffalo ran onward.\n\np: Touched by the goad the shaggy beast went nobly, bound to the pole by the yoke's thong of leather. Performing deeds of might for many people, he, looking on the cows, gained strength and vigour.\n\np: Here look upon this mace, this bull's companion, now lying midway on the field of battle. Therewith hath Mudgala in ordered contest won for cattle for himself, a hundred thousand.\n\np: Far is the evil: who hath here beheld it? Hither they bring the bull whom they are yoking.. To this they give not either food or water. Reaching beyond the pole it gives directions.\n\np: Like one forsaken, she hath found a husband, and teemed as if her breast were full and flowing. With swiftly-racing chario. May we conquer, and rich and blessed be our gains in battle.\n\np: Thou, indra, art the mark whereon the eyes of all life rest, when thou, a Bull who drivest with thy bull, wilt win the race together with thy weakling friend.","people":["Indra","Maghavan"],"places":[],"things":["Victory","Lord","Triumph","Water","Glory","Glorious","Wealth","Food","Might","Rain","Joy","Mighty","Car","Lake","People","Friend","Cattle","Life"],"groups":["Husband","Woman"],"concepts":["Evil","Life","Strength","Glorious"],"hash":"md5-B2AEGb8QsI8RNNtfk+2VWQ==","created":"Monday, April 8, 2024 - 10:51:56 PM"},{"id":"0716ec2e-3432-4fc5-9911-885257cc5e2e","key":"10103","book":"10","title":"HYMN CIII. Indra.","link":"https://indra.ai/rigveda/hymns/10103.html","text":"p: SWIFT, rapidly striking, like a bull who sharpens his horns, terrific, stirring up the people, with eyes that close not, bellowing, Sole Hero, indra. subdued at once a hundred armies.\n\np: With him loud-roaring, ever watchful, Victor, bold, hard to overthrow, Rouser of battle, indra. the Strong, whose hand bears arrows, conquer, ye warriors, now, now vanquish in the combat.\n\np: He rules with those who carry shafts and quivers, indra who with his band rings hosts together, Foe-conquering, strong of arm, Soma, with mighty bow, shooting with well-laid arrows.\n\np: Narasamsa, fly with thy chariot hither, slayer of demons, driving off our foemen. Be thou protector of our cars, destroyer, victor in battle, breaker-up of armies.\n\np: Conspicuous by thy strength, firm, foremost fighter, mighty and fierce, victorious, all-subduing, the Son of Conquest, passing men and heroes, kine-winner, mount thy conquering car, O Indra.\n\np: Cleaver of stalls, kine-winner, armed with thunder, who quells an army and with might destroys it.- Follow him, brothers! quit yourselves like heroes, and like this Indra show your zeal and courage.\n\np: Piercing the cow-stalls with surpassing vigour, indra, the pitiless Hero, wild with anger, Victor in fight, unshaken and resistless,may he protect our armies in our battles.\n\np: Indra guide these: Narasamsa precede them, the guerdon, and  'the offering, and Soma; And let the banded Maruts march in forefront of heavenly hosts that conquer and demolish.\n\np: Ours be the potent host of mighty Indra, King Varuna, and Maruts, and Adityas. Uplifted is the shout of Devas who conquer high-minded Devas who cause the worlds to tremble.\n\np: Bristle thou up our weapons: excite the spirits of my warring heroes. Urge on the strong steeds' might, O Vrtra conquerer, and let the din of conquering cars go upward.\n\np: May Indra aid us when our flags are gathered: victorious be the arrows of our army. May our brave men of war prevail in battle. Ye Devas, protect us in the shout of onset.\n\np: Bewildering the senses of our foemen, seize thou their bodies and depart, O Apva. Attack them, set their hearts on fire and burn them: so let our foes abide in utter darkness.\n\np: Advance, O heroes, win the day. May Indra be your sure defence. Exceeding mighty be your arms, that non. May wound or injure you.","people":["Indra","Soma","Vrtra","Varuna","Narasamsa"],"places":[],"things":["Steeds","Soma","Offering","Men","Might","Strong","Mighty","Car","Armies","Brave","Heroes","People","Hero","King","Cow","Cars"],"groups":["Devas","Maruts","Son","Adityas"],"concepts":["Heavenly","Cars","Strength","Offering","Swift","Winner"],"hash":"md5-H9cVTjwl7hupiJmdX+yd+Q==","created":"Monday, April 8, 2024 - 10:51:56 PM"},{"id":"ab52a0ae-de5c-4984-96d7-2c616a73306c","key":"10104","book":"10","title":"HYMN CIV. Indra.","link":"https://indra.ai/rigveda/hymns/10104.html","text":"p: Soma hath flowed for thee, invoked of mat Speed to  'our offering with both thy Coursers. To thee have streameld the songs or mighty singers, imploring, indra, drink of our libation.\n\np: Drink of the juice which men have washed in waters, and fill thee full, O Lord of Tawny Horses. O Indra, hearer of the laud, with Soma which stones have mixed for thee enhance thy rapture.\n\np: To make thee start, a strong true draught I offer to thee, the Bull, O thou whom Bay Steeds carry. Here take delight, O Indra, in our voices while thou art hymned with power and all our spirit.\n\np: O Mighty Indra, through thine aid, thy prowess, obtaining life, zealous, and skilled in Order, Men in the house who share the sacred banquet stand singing praise that brings them store of children.\n\np: Through thy directions, Lord of Tawny Coursers, thine who art firm, splendid, and blest, the people Obtain most liberal aid for their salvation, and praise thee, indra, through thine excellencies.\n\np: Lord of the Bays, come with thy two Bay Horses, come to our meditations, to drink the juice of Soma. To thee comes offerings which thou acceptest: thou, skilled in holy rites, art he who giveth.\n\np: Him of a thousand powers, subduing foemen, Maghavan praised with hymns and pleased with Soma. Even him our songs approach, resistless Indra: the adorations of the singer laud him.\n\np: The way to bliss for Devas and man thou foundest, indra, seven lovely floods, divine, untroubled, Wherewith thou, rending forts, didst move the ocean, and nine-and-ninety flowing streams of water.\n\np: Thou from the curse didst free the mighty Waters, and as their only Deva.didst watch and guard them. O Indra, cherish evermore thy body with those which thou hast won in quelling Vrtra.\n\np: Heroic power and noble praise is Indra yea, the song worships him invoked of many. Vrtra he quelled, and gave men room and freedom: gakra, victorious, hath conquered armies.\n\np: Call we on Maghayan, auspicious Indra. best Hero in this fight where spoil is gathered, the Strong, who listens, who gives aid in battles, who subdues the Vrtras, wins and gathers riches.","people":["Indra","Soma","Vrtra","Maghavan","Deva"],"places":["Ocean"],"things":["Tawny Coursers","Steeds","Lord","Soma","Waters","Water","Singer","Offering","Men","Streams","Juice","Song","Strong","Mighty","Banquet","Armies","Praise","Delight","People","Bay Horses","Powers","Offerings","Bliss","Songs","Hero","Horses","call","spoil","Riches","Order","Life","Spirit"],"groups":["Devas","Man","Vrtras"],"concepts":["Life","Divine","Heroic","Holy","Sacred","Offering","Offerings","Auspicious","Pleased","Noble"],"hash":"md5-qJgF1uF9xfk0VmfKhm7afA==","created":"Monday, April 8, 2024 - 10:51:56 PM"},{"id":"17de2267-d2a5-4ff6-b4ce-6935c00b0c52","key":"10105","book":"10","title":"HYMN CV. Indra.","link":"https://indra.ai/rigveda/hymns/10105.html","text":"p: WHEN, Vasu, wilt thou love the laud? Now let the channel bring the stream. The juice is ready to ferment.\n\np: He whose two Bay Steeds harnessed well, swerving, pursue the Bird's tail-plumes, with Rowing manes, like heaven and earth, he is the Lord with power to give.\n\np: Bereft of skill is Indra, if, like some outwearied man he fears The sinner, when the Mighty hath prepared himself for victory.\n\np: Indra with these drives round, until he meets with one to worship him: Indra is Master of the pair who snort and swerve upon their way.\n\np: Borne onward by the long-maned Steeds who stretch themselves as ’twere for food, the Deva who wears the helm defends them with his jaws.\n\np: The Mighty sang with Lofty Ones: the Hero fashioned with his strengthlike skilful Matarisvan with his power and might,\n\np: The bolt, which pierced at once the vitals of the Dasyu easy to be slain, with jaw uninjured like the wondrous firmament.\n\np: Grind off our sins: with song will we conquer the men who sing no hymns: Not easily art thou pleased with prayerless offering.\n\np: When threefold flame burns high for thee, to rest on poles of offering, Thou with the living joyest in the self-bright Ship.\n\np: Thy glory was the speckled cup, thy glory was the flawless scoop. Wherewith thou pourest into thy receptacle.\n\np: As hundreds, O Immortal Deva, have sung to thee, so hath Sumitra, yea, Durmitra praised thee here, what time thou holpest Kutsa's son, when Dasyus fell, yea, holpest Kutsa's darling when the Dasyus died.","people":["Indra","Kutsa","Deva","Matarisvan","Vasu"],"places":["Earth","Heaven","Firmament"],"things":["Worship","Victory","Master","Steeds","Lord","Glory","Offering","Food","Men","Stream","Might","Juice","Song","Mighty","Hero","Bird"],"groups":["Dasyus","Dasyu","Son","Immortal","Man"],"concepts":["Love","Immortal","Offering","Pleased"],"hash":"md5-B5KvkQlHosq3gVWTtzRSYg==","created":"Monday, April 8, 2024 - 10:51:56 PM"},{"id":"f8393b35-ecc3-4c3d-86d2-3878aa658c15","key":"10106","book":"10","title":"HYMN CVI. Asvins.","link":"https://indra.ai/rigveda/hymns/10106.html","text":"p: THIS very thing ye Twain hold as your object: ye weave your songs as skilful men weave garments. That y. May come united have I waked you: ye spread out food like days of lovely weather.\n\np: Like two plough-bulls ye move along in traces, and seek like eager guests your bidder's banquet. Ye are like glorious envoys mid the people: like bulls, approach the place where ye are watered.\n\np: Like the two pinions of a bird, connected, like two choice animals, ye have sought our worship. Bright as the fire the votary hath kindled, ye offering in many a spot as roamers.\n\np: Ye are our kinsmen, like two sons, two fathers, strong in your splendour and like kings for conquest; Like rays for our enjoyment, Lords to feed us, ye, like quick bearers, have obeyed our calling.\n\np: You are like two pleasantly moving well-fed (hills) like Mitra and Varuna, the two bestowers of felicity, veracious, possessors of infinite wealth, happy, like two horses plump with fodder, abiding in the firmament, like two rams (are you) to be nourished with sacred food, to be cherished (with oblations).\n\np: You are like two mad elephants bending their forequarters and smiting the foe, like the two sons of Nitosa destroying (foes), and cherishing (friends); you are bright as two water-born (jewels), do you, who are victorious, (render) my decaying mortal body free from decay.\n\np: Fierce (Asvins), like two powerful (heroes), you enable this moving, perishable mortal (frame) to cross over to the objects (of its destination) as over water; extremely strong, like the Rbhus, your chariot, attained its destination swift as the wind, it pervaded (everywhere), it dispensed riches.\n\np: With your bellies full of the Soma, like two saucepans, preservers of wealth, destroyers of enemies. (you are) armed with hatchets, moving like two flying (birds) with forms like the moon, attaining success through the mind, like two laudable beings, (you are) approaching ( 'the offering).\n\np: Like giants, ye will find firm ground to stand on in depths, like feet for one who fords a shallow. Like cars ye will attend to him who orders: ye Two enjoy our wondrous work as sharers.\n\np: Like toiling bees ye bring to us your honey, as bees into the hide that opens downward.\n\np: May we increase the laud and gain us vigour: come to our song, ye whom one chariot carries. Filled be our kine with ripened meath like glory: Bhutamsa hath fulfilled the Asvins' longing.","people":["Soma","Mitra","Varuna","Asvins"],"places":["Firmament"],"things":["Worship","Meath","Work","Born","Soma","Water","Glory","Glorious","Offering","Moon","Wealth","Food","Men","Song","Strong","Banquet","Heroes","Splendour","People","Friends","Songs","Bird","Horses","Riches","Cars"],"groups":["Fathers","Sons","Kings","Rbhus"],"concepts":["Cars","Sacred","Offering","Glorious","Powerful","Swift"],"hash":"md5-BP6E7KOYANFSeZ4oVZYzAw==","created":"Monday, April 8, 2024 - 10:51:56 PM"},{"id":"a6e8b85d-db2c-4e0a-b2dc-b529f10af023","key":"10107","book":"10","title":"HYMN CVII. Daksina.","link":"https://indra.ai/rigveda/hymns/10107.html","text":"p: THESE men's great bounty hath been manifested, and the whole world of life set free from darkness. Great light hath come, vouchsafed us by the Fathers: apparent is the spacious path of Guerdon.\n\np: High up in heaven abide the Guerdon-givers: they who give steeds dwell with the Sun forever. They who give gold are blest with life eternal. they who give robes prolong their lives, O Soma.\n\np: Not from the niggards-for they give not fireely-comes Meed at offering, Devas’ satisfaction: Yea, many men with hands stretched out with Guerdon present their gifts because they dread dishonour.\n\np: These who observe mankind regard oblation as streamy Vayu and light-finding Arka. They satisfy and give their gifts in synod, and pour in streams the seven-mothered Guerdon.\n\np: He who brings Guerdon comes as first invited: chief of the hamlet comes the Guerdon-bearer. Him I account the ruler of the people who was the first to introduce the Guerdon.\n\np: They call him Rsi, Brahman, Sama-chanter, reciter of the laud, leader of worship. The brightly-shining Deva's three forms he knoweth who first bestowed the offerings Guerdon.\n\np: Guerdon bestows the horse, bestows the bullock, Guerdon bestows, moreover, gold that Rsisters. Guerdon gives food which is our life and spirit. He who is wise takes Guerdon for his armour.\n\np: The liberal die not, never are they ruined: the liberal suffer neither harm nor trouble. The light of heaven, the universe about us.all this doth offerings Guerdon give them.\n\np: First have the liberal gained a fragrant dwelling, and got themselves a bride in fair apparel. The liberal have obtained their draught of liquor, and conquered those who, unprovoked, assailed them.\n\np: They deck the fleet steed for the bounteous giver: the maid adorns herself and waits to meet him. His home is like a lake with lotus blossoms, like the Devas’ palaces adorned and splendid.\n\np: Steeds good at draught convey the liberal giver, and lightly rolling moves the car of Guerdon. Assist, ye Devas, the liberal man in battles: the liberal giver conquers foes in combat.","people":["Soma","Vayu","Deva"],"places":["Heaven"],"things":["Worship","Mankind","Leader","Steeds","Soma","Offering","Light","Sun","Food","Men","Streams","Gold","Home","Wise","Car","Chief","Lake","People","Offerings","Horse","call","Life","Spirit","Gifts"],"groups":["Devas","Fathers","Maid","Man","Niggards"],"concepts":["Good","Life","Offering","Offerings","Giver"],"hash":"md5-U9lmmwji6zjfncXQowaESg==","created":"Monday, April 8, 2024 - 10:51:56 PM"},{"id":"b505c424-bdef-41c5-886f-b81f812f4ec8","key":"10108","book":"10","title":"HYMN CVIII. Sarama. Panis.","link":"https://indra.ai/rigveda/hymns/10108.html","text":"p: WHAT wish of Sarama hath brought her hither? The path leads far away to distant places. What charge hast thou for us? Where turns thy journey? How hast thou made thy way o’er Rasa's waters.\n\np: I come appointed messenger of Indra, seeking your ample stores of wealth, O Panis. This hath preserved me from the fear of crossing: thus have I made my way o’er Rasa's waters.\n\np: What is that Indra like, what is his aspect whose envoy, Sarama, from afar thou comest? Let him approach, and we will show him friendship: he shall be made the herdsman of our cattle.\n\np: I know him safe from harm: but he can punish who sent me hither from afar as envoy. Him rivers flowing with deep waters bide not. Low will ye be, O Panis, slain by Indra.\n\np: These are the kine which, Sarama, thou seekest, flying, O Blest One, to the ends of heaven. Who will loose these for thee without a battle? Yea, and sharp-pointed are our warlike weapons.\n\np: Even if your wicked bodies, O ye Panis, were arrow-proof, your words are weak for wounding; And were the path to you as yet unmastered, Narasamsa in neither case will spare you.\n\np: Paved with the rock is this our treasure chamber; filled full of precious things, of kine, and horses. These Panis who are watchful keepers guard it. In vain hast thou approached this lonely station.\n\np: Rsis will come inspirited with Soma, Angirases unwearied, and Navagvas. This stall of cattle will they part among them: then will the Panis wish these words unspoken.\n\np: Even thus, O Sarama, hast thou come hither, forced by celestial might to make the journey. Turn thee not back, for thou shalt be our sister: O Blest One, we will give thee of the cattle.\n\np: Brotherhood, sisterhood, I know not either: the dread Angirases and Indra know them. They seemed to long for kine when I departed. Hence, into distance, be ye gone, O Panis.\n\np: Hence, far away, ye Panis! Let the cattle lowing come forth as holy Law commandeth, Kine which Narasamsa, and Soma, Rsis, sages, and pressing-stones have found when hidden.","people":["Indra","Soma","Narasamsa","Rasa","Sarama"],"places":["Heaven"],"things":["Journey","Rivers","Soma","Waters","Treasure","Wealth","Might","Pressing-Stones","Horses","Cattle"],"groups":["Sister","Rsis","Angirases","Navagvas","Panis","Brotherhood","Sisterhood"],"concepts":["Celestial","Friendship","Holy"],"hash":"md5-LjCZW2/acJgnhx3uauzhOQ==","created":"Monday, April 8, 2024 - 10:51:56 PM"},{"id":"1329da0c-d4ed-42e0-9ae5-0b55da6cac7b","key":"10109","book":"10","title":"HYMN CIX, Devas.","link":"https://indra.ai/rigveda/hymns/10109.html","text":"p: THESE first, the boundless Sea, and Matarisvan, fierce-glowing Fire, the Strong, the Bliss-bestower. And heavenly Floods, first-born by holy Order, exclaimed against the outrage on a Brahman.\n\np: King Soma first of all, without reluctance, made restitution of the Brahman's consort. Mitra and Varuna were the inviters: Agni as Hota; took her hand and led her.\n\np: The man, her pledge, must by her hand be taken when they have cried, she is a Brahman's consort. She stayed not for a herald to conduct her: thus is the kingdom of a ruler guarded.\n\np: Thus spake of her those Devas of old, Seven Rsis who sate them down to their austere devotion: Dire is a Brahman's wife led home by others: in the supremest heaven she plants confusion.\n\np: The Brahmacari goes engaged in duty: he is a member of the Devas’ own body. Through him Narasamsa obtained his consort, as the Devas gained the ladle brought by Soma.\n\np: So then the Devas restored her, so men gave the woman back again. The Kings who kept their promises restored the Brahman's wedded wife,\n\np: Having restored the Brahman's wife, and freed them, with Devas’ aid, from sin, they shared the fulness of the earth, and won themselves extended sway.","people":["Soma","King Soma","Agni","Mitra","Varuna","Narasamsa","Matarisvan"],"places":["Earth","Heaven"],"things":["Born","Soma","Men","Home","Strong","Bliss","King","Order"],"groups":["Devas","Kings","Wife","Rsis","Man","Woman"],"concepts":["Heavenly","Holy"],"hash":"md5-fO1ij1f6xTAjM7zr0NQXoA==","created":"Monday, April 8, 2024 - 10:51:56 PM"},{"id":"144b24c5-e95c-42cd-9b4b-0e9971e21a1c","key":"10110","book":"10","title":"HYMN CX. Apris.","link":"https://indra.ai/rigveda/hymns/10110.html","text":"p: THOU in the house of man this day enkindled worshippest Devas as Deva, O Jatavedas. Observant, bright as Mitra, bring them hither: thou art a sapient and foreknowing envoy.\n\np: Tanunapat, fair-tongued, with sweet meath balming the paths and waysof Order, make them pleasant. Convey  'our offering to heaven, exalting with holy thoughts ourhymns of praise and worship.\n\np: Invoked, deserving prayer and adoration, O Agni, come accordant with the Vasus. Thou art, O Youthful Lord, the Devas’ Invoker, so, best of Offerers, bring them quickly.\n\np: By rule the Sacred Grass is scattered eas ward, a robe to clothe this earth when dawns are breaking. Widely it spreads around and far-extended, fair for the Devas and bringing peace and freedom.\n\np: Let the expansive Doors be widely opened, like wives who deck their beauty for their husbands. Lofty, celestial, all-impelling Portals, admit the Devas and give them easy entrance.\n\np: Pouring sweet dews let holy Night and Morning, each close to each, he seated at their station, Lofty, celestial Dames with gold to deck them. assuming all their fair and radiant beauty.\n\np: Come the two first celestial sweet-voiced Hotars, arranging offering for man to worship As singers who inspire us in assemblies, showing the eas ward light with their direction.\n\np: Let Bharati come quickly to our worship, and Ila showing like a human being. So let Sarasvati and both her fellows, deft Devas, on this fair grass be seated.\n\np: Hotar more skilled in offering, bring hither with speed to-day Deva.Tvastar, thou who knowest. Even him who formed these two, the Earth and Heaven the Parents, with their forms, and every creature..\n\np: Send to our offerings which thyself thou balmest the Companies of Devas in ordered season. Agni, Vanaspati the Immolator sweeten our offered gift with meath and butter.\n\np: Agni, as soon as he was born, made ready  'the offering, and was the Devas’ preceder. May the Devas cat our offering consecrated according to this true Monk's voice and guidance.","people":["Agni","Mitra","Tvastar","Bharati","Sarasvati","Hotar","Deva","Ila","Vanaspati"],"places":["Earth","Heaven"],"things":["Worship","Meath","Lord","Born","Offering","Light","Beauty","Gold","Grass","Praise","Voice","Gift","Offerings","Parents","Order","Morning"],"groups":["Devas","Jatavedas","Dawns","Dames","Human","Man","Vasus"],"concepts":["Celestial","Holy","Sacred","Offering","Offerings"],"hash":"md5-v//yzI73aDNrY9sHgAw/vg==","created":"Monday, April 8, 2024 - 10:51:56 PM"},{"id":"964d406b-ced7-402d-ae37-988cc30d197b","key":"10111","book":"10","title":"HYMN CXI. Indra.","link":"https://indra.ai/rigveda/hymns/10111.html","text":"p: BRING forth your sacred song ye prudent singers, even as are the thoughts of human beings. Let us draw Indra with true deeds anear us: he loves our songs, the Hero, and is potent.\n\np: The hymn shone brightly from the seat of worship: to the kine came the Bull, the Heifer's Offipring With mighty bellowing hath he arisen, and hath pervaded even the spacious regions.\n\np: Indra knows, verily, how to hear our singing, for he, victorious, made a path for Surya. He made the Cow, and be became the Sovran of Heaven, primeval, matchless, and unshaken.\n\np: Praised by Angirases, indra demolished with might the works of the great watery monster Full many regions, too, hath he pervaded, and by his truth supported earth's foundation.\n\np: The counterpart of heaven and earth is Indra: he knoweth all libations, slayeth Susna. The vast sky with the Sun hath he extended, and, best otpillars, stayed it with a pillar.\n\np: The Vrtra-slaver with his bolt felled Vrtra: the magic of the godless, waxen mighty. Here hast thou, Bold Assailant, boldly conquered. Yea, then thine arms were potent.\n\np: When the Dawns come attendant upon Surya their rays discover wealth of divers colours. The Star of heaven is seen as ’twere approaching: none knoweth aught of it as it departeth.\n\np: Far have they gone, the first of all these waters, the waters that flowed forth when Indra sent them. Where is their spring, and where is their foundation? Where now, ye Waters, is your inmost centre?\n\np: Thou didst free rivers swallowed by the Dragon; and rapidly they set themselves in motion, Those that were loosed and those that longed for freedom. Excited now to speed they run unresting.\n\np: Yearning together they have sped to Sindhu: the Fort-destroyer, praised, of old, hath loved them. Indra, may thy terrestrial treasure.s reach us, and our full songs of joy approach thy dwelling.","people":["Indra","Vrtra","Susna","Surya","Sindhu"],"places":["Earth","Heaven","Sky"],"things":["Worship","Rivers","Waters","Sun","Treasure","Wealth","Might","Song","Joy","Mighty","Hymn","Libations","Songs","Hero","Cow"],"groups":["Dawns","Human","Angirases"],"concepts":["Sacred","Truth","Libations"],"hash":"md5-93CnAZdw629QGwoXRvkX+A==","created":"Monday, April 8, 2024 - 10:51:56 PM"},{"id":"c523885f-bd79-49f1-8718-c4ed60c6892d","key":"10112","book":"10","title":"HYMN CXII. Indra.","link":"https://indra.ai/rigveda/hymns/10112.html","text":"p: DRINK of the juice, O Indra, at thy plea. sure, for thy first draught is early morn's libation. Rejoice, that tho. Mayst subdue our . O Hero, and we with lauds will tell thy mighty exploits.\n\np: Thou hast a car more swift than thought, O Indra; thercon come hither, come to drink the Soma. Let thy Bay Steeds, thy Stallions, hasten hither, with whom thou cornest nigh and art delighted.\n\np: Deck out thy body with the fairest colours, with golden splendour of the Sun adorn it. O Indra, turn thee hitherward invited by us thy friends; be seated and be joyful.\n\np: O thou whose grandeur in thy festive transports not even these two great worlds have comprehended. Come, indra, with thy dear Bay Horses harnessed, come to our dwelling and the food thou lovest.\n\np: Pressed for thy joyous banquet is the Soma, Soma whereof thou, indra, ever drinking, Hast waged unequalled battles with thy foemen, which prompts the mighty flow of thine abundance.\n\np: Found from of old is this thy cup, O Indra: Satakratu, drink therefrom the Soma. Filled is the beaker with the meath that gladdens, the beaker which all Deities delight in.\n\np: From many a side with proffered entertainment the folk are calling thee, O Mighty Indra. These our libations shall for thee be richest in sweet meath: dvink thereof and find them pleasant.\n\np: I will declare thy deeds of old, O Indra, the mighty acts which thou hast first accomplished. In genuine wrath thou loosenedst the mountain so that the Brahman easily found the cattle.\n\np: Lord of the hosts, amid our bands be seated: they call thee greatest Sage among the sages. Nothing is done, even far away, without thee: great, wondrous, Maghavan, is the hymn I sing thee.\n\np: Aim of our eyes be thou, for we implore thee Friend of friends and Lord of treasure.s. Fight, Warrior strong in truth, fight thou the battle: give us our share of undivided riches.","people":["Indra","Soma","Satakratu","Maghavan"],"places":[],"things":["Meath","Steeds","Lord","Soma","Sun","Treasure","Food","Flow","Juice","Strong","Mighty","Car","Banquet","Delight","Hymn","Splendour","Bay Horses","Libations","Friends","Warrior","Friend","Hero","Sage","Horses","call","Riches","Cattle"],"groups":["Deities"],"concepts":["Truth","Libations","Swift"],"hash":"md5-F6RG9fIxC2pAFyLfWPHKzQ==","created":"Monday, April 8, 2024 - 10:51:56 PM"},{"id":"469b7494-139a-40c4-8045-404336fda6fc","key":"10113","book":"10","title":"HYMN CXTII. Indra.","link":"https://indra.ai/rigveda/hymns/10113.html","text":"p: THE Heavens and the Earth accordant with all Devas encouraged graciously that vigorous might of his. When he came showing forth his majesty and power, he drank of Soma juice and waxed exceeding strong.\n\np: This majesty of his Visnu extols and lauds, making the stalCthat gives the meath flow forth with inight. When Indra Maghavan with those who followed him had smitten Vrtra he deserved the choice of Devas.\n\np: When, bearing warlike weapons, fain to win thee praise, thou mettest Vrtra, yea, the Dragon, for the fight, then all the Maruts who were gathered with dice there extolled, O Mighty One, thy powerful majesty.\n\np: Soon as he sprang to life he forced asun. der hosts: forward the Hero looked to manly deed and war. He cleft the rock, he let concurrent streams flow forth, and with his skilful art stablished the heavens' wide vault.\n\np: Indra hath evermore possessed surpassing power: he forced, far from each other, heaven and earth apart. He hurled impetuous down his iron thunderbolt, a joy to Varuna's and Mitra's worshipper.\n\np: Then to the mighty powers of Indra, to his wrath, his the fierce Stormer, loud of voice, they came with speed; What time the Potent One rent Vrtra with his strength, who held the waters back, whom darkness compassed round.\n\np: Even in the first of those heroic acts which they who strove together came with might to execute, Deep darkness fell upon the slain, and Indra won by victory the right of being first invoked.\n\np: Then all the Devas extolled, with eloquence inspired by draughts of Soma juice, thy deeds of manly might. As Agni eats the dry food with his tcetlv, he ate Vrtra, the Dragon, maimed by Indra's deadly dart.\n\np: Proclaim his many friendships, met with friendship, made with singers, with the skilful and the eloquent. Indra, when he subdues Dhuni and Cumuri, lists to Dabhiti for his faithful spirit's sake.\n\np: Give riches manifold with noble horses, to be remembered while my songs address thee. May we by easy paths pass all our troubles: find us this day a ford wide and extensive.","people":["Indra","Soma","Vrtra","Agni","Visnu","Mitra","Varuna","Maghavan"],"places":["Earth","Heaven"],"things":["Meath","Victory","Stormer","Soma","Waters","Food","Streams","Flow","Might","Juice","Joy","Strong","Mighty","Praise","Voice","Worshipper","Powers","Songs","Hero","Horses","Riches","Dice","Life","Spirit"],"groups":["Devas","Maruts"],"concepts":["Life","Friendship","Heroic","Strength","Powerful","Noble"],"hash":"md5-t8WlQHwCLhX4Qj3WKOC+8g==","created":"Monday, April 8, 2024 - 10:51:56 PM"},{"id":"5d70860d-8a4c-423f-a53a-49e692f80e25","key":"10114","book":"10","title":"HYMN CXIV, Devas.","link":"https://indra.ai/rigveda/hymns/10114.html","text":"p: Two perfect springs of heat pervade the Threefold, and come for their delight is Matarisvan. Craving the milk of heaven the Devas are present: well do they know the praisesong and the Saman.\n\np: The Monks beard far away, as they are ordered, serve the three Nirrtis, for well they know them. Sages have traced the cause that first produced them, dwelling in distant and mysterious chambers.\n\np: The Youthful One, well-shaped, with four locks braided, brightened with oil, puts on the ordinances. Two Birds of mighty power are seated near her, there where the Deities receive their portion.\n\np: One of these Birds hath passed into the sea of air: thence he looks round and views this universal world. With simple heart I have beheld him from anear: his Mother kisses him and he returns her kiss.\n\np: Him with fair wings though only One in nature, wise singers shape, with songs, in many figures. While they at offers fix the metres, they measure out twelve chalices of Soma.\n\np: While they arrange the four and six-and-thirty, and duly order, up to twelve, the measures, Having disposed  'the offering thoughtful sages send the Car forward with the Rc and Saman.\n\np: The Chariot's majesties are fourteen others: seven sages lead it onward with their Voices. Who will declare to us the ford Apnana, the path whereby they drink first draughts of Soma?\n\np: The fifteen lauds are in a thousand places that is as vast as heaven and earth in measure. A thousand spots contain the mighty thousand. Vak spreadeth forth as far as Prayer extendeth.\n\np: What sage hath learned the metres' application? Who hath gained Vak, the spirit's aim and object? Which ministering priest is called eighth Hero? Who then hath tracked the two Bay Steeds of Indra?\n\np: Yoked to his chariot-pole there stood the Coursers: they only travel round earth's farthest limits. These, when their driver in his home is settled, receive the allotted meed of their exertion.","people":["Indra","Soma","Vak","Matarisvan"],"places":["Earth","Heaven"],"things":["Milk","Steeds","Soma","Offering","Air","Home","Wise","Mighty","Car","Delight","Offers","Songs","Wings","Hero","Sage","Order","Spirit"],"groups":["Devas","Deities","Mother","Monks"],"concepts":["Offering"],"hash":"md5-kBcO8grDlsb5kPt48hqG+g==","created":"Monday, April 8, 2024 - 10:51:56 PM"},{"id":"ed2610a8-5ef2-4d82-91c5-490b43cecb5e","key":"10115","book":"10","title":"HYMN CXV. Agni.","link":"https://indra.ai/rigveda/hymns/10115.html","text":"p: VERILY wondrous is the tender Youngling's growth who never draweth nigh to drink his Mothers' milk. As soon as she who hath no udder bore him, he, faring on his great errand, suddenly grew strong.\n\np: Then Agni was his name, most active to bestow, gathering up the trees with his consuming tooth; Skilled in fair offering, armed with destroying tongue, impetuous as a bull that snorteth in the mead.\n\np: Praise him, yourDeva who, bird-like, rests upon a tree, scattering drops of juice and pouring forth his flood, Speaking aloud with flame as with his lips a priest, and broadening his paths like one of high command.\n\np: Thou Everlasting, whom, far-striding fain to burn, the winds, uninterrupted, never overcome, they have approached, as warriors eager for the fight, heroic Trita, guiding him to gain his wish.\n\np: This Agni is the best of Kanvas, Kanvas' Friend, Conqueror of the foe whether afar or near. May Agni guard the singers, guard the princes well. May Agni grant to us our princes' gracious help.\n\np: Do thou, Supitrya, swiftly following, make thyself the lord of Jatavedas, mightiest of all, who surely gives a boon even in thirsty land most powerful, prepared to aid us in the wilds.\n\np: Thus noble Agni with princes and mortal men is lauded, excellent for conquering strength with chiefs, Men who are well-disposed as friends and true to Law, even as the heavens in majesty surpass mankind.\n\np: O Son of Strength, Victorious, with this title Upastuta's most potent voice reveres thee. Blest with brave sons by thee we will extol thee, and lengthen out the days of our existence.\n\np: Thus, Agni, have the sons of Vrstihavya, the Rsis, the Upastutas invoked thee. Protect them, guard the singers and the princes. With Vasat! have they come, with hands uplifted, with their uplifted hands and cries of Glory!","people":["Agni","Kanvas","Trita"],"places":[],"things":["Mankind","Milk","Lord","Glory","Offering","Boon","Men","Juice","Help","Strong","Praise","Voice","Brave","Excellent","Friends","Drops","Friend","Bird"],"groups":["Jatavedas","Sons","Son","Rsis"],"concepts":["Heroic","Strength","Offering","Powerful","Noble"],"hash":"md5-2+lWWeRWUzHoCj87UOfUTQ==","created":"Monday, April 8, 2024 - 10:51:56 PM"},{"id":"8f246c1a-8bee-48b5-9150-96be1c21acfa","key":"10116","book":"10","title":"HYMN CXV1. Indra.","link":"https://indra.ai/rigveda/hymns/10116.html","text":"p: DRINK Soma juice for mighty power and vigour, drink, Strongest One, that tho. Mayst smite down Vrtra. Drink thou, invoked, for strength, and riches: drink thou thy fill of meath and pour it down, O Indra.\n\np: Drink of the foodful juice stirred into motion, drink what thou choosest of the flowing Soma. Giver of weal, be joyful in thy spirit, and turn thee hitherward to bless and prosper.\n\np: Let heavenly Soma gladden thee, O Indra, let that effused among mankind delight thee. Rejoice in that whereby thou gavest freedom, and that whereby thou conquerest thy foemen.\n\np: Let Indra come, impetuous, doubly mighty, to the poured juice, the Bull, with two Bay Coursers. With juices pressed in milk, with meath presented, glut evermore thy bolt, O Foe-destroyer.\n\np: Dash down, outffaming their sharp flaming weapons, the strong-holds of the men urged on by demons. I give thee, Mighty One, great strength and conquest: go, meet thy foes and rend them in the battle.\n\np: Extend afar the votary's fame and glory, as the firm archer's strength drives off the foeman. Ranged on our side, grown strong in might that conquers, never defeated, still increase thy body.\n\np: To thee have we presented this oblation: accept it, Sovran Ruler, free from anger. Juice, Maghavan, for thee is pressed and ripened: eat, indra, drink of that which stirs to meet thee.\n\np: Eat, indra, these oblations which approach thee: be pleased with food made ready and with Soma. With entertainment we receive thee friendly: effectual be  'theofferings wishes.\n\np: I send sweet speech to Indra and to Agni: with hymns I speed it like a boat through waters. Even thus, the Devas seem moving round about me, the fountains and bestowers of our riches.","people":["Indra","Soma","Vrtra","Agni","Maghavan"],"places":[],"things":["Mankind","Meath","Milk","Soma","Waters","Glory","Food","Men","Might","Juice","Strong","Mighty","Delight","Riches","Spirit","Sovran Ruler"],"groups":["Devas"],"concepts":["Heavenly","Strength","Giver","Pleased","Speech"],"hash":"md5-1BMNC3NKOPGV1OlcuIglAA==","created":"Monday, April 8, 2024 - 10:51:56 PM"},{"id":"be431ff3-3480-462a-abd5-db3b085e7e73","key":"10117","book":"10","title":"HYMN CXVII. Liberality.","link":"https://indra.ai/rigveda/hymns/10117.html","text":"p: THE Devas have not ordained hunger to be our death: even to the well-fed man comes death in varied shape. The riches of the liberal never waste away, while he who will not give finds none to comfort him.\n\np: The man with food in store who, when the needy comes in miserable case begging for bread to eat, Hardens his heart against him-even when of old he did him service-finds not one to comfort him.\n\np: Bounteous is he who gives unto the beggar who comes to him in want of food and feeble. Success attends him in the shout of battle. He makes a friend of him in future troubles.\n\np: No friend is he who to his friend and comrade who comes imploring food, will offer nothing. Let him depart-no home is that to rest in-, and rather seek a stranger to support him.\n\np: Let the rich satisfy the poor implorer, and bend his eye upon a longer pathway. Riches come now to one, now to another, and like the wheels of cars are ever rolling.\n\np: The foolish man wins food with fruitless labour: that food -I speak the truth- shall be his ruin. He feeds no trusty friend, no man to love him. All guilt is he who eats with no partaker.\n\np: The ploughshare ploughing makes the food that feeds us, and with its feet cuts through the path it follows. Better the speaking than the silent Brahman: the liberal friend outyalues him who gives not.\n\np: He with one foot hath far outrun the biped, and the two-footed catches the three-footed. Four-footed creatures come when bipeds call them, and stand and look where five are met together.\n\np: The hands are both alike: their labour differs. The yield of sister milch-kine is unequal. Twins even diffier in their strength and vigour: two, even kinsmen, differ in their bounty.","people":[],"places":[],"things":["Food","Home","Friend","call","Riches","Cars","Death"],"groups":["Devas","Sister","Man"],"concepts":["Death","Cars","Love","Strength","Truth"],"hash":"md5-Fsu+/QH1s17M1m8xXN+mHw==","created":"Monday, April 8, 2024 - 10:51:56 PM"},{"id":"2baf61fc-49d6-4388-87e7-028718bffb02","key":"10118","book":"10","title":"HYMN CXVIII. Agni.","link":"https://indra.ai/rigveda/hymns/10118.html","text":"p: AGNI, refulgent among men thou slayest the devouring fiend, Bright Ruler in thine own abode.\n\np: Thou springest up when worshipped well the drops of butter are thy joy When ladies are brought near to thee.\n\np: Honoured with gifts he shines afar, Agni adorable with song: The dripping ladle balms his face.\n\np: Agni with honey in his mouth, honoured with gifts, is balmed with oil, Refulgent in his wealth of light.\n\np: Praised by our hymns thou kindlest thee, Oblation-bearer, for the Devas As such do mortals call on thee.\n\np: To that Immortal Agni pay worship with oil, ye mortal men. Lord of the house, whom none deceives.\n\np: O Agni, burn the Raksasas with thine unconquerable flame Shine guardian of Eternal Law.\n\np: So, Agni, with thy glowing face burn fierce against the female fiends, Shining among Uruksayas.\n\np: Uruksayas have kindled thee, Oblation-bearer, thee, with hymns. Best Worshipper among mankind.","people":["Agni","Raksasas"],"places":[],"things":["Worship","Mankind","Lord","Shine","Light","Wealth","Men","Song","Joy","Worshipper","Adorable","Drops","call","Gifts"],"groups":["Devas","Immortal"],"concepts":["Immortal","Worshipped","Eternal Law"],"hash":"md5-y4HALqSGS4JZZFfmin26dw==","created":"Monday, April 8, 2024 - 10:51:56 PM"},{"id":"c011ebd0-3045-495c-9df6-041d70da56a5","key":"10119","book":"10","title":"HYMN CXIX. Indra.","link":"https://indra.ai/rigveda/hymns/10119.html","text":"p: THIS, even this was my resolve, to win a cow, to win a steed: Have I not drunk of Soma juice?\n\np: Like violent gusts of wind the draughts that I have drunk have lifted me Have I not drunk of Soma juice?\n\np: The draughts I drank have borne me up, as fleet-foot horses draw a car: Have I not drunk of Soma juice?\n\np: The hymn hath reached me, like a cow who lows to meet her darling calf: Have I not drunk of Soma juice?\n\np: As a wright bends a chariot-seat so round my heart I bend the hymn: Have I not drunk of Soma juice?\n\np: Not as a mote within the eye count the Five Tribes of men with me: Have I not drunk of Soma juice?\n\np: The heavens and earth themselves have not grown equal to one half of me Have I not drunk of Soma juice?\n\np: I in my grandeur have surpassed the heavens and all this spacious earth Have I not drunk of Soma juice?\n\np: Aha! this spacious earth will I deposit either here or there Have I not drunk of Soma juice?\n\np: In one short moment will I smite the earth in fury here or there: Have I not drunk of Soma juice?\n\np: One of my flanks is in the sky; I let the other trail below: Have I not drunk of Soma juice?\n\np: 1, greatest of the MightyOnes, am lifted to the firmament: Have I not drunk of Soma juice?\n\np: I seek the worshipper's abode; oblation-bearer to the Devas: Have I not drunk of Soma juice?","people":["Soma"],"places":["Earth","Firmament","Sky"],"things":["Soma","Men","Juice","Car","Worshipper","Hymn","Cow","Horses"],"groups":["Devas","MightyOnes"],"concepts":[],"hash":"md5-+JXEdV00mpm7MlDpdapTwg==","created":"Monday, April 8, 2024 - 10:51:56 PM"},{"id":"a92d21a0-651f-4208-a8d2-8dffb8c94615","key":"10120","book":"10","title":"HYMN CXX. Indra.","link":"https://indra.ai/rigveda/hymns/10120.html","text":"p: IN all the worlds That was the Best and Highest whence sprang the Mighty Devas, of splendid valour. As soon as born he overcomes his foemen, be in whom all who lend him aid are joyful.\n\np: Grown mighty in his strength, with ample vigour, he as a foe strikes fear into the Dasa, Eager to win the breathing and the breathless. All sang thy praise at banquet and oblation.\n\np: All concentrate on thee their mental vigour, what time these, twice or thrice, are thine assistants. Blend what is sweeter than the sweet with sweetness: win. quickly with our meath that meath in battle.\n\np: Therefore in thee too, thou who winnest riches, at every banquet are the sages joyful. With mightier power, Bold Deva, extend thy firmness: let not malignant Yatudhanas harm thee.\n\np: Proudly we put our trust in thee in battles, when we behold great wealth the prize of combat. I with my words impel thy weapons onward, and sharpen with my meditation thy vital vigour.\n\np: Worthy of praises, many-shaped, most skilful, most energetic, Aptya of the Aptyas: He with his might destroys the seven Danus, subduing many who were deemed his equals.\n\np: Thou in that house which thy protection guardeth bestowest wealth, the higher and the lower. Thou stablishest the two much-wandering Mothers, and bringest many deeds to their completion.\n\np: Brhaddiva, the foremost of light-winners, repeats these holy prayers, this strength of Indra. He rules the great self-luminous fold of cattle, and all the doors of light hath he thrown open.\n\np: Thus hath Brhaddiva, the great Atharvan, spoken to Indra as himself in person. The spotless Sisters, they who are his Mothers, with power exalt him and impel him onward.","people":["Indra","Deva","Aptya"],"places":[],"things":["Meath","Born","Meditation","Light","Wealth","Might","Mighty","Banquet","Praise","Riches","Cattle"],"groups":["Devas"],"concepts":["Holy","Strength"],"hash":"md5-txt35wH1zYaaTfydLtTSZA==","created":"Monday, April 8, 2024 - 10:51:56 PM"},{"id":"13cd2560-207d-408b-9a0e-7a78fe8f6eff","key":"10121","book":"10","title":"HYMN CXXI. Ka.","link":"https://indra.ai/rigveda/hymns/10121.html","text":"p: IN the beginning rose Hiranyagarbha, born Only Lord of all created beings. He fixed and holdeth up this earth and heaven. What Deva.shall we adore with our oblation?\n\np: Giver of vital breath, of power and vigour, he whose commandments all the Devas acknowledge -. The Lord of death, whose shade is life immortal. What Deva.shall we adore with our oblation?\n\np: Who by his grandeur hath become Sole Ruler of all the moving world that breathes and slumbers; He who is Loord of men and Lord of cattle. What Deva.shall we adore with our oblation?\n\np: His, through his might, are these snow-covered mountains, and men call sea and Rasa his possession: His arms are these, his are these heavenly regions. What Deva.shall we adore with our oblation?\n\np: By him the heavens are strong and earth is stedfast, by him light's realm and sky-vault are supported: By him the regions in mid-air were measured. What Deva.shall we adore with our oblation?\n\np: To him, supported by his help, two armies embattled look while trembling in their spirit, when over them the risen Sun is shining. What Deva.shall we adore with our oblation?\n\np: What time the mighty waters came, containing the universal germ, producing Agni, thence sprang the Devas’ one spirit into being. What Deva.shall we adore with our oblation?\n\np: He in his might surveyed the floods containing productive force and generating Worship. He is the Deva.of gods, and none beside him. What Deva.shall we adore with our oblation?\n\np: Nee. May he harm us who is earth's Begetter, nor he whose laws are sure, the heavens' Creator. He who brought forth the great and lucid waters. What Deva.shall we adore with our oblation?\n\np: Prajapati! thou only comprehendest all these created things, and none beside thee. Grant us our hearts' desire when we invoke thee. May we have store of riches in possession.","people":["Agni","Deva","Rasa","Prajapati"],"places":["Earth","Heaven","Mid-Air","Sky"],"things":["Worship","Lord","Born","Mountains","Waters","Light","Air","Creator","Sun","Men","Might","Help","Strong","Mighty","Armies","call","Riches","Cattle","Life","Death","Spirit"],"groups":["Devas","Immortal"],"concepts":["Death","Life","Heavenly","Immortal","Giver","Creator"],"hash":"md5-PFJMTirpG2zg7RPewVay3w==","created":"Monday, April 8, 2024 - 10:51:56 PM"},{"id":"f3125d79-7750-4d70-9c5c-f143b61385d6","key":"10122","book":"10","title":"HYMN CXXII. Agni.","link":"https://indra.ai/rigveda/hymns/10122.html","text":"p: I PRAISE the Deva.of wondrous might like Indra, the lovely pleasant Guest whom all must welcome. May Agni, Monk and Master of the household, give hero strength and all-sustaining riches.\n\np: O Agni, graciously accept this song of mine, thou passing-wise who knowest every ordinance. Enwrapped in holy oil further the course of prayer: the Devas bestow according to thy holy law.\n\np: Immortal, wandering round the seven stations, give, a liberal Giver, to the pious worshipper, Wealth, Agni, with brave sons and ready for his use: welcome the man who comes with fuel unto thee.\n\np: The seven who bring oblations worship thee, the Strong, the first, the Great Chief Monk, Ensign of offering, the oil-anointed Bull, Agni who hears, who sends as Deva.full hero strength to him who freely gives.\n\np: First messenger art thou, meet for election: drink thou thy fill invited to the Anirta, the Maruts in the votary's house adorned thee; with lauds the Bhrgus gave thee light and glory.\n\np: Milking the teeming Cow for all-sustaining food. O Wise One, for the worship-loving worshipper, Thou, Agni, dropping oil, thrice lighting works of Law, showest thy wisdom circling home and offering.\n\np: They who at flushing of this dawn appointed thee their messenger, these men have paid thee reverence. Devas strengthened thee for work that must be glorified, Agni, while they made butter pure for offering.\n\np: Arrangers in our synods, Agni, while they sang Vasisistha s sons have called thee down, the Potent One. Maintain the growth of wealth with men who offering. Ye Devas, preserve us with your blessings evermore.","people":["Indra","Agni","Deva","Dawn"],"places":[],"things":["Worship","Master","Work","Reverence","Glory","Offering","Light","Wealth","Food","Men","Might","Song","Home","Wise","Strong","Chief","Praise","Brave","Worshipper","Hero","Cow","Riches"],"groups":["Devas","Maruts","Sons","Bhrgus","Immortal","Man"],"concepts":["Blessings","Immortal","Holy","Strength","Wisdom","Offering","Giver"],"hash":"md5-cZ1HgP0IU5A6sf1EPoHpQA==","created":"Monday, April 8, 2024 - 10:51:56 PM"},{"id":"886a3d84-0a4c-45e4-88ee-a35579f7f17a","key":"10123","book":"10","title":"HYMN CXXIII. Vena.","link":"https://indra.ai/rigveda/hymns/10123.html","text":"p: SEE, Vena, born in light, hath driven hither, on chariot of the air, the Calves of Prsni. Singers with hymns caress him as an infant there where the waters and the sunlight mingle.\n\np: Vena draws up his wave from out the ocean. mist-born, the fair one's back is made apparent, Brightly he shone aloft on Order's summit: the hosts sang glory to their common birthplace.\n\np: Full many, lowing to their joint-possession, dwelling together stood the Darling's Mothers. Ascending to the lofty height of Order, the bands of singers 'sip the sweets of Amrta.\n\np: Knowing his form, the sages yearned to meet him: they have come nigh to hear the wild Bull's bellow. Performing offering they reached the river: for the Gandharva found the immortal waters.\n\np: The Apsaras, the Lady, sweetly smiling, supports her Lover in sublimest heaven. In his Friend's dwelling as a friend he wanders: he, Vena, rests him on his golden pinion.\n\np: They gaze on thee with longing in their spirit, as on a strong-winged bird that mounteth sky-ward; On thee with wings of gold, Varuna's envoy, the Bird that hasteneth to the home of Yama.\n\np: Erect, to heaven hath the Gandharva mounted, pointing at us his many-coloured weapons; Clad in sweet raiment beautiful to look on, for he, as light, produceth forms that please us.\n\np: When as a spark he cometh near the ocean, still looking with a vulture's eye to heaven, His lustre, joying in its own bright splendour, maketh dear glories in the lowest region.","people":["Varuna","Yama"],"places":["Ocean","Heaven","Sky"],"things":["Born","Waters","Glory","Offering","Light","Air","River","Gold","Home","Strong","Form","Splendour","Wings","Friend","Bird","Order","Spirit","Amrta"],"groups":["Apsaras","Gandharva","Immortal"],"concepts":["Beautiful","Immortal","Offering"],"hash":"md5-1ZshYtLNK+SgPjX9rsQ7rQ==","created":"Monday, April 8, 2024 - 10:51:56 PM"},{"id":"b241f6a3-6f7a-4486-ba92-dac1eaadcdf0","key":"10124","book":"10","title":"HYMN CXXIV. Agni, Etc.","link":"https://indra.ai/rigveda/hymns/10124.html","text":"p: COME to this offering of ours, O Agni, threefold, with seven threads and five divisions. Be our oblation-bearer and preceder: thou hast lain lon enough in during darkness.\n\np: I come a Deva.foreseeing from the godless to immortality by secret pathways, While I, ungracious one, desert the gracious, leave mine own friends and seek the kin of strangers.\n\np: 1, looking to the guest of other lineage, have founded many a rule of Law and Order. I bid farewell to the Great Deva, the Father, and, for neglect, obtain my share of worship.\n\np: I tarried many a year within this altar: I leave the Father, for my choice is Indra. Away pass Agni, Varuna and Soma. Rule ever changes: this I come to favour.\n\np: These Asuras have lost their powers of magic. But thou, O Varuna, if thou dost love me, O King, discerning truth and right from falsehood, come and be Lord and Ruler of my kingdom.\n\np: Here is the light of heaven, here allis lovely; here there is radiance, here is air's wide region. Let us two slaughter Vrtra. Forth, O Soma! Thou art oblation: we therewith will serve thee.\n\np: The Sage hath fixed his form by wisdom in the heavens: Varuna with no violence let the waters flow. Like women-folk, the floods that bring prosperity have eau lit his hue and colour as they gleamed and shone.\n\np: These wait upon his loftiest power and vigour: he dwells in these who triumph in their Deva.ead; And they, like people who elect their ruler, have in abhorrence turned away from Vrtra.\n\np: They call him Swan, the abhorrent floods' Companion, moving in friendship with celestial Waters. The poets in their thought have looked on Indra swiftly approaching when Anustup calls him.","people":["Indra","Soma","Vrtra","Agni","Varuna","Deva"],"places":["Heaven"],"things":["Worship","Lord","Triumph","Soma","Celestial Waters","Waters","Offering","Light","Air","Flow","Form","People","Powers","Friends","King","Sage","Swan","call","Order"],"groups":["Asuras","Father"],"concepts":["Celestial","Friendship","Immortality","Love","Wisdom","Offering","Truth"],"hash":"md5-PwfOsJw0SVlkwAernK46+w==","created":"Monday, April 8, 2024 - 10:51:56 PM"},{"id":"bd32af0a-da2e-438c-8a30-ac6efa345adf","key":"10125","book":"10","title":"HYMN CXXV. Vak.","link":"https://indra.ai/rigveda/hymns/10125.html","text":"p: I TRAVEL with the Rudras and the Vasus, with the Adityas and All-Devas I wander. I hold aloft both Varuna and Mitra, indra and Agni, and the Pair of Asvins.\n\np: I cherish and sustain high-swelling Soma, and Tvastar I support, pusan, and Bhaga. I load with wealth the zealous sdcrificer who pours the juice and offers his oblation\n\np: I am the Queen, the gatherer-up of treasure.s, most thoughtful, first of those who merit worship. Thus Devas have stablished me in many places with many homes to enter and abide in.\n\np: Through me alone all eat the food that feeds them.each man who sees, brewhes, hears the word outspoken They know it not, but yet they dwell beside me. Hear, one and all, the truth as I declare it.\n\np: 1, verily, myself announce and utter the word that Devas and men alike shall welcome. I make the man I love exceeding mighty, make him a sage, a Rsi, and a Brahman.\n\np: I bend the bow for Rudra that his arro. May strike and subdue the hater of devotion. I rouse and order battle for the people, and I have penetrated Earth and Heaven.\n\np: On the world's summit I bring forth the Father: my home is in the waters, in the ocean. Thence I extend o’er all existing creatures, and touch even yonder heaven with my forehead.\n\np: I breathe a strong breath like the wind and tempest, the while I hold together all existence. Beyond this wide earth and beyond the heavens I have become so mighty in my grandeur.","people":["Indra","Soma","Agni","Mitra","Varuna","Asvins","Tvastar","Pusan","Bhaga"],"places":["Ocean","Earth","Heaven"],"things":["Worship","Soma","Waters","Treasure","Wealth","Food","Men","Juice","Home","Strong","Mighty","Offers","People","Sage","Order"],"groups":["Devas","Rudras","Father","Man","Vasus","Adityas"],"concepts":["Love","Truth"],"hash":"md5-slUmr1YKsuFUqmA/bkQ8nQ==","created":"Monday, April 8, 2024 - 10:51:56 PM"},{"id":"430910a5-cce2-4247-979f-91bf5e5a11f4","key":"10126","book":"10","title":"HYMN CXXVI, Devas.","link":"https://indra.ai/rigveda/hymns/10126.html","text":"p: No peril, no severe distress, ye Devas, affects the mortal man, whom Aryaman and Mitra lead, and Varima, of one accord, beyond his foes.\n\np: This very thing do we desire, Varuna, Mitra, Aryaman, Whereby ye guhrd the mortal man from sore distress, and lead him safe beyond his foes.\n\np: These are, each one, our present helps, Varuna, Mitra, Aryaman. Best leaders, best deliverers to lead us on and bear as safe beyond our foes.\n\np: Ye compass round and guard each man, Varuna, Mitra, Aryaman: In your dear keepin. May we be, ye who are excellent as guides beyond our foes.\n\np: Adityas are beyond all foes.Varuna, Mitra, Aryaman: Strong Rudra with the Marut host, indra, Agni let us call for weal beyond our foes.\n\np: These lead us safely over all, Varuna, Mitra, Aryaman, these who are Kings of living men, over all troubles far away beyond our foes.\n\np: May they give bliss to aid us well, Varuna, Mitra, Aryaman: May the Adityas, when we meditate, grant us wide shelter and defence beyond our foes.\n\np: As in this place, O Holy Ones, ye Vasus freed even the Gaud when her feet were fettered. So free us now from trouble and affliction: and let our life be lengthened still, O Api.","people":["Indra","Agni","Mitra","Varuna","Aryaman"],"places":[],"things":["Holy Ones","Men","Strong","Excellent","Bliss","call","Life"],"groups":["Devas","Marut","Kings","Man","Vasus","Adityas"],"concepts":["Life","Holy"],"hash":"md5-bBJw5sfUP0u9XSAP3StDbw==","created":"Monday, April 8, 2024 - 10:51:56 PM"},{"id":"163ba2ce-58c2-4eb2-8a9e-8b3a423e655f","key":"10127","book":"10","title":"HYMN CXXVII. Night.","link":"https://indra.ai/rigveda/hymns/10127.html","text":"p: WITH all her eyes the Deva Night looks forth approaching many a spot: She hath put all her glories on.\n\np: Immortal. she hath filled the waste, the Deva hath filled height and depth: She conquers darkness with her light.\n\np: The Deva as she comes hath set the Dawn her Sister in her place: And then the darkness vanishes.\n\np: So favour us this night, O thou whose pathways we have visited As birds their nest upon the tree.\n\np: The villagers have sought their homes, and all that walks and all that flies, Even the falcons fain for prey.\n\np: Keep off the she-wolf and the wolf, O Urmya, keep the thief away; Easy be thou for us to pass.\n\np: Clearly hath she come nigh to me who decks the dark with richest hues: O Morning, cancel it like debts.\n\np: These have I brought to thee like kine. O Night, thou Child of Heaven, accept This laud as for a conqueror.","people":["Deva","Dawn"],"places":["Heaven"],"things":["Light","Morning"],"groups":["Child","Sister","Immortal"],"concepts":["Immortal"],"hash":"md5-gfPrPp5s6Wsl1BY+TLDWvg==","created":"Monday, April 8, 2024 - 10:51:56 PM"},{"id":"523c425a-5c7d-40c3-86b0-01d6e4c03cba","key":"10128","book":"10","title":"HYMN CXXVIII, Devas.","link":"https://indra.ai/rigveda/hymns/10128.html","text":"p: LET me win glory, Agni, in our battles: enkindling thee. May we support our bodies. May the four regions bend and bow before me: with thee for guardia. May we win in combat.\n\np: May all the Devas be on my side in battle, the Maruts led by Indra, Visnu, Agni. Mine be the middle air's extended region, an. May the wind blow favouring these my wishes.\n\np: May the Devas grant me riches. May the blessing and invocation of the Devas assist me. Foremost in fight be the divine Invokers. May we, unwounded, have brave heroes round us.\n\np: For me let them present all mine oblations, and let my mind's intention be accomplished. May I he guiltless of the least transgression: and, all ye Devas, do ye combine to bless us.\n\np: Ye six divine Expanses, grant us freedom: here, all ye Devas, acquit yourselves like heroes. Let us not lose our children or our bodies: let us not benefit the foe, King Soma!\n\np: Baffling the wrath of our opponents, Agni, guard us as our infallible Protector. Let these thy foes turn back and seek their houses, and let their thought who watch at home be ruined.\n\np: Lord of the world, Creator of creators the saviour Deva who overcomes the foeman. May Devas, Narasamsa, both Asvins shelter from ill this offering and offerer.\n\np: Foodful, and much-invoked, at this our callin. May the great Bull vouchsafe us wide protection. Lord of Bay Coursers, indra, blew our children: harm us not, give us not as prey to others.\n\np: Let those who are our foemen stay. afar from us: with Indra and with Agni we will drive them off. Vasus, Adityas, Rudras have exalted me, made me far-reaching, mighty, thinker, sovran lord.","people":["Indra","Soma","King Soma","Agni","Visnu","Asvins","Narasamsa","Deva"],"places":[],"things":["Lord","Soma","Glory","Offering","Air","Creator","Home","Mighty","Blessing","Brave","Heroes","King","Riches"],"groups":["Devas","Maruts","Rudras","Vasus","Adityas"],"concepts":["Divine","Offering","Creator"],"hash":"md5-6qPnqg5REW+pO4Nz/vxz6Q==","created":"Monday, April 8, 2024 - 10:51:56 PM"},{"id":"2561c363-1599-4ce7-93a5-b3dfe7a3a7a5","key":"10129","book":"10","title":"HYMN CXXIX. Creation.","link":"https://indra.ai/rigveda/hymns/10129.html","text":"p: THEN was not non-existent nor existent: there was no realm of air, no sky beyond it. What covered in, and where? and what gave shelter? Was water there, unfathomed depth of water?\n\np: Death was not then, nor was there aught immortal: no sign was there, the day's and night's divider. That One Thing, breathless, breathed by its own nature: apart from it was nothing whatsoever.\n\np: Darkness there was: at first concealed in darkness this All was indiscriminated chaos. All that existed then was void and form less: by the great power of Warmth was born that Unit.\n\np: Thereafter rose Desire in the beginning, Desire, the primal seed and germ of Spirit. Sages who searched with their heart's thought discovered the existent's kinship in the non-existent.\n\np: Transversely was their severing line extended: what was above it then, and what below it? There were begetters, there were mighty forces, free action here and energy up yonder\n\np: Who verily knows and who can here declare it, whence it was born and whence comes this creation? The Devas are later than this world's production. Who knows then whence it first came into being?\n\np: He, the first origin of this creation, whether he formed it all or did not form it, whose eye controls this world in highest heaven, he verily knows it, or perhaps he knows not.","people":[],"places":["Heaven","Sky"],"things":["Born","Water","Air","Mighty","Form","Death","Spirit"],"groups":["Devas","Immortal"],"concepts":["Death","Immortal"],"hash":"md5-sRfTJnGwHUN8e3ZAuaOmlQ==","created":"Monday, April 8, 2024 - 10:51:56 PM"},{"id":"5b4b4aca-fef9-4a65-b4d2-3bc15d669693","key":"10130","book":"10","title":"HYMN CXXX. Creation.","link":"https://indra.ai/rigveda/hymns/10130.html","text":"p: THE offering drawn out with threads on every side, stretched by a hundred sacred ministers and one. This do these Fathers weave who hitherward are come: they sit beside the warp and cry, Weave forth, weave back.\n\np: The Man extends it and the Man unbinds it: even to this vault of heaven hath he outspun, it. These pegs are fastened to the seat of worship: they made the Sama-hymns their weaving shuttles.\n\np: What were the rule, the order and the model? What were the wooden fender and the butter? What were the hymn, the chant, the recitation, when to the Deva.all Deities paid worship?\n\np: Closely was Gayatri conjoined with Agni, and closely Savitar combined with Usnih. Brilliant with Ukthas, Soma joined Anustup: Narasamsa's voice by Brhati was aided.\n\np: Viraj adhered to Varuna and Mitra: here Tristup day by day was Indra's portion. Jagati entered all the Devas together: so by this knowledge men were raised to Rsis.\n\np: So by this knowledge men were raised to Rsis, when ancient offering sprang up, our Fathers. With the mind's eye I think that I behold them who first performed this offerings worship.\n\np: They who were versed in ritual and metre, in hymns and rules, were the Seven Deva like Rsis. Viewing the path of those of old, the sages have taken up the reins like chariot-drivers.","people":["Indra","Soma","Agni","Mitra","Varuna","Narasamsa","Savitar","Deva"],"places":["Heaven"],"things":["Worship","Soma","Offering","Men","Voice","Hymn","Offerings","Order"],"groups":["Devas","Fathers","Deities","Rsis","Man"],"concepts":["Sacred","Offering","Offerings"],"hash":"md5-rGOgPMJxH6TIYbHbWQlZCw==","created":"Monday, April 8, 2024 - 10:51:56 PM"},{"id":"201fc1d2-dd91-49d5-bd08-1f0bfa85a30a","key":"10131","book":"10","title":"HYMN CXXXI. Indra.","link":"https://indra.ai/rigveda/hymns/10131.html","text":"p: DRIVE all our enemies away, O Indra, the western, mighty Conqueror, and the eastern. Hero, drive off our northern foes and southern, that we in thy wide shelte. May be joyful.\n\np: What then? As men whose fields are full of barley reap the ripe corn removing it in order, So bring the food of those men, bring it hither, who went not to prepare the grass for worship.\n\np: Men come not with one horse at sacred seasons; thus they obtain no honour in assemblies. Sages desiring herds of kine and horses strengthen the mighty Indra for his friendship.\n\np: Ye, Asvins, Lords of Splendour, drank full draughts of grateful Soma juice, and aided Indra in his work with Namuci of Asura birth.\n\np: As parents aid a son, both Asvins, indra, aided thee with their wondrous Powers and wisdom. When thou, with might. hadst drunk the draught that gladdens, Sarasvati refreshed thee.\n\np: Indra is strong to save, rich in assistanc. May he, possessing all, be kind and gracious. May he disperse our foes and give us safety, an. May we be the lords of hero vigou r.\n\np: May we enjoy his favour, his the Hol. May we enjoy his blessed loving kindness. May this rich Indra, as our good Protector, drive off and keep afar all those who hate us.","people":["Indra","Soma","Asvins","Sarasvati","Namuci"],"places":[],"things":["Worship","Work","Seasons","Soma","Food","Men","Might","Juice","Strong","Mighty","Grass","Splendour","Powers","Hero","Parents","Horses","Horse","Order"],"groups":["Asura","Son"],"concepts":["Good","Birth","Friendship","Sacred","Wisdom"],"hash":"md5-t5K+zIcj/TwwF37kyY1keA==","created":"Monday, April 8, 2024 - 10:51:56 PM"},{"id":"cf66bf66-a02a-44e8-84b4-550a170ce428","key":"10132","book":"10","title":"HYMN CXXXII. Mitra. Varuna.","link":"https://indra.ai/rigveda/hymns/10132.html","text":"p: MAY Dyaus the Lord of lauded wealth, and Earth stand by the man who offers offering, an. May the Asvins, both the Devas, strengthen the worshipper with bliss.\n\np: As such we honour you, Mitra and Varuna, with hasty zeal, most blest, you who sustain the folk. May we, through your friendship for the worshipper, subdue the fiends.\n\np: And when we seek to win your love and friendship, weẉho have precious wealth in our possession, or when the worshipper augments his riches let not his treasure.s be shut up\n\np: That other, Asura! too was born of Heaven. thou art, O Varuna, the King of all men. The chariot's Lord was well content, forbearing to anger Death by sin so great. This sin hath Sakaputa here committed. Heroes who fled to their dear friend he slayeth, when the Steed bringeth down your grace and favour in bodies dear and worshipful.\n\np: Your Mother Aditi, ye wise, was purified with water even as earth is purified from heaven. Show love and kindness here below: wash her in rays of heavenly light.\n\np: Ye Twain have seated you as Lords of Wealth, as one who mounts a car to him who sits upon the pole, upon the wood. These our disheartened tribes Nrmedhas saved from woe, Sumedhas saved from Woe.","people":["Mitra","Varuna","Asvins","Aditi"],"places":["Earth","Heaven"],"things":["Lord","Born","Water","Offering","Light","Treasure","Wealth","Men","Wise","Car","Worshipper","Heroes","Offers","Bliss","Friend","King","Riches","Death"],"groups":["Devas","Asura","Dyaus","Mother","Man"],"concepts":["Death","Heavenly","Friendship","Love","Offering"],"hash":"md5-ik9vBZhMQdQ4L5vnwoY/eA==","created":"Monday, April 8, 2024 - 10:51:56 PM"},{"id":"b7d771a9-c62c-49e7-a719-f99f6ba998fd","key":"10133","book":"10","title":"HYMN CXXXIII. Indra.","link":"https://indra.ai/rigveda/hymns/10133.html","text":"p: SING strength to Indra that shall set his chariot in the foremost place. Giver of room in closest fight, slayer of foes in shock of war, be thou our great encourager. Let the weak bowstrings break upon the bows of feeble enemies.\n\np: Thou didst destroy the Dragon: thou sentest the rivers down to earth. Foeless, O Indra, wast thou born. Thou tendest well each choicest thing. Therefore we draw us close to thee. Let the weak bowstrings break upon the bows of feeble enemies.\n\np: Destroyed be all malignities and all our enemy's designs. Thy bolt thou castest, at the foe, O Indra, who would srnite us dead: thy liberal bounty gives us wealth.\n\np: The robber people round about, indra, who watch and aim at us. Trample them down beneath thy foot; a conquering scatterer art thou.\n\np: Whoso assails us, indra, be the man a stranger or akin, Bring down, thyself, his strength although it be as vast as are the heavens.\n\np: Close to thy friendship do we cling, O Indra, and depend, or, thee. Lead us beyond all pain and grief along the path of holy Law.\n\np: Do thou bestow upon us her, O Indra, who yields according to the singer's longing, that the great Co. May, with exhaustless udder, pouring a thousand streams, give milk to feed us.","people":["Indra"],"places":["Earth"],"things":["Milk","Born","Rivers","Singer","Wealth","Streams","People"],"groups":["Man"],"concepts":["Friendship","Holy","Strength","Giver"],"hash":"md5-EfQmD0tle3YiD+o47tkGVg==","created":"Monday, April 8, 2024 - 10:51:56 PM"},{"id":"94fd38bb-74d5-447c-805a-c58ef75d812b","key":"10134","book":"10","title":"HYMN CXXXIV. Indra.","link":"https://indra.ai/rigveda/hymns/10134.html","text":"p: As, like the Morning, thou hast filled, O Indra, both the earth and heaven. So as the Mighty One, great King of all the mighty world of men, the Deva Mother brought thee forth, the Blessed Mother gave thee life.\n\np: Relax that mortal's stubborn strength whose heart is bent on wickedness. Trample him down beneath thy feet who watches for and aims at us. The Deva Mother brought thee forth, the Blessed Mother gave thee life.\n\np: Shake down, O Slayer of the foe, those great all splendid enemies. With all thy powers, O Sakra, all thine helps, O Indra, shake them down:\n\np: As thou, O Satakratu O Indrv, shakest all things down As wealth for him who sheds the juice, with thine assistance thousandfold.\n\np: Around, on every side like drops of sweat let lightning-flashes fall. Let all malevolence pass away from us like threads of Darva grass.\n\np: Thou bearest in thine hand a lance like a long hook, great Counsellor! As with his foremost foot a goat, draw down the branch, O Maghavan.\n\np: Never, O Devas, do we offend, nor are we ever obstinate: we walk as holy texts command. Closely we clasp and cling to you, cling to your sides, beneath your arms.","people":["Indra","Satakratu","Sakra","Maghavan","Deva"],"places":["Earth","Heaven"],"things":["Wealth","Men","Juice","Mighty","Grass","Powers","Drops","King","Morning","Life"],"groups":["Devas","Mother"],"concepts":["Life","Holy","Strength"],"hash":"md5-1gCSVNk1aSzeprQVrZqbBw==","created":"Monday, April 8, 2024 - 10:51:56 PM"},{"id":"05fb8b88-6ec2-46f6-b410-5f3d7a8741d6","key":"10135","book":"10","title":"HYMN CXXXV. Yama.","link":"https://indra.ai/rigveda/hymns/10135.html","text":"p: IN the Tree clothed with goodly leaves where Yama drinketh with the Devas, the Father, Master of the house, tendeth with love our ancient Sires.\n\np: I looked reluctantly on him who cherishes those men of old, On him who treads that evil path, and then I yearned for this again.\n\np: Thou mountest, though thou dost not see, O Child, the new and wheel-less car Which thou hast fashioned mentally, onepoled but turning every way.\n\np: The car which thou hast made to roll hitherward from the Sages, Child! This hath the Saman followed close, hence, laid together on a ship.\n\np: Who was the father of the child? Who made the chariot roll away? Who will this day declare to us how the funeral gift was made?\n\np: When the funeral gift was placed, straightway the point of flame appeared. A depth extended in the front: a passage out was made behind.\n\np: Here is the seat where Yama dwells, that which is called the Home of Devas: Here minstrels blow the flute for him here he is glorified with songs.","people":["Yama"],"places":[],"things":["Master","Men","Home","Car","Gift","Songs","Wheel"],"groups":["Devas","Father","Child"],"concepts":["Evil","Love"],"hash":"md5-ODzxTNT7uyAf0MGA3t93hg==","created":"Monday, April 8, 2024 - 10:51:56 PM"},{"id":"ca5df1db-d303-4a39-bebd-ae80b04b28d9","key":"10136","book":"10","title":"HYMN CXXXVI. Kesins.","link":"https://indra.ai/rigveda/hymns/10136.html","text":"p: HE with the long loose locks supports Agni, and moisture, heaven, and earth: He is all sky to look upon: he with long hair is called this light.\n\np: The Munis, girdled with the wind, wear garments soiled of yellow hue. They, following the wind's swift course go where the Devas have gone before.\n\np: Transported with our Munihood we have pressed on into the winds: You therefore, mortal men. behold our natural bodies and no more.\n\np: The Muni, made associate in the holy work of every Deva, Looking upon all varied forms flies through the region of the air.\n\np: The Steed of Vata, Vayu's friend, the Muni, by the Devas impelled, in both the oceans hath his home, in eastern and in western sea.\n\np: Treading the path of sylvan beasts, Gandharvas, and Apsarases. He with long locks, who knows the wish, is a sweet most delightful friend\n\np: Vayu hath churned for him: for him he poundeth things most hard to bend, when he with long loose locks hath drunk, with Rudra, water from the cup.","people":["Agni","Vayu","Deva","Vata"],"places":["Earth","Heaven","Sky"],"things":["Work","Water","Light","Air","Men","Home","Friend"],"groups":["Devas","Gandharvas"],"concepts":["Holy","Swift"],"hash":"md5-4nrB+bT7FOnvD7EutWTORg==","created":"Monday, April 8, 2024 - 10:51:56 PM"},{"id":"8554ae5e-3c21-4cdf-9994-dd493dea0a96","key":"10137","book":"10","title":"HYMN CXXXVII Devas.","link":"https://indra.ai/rigveda/hymns/10137.html","text":"p: YE Devas, raise up once more the man whom ye have humbled and brought low. O Devas, restore to life again the man who hatb committed sin.\n\np: Two several winds are blowing here, from Sindhu, from a distant land. May one breathe energy to thee, the other blow disease away.\n\np: Hither, O Wind, blow healing balm, blow all disease away, thou Wind; For thou who hast all medicine comest as envoy of the Devas.\n\np: I am come nigh to thee with balms to give thee rest and keep thee safe. I bring thee blessed strength, I drive thy weakening malady away.\n\np: Here let the Devas deliver him, the Maruts’ band deliver him: All things that be deliver him that he be freed from his disease.\n\np: The Waters have their healing power, the Waters drive disease away. The Waters have a balm for all: let them make medicine for thee.\n\np: The tongue that leads the voice precedes. Then with our ten-fold branching hands, with these two chasers of disease we stroke thee with a gentle touch.","people":["Sindhu"],"places":[],"things":["Waters","Voice","Life"],"groups":["Devas","Maruts","Man"],"concepts":["Life","Strength"],"hash":"md5-/iosYOTgtlAfracsIHMy+Q==","created":"Monday, April 8, 2024 - 10:51:56 PM"},{"id":"e5ac0c7a-21e7-4132-90de-c0e7ecf84203","key":"10138","book":"10","title":"HYMN CXXXVIII. Indra.","link":"https://indra.ai/rigveda/hymns/10138.html","text":"p: ALLIED with thee in friendship, indra, these, thy monks, remembering Holy Law, rent Vrtra limb from limb, when they bestowed the Dawns and let the waters flow, and when thou didst chastise dragons at Kutsa's call.\n\np: Thou sentest forth productive powers, clavest the hills, thou dravest forth the kine, thou drankest pleasant meath. Thou gavest increase through this Tree's surpassing might. The Sun shone by the hymn that sprang from Holy Law.\n\np: In the mid-way of heaven the Sun unyoked his car: the Arya found a match to meet his Dam foe. Associate with Rjisvan Indra overthrew the solid forts of Pipru, conjuring Asura.\n\np: He boldly cast down forts which none had e’er assailed: unwearied he destroycd the godless treasure.-stores. Like Sun and Moon he took the stronghold's wealth away, and, praised in song, demolished foes with flashing dart.\n\np: Armed with resistless weapons, with vast power to cleave, the Vrtra conquerer whets his darts and deals fordi wounds. Bright Usas was afraid of Indra's slaughtering bolt: she went upon her way and left her chariot there.\n\np: These are thy famous exploits, only thine, when thou alone hast left the other reft of offering. Thou in the heavens hast set the ordering of the Moons: the Father bears the felly portioned out by thee.","people":["Indra","Vrtra","Kutsa","Usas","Rjisvan"],"places":["Heaven"],"things":["Meath","Waters","Offering","Sun","Moon","Treasure","Wealth","Flow","Might","Song","Car","Hymn","Powers","call"],"groups":["Asura","Dawns","Father","Monks"],"concepts":["Friendship","Holy","Offering"],"hash":"md5-J/iwk4Z0eLz99XTuhdYrmw==","created":"Monday, April 8, 2024 - 10:51:56 PM"},{"id":"ff955b4e-4bf9-4bb0-9a53-a2c8df186acd","key":"10139","book":"10","title":"HYMN CXXXIX. Savitar.","link":"https://indra.ai/rigveda/hymns/10139.html","text":"p: SAVITAR, golden-haired, hath lifted eas ward, bright With the sunbeams, his eternal lustre; He in whose energy wise Pusan marches, surveying all existence like a herdsman.\n\np: Beholding men he sits amid the heaven filling the two world-halves and air's wide region. He looks upon the rich far-spreading pastures between the eastern and the western limit.\n\np: He, root of wealth, the gatherer-up of treasure.s, looks with his might on every form and figure. Savitar, like a Deva.hose Law is constant, stands in the battle for the spoil like Indra.\n\np: Waters from offering came to the Gandharva Visvavasu, O Soma, when they s w him. Indra, approaching quickly, marked their going, and looked around upon the Sun's enclosures.\n\np: This song Visvavasu shall sing us, meter of air's mid-realm celestial Gandharva, that we may know aright both truth and falsehood. May he inspire our thoughts and help our praises.\n\np: In the floods' track he found the bootyseeker: the rocky cow-pen's doors he threw wide open. These, the Gandharva told him, Rowed with Amrta. Indra knew well the puissancc of the dragons.","people":["Indra","Soma","Savitar","Pusan","Deva","Visvavasu"],"places":["Heaven"],"things":["Soma","Waters","Offering","Air","Sun","Treasure","Wealth","Men","Might","Song","Help","Wise","Form","Cow","spoil","Amrta"],"groups":["Gandharva"],"concepts":["Celestial","Offering","Truth"],"hash":"md5-GiARWbz3NU+O+lh4W1JgJw==","created":"Monday, April 8, 2024 - 10:51:56 PM"},{"id":"1e8b7f60-e90e-42c8-9d5a-4f08a9b23501","key":"10140","book":"10","title":"HYMN CXL. Agni.","link":"https://indra.ai/rigveda/hymns/10140.html","text":"p: AGNI, life-power and fame are thine: thy fires blaze mightily, thou rich in wealth of beams! Sage, passing bright, thou givest to the worshipper, with strength, the food that merits laud.\n\np: With brilliant, purifying sheen, with perfect sheen thou liftest up thyself in light. Thou, visiting both thy Mothers, aidest them as Son: thou joinest close the earth and heaven.\n\np: O Jatavedas, Son of Strength, rejoice ihyself, gracious, in our fair hymns and songs. In thee are treasure.d various forms of strengthening food, born nobly and of wondrous help.\n\np: Agni, spread forth, as Ruler, over living things: give wealth to us, Immortal Deva. Thou shinest out from beauty fair to look upon: thou leadest us to conquering power.\n\np: To him, the wise, who orders offerings, who hath great riches un der his control, Thou givest blest award of good, and plenteous food, givest him wealth that conquers all.\n\np: The men have set before them them for their welfare Agni, strong, visible to all, the Holy. Thee, Deva like One, with ears to hear, most famous, men's generations magnify with praise-songs.","people":["Agni","Deva"],"places":["Earth","Heaven"],"things":["Born","Light","Treasure","Wealth","Food","Men","Beauty","Help","Wise","Strong","Praise","Worshipper","Offerings","Songs","Sage","Riches","Life"],"groups":["Jatavedas","Son","Immortal"],"concepts":["Good","Life","Immortal","Holy","Strength","Offerings"],"hash":"md5-rPLQcbSUyZT/j/Ur+Nf0bw==","created":"Monday, April 8, 2024 - 10:51:56 PM"},{"id":"6df418cc-fbbd-4d7d-91e0-80cbdf2fbe15","key":"10141","book":"10","title":"HYMN CXLI, Devas.","link":"https://indra.ai/rigveda/hymns/10141.html","text":"p: TURN hither, Agni, speak to us: come to us with a gracious mind. Enrich us, Master of the house: thou art the Giver of our wealth.\n\np: Let Aryarnan vouchsafe us wealth, and Bhaga, and Narasamsa. Let the Devas give their gifts, and let Sunrta, Deva, grant us wealth.\n\np: We call King Soma to our aid, and Agni with our songs and hymns, Adityas, Visnu, Surya, and the Brahman Monk Narasamsa.\n\np: Indra, Vayu, Narasamsa, Devas swift to listen, we invoke, that in the synod all the fol. May be benevolent to us.\n\np: Urge Aryaman to send us gifts, and Indra, and Narasamsa, Vata, Visnu, Sarasvati and the Strong Courser Savitar.\n\np: Do thou, O Agni, with thy fires strengthen our meditation and offering: Urge givers to bestow their wealth to aid our service of the Devas.","people":["Indra","Soma","King Soma","Agni","Vayu","Visnu","Narasamsa","Savitar","Sarasvati","Bhaga","Sunrta","Deva","Surya","Vata","Aryaman"],"places":[],"things":["Master","Meditation","Soma","Offering","Wealth","Strong","Songs","King","call","Gifts"],"groups":["Devas","Adityas"],"concepts":["Offering","Giver","Swift"],"hash":"md5-PYW59vvPT1AXso+skCYlwg==","created":"Monday, April 8, 2024 - 10:51:56 PM"},{"id":"15a700f6-c59c-442f-b911-a2f00549486f","key":"10142","book":"10","title":"HYMN CXLII. Agni.","link":"https://indra.ai/rigveda/hymns/10142.html","text":"p: WITH thee, O Agni, was this singer of the laud: he hath no other kinship, O thou Son of Strength. Thou givest blessed shelter with a triple guard. Keep the destructive lightning far away from us.\n\np: Thy birth who seekest food is in the falling flood, Agni: as Comrade thou winnest all living things. Our coursers and our songs shall be victorious: they of themselves advance like one who guards the herd.\n\np: And thou, O Agni, thou of Deva like nature, sparest the stones, while caring up the brus wood. Then are thy tracks like deserts in the corn-lands. Let us not stir to wrath thy mighty arrow.\n\np: O'er hills through vales devouring as thou goest, thou partest like an army fain for booty As when a barber shaves a beard, thou shavest earth when the wind blows on thy flame and fans it.\n\np: Apparent are his lines as he approaches the course is single, but the cars are many, when, Agni making thine arms resplendent, advancest o’er the land spread out beneath thee.\n\np: Now let thy strength, thy burning flames fly upward, thine energies, O Agni, as thou toilest. Gape widely, bend thee, waxing in thy vigour: let all the Vasus sit this day beside thee.\n\np: This is the waters' reservoir, the great abode of gathered streams. Take thou another path than this, and as thou listest walk thereon.\n\np: On thy way hitherward and hence let flowery Durva grass spring up Let there be lakes with lotus blooms. These are the mansions of the flood.","people":["Agni","Deva"],"places":["Earth"],"things":["Waters","Singer","Food","Streams","Mighty","Grass","Reservoir","Songs","Cars"],"groups":["Son","Vasus"],"concepts":["Birth","Cars","Strength"],"hash":"md5-RdiVBcxBFQr1Cq1Xw/fXHQ==","created":"Monday, April 8, 2024 - 10:51:56 PM"},{"id":"8ee0b44f-71fc-43f3-b422-dd42337e8631","key":"10143","book":"10","title":"HYMN CXLIII. Asvins.","link":"https://indra.ai/rigveda/hymns/10143.html","text":"p: YE made that Atri, worn with eld, free as a horse to win the goal. When ye restored to youth and strength Kaksivan like a car renewed,\n\np: Ye freed that Atri like a horse, and brought him newly-born to earth. Ye loosed him like a firm-tied knot which Devas unsoiled by dust had bound.\n\np: Heroes who showed most wondrous power to Atri, strive to win fair songs; For then, O Heroes of the sky, your hymn of praise shall cease no more.\n\np: This claims your notice, Bounteous Devas! - oblation, Asvins! and our love, that ye, O Heroes, in the figh. May bring us safe to ample room.\n\np: Ye Twain to Bhujyu tossed about in ocean at the region's end, Nasatyas, with your winged sterds came nigh, and gave him strength to win.\n\np: Come with your joys, most liberal Devas, Lords of all treasure.s, bringing weal. Like fresh full waters to a well, so. Heroes come and be with us.","people":["Asvins","Nasatyas","Atri","Kaksivan"],"places":["Ocean","Earth","Sky"],"things":["Born","Waters","Treasure","Car","Praise","Hymn","Heroes","Songs","Horse"],"groups":["Devas"],"concepts":["Love","Strength"],"hash":"md5-dicP4Bx7cnazEBQqMu6YWA==","created":"Monday, April 8, 2024 - 10:51:56 PM"},{"id":"e7419b34-5cd6-42c4-b317-8e632b7486ce","key":"10144","book":"10","title":"HYMN CXLIV. Indra.","link":"https://indra.ai/rigveda/hymns/10144.html","text":"p: THIS deathless Indu, like a steed, strong and of full vitality, belongs to thee, the Orderer.\n\np: Here, by us, for the worshipper, is the wise bolt that works with skill. It brings the bubbling beverage as a dexterous man brings the effectual strong drink.\n\np: Impetuous Ahisuva, a bull among cows of his, looked down upon the restless Hawk.\n\np: That the strong-pinioned Bird hath brought, Child of the Falcon, from afar, what moves upon a hundred wheels along the female Dragon's path.\n\np: Which, fair, unrobbed, the Falcon brought thee in his foot, the red-hued dwelling of the juice; Through this came vital power which lengthens out our days, and kinship through its help awoke.\n\np: So Indra is by lndu's power; e’en among Devas will it repel great treachery. Wisdom, most Sapient One, brings force that lengthens life. May wisdom bring the juice to us.","people":["Indu","Indra"],"places":[],"things":["Juice","Help","Wise","Strong","Worshipper","Bird","Life"],"groups":["Devas","Child","Man"],"concepts":["Life","Wisdom"],"hash":"md5-3Wk7aydlq9AfqzSVNy6I1Q==","created":"Monday, April 8, 2024 - 10:51:56 PM"},{"id":"c9c67cdd-9f7d-4f72-a635-f3df897fba64","key":"10145","book":"10","title":"HYMN CXLV. Sapatnibadhanam.","link":"https://indra.ai/rigveda/hymns/10145.html","text":"p: FROM out the earth I dig this plant, a herb of most effectual power, Wherewith one quells the rival wife and gains the husband for oneself.\n\np: Auspicious, with expanded leaves, sent by the Devas, victorious plant, Blow thou the rival wife away, and make my husband only mine.\n\np: Stronger am 1, O Stronger One, yea, mightier than the mightier; And she who is my rival wife is lower than the lowest dames.\n\np: Her very name I utter not: she takes no pleasure in this man. Far into distance most remote drive we the rival wife away.\n\np: I am the conqueror, and thou, thou also act victorious: As victory attends us both we will subdue my fellow-wife.\n\np: I have gained thee for vanquisher, have grasped thee with a stronger spell. As a cow hastens to her calf, so let thy spirit speed te me, hasten like water on its way.","people":[],"places":["Earth"],"things":["Victory","Water","Cow","Spirit"],"groups":["Devas","Dames","Wife","Husband","Man"],"concepts":["Auspicious"],"hash":"md5-eDaIsi08+mgwu/7kOzK5+A==","created":"Monday, April 8, 2024 - 10:51:56 PM"},{"id":"60af7a6b-2bef-4874-af3a-b17139aa6d37","key":"10146","book":"10","title":"HYMN CXLVI. Aranyani.","link":"https://indra.ai/rigveda/hymns/10146.html","text":"p: GODDESS of wild and forest who seemest to vanish from the sight. How is it that thou seekest not the village? Art thou not afraid?\n\np: What time the grasshopper replies and swells the shrill cicala's voice, Seeming to sound with tinkling bells, the Lady of the Wood exults.\n\np: And, yonder, cattle seem to graze, what seems a dwelling-place appears: Or else at eve the Lady of the Forest seems to free the wains.\n\np: Here one is calling to his cow, another there hath felled a tree: At eve the dweller in the wood fancies that somebody hath screamed.\n\np: The Deva never subdues, unless some murderous enemy approach. Man eats of savoury fruit and then takes, even as he wills, his rest.\n\np: Now have I praised the Forest Queen, sweet-scented, redolent of balm, the Mother of all sylvan things, who tills not but hath stores of food.","people":["Deva"],"places":[],"things":["Food","Voice","Cow","Cattle"],"groups":["Mother","Man"],"concepts":[],"hash":"md5-LV3Mtw1moUJf07Hkli5ugQ==","created":"Monday, April 8, 2024 - 10:51:56 PM"},{"id":"2db82cbd-078c-422c-9353-587385b202f1","key":"10147","book":"10","title":"HYMN CXLVII Indra.","link":"https://indra.ai/rigveda/hymns/10147.html","text":"p: I TRUST in thy first wrathful deed, O Indra, when thou slewest Vrtra and didst work to profit man; What time the two world-halves fell short of thee in might, and the earth trembled at thy force, O Thunder-anned.\n\np: Thou with thy magic powers didst rend the conjurer Vrtra, O Blameless One, with heart that longed for fame. Heroes elect thee when they battle for the prey, thee in all offers worthy of renown.\n\np: Deva.Much-invoked, take pleasure in these princes here, who, thine exalters, Maghavan, have come to wealth. In synods, when the rite succeeds, they hymn the Strong for sons and progeny and riches undisturbed.\n\np: That man shall find delight in well-protected wealth whose care provides for him the quick-sought joyous draught. Bringing oblations, strengthened Maghavan, by thee, he swiftly wins the spoil with heroes in the fight.\n\np: Now for our band when lauded, make ample room with might, and grant us riches. Magician thou, our Varuna and Mitra, deal food to us, O Wondrous, as Dispenser.","people":["Indra","Vrtra","Mitra","Varuna","Maghavan","Deva"],"places":["Earth"],"things":["Work","Wealth","Food","Might","Strong","Delight","Hymn","Heroes","Offers","Powers","Dispenser","spoil","Riches"],"groups":["Sons","Progeny","Man"],"concepts":[],"hash":"md5-Crvk6vCc03GioAxre9q2Pw==","created":"Monday, April 8, 2024 - 10:51:56 PM"},{"id":"1a455e32-8dad-4ae6-ad56-dfd5684b6d9c","key":"10148","book":"10","title":"HYMN CXLVIII. Indra.","link":"https://indra.ai/rigveda/hymns/10148.html","text":"p: WHEN we have pressed the juice we laud thee, indra, and when, most Valorous we have won the booty. Bring us prosperity, as each desires it under thine own protection. May we conquer.\n\np: Sublime from birth. Mayst thou O Indra. Hero, with Surya overcome the Dasa races. As by a fountain's side, we bring the Soma that lay concealed, close-hidden in the waters.\n\np: Answer the votary's hymns, for these thou knowest, craving the Rsis’ prayer, thyself a Singer May we be they who take delight in Somas: these with sweet food for thee, O Chariot-rider.\n\np: These holy prayers, O Indra, have I sung thee: grant to the men the strength of men, thou Hero. Be of one mind with those in whom thou joyest: keep thou the singers safe and their companions.\n\np: Listen to Prthi's call, heroic Indra, and be thou lauded by the hymns of Venyahim who hath sung thee to thine oil-rich dwelling, whose rolling songs have sped thee like a torrent.","people":["Indra","Soma","Surya"],"places":[],"things":["Soma","Waters","Singer","Food","Men","Juice","Delight","Songs","Hero","call"],"groups":["Rsis"],"concepts":["Birth","Heroic","Holy","Strength"],"hash":"md5-qDEFCikl/ZtfPo0MV9mf/w==","created":"Monday, April 8, 2024 - 10:51:56 PM"},{"id":"e71c20d8-6b8d-4598-a02d-60eb450f87cd","key":"10149","book":"10","title":"HYMN CXLIX. Savitar.","link":"https://indra.ai/rigveda/hymns/10149.html","text":"p: SAVITAR fixed the earth with bands to bind it, and made heaven stedfast where no prop supported. Savitar milked, as ’twere a restless courser, air, sea bound fast to what no foot had trodden.\n\np: Well knoweth Savitar, O Child of Waters, where ocean, firmly fixt, o’erflowed its limit. Thence sprang the world, from that uprose the region: thence heaven spread out and the wide earth expanded.\n\np: Then, with a full crowd of Immortal Beings, this other realm came later, high and holy. First, verily, Savitar's strong-pinioned Eagle was born: and he obeys his law forever.\n\np: As warriors to their steeds, kine to their village, as fond milk giving cows approach their youngling, as man to wife, let Savitar come downward to us, heaven's bearer, Lord of every blessing.\n\np: Like the Angirasa Hiranvastupa, I call thee, Savitar, to this achievement: So worshipping and lauding thee for favour I watch for thee as for the stalk of Soma.","people":["Soma","Savitar"],"places":["Ocean","Earth","Heaven"],"things":["Milk","Steeds","Lord","Born","Soma","Waters","Air","Strong","Blessing","call"],"groups":["Child","Wife","Immortal","Man"],"concepts":["Immortal","Holy"],"hash":"md5-OIh1Lgus3nIxraO3OherfQ==","created":"Monday, April 8, 2024 - 10:51:56 PM"},{"id":"b06c5fa5-a875-4cc7-ab1d-05a371675750","key":"10150","book":"10","title":"HYMN CL. Agni.","link":"https://indra.ai/rigveda/hymns/10150.html","text":"p: THOU, bearer of oblations, though kindled, art kindled for the Devas. With the Adityas, Rudras, Vasus, come to us: to show us favour come to us.\n\np: Come hither and accept with joy this offering and hymn of ours. O kindled Deva, we mortals are invoking thee, calling on thee to show us grace.\n\np: I laud thee Jatavedas, thee Lord of all blessings, with my song. Agni, bring hitherward the Devas whose Laws we love, whose laws we love, to show us grace.\n\np: Agni the Deva.was made the great High-Monk of Devas, Rsis have kindled Agni, men of mortal mould. Agni I invocate for winning ample wealth. kindly disposed for winning wealth.\n\np: Atri and Bharadvaja and Gavisthira, Kanva and Trasadasyu, in our fight he helped. On Agni calls Vasistha, even the household priest, the household priest to win his grace.","people":["Agni","KanVa","Vasistha","Atri","Deva"],"places":[],"things":["Lord","Offering","Wealth","Men","Song","Joy","Hymn","Winning"],"groups":["Devas","Rudras","Jatavedas","Rsis","Vasus","Adityas"],"concepts":["Blessings","Love","Offering"],"hash":"md5-X6MnknbG+ud6uggnMPkZPw==","created":"Monday, April 8, 2024 - 10:51:56 PM"},{"id":"2279d8c9-83f7-4257-b6d6-6776b5e9a863","key":"10151","book":"10","title":"HYMN CLI. Faith.","link":"https://indra.ai/rigveda/hymns/10151.html","text":"p: By Faith is Agni kindled, through Faith is oblation offered up. We celebrate with praises Faith upon the height of happiness.\n\np: Bless thou the man who gives, O Faith; Faith, bless the man who fain would give. Bless thou the liberal worshippers: bless thou the word that I have said.\n\np: Even as the Deities maintained Faith in the mighty Asuras, So make this uttered wish of mine true for the liberal worshippers.\n\np: Guarded by Vayu, Devas and men who offering draw near to Faith. Man winneth Faith by yearnings of the heart, and opulence by Faith.\n\np: Faith in the early morning, Faith at noonday will we invocate, Faith at the setting of the Sun. O Faith, endow us with belief.","people":["Agni","Vayu"],"places":[],"things":["Offering","Sun","Men","Mighty","Faith","Morning"],"groups":["Devas","Asuras","Deities","Worshippers","Man"],"concepts":["Offering"],"hash":"md5-2lzJWcKXKAmoEzpS9igH4w==","created":"Monday, April 8, 2024 - 10:51:56 PM"},{"id":"7be64b58-6ed8-4775-962f-8cf7e7d4ae3d","key":"10152","book":"10","title":"HYMN CLII. Indra.","link":"https://indra.ai/rigveda/hymns/10152.html","text":"p: A MIGHTY Governor art thou, Wondrous, Destroyer of the foe, whose friend is never done to death, and never, never overcome.\n\np: Lord of the clan, who brings us bliss, Strong, Warrior, Slayer of the fiend, may India, Soma-drinker, go before us, Bull who gives us peace.\n\np: Drive Raksasas and foes away, break thou in pieces Vrtra'sjaws: O Vrtra-subduing Indra, quell the foeman's wrath who threatens us.\n\np: O Indra, beat our foes away, humble the men who challenge us: Send down to nether darkness him who seeks to do us injury.\n\np: Baffle the foeman's plan, ward off his weapon who would conquer us. Give shelter from his furious wrath, and keep his murdering dart afar.","people":["Indra","Soma","Vrtra","Raksasas"],"places":[],"things":["Lord","Soma","Men","Humble","Strong","Mighty","Bliss","Warrior","Friend","Death"],"groups":[],"concepts":["Death"],"hash":"md5-xy6c9kUb67q126wuvD2TFQ==","created":"Monday, April 8, 2024 - 10:51:56 PM"},{"id":"278c2925-b4a5-4d10-b1e4-5afb4af263a1","key":"10153","book":"10","title":"HYMN CLIII. Indra.","link":"https://indra.ai/rigveda/hymns/10153.html","text":"p: SWAYING about, the Active Ones came nigh to Indra at his birth, and shared his great heroic might.\n\np: Based upon strength and victory and power, O Indra is thy birth: Thou, Mighty One, art strong indeed.\n\np: Thou art the Vrtra conquerer Indra, hast spread the firmament: Thou hast with might upheld the heavens.\n\np: Thou, indra, bearest in thine arms the lightning that accords with thee, Whetting thy thunderbolt with might.\n\np: Thou, indra, art preeminent over all creatures in thy might: Thou hast pervaded every place.","people":["Indra","Vrtra"],"places":["Firmament"],"things":["Victory","Might","Strong","Mighty"],"groups":[],"concepts":["Birth","Heroic","Strength"],"hash":"md5-HMOB+OWhbXMMkIMURtCxXQ==","created":"Monday, April 8, 2024 - 10:51:56 PM"},{"id":"917ffe78-0a0d-4a4e-840b-f4bbe78e618f","key":"10154","book":"10","title":"HYMN CLIV. New Life.","link":"https://indra.ai/rigveda/hymns/10154.html","text":"p: FOR some is Soma purified, some sit by offerings oil: To those for whom the meath flows forth, even to those let him depart.\n\np: Invincible through Fervour, those whom Fervour hath advanced to heaven, who showed great Fervour in their lives, -even to those let him depart.\n\np: The heroes who contend in war and boldly cast their lives away, or who give guerdon thousandfold, -even to those let him depart.\n\np: Yea, the first followers of Law, Law's pure and holy strengtheners, the Fathers, Yama! Fervour-moved,even to those let him depart.\n\np: Skilled in a thousand ways and means, the sages who protect the Sun, the Rsis, Yama! Fervour-moved.even to those let him depart.","people":["Soma","Yama"],"places":["Heaven"],"things":["Meath","Soma","Sun","Heroes","Offerings"],"groups":["Fathers","Rsis"],"concepts":["Holy","Offerings"],"hash":"md5-7X8UMJL6EOQr7AU8S9NoAw==","created":"Monday, April 8, 2024 - 10:51:56 PM"},{"id":"ae745b6e-f845-43a0-b286-cafce838d3f3","key":"10155","book":"10","title":"HYMN CLV. Various.","link":"https://indra.ai/rigveda/hymns/10155.html","text":"p: ARAYI, one-eyed limping hag, fly, ever-screeching, to the hill. We frighten thee away with these, the heroes of Sirimbitha.\n\np: Scared from this place and that is she, destroyer of each germ unborn. Go, sharp-horned Brahmanaspti and drive Arayi far away.\n\np: Yon log that floats without a man to guide it on the river's edge. Seize it, thou thing with hideous jaws, and go thou far away thereon.\n\np: When, foul with secret stain and spot, ye hastened onward to the breast, All Indra's enemies were slain and passed away like froth and foam.\n\np: These men have led about the cow, have duly carried Agni round, and raised their glory tg the Devas. Who will attack them with success?","people":["Indra","Agni"],"places":[],"things":["Glory","Men","River","Heroes","Cow"],"groups":["Devas","Man"],"concepts":[],"hash":"md5-qhLJa6n+RisIqNMDZmV1Sg==","created":"Monday, April 8, 2024 - 10:51:56 PM"},{"id":"d42b83e2-d298-43a1-914a-4fcb1a9d8332","key":"10156","book":"10","title":"HYMN CLVI. Agni.","link":"https://indra.ai/rigveda/hymns/10156.html","text":"p: LET songs of ours speed Agni forth like a fleet courser in the race, and we will win each prize through him.\n\np: Agni the dart whereby we gain kine for ourselves with help from thee. That send us for the gain of wealth.\n\np: O Agni, bring us wealth secure, vast wealth in horses and in kine: Oil thou the socket, turn the wheel.\n\np: O Agni, thou hast made the Sun, Eternal Star, to mount the sky, bestowing light on living men.\n\np: Thou, Agni, art the people's light, best, dearest, seated in thy shrine: Watch for the singer, give him life.","people":["Agni"],"places":["Sky"],"things":["Singer","Light","Sun","Wealth","Men","Help","People","Songs","Horses","Life","Wheel"],"groups":[],"concepts":["Life"],"hash":"md5-5kbYIIcmgnRkz6suTwNcrQ==","created":"Monday, April 8, 2024 - 10:51:56 PM"},{"id":"d55fd16c-65c2-466f-ad91-107528c0826c","key":"10157","book":"10","title":"HYMN CLVII, Devas.","link":"https://indra.ai/rigveda/hymns/10157.html","text":"p: WE will, with Indra and all Devas to aid us, bring these existing worlds into subjection.\n\np: Our offering, our bodies, and our offspr. let Indra form together with Adityas.\n\np: With the Adityas, with the band of Maruts. May Indra be Protector of our bodies.\n\np: As when the Devas came, after they had slaughtered the Asuras, keeping safe their Deva like nature,\n\np: Brought the Sun hitherward with mighty powers, and looked about them on their vigorous Deva.ead.","people":["Indra","Deva"],"places":[],"things":["Offering","Sun","Mighty","Form","Powers"],"groups":["Devas","Asuras","Maruts","Adityas"],"concepts":["Offering"],"hash":"md5-xsO+dZUt0FeJUKBR9bcxOw==","created":"Monday, April 8, 2024 - 10:51:56 PM"},{"id":"21d85407-05ea-4696-b7aa-2324b81faed1","key":"10158","book":"10","title":"HYMN CLVIII. Surya.","link":"https://indra.ai/rigveda/hymns/10158.html","text":"p: MAY Surya guard us out of heaven, and Vata from the firmament, and Agni from terrestrial spots.\n\np: Thou Savitar whose flame deserves hundred libations, be thou pleased: From failing lightning keep us safe.\n\np: May Savitar the Deva, an. May Parvata also give us sight; May the Creator give us sight.\n\np: Give sight unto our eye, give thou our bodies sight that the, may see: May we survey, discern this world.\n\np: Thus, Surya. May we look on thee, on thee most lovely to behold, See clearly with the eyes of men.","people":["Agni","Savitar","Deva","Surya","Vata"],"places":["Heaven","Firmament"],"things":["Creator","Men","Libations"],"groups":[],"concepts":["Libations","Pleased","Creator"],"hash":"md5-KGLiKsvQdHvOrJ2lNPsmwA==","created":"Monday, April 8, 2024 - 10:51:56 PM"},{"id":"9999ead4-ba55-4c19-8697-4c3004c4095c","key":"10159","book":"10","title":"HYMN CLIX. Saci Paulomi.","link":"https://indra.ai/rigveda/hymns/10159.html","text":"p: YON Sun hath mounted up, and this my happy fate hate mounted high. I knowing this, as conqueror have won my husband for mine own.\n\np: I am the banner and the head, a mighty arbitress am I: I am victorious, and my Lord shall be submissive to my will.\n\np: My Sons are slayers of the foe, my Daughter is a ruling Queen: I am victorious: o’er my Lord my song of triumph is supreme.\n\np: Oblation, that which Indra gave and thus grew glorious and most high. This have I offered, O ye Devas, and rid me of each rival wife.\n\np: Destroyer of the rival wife, Sole Spouse, victorious, conqueror, the others' glory have I seized as ’twere the wealth of weaker Dames.\n\np: I have subdued as conqueror these rivals, these my fellow-wives, that . May hold imperial sway over this Hero and the folk.","people":["Indra"],"places":[],"things":["Lord","Triumph","Glory","Glorious","Sun","Wealth","Song","Mighty","Hero","Spouse"],"groups":["Devas","Sons","Dames","Wife","Husband"],"concepts":["Glorious"],"hash":"md5-iuV8pakzpZmHJTgL1vT8dQ==","created":"Monday, April 8, 2024 - 10:51:56 PM"},{"id":"2a05b6a6-aa91-4210-8e23-b9c798ccda58","key":"10160","book":"10","title":"HYMN CLX. Indra.","link":"https://indra.ai/rigveda/hymns/10160.html","text":"p: TASTE this strong draught enriched with offered offerings: with all thy chariot here unyoke thy Coursers. Let not those other offerers stay thee, indra: these offerings shed for thee are ready.\n\np: Thine is the juice effused, thine are the juices yet to be pressed: our resonant songs invite thee. O Indra, pleased to-day with this libation, come, thou who knowest all and drink the Soma.\n\np: Whoso, devoted to the Deva, effuses Soma for him with yearning heart and spirit. Never doth Indra give away his cattle: for him he makes the lovely Soma famous.\n\np: He looks with Ioving favour on the mortal who, like a rich man, pours for him the Soma. Maghavan in his bended arm supports him: he subdues, unasked, the men who hate devotion.\n\np: We call on thee to come to us, desirous of goods and spoil, of cattle, and of horses. For thy new love and favour are we present: let us invoke thee, indra, as our welfare.","people":["Indra","Soma","Maghavan","Deva"],"places":[],"things":["Soma","Men","Juice","Strong","Offerings","Songs","Horses","call","spoil","Cattle","Spirit"],"groups":["Man"],"concepts":["Love","Offerings","Pleased"],"hash":"md5-bmQapyaA5pKMZQa70qqWaA==","created":"Monday, April 8, 2024 - 10:51:56 PM"},{"id":"e6e1fc0c-db0c-4b38-b362-5dc76caa894d","key":"10161","book":"10","title":"HYMN CLXI. Indra.","link":"https://indra.ai/rigveda/hymns/10161.html","text":"p: FOR life I set thee free by this oblation from the unknown decline and from Consumption; Or, if the grasping demon have possessed him, free him from her, O Indra, thou and Agni.\n\np: Be his days ended, be he now departed, be he brought very near to death already, Out of Destruction's lap again I bring him, save him for life to last a hundred autumns.\n\np: With hundred-eyed oblation, hundred-autumned, bringing a hundred lives, have I restored him, that Indra for a hundred year. May lead him safe to the farther shore of all misfortune.\n\np: Live, waxing in thy strength, a hundred autumns, live through a hundred springs, a hundred winters. Through hundred-lived oblation Indra, Agni, Narasamsa, Savitar yield him for a hundred!\n\np: So have I found and rescued thee thou hast returned with youth renewed. Whole in thy members! I have found thy sight and all thy life for thee.","people":["Indra","Agni","Narasamsa","Savitar"],"places":[],"things":["Life","Death"],"groups":[],"concepts":["Death","Life","Strength"],"hash":"md5-KFtMAKBL46WZR9XveKPVZQ==","created":"Monday, April 8, 2024 - 10:51:56 PM"},{"id":"f6cb3526-4fcd-4d31-873c-e9afd2ed098f","key":"10162","book":"10","title":"HYMN CLXII. Agni","link":"https://indra.ai/rigveda/hymns/10162.html","text":"p: MAY Agni, yielding to our meditation, the Raksas-slayer, drive away The malady of evil name that hath beset thy labouring womb.\n\np: Agni, concurring in the prayer, drive off the eater of the flesh, the malady of evil name that hath attacked thy babe and womb.\n\np: That which destroys the sinking germ, the settled, moving embryo, that which will kill the babe at birth.even this will we drive far away.\n\np: That which divides thy legs that he may lie between the married pair, that penetrates and licks thy side.even this will we exterminate.\n\np: What rests by thee in borrowed form of brother, lover, or of lord, and would destroy thy Progeny.even this will we exterminate.\n\np: That which through sleep or darkness hath deceived thee and lies down by thee, and will destroy thy progeny.even this will we exterminate.","people":["Agni"],"places":[],"things":["Lord","Meditation","Form"],"groups":["Brother","Progeny"],"concepts":["Evil","Birth"],"hash":"md5-vkEZmU8I8QalP9EJD6dm5g==","created":"Monday, April 8, 2024 - 10:51:56 PM"},{"id":"367f5aaa-c7c9-476a-88db-5c0922097930","key":"10163","book":"10","title":"HYMN CLXIII","link":"https://indra.ai/rigveda/hymns/10163.html","text":"p: FROM both thy nostrils, from thine eyes, from both thine ears and from thy chin, forth from thy head and brain and tongue I drive thy malady away.\n\np: From the neck-tendons and the neck, from the breast-bones and from the spine, From shoulders, upper, lower arms, I drive thy malady away.\n\np: From viscera and all within, forth from the rectum, from the heart, From kidneys, liver, and from spleen, I drive thy malady away.\n\np: From thighs, from knee-caps, and from heels, and from the forepart of the feet, From hips from stomach, and from groin I drive thy malady away.\n\np: From what is voided from within, and from thy hair, and from they nails, From all thyself from top to toe, I drive thy malady away.\n\np: From every member, every hair, disease that comes in every joint, From all thyself, from top to toe, I drive thy malady away.","people":[],"places":[],"things":[],"groups":[],"concepts":[],"hash":"md5-KDszJABUGFeE3T2EV62iTg==","created":"Monday, April 8, 2024 - 10:51:56 PM"},{"id":"75f22e94-c758-483f-b93d-f793b4788f04","key":"10164","book":"10","title":"HYMN CLXIV. Dream-charm.","link":"https://indra.ai/rigveda/hymns/10164.html","text":"p: AVAUNT, thou Master of the mind Depart, and vanish far away. Look on Destruction far from hence. The live man's mind is manifold.\n\np: A happy boon do men elect, a mighty blessing they obtain. Bliss with Vaivasvata they see. The live man's mind seeks many a place.\n\np: If by address, by blame, by imprecation we have committed sin, awake or sleeping, All hateful acts of ours, all evil doing. May Agni bear away to distant places.\n\np: When, indra, Narasamsa, our deeds are wrongful and unjust, may provident Angirasa prevent our foes from troubling, us.\n\np: We have prevailed this day and won: we are made free from sin and guilt. Ill thoughts, that visit us awake or sleeping, seize the man we hate, yea, seize the man who hateth us.","people":["Indra","Agni","Narasamsa"],"places":[],"things":["Master","Boon","Men","Mighty","Blessing","Bliss"],"groups":["Man"],"concepts":["Evil"],"hash":"md5-y9qbCgoEFD6vaWOkTAY7hg==","created":"Monday, April 8, 2024 - 10:51:56 PM"},{"id":"9f4f89ac-8241-4c39-8682-9b4c4c939ee7","key":"10165","book":"10","title":"HYMN CLXV, Devas.","link":"https://indra.ai/rigveda/hymns/10165.html","text":"p: GODS, whatsoe’er the Dove came hither seeking, sent to us as the envoy of Destruction, for that let us sing hymns and make atonement. Well be it with our quadrupeds and bipeds.\n\np: Auspicious be the Dove that hath been sent us, a harmless bird, ye Devas, within our dwelling. May Agni, Sage, be pleased with our oblation, an. May the Missile borne on wings avoid us.\n\np: Let not the Arrow that hath wings distract us: beside the fire-place, on the hearth it settles. May, it bring welfare to our men and cattle: here let the Dove, ye Devas, forbear to harm us.\n\np: The screeching of the owl is ineffective and when beside the fire the Dove hath settled, to him who sent it hither as an envoy, to him be reverence paid, to Death, to Yama.\n\np: Drive forth the Dove, chase it with holy verses: rejoicing, bring ye hither food and cattle, Barring the way against all grief and trouble. Let the swift bird fly forth and leave us vigour.","people":["Agni","Yama"],"places":[],"things":["Reverence","Food","Men","Wings","Bird","Sage","Cattle","Death"],"groups":["Devas"],"concepts":["Death","Holy","Auspicious","Swift","Pleased"],"hash":"md5-7uitLhj/REbgjVOVBhnP/Q==","created":"Monday, April 8, 2024 - 10:51:56 PM"},{"id":"2794d781-46cf-4e64-8f3d-2faeedf6b16f","key":"10166","book":"10","title":"HYMN CLXVI. Sapatnanasanam.","link":"https://indra.ai/rigveda/hymns/10166.html","text":"p: MAKE me a bull among my peers, make me my rivals, conqueror: Make me the slayer of my foes, a sovran ruler, lord of kine\n\np: I am my rivals’ slayer, like Indra unwounded and unhurt, and all these enemies of mine are vanquished and beneath my feet.\n\np: Here, verily, I bind you fast, as the two bow-ends with the string. Press down these men, O Lord of Speech, that the, may humbly speak to me.\n\np: Hither I came as conqueror with mighty all-effecting power, and I have mastered all your thought, your synod, and your holy work.\n\np: May I be highest, having gained your strength in war, your skill in peace my feet have trodden on your heads. Speak to me from beneath my feet, as frogs from out the water croak, as frogs from out the water croak.","people":["Indra"],"places":[],"things":["Work","Lord","Water","Men","Mighty","Sovran Ruler"],"groups":[],"concepts":["Holy","Strength","Speech"],"hash":"md5-R4yAbmsC8wqS8JXZDIQ0ZQ==","created":"Monday, April 8, 2024 - 10:51:56 PM"},{"id":"5e68f39c-c792-45fe-a180-412f1ff91533","key":"10167","book":"10","title":"HYMN CLXVII. Indra.","link":"https://indra.ai/rigveda/hymns/10167.html","text":"p: THIS pleasant meath, O Indra, is effused for thee: thou art the ruling Lord of beaker and of juice. Bestow upon us wealth with many hero sons: thou, having glowed with Fervour, wonnest heavenly light.\n\np: Let us call Sakra to libations here effused, winner of light who joyeth in the potent juice. Mark well this offering of ours and come to us: we pray to Maghavan the Vanquisher of hosts.\n\np: By royal Soma's and by Varuna's decree, under Narasamsa's and Anumati's guard, This day by thine authority maker, Disposer thou! have I enjoyed the jars.\n\np: 1, too, urged on, have had my portion, in the bowl, and as first Prince I drew forth this my hymn of praise, when with the prize I came unto the flowing juice, O Visvamitra, Jamadagni, to your home.","people":["Indra","Soma","Varuna","Sakra","Maghavan","Narasamsa"],"places":[],"things":["Meath","Lord","Soma","Offering","Light","Wealth","Juice","Home","Praise","Hymn","Libations","Hero","call"],"groups":["Sons"],"concepts":["Heavenly","Offering","Libations","Winner"],"hash":"md5-0ajG8jFHnnACBqpGIYmyEw==","created":"Monday, April 8, 2024 - 10:51:56 PM"},{"id":"8bf5a393-c2e9-458c-9e8d-485a7202394b","key":"10168","book":"10","title":"HYMN CLXVIII. Vayu.","link":"https://indra.ai/rigveda/hymns/10168.html","text":"p: O THE Wind's chariot, O its power and glory! Crashing it goes and hath a voice of thunder. It makes the regions red and touches heaven, and as it moves the dust of earth is scattered.\n\np: Along the traces of the Wind they hurry, they come to him as dames to an assembly. Borne on his car with these for his attendants, the Deva.speeds forth, the universe's Monarch.\n\np: Travelling on the paths of air's mid-region, no single day doth he take rest or slumber. Holy and earliest-born, Friend of the waters, where did he spring and from what region came he?\n\np: Germ of the world, the Deities’ vital spirit, this Deva moves ever as his will inclines him. His voice is heard, his shape is ever viewless. Let us adore this Wind with our oblation.","people":["Deva","Attendants"],"places":["Earth","Heaven"],"things":["Born","Waters","Glory","Air","Car","Voice","Friend","Spirit"],"groups":["Deities","Dames"],"concepts":["Holy"],"hash":"md5-t1L9kEe+zB+irXJv80ssuQ==","created":"Monday, April 8, 2024 - 10:51:56 PM"},{"id":"94f0e316-58e8-4b81-be4a-eccb7f238a51","key":"10169","book":"10","title":"HYMN CLXIX. COWS.","link":"https://indra.ai/rigveda/hymns/10169.html","text":"p: MAY the wind blow upon our Cows with healing. May they eat herbage full of vigorous juices. May they drink waters rich in life and fatness: to food that moves on feet be gracious, Rudra.\n\np: Like-coloured, various-hued, or single-coloured, whose names through offering are known to Agni, whom the Angirases produced by Fervour.vouchsafe to these, parjanya, great protection.\n\np: Those who have offered to the Devas their bodies, whose varied forms are all well known to Soma. Those grant us in our cattle-pen, O Indra, with their full streams of milk and plenteous offspring.\n\np: Prajapati, bestowing these upon me, one-minded with all Devas and with the Fathers, Hath to our cow-pen brought auspicious cattle: s. May we own the offspring they will bear us.","people":["Indra","Soma","Agni","Parjanya","Prajapati"],"places":[],"things":["Milk","Soma","Waters","Offering","Food","Streams","Offspring","Cow","Cattle","Life"],"groups":["Devas","Fathers","Angirases"],"concepts":["Life","Offering","Auspicious"],"hash":"md5-kYeSslEk2n4sjEX5xdpZPg==","created":"Monday, April 8, 2024 - 10:51:56 PM"},{"id":"754cabc8-4a18-4159-acf5-3dde036bfab8","key":"10170","book":"10","title":"HYMN CLXX. Surya.","link":"https://indra.ai/rigveda/hymns/10170.html","text":"p: MAY the Bright Deva.drink glorious Soma-mingled meath, giving  'the offering's lord uninjured life; He who, wind-urged, in person guards our offspring well, hath nourished them with food and shines o’er many a land.\n\np: Radiant, as high Truth, cherished, best at winning strength, Truth based upon the statute that supports the heavens. He rose, a light, that kills Vrtras and enemies, best slayer of the Dasyus, Asuras, and foes.\n\np: This light, the best of lights, supreme, all-conquering, winner of riches, is exalted with high laud. All-lighting, radiant, mighty as the Sun to see, he spreadeth wide unfailing victory and strength.\n\np: Beaming forth splendour with thy light, thou hast attained heaven's lustrous realm. By thee were brought together all existing things, possessor of all Deva.ead, All-effecting Deva.","people":["Soma","Deva"],"places":["Heaven"],"things":["Meath","Victory","Lord","Soma","Glorious","Offering","Light","Sun","Food","Offspring","Mighty","Splendour","Winning","Riches","Life"],"groups":["Asuras","Dasyus","Vrtras"],"concepts":["Life","Strength","Offering","Truth","Glorious","Winner"],"hash":"md5-H2LGaA2tKkXHnxBzQRbVxg==","created":"Monday, April 8, 2024 - 10:51:56 PM"},{"id":"9855856e-8055-4380-b64a-91c244c1bb23","key":"10171","book":"10","title":"HYMN CLXXI. Indra.","link":"https://indra.ai/rigveda/hymns/10171.html","text":"p: FOR Ita's sake who pressed the juice Indra, didst protect his car, and hear the Soma-giver's call.\n\np: Thou from his skin hast borne the head of the swift-moving combatant, and sought the Soma-pourer's home.\n\np: Venya, that mortal man, hast thou, for Astrabudhna the devout, O Indra, many a time set free.\n\np: Bring, indra, to the east again that Sun who now is in the west, Even against the will of Devas.","people":["Indra","Soma"],"places":[],"things":["Soma","Sun","Juice","Home","Car","call"],"groups":["Devas","Man"],"concepts":["Devout","Giver","Swift"],"hash":"md5-0w3UmSX6EnsSFkCAjZWtCw==","created":"Monday, April 8, 2024 - 10:51:56 PM"},{"id":"126c7291-8e1b-4767-8902-37fa43e8fdba","key":"10172","book":"10","title":"HYMN CLXXII. Dawn.","link":"https://indra.ai/rigveda/hymns/10172.html","text":"p: WITH all thy beauty come: the kine approaching with full udders follow on thy path.\n\np: Come with kind thoughts, most liberal, rousing the warrior's hymn of praise, with bounteous ones,\n\np: As nourishers we tie the thread, and, liberal with our bounty, offer offering.\n\np: Dawn drives away her Sister's gloom, and, through her excellence, makes her retrace her path.","people":["Dawn"],"places":[],"things":["Offering","Beauty","Praise","Hymn","Warrior"],"groups":["Sister"],"concepts":["Offering"],"hash":"md5-b9jRIYzWhBSrLs4VMhsGWw==","created":"Monday, April 8, 2024 - 10:51:56 PM"},{"id":"1f231577-74dd-44ce-b3b4-a955e3496ce4","key":"10173","book":"10","title":"HYMN CLXXIII. The King.","link":"https://indra.ai/rigveda/hymns/10173.html","text":"p: BE with us; I have chosen thee: stand stedfast and immovable. Let all the people wish for thee let not thy kingship fall away.\n\np: Be even here; fall not away be like a mountain unremoved. Stand stedfast here like Indra's self, and hold the kingship in the grasp.\n\np: This man hath Indra stablished, made secure by strong oblation's power. May Soma speak a benison, and Narasamsa, on him.\n\np: Firm is the sky and firm the earth, and stedfast also are these hills. Stedfast is all this living world, and stedfast is this King of men.\n\np: Stedfast. May Varuna the King, stedfast, the Deva.Narasamsa, Stedfast. May Indra, stedfast too. May Agni keep thy stedfast reign.\n\np: On constant Soma let us think with constant offerings, and may Indra make the clans bring tribute unto thee alone.","people":["Indra","Soma","Agni","Varuna","Narasamsa","Deva"],"places":["Earth","Sky"],"things":["Soma","Men","Strong","People","Offerings","Tribute","King"],"groups":["Man"],"concepts":["Offerings"],"hash":"md5-jTRMblCWcQtUOb2Nw7GveQ==","created":"Monday, April 8, 2024 - 10:51:56 PM"},{"id":"6f10172b-39ce-4cb0-a1cb-8853cdbbea1d","key":"10174","book":"10","title":"HYMN CLXXIV. The King.","link":"https://indra.ai/rigveda/hymns/10174.html","text":"p: WITH offering for success in fight whence Indra was victorious. With this, O Narasamsa, let us attain to royal sway.\n\np: Subduing those who rival us, subduing all malignities, withstand the man who menaces, withstand the man who angers us.\n\np: Soma and Savitar the Deva.have made thee a victorious King All elements have aided thee, to make thee general conqueror.\n\np: Oblation, that which Indra. gave and thus grew glorious and most high. This have I offered, Devas! and hence now, verily, am rivalless.\n\np: Victorious, with royal sway, Over these being. May I rule. May I be Sovran of the folk.","people":["Indra","Soma","Narasamsa","Savitar","Deva"],"places":[],"things":["Soma","Glorious","Offering","Elements","King"],"groups":["Devas","Man"],"concepts":["Offering","Glorious"],"hash":"md5-TsyaEWn4ahocDb7D0ZHWpA==","created":"Monday, April 8, 2024 - 10:51:56 PM"},{"id":"50736c2f-baca-4fd1-81d6-5b5d8d0fed98","key":"10175","book":"10","title":"HYMN CLXXV. Press-stones.","link":"https://indra.ai/rigveda/hymns/10175.html","text":"p: MAY Savitar the Deva, O Stones, stir you according to the Law: Be harnessed to the shafts, and press.\n\np: Stones, drive calamity away, drive ye away malevolence: Make ye the Cows our medicine.\n\np: Of one accord the upper Stones, giving the Bull his bull-like strength, Look down with pride on those below.\n\np: May Savitar the Deva, O Stones, stir you as Law commands for him Who offers, pouring juice.","people":["Savitar","Deva"],"places":[],"things":["Juice","Offers"],"groups":[],"concepts":["Strength"],"hash":"md5-ffSLYJesqi0ecUjirGuq3A==","created":"Monday, April 8, 2024 - 10:51:57 PM"},{"id":"acbdaf9b-383f-404a-93f0-334d0538376e","key":"10176","book":"10","title":"HYMN CLXXVI. Agni.","link":"https://indra.ai/rigveda/hymns/10176.html","text":"p: WITH hymns of praise their sons have told aloud the Rbhus' mighty deeds. Who, all-supporting, have enjoyed the earth as, twere a mother cow.\n\np: Bring forth the Deva with song divine, being Jatavedas hitherward, to bear our gifts at once to heaven.\n\np: He here, a devoted Monk, led forward comes to offering. Like a car covered for the road, he, glowing, knows, himself, the way.\n\np: This Agni rescues from distress, as ’twere from the Immortal Race, a Deva.yet mightier than strength, a Deva who hath been made for life.","people":["Agni","Deva"],"places":["Earth","Heaven"],"things":["Offering","Song","Mighty","Car","Praise","Cow","Life","Gifts"],"groups":["Jatavedas","Sons","Mother","Immortal","Rbhus"],"concepts":["Life","Divine","Immortal","Strength","Offering"],"hash":"md5-3Nwdmb/UL1i//v0GybPbzw==","created":"Monday, April 8, 2024 - 10:51:57 PM"},{"id":"cfc0416f-03b1-4889-9577-f6e70dbe7444","key":"10177","book":"10","title":"HYMN CLXXVII. Mayabheda.","link":"https://indra.ai/rigveda/hymns/10177.html","text":"p: THE sapient with their spirit and their mind behold the Bird adorned with all an Asura's magic might. Sages observe him in the ocean's inmost depth: the wise disposers seek the station of his rays.\n\np: The flying Bird bears Speech within his spirit: erst the Gandharva in the womb pronounced it: And at the seat of offering the sages cherish this radiant, heavenly-bright invention.\n\np: I s w the Herdsman, him who never resteth, approaching and departing on his pathways. He, clothed in gathered and diffusive splendour, within the worlds continually travels.","people":[],"places":["Ocean"],"things":["Offering","Might","Wise","Splendour","Bird","Spirit"],"groups":["Asura","Gandharva"],"concepts":["Heavenly","Offering","Speech"],"hash":"md5-soKvaNaL8pIB4GitXqYU/Q==","created":"Monday, April 8, 2024 - 10:51:57 PM"},{"id":"2819e0f2-5e2d-47fc-9796-417c1729d056","key":"10178","book":"10","title":"HYMN CLXXVIII. Tarksya.","link":"https://indra.ai/rigveda/hymns/10178.html","text":"p: THIS very mighty one whom Devas commission, the Conqueror of cars, ever triumphant, Swift, fleet to battle, with uninjured fellies, even Tarksya for our weal will we call hither.\n\np: As though we offered up our gifts to Indra, may we ascend. him as a ship. for safety. Like the two wide worlds, broad, deep far-extended. May we be safe both when he comes and leaves you.\n\np: He who with might the Five Lands hath pervaded, like Surya with his lustre, and the waters— His strength wins hundreds, thousands none avert it, as the young maid repelleth not her lover.","people":["Indra","Surya","Tarksya"],"places":[],"things":["Waters","Might","Mighty","Ascend","call","Cars","Gifts"],"groups":["Devas","Maid"],"concepts":["Cars","Strength","Swift"],"hash":"md5-hRD71n0xj3ZWap+nQHmx7A==","created":"Monday, April 8, 2024 - 10:51:57 PM"},{"id":"f7e6ce5b-b64d-4c81-8a74-6f8643eece84","key":"10179","book":"10","title":"HYMN CLXXIX. Indra.","link":"https://indra.ai/rigveda/hymns/10179.html","text":"p: Now lift ye up yourselves and look on Indra's seasonable share. If it be ready, offer it; unready, ye have been remise.\n\np: Oblation is prepared: come to us, indra; the Sun hath travelled over half his journey. Friends with their stores are sitting round thee waiting like lords of clans for the tribe's wandering chieftain.\n\np: Dressed in the udder and on fire, I fancy; well-dressed, I fancy, is this recent present. Drink, indra, of the curd of noon's libation with favour, Thunderer, thou whose deeds are mighty.","people":["Indra"],"places":[],"things":["Journey","Sun","Mighty","Friends"],"groups":[],"concepts":[],"hash":"md5-cC+2gBwBMH2KfrRMn9eXog==","created":"Monday, April 8, 2024 - 10:51:57 PM"},{"id":"e09a8128-59e4-4618-a104-6db9a63d59f7","key":"10180","book":"10","title":"HYMN CLXXX. Indra.","link":"https://indra.ai/rigveda/hymns/10180.html","text":"p: O MUCH-INVOKED, thou hast subdued thy foemen: thy might is loftiest; here display thy bounty. In thy right hand, O Indra, bring us treasure.s: thou art the Lord of rivers filled with riches.\n\np: Like a dread wild beast roaming on the mountain thou hast approached us from the farthest distance. Whetting thy bold and thy sharp blade, O Indra, crush thou the foe and scatter those who hate us.\n\np: Thou, mighty Indra, sprangest into being as strength for lovely lordship o’er the people. Thou drovest off the folk who were unfriendly, and to the Devas thou gavest room and freedom.","people":["Indra"],"places":[],"things":["Lord","Rivers","Treasure","Might","Mighty","People","Riches"],"groups":["Devas"],"concepts":["Strength"],"hash":"md5-U2drsh2ONAp1eglDsTC5iA==","created":"Monday, April 8, 2024 - 10:51:57 PM"},{"id":"af88781e-0fe7-40e1-a277-c8d694b1f6f1","key":"10181","book":"10","title":"HYMN CLXXXI, Devas.","link":"https://indra.ai/rigveda/hymns/10181.html","text":"p: VASIṢṬHA mastered the Rathantara, took it from radiant Dhatar, Savitar, and Visnu, Oblation, portion of fourfold oblation, known by the names of Saprathas and Prathas.\n\np:  These sages found what lay remote and hidden,  'the offering's loftiest secret essence. From radiant Dhatar, Savitar, and Visnu, from Agni, Bharadvaja brought the Brhat.\n\np: They found with mental eyes the earliest Yajus, a pathway to the Devas, that had descended. From radiant Dhatar, Savitar, and Visnu, from Surya did these sages bring the Gharma.","people":["Dhatar","Agni","Visnu","Savitar","Surya"],"places":[],"things":["Offering"],"groups":["Devas"],"concepts":["Offering"],"hash":"md5-0UVI04bsN9g+n6SYzXHHCg==","created":"Monday, April 8, 2024 - 10:51:57 PM"},{"id":"56ec7013-ef0e-4efe-96fb-5ccf33e5187d","key":"10182","book":"10","title":"HYMN CLXXXII. Narasamsa.","link":"https://indra.ai/rigveda/hymns/10182.html","text":"p: BRHASPATI lead us safely over troubles and turn his evil thought against the sinner; Repel the curse, and drive away ill-feeling, and give  'the offeringr peace and comfort!\n\np: May Narasamsa aid us at Prayaja: blest be our Anuyaja at invokings. May he repel the curse, and chase ill-feeling, and give  'the offeringr peace and comfort.\n\np: May he whose head is flaming burn the demons, haters of prayer, so that the arrow subdue them. May he repel the curse and chase ill-feeling, and give  'the offeringr peace and comfort.","people":["Narasamsa"],"places":[],"things":[],"groups":[],"concepts":["Evil"],"hash":"md5-pZwQO58qzAVGPlgWuB+DYw==","created":"Monday, April 8, 2024 - 10:51:57 PM"},{"id":"398ba405-59c3-4d4c-9a54-bc1ce8ba4ff2","key":"10183","book":"10","title":"HYMN CLXXXIII. The Offerer, Etc.","link":"https://indra.ai/rigveda/hymns/10183.html","text":"p: I SAW thee meditating in thy spirit what sprang from Fervour and hath thence developed. Bestowing offspring here, bestowing riches, spread in thine offspring, thou who cravest children.\n\np: I s w thee pondering in thine heart, and praying that in due time thy body might be fruitful. Come as a youthful woman, rise to meet me: spread in thine offspring, thou who cravest children.\n\np: In plants and herbs, in all existent beings I have deposited the germ of increase. All progeny on earth have I engendered, and sons in women who will be hereafter.","people":[],"places":["Earth"],"things":["Might","Offspring","Riches","Spirit"],"groups":["Sons","Progeny","Woman"],"concepts":[],"hash":"md5-fV8VG5GXLbXgRnl6l5aKpA==","created":"Monday, April 8, 2024 - 10:51:57 PM"},{"id":"580b1976-8b46-4263-a372-fb9ca00c3aeb","key":"10184","book":"10","title":"HYMN CLXXXIV.","link":"https://indra.ai/rigveda/hymns/10184.html","text":"p: MAY Visnu form and mould the womb. May Tvastar duly shape the forms, prajapati infuse the stream, and Dhatar lay the germ for thee.\n\np: O Sinivali, set the germ, set thou the germ, Sarasvati: May the Twain Devas bestow the germ, the Asvins crowned with lotuses.\n\np: That which the Asvins Twain rub forth with the attrition-sticks of gold. That germ of thine we invocate, that in the tenth month tho. Mayst bear.","people":["Dhatar","Visnu","Asvins","Tvastar","Sarasvati","Prajapati"],"places":[],"things":["Stream","Gold","Form"],"groups":["Devas"],"concepts":[],"hash":"md5-8iSlELhIvdNPbvGnAOKEDQ==","created":"Monday, April 8, 2024 - 10:51:57 PM"},{"id":"17d93796-336a-4c86-a46f-f4a2e3894864","key":"10185","book":"10","title":"HYMN CLXXXV. Aditi.","link":"https://indra.ai/rigveda/hymns/10185.html","text":"p: GREAT, unassailable must he the heavenly favour of Three Devas, Varuna, Mitra, Aryaman.\n\np: O'er these, neither at home nor yet abroad or pathways that are Strange, the evil-minded foe hath power\n\np: Nor over him. the man on whom the Sons of Aditi bestow Eternal light that h. May live.","people":["Mitra","Varuna","Aditi","Aryaman"],"places":[],"things":["Light","Home"],"groups":["Devas","Sons","Man"],"concepts":["Evil","Heavenly"],"hash":"md5-kn6rUPK7sXc2iMqaCa8jTw==","created":"Monday, April 8, 2024 - 10:51:57 PM"},{"id":"896951ec-e520-4f6d-b88f-9bec6b92069c","key":"10186","book":"10","title":"HYMN CLXXXVI. Vayu.","link":"https://indra.ai/rigveda/hymns/10186.html","text":"p: FILLING our hearts with health and joy. May Vata breathe his balm on us May he prolong our days of life.\n\np: Thou art our Father, Vata, yea, thou art a Brother and a friend, So give us strength that we may live.\n\np: The store of Amrta laid away yonder, O Vata, in thine home. Give us thereof that we may live.","people":["Vata"],"places":[],"things":["Joy","Home","Friend","Life","Amrta"],"groups":["Father","Brother"],"concepts":["Life","Strength"],"hash":"md5-1aihJLjjKelVQe0XZvSiFw==","created":"Monday, April 8, 2024 - 10:51:57 PM"},{"id":"c7158baa-3f5d-439f-ba6e-a03a95b6c3ab","key":"10187","book":"10","title":"HYMN CLXXXVII. Agni.","link":"https://indra.ai/rigveda/hymns/10187.html","text":"p: To Agni send I forth my song, to him the Bull of all the folk: May he bear us past our foes.\n\np: Who from the distance far away shines brilliantly across the wastes: May he bear us past our foes.\n\np: The Bull with brightly-gleaming flame who utterly consumes the fiends May he bear us past our foes.\n\np: Who looks on all existing things and comprehends them with his viewe may he bear us past our foes.\n\np: Resplendent Agni, who was born in farthest region of the air: May he bear us past our foes.","people":["Agni"],"places":[],"things":["Born","Air","Song"],"groups":[],"concepts":[],"hash":"md5-gCg8gqesPy/3XW4DKyjheg==","created":"Monday, April 8, 2024 - 10:51:57 PM"},{"id":"35fa00a7-974c-4ed8-a255-55696e914f91","key":"10188","book":"10","title":"HYMN CLXXXVIII. Agni.","link":"https://indra.ai/rigveda/hymns/10188.html","text":"p: Now send ye Jatavedas forth, send hitherward the vigorous Steed To seat him on our sacred grass.\n\np:  I raise the lofty eulogy of Jatavedas, raining boons, with sages for his hero band.\n\np: With flames of Jatavedas which carry oblation to the Devas, may he promote  'our offering.","people":[],"places":[],"things":["Offering","Grass","Hero"],"groups":["Devas","Jatavedas"],"concepts":["Sacred","Offering"],"hash":"md5-N2DnQ/Fm80ZE+LE/CxJT/g==","created":"Monday, April 8, 2024 - 10:51:57 PM"},{"id":"4674f510-0706-4aaf-80d9-bdba639ffb13","key":"10189","book":"10","title":"HYMN CLXXXIX. Surya.","link":"https://indra.ai/rigveda/hymns/10189.html","text":"p: THIS spotted Bull hath come, and sat before the Mother in the east, Advancing to his Father heaven.\n\np: Expiring when he draws his breath, she moves along the lucid spheres: The Bull shines out through all the sky.\n\np: Song is bestowed upon the Bird: it rules supreme through thirty realms Throughout the days at break of morn.","people":[],"places":["Heaven","Sky"],"things":["Song","Bird"],"groups":["Father","Mother"],"concepts":[],"hash":"md5-metk9SNkk6mmt9EeO7gJIw==","created":"Monday, April 8, 2024 - 10:51:57 PM"},{"id":"caacc447-515a-41d4-985b-9edbab12d82b","key":"10190","book":"10","title":"HYMN CXC. Creation.","link":"https://indra.ai/rigveda/hymns/10190.html","text":"p: FROM Fervour kindled to its height Eternal Law and Truth were born: Thence was the Night produced, and thence the billowy flood of sea arose.\n\np: From that same billowy flood of sea the Year was afterwards produced, ordainer of the days nights, Lord over all who close the eye.\n\np: Dhatar, the great Creator, then formed in due order Sun and Moon. He formed in order Heaven and Earth, the regions of the air, and light.","people":["Dhatar"],"places":["Earth","Heaven"],"things":["Lord","Born","Light","Air","Creator","Sun","Moon","Order"],"groups":[],"concepts":["Truth","Creator","Eternal Law"],"hash":"md5-h2dPkqFbUT3pOAxMcHMQqg==","created":"Monday, April 8, 2024 - 10:51:57 PM"},{"id":"b4cc7146-c0c8-44d6-b88c-dd55338050db","key":"10191","book":"10","title":"HYMN CXCI. Agni.","link":"https://indra.ai/rigveda/hymns/10191.html","text":"p: THOU, mighty Agni, gatherest up all that is precious for thy friend. Bring us all treasure.s as thou art enkindled in libation's place\n\np: Assemble, speak together: let your minds be all of one accord, as ancient Devas unanimous sit down to their appointed share.\n\np: The place is common, common the assembly, common the mind, so be their thought united. A common purpose do I lay before you, and worship with your general oblation.\n\np: One and the same be your resolve, and be your minds of one accord. United be the thoughts of all that al. May happily agree.","people":["Agni"],"places":[],"things":["Worship","Treasure","Mighty","Friend"],"groups":["Devas"],"concepts":[],"hash":"md5-8Lhn8qhYHafCMmatnm7l1Q==","created":"Monday, April 8, 2024 - 10:51:57 PM"}],"copyright":"©2023 Quinn Michaels (indra.ai). All rights reserved.","created":"Monday, April 8, 2024 - 10:51:52 PM"}