{"id":"df9f7807-ebcc-4902-95cb-66b5dbb141a9","key":"06","link":"https://indra.ai/rigveda/books/06.html","hymns":[{"id":"c71de47d-a2ee-4668-b41e-0432324c3e8b","key":"06001","book":"06","title":"HYMN I. Agni.","link":"https://indra.ai/rigveda/hymns/06001.html","text":"p: THOU, first inventor of this prayer, O Agni, Worker of Marvels, hast become our Herald. Thou, Bull, hast made us strength which non. May conquer, strength that shall overcome all other prowess.\n\np: As Monk thou sattest at the seat of worship, furthering us, best offerer, meet for honour. So first to thee have pious men resorted, turning thy mind to thoughts of ample riches.\n\np: In thee, still watching, they have followed riches, who goest with much wealth as with an army, the radiant Agni, lofty, fair to look on, worshipped with marrow, evermore resplendent.\n\np: They who approached the Deva's abode with homage, eager for glory, won them perfect glory: Yea, they gained even offerings titles, and found delight in thine auspicious aspect.\n\np: On earth the people magnify thee greatly, thee their celestial and terrestrial riches. Thou. Helper, must be known as our Preserver, Father and Mother of mankind forever.\n\np: Dear priest among mankind, adorable Agni hath seated him, joy-giver, skilled in worship. Let us approach thee shining in thy dwelling, kneeling upon our knees, with adoration.\n\np: Longing for bliss, pure-minded, devoted, Agni, we seek thee, such, meet to be lauded. Thou, Agni, leddest forth our men to battle, refulgent with the heaven's exalted splendour.\n\np: Sage of mankind, all peoples' Lord and Master, the Bull of men, the sender down of blessings, Still pressing on, promoting, purifying, Agni the Holy One, the Lord of riches.\n\np: Agni, the mortal who hath toiled and worshipped, brought thee oblations with his kindled fuel, and well knows offering with adoration, gains every joy with thee to guard and help him.\n\np: Mightily let us worship thee the Mighty, with reverence, Agni! fuel and oblations, with songs, O Son of Strength, with hymns, with altar: s. May we strive for thine auspicious favour.\n\np: Thou who hast covered heaven and earth with splendour and with thy glories, glorious and triumphant. Continue thou to shine on us, O Agni, with strength abundant, rich, and lon enduring.\n\np: Vouchsafe us ever, as man needs, O Vasu, abundant wealth of kine for son and offspring. Food noble, plenteous, far from sin and evil, he with us, and fair fame to make us happy.\n\np: May I obtain much wealth in many places by love of thee and through thy grace, King Agni; For in thee Bounteous One, in thee the Sovran, Agni, are many boons for him who serves thee.","people":["Agni","Deva","Vasu"],"places":["Earth","Heaven"],"things":["Worship","Mankind","Master","Lord","Reverence","Glory","Glorious","Offering","Shine","Wealth","Food","Men","Joy","Help","Offspring","Mighty","Delight","Adorable","Splendour","People","Offerings","Bliss","Songs","King","Sage","Riches"],"groups":["Father","Mother","Son","Man"],"concepts":["Celestial","Evil","Blessings","Love","Holy","Strength","Offering","Offerings","Worshipped","Giver","Auspicious","Glorious","Noble"],"hash":"md5-i0p2EC4Yf43y6oEKsx5gPg==","created":"Monday, April 8, 2024 - 10:51:52 PM"},{"id":"daffd3b9-f8aa-48f7-988b-2689106cfbe4","key":"06002","book":"06","title":"HYMN II. Agni.","link":"https://indra.ai/rigveda/hymns/06002.html","text":"p: THOU, Agni, even as Mitra, hast a princely glory of thine own. Thou, active Vasu, makest fame increase like full prosperity.\n\np: For, verily, men pray to thee with offers and with songs. To thee the Friendly Courser, seen of all, comes speeding through the air.\n\np: Of one accord men kindle thee Heaven's signal of  'the offering, when, craving bliss, this race of man invites thee to the solemn rite.\n\np: Let the man thrive who travails sore, in meditation, far thee the Bountiful. He with the help of lofty Dyaus comes safe through straits of enmity.\n\np: The mortal who with fuel lights thy flame and offers unto thee, Supports a house with many a branch, Agni, to live a hundred years.\n\np: Thy bright smoke lifts itself aloft, and far-extended shines in heaven. For, purifier! like the Sun thou beamest with thy radiant glow.\n\np: For in men's houses thou must be glorified as a well-loved guest, Gay like an elder in a fort, claiming protection like a son.\n\np: Thou, Agni, like an able steed, art urged by wisdom in the wood. Thou art like wind; food, home art thou, like a young horse that runs astray.\n\np: E’en things imperishable O Agni, like a gazing ox, Eatest, when hosts, Eternal One! of thee the Mighty rend the woods.\n\np: Agni, thou enterest as Monk the home of men who offering. Lord of the people, prosper them. Accept the ofrering, Angiras!\n\np: O Agni, Deva with Mitra's might, call hither the favour of the Devas from earth and heaven. Bring weal from heaven, that me. May dwell securely. May we o’ercome the foe's malign oppressions. May we o’ercome them, through thy help o’ercome them.","people":["Agni","Angiras","Mitra","Deva","Vasu"],"places":["Earth","Heaven"],"things":["Lord","Meditation","Glory","Offering","Air","Sun","Food","Men","Might","Help","Home","Mighty","Offers","People","Bliss","Songs","Horse","call"],"groups":["Devas","Dyaus","Son","Man"],"concepts":["Wisdom","Offering"],"hash":"md5-nlbIF6jH2iCSTmDiSG9/zg==","created":"Monday, April 8, 2024 - 10:51:52 PM"},{"id":"45ccdf84-00b3-4b45-8a51-fc106f63d9ec","key":"06003","book":"06","title":"HYMN III. Agni.","link":"https://indra.ai/rigveda/hymns/06003.html","text":"p: TRUE, guardian of the Law, thy faithful servant wins ample light and dwells in peace, O Agni, whom thou, as Varuna in accord with Mitra, guardest, O Deva, by banishing his trouble.\n\np: He hath paid offers, toiled in worship, and offered gifts to wealth-increasing Agni. Him the displeasure of the famous moves not, outrage and scorn affect not such a mortal.\n\np: Bright Deva, whose look is free from stain like Surya's swift, what time thou earnestly desirest, Hast gear to give us. Come with joy at evening, where, Child of Wood, tho. Mayest also tarry.\n\np: Fierce is his gait and vast his wondrous body: he champeth like a horse with bit and bridle, and, darting forth his tongue, as ’twere a hatchet, burning the woods, smelteth them like a smelter.\n\np: Archer-like, fain toshoot, he sets his arrow, and whets his splendour like the edge of iron. The messenger of night with brilliant pathway, like a tree-roosting bird of rapid pinion.\n\np: In beams of morn he clothes him like the singer, and bright as Mitra with his splendour crackles. Red in the night, by day the men's possession: red, he belongs to men by day, Immortal.\n\np: Like Heaven's when scattering beams his voice was uttered: among the plants the radiant Hero shouted, who with his glow in rapid course came hither to fill both worlds, well-wedded Dames, with treasure..\n\np: Who, with supporting streams and rays that suit him, hath flashed like lightning with his native vigour. Like the deft Maker of the band of Maruts, the bright impetuous One hath shone refulgent.","people":["Agni","Mitra","Varuna","Deva","Surya"],"places":["Heaven"],"things":["Worship","Singer","Light","Treasure","Wealth","Men","Streams","Joy","Voice","Splendour","Offers","Hero","Bird","Horse","Gifts"],"groups":["Maruts","Dames","Child","Immortal"],"concepts":["Immortal","Swift"],"hash":"md5-RDatnoFVGRgxSgiCKb32OQ==","created":"Monday, April 8, 2024 - 10:51:52 PM"},{"id":"f4b7cf93-f6c8-4dad-83d8-801330e4e804","key":"06004","book":"06","title":"HYMN IV Agni.","link":"https://indra.ai/rigveda/hymns/06004.html","text":"p: As at man's service of the Devas, invoker Son of Strength, dost offering and worship, So bring for us to-day all Devas together, bring willingly the willing Devas, O Agni.\n\np: May Agni, radiant Herald of the morning, meet to be known, accept our praise with favour. Dear to all life, mid mortal men Immortal, our guest, awake at dawn, is Jatavedas.\n\np: Whose might the very heavens regard with wonder: bright as the Sun he clothes himself with lustre. He who sends forth, Eternal Purifier, hath shattered e’en the ancient works of Asna.\n\np: Thou art a Singer, Son! our feast-companion: Agni at birth prepared his food and pathway. Therefore vouchsafe us strength, O Strength-bestower. Win like a King: foes trouble not thy dwelling.\n\np: Even he who cats his firm hard food with swiftness,and overtakes the nights as Vayu kingdoms. May we o’ercome those who resist thine orders, like a steed casting down the flying foemen.\n\np: Like Surya with his fulgent rays, O Agni, thou overspreadest both the worlds with splendour. Decked with bright colour he dispels the darkness, like Ausija, with clear flame swifily flying.\n\np: We have elected thee as most delightful for thy beams' glow: hear our great laud, O Agni. The best men praise thee as the peer of Indra in strength, mid Devas, like Viyu in thy bounty.\n\np: Now, Agni, on the tranquil paths of riches come to us for our weal: save us from sorrow. Grant chiefs and bard this boon. May we live happy, with hero children, through a hundred winters.","people":["Indra","Agni","Vayu","Surya","Dawn"],"places":[],"things":["Worship","Singer","Offering","Sun","Boon","Food","Men","Might","Praise","Splendour","Hero","King","Riches","Morning","Life"],"groups":["Devas","Jatavedas","Son","Immortal","Man"],"concepts":["Birth","Life","Immortal","Strength","Offering"],"hash":"md5-dCVeA58hOJ3sLqOzc+PBNQ==","created":"Monday, April 8, 2024 - 10:51:52 PM"},{"id":"55d6f84a-8612-4505-9562-07e0a0e6b64e","key":"06005","book":"06","title":"HYMN V. Agni.","link":"https://indra.ai/rigveda/hymns/06005.html","text":"p: I INVOCATE your Son of Strength, the Youthful, with hymns, the Youngest Deva, whose speech is guileless; Sage who sends wealth comprising every treasure., bringer of many boons, devoid of malice.\n\np: At eve and morn thy pious servants bring thee their precious gifts, O Monk of many aspects, On whom, the Purifier, all things living as on firm. ground their happiness have stablished.\n\np: Thou from of old hast dwelt among these people, by mental power the charioteer of blessings. Hence sendest thou, O sapient Jatavedas, to him who serves thee treasure.s in succession.\n\np: Agni, whoever secretly attacks us, the neighbour, thou with Mitra's might! who harms us, Burn him with thine own Steers forever youthful, burning with burning heat, thou fiercest burner.\n\np: He who serves thee with offering and fuel, with hymn, O Son of Strength, and chanted praises. Shines out, Immortal! in the midst of mortals, a sage, with wealth, with splendour and with glory.\n\np: Do this, O Agni, when we urge thee, quickly, triumphant in thy might subdue our foemen. When thou art praised with words and decked with brightness, accept this chanted hymn, the singer's worship.\n\np: Help us, that we may gain this wish, O Agni, gain riches, Wealthy One! with store of heroes. Desiring strength from the, may we be strengthened, and win, Eternal! thine eternal glory.","people":["Agni","Mitra","Deva"],"places":[],"things":["Worship","Glory","Singer","Offering","Treasure","Wealth","Might","Help","Hymn","Heroes","Splendour","People","Sage","Riches","Gifts"],"groups":["Jatavedas","Steers","Son","Immortal"],"concepts":["Blessings","Immortal","Strength","Offering","Speech"],"hash":"md5-CFd2WtKRjpF7Nq3OitmFSw==","created":"Monday, April 8, 2024 - 10:51:52 PM"},{"id":"0e107d9b-c30b-47d4-957d-e2f00f7827d4","key":"06006","book":"06","title":"HYMN VI. Agni.","link":"https://indra.ai/rigveda/hymns/06006.html","text":"p: HE who seeks furtherance and grace to help him goes to the Son of Strength with newest worship, Calling the heavenly Monk to share the banquet, who rends the wood, bright, with his blackened pathway.\n\np: White-hued and thundering he dwells in splendour, most Youthful, with the loudvoiced and eternal- Agni, most variform, the Purifier, who follows crunching many ample forests.\n\np: Incited by the wind thy flames, O Agni, move onward, pure One! pure, in all directions. Thy most destructive heavenly Navagvas break the woods down and devastate them boldly.\n\np: Thy pure white horses from their bonds are loosened: O Radiant One, they shear the ground beneath them, and far and wide shines out thy flame, and flickers rapidly moving over earth's high ridges.\n\np: Forth darts the Bull's tongue like the sharp stone weapon discharged by him who fights to win the cattle. Agni's fierce flame is like a hero's onset: dread and resistless he destroys the forests.\n\np: Thou with the sunlight of the great Impeller hast boldly over-spread the earth's expanses. So drive away with conquering might all perils. fighting out foemen burn up those who harm us.\n\np: Wondrous! of wondrous power! give to the singer wealth wondrous, marked, most wonderful, life-giving. Wealth bright, O Bright One, vast, with many heroes, give with thy bright flames to the man who lauds thee.","people":["Agni"],"places":["Earth"],"things":["Worship","Singer","Wealth","Might","Help","Banquet","Heroes","Splendour","Hero","Horses","Cattle","Life"],"groups":["Son","Navagvas","Man"],"concepts":["Life","Heavenly","Strength"],"hash":"md5-dxqO/qRpnj+wOsL+vdnu3g==","created":"Monday, April 8, 2024 - 10:51:52 PM"},{"id":"530f89d8-90d9-4a57-8c45-f487a6c4b7e9","key":"06007","book":"06","title":"HYMN VII. Agni.","link":"https://indra.ai/rigveda/hymns/06007.html","text":"p: Him, messenger of earth and head of heaven, Agni Vaisvanara, born in holy Order, the Sage, the King, the guest of men, a vessel fit for their mouths, the Devas have generated.\n\np: Him have they praised, mid-point of offers, great cistern of libations, seat of riches. Vaisvanara, conveyer of oblations, ensign of worship, have the Devas engendered.\n\np: From thee, O Agni, springs the mighty singer, from thee come heroes who subdue the foeman. O King, Vaisvanara, bestow thou on us excellent treasure.s worthy to belonged fo r.\n\np: To thee, Immortal! When to life thou springest, all the Devas sing for joy as to their infant. They by thy mental powers were made immortal, Vaisvanara, when thou shonest from thy Parents.\n\np: Agni Vaisvanara, no one hath ever resisted these thy mighty ordinances, when thou, arising from thy Parents' bosom, foundest the light for days' appointed courses.\n\np: The summits of the heaven are traversed through and through by the Immortal's light, Vaisvanara's brilliancy. All creatures in existence rest upon his head. The Seven swift-flowing Streams have grown like branches forth,\n\np: Vaisvanara, who measured out the realms of air, Sage very wise who made the lucid spheres of heaven, the Undeceivable who spread out all the worlds, keeper is he and guard of immortality.","people":["Agni","Vaisvanara"],"places":["Earth","Heaven"],"things":["Worship","Born","Singer","Light","Air","Treasure","Men","Streams","Joy","Wise","Mighty","Heroes","Offers","Excellent","Powers","Libations","King","Sage","Parents","Riches","Order","Life"],"groups":["Devas","Immortal"],"concepts":["Life","Immortality","Immortal","Holy","Libations","Swift"],"hash":"md5-5D8QR9ZLX2gaC1aHQ0i9FA==","created":"Monday, April 8, 2024 - 10:51:52 PM"},{"id":"4067bb2f-ba65-49aa-b500-ddd481981917","key":"06008","book":"06","title":"HYMN VIII. Agni.","link":"https://indra.ai/rigveda/hymns/06008.html","text":"p: AT Jatavedas' holy gathering I will tell aloud the conquering might of the swift red-hued Steer. A pure and fresher hymn flows to Vaisvanara, even as for Agni lovely Soma is made pure.\n\np: That Agni, when in loftiest heaven he sprang to life, Guardian of Holy Laws, kept and observed them well. Exceeding wise, he measured out the firmament. Vaisvanara attained to heaven by mightiness.\n\np: Wonderful Mitra propped the heaven and earth apart, and covered and concealed the darkness with his light. He made the two bowls part asunder like two skins. Vaisvanara put forth all his creative power.\n\np: The Migbty seized him in the bosom of the floods: the people waited on the King who should be praised. As envoy of Vivasvan MatariSvan brought Agni Vaisvanara hither from far away.\n\np: In every age bestow upon the singers wealth, worthy of holy synods, glorious, ever new. King, undecaying, as it were with sharpened bolt, smite down the sinner like a tree with lightning-flash.\n\np: Do thou bestow, O Agni, on our wealthy chiefs, rule, with good heroes, undecaying, bending not. May we win for us strength. O Vaisvanara, hundredfold, thousandfold, O Agni, by thy help.\n\np: O thou who dwellest in three places. Helper, keep with effective guards our princely patrons. Keep our band, Agni, who have brought thee presents. Lengthen their lives, Vaisvanara, when lauded.","people":["Soma","Agni","Mitra","Vivasvan","Vaisvanara","Matarisvan"],"places":["Earth","Heaven","Firmament"],"things":["Soma","Glorious","Light","Wealth","Might","Help","Wise","Hymn","Heroes","Creative","People","King","Life"],"groups":["Jatavedas"],"concepts":["Good","Life","Holy","Strength","Glorious","Swift"],"hash":"md5-RNInktzGKwPU1d9hvZB9cg==","created":"Monday, April 8, 2024 - 10:51:52 PM"},{"id":"07e6cac7-492b-46b3-a8b9-8ac95ba12b9c","key":"06009","book":"06","title":"HYMN IX. Agni.","link":"https://indra.ai/rigveda/hymns/06009.html","text":"p: ONE half of day is dark, and bright the other: both atmospheres move on by sage devices. Agni Vaisvanara, when born as Sovran, hath with his lustre overcome the darkness.\n\np: I know not either warp or woof, I know not the web they weave when moving to the contest. Whose son shall here speak words that must be spoken without assistance from the Father near him?\n\np: For both the warp and woof he understandeth, and in due time shall speak what should be spoken, who knoweth as the immortal world's Protector, descending, seeing with no aid from other.\n\np: He is the Monk, the first of all: behold him. Mid mortal men he is the light immortal. Here was he born, firm-seated in his station Immortal, ever waxing in his body.\n\np: A firm light hath been set for men to look on: among all things that fly the mind is swiftest. All Devas of one accord, with one intention, move unobstructed to a single purpose.\n\np: Mine ears unclose to hear, mine eye to see him; the light that harbours in my spirit broadens. Far roams my mind whose thoughts are in the distance. What shall I speak, what shall I now imagine?\n\np: All the Devas bowed them down in fear before thee, Agni, when thou wast dwelling in the darkness. Vaisvanara be gracious to assist us. May the Immortal favour us and help us.","people":["Agni","Vaisvanara"],"places":[],"things":["Born","Light","Men","Help","Sage","Spirit"],"groups":["Devas","Father","Son","Immortal"],"concepts":["Immortal"],"hash":"md5-rpyqJxMNeAF33yxfV/c/yw==","created":"Monday, April 8, 2024 - 10:51:52 PM"},{"id":"7107ae39-41b2-44c2-b2d7-608f7c5e2b1c","key":"06010","book":"06","title":"HYMN X. Agni.","link":"https://indra.ai/rigveda/hymns/06010.html","text":"p: INSTALL at offering, while the rite advances, your pleasant, heavenly Agni, meet for praises. With hymns-for he illumines us-install him. He, Jatavedas, makes our rites successful.\n\np: Hear this laud, Radiant Monk of many aspects, O Agni with the fires of man enkindled, Laud which bards send forth pure as sacred butter, strength to this man, as ’twere for self-advantage.\n\np: Mid mortal men that singer thrives in glory who offers gifts with hymns of praise to Agni, and the Deva, wondrous bright, with wondrous assists helps him to win a stable filled with cattle.\n\np: He, at his birth, whose path is black behind him, filled heaven and earth with far-apparent splendour: And he himself hath been. through night's thick darkness, made manifest by light, the Purifier.\n\np: With thy most mighty aid, confer, O Agni, wonderful wealth on us and on our princes, who stand preeminent, surpassing others in liberal gifts, in fame, and hero virtues.\n\np: Agni, accept this offering with gladness, which, seated here, the worshipper presenteth. Fair hymns hadst thou among the Bharadvajas, and holpest them to gain abundant vigour.\n\np: Scatter our foes, increase our store. May we he glad a hundred winters with brave sons.","people":["Agni","Deva"],"places":["Earth","Heaven"],"things":["Glory","Singer","Offering","Light","Wealth","Men","Mighty","Praise","Brave","Worshipper","Splendour","Offers","Hero","Cattle","Gifts"],"groups":["Jatavedas","Sons","Man"],"concepts":["Birth","Heavenly","Sacred","Strength","Offering"],"hash":"md5-wBIOamb/3Dk9Iz8gmAo9MA==","created":"Monday, April 8, 2024 - 10:51:52 PM"},{"id":"f1b76936-1db0-4303-b7f7-348e271a6632","key":"06011","book":"06","title":"HYMN XI. Agni.","link":"https://indra.ai/rigveda/hymns/06011.html","text":"p: EAGERLY Offering thou, most skilful, Agni! Monk, pressing on as if the Maruts sent thee. To our oblation bring the two Nasatyas, Mitra and Varuna and Earth and Heaven.\n\np: Thou art our guileless, most delightful Herald, the Deva, among mankind, of holy synods. A Monk with purifying tongue, O Agni, offering with thy mouth to thine own body.\n\np: For even the blessed longing that is in thee would bring the Devas down to the singer's worship, when the Angirases' sagest Sage, the Poet, sings the sweet measure at the solemn service.\n\np: Bright hath he beamed, the wise, the far-refulgent. Worship the two widespreading Worlds, O Agni, whom as the Living One rich in oblations the Five Tribes, bringing gifts, adorn with homage.\n\np: When I with reverence clip the grass for Agni, when the trimmed ladle, fullof oil, is lifted, Firm on the seat of earth is based the altar: eye-like,  'the offering is directed Sun-ward.\n\np: Enrich us, O thou Monk of many aspects, with the Devas, Agni, with thy fires, enkindled. O Son of Strength, clad in the robe of riches. May we escape from woe as from a prison.","people":["Agni","Mitra","Varuna","Nasatyas","Deva"],"places":["Earth","Heaven"],"things":["Worship","Mankind","Reverence","Singer","Offering","Sun","Wise","Grass","Sage","Riches","Gifts"],"groups":["Devas","Maruts","Son","Angirases"],"concepts":["Holy","Strength","Offering"],"hash":"md5-V245dgmpK5F7yVVGkM5vXw==","created":"Monday, April 8, 2024 - 10:51:52 PM"},{"id":"47e8cf5d-7a98-4baa-850e-fe27c799dadd","key":"06012","book":"06","title":"HYMN XII. Agni.","link":"https://indra.ai/rigveda/hymns/06012.html","text":"p: KING of trimmed grass. Herald within the dwelling. May Agni worship the Impeller's World-halves. He, Son of Strength, the Holy, from a distance hath spread himself abroad with light like Surya.\n\np: In thee, most wise, shall Dyaus, for full perfection, King! Holy One! pronounce the call to worship. Found in three places, like the Speeder's footstep, come to present men's riches as oblations!\n\np: Whose blaze most splendid, sovran in the forest, shines waxing on his way like the - Impeller. He knows himself, like as a guileless smelter, not to be stayed among the plants, Immortal.\n\np: Our friends extol him like a steed for vigour even Agni in the dwelling, jatave~as. Trce-fed, he fights with power as doth a champion, like Dawn's Sire to be praised with offers.\n\np: Men wonder at his shining glows when, paring the woods with case, o’er the broad earth he goeth, and, like a rushing flood, loosed quickly, burneth, swift as a guilty thief, o’er desert places.\n\np: So mighty thou protectest us from slander, O Champion, Agni! with all fires enkindled. Bring opulence and drive away affliction. May brave sons gladden us through a hundred winters.","people":["Agni","Surya","Dawn"],"places":["Earth"],"things":["Worship","Light","Men","Wise","Mighty","Grass","Brave","Offers","Friends","King","call","Riches"],"groups":["Dyaus","Sons","Son","Immortal"],"concepts":["Immortal","Holy","Strength","Swift"],"hash":"md5-79sOzxEO3ZK8aPngf/keLw==","created":"Monday, April 8, 2024 - 10:51:52 PM"},{"id":"6a72bba9-ad54-4507-b368-e83b52d21fe3","key":"06013","book":"06","title":"HYMN XIII. Agni.","link":"https://indra.ai/rigveda/hymns/06013.html","text":"p: FROM thee, as branches from a tree, O Agni, from thee, Auspicious Deva. spring all our blessings- Wealth swiftly, strength in battle with our foemen, the rain besought of heaven, the flow of waters.\n\np: Thou art our Bhaga to send wealth thou dwellest, like circumambient air, with wondrous splendour. Friend art thou of the lofty Law, like Mitra, Controller, Agni! Deva. of many a blessing.\n\np: Agni! the hero subdues with might his foeman; the singer bears away the Pani's booty- Even he whom thou, Sage, born in Law, incitest by wealth, accordant with the Child of Waters.\n\np: The man who, Son of Strength 1 with offers, hymns, lauds, attracts thy fervour to the altar, Enjoys each precious thing, O Deva, O Agni, gains wealth of corn and is the lord of treasure.s.\n\np: Grant, Son of Strength, to men for their subsistence such things as bring high fame and hero children. For thou with might givest much food in cattle even to the wicked wolf when he is hungry.\n\np: Eloquent, Son of Strength, most Mighty, Agni, vouchsafe us seed and offspring, full of vigour. May I by all my songs obtain abundance. May brave sons gladden us through a hundred winters.","people":["Agni","Mitra","Bhaga","Deva"],"places":["Heaven"],"things":["Lord","Born","Waters","Singer","Air","Treasure","Wealth","Food","Men","Flow","Might","Rain","Offspring","Mighty","Blessing","Brave","Splendour","Offers","Songs","Friend","Hero","Sage","Cattle"],"groups":["Sons","Son","Child","Man"],"concepts":["Blessings","Strength","Auspicious","Circumambient"],"hash":"md5-kHgcJUI+KSqiYtf7Crnw5Q==","created":"Monday, April 8, 2024 - 10:51:52 PM"},{"id":"7fda5044-60f8-481b-88e3-45ede8cbdb7c","key":"06014","book":"06","title":"HYMN XIV. Agni.","link":"https://indra.ai/rigveda/hymns/06014.html","text":"p: WHOSO to Agni hath endeared his thought and service by his hymns, that mortal cats before the rest, and finds sufficiency of food.\n\np: Agni, in truth, is passing wise, most skilled in ordering, a Seer. At offers Manus' sons glorify Agni as their Monk.\n\np: The foeman's wealth in many a place, Agni, is emulous to help. Men fight the fiend, and seek by rites to overcome the riteless foe.\n\np: Agni bestows the hero chief, winner of waters, firm in fray. Soon as they look upon his might his enemies tremble in alarm.\n\np: For with his wisdom Agni, Deva, protects the mortal from reproach, whose conquering wealth is never checked, is never checked in deeds of might.\n\np: O Agni, Deva with Mitra's might call hither the favour of the Devas from earth and heaven. Bring weal from heaven that me. May dwell securely. May we o’ercome the foe's malign oppressions. May we o’ercome them, through thy help o’ercome them.","people":["Agni","Mitra","Deva"],"places":["Earth","Heaven"],"things":["Waters","Wealth","Food","Men","Might","Help","Wise","Chief","Offers","Hero","call"],"groups":["Devas","Sons"],"concepts":["Wisdom","Truth","Winner"],"hash":"md5-bzGYigJm7zRd4/e3udeZRw==","created":"Monday, April 8, 2024 - 10:51:52 PM"},{"id":"fc473823-d050-4a56-b66b-816c789e16b1","key":"06015","book":"06","title":"HYMN XV. Agni.","link":"https://indra.ai/rigveda/hymns/06015.html","text":"p: WITH this my song I strive to reach this guest of yours, who wakes at early morn, the Lord of all the tribes. Each time he comes from heaven, the Pure One from of old: from ancient days the Child cats everlasting food.\n\np: Whom, well-dis sed, the Blirgus stablished as a rriend, whom men must glorify, high-flaming in the wood. As such, most friendly, thou art every day extolled in lauds by Vitahavya, O thou wondrous Deva.\n\np: Be thou the foeless helper of the skilful man, subduer of the enemy near or far away. Bestow a wealthy home on men, O Son of Strength. Give Vitahavya riches spreading far and wide, give Bharadvaja wide-spread wealth.\n\np: Him, your refulgent guest, Agni who comes from heaven, the Herald of mankind, well-skilled in sacred rites, who, like a holy singer, utters heavenly words, oblation-bearer, envoy, Deva, I seek with hymns.\n\np: Who with his purifying, eye-attracting form hath shone upon the earth as with the light of Dawn. Who speeding on, as in the fight of Etaia, cometh, untouched by age, as one athirst in heat.\n\np: Worship ye Agni, Agni, with your log of wood; praise your beloved, your beloved guest with songs. Invite ye the Immortal hither with your hymns. A Deva.among the Devas, he loveth what is choice, loveth our service, Deva.mid Devas.\n\np: Agni inflamed with fuel in my song I sing, pure, Cleanser, steadlast, set in tront at offering. Wise Jatavedas we implore with prayers for bliss the Monk, the holy Singer, bounteous, void of guile.\n\np: Men, Agni, in each age have made thee, Deathiess One, their envoy, offering-bearer, guard adorable. With reverence Devas and mortals have established thee, the ever-watchful, omnipresent Household Lord.\n\np: Thou, Agni, ordering the works and ways of both, as envoy of the Devas traversest both the worlds. When we lay claim to thy regard and gracious fare, be thou to us a thriceprotecting friendly guard.\n\np: Him fair of face, rapid, and fair to look on, him very wis. May we who know not follow. Let him who knows all rules invite for worship, Agru announce our offering to the Immortals.\n\np: Him, Agni, thou deliverest and savest who brings him prayer to thee the Wise, O Hero, the end of offering or its inception; yea, thou endowest him with power and riches.\n\np: Guard us from him who would assail us, Agni, preserve us, O thou Victor, from dishonour. May wealth be ours, desirable in thousands.\n\np: Agni, the Monk, is King, Lord of the homestead, he, Jatayedas, knows all generations. Most skilful worshipper mid Devas and mortals. May he begin  'the offering, the Holy.\n\np: Whate’er to-day thou, bright-flamed Monk, enjoyest from the man's rite-for thou art offerer- Worship, for duly dost thou spread in greatness: bear off thine ofrerings of to-day, most Youthful.\n\np: Look thou upon the offerings duly laid for thee. Fain would he set thee here to worship Heaven and,Earth. Help us, O liberal Agni, in the strife for spoil, so that we may o’ercome all things that trouble us, o’ercome, o’ercome them with thy help.\n\np: Together with all Devas, O fair-faced Agni, be seated first upon the woollined altar, Nest-like, bedewed with oil. Bear this our worship to Savitar who offers rightly.\n\np: Here the arranging monks, as did Atharvan, rub this Agni forth, whom, not bewildered, as he moved in winding ways, they brought from gloom.\n\np: For the Devas’ banquet be thou born, for full perfection and for weal. Bring the Immortal Devas who strengthen holy Law: so let  'our offering reach the Devas.\n\np: O Agni, Lord and Master of men's homesteads, with kindled fuel we have made thee mighty. Let not our household gear be found defective. Sharpen us with thy penetrating splendour.","people":["Agni","Savitar","Deva","Dawn"],"places":["Earth","Heaven"],"things":["Worship","Mankind","Master","Lord","Born","Reverence","Singer","Offering","Light","Wealth","Food","Men","Song","Help","Home","Wise","Mighty","Banquet","Praise","Worshipper","Form","Adorable","Splendour","Offers","Offerings","Bliss","Songs","Hero","King","spoil","Riches"],"groups":["Devas","Jatavedas","Son","Child","Immortal","Man","Monks"],"concepts":["Heavenly","Immortal","Holy","Sacred","Strength","Offering","Offerings"],"hash":"md5-d0kvUWumDlctTB0Vm2+u7A==","created":"Monday, April 8, 2024 - 10:51:52 PM"},{"id":"286dccec-d907-4128-8775-7c88a7086654","key":"06016","book":"06","title":"HYMN XVI. Agni.","link":"https://indra.ai/rigveda/hymns/06016.html","text":"p: PRIEST of all offers hast thou been appointed by the Devas, Agni, amid the race of man.\n\np: So with thy joyous tongues for us offering nobly in this rite. Bring thou the Devas and worship them.\n\np: For well, O Deva, Disposer, thou knowest, straight on, the paths and ways, Agni, most wise in offering.\n\np: Thee, too, hath Bharata of old, with mighty men, implored for bliss. And worshipped thee the worshipful.\n\np: Thou givest these abundant boons to Divodasa pouring forth, to Bharadvaja offering gifts.\n\np: Do thou, Immortal Messenger, bring hither the Celestial Folk; Hearing the singer's eulogy.\n\np: Mortals with pious thought implore thee, Agni, Deva, at holy rites, to come unto the feast of Devas.\n\np: I glorify thine aspect and the might of thee the Bountilul. All those who love shall joy in thee,\n\np: Invoker placed by Manus Agni, art near, the wisest Monk: Pay worship to the Tribes of Heaven.\n\np: Come, Agni, lauded, to the feast; come to the offering of the gifts. As Monk be seated on the grass.\n\np: So, Angiras, we make thee strong with fuel and with holy oil. Blaze high, thou youngest of the Devas.\n\np: For us thou winnest, Agni, Deva, heroic strength exceeding great, far-reaching and of high renown.\n\np: Agni, Atharvan brought thee forth, by rubbing, from the lotus-flower, the head of Visva, of the Monk.\n\np: Thee. Vrtra's slayer, breaker down of castles, hath Atharvan's son, Dadhyac the Rsi, lighted up.\n\np: The hero Pathya kindled thee the Dasyus'. most destructive foe, Winner of spoil in every fight.\n\np: Come, here, O Agni, will I sing verily other songs to thee, and with these drops shalt thou grow strong.\n\np: Where’er thy mind applies itself, vigour preeminent hast thou: There wilt thou gain a dwelling-place.\n\np: Not for a moment only lasts thy bounty, good to many a one! Our service therefore shalt thou gain.\n\np: Agni, the Bharata, hath been sought, the Vrtra conquerer, marked of all, Yea, Divodasa's Hero Lord.\n\np: For he gave riches that surpass in greatness all the things of earth, Fighting untroubled, unsubdued.\n\np: Thou, Agni, as in days of old, with recent glory, gathered light, Hast overspread the lofty heaven.\n\np: Bring to your Agni, O my friends, boldly your laud and offering: Give the Disposer praise and song.\n\np: For as sagacious Herald he hath sat through every age of man, Oblation-bearing messenger.\n\np: Bring those Two Kings whose ways are pure, Adityas, and the Marut host, Excellent Deva. and Heaven and Earth.\n\np: For strong and active mortal man, excellent, Agni, is the look Of thee Immortal, Son of Strength\n\np: Rich through his wisdom, noblest be the giver serving thee to-day: The man hath brought his hymn of praise.\n\np: These, Agni, these are helped by thee, who strong and active all their lives, O'ercome the malice of the foe, fight down the malice ofthe foe.\n\np: May Agni with his pointed blaze cast down each fierce devouring fiend May Agni win us wealth by war.\n\np: O active Jatavedas, bring riches with store of hero sons: Slay thou the demons, O Most Wise.\n\np: Keep us, O Jatavedas, from the troubling of the man of sin: Guard us thou Sage who knowest prayer.\n\np: Whatever sinner, Agni, brings oblations to procure our death, Save us from woe that he would work.\n\np: Drive from us with thy tongue, O Deva, the man who doeth evil deeds, the mortal who would strike us dead.\n\np: Give shelter reaching far and wide to Bharadvaja, conquering Lord! Agni, send wealth most excellent.\n\np: May Agni subdue the Vrtras.fain for riches, through the lord of song, Served with oblation, kindled, bright.\n\np: His Father's Father, shining in his Mother's everlasting side, Set on the seat of holy Law.\n\np: O active Jatavedas, bring devotion that wins progeny, Agni, that he may shine to heaven.\n\np: O Child of Strength, to thee whose look is lovely we with dainty food, O Agni, have poured forth our songs.\n\np: To thee for shelter are we come, as to the shade from fervent heat Agni, who glitterest like gold.\n\np: Mighty as one who subdues with shafts, or like a bull with sharpened horn, Agni, thou breakest down the forts.\n\np: Whom, like an infant newly born, devourer, in their arms they bear, Men's Agni, skilled in holy rites.\n\np: Bear to the banquet of the Devas the Deva.best finder-out of wealth, Let him he seated in his place.\n\np: In Jatavedas kindle ye the dear guest who hath now appeared In a soft place, the homestead's Lord.\n\np: Harness, O Agni, O thou Deva, thy steeds which are most excellent: They bear thee as thy spirit wills.\n\np: Come hither, bring the Devas to us to taste the offerings feast, to drink the draught of Soma juice.\n\np: O Agni of the Bharatas, blaze high with everlasting might, Shine forth and gleam, Eternal One.\n\np: The mortal man who serves the Deva with banquet, and, bringing gifts at offering, lauds Agni, may well attract, with prayer and hands uplifted, the Monk of Heaven and Earth, true Offerer.\n\np: Agni, we bring thee, with our hymn, oblation fashioned in the heart. Let these be oxen unto thee, let these be bulls and kine to thee.\n\np: The Devas enkindle Agni, best slayer of Vrtra, first in rank, the Mighty, One who brings us wealth and crushes down the Raksasas.","people":["Soma","Vrtra","Agni","Angiras","Bharata","Deva","Raksasas"],"places":["Earth","Heaven"],"things":["Worship","Steeds","Work","Lord","Born","Soma","Glory","Singer","Offering","Shine","Light","Wealth","Food","Men","Might","Juice","Song","Joy","Gold","Wise","Strong","Mighty","Grass","Banquet","Praise","Hymn","Offers","Excellent","Offerings","Friends","Bliss","Songs","Drops","Hero","Sage","spoil","Riches","Death","Spirit","Gifts"],"groups":["Devas","Dasyus","Marut","Jatavedas","Sons","Kings","Bharatas","Father","Mother","Son","Child","Immortal","Progeny","Man","Vrtras","Adityas"],"concepts":["Celestial","Good","Evil","Death","Heroic","Love","Immortal","Holy","Strength","Wisdom","Offering","Offerings","Worshipped","Giver","Winner"],"hash":"md5-01rDH6RoLt++8A0UaMPg0Q==","created":"Monday, April 8, 2024 - 10:51:52 PM"},{"id":"c12ad9d8-ec51-4e8c-a6b9-dce35a52364f","key":"06017","book":"06","title":"HYMN XVII. Indra.","link":"https://indra.ai/rigveda/hymns/06017.html","text":"p: DRINK Soma, Mighty One, for which, when lauded, thou breakest through the cattle-stall, O Indra; Thou who, O Bold One, armed with thunder conquered Vrtra with might, and every hostile being.\n\np: Drink it thou Deva who art impetuous victor, Lord of our hymns, with beauteousjaws, the Hero, Render of kine-stalls, car-borne, thunder-wielding, so pierce thy way to wondrous strength, O Indra.\n\np: Drink as of old, and let the draught delight thee. hear thou our meditation and let our songs exalt thee. Make the Sun visible, make food abundant, slaughter the foes, pierce through and free the cattle.\n\np: These gladdening drops, O Indra, Self-sustainer, quaffed shall augment thee in thy mighty splendour. Yea, let the cheering drops delight thee greatly, great, perfect, strong, powerful, all-subduing.\n\np: Gladdened whereby, bursting the firm enclosures, thou gavest splendour to the Sun and Morning. The mighty rock that compassed in the cattle, ne’er moved, thou shookest from its seat, O Indra.\n\np: Thou with thy wisdom, power, and works of wonder, hast stored the ripe milk in the raw cows' udders Unbarred the firm doors for the kine of Morning, and, with the Angirases, set free the cattle.\n\np: Thou hast spread out wide earth, a mighty marvel, and, high thyself, propped lofty heaven, O Indra. Both worlds, whose Sons are Devas, thou hast supported, young, Mothers from old time ofholy Order.\n\np: Yea, indra, all the Deities installed thee their one strong Champion in the van for battle. What time the godless was the Devas’ assailant, indra they chose to win the light of heaven.\n\np: Yea, e’en that heaven itself of old bent backward before thy bolt, in terror of its anger, when Indra, life of every living creature., smote down within his lair the assailing Dragon.\n\np: Yea, Strong One! Tvastar turned for thee, the Mighty, the bolt with thousand spikes and hundred edges, Eager and prompt at will, wherewith thou crushedst the boasting Dragon, O impetuous Hero.\n\np: He dressed a hundred buffaloes, O Indra, for thee whom all accordant Maruts strengthen. He, pusan Visnu, poured forth three great vessels to him, the juice that cheers, that slaughters Vrtra.\n\np: Thou settest free the rushing wave of waters, the floods' great swell encompassed and obstructed. Along steep slopes their course thou tumedst, indra, directed downward, speeding to the ocean.\n\np: May our new prayer bring thee to protect us, thee well-armed Hero with thy bolt of thunder, indra, who made these worlds, the Strong, the ty, who never groweth old, the victory-giver.\n\np: So, indra, form us brilliant holy singers for strength, for glory, and for food and riches. Give Bharadvaja hero patrons, indra Indra, be ours upon the day of trial.\n\np: With thi. May we obtain strength Deva.appointed, and brave sons gladden us through a hundred winters.","people":["Indra","Soma","Vrtra","Visnu","Tvastar","Pusan","Deva"],"places":["Ocean","Earth","Heaven"],"things":["Victory","Milk","Lord","Meditation","Soma","Waters","Glory","Light","Sun","Food","Might","Juice","Strong","Mighty","Car","Brave","Delight","Form","Splendour","Songs","Drops","Hero","Riches","Order","Morning","Cattle","Life"],"groups":["Devas","Maruts","Sons","Deities","Angirases"],"concepts":["Life","Holy","Strength","Wisdom","Giver","Powerful"],"hash":"md5-6Fi/OLgUBO1H6cIlmMsZBg==","created":"Monday, April 8, 2024 - 10:51:52 PM"},{"id":"3190e8ea-b725-4c0b-9f38-485008024f7a","key":"06018","book":"06","title":"HYMN XVIII. Indra.","link":"https://indra.ai/rigveda/hymns/06018.html","text":"p: GLORIFY him whose might is all-surpassing, indra the much-invoked who fights uninjured. Magnify with these songs the never-vanquished, the Strong, the Bull of men, the Mighty Victor.\n\np: He, Champion. Hero, Warrior, Lord of battles, impetuous, loudly roaring, great destroyer, who whirls the dust on high, alone, oerthrower, hath made all races of mankind his subjects.\n\np: Thou, thou alone, hast tamed the Dasyus; singly thou hast subdued the people for the Arya. In this, or is it not, thine hero exploit, indra? Declare it at the proper season.\n\np: For true, I deem, thy strength is, thine the Mighty, thine, O Most Potent, thine the Conquering Victor; Strong, of the strong, most Mighty, of the mighty, thine, driver of the churl to acts of bounty.\n\np: Be this our ancient bond of friendship with you and with Angirases here who speak of Vala. Thou, Wondrous, Shaker of things firm, didst smite him in his fresh strength, and force his doors and castles.\n\np: With holy thoughts must he be called, the Mighty, showing his power in the great fight with Vrtra. He must be called to give us seed and offspring, the Thunderer must he moved and sped to battle.\n\np: He in his might, with name that lives forever, hath far surpassed all human generations. He, most heroic, hath his home with splendour, with glory and with riches and with valour.\n\np: Stranger to guile, who ne’er was false or faithless, bearing a name tha. May be well remembered, indra crushed Cumuri, Dhuni, Sambara, pipru, and Susna, that their castles fell in ruin.\n\np: With saving might that must be praised and lauded, indra, ascend thy car to smite down Vrtra. In thy right hand hold fast thy bolt of thunder, and weaken, Bounteous Lord, his art and magic.\n\np: As Agni, as the dart burns the dry forest, like the dread shaft burn down the fiends, O Indra; Thou who with high deep-reaching spear hast broken, hast covered over mischief and conquered it.\n\np: With wealth, by thousand paths come hither, Agni, paths that bring ample strength, O thou Most Splendid. Come, Son of Strength, o’er whom, invoked of many! the godless hath no power to keep thee distant.\n\np: From heaven, from earth is bruited forth the greatness of him the firm, the fiery, the resplendent. No foe hath he, no counterpart, no refuge is there from him the Conqueror full of wisdom\n\np: This day the deed that thou hast done is famous, when thou, for him, with many thousand others Laidest low Kutsa, Ayu, Atithigva, and boldly didst deliver Turvayana.\n\np: In thee, O Deva, the wisest of the Sages, all Devas were joyful when thou slewest Ahi. When lauded for thyself, thou gavest freedom to sore-afflicted Heaven and to the people.\n\np: This power of thine both heaven and earth acknowledge, the deathless Devas acknowledge it, O Indra. Do what thou ne’er hast done, O Mighty Worker: beget a new hymn at thy offers.","people":["Indra","Vrtra","Agni","Susna","Kutsa","Deva","Atithigva","Ayu","Turvayana","Ahi"],"places":["Earth","Heaven"],"things":["Mankind","Lord","Glory","Wealth","Men","Might","Home","Offspring","Strong","Mighty","Car","Hymn","Ascend","Splendour","Offers","People","Songs","Warrior","Hero","Mighty Victor","Riches"],"groups":["Devas","Dasyus","Human","Son","Angirases"],"concepts":["Friendship","Heroic","Holy","Strength","Wisdom"],"hash":"md5-hv8uemClh6xOo4UQXXyxnw==","created":"Monday, April 8, 2024 - 10:51:53 PM"},{"id":"dd52f57b-5af8-4e67-8c21-c11121de6bd2","key":"06019","book":"06","title":"HYMN XIX. Indra.","link":"https://indra.ai/rigveda/hymns/06019.html","text":"p: GREAT, hero-like controlling men is Indra, unwasting in his powers, doubled in vastness. He, turned to us, hath grown to hero vigour: broad, wide, he hath been decked by those who serve him.\n\np: The bowl made Indra swift to gather booty, the High, the Lofty, Youthful, Undecayinghim who hath waxed by strength which non. May conquer, and even at once grown to complete perfection.\n\np: Stretch out those hands of thine, extend to us ward thy wide capacious arms, and grant us glory. Like as the household herdsman guards the cattle, so move thou round about us in the combat.\n\np: Now, fain for strength, let us invite your Indra hither, who lieth hidden with his Heroes. Free from all blame, without reproach, uninjured, e’en as were those who sang, of old, his praises.\n\np: With steadfast laws, wealth-giver, strong through Soma, he hath much fair and precious food to feed us. In him unite all paths that lead to riches, like rivers that commingle with the ocean.\n\np: Bring unto us the mightiest might, O Hero, strong and most potent force, thou great Subduer! All splendid vigorous powers of men vouchsafe us, Lord of Bay Steeds, that the, may make us joyful.\n\np: Bring us, grown mighty in its strength, O Indra, thy friendly rapturous joy that wins the battle, Wherewith by thee assisted and triumphant, we may laud thee in gaining seed and offspring.\n\np: Indra, bestow on us the power heroic skilled and exceeding strong, that wins the booty, Wherewith, by thine assistance, we may conquer our foes in battle, be they kin or stranger.\n\np: Let thine heroic strength come from behind us, before us, from above us or below us. From every sid. May it approach us, indra. Give us the glory of the realm of splendour.\n\np: With most heroic aid from thee, like heroes Indra, may we win wealth by deeds glory. Thou, King, art Lord of earthly, heavenly treasure.: vouchsafe us riches vast, sublime, and lasting.\n\np: The Bull, whose strength hath waxed, whom Maruts follow, free-giving Indra, the Celestial Ruler, Mighty, all-conquering, the victory-giver, him let us call to grant us new protection.\n\np: Give up the people who are high and haughty to these men and to me, O Thunder-wielder! Therefore upon the earth do we invoke thee, where heroes win, for sons and kine and waters.\n\np: Through these thy friendships, Deva.invoked of many. May we be victors over every foeman. Slaying both kinds of foe. May we, O Hero, be happy, helped by thee, with ample riches.","people":["Indra","Soma","Deva"],"places":["Ocean","Earth"],"things":["Victory","Steeds","Lord","Rivers","Soma","Waters","Glory","Treasure","Wealth","Food","Men","Might","Joy","Offspring","Strong","Mighty","Heroes","Splendour","People","Powers","Hero","King","call","Riches","Cattle"],"groups":["Maruts","Sons"],"concepts":["Celestial","Heavenly","Heroic","Strength","Giver","Swift"],"hash":"md5-Tb8wOXucQw2ce0J7ZCZ+oQ==","created":"Monday, April 8, 2024 - 10:51:53 PM"},{"id":"9c39c20b-cdcb-40a4-9761-a07dcdf3848a","key":"06020","book":"06","title":"HYMN XX. Indra.","link":"https://indra.ai/rigveda/hymns/06020.html","text":"p: GIVE us wealth, indra, that with might, as heaven o’ertops the earth, o’ercomes our foes in battle Wealth that brings thousands and that wins the corn-lands, wealth, Son of Strength! that vanquishes the foeman.\n\np: Even as the power of Dyaus, to thee, O Indra, all Asura sway was by the Devas entrusted, when thou, Impetuous! leagued with Visnu, slewest Vrtra the Dragon who enclosed the waters.\n\np: Indra, Strong, Victor, Mightier than the mighty, addressed with prayer and perfect in his splendour, Lord of the bolt that breaketh forts in pieces, became the King of the sweet juice of Soma..\n\np: There, indra, while the light was won, the Panis f1ed, 'neath a hundred blows, for wise Dasoni, and greedy Susna's magical devices nor left he any of their food remaining.\n\np: What time the thunder fell and Susna perished, all life's support from the great Druh was taken. Indra made room for his car-drivcr Kutsa who sate beside him, when he gained the sunlight.\n\np: As the Hawk rent for him the stalk that gladdens, he wrenched the head from Namuci the Dasa. He guarded Nam, Sayya's son, in slumber, and sated him with food, success, and riches.\n\np: Thou, thunder-armed, with thy great might hast shattered Pipru's strong forts who knew the wiles of serpents. Thou gavest to thy worshipper Rjisvan imperishable Wealth, O Bounteous Giver.\n\np: The crafty Vetasu, the swift Dasni, and Tugra speedily with all his servants, Hath Indra, gladdening with strong assistance, forced near as ’twere to glorify the Mother.\n\np: Resistless, with the hosts he battles, bearing in both his arms the Vrtra-subduing thunder. He mounts his Bays, as the car-seat an archer: yoked at a word they bear the lofty Indra.\n\np: May we, O Indra, gain by thy new favour: so Parus laud thee, with their offers, that thou hast wrecked seven autumn forts, their shelter, slain Dasa tribes and aided Purukutsa.\n\np: Favouring Usana the son of Kavi, thou wast his ancient strengthener, O Indra. Thou gavest Navavastva. as a present, to the great father gavest back his grandson.\n\np: Thou, roaring Indra, drovest on the waters that made a roaring sound like rushing rivers, what time, O Hero, o’er the sea thou broughtest, in safety broughtest Turvasa and Yadu.\n\np: This Indra, was thy work in war: thou sentest Dhuni and Cumuri to sleep and slumber. Dabhiti lit the flame for thee, and worshipped with fuel, hymns, poured Soma, dressed oblations.","people":["Indra","Soma","Vrtra","Visnu","Yadu","Turvasa","Susna","Usana","Tugra","Kutsa","Namuci","Rjisvan"],"places":["Earth","Heaven"],"things":["Work","Lord","Rivers","Soma","Waters","Light","Wealth","Food","Might","Juice","Wise","Strong","Mighty","Car","Worshipper","Splendour","Offers","Hero","King","Riches","Life"],"groups":["Devas","Asura","Dyaus","Father","Mother","Son","Panis"],"concepts":["Life","Strength","Worshipped","Giver","Swift"],"hash":"md5-U954HZW84ANcAwr8TSidpQ==","created":"Monday, April 8, 2024 - 10:51:53 PM"},{"id":"6f7c1a72-f2c8-4683-92f1-3f7a31cdaa6b","key":"06021","book":"06","title":"HYMN XXI. Indra, Devas.","link":"https://indra.ai/rigveda/hymns/06021.html","text":"p: THESE the most constant singer's invocations call thee who art to be invoked, O Hero; Hymns call anew the chariot-borne, Eternal: by eloquence men gain abundant riches.\n\np: I praise that Indra, known to all men, honoured with songs, extolled with hymns at offers, whose majesty, rich in wondrous arts, surpasseth the magnitude of earth, and heaven in greatness.\n\np: He hath made pathways, with the Sun to aid him, throughout the darkness that extended pathless. Mortals who yearn to worship ne’er dishonour, O Mighty Deva, thy Law who art Immortal.\n\np: And he who did these things, where is that Indra? among what tribes? what people doth he visit? What offering contents thy mind , and wishes? What priest among them all? what hymn, O Indra?\n\np: Yea, here were they who, born of old, have served thee, thy friends of ancient time, thou active Worker. Bethink thee now of these, invoked of many! the midmost and the recent, and the youngest.\n\np: Inquiring after him, thy later servants, indra, have gained thy former old traditions. Hero, to whom the prayer is brought, we praise thee as great for that wherein we know thee mighty.\n\np: The demon's strength is gathered fast against thee: great as that strength hath grown, go forth to meet it. With thine own ancient friend and companion, the thunderbolt, brave Champion! drive it backward.\n\np: Hear, too, the prayer of this thy present beadsman, O Indra. Hero, cherishing the singer. For thou wast aye our fathers' Friend aforetime, still swift to listen to their supplication.\n\np: Bring to our help this day, for our protection, Varuna, Mitra , indra, and the Maruts, pusan and Visnu, Agni and Purandhi, Savitar also, and the Plants and Mountains.\n\np: The singers here exalt with hymns and praises thee who art very Mighty and Most Holy. Hear, when invoked, the invoker's invocation. Beside thee there is nonelike thee, Immortal!\n\np: Now to my words come quickly thou who knowest, O Son of Strength, with all who claim our worship, who visit sacred rites, whose tongue is Agni, Devas who made Manu stronger than the Dasyu.\n\np: On good and evil ways be thou our Leader, thou who art known to all as Path-preparer. Bring power to us, O Indra, with thy Horses, Steeds that are best to draw, broad-backed, unwearied.","people":["Indra","Agni","Visnu","Mitra","Varuna","Savitar","Pusan","Deva","Purandhi"],"places":["Earth","Heaven"],"things":["Worship","Leader","Steeds","Born","Mountains","Singer","Offering","Sun","Men","Help","Mighty","Praise","Brave","Hymn","Offers","People","Friends","Songs","Friend","Hero","Horses","call","Riches"],"groups":["Devas","Dasyu","Maruts","Fathers","Son","Immortal"],"concepts":["Good","Evil","Immortal","Holy","Sacred","Strength","Offering","Swift"],"hash":"md5-bqcLKYbluVz4YbqcVcpgeA==","created":"Monday, April 8, 2024 - 10:51:53 PM"},{"id":"739ea13a-f193-404a-9a29-bc11d925fbbf","key":"06022","book":"06","title":"HYMN XXII. Indra.","link":"https://indra.ai/rigveda/hymns/06022.html","text":"p: WITH these my hymns I glorify that Indra who is alone to be invoked by mortals, the Lord, the Mighty One, of manly vigour, victorious. Hero, true, and full of wisdom.\n\np: Our sires of old. Navagvas, sages seven, while urging him to show his might, extolled him, Dwelling on heights, swift, smiting down opponents, guileless in word, and in his thoughts most mighty.\n\np: We seek that Indra to obtain his riches that bring much food, and men, and store of heroes. Bring us, Lord of Bay Steeds, to make us joyful, celestial wealth, abundant, undecaying.\n\np: Tell thou us this, if at thy hand aforetime the earlier singers have obtained good fortune, what is thy share and portion, Strong Subduer, Asura-slayer, rich, invoked of many?\n\np: He who for car-borne Indra, armed with thunder, hath a hymn, craving, deeply-piercing, fluent, who sends a son effectual, firmly-grasping, and strength-bestowing, he comes near the mighty.\n\np: Strong of thyself, thou by this art hast shattered, with thought-swift Parvata, him who waxed against thee, and, Mightiest! roaring! boldly rent in pieces things that were firmly fixed and never shaken.\n\np: Him will we fit for you with new devotion, the strongest Ancient One, in ancient manner. May that Indra, boundless, faithful Leader, conduct us o’er all places hard to traverse.\n\np: Thou for the people who oppress hast kindled the earthly firmament and that of heaven. With heat, O Bull, on every side consume them: heat earth and flood for him who hates devotion.\n\np: Of all the Heavenly Folk, of earthly creatures thou art the King, O Deva.of splendid aspect. In thy right hand, O Indra, grasp die thunder: Eternal! thou destroyest all enchantments.\n\np: Give us confirmed prosperity, O Indra, vast and exhaustless for the foe's subduing. Strengthen therewith the Arya's hate and Dasa's, and let the arms of Nahusas be mighty.\n\np: Come with thy team which brings all blessings hither, Disposer, much-invoked, exceeding holy. Thou whom no fiend, no Deva.can stay or hinder, come swittly with these Steeds in my direction.","people":["Indra","Deva"],"places":["Earth","Heaven","Firmament"],"things":["Leader","Steeds","Lord","Wealth","Food","Men","Might","Strong","Mighty","Car","Hymn","Heroes","People","Hero","King","Riches"],"groups":["Asura","Son","Navagvas"],"concepts":["Celestial","Good","Heavenly","Blessings","Holy","Strength","Wisdom","Ancient One","Swift"],"hash":"md5-gjuiWEegqXQ8YwdKdaM8IA==","created":"Monday, April 8, 2024 - 10:51:53 PM"},{"id":"ced8fd6e-62a0-462a-a79f-5ed2d8a07cf1","key":"06023","book":"06","title":"HYMN XXIII. Indra.","link":"https://indra.ai/rigveda/hymns/06023.html","text":"p: THOU art attached to pressed-out Soma, indra, at laud, at prayer, and when the hymn is chanted; Or when with yoked Bays, Maghavan, thou comest, O Indra, bearing in thine arms the thunder.\n\np: Or when on that decisive day thou holpest the presser of the juice at Vrtra's slaughter; Or when thou, while the strong one feared, undaunted, gavest to death, indra, the daring Dasyus.\n\np: Let Indra drink the pressed-out Soma. Helper and mighty Guide of him who sings his praises. He gives the hero room who pours oblations, and treasure. even to the lowly singer.\n\np: E’en humble rites with his Bay steeds he visits: he wields the bolt, drinks Soma, gives us cattle. He makes the valiant rich in store of heroes, accepts our praise and hears the singer's calling.\n\np: What he hath longed for we have brought to Indra, who from the days of old hath done us service. While Soma flows we will sing hymn, and laud him, so that our meditatio. May streng. then Indra's vigour.\n\np: Thou hast made prayer the means of thine exalting, therefore we wait on thee with hymns, O Indra, may we, by the pressed Soma, Somadrinker! bring thee, with offering, blissful sweet refreshment.\n\np: Mark well our offerings cake, delighted Indra, drink Soma and the milk commingled. Here on  'theofferings grass be seated: give ample room to thy devoted servant.\n\np: O Mighty One, be joyful as thou willest. Let these  'our offerings reach and find thee; An. May this hymn and these our invocations turn thee, whom many men invoke, to help us.\n\np: Friends, when thejuices flow, replenish duly your own, your bounteous Indra with the Soma. Will it not aid him to support us? Indra. spares him who sheds the juice to win his favour.\n\np: While Soma flowed, thus Indra hath been lauded, Ruler of nobles, mid the Bharadvajas, that Indr. May become the singer's patron and give him wealth in every kind of treasure..","people":["Indra","Soma","Vrtra","Maghavan"],"places":[],"things":["Milk","Steeds","Soma","Singer","Offering","Treasure","Wealth","Men","Flow","Juice","Humble","Help","Strong","Mighty","Grass","Praise","Hymn","Heroes","Offerings","Friends","Hero","Cattle","Death"],"groups":["Dasyus"],"concepts":["Death","Offering","Offerings"],"hash":"md5-itEEE0eJeOS1uQvTG2Pesw==","created":"Monday, April 8, 2024 - 10:51:53 PM"},{"id":"355c33f8-3775-44a8-bfda-1b0510b58040","key":"06024","book":"06","title":"HYMN XXIV. Indra.","link":"https://indra.ai/rigveda/hymns/06024.html","text":"p: STRONG rapturous joy, praise, glory are with Indra: impetuous Deva, he quaffs the juice of Soma: That Maghavan whom men must laud with singing. Heaven-dweller, King of songs, whose help is lasting.\n\np: He, Friend of man, most wise, victorious Hero, hears, with far-reaching aid, the singer call him. Excellent, praise of Men, the bard's Supporter, Strong, he gives strength, extolled in holy synod.\n\np: The lofty axle of thy wheels, O Hero, is not surpassed by heaven and earth in greatness. Like branches of a tree, invoked of many manifold aids spring forth from thee, O Indra.\n\np: Strong Lord, thine energies, endowed with vigour, are like the paths of kine converging homeward. Like bonds of cord, indra, that bind the younglings, no bonds are they, O thou of boundless bounty.\n\np: One act to-day, another act tomorrow oft Indra makes what is not yet existeni. Here have we Mitra, Varuna, and Pusan to overcome the foeman's domination.\n\np: By song and offering men brought the waters from thee, as from a mountain's ridge, O Indra. Urging thy might, with these fair lauds they seek thee, O theme of song, as horses rush tobattle.\n\np: That Indra whom nor months nor autumn seasons wither with age, nor fleeting days enfeeble. Stil. May his body Wax, e’en now so mighty, glorified by the lauds and hymns that praise him.\n\np: Extolled, he bends not to the strong, the steadfast, nor to the bold incited by the Dasyu. High mountains are as level plains to Indra: even in the deep he finds firm ground to rest on.\n\np: Impetuous Speeder through all depth and distance, give strengthening food, thou drinker of the juices. Stand up erect to help us, unreluctant, what time the gloom of night brightens to morning.\n\np: Hasting to help, come hither and protect him, keep him from harm when he is here, O Indra. At home, abroad, from injury preserve him. May brave sons gladden us through a hundred winters.","people":["Indra","Soma","Mitra","Varuna","Maghavan","Pusan","Deva"],"places":["Earth","Heaven"],"things":["Lord","Seasons","Mountains","Soma","Waters","Glory","Singer","Offering","Food","Men","Might","Juice","Song","Joy","Help","Home","Wise","Strong","Mighty","Praise","Brave","Excellent","Songs","Friend","Hero","King","Horses","call","Morning"],"groups":["Dasyu","Sons","Man"],"concepts":["Holy","Strength","Offering"],"hash":"md5-qkC0Slfv2cp1niMxfu00VQ==","created":"Monday, April 8, 2024 - 10:51:53 PM"},{"id":"ca255863-b828-4b92-973b-78d0f901c56c","key":"06025","book":"06","title":"HYMN XXV. Indra.","link":"https://indra.ai/rigveda/hymns/06025.html","text":"p: WITH thine assistance, O thou Mighty Indra, be it the least, the midmost, or the highest. Great with those aids and by these powers support us, Strong Deva. in battle that subdues our foemen.\n\np: With these discomfit hosts that fight against us, and check the opponent's wrath, thyself uninjured. With these chase all our foes to every quarter: subdue the tribes of Dasas to the Arya.\n\np: Those who array themselves as foes to smite us, O Indra, be they kin or be they strangers. Strike thou their manly strength that it be feeble, and drive in headlong flight our foemen backward.\n\np: With strength of limb the hero subdues the hero, when bright in arms they range them for the combat. When two opposing hosts contend in battle for seed and offspring, waters, kine, or corn-lands.\n\np: Yet no strong man hath conquered thee, no hero, no brave, no warrior trusting in his valour. Not one of these is match for thee, O Indra. Thou far surpassest all these living creatures.\n\np: He is the Lord of both these armies' valour when the commanders call them to the conflict: When with their ranks expanded they are fighting with a great foe or for a home with heroes.\n\np: And when the people stir themselves for battle, be thou their saviour, indra, and protector, and theirs, thy manliest of our friends, the pious, the chiefs who have installed us monks, O Indra.\n\np: To thee for high dominion hath been forevermore, for slaughtering the Vrtras, All lordly power and might, O Holy Indra, given by Devas for victory in battle.\n\np: So urge our hosts together in the combats: yield up the godless bands that fight against us. Singing, at mor. May we find thee with favour, yea, indra, and e’en now, we Bharadvajas.","people":["Indra","Deva"],"places":[],"things":["Victory","Lord","Waters","Might","Home","Offspring","Strong","Mighty","Armies","Brave","Heroes","People","Powers","Friends","Warrior","Hero","call"],"groups":["Devas","Man","Vrtras","Monks"],"concepts":["Holy","Strength"],"hash":"md5-tHP5W6rIgBe4/xs18YJy+A==","created":"Monday, April 8, 2024 - 10:51:53 PM"},{"id":"1f0b592f-4dbd-446d-b3e7-f4ecf20cd0a8","key":"06026","book":"06","title":"HYMN XXVI. Indra.","link":"https://indra.ai/rigveda/hymns/06026.html","text":"p: O INDRA, hear us. Raining down the Soma, we call on thee to win us mighty valour. Give us strong assist on the day of trial, when the tribes gather on the field of battle.\n\np: The warrior, son of warrior sire, invokes thee, to gain great strength tha. May be won as booty: To thee, the brave man's Lord, the fiends' subduer, he looks when fighting hand to hand for cattle.\n\np: Thou didst impel the sage to win the daylight, didst ruin Susna for the pious Kutsa. The invulnerable demon's head thou clavest when thou wouldst win the praise of Atithigva.\n\np: The lofty battle-car thou broughtest forward; thou holpest Dasadyu the strong when fighting. Along with Vetasu thou slewest Tugra, and madest Tuji strong, who praised thee, indra.\n\np: Thou madest good the laud, what time thou rentest a hundred thousand fighting . O Hero, Slewest the Dasa Sambara of the mountain, and with strange aids didst assist Divodasa.\n\np: Made glad with Soma-draughts and faith, thou sentest Cumuri to his sleep, to please Dabhiti. Thou, kindly giving Raji to Pithinas, slewest with might, at once, the sixty thousand.\n\np: May I too, with the liberal chiefs, O Indra, acquire thy blin supreme and domination, when, Mightiest! Hero-girt! Nahusa heroes boast them in thee, the triply-strong Defender.\n\np: May we he thy friends, thy best beloved, O Indra, at this holy invocation. Best be Pratardani, illustrious ruler, in subduing foemen and in gaining riches.","people":["Indra","Soma","Susna","Tugra","Kutsa","Atithigva"],"places":[],"things":["Lord","Soma","Might","Strong","Mighty","Car","Praise","Brave","Faith","Heroes","Friends","Warrior","Hero","Sage","call","Riches","Cattle"],"groups":["Son","Man"],"concepts":["Good","Holy","Strength"],"hash":"md5-sR+uqQje6Wy4KRwcebTpMw==","created":"Monday, April 8, 2024 - 10:51:53 PM"},{"id":"268d6e16-fb40-47f3-b27e-1f0b2d909ca0","key":"06027","book":"06","title":"HYMN XXVII. Indra.","link":"https://indra.ai/rigveda/hymns/06027.html","text":"p: WHAT deed hath Indra done in the wild transport, in quaffing or in friendship with, the Soma? What joys have men of ancient times or recent obtained within the chamber of libation?\n\np: In its wild joy Indra hath proved him faithful, faithful in quaffing, faithful in its friendship. His truth is the delight that in this chamber the men of old and recent times have tasted.\n\np: All thy vast power we know not, know not the riches of thy full abundance. No one hath seen that might of thine, productive of bounty every day renewed, O Indra.\n\np: This one great power of thine our eyes have witnessed, wherewith thou slewest Varasikha's children, when by the force of thy descending thunder, at the mere solund, their boldest was demolished.\n\np: In aid of Abhyavartin Cayamana, indra conquered the seed of Varasikha. At Hariyupiya he smote the vanguard of the Vrcivans, and the rear fled frighted.\n\np: Three thousand, mailed, in quest of fame, together, on the Yavyavati, O much-sought Indra, Vrcivan's sons, falling before the arrow, like bursting vessels went to their destruction.\n\np: He, whose two red Steers, seeking goodly pasture, plying their tongues move on 'twixt earth and heaven, Gave Turvasa to Srnjaya, and, to aid him, gave the Vrcivans up to Daivavata.\n\np: Two wagon-teams, with damsels, twenty oxen, O Agni, Abhydvartin Cayamdna, the liberal Sovran, giveth me. This guerdon of Prthu's seed is hard to win from others.","people":["Indra","Soma","Agni","Turvasa"],"places":["Earth","Heaven"],"things":["Soma","Men","Might","Joy","Delight","Riches"],"groups":["Sons","Steers"],"concepts":["Friendship","Truth"],"hash":"md5-DAPyQxtUk5k0/nqtYPyt3g==","created":"Monday, April 8, 2024 - 10:51:53 PM"},{"id":"22a57c9e-64d6-4550-8367-60cb6f40bc47","key":"06028","book":"06","title":"HYMN XXVIII. Cows.","link":"https://indra.ai/rigveda/hymns/06028.html","text":"p: THE Kine have come and brought good fortune: let them rest in the cow-pen and be happy near us. Here let them stay prolific, many-coloured, and yield through many morns their milk for Indra.\n\np: Indra aids him who offers offering and gifts: he takes not what is his, and gives him more thereto. Increasing ever more and ever more his wealth, he makes the pious dwell within unbroken bounds.\n\np: These are ne’er lost, no robber ever injures them: no evil-minded foe attempts to harass them. The master of the Kine lives many a year with these, the Cows whereby he pours his gifts and serves the Devas.\n\np: The charger with his dusty brow o’ertakes them not, and never to the shambles do they take their way. These Cows, the cattle of the pious worshipper, roam over widespread pasture where no danger is.\n\np: To me the Cows seem Bhaga, they seem Indra, they seem a portion of the first-poured Soma. These present Cows, they, O ye Indra. I long for Indra with my heart and spirit.\n\np: O Cows, ye fatten e’en the worn and wasted, and make the unlovely beautiful tolook on. Prosper my house, ye with auspicious voices. Your power is glorified in our assemblies.\n\np: Crop goodly pasturage and be prolific drink pure sweet water at good drinking places. Never be thief or sinful man your matter, an. May the dart of Rudra still avoid you.\n\np: Now let this close admixture be close intermigled with these Cows, Mixt with the Steer's prolific flow, and, indra, with thy hero might.","people":["Indra","Soma","Bhaga"],"places":[],"things":["Master","Milk","Soma","Water","Offering","Wealth","Flow","Might","Worshipper","Offers","Hero","Cow","Cattle","Spirit","Gifts"],"groups":["Devas","Man"],"concepts":["Good","Evil","Beautiful","Offering","Auspicious"],"hash":"md5-3fLDwnPG0ZcAM+risB3+Ew==","created":"Monday, April 8, 2024 - 10:51:53 PM"},{"id":"484e9f1d-0c0a-4a3d-88a5-35ba3c8a5031","key":"06029","book":"06","title":"HYMN XXIX Indra.","link":"https://indra.ai/rigveda/hymns/06029.html","text":"p: YOUR men have followed Indra for his friendship, and for his loving-kindness glorified him. For he bestows great wealth, the Thunder-wielder: worship him, Great and Kind, to win his favour.\n\np: Him to whose hand, men closely cling, and drivers stand on his golden chariot firmly stationed. With his firm arms he holds the reins; his Horses, the Stallions, are yoked ready for the journey.\n\np: Thy devotees embrace thy feet for glory. Bold, thunder-armed, rich, through thy strength, in guerdon, Robed in a garment fair as heaven to look on, thou hast displayed thee like an active dancer.\n\np: That Soma when effused hath best consistence, for which the food is dressed and grain is mingled; By which the men who pray, extolling Indra chief favourites of Devas, recite their praises.\n\np: No limit of thy might hath been appointed, which by its greatness sundered earth and heaven. These the Prince filleth full with stron endeavour, driving, as ’twere, with help his flocks to waters.\n\np: So be the lofty Indra prompt to listen. Helper unaided, golden-visored Hero. Yea, s. May he, shown forth in might unequalled, smite down the many Vrtras and the Dasyus.","people":["Indra","Soma"],"places":["Earth","Heaven"],"things":["Worship","Journey","Soma","Waters","Glory","Wealth","Food","Men","Might","Help","Chief","Hero","Horses"],"groups":["Devas","Dasyus","Vrtras"],"concepts":["Friendship","Strength"],"hash":"md5-NwmDi+yuNVYM/GAEIiaDMw==","created":"Monday, April 8, 2024 - 10:51:53 PM"},{"id":"208d6454-e7b4-46cf-9596-6be026403ae8","key":"06030","book":"06","title":"HYMN XXX. Indra.","link":"https://indra.ai/rigveda/hymns/06030.html","text":"p: INDRA hath waxed yet more for hero prowess, alone, Eternal, he bestoweth treasure.s. Indra transcendeth both the worlds in greatness: one half of him equalleth earth and heaven.\n\np: Yea, mighty I esteem his Deva like nature: none hindereth what he hath once determined. Near and afar he spread and set the regions, and every day the Sun became apparent.\n\np: E’en now endures thine exploit of the Rivers, when, indra, for their floods thou clavest passage. Like men who sit at meat the mountains settled: by thee, most Wise! the regions were made steadfast.\n\np: This is the truth, non else is like thee, indra, no Deva.superior to thee, no mortal. Thou slewest Ahi who besieged the waters, and lettest loose the streams to hurry seaward.\n\np: Indra, thou breakest up the floods and portals on all sides, and the firmness of the mountain. Thou art the King of men, of all that liveth, engendering at once Sun. Heaven, and Morning.","people":["Indra","Deva","Ahi"],"places":["Earth","Heaven"],"things":["Mountains","Rivers","Waters","Sun","Treasure","Men","Streams","Wise","Mighty","Hero","King","Morning"],"groups":[],"concepts":["Truth"],"hash":"md5-JuGBuUZ2IZrCNW7Sy1Mirg==","created":"Monday, April 8, 2024 - 10:51:53 PM"},{"id":"df23581d-80af-45e3-b40c-9d1297821de3","key":"06031","book":"06","title":"HYMN XXXI Indra.","link":"https://indra.ai/rigveda/hymns/06031.html","text":"p: SOLE Lord of wealth art thou, O Lord of riches: thou in thine hands hast held the people, indra! Men have invoked thee with contending voices for seed and waters, progeny and sunlight.\n\np: Through fear of thee, O Indra, all the regions of earth, though naugh. May move them, shake and tremble. All that is firm is frightened at thy coming, -the earth, the heaven, the mountain, and the forest.\n\np: With Kutsa, indra! thou didst conquer Susna, voracious, bane of crops, in fight for cattle. In the close fray thou rentest him: thou stolest the Sun's wheel and didst drive away misfortunes.\n\np: Thou smotest to the ground the hundred castles, impregnable, of Sambara the Dasyu, when, Strong, with might thou holpest Divodasa who poured libations out, O Soma-buyer, and madest Bharadvaja rich who praised thee.\n\np: As such, true Hero, for great joy of battle mount thy terrific car, O Brave and Manly. Come with thine help to me, thou distant Roamer, and, glorious Deva, spread among men my glory.","people":["Indra","Soma","Susna","Kutsa","Deva"],"places":["Earth","Heaven"],"things":["Lord","Soma","Waters","Glory","Glorious","Sun","Wealth","Men","Might","Joy","Help","Strong","Car","Brave","People","Libations","Hero","Riches","Cattle","Wheel"],"groups":["Dasyu","Progeny"],"concepts":["Glorious","Libations"],"hash":"md5-NEze6tyf4LiveL9TYyQo4g==","created":"Monday, April 8, 2024 - 10:51:53 PM"},{"id":"203e925a-b9c6-4dac-b681-d79b27127cd7","key":"06032","book":"06","title":"HYMN XXXII Indra.","link":"https://indra.ai/rigveda/hymns/06032.html","text":"p: I WITH my lips have fashioned for this Hero words never matched, most plentiful and auspicious, for him the Ancient, Great, Strong, Energetic, the very mighty Wielder of the Thunder.\n\np: Amid the sages, with the Sun he brightened the Parents: glorified, he burst the mountain; And, roaring with the holy-thoughted singers, he loosed the bond that held the beams of Morning.\n\np: Famed for great deeds, with monks who kneel and laud him, he still hath conquered in the frays for cattle, and broken down the forts, the Fort-destroyer, a friend with friends, a Sage among the sages.\n\np: Come with thy girthed mares, with abundant vigour and plenteous strength to him who sings thy praises. Come hither, borne by mares with many heroes, Lover of song! Steer! for the people's welfare.\n\np: Indra with rush and might, sped by his Coursers, hath swiftly won the waters from the southward. Thus set at liberty the rivers daily flow to their goal, incessant and exhaustless.","people":["Indra"],"places":[],"things":["Rivers","Waters","Sun","Flow","Might","Song","Strong","Mighty","Heroes","People","Friends","Friend","Hero","Sage","Parents","Morning","Cattle"],"groups":["Monks"],"concepts":["Holy","Strength","Auspicious"],"hash":"md5-rGce6h4jrnEAj4+uQKFspw==","created":"Monday, April 8, 2024 - 10:51:53 PM"},{"id":"7b3fb6c0-dd30-41f9-b76a-a9b78f53c5a1","key":"06033","book":"06","title":"HYMN XXXIII. Indra.","link":"https://indra.ai/rigveda/hymns/06033.html","text":"p: GIVE us the rapture that is mightiest, indra, prompt to bestow and swift to aid, O Hero, that wins with brave steeds where brave steeds encounter, and quells the Vrtras and the foes in battle.\n\np: For with loud voice the tribes invoke thee, indra, to aid them in the battlefield of heroes. Thou, with the singers, hast pierced through the Panis: the charger whom thou aidest wins the booty.\n\np: Both races, indra, of opposing foemen, O Hero, both the Arya and the Dasa, Hast thou struck down like woods with well-shot lightnings: thou rentest them in fight, most manly Chieftain!\n\np: Indra, befriend us with no scanty assist, prosper and aid us, Loved of all that liveth, when, fighting for the sunlight, we invoke thee, O Hero, in the fray, in war's division.\n\np: Be ours, O Indra, now and for the future, be graciously inclined and near to help us. Thu. May we, singing, sheltered by the Mighty, win many cattle on the day of trial.","people":["Indra"],"places":[],"things":["Steeds","Help","Mighty","Voice","Brave","Heroes","Hero","Cattle"],"groups":["Panis","Vrtras"],"concepts":["Swift"],"hash":"md5-woElS/8DZvNb9defDmRiBg==","created":"Monday, April 8, 2024 - 10:51:53 PM"},{"id":"1022151e-fdc2-4cd4-96e4-35fd442905ac","key":"06034","book":"06","title":"HYMN XXXIV. Indra.","link":"https://indra.ai/rigveda/hymns/06034.html","text":"p: FULL Many songs have met in thee, O Indra, and many a noble thought from thee proceedeth. Now and of old the eulogies of sages, their holy hymns and lauds, have yearned for Indra.\n\np: He, praised of many, bold, invoked of many, alone is glorified at offers. Like a car harnessed for some great achievement, indra must be the cause of our rejoicing.\n\np: They make their way to Indra and exalt him, bim whom no prayers and no laudations trouble; For when a hundred or a thousand singers. laud him who loves the song their praise delights him.\n\np: As brightness mingles with the Moon in heaven, the offered Soma yearns to mix with Indra. Like water brought to men in desert places, our gifts at offering have still refreshed him.\n\np: To him this mighty eulogy, to Indra hath this our laud been uttered by the poets, that in the great encounter with the foemen, Loved of all life, indr. May guard and help us.","people":["Indra","Soma"],"places":["Heaven"],"things":["Soma","Water","Offering","Moon","Men","Song","Help","Mighty","Car","Praise","Offers","Songs","Life","Gifts"],"groups":[],"concepts":["Life","Holy","Offering","Noble"],"hash":"md5-RC6sFWthKZqTX4h80Cch1Q==","created":"Monday, April 8, 2024 - 10:51:53 PM"},{"id":"11599afe-9a2c-4bd5-9587-fe9f6d6bed71","key":"06035","book":"06","title":"HYMN XXXV. Indra.","link":"https://indra.ai/rigveda/hymns/06035.html","text":"p: WHEN shall our meditations rest in thy car beside thee? When dost thou give the singer food for thousands? When wilt thou clothe this poet's laud with plenty, and when wilt thou enrich our hymns with booty?\n\np: When wilt thou gatber men with men, O Indra, heroes with heroes, and prevail in combat? Thou shalt win triply kine in frays for cattle, so, indra, give thou us celestial glory.\n\np: Yea, when wilt thou, O Indra, thou Most Mighty, make the prayer all-sustaining for the singer? When wilt thou yoke, as we yoke songs, thy Horses, and come to offerings that bring wealth in cattle?\n\np: Grant to the Singer food with store of cattle, splendid with horses and the fame of riches. Send food to swell the MilchCow good at milking: bright be its shine among the Bharadvajas.\n\np: Lead otherwise this present foeman, Sakra! Hence art thou praised as Hero, foe destroyer Him who gives pure gift. May I praise unceasing. Sage, quicken the Angirases by devotion.","people":["Indra","Sakra"],"places":[],"things":["Glory","Singer","Shine","Wealth","Food","Men","Mighty","Car","Praise","Heroes","Gift","Offerings","Songs","Hero","Sage","Horses","Riches","Cattle","MilchCow"],"groups":["Angirases"],"concepts":["Celestial","Good","Offerings"],"hash":"md5-OgdpgP6TmQB0aNuFM2Rh9w==","created":"Monday, April 8, 2024 - 10:51:53 PM"},{"id":"cac12366-018e-4636-ba72-145ec32a2747","key":"06036","book":"06","title":"HYMN XXXVI. Indra.","link":"https://indra.ai/rigveda/hymns/06036.html","text":"p: THY raptures ever were for all men's profit: so evermore have been thine earthly riches. Thou still hast been the dealer-forth of vigour, since among Devas thou hast had power and Deva.ead.\n\np: Men have obtained his strength by sacrificing, and ever urged him, on to hero valour. For the rein-seizing, the impetuous Charger they furnished power even for Vrtra's slaughter.\n\np: Associate with him, as teams of horses, help, manly might, and vigour follow Indra. As rivers reach the sea, so, strong with praises, our holy songs reach him the Comprehensive.\n\np: Lauded by us, let flow the spring, O Indra, of excellent and brightly-shining riches. For thou art Lord of men, without an equal: of all the world thou art the only Sovran.\n\np: Hear what tho. Mayst hear, thou who, fain for worship, as heaven girds earth, guardest thy servant's treasure.; Tlat tho. Mayst be our own, joying in power, famed through thy might in every generation.","people":["Indra","Vrtra","Deva"],"places":["Earth","Heaven"],"things":["Worship","Lord","Rivers","Treasure","Men","Flow","Might","Help","Strong","Excellent","Songs","Hero","Horses","Riches"],"groups":["Devas"],"concepts":["Holy","Strength"],"hash":"md5-oTQsenJcO3+pDWH/LJmMKA==","created":"Monday, April 8, 2024 - 10:51:53 PM"},{"id":"c7079774-c7e3-4830-8ed2-6e8ea58f85f4","key":"06037","book":"06","title":"HYMN XXXVII Indra.","link":"https://indra.ai/rigveda/hymns/06037.html","text":"p: LET thy Bay Horses, yoked, O mighty Indra, bring thy car hither fraught with every blessing. For thee, the Heavenly, e’en the poor invoketh. May we this day, thy feast-companions, prosper.\n\np: Forth to the vat the brown drops flow for service, and purified proceed directly forward. May Indra drink of this, our guest aforetime, Celestial King of the strong draught of Soma.\n\np: Bringing us hitherward all-potent Indra on well-wheeled chariot. May the Steeds who bear him Convey him on the road direct to glory, and ne’e. May Vayu's Amrta cease and fail him.\n\np: Supreme, he stirs this man to give the guerdon.Indra, most efficacious of the princes. Wherewith, O Thunderer, thou removest sorrow, and, Bold One! partest wealth among the nobles.\n\np: Indra is hewho gives enduring vigour. May our songs magnify the Deva.Most Mighty. Best Vrtra conquerer be the Hero Indra these things he gives as Prince, with stron endeavour.","people":["Indra","Soma","Vrtra","Vayu","Deva"],"places":[],"things":["Steeds","Soma","Glory","Wealth","Flow","Strong","Mighty","Car","Blessing","Bay Horses","Songs","Drops","Hero","King","Horses","Amrta"],"groups":["Man"],"concepts":["Celestial","Heavenly"],"hash":"md5-4D7/lUFsOZHDVEgJGNkazw==","created":"Monday, April 8, 2024 - 10:51:53 PM"},{"id":"ccda9efb-c798-43e3-9f57-9591e0d64925","key":"06038","book":"06","title":"HYMN XXXVIII. Indra.","link":"https://indra.ai/rigveda/hymns/06038.html","text":"p: HE hath drunk hence, most Marvellous, and carried away our great and splendid call on Indra. The Bounteous, when we serve the Devas, accepteth song yet more famous and the gifts we bring him.\n\np: The speaker filleth with a cry to Indra his ears who cometh nigh e’en from a distance. May this my call bring Indra to my presence, this call to Devas composed in sacred verses.\n\np: Him have I sung with my best song and praises, indra of ancient birth and Everlasting. For prayer and songs in him are concentrated: let laud wax mighty when addressed to Indra:\n\np: Indra, whom offering shall strengthen, Soma, and song and hymn, and praises and devotion, whom Dawns shall strengthen when the night departeth, indra whom days shall strengthen, months, and autumns.\n\np: Him, born for conquering might in full perfection, and waxen strongfor bounty and for glory, Great, powerful, will we to-day, O singer, invite to aid. us and to quell our foemen.","people":["Indra","Soma"],"places":[],"things":["Born","Soma","Glory","Singer","Offering","Might","Song","Mighty","Hymn","Songs","call","Gifts"],"groups":["Devas","Dawns"],"concepts":["Birth","Sacred","Offering","Powerful"],"hash":"md5-aZGNsknkgSk5cIc6+khayg==","created":"Monday, April 8, 2024 - 10:51:53 PM"},{"id":"7f8ba855-d711-41b5-8851-bcf33193185a","key":"06039","book":"06","title":"HYMN XXXIX Indra.","link":"https://indra.ai/rigveda/hymns/06039.html","text":"p: OF this our charming, our celestial Soma, eloquent, wise, Monk, with inspired devotion, Of this thy close attendant, hast thou drunken. Deva, send the singer food with milk to grace it.\n\np: Craving the kine, rushing against the mountain led on by Law, with holyminded comrades. He broke the never-broken ridge of Vala. With words of might Indra subdued the Panis.\n\np: This Indu lighted darksome nights, O Indra, throughout the years, at morning and at evening. Him have they stablished as the days' bright ensign. He made the Mornings to be born in splendour.\n\np: He shone and caused to shme the worlds that shone not. By Law he lighted up the host of Mornings. He moves with Steeds yoked by eternal Order, contenting men with nave that finds the sunlight.\n\np: Now, praised, O Ancient King! fill thou the singer with plenteous food that h. May deal forth treasure.s. Give waters, herbs that have no poison, forests, and kine, and steeds, and men, to him who lauds thee.","people":["Indu","Indra","Soma","Deva"],"places":[],"things":["Milk","Steeds","Born","Soma","Waters","Singer","Treasure","Food","Men","Might","Wise","Splendour","King","Order","Morning"],"groups":["Panis"],"concepts":["Celestial"],"hash":"md5-w6U000MqTp1jBvJJ8PvHqw==","created":"Monday, April 8, 2024 - 10:51:54 PM"},{"id":"071dd178-9389-4744-b91d-5cfb399ad5d8","key":"06040","book":"06","title":"HYMN XL. Indra","link":"https://indra.ai/rigveda/hymns/06040.html","text":"p: DRINK, indra; juice is shed to make thee joyful: loose thy Bay Steeds and give thy friends their freedom. Begin the song, seated in our assembly. Give strength for offering to him who singeth.\n\np: Drink thou of this whereof at birth, O Indra, thou drankest, Mighty One for power and rapture. The men, the pressing-stones, the cows, the waters have made this Soma ready for thy drinking.\n\np: The fire is kindled, Soma pressed, O Indra: let thy Bays, best to draw, convey thee hither. With mind devoted, indra, I invoke thee. Come, for our great prosperity approach us.\n\np: Indra, come hither: evermore thou camest through our great strong desire to drink the Soma. Listen and hear the prayers which now we offer, and let this offering increase thy vigour.\n\np: Mayst thou, O Indra, on the day of trial, present or absent, wheresoe’er thou dwellest, thence, with thy team, accordant with the Maruts, Song-lover! guard  'our offering, to help us.","people":["Indra","Soma"],"places":[],"things":["Steeds","Soma","Waters","Offering","Men","Juice","Song","Help","Strong","Mighty","Pressing-Stones","Friends"],"groups":["Maruts"],"concepts":["Birth","Strength","Offering"],"hash":"md5-wpmlw4I+SepUqFPFcrEQ6g==","created":"Monday, April 8, 2024 - 10:51:54 PM"},{"id":"79f72a5a-ac05-4502-bf4f-87f16b5f6e4d","key":"06041","book":"06","title":"HYMN XLI. Indra.","link":"https://indra.ai/rigveda/hymns/06041.html","text":"p: COME gracious to  'our offering, O Indra: pressed Soma-drops are purified to please thee. As cattle seek their home, so Thunderwielder, come, indra, first of those who claim our worship.\n\np: With that well-formed most wide-extending palate, wherewith thou ever drinkest streams of sweetness, Drink thou; the Adhvaryu standeth up before thee: let thy spoil-winning thunderbolt attend thee.\n\np: This drop, steer-strong and omniform, the Soma, hath been made ready for the Bull, for India. Drink this, Lord of the Bays, thou Strong Supporter, this that is thine of old, thy food forever.\n\np: Soma when pressed excels the unpressed Soma, better, for one who knows, to give him pleasure. Come to this offering of ours, O Victor replenish all thy powers with this libation.\n\np: We call on thee, O Indra: come thou hither: sufficient be the Soma for thy body. Rejoice thee, Satakratu! in the juices guard us in wars, guard us among our people.","people":["Indra","Soma","Satakratu"],"places":[],"things":["Worship","Lord","Soma","Offering","Food","Streams","Home","Strong","People","Powers","Drops","Winning","call","spoil","Cattle"],"groups":[],"concepts":["Offering"],"hash":"md5-yJ7TFXZUk3Z0BFNYGi50gg==","created":"Monday, April 8, 2024 - 10:51:54 PM"},{"id":"6d2adcfa-a501-4c05-844c-eb751064d6e4","key":"06042","book":"06","title":"HYMN XLII. Indra.","link":"https://indra.ai/rigveda/hymns/06042.html","text":"p: BRING offerings gifts to him, Omniscient, for he longs to drink, the Wanderer who comes with speed, the Hero ever in the van.\n\np: With Soma go ye nigh to him chief drinker of the Soma's juice: With beakers to the Impetuous Deva, to Indra with the drops effused.\n\np: What time, with Soma, with the juice effused, ye come before the Deva, Full wise he knows the hope of each, and, Bold One, strikes this foe and that.\n\np: To him, Adhvaryu! yea, to him give offerings of the juice expressed. Will he not keep us safely from the spiteful curse of each presumptuous high-born foe?","people":["Indra","Soma","Deva"],"places":[],"things":["Born","Soma","Juice","Wise","Chief","Offerings","Drops","Hero","Gifts"],"groups":[],"concepts":["Offerings"],"hash":"md5-DPtbjF573CeUxwldPbi2BQ==","created":"Monday, April 8, 2024 - 10:51:54 PM"},{"id":"0a00f0f3-c8d0-469c-b7be-2527e40ddd55","key":"06043","book":"06","title":"HYMN XLIII. Indra","link":"https://indra.ai/rigveda/hymns/06043.html","text":"p: IN whose wild joy thou madest once Sambara Divodasa's prey, This Soma is pressed out for thee, O Indra: drink!\n\np: Whose gladdening draught, shed from the points, thou guardest in the midst and end, This Soma is pressed out for thee, O Indra drink!\n\np: In whose wild joy thou settest free the kine held fast within the rock, This Soma is pressed out for thee, O Indra: drink!\n\np: This, in whose juice delighting thou gainest the might of Maghavan, This Soma is pressed out for thee, O Indra drink!","people":["Indra","Soma","Maghavan"],"places":[],"things":["Soma","Might","Juice","Joy"],"groups":[],"concepts":[],"hash":"md5-PLoeRbkJAaWavEBFYSDkSg==","created":"Monday, April 8, 2024 - 10:51:54 PM"},{"id":"f750acff-a8f5-490c-850c-b686f56d6153","key":"06044","book":"06","title":"HYMN XLIV. Indra.","link":"https://indra.ai/rigveda/hymns/06044.html","text":"p: THAT which is wealthiest, Wealthy Deva.in splendoursmost illustrious, Soma is pressed: thy gladdening draught, indra! libation's Lord! is this.\n\np: Effectual, most Effectual One! thine, as bestowing wealth of hymns, Soma is pressed: thy gladdening draught, indra! libation's Lord! is this.\n\np: Wherewith thou art increased in strength, and conquerest with thy proper aids, Soma is pressed: thy gladdening draught, indra! libation's Lord! is this.\n\np: Him for your sake I glorify as Lord of Strength who wrongeth none, the Hero Indra, conquering all, most Bounteous, Deva.of all the tribes.\n\np: Those Devas, both Heaven and Earth, revere the power and might of himhim whom our songs increase in strength, the Lord of bounty swift to come.\n\np: To seat your Indra, I will spread abroad with power this song of praise. The saving assists that abide in him, like songs, extend and grow.\n\np: A recent Friend, he found the skilful priest: he drank, and showed forth treasure. from the Devas. He conquered, borne by strong all-shaking mares, and was with far-spread power his friends' Protector.\n\np: In course of Law the sapient juice was quaffed: the Deities to glory turned their mind. Winning through hymns a lofty title, he, the Lovely, made his beauteous form apparent.\n\np: Bestow on us the most illustrious strength ward off men's manifold malignities. Give with thy might abundant vital force, and aid us graciously in gaining riches.\n\np: We turn to thee as Giver, liberal Indra. Lord of the Bay Steeds, be not thou ungracious. No friend among mankind have we to lookto: why have men called thee him who spurs the niggard?\n\np: Give us not up, Strong Hero! to the hungry: unharmed be we whom thou, so rich, befriendest. Full many a boon hast thou for men demolish those who present no gifts nor pour oblations.\n\np: As Indra thundering impels the rain-clouds, so doth he send us store of kine and horses. Thou art of old the Cherisher of singers let not the rich who bring no gifts deceive thee.\n\np: Adbyaryu, hero, bring to mighty Indrafor he is King thereof-the pressed-out juices; To him exalted by the hymns and praises, ancient and modern, of the singing Rsis.\n\np: In the wild joy of this hath Indra, knowing full many a form, struck down resistless Vrtras. Proclaim aloud to him the savoury Soma so that the Hero, strong of jawe may drink it.\n\np: May Indra drink this Soma poured to please him, and cheered therewith subdue Vrtra with his thunder. Come to  'our offering even from a distance, good lover of our songs, the bard's Supporter.\n\np: The cup whence Indra drinks the draught is present: the Amrta dear to Indra hath been drunken, that he may cheer the Deva.to gracious favour, and keep far from us hatred and affliction.\n\np: Therewith enraptured. Hero, subdue our foemen, the unfriendly, Maghavan be they kin or strangers, Those who still aim their hostile darts to smite us, turn them to flight, O Indra, crush and kill them.\n\np: O Indra Maghavan, in these our battles win easy paths for us and ample freedom. That we may gain waters and seed and offspring, set thou our princes on thy side, O Indra.\n\np: Let thy Bay Stallions, harnessed, bring thee hither, Steeds with strong chariot and strong reins to hold them, Strong Horses, speeding hither, bearing thunder, well-harnessed, for the stron exciting potion.\n\np: Beside the vat, Strong Deva. stand thy strong Horses, shining with holy oil, like waves exulting. Indra, they bring to thee, the Strong and Mighty, Soma of juices shed by mighty press-stones.\n\np: Thou art the Bull of earth, the Bull of heaven, Bull of the rivers, Bull of standing waters. For thee, the Strong, O Bull, hath Indu swollen. juice pleasant, sweet to drink, for thine election.\n\np: This Deva, with might, when first he had his being, with Indra for ally, held fast the Pani. This Indu stole away the warlike weapons, and foiled the arts of his malignant father.\n\np: The Dawns he wedded to a glorious Consort, and set within the Sun the light that lights him. He found in heaven, in the third lucid regions, the threefold Amrta in its close concealment.\n\np: He stayed and held the heaven and earth asunder: the chariot with the sevenfold reins he harnessed. This Soma Set with power within the milch-kine a spring whose ripe contents ten fingers empty.","people":["Indu","Indra","Soma","Vrtra","Maghavan","Deva"],"places":["Earth","Heaven"],"things":["Mankind","Cheer","Steeds","Lord","Rivers","Soma","Waters","Glory","Glorious","Offering","Light","Sun","Treasure","Wealth","Boon","Men","Might","Juice","Rain","Song","Joy","Offspring","Strong","Mighty","Praise","Form","Friends","Songs","Friend","Hero","King","Horses","Winning","Riches","Gifts","Amrta"],"groups":["Devas","Deities","Dawns","Father","Rsis","Vrtras"],"concepts":["Good","Holy","Strength","Offering","Giver","Glorious","Swift"],"hash":"md5-59HPoR+2luiEhk3e73E0bQ==","created":"Monday, April 8, 2024 - 10:51:54 PM"},{"id":"e6ab671e-7ab8-4261-84fe-b62268687b60","key":"06045","book":"06","title":"HYMN XLV. Indra.","link":"https://indra.ai/rigveda/hymns/06045.html","text":"p: THAT Indra is our youthful Friend, who with his trusty guidance led Turvasa, Yadu from afar.\n\np: Even to the dull and uninspired Indra, gives vital power, and wins Even with slow steed the offered prize.\n\np: Great are his ways of guiding us, andnanilbld are Ins eulogies: His kind protections never fail.\n\np: Friends, sing your psalm and offer praise to him to whom the prayer is brought: For our great Providence is he.\n\np: Thou, Slaughterer of Vrtra, art Guardian and Friend of one and two, Yea, of a man like one of us.\n\np: Beyond men's hate thou leadest us, and givest cause to sing thy praise: Good hero art thou called by men.\n\np: I call with hymns, as ’twere a cow to milk, the Friend who merits praise, the Brahman who accepts the prayer.\n\np: Him in whose hands they say are stored all treasure.s from the days of old, the Hero, conquering in the fight.\n\np: Lord of Strength, Caster of the Stone, destroy the firm forts built by men, and foil their arts, unbending Deva.\n\np: Thee, thee as such, O Lord of Power, O Indra, Soma-drinker, true, We, fain for glory, have invoked.\n\np: Such as thou wast of old, and art now to be called on when the prize lies ready, listen to our call.\n\np: With hymns and coursers we will gain, indra, through thee, both steeds and spoil Most glorious, and the proffered prize.\n\np: Thou, indra, Lover of the Song, whom men must stir to help, hast been Great in the contest for the prize.\n\np: Slayer of foes, whatever aid of thine imparts the swiftest course, with that impel our car to speed.\n\np: As skilfullest of those who drive the chariot, with our art and aim, O Conqueror, win the proffered prize.\n\np: Praise him who, Matchless and Alone, was born the Lord of living men, most active, with heroic soul.\n\np: Thou who hast been the singers' Friend, a friend auspicious with thine aid, as such, O Indra, favour us.\n\np: Grasp in thine arms the thunderbolt, O Thunder-armed, to subdue the fiends: Mayst thou subdue the foemen's host.\n\np: I call the ancient Friend, allied with wealth, who speeds the lowly manhim to whom chiefly prayer is brought.\n\np: For he alone is Lord of all the treasure.s of the earth: he speeds Hither, chief Lover of the Song.\n\np: So with thy yoked teams satisfy our wish with power and wealth in steeds And cattle, boldly, Lord of kine!\n\np: Sing this, what time the ' juice is pressed, to him your Hero, Much-invoked, to please him as a mighty Steer.\n\np: He, Excellent, withholdeth not his gift of power and wealth in kine, when he hath listened to our songs.\n\np: May he with might unclose for us the cow's stall, whosesoe’er it be, to which the Dasyu-slayer goes.\n\np: O Indra Satakratu, these our songs have called aloud to theelike mother cows to meet their calves.\n\np: Hard is thy love to win: thou art a Steer to him who longs for steers: Be to one craving steeds a Steed.\n\np: Delight thee with the juice we pour for thine own great munificence: Yield not thy singer to reproach.\n\np: These songs with every draught we pour come, Lover of the Song, to thee, as milch-kine hasten to their young\n\np: To thee most oft invoked, amid the many singers' rivalry Who beg with all their might for wealth.\n\np: Nearest and most attractiv. May our laud, O Indra come to thee. Urge thou us on to ample wealth.\n\np: Brbu hath set himself above the Panis, o’er their highest headlike the wide bush on Gan!ga's bank.\n\np: He whose good bounty, thousandfold, swift as the rushing of the wind, Suddenly offers as a gift.\n\np: So all our singers ever praise the pious Brbu's noble deed, Chief, best to give his thousands, best to give a thousand liberal gifts.","people":["Indra","Soma","Vrtra","Yadu","Turvasa","Satakratu","Deva"],"places":["Earth"],"things":["Milk","Steeds","Lord","Born","Soma","Glory","Glorious","Singer","Treasure","Wealth","Men","Might","Juice","Song","Help","Mighty","Car","Chief","Praise","Delight","Gift","Offers","Excellent","Friends","Songs","Friend","Hero","Cow","call","spoil","Cattle","Gifts"],"groups":["Dasyu","Steers","Mother","Panis","Man"],"concepts":["Good","Heroic","Love","Strength","Auspicious","Glorious","Swift","Noble"],"hash":"md5-b/4GiLIpBuF/JPms3NeoiA==","created":"Monday, April 8, 2024 - 10:51:54 PM"},{"id":"e270f681-e3d0-42ba-a773-5f18e7f6db14","key":"06046","book":"06","title":"HYMN XLVI. Indra.","link":"https://indra.ai/rigveda/hymns/06046.html","text":"p: THAT we may win us wealth and power we poets, verily, call on thee: In war men call on thee, indra, the hero's Lord, in the steed's race-course call on thee.\n\np: As such, O Wonderful, whose hand holds thunder, praised as mighty, Caster of the Stone! Pour on us boldly, indra, kine and chariotsteeds, ever to be the conqueror's strength.\n\np: We call upon that Indra, who, most active, ever subdues the foe: Lord of the brave, most Manly, with a thousand powers, help thou and prosper us in fight.\n\np: Rcisama, thou forcest men as with a bull, with anger, in the furious fray. Be thou our Helper in the mighty battle fought for sunlight, water, and for life.\n\np: O Indra, bring us name and fame, enriching, mightiest, excellent, Wherewith, O Wondrous Deva, fair-visored, thunder-armed, thou hast filled full this earth and heaven.\n\np: We call on thee, O King, Mighty amid the Devas, Ruler of men, to assist us. All that is weak in us, Excellent Deva, make firm: make our foes easy to subdue.\n\np: All strength and valour that is found, indra, in tribes of Nahusas, and all the splendid fame that the Five Tribes enjoy Bring, yea, all manly powers at once.\n\np: Or, Maghavan, what vigorous strength in Trksi lay, in Druhyus or in Paru's folk, Fully bestow on us, that, in the conquering fray, we may subdue our foes in fight.\n\np: O Indra, grant a happy home, a triple refuge triply strong. Bestow a dwelling-place on the rich lords and me, and keep thy dart afar from these.\n\np: They who with minds intent on spoil subdue the foe, boldly attack and smite him down. From these, O Indra Maghavan who lovest song, be closest guardian of our lives.\n\np: And now, O Indra, strengthen us: come near and aid us in the fight, what time the feathered shafts are flying in the air, the arrows with their sharpened points.\n\np: Give us, where heroes strain their bodies in the fight, the shelter that our fathers loved. To us and to our sons give refuge: keep afar all unobserved hostility.\n\np: When, indra, in the mighty fray thou urgest chargers to their speed, On the uneven road and on a toilsome path, like falcons, eager for renown,\n\np: Speeding like rivers rushing down a steep descent, responsive to the urging call, that come like birds attracted to the bait, held in by reins in both the driver's hands.","people":["Indra","Maghavan","Deva"],"places":["Earth","Heaven"],"things":["Lord","Rivers","Water","Air","Wealth","Men","Song","Help","Home","Strong","Mighty","Brave","Heroes","Excellent","Powers","Hero","King","call","spoil","Life"],"groups":["Devas","Fathers","Sons"],"concepts":["Life","Strength"],"hash":"md5-A2QbQ3qX5SLFFUAyOVvadg==","created":"Monday, April 8, 2024 - 10:51:54 PM"},{"id":"b084c7f2-de84-4f25-9ba8-b7ba3f2eab55","key":"06047","book":"06","title":"HYMN XLVII. Indra, Varuna, and Mitra.","link":"https://indra.ai/rigveda/hymns/06047.html","text":"p: YEA, this is good to taste and full of. sweetness, verily it is strong and rich in flavour. No on. May conquer Indra in the battle when he hath drunken of the draught we offer.\n\np: This sweet juice here had mightiest power to gladden: it boldened Indra when he siaughtered Vrtra, when he defeated Sambara's many onslaughts, and battered down his nineand ninety ramparts.\n\np: This stirreth up my voice when I have drunk it: this hath aroused from sleep my yearning spirit. This Sage hath measured out the six expanses from which no single creature. is excluded.\n\np: This, even this, is he who hath created the breadth of earth, the lofty height of heaven. He formed the nectar in three headlong rivers. Soma supports the wide mid-air above us.\n\np: He found the wavy sea of brilliant colours in forefront of the Dawns who dwell in brightness. This Mighty One, the Steer begirt by Maruts, hath propped the heavens up with a mighty pillar.\n\np: Drink Soma boldly from the beaker, indra, in war for treasure.s. Hero, Vrtra conquerer! Fill thyself full at the mid-day libation, and give us wealth, thou Treasury of riches.\n\np: Look out for us, O Indra, as our Leader, and guide us on to gain yet goodlier treasure.. Excellent Guardian, bear us well through peril, and lead us on to wealth with careful guidance.\n\np: Lead us to ample room, O thou who knowest, to happiness, security, and sunlight. High, indra, are the arms of thee the Mighty. May we betake. us to their lofty shelter.\n\np: Set us on widest chariot-seat, O Indra, with two steeds best to draw, O Lord of Hundreds! Bring us the best among all sorts of offerings: let not the foe's wealth, Maghavan, subdue us.\n\np: Be gracious, indra, let my days be lengthened: sharpen my thought as ’twere a blade of iron Approve whatever words I speak, dependent on thee, and grant me thy divine protection.\n\np: Indra the Rescuer, indra the Helper. Hero who listens at each invocation, Sakra I call, indra invoked of many. May Indra Maghavan prosper and bless us.\n\np: May helpful Indra as our good Protector, Lord of all treasure.s, favour us with assist, Baffle our foes, and give us rest and safety, an. May we be the lords of hero vigour.\n\np: May we enjoy the grace of him the Holy, yea. May we dwell in his auspicious favour. May helpful Indra as our good Preserver drive from us, even from afar, our foemen.\n\np: Like rivers rushing down a slope, O Indra, to thee haste songs and prayers and linked verses. Thou gatherest, Thunderer! like widespread bounty, kine, water, drops, and manifold libations.\n\np: Who lauds him, satisfies him, pays him worship? E’en the rich noble still hath found him mighty. With power, as when one moves his feet alternate, he makes the last precede, the foremost follow.\n\np: Famed is the Hero as each strong man's tamer, ever advancing one and then another. King of both worlds, hating the high and haughty, indra protects the men who are his people.\n\np: He loves no more the men he loved aforetime: he turns and moves away allied with others. Rejecting those who disregard his worship, indra victorious lives through many autumns.\n\np: In every figure he hath been the mode: this is his only form for us to look on. Indra moves multiform by his illusions; for his Bay Steeds are yoked, ten times a hundred.\n\np: Here Tvastar, yoking to the car the Bay Steeds, hath extended sway. Who will forever stand upon the foeman's side, even when our princes sit at ease?\n\np: Devas, we have reached a country void of pasture the land, though spacious, was too small to hold us. Narasamsa, provide in war for cattle; find a path, indra, for this faithful singer.\n\np: Day after day far from their seat he drove them, alike, from place to place, those darksome creatures. The Hero slew the meanly-huckstering Dasas, Varcin and Sambara, where the waters gather.\n\np: Out of thy bounty, indra, hath Prastoka bestowed ten coffers and ten mettled horses. We have received in turn from Divodasa Sambara's wealth, the gift of Atithigva.\n\np: Ten horses and ten treasure.-chests, ten garments as an added gift, these and ten lumps of gold have I received from Divodasa's hand.\n\np: Ten cars with extra steed to each, for the Atharvans hundred cows, Hath Asvatha to Payu given.\n\np: Thus Srnjaya's son honoured the Bharadvajas, recipients of all noble gifts and bounty.\n\np: Lord of the wood, be firm and strong in body: be, bearing us, a brave victorious hero Show forth thy strength, compact with straps of leather, and let thy rider win all spoils of battle.\n\np: Its mighty strength was borrowed from the heaven and earth: its conquering force was brought from sovrans of the wood. Honour with holy gifts the Car like Indra's bolt, the Car bound round with straps, the vigour of the floods.\n\np: Thou Bolt of Indra, Vanguard of the Maruts, close knit to Varuna and Child of Mitra. As such, accepting gifts which here we offer, receive, O Deva like Chariot, these oblations.\n\np: Send forth thy voice aloud through earth and heaven, and let the world in all its breadth regard thee; O Drum, accordant with the Devas and Indra, drive thou afar, yea, very far, our foemen.\n\np: Thunder out strength and fill us full of vigour: yea, thunder forth and drive away all dangers. Drive hence, O War-drum, drive away misfortune: thou art the Fist of Indra: show thy firmness.\n\np: Drive hither those, and these again bring hither: the War-drum speaks aloud as battle's signal. Our heroes, winged with horses, come together. Let our car-warriors, indra, be triumphant.","people":["Indra","Soma","Vrtra","Mitra","Varuna","Sakra","Maghavan","Narasamsa","Tvastar","Deva","Atithigva"],"places":["Earth","Heaven","Mid-Air"],"things":["Worship","Leader","Steeds","Lord","Rivers","Soma","Waters","Water","Singer","Air","Treasure","Wealth","Men","Juice","Gold","Strong","Mighty","Car","Voice","Brave","Heroes","Gift","Form","Excellent","People","Offerings","Libations","Songs","Drops","Hero","King","Sage","Horses","call","Riches","Cars","Cattle","Security","Spirit","Gifts"],"groups":["Devas","Maruts","Dawns","Son","Child","Man"],"concepts":["Good","Divine","Firm and Strong","Cars","Holy","Strength","Offerings","Auspicious","Libations","Noble"],"hash":"md5-o5EW6EYH02kmCjVGSbXXPw==","created":"Monday, April 8, 2024 - 10:51:54 PM"},{"id":"b40eaa84-c3bb-4a32-8680-874a3d5c3772","key":"06048","book":"06","title":"HYMN XLVIII. Agni and Others.","link":"https://indra.ai/rigveda/hymns/06048.html","text":"p: SING to your Agni with each song, at every offering, for strength. Come, let us praise the Wise and Everlasting Deva, even as a well-beloved Friend,\n\np: The Son of Strength; for is he not our gracious Lord? Let us serve him who bears our gifts. In battl. May he be our help and strengthener, yea, be the saviour of our lives.\n\np: Agni, thou beamest forth with light, great Hero, never changed by time. Shining, pure Agni! with a light that never fades, beam with thy fair beams brilliantly.\n\np: Thou worshippest great Devas: bring them without delay by wisdom and thy wondrous power. O Agni, make them turn hither to assist us. Give strength, and win it for thyself.\n\np: He whom floods, stones, and trees support, the offspring of eternal Law; He who when rubbed with force is brought to life by men upon the lofty height of earth;\n\np: He who hath filled both worlds fult with his brilliant shine, who hastens with his smoke to heaven; He made himself apparent through the gloom by night, the Red Bull in the darksome nights, the Red Bull in the darksome nights.\n\np: O Agni, with thy lofty beams, with thy pure brilliancy, O Deva, Kindled, most Youthful One! by Bharadvaja's hand, shine on us, O pure Deva, with wealth, shine, purifier! splendidly.\n\np: Thou art the Lord of house and home of all the tribes, O Agni, of all tribes of men. Guard with a hundred forts thy kindler from distress, through hundred winters, Youngest Deva. and those who make thy singers rich.\n\np: Wonderful, with thy favouring help, send us thy bounties, gracious Lord. Thou art the Charioteer, Agni, of earthly wealth: find rest and safety for our seed.\n\np: With guards unfailing never negligent speed thou our children and our progeny. Keep far from us, O Agni, all celestial wrath and wickedness of godless men.\n\np: Hither, O friends, with newest song drive her who freely pours her milk; Loose her who never turns away;\n\np: Who, for the host of Maruts bright with native sheen, hath shed immortal fame like milk. Whom the impetuous Maruts look upon with love, who moves in splendour on their ways.\n\np: For Bharadvaja she poured down in days of old The MilchCow yielding milk for all, and food that gives all nourishment.\n\np: Your friend like Indra passing wise, with magic power like Varuna. Like Aryaman joy-giving, bringing plenteous food like ViSnxu for my wish, I praise,\n\np: Bright as the host of Maruts mighty in their roar. May they bring Pusan free from foes; May they bring hither hundreds, thousands for our men. May they bring hidden stores to light, and make wealth easy to be found.\n\np: Haste to me, pusan, in thine car, bright Deity: I fain would speak: Most sinful is our foeman's hate.\n\np: Tear not up by the roots the Kakambira tree: destroy thou all malignity. Let them not snare by day the neck of that Celestial Bird the Sun.\n\np: Uninjured let thy friendship be, like the smooth surface of a skin, a flawless skin, containing curds, full to the mouth, containing curds.\n\np: For thou art high above mankind, in glory equal to the Devas. Therefore, O Pusan, look upon us in the fight: now help us as in days of old.\n\np: May the kind excellence of him the Kind, loud Roarers! be our guide, be it the Deva's, O Maruts, or a mortal man's who worships, ye impetuous Ones!\n\np: They whose high glory in a moment like the Deva, the Sun, goes round the space of heaven, the Maruts have obtained bright strength, a sacred name, strength that destroys the Vrtras, strength Vrtra-destroying excellent.\n\np: Once, only once, the heaven was made, once only once, the earth was formed- Once, only Prsni's milk was shed: no second, after this, is born.","people":["Indra","Vrtra","Agni","Varuna","Pusan","Deva","Aryaman"],"places":["Earth","Heaven"],"things":["Mankind","Milk","Lord","Born","Glory","Offering","Shine","Light","Sun","Wealth","Food","Men","Song","Joy","Help","Home","Wise","Offspring","Mighty","Car","Praise","Splendour","Excellent","Friends","Friend","Hero","Bird","Life","MilchCow","Gifts"],"groups":["Devas","Maruts","Son","Immortal","Progeny","Man","Vrtras"],"concepts":["Celestial","Life","Friendship","Love","Immortal","Sacred","Strength","Wisdom","Offering","Eternal Law"],"hash":"md5-xioXI7EOMLBxxo/+SKsU5w==","created":"Monday, April 8, 2024 - 10:51:54 PM"},{"id":"7b1231f8-dcab-4d1b-88bd-680156966382","key":"06049","book":"06","title":"HYMN XLIX, Devas.","link":"https://indra.ai/rigveda/hymns/06049.html","text":"p: I LAUD with newest songs the Righteous People, Mitra and Varuna who make us happy. Let them approach, here let them listen,Agni, Varuna, Mitra, Lords of fair dominion.\n\np: Him, to be praised at each tribe's offers, the Two young Matrons' sober-minded Herald, the Son of Strength, the Child of Heaven, the signal of offering, red Agni will I worship.\n\np: Unlike in form are the Red Deva's two Daughters: one is the Sun's, and stars bedeck the other. Apart, the Sanctifiers, in succession, come to the famed hymn, praised in holy verses.\n\np: I with a lofty song call hither Vayu, all-bounteous, filler of his car, most wealthy. Thou, Sage, with bright path, Lord of harnessed horses, impetuous, promptly honourest the prudent.\n\np: That chariot of the Asvins, fair to look on, pleaseth me well, yoked with a thought, refulgent, Wherewith, Nasatyas, Chiefs, ye seek our dwelling, to give new strength to us and to our children.\n\np: Bulls of the Earth, O Vata and Parjanya, stir up for us the regions of the water. Hearers of truth, ye, Sages, World-Supporters, increase his living wealth whose songs delight you.\n\np: May Sarasvati, the Hero's Consort, brisk with rare life, the lightning's Child, inspire us, and, with the Dames accordant, give the singer a refuge unassailable and flawless.\n\np: I praise with eloquence him who guards all pathways. He, when his love impelled him, went to Arka. May he vouchsafe us gear with gold to grace it. May Pusan make each prayer of ours efective.\n\np: May Herald Agni, fulgent, bring for worship Tvastar adored, in homes and swift to listen, Glorious, first to share, the life-bestower, the ever active Deva, fair-armed, fair-handed.\n\np: Rudra by day, Rudra at night we honour with these our songs, the Universe's Father. Him great and lofty, blissful, undecaying let us call specially as the Sage impels us.\n\np: Ye who are youthful, wise, and meet for worship, come, Martits, to the longing of the singer. Coming, as erst to Angiras, O Heroes, ye animate and quicken e’en the desert.\n\np: Even as the herdsman driveth home his cattle, I urge my songs to him the strong swift Hero May he, the glorious, lay upon his body the singer's hymns, as stars bedeck the heaven.\n\np: He who for man's behoof in his afiliction thrice measured out the earthly regions, Visnu- When one so great as thou affordeth shelter. May we with wealth and with ourselves be happy.\n\np: Sweet be this song of mine to Ahibudhnya, parvata, Savitar, with Floods and Lightnings; Sweet, with the Plants, to Devas who seek oblations. May liberal Bhaga speed us on to riches.\n\np: Give riches borne on cars, with many heroes, contenting men, the guard of mighty Order. Give us a lasting home that we may battle with godless bands of men who fight against us, and meet with tribes to whom the Devas are gracious.","people":["Agni","Angiras","Vayu","Visnu","Mitra","Varuna","Asvins","Nasatyas","Tvastar","Savitar","Pusan","Sarasvati","Bhaga","Deva","Vata","Parjanya","Ahibudhnya"],"places":["Earth","Heaven"],"things":["Worship","Lord","Water","Glorious","Singer","Offering","Sun","Wealth","Men","Song","Gold","Home","Wise","Strong","Mighty","Car","Praise","Delight","Hymn","Heroes","Form","Offers","People","Songs","Hero","Sage","Horses","call","Riches","Cars","Order","Cattle","Life"],"groups":["Devas","Dames","Father","Son","Child","Man"],"concepts":["Life","Cars","Love","Holy","Strength","Offering","Truth","Glorious","Swift"],"hash":"md5-kw5SPG0RNOmp90u0aF8glw==","created":"Monday, April 8, 2024 - 10:51:54 PM"},{"id":"1807dd57-a609-4f61-81ea-dce134de8d23","key":"06050","book":"06","title":"HYMN L, Devas.","link":"https://indra.ai/rigveda/hymns/06050.html","text":"p: I CALL with prayers on Aditi your Deva, on Agni, Mitra, Varuna for favour, On Aryaman who gives unasked, the gracious, on Devas who save, on Savitar and Bhaga.\n\np: Visit, to prove us free from sin, O Surya Lord of great might, the bright Devas sprung from Daksa, Twice-born and true, observing sacred duties, Holy and full of light, whose tongue is Agni.\n\np: And, O ye Heaven and Earth, a wide dominion, O ye most blissful Worlds, our lofty shelter, Give ample room and freedom for our dwelling, a home, ye Hemispheres, which non. May rival.\n\np: This day invite. May the Sons of Rudra, resistless, excellent, stoop down to meet us; For, when beset with slight or sore affliction, we ever call upon the Devas, the Maruts;\n\np: To whom the Deva Rodasi clings closely, whom Pusan follows bringing ample bounty. What time ye hear our call and come, O Maruts, upon your separate path all creatures tremble.\n\np: With a new hymn extol, O thou who singest, the Lover of the Song, the Hero Indra, may he, exalted, hear our invocation, and grant us mighty wealth and strength when lauded.\n\np: Give full protection, Friends of man, ye Waters, in peace and trouble, to our sons and grandsons. For ye are our most motherly physicians, parents of all that standeth, all that moveth.\n\np: May Savitar come hither and approach us, the Deva who rescues, Holy, goldenhanded, the Deva who, bounteous as the face of Morning, discloses precious gifts for him who worships.\n\np: And thou, O Son of Strength, do thou turn hither the Devas to-day to this our holy service. May I forevermore enjoy thy bounty and, Agni, by thy grace be rich in heroes.\n\np: Come also to my call, O ye Nasatyas, yea, verily, through my meditations, ye Holy Sages. As from great darkness ye delivered Atri, protect us, Chiefs, from danger in the conflict.\n\np: O Devas, bestow upon us riches, splendid with strength and heroes, bringing food in plenty. Be gracious, helpful Devas of earth, of heaven, born of the Cow, and dwellers in the waters.\n\np: May Rudra and Sarasvati, accordant, Visnu and Vayu, pour down gifts and bless us; Rbhuksan, Vaja, and divine Vidhatar, parjanya, Vata make our food abundant.\n\np: May this Deva Savitar, the Lord, the Offspring of Waters, pouring down his dew be gracious, and, with the Devas and Dames accordant, Tvastar; Dyaus with the Devas and Prthivi with oceans.\n\np: May Aja-Ekapad and Ahibudhnya, and Earth and Ocean hear our invocation; All Devas who strengthen Law, invoked and lauded, and holy texts uttered by sages, help us.\n\np: So with my thoughts and hymns of praise the children of Bharadvaja sing aloud to please you. The Dames invoked, and the resistless Vasus, and all ye Holy Ones have been exalted.","people":["Indra","Agni","Vayu","Visnu","Mitra","Varuna","Nasatyas","Tvastar","Savitar","Pusan","Sarasvati","Bhaga","Atri","Deva","Surya","Vata","Aditi","Rodasi","Vidhatar","Parjanya","Aja-Ekapad","Ahibudhnya","Daksa","Aryaman","Vaja","Prthivi","Rbhuksan"],"places":["Ocean","Earth","Heaven"],"things":["Holy Ones","Lord","Born","Waters","Light","Wealth","Food","Might","Song","Help","Home","Offspring","Mighty","Praise","Hymn","Heroes","Excellent","Friends","Hero","Cow","Parents","call","Riches","Morning","Gifts"],"groups":["Devas","Dyaus","Maruts","Sons","Dames","Son","Man","Vasus"],"concepts":["Divine","Holy","Sacred","Strength"],"hash":"md5-LO2j/pvxp10JSP3feY1uxw==","created":"Monday, April 8, 2024 - 10:51:54 PM"},{"id":"6f5b9b0c-163c-4503-8527-c7113d2828ec","key":"06051","book":"06","title":"HYMN LI, Devas.","link":"https://indra.ai/rigveda/hymns/06051.html","text":"p: THAT mighty eye of Varuna and Mitra, infallible and dear, is moving upward. The pure and lovely face of holy Order hath shone like gold of heaven in its arising.\n\np: The Sage who knows these Devas’ three ranks and orders, and all their generations near and distant, beholding good and evil acts of mortals, Sura marks well the doing of the pious.\n\np: I praise you Guards of mighty Law eternal, Aditi, Mitra, Varuna, the noble, Aryaman, Bhaga, all whose thoughts are faithful: hither I call the Bright who share in common.\n\np: Lords of the brave, infallible, foe-destroyers, great Kings, bestowers of fair homes to dwell in, Young. Heroes, ruling heaven with strong dominion, Adityas, Aditi I seek with worship.\n\np: O Heaven our Father, Earth our guileless Mother, O Brother Agni, and ye Vasus, bless us. Grant us, O Aditi and ye Adityas, all of one mind, your manifold protection.\n\np: Give us not up to any evil creature., as spoil to wolf or she-wolf, O ye Holy. For ye are they who guide aright our bodies, ye are the rulers of our speech and vigour.\n\np: Let us not suffer for the sin of others, nor do the deed which ye, O Vasus, punish. Ye, Universal Devas! are all-controllers. May he do harm unto himself who hates Me.\n\np: Mighty is homage: I adopt and use it. Homage hath held in place the earth and heaven. Homage to Devas! Homage commands and rules them. I banish even committed sin by homage\n\np: You Furtherers of Law, pure in your spirit, infallible, dwellers in the home of Order, to you all Heroes mighty and far-seeing I bow me down, O Holy Ones, with homage.\n\np: For these are they who shine with noblest splendour; through all our troubles these conduct us safely- Varuna, Mitra, Agni, mighty Rulers, trueminded, faithful to the hymn's controllers.\n\np: May they, Earth, Aditi, indra, Bhaga, pusan increase our laud, increase the Fivefold people. Giving good help, good refuge, goodly guidance, be they our good deliverers, good protectors.\n\np: Come now, O Devas, to your celestial station: the Bharadvajas' priest entreats your favour. He, sacrificing, fain for wealth, hath honoured the Devas vath those who sit and share oblations.\n\np: Agni, drive thou the wicked foe, the evil-hearted thief away, Far, far, Lord of the brave I and give us easy paths.\n\np: Soma, these pressing-stones have called aloud to win thee for our Friend. Destroy the greedy Pani, for a wolf is he.\n\np: Ye, O most bountiful, are they who, led by Indra, seek the sky. Give us good paths for travel: guard us ivell at home.\n\np: Now have we entered on the road that leads to bliss, without a foe, the road whereon a man escapes all enemies and gathers wealth.","people":["Indra","Soma","Agni","Mitra","Varuna","Pusan","Bhaga","Aditi","Aryaman"],"places":["Earth","Heaven","Sky"],"things":["Worship","Holy Ones","Lord","Soma","Law Eternal","Shine","Wealth","Gold","Help","Home","Strong","Mighty","Praise","Brave","Hymn","Heroes","Splendour","People","Pressing-Stones","Bliss","Friend","Sage","call","spoil","Order","Spirit"],"groups":["Devas","Kings","Father","Mother","Brother","Man","Vasus","Adityas"],"concepts":["Celestial","Good","Evil","Holy","Noble","Speech"],"hash":"md5-TD3cS1LE6+iEdu1KRpzp2g==","created":"Monday, April 8, 2024 - 10:51:54 PM"},{"id":"8b26bc96-7f27-464a-9d22-ac3e80f82d0e","key":"06052","book":"06","title":"HYMN LIL Devas.","link":"https://indra.ai/rigveda/hymns/06052.html","text":"p: THIS I allow not in the earth or heaven, at offering or in these holy duties. May the huge mountains crush him down: degraded be Atiyaja's sacrificing patron.\n\np: Or he who holds us in contempt, O Maruts, or seeks to blame the prayer that we are making, may agonies of burning be his portion. May the sky scorch the man who hates devotion.\n\np: Why then, O Soma, do they call thee keeper of prayer? Why then our guardian from reproaches? Why then beholdest thou how men revile us? Cast thy hot dart at him who hates devotion.\n\np: May Mornings as they spring to life, protect me, an. May the Rivers as they swell preserve me. My guardians be the firmly-seated mountains: the Fathers, when I call on Devas, defend me!\n\np: Through all our day. May we be healthy. minded, and look upon the Sun when he arises. Grant this the Treasure-Lord of treasure.s, coming, observant, oftenest of Devas, with assist!\n\np: Most near, most oft comes Indra with protection, and she Sarasvati, who swells with rivers - Parjanya, bringing health with herbs, and Agni, well lauded swift to listen, like a father.\n\np: Hear this mine invocation; come hither, O Universal Devas, be seated on this holy grass.\n\np: To him who comes to meet you, Devas, with offerings bathed in holy oil- Approach ye, one and all, to him.\n\np: All Sons of Immortality shall listen to the songs we sing, and be exceeding good to us.\n\np: May all the Devas who strengthen Law, with Rtus, listening to our call, be pleased with theit appropriate draught.\n\np: May Indra, with the Marut host, with Tvastar, Mitra, Aryaman, accept the laud and these our gifts.\n\np: O Agni, Monk, as rules ordain, offer this offering of ours, Remembering the Heavenly Folk.\n\np: Listen, All-Devas, to this mine invocation, Ye who inhabit heaven, and air's midregions, All ye, O Holy Ones, whose tongue is Agni, seated upon this sacred grass, be joyful.\n\np: May the All-Devas who claim our worship hear my thought. May the two World-halves hear it, and the Waters’ Child. Let me not utter words that y. May disregard. Closely allied with yo. May we rejoice in bliss.\n\np: And those who, Mighty, with the wiles of serpents, were born on earth, in heaven, where waters gather- May they vouchsafe us life of full duration. May the Devas kindly give us nights and mornings.\n\np: At this my call, O Agni and Parjanya, help, swift to hear, my thought and our laudation. One generates holy food, the other offspring, so grant us food enough with store of children.\n\np: When holy grass is strewn and fire enkindled, with hymn and lowly homage I invite you. All-Devas, to day in this our great assembly rejoice, ye Holy, in the gifts we offer.","people":["Indra","Soma","Agni","Mitra","Tvastar","Sarasvati","Parjanya","Aryaman"],"places":["Earth","Heaven","Sky"],"things":["Worship","Holy Ones","Lord","Born","Mountains","Rivers","Soma","Waters","Offering","Air","Sun","Treasure","Food","Men","Help","Offspring","Mighty","Grass","Hymn","Offerings","Bliss","Songs","call","Life","Gifts"],"groups":["Devas","Maruts","Marut","Fathers","Sons","Rtus","Father","Child","Man"],"concepts":["Good","Life","Heavenly","Immortality","Holy","Sacred","Offering","Offerings","Swift","Pleased"],"hash":"md5-GOnV6V1Lmjct9EF72AzVZg==","created":"Monday, April 8, 2024 - 10:51:54 PM"},{"id":"25509dd9-7583-48e0-8e2a-bcb3fd8094be","key":"06053","book":"06","title":"HYMN LIII. Pusan.","link":"https://indra.ai/rigveda/hymns/06053.html","text":"p: LORD of the path, O Pusan, we have yoked and bound thee to our hymn, Even as a car, to win the prize.\n\np: Bring us the wealth that men require, a manly master of a house, free-handed with the liberal meed.\n\np: Even him who would not give, do thou, O glowing Pusan, urge to give, and make the niggard's soul grow soft.\n\np: Clear paths that we may win the prize; scatter our enemies afar. Strong Deva, be all our thoughts fulfilled.\n\np: Penetrate with an awl, O Sage, the hearts of avaricious churls, and make them subject to our will.\n\np: Thrust with thine awl, O Pusan: seek that which the niggard's heart holds dear, and make him subject to our will.\n\np: Tear up and read in pieces, Sage, the hearts of avaricious churls, and make them subject to our will.\n\np: Thou, glowing Pusan, carriest an awl that urges men to prayer; Therewith do thou tear up and rend to shreds the heart of every one.\n\np: Thou bearest, glowing Lord! a goad with horny point that guides the cows Thence do we seek thy gift of bliss.\n\np: And make this hymn of ours produce kine, horses, and a store of wealth For our delight and use as men.","people":["Pusan","Deva"],"places":[],"things":["Master","Lord","Wealth","Men","Strong","Car","Delight","Hymn","Gift","Bliss","Sage","Horses"],"groups":[],"concepts":[],"hash":"md5-EuHyFWjD2TJ2b9t0uciyVA==","created":"Monday, April 8, 2024 - 10:51:54 PM"},{"id":"bec38525-52e9-480f-a50d-dbe31bf8ab68","key":"06054","book":"06","title":"HYMN LIV. Pusan.","link":"https://indra.ai/rigveda/hymns/06054.html","text":"p: O PUSAN, bring us to the man who knows, who shall direct us straight, and say unto us, It is here.\n\np: May we go forth with Pusan who shall point the houses out to us, and say to us, these same are they.\n\np: Unharmed is Pusan's chariot wheel; the box ne’er falleth to the ground, Nor doth the loosened felIy shake.\n\np: Pusan forgetteth not the man who serveth him with offered gift: That man is first to gather wealth.\n\np: May Pusan follow near our kine. May Pusan keep our horses safe: May Pusan gather gear for us.\n\np: Follow the kine of him who pours libations out and worships thee; And ours who sing thee songs of praise.\n\np: Let none be lost, none injured, none sink in a pit and break a limb. Return with these all safe and sound.\n\np: Pusan who listens to our meditations, the Strong whose wealth is never lost, the Lord of riches, we implore.\n\np: Secure in thy protecting care, O Pusan, neve. May we fail. We here are they who sing thy praise.\n\np: From out the distance, far and wide. May Pusan stretch his right hand forth, and drive our lost again to us.","people":["Pusan"],"places":[],"things":["Lord","Wealth","Strong","Praise","Gift","Libations","Songs","Horses","Riches","Wheel"],"groups":["Man"],"concepts":["Libations"],"hash":"md5-ceV1tPExkvoWkVpo9h8Dlw==","created":"Monday, April 8, 2024 - 10:51:54 PM"},{"id":"d75d7e64-177c-41ab-98e8-8cc4bfa552c5","key":"06055","book":"06","title":"HYMN LV. Pusan.","link":"https://indra.ai/rigveda/hymns/06055.html","text":"p: SON of Deliverance, come, bright Deva. Let us twain go together: be our charioteer of offering.\n\np: We meditate for wealth to thee most skilled of charioteers, with braided hair, Lord of great riches, and our Friend.\n\np: Bright Deva whose steeds are goats, thou art a stream of wealth, a treasure.-heap, the Friend of every pious man.\n\np: Pusan, who driveth goats for steeds, the strong and Mighty, who is called His Sister's lover, will we laud.\n\np: His Mother's suitor I address. May he who loves his Sister hear, Brother of Indra, and my Friend.\n\np: May the sure-footed goats come nigh, conveying Pusan on his car, the Deva who visiteth mankind.","people":["Indra","Pusan","Deva"],"places":[],"things":["Mankind","Steeds","Lord","Offering","Treasure","Wealth","Stream","Strong","Mighty","Car","Friend","Riches"],"groups":["Mother","Son","Brother","Sister","Man"],"concepts":["Offering"],"hash":"md5-Lhyq1E+TTC2AxhNbGV7NtA==","created":"Monday, April 8, 2024 - 10:51:54 PM"},{"id":"75c62c4c-b048-4239-835a-38a3b9e3fb0a","key":"06056","book":"06","title":"HYMN LVI, pusan.","link":"https://indra.ai/rigveda/hymns/06056.html","text":"p: WHOSO remembers Pusan as cater of mingled curd and meal Need think no more upon the Deva.\n\np: And he is best of charioteers. Indra, the hero's Lord, allied With him as Friend, destroys the foes.\n\np: And there the best of charioteers hath guided through the speckled cloud The golden wheel of Sura's car.\n\np: Whate’er we speak this day to thee, Wise, Wondrous Deva whom many praise, Give thou fulfilment of our thought.\n\np: Lead on this company of ours, that longs for kine, to win the spoil: Thou, pusan, art renowned afar.\n\np: Prosperity we crave from thee, afar from sin and near to wealth, Tending to perfect happiness both for to. morrow and to-day.","people":["Indra","Pusan","Deva"],"places":[],"things":["Lord","Wealth","Wise","Car","Praise","Friend","Hero","spoil","Wheel"],"groups":[],"concepts":[],"hash":"md5-Ibvp5oIewl3pTZ9pMjluxw==","created":"Monday, April 8, 2024 - 10:51:54 PM"},{"id":"95cb2c60-3818-44ce-9c65-a69d6a6a3880","key":"06057","book":"06","title":"HYMN LVII. Indra and Pusan.","link":"https://indra.ai/rigveda/hymns/06057.html","text":"p: INDRA and Pusan will we call for friend ship and prosperity And for the winning of the spoil.\n\np: One by the Soma sits to drink juice which the mortar hath expressed: The other longs for curd and meal.\n\np: Goats are the team that draws the one: the other hath Bay Steeds at hand; With both of these he subdues the fiends.\n\np: When Indra, wondrous strong, brought down the streams, the mighty waterfloods, pusan was standing by his side.\n\np: To this, to Pusan's favouring love, and Indra's. May we closely cling, as to a tree's extended bough.\n\np: As one who drives a car draws in his reins. May we draw Pusan near, and Indra, for our great success.","people":["Indra","Soma","Pusan"],"places":[],"things":["Steeds","Soma","Streams","Juice","Strong","Mighty","Car","Friend","Winning","call","spoil"],"groups":[],"concepts":["Love"],"hash":"md5-tKyMAlQtByqzxEvqizfsCQ==","created":"Monday, April 8, 2024 - 10:51:54 PM"},{"id":"7a918058-0042-439e-801b-81c57e4ae538","key":"06058","book":"06","title":"HYMN LVIII. Pusan.","link":"https://indra.ai/rigveda/hymns/06058.html","text":"p: LIKE heaven art thou: one form is bright, one holy, like Day and Night dissimilar in colour. All magic powers thou aidest, self-depen. dent! Auspicious be thy bounty here, O Pusan.\n\np: Goat-borne, the guard of cattle, he whose home is strength, inspirer of the hymn, set over all the world; Brandishing here and there his lightly. moving goad, beholding every creature., pusan, Deva, goes forth.\n\np: O Pusan, with thy golden ships that travel across the ocean, in the air's mid-region, Thou goest on an embassy to Surya, subdued by love, desirous of the glory.\n\np: Near kinsman of the heaven and earth is Pusan, liberal, Lord of food, of wondrous iustre, whom strong and vigorous and swiftlymoving, subdued by love, the Deities gave to Surya.","people":["Pusan","Deva","Surya"],"places":["Ocean","Earth","Heaven"],"things":["Lord","Glory","Air","Food","Home","Strong","Hymn","Form","Powers","Cattle"],"groups":["Deities"],"concepts":["Love","Holy","Strength","Auspicious"],"hash":"md5-OaNzgVyW5dzAunMCQB5CrA==","created":"Monday, April 8, 2024 - 10:51:54 PM"},{"id":"926fa3a3-33f5-4f1a-a9af-7c7769f00993","key":"06059","book":"06","title":"HYMN LIX. Indra and Agni.","link":"https://indra.ai/rigveda/hymns/06059.html","text":"p: I WILL declare, while juices flow, the manly deeds that ye have done: Your Fathers, enemies of Devas, were smitten down, and, indra and Agni, ye survive.\n\np: Thus, indra and Agnip verily your greatness merits loftiest praise, Sprung from one common Father, brothers, twins are ye; your Mother is in every place.\n\np: These who delight in flowing juice, like fellow horses at their food, indra and Agni, Devas armed with the thunderbolt, we call this day to come with help.\n\np: Indra and Agni, Friends of Law, served with rich gifts, your speech is kind To him who praises you while these libations flow: that man, O Devas, ye ne’er consume.\n\np: What mortal understands, O Devas, indra and Agni, this your way? One of you, yoking Steeds that move to every side, advances in your common car.\n\np: First, indra and Agni, hath this Maid come footless unto those with feet. Stretching her head and speaking loudly with her tongue, she hath gone downward thirty steps.\n\np: E’en now, O Indra and Agni, men hold in their arms and stretch their bows. Desert us not in this great fray, in battles for the sake of kine.\n\np: The foeman's sinful enmities, indra and Agni, vex me sore. Drive those who hate me far away, and keep them distant from the Sun.\n\np: Indra and Agni, yours are all the treasure.s of the heavens and earth. Here give ye us the opulence that prospers every living man.\n\np: O Indra and Agni, who accept the laud, and hear us for our praise, Come near us, drawn by all our songs, to drink of this our Soma juice.","people":["Indra","Soma","Agni"],"places":["Earth"],"things":["Steeds","Soma","Sun","Treasure","Food","Men","Flow","Juice","Help","Car","Praise","Delight","Libations","Friends","Songs","Horses","call","Gifts"],"groups":["Devas","Fathers","Maid","Father","Mother","Man"],"concepts":["Libations","Speech"],"hash":"md5-GrXsfDQC3AGZ5MSyEj0r7w==","created":"Monday, April 8, 2024 - 10:51:54 PM"},{"id":"05c8b9e6-5b91-40b4-8500-525d6fabb56f","key":"06060","book":"06","title":"HYMN LX. Indra and Agni.","link":"https://indra.ai/rigveda/hymns/06060.html","text":"p: HE subdues the foe and wins the spoil who worships Indra and Agni, strong and mighty Heroes, who rule as Sovrans over ample riches, victorious, showing forth their power in conquest.\n\np: So battle now, O Indra and thou, Agni, for cows and waters, sunlight, stolen Mornings. Team-borne, thou makest kine thine own, O Agni: thou, indra, light, Dawns, regions, wondrous waters.\n\np: With Vrtra-subduing might, indra and Agni, come, drawn by homage, O ye Vrtra conquerers. Indra and Agni, show yourselves among us with your supreme and unrestricted bounties.\n\np: I call the Twain whose deeds of old have all been famed in ancient days O Indra and Agni, harm us not.\n\np: The Strong, the scatterers of the foe, indra and Agni, we invoke; May they be kind to one like me.\n\np: They subdue our Arya foes, these Lords of heroes, subdue our Dasyu foes And drive our enemies away.\n\np: Indra and Agni, these our songs of praise have sounded forth to you: Ye who bring blessings! drink the juice.\n\np: Come, indra and Agni, with those teams, desired of many, which ye have, O Heroes, for the worshipper.\n\np: With those to this libation poured, ye Heroes, indra and Agni, come: Come ye to drink the Soma juice.\n\np: Glorify him who compasses all forests with his glowing flame, and leaves them blackened with his tongue.\n\np: He who gains Indra's bliss with fire enkindled finds an easy way Over the floods to happiness.\n\np: Give us fleet coursers to convey Indra and Agni, and bestow Abundant strengthening food on us.\n\np: Indra and Agni, I will call you hither and make you joyful with the gifts I offer. Ye Twain are givers both of food and riches: to win me strength and vigour I invoke you.\n\np: Come unto us with riches, come with wealth in horses and in kine. Indra and Agni, we invoke you both, the Devas, as Friends for friendship, bringing bliss.\n\np: Indra and Agni, hear his call who worships. with libations poured. Come and enjoy the offerings, drink the sweetly-flavoured Soma juice.","people":["Indra","Soma","Vrtra","Agni"],"places":[],"things":["Soma","Waters","Light","Wealth","Food","Might","Juice","Strong","Mighty","Praise","Worshipper","Heroes","Offerings","Libations","Friends","Bliss","Songs","Horses","call","spoil","Riches","Gifts"],"groups":["Devas","Dasyu","Dawns"],"concepts":["Friendship","Blessings","Strength","Offerings","Libations"],"hash":"md5-PTlkrjKMRDS4XPHvz7NqtQ==","created":"Monday, April 8, 2024 - 10:51:54 PM"},{"id":"2852c923-23ae-48d4-9e59-086a4c78452f","key":"06061","book":"06","title":"HYMN LXI. Sarasvati.","link":"https://indra.ai/rigveda/hymns/06061.html","text":"p: To Vadhryasva when. be worshipped her with gifts she gave fierce Divodasa, canceller of debts. Consumer of the churlish niggard, one and all, thine, O Sarasvati, are these effectual boons.\n\np: She with her might, like one who digs for lotus-stems, hath burst with her strong waves the ridges of the hills. Let us invite with songs and holy hymns for help Sarasvati who slayeth the Paravatas.\n\np: Thou castest down, Sarasvati, those who scorned the Devas, the brood of every Brsaya skilled in magic arts. Thou hast discovered rivers for the tribes of men, and, rich in wealth! made poison flow away from them.\n\np: May the divine Sarasvati, rich in her wealth, protect us well, Furthering all our thoughts with might\n\np: Whoso, divine Sarasvati, invokes thee where the prize is setlike Indra when he smites the foe.\n\np: Aid us, divine Sarasvad, thou who art strong in wealth and power Like Pusan, give us opulence.\n\np: Yea, this divine Sarasvati, terrible with her golden path, Foe-slayer, claims our eulogy.\n\np: Whose limitless unbroken flood, swift-moving with a rapid rush, Comes onward with tempestuous roar.\n\np: She hath spread us beyond all foes, beyond her Sisters, Holy One, as Surya spreadeth out the days.\n\np: Yea, she most dear amid dear stream, Seven-sistered, graciously inclined, Sarasvati hath earned our praise.\n\np: Guard us from hate Sarasvati, she who hath filled the realms of earth, and that wide tract, the firmament!\n\np: Seven-sistered, sprung from threefold source, the Five Tribes' prosperer, she must be Invoked in every deed of might.\n\np: Marked out by majesty among the MightyOnes, in glory swifter than the other rapid Streams, Created vast for victory like a chariot, Sarasvati must be extolled by every sage.\n\np: Guide us, Sarasvati, to glorious treasure.: refuse us not thy milk, nor spurn us from thee. Gladly accept our friendship and obedience: let us not go from thee to distant countries.   ","people":["Indra","Pusan","Sarasvati","Surya"],"places":["Earth","Firmament"],"things":["Victory","Milk","Rivers","Glory","Glorious","Treasure","Wealth","Men","Streams","Stream","Flow","Might","Help","Strong","Praise","Songs","Sage","Gifts"],"groups":["Devas","MightyOnes"],"concepts":["Divine","Friendship","Holy","Worshipped","Glorious","Swift"],"hash":"md5-n3IfBVChU00/+MT4WowhJg==","created":"Monday, April 8, 2024 - 10:51:54 PM"},{"id":"2b233977-8cd8-4cb7-84f6-b2c93194ca7d","key":"06062","book":"06","title":"HYMN LXII. Asvins.","link":"https://indra.ai/rigveda/hymns/06062.html","text":"p: I LAUD the Heroes Twain, this heaven's Controllers: singing with songs of praise I call the Asvins, fain in a moment, when the morns are breaking, to part the earth's ends and the spacious regions.\n\np: Moving to offering through realms of lustre they light the radiance of the car that bears them. Traversing many wide unmeasured spaces, over the wastes ye pass, and fields, and waters.\n\np: Ye to that bounteous path of yours, ye mighty, have ever borne away our thoughts with horses, Mind-swift and full of vigour, that the trouble of man who offers gifts might cease and slumber.\n\np: So ye, when ye have yoked your chariothorses, come to the hymn of the most recent singer. Our true and ancient Herald Monk shall bring you, the Youthful, bearing splendour, food, and vigour.\n\np: With newest hymn I call those Wonder-Workers, ancient and brilliant, and exceeding mighty, Bringers of bliss to him who lauds and praises, bestowing varied bounties on the singer.\n\np: So ye, with birds, out of the sea and waters bore Bhujyu, son of Tugra, through the regions. Speeding with winged steeds through dustless spaces, out of the bosom of the flood they bore him.\n\np: Victors, car-borne, ye rent the rock asunder: Bulls, heard the calling of the eunuch's consort. Bounteous, ye filled the cow with milk for Sayu: thus, swift and zealous Ones, ye showed your favour.\n\np: Whate’er from olden time. Heaven, Earth! existeth great object of the wrath of Devas and mortals, make that, Adityas, Vasus, sons of Rudra, an evil brand to one allied with demons.\n\np: May he who knows, as Varuna and Mitra, air's realm, appointing both the Kings in season, Against the secret fiend cast forth his weapon, against the lying words that strangers utter.\n\np: Come to our home with friendly wheels, for offipring; come on your radiant chariot rich in heroes. Strike off, ye Twain, the heads of our assailants who with man's treacherous attack approach us.\n\np: Come hitherward to us with teams of horses, the highest and the midmost and the lowest. Bountiful Lords, throw open to the singer doors e’en of the firm-closed stall of cattle.","people":["Mitra","Varuna","Asvins","Tugra","Sayu"],"places":["Earth","Heaven"],"things":["Milk","Steeds","Waters","Singer","Offering","Light","Air","Food","Might","Home","Mighty","Car","Praise","Hymn","Heroes","Splendour","Offers","Bliss","Songs","Cow","Horses","call","Cattle","Gifts"],"groups":["Devas","Sons","Kings","Son","Man","Vasus","Adityas"],"concepts":["Evil","Wonder-Workers","Offering","Swift"],"hash":"md5-e7Pqk70n82NCv35wkmxngA==","created":"Monday, April 8, 2024 - 10:51:54 PM"},{"id":"ecba9e90-d85b-42df-b8bb-8793285137d3","key":"06063","book":"06","title":"HYMN LXIII. Asvins.","link":"https://indra.ai/rigveda/hymns/06063.html","text":"p: WHERE hath the hymn with reverence, like an envoy, found both fair Devas to-day, invoked of many- Hymn that hath brought the two Nasatyas hither? To this man's thought be ye, both Devas, most friendly.\n\np: Come readily to this mine invocation, lauded with songs, that y. May drink the juices. Compass this house to keep it from the foeman, that non. May force it, either near or distant.\n\np: Juice in wide room hath been prepared to feast you: for you the grass is strewn, most soft to tread on. With lifted hands your servant hath adored you. Yearningfor you the press-stones shed the liquid.\n\np: Agni uplifts him at y 'our offerings: forth goes the oblation dropping oil and glowing. Up stands the grateful-minded priest, elected, appointed to invoke the two Nasatyas.\n\np: Lords of great wealth! for glory, Surya's Daughter mounted your car that brings a hundred assists. Famed for your magic arts were ye, magicians! amid the race of Devas, ye dancing Heroes!\n\np: Ye Twain, with these your glories fair to look on, brought, to win victory, rich gifts for Surya. After you flew your birds, marvels of beauty: dear to our hearts! the song, well lauded, reached you.\n\np: May your winged coursers, best to draw. Nasatyas! convey you to the object of your wishes. Swift as the thought, your car hath been sent onward to food of many a sort and dainty offerings.\n\np: Lords of great wealth, manifold is your bounty: ye filled our cow with food that never faileth. Lovers of sweetness! yours are praise and singers, and poured libations which have sought your favour.\n\np: Mine were two mares of Puraya, brown, swift-footed; a hundred with Sumidha, food with Peruk Sanda gave ten gold-decked and well-trained horses, tame and obedient and of lofty stature.\n\np: Nasatyas! Purupanthas offered hundreds, thousands of steeds to him who sang your praises, Gave. Heroes! to the singer Bharadvaja. Ye-Wonder-Workers, let the fiends be slaughtered.\n\np: May I with princes share your bliss in freedom.","people":["Agni","Nasatyas","Surya"],"places":[],"things":["Victory","Steeds","Reverence","Glory","Singer","Wealth","Food","Juice","Song","Beauty","Gold","Grass","Car","Praise","Hymn","Heroes","Offerings","Libations","Bliss","Songs","Cow","Horses","Gifts"],"groups":["Devas","Man"],"concepts":["Wonder-Workers","Offerings","Libations","Swift"],"hash":"md5-pnNWersEg80O1jgt48HP+w==","created":"Monday, April 8, 2024 - 10:51:55 PM"},{"id":"9c0c452d-482c-49c9-a1ff-99b6d3d6b051","key":"06064","book":"06","title":"HYMN LXIV. Dawn.","link":"https://indra.ai/rigveda/hymns/06064.html","text":"p: THE radiant Dawns have risen up for glory, in their white splendour like the waves of waters. She maketh paths all easy, fair to travel, and, rich, hath shown herself benign and friendly.\n\np: We see that thou art good: far shines thy lustre; thy beams, thy splendours have flown up to heaven. Decking thyself, thou makest bare thy bosom, shining in majesty, thou Deva Morning.\n\np: Red are the kine and luminous that bear her the Blessed One who spreadeth through the distance. The foes she chaseth like a valiant archer, like a swift warrior she repelleth darkness.\n\np: Thy ways are easy on the hills: thou passest Invincible! Se1f-luminous! through waters. So lofty Deva with thine ample pathway, Daughter of Heaven, bring wealth to give us comfort.\n\np: Dawn, bring me wealth: untroubled, with thine oxen thou bearest riches at thy will and pleasure; Thou who, a Deva, Child of Heaven, hast shown thee lovely through bounty when we called thee early.\n\np: As the birds fly forth from their restingplaces, so men with store of food rise at thy dawning. Yea, to the liberal mortal who rernaineth at home, O Deva Dawn, much good thou bringest.","people":["Deva","Dawn"],"places":["Heaven"],"things":["Waters","Glory","Wealth","Food","Men","Home","Splendour","Warrior","Riches","Morning"],"groups":["Dawns","Child"],"concepts":["Good","Swift"],"hash":"md5-UpLIDVvt0hoZ3waxZ1KiSw==","created":"Monday, April 8, 2024 - 10:51:55 PM"},{"id":"7bfd7287-1c01-4a51-8ae1-aee4d3d4a4de","key":"06065","book":"06","title":"HYMN LXV. Dawn.","link":"https://indra.ai/rigveda/hymns/06065.html","text":"p: SHEDDING her light on human habitations this Child of Heaven hath called us from our slumber; She who at night-time with her argent lustre hath shown herself e’en through the shades of darkness.\n\np: All this with red-rayed steeds have they divided: the Dawns on bright cars shine in wondrous fashion. They, bringing near the stately rite's commencement, drive far away the night's surrounding shadows.\n\np: Dawns, bringing hither, to the man who worships, glory and power and might and food and vigour, Opulent, with imperial sway like heroes, favour your servant and this day enrich him.\n\np: Now is there treasure. for the man who serves you, now for the hero, Dawns! who brings oblation; Now for the singer when he sings the praise-song. Even to one like me ye brought aforetime.\n\np: O Dawn who standest on the mountain ridges, Angirases now praise thy stalls of cattle. With prayer and holy hymn they burst them open: the heroes' calling on the Devas was fruitful.\n\np: Shine on us as of old, thou Child of Heaven,on him, rich Maid! who serves like Bharadvaja. Give to the singer wealth with noble heroes, and upon us bestow wide-spreading glory.","people":["Dawn"],"places":["Heaven"],"things":["Steeds","Glory","Singer","Shine","Light","Treasure","Wealth","Food","Might","Song","Praise","Hymn","Heroes","Hero","Cars","Cattle"],"groups":["Devas","Dawns","Human","Maid","Child","Angirases","Man"],"concepts":["Cars","Holy","Noble"],"hash":"md5-Cn+7MZp4RhGQ0t7Ibj6ZnQ==","created":"Monday, April 8, 2024 - 10:51:55 PM"},{"id":"e5850f0a-d865-42c5-94f7-09cff592385a","key":"06066","book":"06","title":"HYMN LXVI. Maruts.","link":"https://indra.ai/rigveda/hymns/06066.html","text":"p: E'EN to the wise let that be still a wonder to which the general name of Cow is given. The one hath swelled among mankind for milking: Prsni hath drained but once her fair bright udder.\n\np: They who like kindled flames of fire are glowing. the Maruts, twice and thrice have waxen mighty. Golden and dustless were their cars, invested with their great strength and their heroic vigour.\n\np: They who are Sons of the rain-pouring Rudra, whom the long-lasting One had power to foster: The MightyOnes offerings known to have received for man's advantage.\n\np: They shrink not from the birth; in this same manner still resting there they purge away reproaches. When they have streamed forth, brilliant, at their pleasure, with their own splendour they bedew their bodies.\n\np: Even those who bear the brave bold name of Maruts, whom not the active quickly wins. Even the liberal wards not off those fierce ones, those who are light and agile in their greatness.\n\np: When, strong in strength and armed with potent weapons, they had united wellformed earth and heaven, Rodasl stood among these furious Heroes like splendour shining with her native brightness.\n\np: No team of goats shall draw your car, O Maruts, no horse no charioteer be he who drives it. Halting not, reinless, through the air it travels, speeding alone its paths through earth and heaven.\n\np: Non. May obstruct, none overtake, O Maruts, him whom ye assist in the strife of battle For sons and progeny, for kine and waters: he bursts the cow-stall on the day of trial.\n\np: Bring a bright hymn to praise the band of Maruts, the Singers, rapid, strong in native vigour, who conquer mighty strength with strength more mighty: earth shakes in terror at their wars, O Agni.\n\np: Bright like the flashing flames of offers, like tongues of fire impetuous in their onset, Chanting their psalm, singing aloud, like heroes, splendid from birth, invincible, the Maruts.\n\np: That swelling band I call with invocation, the brood of Rudra, armed with glittering lances. Pure hymns are meet for that celestial army: like floods and mountains have the Strong Ones battled.","people":["Agni","Rodasl"],"places":["Earth","Heaven"],"things":["Mankind","Mountains","Waters","Light","Air","Rain","Wise","Strong","Mighty","Car","Praise","Brave","Hymn","Heroes","Splendour","Offers","Offerings","Cow","Horse","call","Cars"],"groups":["Maruts","Sons","Progeny","MightyOnes","Man"],"concepts":["Celestial","Birth","Heroic","Cars","Strength","Offerings"],"hash":"md5-GlZKuRW6kNgls0H0Ok21Xw==","created":"Monday, April 8, 2024 - 10:51:55 PM"},{"id":"2836e79d-217b-47cf-a15e-1633a1b8228b","key":"06067","book":"06","title":"HYMN LXVIL Mitra and Varuna.","link":"https://indra.ai/rigveda/hymns/06067.html","text":"p: NOW Mitra and Varuna shall be exalted high by your songs, noblest of all existing; They who, as ’twere with reins are best Controllers, unequalled with their arms to check the people.\n\np: To you Two Devas is this my thought extended, turned to the sacred grass with loving homage. Give us, O Mitra and Varuna, a dwelling safe from attack, which ye shall guard, Boon-Givers!\n\np: Come hither, Mitra and Varuna, invited with eulogies and loving adoration, Ye who with your might, as Work-Controllers, urge even men who quickly hear to labour.\n\np: Whom, of pure origin, like two strong horses, Aditi bore as babes in proper season, whom, Mighty at your birth, the Mighty Deva brought forth as terrors to the mortal foeman.\n\np: As all the Devas in their great joy and gladness gave you with one accord your high dominion, as ye surround both worlds, though wide and spacious your spies are ever true and never bewildered.\n\np: So, through the days maintaining princely power. ye prop the height as ’twere from loftiest heaven. The Star of all the Devas, established, filleth the heaven and earth with food of man who liveth.\n\np: Take the strong drink, to quaff till ye are sated, when he and his attendants fill the chamber. The young Maids brook not that none seeks to win them, when, Quickeners of all! they scatter moisture.\n\np: So with your tongue come ever, when your envoy, faithful and very wise, attends our worship. Nourished by holy oil! he this yGur glory: annihilate  'theofferings trouble.\n\np: When, They strive against you and break tlie friendly laws ye have established, they, neither Devas nor men in estimation, like Api's sons have godless offers.\n\np: When singers in their song uplift their voices, some chant the Nivid texts with steady purpose. The. May we sing you lauds that shall be fruitful: dp ye not rival all the Devas in greatness?\n\np: O Mitra and Varuna. May your large bounty come to us hither, near to this our dwelling, when the kine haste to us, and when they harness the fleet-foot mettled stallion for the battle.","people":["Mitra","Varuna","Deva","Attendants","Aditi"],"places":["Earth","Heaven"],"things":["Worship","Work","Glory","Boon","Food","Men","Might","Song","Joy","Wise","Strong","Mighty","Grass","Offers","People","Songs","Horses"],"groups":["Devas","Sons","Man"],"concepts":["Birth","Holy","Sacred"],"hash":"md5-X9VnuP5IfVRHWixnK9Z3pA==","created":"Monday, April 8, 2024 - 10:51:55 PM"},{"id":"0887b228-f169-47b3-9229-cfbce6237531","key":"06068","book":"06","title":"HYMN LXVIII. Indra-Varuna.","link":"https://indra.ai/rigveda/hymns/06068.html","text":"p: HIS honouring rite whose grass is trimmed is offered swiftly to you, in Manu's wise, accordant, the rite which Indra-Varuna shall carry this day to high success and glorious issue.\n\np: For at Devas’ worship they are best through vigour; they have become the strongest of the Heroes; With mighty strength, most liberal of the Princes, Chiefs of the host.\n\np: Praise those Twain Devas for powers that merit worship, indra and Varuna, for bliss, the joyous. One with his might and thunderbolt the other as a Sage stands near in troubles.\n\np: Though dames and men have waxen strong and mighty, and all the Devas selfpraised among the Heroes, Ye, indra-Varuna, have in might surpassed them, and thus were ye spread wide, O Earth and Heaven.\n\np: Righteous is he, and liberal and helpful who, indra-Varuna, brings you gifts with gladness. That bounteous man through food shall conquer faemen, and win him opulence and wealthy people.\n\np: May wealth which ye bestow in food and treasure. on him who brings you gifts and offers, Wealth, Devas! which breaks the curse of those who vex us, be, indra-Varuna, e’en our own possession.\n\np: So also, indra-Varuna. May our princes have riches swift to save, with Devas to guard them. They whose great might gives victory in battles, and their triumphant glory spreads with swiftness.\n\np: Indra. and Varuna, Devas whom we are lauding, with your heroic glory. May we, who praise the strength of what is mighty, pass dangers, as with boats we cross the waters.\n\np: Now will I sing a dear and far-extending hymn to Varuna the Deva, immortal Deva, who, mighty Governor, Eternal, as with flame, illumines both wide worlds with majesty and power.\n\np: True to Law, indra-Varuna, your chariot cometh to the banquet of the Devas, to offering, as it were home, that y. May drink.\n\np: Indra and Varuna, drink your fill, ye Heroes, of this invigorating hymn. This juice is shed on this trimmed grass be seated, and rejoice you..","people":["Indra","Varuna","Deva"],"places":["Earth","Heaven"],"things":["Worship","Victory","Waters","Glory","Glorious","Offering","Treasure","Wealth","Food","Men","Might","Juice","Home","Wise","Strong","Mighty","Grass","Banquet","Praise","Hymn","Heroes","Offers","People","Powers","Bliss","Sage","Riches","Gifts"],"groups":["Devas","Dames","Immortal","Man"],"concepts":["Heroic","Immortal","Strength","Offering","Glorious","Swift"],"hash":"md5-qWqSn+dtF+lLvGMK4N//Ug==","created":"Monday, April 8, 2024 - 10:51:55 PM"},{"id":"a011adf3-8198-4412-af52-399c117dfeb3","key":"06069","book":"06","title":"HYMN LXIX. Indra-Visnu","link":"https://indra.ai/rigveda/hymns/06069.html","text":"p: INDRA and Visnu, at my task's completion I urge you on with food and sacred service. Accept  'the offering and grant us riches, leading us on by unobstructed pathways.\n\np: Ye who inspire all hymns, indra and Visnu, ye vessels who contain the Soma juices, may hymns of praise that now are sung address you, the lauds that are recited by the singers.\n\np: Lords of joy-giving draughts, indra and Visnu, come, giving gifts of treasure., to the Soma. With brilliant rays of hymns let chanted praises, repeated with the lauds, adorn and deck you.\n\np: May your foe-conquering horses bring you hither, indra and Visnu, sharers of the banquet. Of all our hymns accept the invocations list to my meditations, and hear the songs I sing you.\n\np: This your deed, indra-Visnu, must be lauded. Ye made the firmament of larger compass, and made the regions broad for our existence.\n\np: Strengthened with sacred offerings, indraVisnu, first eaters, served with worship ana oblation, Fed with the holy oil, vouchsafe us riches ye are the lake, the vat that holds the Soma.\n\np: Drink of this meath, O Indra and Visnu; drink ye your fill of Soma, Wonder-Workers. The sweet exhilarating juice hath reached you. Hear ye my meditations, give ear unto my calling.\n\np: Ye Twain have conquered, ne’er have yc been conquered: never hath either of the Twain been vanquished. Ye, indra-Visnu, when ye fought the battle, produced this infinite with three divisions.","people":["Indra","Soma","Visnu"],"places":["Firmament"],"things":["Worship","Meath","Soma","Offering","Treasure","Food","Juice","Joy","Banquet","Praise","Lake","Offerings","Songs","Horses","Riches","Gifts"],"groups":[],"concepts":["Wonder-Workers","Holy","Sacred","Offering","Offerings"],"hash":"md5-IDLZeoymFWlTBwevQp38Lw==","created":"Monday, April 8, 2024 - 10:51:55 PM"},{"id":"4a069e9a-dd5b-4860-8f3e-724416309297","key":"06070","book":"06","title":"HYMN LXX. Heaven and Earth.","link":"https://indra.ai/rigveda/hymns/06070.html","text":"p: FILLED full of fatness, compassing all things that be, wide, spacious, dropping meath, beautiful in their form, the Heaven and the Earth by Varuna's decree, unwasting, rich in germs, stand parted each from each.\n\np: The Everlasting Pair, with full streams, rich in milk, in their pure rule pour fatness for the pious man. Ye who are Regents of this world, O Earth and Heaven, pour into us the genial flow that prospers meit.\n\np: Whoso, for righteous life, pours offerings to you, O Heaven and Earth, ye Hemispheres, that man succeeds. He in his seed is born again and spreads by Law: from you flow things diverse in form, but ruled alike.\n\np: Enclosed in fatness. Heaven and Earth are bright therewith: they mingle with the fatness which they still increase. Wide, broad, set foremost at election of the priest, to them the singers pray for bliss to further them.\n\np: May Heaven and Earth pour down the balmy rain for us, balm-dropping, yielding balm, with balm upon your path, bestowing by your Deva.ead offering and wealth, great fame and strength for us and good heroic might.\n\np: May Heaven and Earth make food swell plenteously for us, all-knowing Father, jother, wondrous in their works. Pouring out bounties. May, in union, both the Worlds, all beneficial, send us gain, and power, and wealth.","people":["Varuna","Deva"],"places":["Earth","Heaven"],"things":["Meath","Milk","Born","Offering","Wealth","Food","Streams","Flow","Might","Rain","Form","Offerings","Bliss","Life"],"groups":["Father","Man"],"concepts":["Good","Life","Beautiful","Heroic","Strength","Offering","Offerings"],"hash":"md5-CHY14BazpKiGmIhhKPxzlQ==","created":"Monday, April 8, 2024 - 10:51:55 PM"},{"id":"b7d7149f-cfa0-4efa-83e1-cc094118f726","key":"06071","book":"06","title":"HYMN LXXI. Savitar.","link":"https://indra.ai/rigveda/hymns/06071.html","text":"p: FULL of effectual wisdom Savitar the Deva.hath stretched out golden arms that h. May bring forth life. Young and most skilful, while he holds the region up, the Warrior sprinkles fatness over both his hands.\n\np: May we enjoy the noblest vivifying force of Savitar the Deva, that h. May give us wealth: For thou art mighty to produce and lull to rest the world of life that moves on two feet and on four.\n\np: Protect our habitation, Savitar, this day, with guardian aids around, auspicious, firm and true. Deva.of the golden tongue, keep us for newest bliss: let not the evil-wisher have us in his power.\n\np: This Savitar the Deva, the golden-handed, Friend of the home, hath risen to meet the twilight. With cheeks of brass, with pleasant tongue, the Holy, he sends the worshipper rich gifts in plenty.\n\np: Like a Director, Savitar hath extended his golden arms, exceeding fair to look on. He hath gone up the heights of earth and heaven, and made each monster fall and cease from troubling.\n\np: Fair wealth, O Savitar, to-day, to-morrow, fair wealth produce for us each day that passes. May we through this our song be happy gainers, Deva, of a fair and spacious habitation.","people":["Savitar","Deva"],"places":["Earth","Heaven"],"things":["Wealth","Song","Home","Mighty","Worshipper","Bliss","Warrior","Friend","Life","Gifts"],"groups":[],"concepts":["Evil","Life","Holy","Wisdom","Auspicious"],"hash":"md5-7I52druBdKdcf40nRujHgw==","created":"Monday, April 8, 2024 - 10:51:55 PM"},{"id":"f6569312-9efc-4fa8-aaa6-6b5c8c597d36","key":"06072","book":"06","title":"HYMN LXXII. Indra and Soma.","link":"https://indra.ai/rigveda/hymns/06072.html","text":"p: GREAT is this might of yours, indra and Soma, the first high exploits were your own achievements. Ye found the Sun ye found the light of heaven: ye killed all darkness and the Devas’ blasphemers.\n\np: Ye, indra-Soma, gave her light to Morning, and led the Sun on high with all his splendour. Ye stayed the heaven with a supporting pillar, and spread abroad apart, the Earth, the Mother.\n\np: Ye slew the flood -obstructing serpent Vrtra, indra and Soma, Heaven approved your exploit. Ye urged to speed the currents of the rivers, and many seas have ye filled full with waters.\n\np: Ye in the unripe udders of the milch-kine have set the ripe milk, indra and Soma. Ye have held fast the unimpeded whiteness within these many-coloured moving creatures.\n\np: Verily ye bestow, indra and Soma, wealth, famed, victorious, passing to our children. Ye have invested men, ye Mighty Beings, with manly strength that conquers in the battle.","people":["Indra","Soma","Vrtra"],"places":["Earth","Heaven"],"things":["Milk","Rivers","Soma","Waters","Light","Sun","Wealth","Men","Might","Mighty","Splendour","Morning"],"groups":["Devas","Mother"],"concepts":["Strength"],"hash":"md5-mtercY9j8HcNJntXR7gA4g==","created":"Monday, April 8, 2024 - 10:51:55 PM"},{"id":"3900bbfe-d9f2-4646-aac3-ce3ed2a8e65e","key":"06073","book":"06","title":"HYMN LXXIII. Narasamsa.","link":"https://indra.ai/rigveda/hymns/06073.html","text":"p: SERVED with oblations, first-born, mountain-render, Angiras' son, Narasamsa, the Holy, with twice-firm path, dwelling in light, our Father, roars loudly, as a bull, to Earth and Heaven.\n\np: Narasamsa, who made for such a people wide room and verge when Devas were invocated, Slaying his enemies, breaks down their castles, quelling his foes and conquering those who hate him.\n\np: Narasamsa in war hath won rich treasure.s, hath won, this Deva, the great stalls filled with cattle. Striving to win waters and light, resistless, Narasamsa with lightning smites the foeman.","people":["Angiras","Narasamsa","Deva"],"places":["Earth","Heaven"],"things":["Born","Waters","Light","Treasure","People","Cattle"],"groups":["Devas","Father","Son"],"concepts":["Holy"],"hash":"md5-7Ks+WRHSamFeaV//Fo4amQ==","created":"Monday, April 8, 2024 - 10:51:55 PM"},{"id":"da8c36b4-3e01-4460-8ea0-90d6c0cbca44","key":"06074","book":"06","title":"HYMN LXXIV. Soma-Rudra.","link":"https://indra.ai/rigveda/hymns/06074.html","text":"p: HOLD fast your Deva like sway, O Soma-Rudra: let these  'our offerings quickly reach you. Placing in every house your seven great treasure.s, bring blessing to our quadrupeds and bipeds.\n\np: Soma and Rudra, chase to every quarter the sickness that hath visited our dwelling. Drive Nirrti away into the distance, and give us excellent and happy glories.\n\np: Provide, O Soma-Rudra, for our bodies all needful medicines to heal and cure us. Set free and draw away the sin committed which we have still inherent in our persons.\n\np: Armed with keen shafts and weapons, kind and loving, be gracious unto us, Soma and Rudra. Release us from the noose of Varuna; keep us from sorrow, in your tender loving-kindness.","people":["Soma","Varuna","Deva"],"places":[],"things":["Soma","Treasure","Blessing","Excellent","Offerings"],"groups":[],"concepts":["Offerings"],"hash":"md5-Soa3YJEbsKcTF+9invR/2A==","created":"Monday, April 8, 2024 - 10:51:55 PM"},{"id":"82e4fca1-bc99-441b-b5b7-bb5f4bff6d52","key":"06075","book":"06","title":"HYMN LXXV. Weapons of War.","link":"https://indra.ai/rigveda/hymns/06075.html","text":"p: THE warrior's look is like a thunderous rain-cloud's, when, armed with mail, he seeks the lap of battle. Be thou victorious with unwounded body: so let the thickness of thy mail protect thee.\n\np: With Bow let us win kine, with Bow the battle, with Bow be victors in our hot encounters. The Bow brings grief and sorrow to the foeman: armed with the Bo. May we subdue all regions.\n\np: Close to his car, as fain to speak, she presses, holding her well-loved Friend in her embraces. Strained on the Bow, she whispers like a woman-this Bowstring that preserves us in the combat.\n\np: These, meeting like a woman and her lover, bear, mother-like, their child upon their bosom. May the two Bow-ends, starting swift asunder, scatter, in unison, the foes who hate us.\n\np: With many a son, father of many daughters. He clangs and clashes as he goes to battle. Slung on the back, pouring his brood, the Quiver vanquishes all opposing bands and armies.\n\np: Upstanding in the Car the skilful Charioteer guides his strong Horses on whithersoe’er he will. See and admire the strength of those controlling Reins which from behind declare the will of him who drives.\n\np: Horses whose hoofs rain dust are neighing loudly, yoked to the Chariots, showing forth their vigour, with their forefeet descending on the foemen, they, never flinching, trample and destroy them.\n\np: Car-bearer is the name of his oblation, whercon are laid his Weapons and his Armour. So let us here, each day that passes, honour the helpful Car with hearts exceeding joyful.\n\np: In sweet association lived the fathers who gave us life, profound and strong in trouble, Unwearied, armed with shafts and wondrous weapons, free, real heroes, conquerors of armies.\n\np: The Brahmans, and the Fathers meet for Soma-draughts, and, graciously inclined, unequalled Heaven and Earth. Guard us trom evil, pusan, guard us strengtheners of Law: let not the evil-wisher master us.\n\np: Her tooth a deer, dressed in an eagle's feathers, bound with cow-hide, launched forth, she flieth onward. There where the heroes speed hither and thither, ther. May the Arrows shelter and protect us.\n\np: Avoid us thou whose flight is straight, and let our bodies be as stone. May Soma kindly speak to us, and Aditi protect us well.\n\np: He lays his blows upon their backs, he deals his blows upon their thighs. Thou, Whip, who urgest horses, drive sagacious horses in the fray.\n\np: It compasses the arm with serpent windings, fending away the friction of the bowstring: May the Brace, well-skilled in all its duties, guard manfully the man from every quarter.\n\np: Now to the Shaft with venom smeared, tipped with deer-horn, with iron mouth, Celestial, of Parjanya's seed, be this great adoration paid.\n\np: Loosed from the Bowstring fly away, thou Arrow, sharpened by our meditation. Go to the foemen, strike them home, and let not one be left alive.\n\np: There where the flights of Arrows fall like boys whose locks are yet unshorn. Even ther. May Narasamsa, and Aditi protect us well, protect us well through all our days.\n\np: Thy vital parts I cover with thine Armour: with immortality King Soma clothe thee. Varuna give thee what is more than ample, and in thy triump. May the Devas be joyful.\n\np: Whoso would harm us, whether he be a strange foe or one of us,","people":["Soma","King Soma","Varuna","Narasamsa","Pusan","Aditi","Parjanya"],"places":["Earth","Heaven"],"things":["Master","Meditation","Soma","Chariots","Rain","Home","Strong","Car","Armies","Heroes","Warrior","Friend","King","Cow","Horses","Life"],"groups":["Devas","Fathers","Brahmans","Father","Mother","Son","Child","Man","Woman"],"concepts":["Celestial","Evil","Life","Immortality","Strength","Swift"],"hash":"md5-X6gkSjHzlJoiVX6qMbi13Q==","created":"Monday, April 8, 2024 - 10:51:55 PM"}],"copyright":"©2023 Quinn Michaels (indra.ai). All rights reserved.","created":"Monday, April 8, 2024 - 10:51:52 PM"}