{"id":"3958193e-5ef1-4aff-812e-767b7fe98434","key":"08","link":"https://indra.ai/rigveda/books/08.html","hymns":[{"id":"f3364bb2-0c26-4106-adc2-9aaac8afb58a","key":"08001","book":"08","title":"HYMN I. Indra.","link":"https://indra.ai/rigveda/hymns/08001.html","text":"p: GLORIFY naught besides, O Friends, so shall no sorrow trouble you. Praise only might Indra, and say your lauds repeatedly.\n\np: Even him, eternal who is cause of both of enmity and peace, to both sides most munificent.\n\np: Although these men in sundry ways invoke thee to obtain thine aid, be this our meditation, addressed, O Indra, unto thee, thine exaltation every day.\n\np: Those skilled in song, O Maghavan among these men o’ercome with might the foeman's songs. Come hither, bring us strength in many a varied form most near that he may assist us.\n\np: O Indra, I would not sell thee for a mighty price, Thunderer! Lord of countless wealth!\n\np: O Indra, thou art more to me than sire or brother is. O Indra, to give us wealth abundantly.\n\np: Where art thou? Whither art thou gone? For many a place attracts thy mind. Haste, Warrior, Lord of battle's din, haste, holy songs have sounded forth.\n\np: Sing out the song to him for his faithful friend, hymns to bring the Thunderer to , sit on sacred grass.\n\np: The Horses which are thine in tens, in hundreds, yea, in thousands thine, Even those vigorous Steeds, fleet-footed in the course, with those come quickly near to us.\n\np: This day I call the holy song, indra the richly-yielding Milch-cow who provides unfailing food in ample stream.\n\np: With Vata's rolling winged car, Indra, the unconquered One.\n\np: He without ligature closed up the wound again, most wealthy Maghavan, who maketh whole the injured part.\n\np: May we be never cast aside, and strangers, as it were, to thee. We, Thunder-wielding Indra, count ourselves as friends.\n\np: O Vrtra conquerer, we were thought slow and unready for the fray. Yet once in thy great bount, O Hero, after praising thee.\n\np: If he will listen to my laud, the, may out Soma-drops that flow Rapidly through the strainer gladden Indra, drops due to the Tugryas’ Strengthener.\n\np: Come now unto the common laud of thee and of thy faithful friend. May our praise give joy to thee. Fain would I sing thine eulogy.\n\np: May our the waters wash it clean. The men investing it with raiment made of milk shall milk it forth from out the stems.\n\np: Whether thou come from earth or from the lustre of the lofty heaven, wax stronger in thy body through my song of praise: fill full all creatures, O most Wise.\n\np: Most gladdening and most excellent. May Sakra make it swell sent forth with every prayer and asking, as it were, for strength.\n\np: Let me not, still beseeching thee with earnest song at Soma rites, Anger thee like some wild beast. Who would not beseech him who hath power to grant his prayer?\n\np: The draught made swift with rapturous joy, effectual with its mighty strength, All-conquering, distilling transport, let him drink, for he gives us gifts.\n\np: Where bliss is not. May he, All-praised, Deva whom the pious glorify, bestow great wealth upon the mortal worshipper who sheds the juice and praises him.\n\np: Come, indra, and rejoice thyself, O Deva, in manifold affluence. Thou fillest like a lake thy vast capacious bulk with Soma and with draughts besides.\n\np: A thousand and a hundred Steeds are harnessed to thy golden car. May the long-maned Bays, yoked by devotion, bring Indra to drink the Soma juice.\n\np: Yoked to thy chariot wrought of gold. May thy two Bays with peacock tails, Convey thee hither, Steeds with their white backs, to quaff sweet juice that makes us eloquent.\n\np: So drink, thou Lover of the Song, as the first drinker, of this juice. This the outpouring of the savoury sap prepared is good and meet to gladden thee.\n\np: He who alone by wondrous deed is Mighty, Strong by holy works, may he come, fair of cheek. May he not stay afar, but come and hear our call.\n\np: In the quick moving castle, indra, from of old, hast followed after light.\n\np: My praises when the Sun hath risen, my praises at the time of noon, My praises at the coming of the gloom of night, O Indra, have gone forth to thee.\n\np: Praise yea, praise him.\n\np: When to the car, by faith, he yoked the horses longing for the way.\n\np: May he with their cloths of gold, may he, Asanga's son Svanadratha, obtain all joy and high felicities.\n\np: Playoga's son Asanga, by ten thousand, O Agni, hath surpassed the rest in giving. For me ten bright-hued oxen have come forward like lotus-stalks from out a lake upstanding.\n\np: What time his perfect restoration to his lost strength and manhood was apparent, now art thou well, my lord, and shalt be happy.","people":["Indra","Soma","Vrtra","Agni","Sakra","Maghavan","Deva","Vata"],"places":["Earth","Heaven"],"things":["Milk","Steeds","Lord","Meditation","Soma","Waters","Light","Sun","Wealth","Food","Men","Stream","Flow","Might","Juice","Song","Joy","Gold","Wise","Strong","Mighty","Grass","Car","Praise","Faith","Worshipper","Form","Lake","Excellent","Friends","Bliss","Songs","Drops","Warrior","Friend","Hero","Cow","Horses","call","Gifts"],"groups":["Son","Brother"],"concepts":["Good","Golden Car","Holy","Sacred","Strength","Swift"],"hash":"md5-MAZGLqcrFLWpxw+vUULf9Q==","created":"Monday, April 8, 2024 - 10:51:52 PM"},{"id":"8ed27348-98b5-4795-896b-a421b466f444","key":"08002","book":"08","title":"HYMN II. Indra.","link":"https://indra.ai/rigveda/hymns/08002.html","text":"p: HERE is the Soma juice expressed; O Vasu, drink till thou art full: Undaunted Deva, we give it thee.\n\np: Washed by the men, pressed out with stones, strained through the filter made of wool, ’Tis like a courser bathed in stream.\n\np: This juice have we made sweet for thee like barley, blending it with milk. Indra, I call thee to our feast.\n\np: Beloved of all, indra alone drinks up the flowing Soma juice Among the Devas and mortal men.\n\np: The Friend, whom not the brilliant-hued, the badly-mixt or bitter draught, Repels, the far-extending Deva.\n\np: While other men than we with milk chase him as hunters chase a deer, and with their kine inveigle him.\n\np: For him, for Indra, for the Deva, be pressed three draughts of Soma juice In the juice-drinker's own abode.\n\np: Three reservoirs exude their drops, filled are three beakers to the brim, All for one offering to the Deva.\n\np: Pure art thou, set in many a place, and blended in the midst with milk And curd, to cheer the Hero best.\n\np: Here, indra, are thy Soma-draughts pressed out by us, the strong, the pure: They crave admixture of the milk.\n\np: O Indra, pour in milk, prepare the cake, and mix the Soma-draught. I hear them say that thou art rich.\n\np: Quaffed juices fight within the breast. The drunken praise not by their wine, the naked praise not when it rains.\n\np: Rich be the praiser of one rich, munificent and famed like thee: High rank be his, O Lord of Bays.\n\np: Foe of the man who adds no milk, he heeds not any chanted hymn Or holy psalm tha. May he sung.\n\np: Give us not, indra, as a prey unto the scornful or the proud: Help, Mighty One, with power and might.\n\np: This, even this, O Indra, we implore. as thy devoted friends, the Kanvas praise thee with their hymns.\n\np: Naught else, O Thunderer, have I praised in the skilled singer's eulogy: On thy land only have I thought.\n\np: The Devas seek him who presses out the Soma; they desire not sleep They punish sloth unweariedly.\n\np: Come hither swift with gifts of wealth - be not thou angry with us-like a great man with a youthful bride.\n\np: Let him not, wrathful with us, spend the evening far from us to-daylike some unpleasant son-in-law.\n\np: For well we know this Hero's love, most liberal of the boons he gives, His plans whom the three worlds display.\n\np: Pour forth the gift which Kanvas bring, for none more glorious do we know Than the Strong Lord with countless aids.\n\np: O presser, offer Soma first to Indra. Hero, Sakra, him. The Friend of man, that h. May drink;\n\np: Who, in untroubled ways, is best provider, for his worshippers. Of strength in horses and in kine.\n\np: Pressers, for him blend Soma juice, each draught most excellent, for him. The Brave, the Hero, for his joy.\n\np: The Vrtra conquerer drinks the juice. May he who gives a hundred aids Approach, nor stay afar from us.\n\np: May the strong Bay Steeds, yoked by prayer, bring hither unto us our Friend, Lover of Song, renowned by songs.\n\np: Sweet are the Soma juices, come! Blent are the Soma juices, come! Rsi-like, mighty, fair of cheek, come hither quickly to the feast.\n\np: And lauds which strengthen thee for great bounty and valour, and exalt Indra who doeth glorious deeds,\n\np: And songs to thee who lovest song, and all those hymns addressed to thee- These evermore confirm thy might.\n\np: Thus he, sole doer of great deeds whose hand holds thunder, gives us strength. He who hath never been subdued.\n\np: Vrtra he subdues with his right hand, even Indra, great with mighty power, and much-invoked in many a place.\n\np: He upon whom all men depend, all regions, all achievements, he Takes pleasure in our wealthy chiefs.\n\np: All this hath he accomplished, yea, indra, most gloriously renowned, who gives our wealthy princes strength.\n\np: Who drives his chariot seeking spoil, from afar, to him he loves: For swift is he to bring men wealth.\n\np: The Sage who, winning spoil with steeds, subdues Vrtra. Hero with the men, His servant's faithful assister.\n\np: O Priyamedhas, worship with collected mind this Indra whom The Soma hath full well inspired.\n\np: Ye Kanvas, sing the Mighty One, Lord of the Brave, who loves renown, All-present, glorified by song.\n\np: Strong Friend, who, with no trace of feet, restores the cattle to the men, who rest their wish and hope on him.\n\np: Shaped as a Ram, Stone-hurler I once thou camest hither to the son Of Kanva, wise Medhyatithi.\n\np: VibhIndu, thou hast helped this man, giving him thousands four times ten, and afterward eight thousand more.\n\np: And these twain pouring streams of milk, creative, daughters of delight, for wedlock sake I glorify.","people":["Indra","Soma","Vrtra","KanVa","Sakra","Kanvas","Deva","Vasu","Vibhindu"],"places":[],"things":["Worship","Cheer","Milk","Provider","Steeds","Lord","Soma","Glorious","Singer","Offering","Wealth","Men","Streams","Stream","Might","Juice","Song","Joy","Help","Wise","Strong","Mighty","Praise","Brave","Delight","Hymn","Creative","Gift","Excellent","Lord of Bays","Friends","Songs","Drops","Friend","Hero","Sage","Horses","Winning","call","spoil","Cattle","Gifts"],"groups":["Devas","Worshippers","Son","Man"],"concepts":["Love","Holy","Strength","Offering","Glorious","Swift"],"hash":"md5-3J2s5a04anp/fLfvS95bmg==","created":"Monday, April 8, 2024 - 10:51:52 PM"},{"id":"4d9c0ecb-22ad-4595-a574-6171720dd02e","key":"08003","book":"08","title":"HYMN III. Indra.","link":"https://indra.ai/rigveda/hymns/08003.html","text":"p: DRINK, indra, of the savoury juice, and cheer thee with our milky draught. Be, for our weal, our Friend and sharer of the feast, and let thy wisdom guard us well.\n\np: In thy kind grace and favou. May we still be strong: expose us not to foe's attack. With manifold assistance guard and assist us, and bring us to felicity.\n\np: May these my songs of praise exalt thee, Lord, who hast abundant wealth. Men skilled in holy hymns, pure, with the hues of fire, have sung them with their lauds to thee.\n\np: He, with his might enhanced by Rsis thousandfold, hath like an ocean spread himself. His majesty is praised as true at solemn rites, his power where holy singers rule.\n\np: Indra for worship of the Devas, indra while offering proceeds, indra, as worshippers in battle-shock, we call, indra that we may win the spoil.\n\np: With might hath Indra spread out heaven and earth, with power hath Indra lighted up the Sun. In Indra are all creatures closely held; in him meet the distilling Soma-drops.\n\np: Men with their lauds are urging thee, indra, to drink the Soma first. The Rbhus in accord have lifted up their voice, and Rudras sung thee as the first.\n\np: Indra increased his manly strength at offering, in the wild rapture of this juice. And living men to-day, even as of old, sing forth their praises to his majesty.\n\np: I crave of thee that hero strength, that tho. Mayst first regard this prayer, Wherewith thou holpest Bhrgu and the Yatis and Praskanva when the prize was staked.\n\np: Wherewith thou sentest mighty waters to the sea, that, indra, is thy manly strength. For ever unattainable is this power of him to whom the worlds have cried aloud.\n\np: Help us, O Indra, when we pray to thee for wealth and hero might. First help thou on to strength the man who strives to win, and aid our laud, O Ancient One.\n\np: Help for us, indra, as thou holpest Paura once, this man's devotions bent on gain. Help, as thou gavest Rusama and Syavaka and Svarnara and Krpa aid.\n\np: What newest of imploring prayers shall, then, the zealous mortal sing? For have not they who laud his might, and Indra-power won for themselves the light of heaven?\n\np: When shall they keep the Law and praise thee mid the Devas? Who counts as Rsi and as sage? When ever wilt thou, indra Maghavan, come nigh to presser's or to praiser's call?\n\np: These songs of ours exceeding sweet, these hymns of praise ascend to theelike ever-conquering chariots that display their strength, gain wealth, and give unfailing aid.\n\np: The Bhrgus are like Suns, like Kanvas, and have gained all that their thoughts were bent upon. The living men of Priyamedha's race have sung exalting Indra with their lauds.\n\np: Best slayer of the Vrtras, yoke thy Bay Steeds, indra, from afar. Come with the High Ones hither, Maghavan, to us, Mighty, to drink the Soma juice.\n\np: For these, the bards and singers, have cried out to thee with prayer, to gain  'the offering. As such Indra, who lovest song, even as a lover bear my call.\n\np: Thou from the lofty plains above, O Indra, hurledst Vrtra down. Thou dravest forth the kine of guileful Mrgaya and Arbuda from the mountain's hold.\n\np: Bright were the flaming fires, the Sun gave forth his shine, and Soma, indra's juice, shone clear. Indra, thou blewest the great Dragon from the air: men must regard that valorous deed.\n\np: The fairest courser of them all, who runneth on as ’twere to heaven. Which Indra and the Maruts gave, and Pakasthaman Kaurayan.\n\np: To me hath Pakasthaman given, a ruddy horse, good at the pole, filling is girth and rousing wealth;\n\np: Compared with whom no other ten strong coursers, harnessed to the pole, bear Tugrya to his dwelling place.\n\np: Raiment is body, food is life, and healing ointment giveth strength. As the free-handed giver of the ruddy steed, I have named Pakasthaman fourth.","people":["Indra","Soma","Vrtra","Maghavan","Priyamedha","Praskanva","Kanvas","Arbuda"],"places":["Ocean","Earth","Heaven"],"things":["Worship","Cheer","Steeds","Lord","Soma","Waters","Chariots","Offering","Shine","Light","Air","Sun","Wealth","Food","Men","Might","Juice","Song","Help","Strong","Mighty","Praise","Voice","Ascend","Songs","Drops","Friend","Hero","Sage","Horse","call","spoil","Life"],"groups":["Devas","Maruts","Rudras","Worshippers","Bhrgus","Rsis","Man","Vrtras","Rbhus"],"concepts":["Good","Life","Holy","Strength","Wisdom","Offering","Giver","Ancient One"],"hash":"md5-FRdS3zmXJ8Qm6TC8WbDF+w==","created":"Monday, April 8, 2024 - 10:51:52 PM"},{"id":"774bec71-a4bf-4eaf-8e73-b60e150f0623","key":"08004","book":"08","title":"HYMN IV. Indra.","link":"https://indra.ai/rigveda/hymns/08004.html","text":"p: THOUGH, indra, thou art called by men eas ward and wes ward, north and south, Thou chiefly art with Anava and Turvasa, brave Champion I urged by men to Come.\n\np: Or, indra, when with Ruma, Rusama, Syavaka, and Krpa thou rejoicest thee, Still do the Kanvas, bringing praises, with their prayers, O Indra, draw thee hither: come.\n\np: Even as the wild-bull, when he thirsts, goes to the desert's watery pool, Come hither quickly both at morning and at eve, and with the Kanvas drink thy fill.\n\np: May the drops gladden thee, rich Indra, and obtain bounty for him who pours the juice. Soma pressed in the mortar didst thou take and drink, and hence hast won surpassing might.\n\np: With mightier strength he conquered strength, with energy he crushed their wrath. O Indra, Strong in youth, all those who sought the fray bent and bowed down to thee like trees.\n\np: He who wins promise of thine aid goes girt as with a thousand mighty men of war. He makes his son preeminent in hero might: he serves with reverential prayer.\n\np: With thee, the Mighty, for our Friend, we will not fear or feel fatigue. May we see Turvasa and Yadu: thy great deed, O Hero, must be glorified.\n\np: On his left hip the Hero hath reclined himself: the proffered feast offends him not. The milk is blended with the honey of the bee: quickly come hither, baste, and drink.\n\np: Indra, thy friend is fair of form and rich in horses, cars, and kine. He evermore hath food accompanied by wealth, and radiant joins the company.\n\np: Come like a thirsty antelope to the drinking-place: drink Soma to thy heart's desire. Raining it down day after day, thou gainest thy surpassing might.\n\np: Monk, let the Soma juice flow forth, for Indra longs to drink thereof. He even now hath yoked his vigorous Bay Steeds: the Vrtra conquerer hath come near.\n\np: The man with whom thou fillcst thee with Soma deems himself a pious worshipper. This thine appropriate food is here poured out for thee: come, hasten forward. drink of it,\n\np: Press out the Soma juice, ye monks, for Indra borne upon his car. The pressing-stones speak loud of Indra, while they shed the juice which, offered, honours him.\n\np: To the brown juic. May his dear vigorous Bay Steeds bring Indra, to our holy task. Hither let thy Car-steeds who seek  'the offering bring thee to our water-offerings.\n\np: Pusan, the Lord of ample wealth, for firm alliance we elect. May he with wisdom, Sakra! Looser! Much-invoked! aid us to riches and to seed.\n\np: Sharpen us like a razor in the barber's hands: send riches thou who settest free. Easy to find with thee are treasure.s of the Dawn for mortal man whom thou dost speed.\n\np: Pusan, I long to win thy love, I long to praise thee, Radiant Deva. Excellent Lord, ’tis strange tome, no wish have I to sing the psalm that Pajra sings.\n\np: My kine, O Radiant Deva, seek pasture where they will, my during wealth, Immortal One. Be our protector, pusan! be, most liberal Lord, propitious to our gathering strength.\n\np: Rich was the gift Kurunga gave, a hundred steeds at morning rites. Among the gifts of Turvasas we thought of him, the opulent, the splendid King.\n\np: What by his morning songs Kanva, the powerful, hath, with the Priyamedhas, gained-\n\np: The herds of sixty thousand pure and spotless kine, have I, the Rsi, driven away.\n\np: The very trees were joyful at my coming: kine they obtained in plenty, steeds in plenty.","people":["Indra","Soma","Vrtra","Yadu","Turvasa","KanVa","Sakra","Pusan","Kanvas","Deva","Dawn"],"places":[],"things":["Milk","Steeds","Lord","Soma","Water","Offering","Treasure","Wealth","Food","Men","Flow","Might","Juice","Strong","Mighty","Car","Praise","Brave","Worshipper","Gift","Form","Excellent","Pressing-Stones","Offerings","Songs","Drops","Friend","Hero","King","Horses","Riches","Cars","Morning","Gifts"],"groups":["Son","Immortal","Man","Monks"],"concepts":["Cars","Love","Immortal","Holy","Strength","Wisdom","Offering","Offerings","Powerful"],"hash":"md5-WmDtqlBdLlOruWrgGiRbKQ==","created":"Monday, April 8, 2024 - 10:51:52 PM"},{"id":"eb0311b8-7e90-4a16-b6d2-c67c922f2a4a","key":"08005","book":"08","title":"HYMN V. Asvins.","link":"https://indra.ai/rigveda/hymns/08005.html","text":"p: WHEN, even as she were present here, red Dawn hath shone from far away, she spreadeth light on every side.\n\np: Like Heroes on your will-yoked car farshining, Wonder-Workers! ye Attend, O Asvins, on the Dawn.\n\np: By you, O Lords of ample wealth our songs of praise have been observed: As envoy have I brought the prayer.\n\np: Kanvas must praise the Asvins dear to many, making many glad, most rich, that the, may assist us.\n\np: Most liberal, best at winning strength, inciters, Lords of splendour who Visit the worshipper's abode.\n\np: So for devout Sudeva dew with fatness his unfailing mead, and make it rich for offering.\n\np: Hitherward running speedily with horses, as with rapid hawks, Come, Asvins, to our song of praise\n\np: Wherewith the three wide distances, and all the lights that are in heaven. Ye traverse, and three times of night.\n\np: O Finders of the Day, that we may win us food of kine and wealth, Open the paths for us to tread.\n\np: O Asvins, bring us wealth in kine, in noble heroes, and in cars: Bring us the strength that horses give.\n\np: Ye Lords of splendour, glorified, ye Wonder-Workers borne on paths Of gold, drink sweets with Somajuice.\n\np: To us, ye Lords of ample wealth, and to our wealth chiefs extend Wide shelter, ne’er to be assailed.\n\np: Come quickly downward to the prayer of people whom ye favour most: Approach not unto other folk.\n\np: Ye Asvins whom our minds perceive, drink of this lovely gladdening draught, the mcath which we present to you.\n\np: Bring riches hither unto us in hundreds and in thousands, source Of plenteous food, sustaining all.\n\np: Verily sages call on you, ye Heroes, in full many a place. Moved by the monks, O Asvins, conic.\n\np: Men who have trimmed the sacred grass, bringing oblations and prepared, O Asvins, are invoking you.\n\np: May this our hymn of praise to-day, most powerful to bring you, be, O Asvins, nearest to your hearts.\n\np: The skin filled full of savoury meath, laid in the pathway of your car- O Asvins, drink ye both therefrom.\n\np: For this, ye Lords of ample wealth, bring blessing for our herd, our kine, Our progeny, and plenteous food.\n\np: Ye too unclose to us like doors the strengthening waters of the sky, and rivers, ye who find the day.\n\np: When did the son of Tugra serve you, Men? Abandoned in the sea, that with winged steeds your car might fly.\n\np: Ye, O Nasatyas, ministered to Kanva with repeated aid, when cast into the heated pit.\n\np: Come near with those most recent aids of yours which merit eulogy, when I invoke you, Wealthy Devas.\n\np: As ye protected Kanva erst, priyamedha and Upastuta, Atri, Sinjara, Asvins Twain\n\np: And Amsu in decisive fight, Agastya in the fray for kine. And, in his battles, Sobhari.\n\np: For so much bliss, or even more, O Asvins, Wealthy Devas, than this, We meditate white singing hymns to you.\n\np: Ascend your car with golden seat, O Asvins, and with reins of gold, that reaches even to the sky.\n\np: Golden is its supporting shaft, the axle also is of gold, and both the wheels are made of gold.\n\np: Thereon, ye Lords of ample wealth, come to us even from afar, Come ye to this mine eulogy.\n\np: From far away ye come to us, Asvins, enjoying plenteous food Of Dasas, O Immortal Ones.\n\np: With splendour, riches, and renown, O Asvins, hither come to us, Nasatyas, shining brilliantly.\n\np: May dappled horses, steeds who fly with pinions, bring you hitherward To people skilled in offerings.\n\np: The whcel delayeth not that car of yours accompanied by song, that cometh with a store of food.\n\np: Borne on that chariot wrought of gold, with coursers very fleet of foot, Come, O Nasatyas, swift as thought.\n\np: O Wealthy Devas, ye taste and find the brisk and watchful wild beast good. Associate wealth with food for us.\n\np: As such, O Asvins, find for me my share of new-presented gifts, as Kasu, Cedi's son, gave me a hundred head of buffaloes, and ten thousand kine.\n\np: He who hath given me for mine own ten Kings like gold to look upon. At Caidya's feet are all the people round about, all those who think upon the shield.\n\np: No man, not any, goes upon the path on which the Cedis walk. No other prince, no folk is held more liberal of gifts than they.","people":["KanVa","Asvins","Nasatyas","Atri","Priyamedha","Tugra","Agastya","Kanvas","Dawn"],"places":["Heaven","Sky"],"things":["Meath","Steeds","Rivers","Waters","Offering","Light","Wealth","Food","Men","Might","Song","Gold","Grass","Car","Blessing","Praise","Worshipper","Hymn","Heroes","Ascend","Splendour","People","Offerings","Bliss","Songs","Horses","Winning","call","Riches","Cars","Gifts"],"groups":["Devas","Kings","Son","Immortal","Progeny","Man","Monks"],"concepts":["Good","Wonder-Workers","Cars","Immortal","Sacred","Strength","Devout","Offering","Offerings","Powerful","Swift","Noble"],"hash":"md5-OW/EjOgQbUckekcbK2nCCg==","created":"Monday, April 8, 2024 - 10:51:52 PM"},{"id":"88eeee13-1ea7-47e2-b5c4-e5a04cc348cd","key":"08006","book":"08","title":"HYMN VI Indra","link":"https://indra.ai/rigveda/hymns/08006.html","text":"p: INDRA, great in his power and might, and like Parjanya rich in rain, is magnified by Vatsa's lauds.\n\np: When the monks, strengthening the Son of Holy Law, present their gifts, Singers with Order's hymn of praiser.\n\np: Since Kanvas with their lauds have made Indra complete  'the offering. Words are their own appropriate arms.\n\np: Before his hot displeasure all the peoples, all the men, bow down, as rivers bow them to the sea.\n\np: This power of his shone brightly forth when Indra brought together, like a skin, the worlds of heaven and earth.\n\np: The fiercely-moving Vrtra's head he severed with his thunderbolt, His mighty hundred-knotted bolt.\n\np: Here are-we sing them loudly forth-our thoughts among-the best of songs. Even lightnings like the blaze of fire.\n\np: When bidden thoughts, spontaneously advancing, glow, and with the stream Of offering the Kanvas shine.\n\np: Indra, may we obtain that wealth in horses and in herds of cows, and prayer tha. May be noticed first.\n\np: I from my Father have received deep knowledge of the Holy Law I was born like unto the Sun.\n\np: After the lore of ancient time I make, like Kanva, beauteous songs, and Indra's selfgains strength thereby.\n\np: Whatever Rsis have not praised thee, indra, or have lauded thee, by me exalted wax thou strong.\n\np: When his wrath thundered, when he rent Vrtra to pieces, limb by limb. He sent the waters to the sea.\n\np: Against the Dasyu gusna thou, indra, didst hurl thy during bolt: Thou, Dread one, hast a hero's fame.\n\np: Neither the heavens nor firmaments nor regions of the earth contain Indra, the Thunderer with his might.\n\np: O Indra him who lay at length staying thy copious waters thou, in his own footsteps, smotest down\n\np: Thou hiddest deep in darkness itim, O Indra, who had set his grasp On spacious heaven and earth conjoined.\n\np: Indra, whatever Yatis and Bhrgus have offered praise to thee, Listen, thou Mighty, to my call.\n\np: Indra, these spotted cows yield thee their butter and the milky draught; Aiders, thereby, of offering;\n\np: Which, teeming, have received thee as a life-germ, indra, with their mouthlike Surya who sustaineth all.\n\np: O Lord of Might, with hymns of praise the Kanvas have increased thy power, the drops poured forth have strengthened thee.\n\np: Under thy guidance, indra, mid thy praises, Lord of Thunder, shall The offering be soon performed.\n\np: Indra, disclose much food for us, like a stronghold with store of kine: Give progeny and heroic strength.\n\np: And, indra, grant us all that wealth of fleet steeds which shone bright of old Among the tribes of Nahusas.\n\np: Hither thou seemest to attract heaven's fold which shines before our eyes, when, indra, thou art kind to us.\n\np: Yea, when thou puttest forth thy power, indra, thou governest the folk. Mighty, unlimited in strength.\n\np: The tribes who bring oblations call to thee, to thee to give them help, with drops to thee who spreadest far.\n\np: There where the mountains downward slope, there by the meeting of the streams The Sage was manifest with song.\n\np: Thence, marking, from his lofty place downward he looks upon the sea, and thence with rapid stir he moves.\n\np: Then, verify, they see the light refulgent of primeval seed, Kindled on yonder side of heaven.\n\np: Indra, the Kanvas all exalt thy wisdom and thy manly power, and, Mightiest! thine heroic strength.\n\np: Accept this eulogy of mine, indra, and guard me carefully: Strengthen my thought and prosper it.\n\np: For thee, O Mighty, Thunder-armed, we singers through devotionhave Fashioned the hymn that we may live.\n\np: To Indra have the Kanvas sung, like waters speeding down a slope: The song is fain to go to him.\n\np: As rivers swell the ocean, so our hymns of praise make Indra strong, Eternal, of resistIess wrath.\n\np: Come with thy lovely Bay Steeds, come to us from regions far away O Indra, drink this Soma juice.\n\np: Best slayer of Vrtras, men whose sacred grass is ready trimmed Invoke thee for the gain of spoil.\n\np: The heavens and earth come after thee as the wheel follows Etasa: To thee flow Soma-drops effused.\n\np: Rejoice, O Indra, in the light, rejoice in Saryandyan, be Glad in  'theofferings hymn.\n\np: Grown strong in heaven, the Thunder-armed hath bellowed, Vrtra conquerer, Bull, Chief drinker of the Soma juice.\n\np: Thou art a Rsi born of old, sole Ruler over all by might: Thou, indra, guardest well our wealth.\n\np: May thy Bay Steeds with beauteous backs, a hundred, bring thee to the feast, Bring thee to these our Soma-draughts.\n\np: The Kanvas with their hymns of praise have magnified this ancient thought That swells with streams of meath and oil.\n\np: Mid mightiest Devas let mortal man choose Indra at  'the offering, indra, whoe’er would win, for help.\n\np: Thy steeds, by Priyamedhas praised, shall bring thee, Deva whom all invoke, Hither to drink the Somajuice.\n\np: A hundred thousand have I gained from Parsu, from Tirindira, and presents of the Yadavas.\n\np: Ten thousand head of kine, and steeds three times a hundred they bestowed On Pajra for the Sama-song.\n\np: Kakuha hath reached up to heaven, bestowing buffaloes yoked in fours, and matched in fame the Yadavas.","people":["Indra","Soma","Vrtra","KanVa","Kanvas","Etasa","Deva","Surya","Parjanya"],"places":["Ocean","Earth","Heaven"],"things":["Meath","Steeds","Lord","Born","Mountains","Rivers","Soma","Waters","Offering","Shine","Light","Sun","Wealth","Food","Men","Streams","Stream","Flow","Might","Juice","Rain","Song","Help","Strong","Mighty","Grass","Chief","Praise","Hymn","Songs","Drops","Hero","Sage","Horses","call","spoil","Order","Life","Gifts","Wheel"],"groups":["Devas","Dasyu","Bhrgus","Father","Son","Progeny","Rsis","Man","Vrtras","Monks"],"concepts":["Life","Heroic","Holy","Sacred","Strength","Wisdom","Offering"],"hash":"md5-KifR0RHQpIe8RfbNBN3/SQ==","created":"Monday, April 8, 2024 - 10:51:52 PM"},{"id":"bbdf189f-fb3f-4129-91e4-897e7a11fa99","key":"08007","book":"08","title":"HYMN VII. Maruts.","link":"https://indra.ai/rigveda/hymns/08007.html","text":"p: O MARUTS, when the sage hath poured the Trstup forth as food for you, Ye shine amid the mountain-clouds.\n\np: When, Bright Ones, fain to show your might ye have determined on your course, the mountain-clouds have bent them down.\n\np: Loud roaring with the winds the Sons of Prsni have upraised themselves: They have poured out the streaming food.\n\np: The Maruts spread the mist abroad and make mountains rock and reel, when with the winds they go their way\n\np: What time the rivers and the hills before your coming bowed them down, So to sustain your mighty force.\n\np: We call on you for aid by night, on you for assist in the day, On you while offering proceeds.\n\np: These, verily, wondrous, red of hue, speed on their courses with a roar Over the ridges of the sky.\n\np: With might they drop the loosened rein so that the Su. May run his course, and spread themselves with beams of light.\n\np: Accept, ye Maruts, this my song, accept ye this mine hymn of praise, accept, Rbhuksans, this my call.\n\np: The dappled Cows have poured three lakes, meath for the Thunder-wielding Deva, From the great cask, the watery cloud.\n\np: O Maruts, quickly come to us when, longing for felicity, We call you hither from the sky.\n\np: For, Rudras and Rbhuksans, ye, most Bountiful, are in the house, Wise when the gladdening draught is drunk.\n\np: O Maruts, send us down from heaven riches distilling rapturous joy, with plenteous food, sustaining all.\n\np: When, Bright Ones, hither from the hills ye have resolved to take your way, Ye revel in the drops effused.\n\np: Man should solicit with his lauds happiness which belongs to them, So great a band invincible.\n\np: They who like fiery sparks with showers of rain blow through the heaven and earth, Milking the spring that never fails.\n\np: With chariots and tumultuous roar, with tempests and with hymns of praise The Sons of Prsni hurry forth.\n\np: For wealth, we think of that whereby ye aided Yadu, Turvasa, and KanVa who obtained the spoil.\n\np: May these our offerings Bounteous Ones I that flow in streams like holy oil, with Kanva's hymns, increase your might.\n\np: Where, Bounteous Lords for whom the grass is trimmed, are ye rejoicing now? What Brahman is adoring you?\n\np: Is it not there where ye of old, supplied with sacred grass, for lauds Inspired the strong in offering?\n\np: They brought together both the worlds, the mighty waters, and the Sun, and, joint by joint, the thunderbolt.\n\np: They sundered Vrtra limb from limb and split the gloomy mountain-clouds, performing a heroic deed.\n\np: They reinforced the power and strength of Trita as he fought, and helped Indra in battle with the foe.\n\np: They deck themselves for glory, bright, celestial, lightning in their hands, and helms of gold upon their heads.\n\np: When eagerly ye from far away came to the cavern of the Bull. He bellowed in his fear like Heaven.\n\np: Borne by your golden-footed steeds, O Devas, come hither to receive The offering we offer you.\n\np: When the red leader draws along their spotted deer yoked to the car. The Bright Ones come, and shed the rain.\n\np: Susoma, Saryakiavan, and Arjika full of homes, have they. These Heroes, sought with downward car.\n\np: When, Maruts, ye come to him, the singer who invokes you thus, with favours to your suppliant?\n\np: What now? where have ye still a friend since ye left Indra all alone? Who counteth on your friendship now?\n\np: The Kanvas sing forth Agni's praise together with our Maruts’ who Wield thunder and wear swords of gold.\n\np: Hither for new felicit. May I attract the Impetuous Ones, the Heroes with their wondrous strength\n\np: Before them sink the very hills deerning themseives abysses: yea, Even the mountains bend them down.\n\np: Steeds flying on their tortuous path through mid-air carry them, and give The man who lauds them strength and life.\n\np: Agni was born the first of all, like Surya lovely with his light: With lustre these have spread abroad.","people":["Indra","Vrtra","Agni","Yadu","Turvasa","KanVa","Kanvas","Trita","Deva","Surya"],"places":["Arjika","Susoma","Saryakiavan","Earth","Heaven","Mid-Air","Sky"],"things":["Meath","Leader","Steeds","Born","Mountains","Rivers","Waters","Chariots","Glory","Singer","Offering","Shine","Light","Air","Sun","Wealth","Food","Streams","Flow","Might","Rain","Song","Joy","Gold","Wise","Strong","Mighty","Grass","Car","Praise","Hymn","Heroes","Offerings","Drops","Friend","Sage","call","spoil","Riches","Life"],"groups":["Devas","Maruts","Rudras","Rbhuksans","Sons","Man"],"concepts":["Celestial","Life","Friendship","Heroic","Holy","Sacred","Strength","Offering","Offerings"],"hash":"md5-KCnu0AW7A6y1eMiSuEFOhQ==","created":"Monday, April 8, 2024 - 10:51:52 PM"},{"id":"a08c1756-afa9-4a80-9e89-865773b3add9","key":"08008","book":"08","title":"HYMN VIII. Asvins.","link":"https://indra.ai/rigveda/hymns/08008.html","text":"p: WITH all the assists that are yours, O Asvins, hither come to us: Wonderful, borne on paths of gold, drink ye the meath with Soma juice.\n\np: Come now, ye Asvins, on your car decked with a sun-bright canopy, Bountiful, with your golden forms, Sages with depth of intellect.\n\np: Come hither from the Nahusas, come, drawn by pure hymns, from mid-air. O Asvins, drink the savoury juice shed in the Kanvas' offering.\n\np: Come to us hither from the heavens, come from mid-air, well-loved by us: Here Kanva's son hath pressed for you the pleasant meath of Soma juice.\n\np: Come, Asvins, to give car to us, to drink the Soma, Asvins, come. Hail, Strengtheners of the praise-song speed onward, ye Heroes, with your thoughts.\n\np: As. Heroes, in the olden time the Rsis called you to their aid, So now, O Asvins, come to us, come near to this mine eulogy.\n\np: Even from the luminous sphere of heaven come to us, ye who find the light, Carers for Vatsa, through our meditations, and lauds, O yewho hearour call.\n\np: Do others more than we adore the Asvins with their hymns of praise? The Rsi Vatsa, Kanva's son, hath magnified you with his songs.\n\np: The holy singer with his hymns hath called you, Asvins, hither-ward; Best Vrtra conquerers, free from stain, as such bring us felicity.\n\np: What time, ye Lords of ample wealth, the Lady mounted on your car, then, O ye Asvins, ye attained all wishes that your hearts desired.\n\np: Come thence, O Asvins, on your car that hath a thousand ornaments: Vatsa the sage, the sage's son, hath sung a song of sweets to you.\n\np: Cheerers of many, rich in goods, discoverers of opulence, the Asvins, Riders through the sky, have welcomed this my song of praise.\n\np: O Asvins, grant us all rich gifts wherewith no man mav interfere. Make us observe the stated times: give us not over to reproach.\n\np: Whether, Nasatyas, ye be nigh, or whether ye be far away, Come thence, O Asvins, on your car that hath a thousand ornaments.\n\np: Vatsa the Rsi with his songs, Nasatyas, hath exalted you: Grant him rich food distilling oil, graced with a thousand ornaments.\n\np: Bestow on him, O Asvins, food that strengthens, and that drops with oil, On him who praises you for bliss, and, Lords of bounty, prays for wealth.\n\np: Come to us, ye who subdue the foe, Lords of rich treasure., to this hymn. O Heroes, give us high renown and these good things of earth for help.\n\np: The Priyamedhas have invoked you with all assists that are yours, You, Asvins, Lords of solemn rites, with calls entreating you to come.\n\np: Come to us, Asvins, ye Who bring felicity, auspicious Ones, to Vatsa who with prayer and hymn, lovers of song, hath honoured you.\n\np: Aid us, O Heroes, for those hymns for which ye helped GoSarya erst, Gave Vasa, Dasavraja aid, and Kanva and Medhatithi:\n\np: And favoured Trasadasyu, ye Heroes, in spoil-deciding fray: For these, O Asvins, graciously assist us in acquiring strength.\n\np: O Asvins. May pure hymns of ours, and songs and praises, honour you: Best slayers everywhere of foes, as such we fondly yearn for you.\n\np: Three places of the Asvins, erst concealed, are made apparent now. Both Sages, with the flight of Law come hither unto those who live.","people":["Soma","Vrtra","KanVa","Asvins","Nasatyas","Kanvas"],"places":["Earth","Heaven","Mid-Air","Sky"],"things":["Meath","Soma","Singer","Offering","Light","Air","Sun","Treasure","Wealth","Food","Juice","Song","Gold","Help","Car","Praise","Hymn","Heroes","Bliss","Songs","Drops","Sage","call","spoil","Gifts"],"groups":["Son","Rsis","Man"],"concepts":["Good","Holy","Strength","Offering","Auspicious"],"hash":"md5-bTdQdOhbvPw8jBpMuGdxpA==","created":"Monday, April 8, 2024 - 10:51:52 PM"},{"id":"4d9b3549-b5d4-41c8-9add-94dfbe588ca6","key":"08009","book":"08","title":"HYMN IX. Asvins.","link":"https://indra.ai/rigveda/hymns/08009.html","text":"p: To help and favour Vatsa now, O Asvins, come ye hitherward. Bestow on him a dwelling spacious and secure, and keep malignities away.\n\np: All manliness that is in heaven, with the Five Tribes, or in mid-air, bestow, ye Asvins, upon us.\n\np: Remember Kanva first of all among the singers, Asvins, who Have thought upon your wondrous deeds.\n\np: Asvins, for you with song of praise this hot oblation is effused, This your sweet Soma juice, ye Lords of ample wealth, through which ye think upon the foe.\n\np: Whatever ye have done in floods, in the tree, Wonder-Workers, and in growing plants, therewith, O Asvins, assist me.\n\np: What force, Nasatyas, ye exert, whatever, Devas, ye tend and heal, This your own Vatsa gains not by his hymns alone: ye visit him who offers gifts.\n\np: Now hath the Rsi splendidly thought out the Asvins' hymn of praise. Let the Atharvan pour the warm oblation forth, and Soma very rich in sweets.\n\np: Ye Asvins, now ascend your car that lightly rolls upon its way. May these my praises make you speed hitherward like a cloud of heaven.\n\np: When, O Nasatyas, we this day make you speed hither with our hymns, or, Asvins, with our songs of praise, remember Kanya specially.\n\np: As erst Kaksivan and the Rsi Vyasva, as erst Dirghatamas invoked your presence, or, in the offerings chambers, Vainya Prthi, so be ye mindful of us here, O Asvins.\n\np: Come as home-guardians, saving us from foemen, guarding our living creatures and our bodies, Come to the house to give us seed and offspring,\n\np: Whether with Indra ye be faring, Asvins, or resting in one dwelling-place with Vayu, in concord with the Rbhus or Adityas, or standing still in Visnu's striding-places.\n\np: When I, O Asvins, call on you to-day that . May gather strength, or as all-conquering might in war, be that the Asvins' noblest grace.\n\np: Now come, ye Asvins, hitherward: here are oblations set for you; These Soma-draughts to aid Yadu and Turvasa, these offered you mid Kaniva's Sons.\n\np: Whatever healing balm is yours, Nisatyas, near or far away, therewith, great Sages, grant a home to Vatsa and to Vimada.\n\np: Together with the Deva, with the Asvins' Speech have I awoke. Thou, Deva, hast disclosed the hymn, and holy gift from mortal men.\n\np: Awake the Asvins, Deva Dawn! Up Mighty Lady of sweet strains! Rise, straightway, priest of offering! High glory to the gladdening draught!\n\np: Thou, Dawn, approaching with thy light shinest together with the Sun, and to this man-protecting home the chariot ofthe Asvins comes.\n\np: When yellow stalks give forth the juice, as cows from udders pour their milk, and voices sound the song of praise, the Asvins' worshippers show first.\n\np: Forward for glory and for strength, protection that shall conquer men, and power and skill, most sapient Ones!\n\np: When Asvins, worthy of our lauds, ye seat you in the father's house. With wisdom or the bliss ye bring.","people":["Indra","Soma","Vayu","Visnu","Yadu","Turvasa","KanVa","Asvins","Nasatyas","Deva","Dawn","Vimada","Kaksivan"],"places":["Heaven","Mid-Air"],"things":["Milk","Soma","Glory","Offering","Light","Air","Sun","Wealth","Men","Might","Juice","Song","Help","Home","Offspring","Mighty","Car","Praise","Hymn","Gift","Ascend","Offers","Offerings","Bliss","Songs","call","Gifts"],"groups":["Devas","Sons","Worshippers","Father","Man","Adityas","Rbhus"],"concepts":["Wonder-Workers","Holy","Strength","Wisdom","Offering","Offerings","Speech"],"hash":"md5-r3EqmUS70pLTDgv1TA42KA==","created":"Monday, April 8, 2024 - 10:51:52 PM"},{"id":"26a4c56e-13ac-4144-bb54-acc76b1c9c3c","key":"08010","book":"08","title":"HYMN X. Asvins.","link":"https://indra.ai/rigveda/hymns/08010.html","text":"p: WHETHER ye travel far away or dwell in yonder light of heaven, or in a mansion that is built above the sea, come thence, ye Asvins, hitherward.\n\np: Or if for Manu.ye prepared  'the offering, remember also Kanva's son. I call Narasamsa, indra, Visnu, all the gods, the Asvins borne by rapid steeds.\n\np: Those Asvins I invoke who work marvels, brought hither to receive, with whom our friendship is most famed, and kinship passing that of Devas.\n\np: On whom the solemn rites depend, whose worshippers rise without the Sun: These who foreknow the holy work of offering, and by their Deva.ead drink the sweets of Soma juice.\n\np: Whether ye, Lords of ample wealth, now linger in the cast or west, with Druhyu, or with Anu, Yadu, Turvaga, I call you hither; come to me.\n\np: Lords of great riches, whether through the firmament ye fly or speed through heaven and earth, or with your Deva like natures stand upon your cars, come thence, O Asvins, hitherward.","people":["Indra","Soma","Visnu","Yadu","KanVa","Asvins","Narasamsa","Deva","Turvaga"],"places":["Earth","Heaven","Firmament"],"things":["Steeds","Work","Soma","Offering","Light","Sun","Wealth","Juice","call","Riches","Cars"],"groups":["Devas","Worshippers","Son"],"concepts":["Friendship","Cars","Holy","Offering"],"hash":"md5-MuQ79FbX4eu3AoBVnSy6DQ==","created":"Monday, April 8, 2024 - 10:51:52 PM"},{"id":"e604e984-3084-44c7-928b-ae3a4d11d7e4","key":"08011","book":"08","title":"HYMN XI. Agni.","link":"https://indra.ai/rigveda/hymns/08011.html","text":"p: THOU Agni, Deva.mid mortal men, art guard of sacred rites, thou art To be adored at offerings.\n\np: O Mighty Agni, thou must be glorified at our festivals, bearing our offerings to the Devas.\n\np: O Jatavedas Agni, fight and drive our foes afar from us, themand their godless enmities.\n\np: Thou, Jatavedas, seekest not the worship of a hostile man, However nigh itbe to thee.\n\np: We sages, mortals as we are, adore the mighty name oof thee, Immortal Jatavedas' name.\n\np: Sages, we call the Sage to help, mortals, we call the Deva.to aid: We call on Agni with our songs.\n\np: May Vatsa draw- thy mind away even from thy loftiest dwelling-place, Agni, with song that yearns for thee.\n\np: Thou art the same in many a place: mid all the people thou art Lord. In fray and fightt we call on thee.\n\np: When we are seeking strength we call Agni to help us in the strife, the giver of rich gifts in war.\n\np: Ancient, adorablie at offers, Monk from of old, meet for our praise, thou sittest. Fill full and satisfy thy body, Agni, and win us happiness by offering worship.","people":["Agni","Deva"],"places":[],"things":["Worship","Lord","Offering","Men","Song","Help","Mighty","Praise","Offers","People","Offerings","Songs","Sage","call","Gifts"],"groups":["Devas","Jatavedas","Immortal","Man"],"concepts":["Immortal","Sacred","Strength","Offering","Offerings","Giver"],"hash":"md5-VXJjk3Dg6Lq7CnEwyD8QCA==","created":"Monday, April 8, 2024 - 10:51:52 PM"},{"id":"a4f0cff6-b613-4473-b498-e40935f692f6","key":"08012","book":"08","title":"HYMN XII. Indra.","link":"https://indra.ai/rigveda/hymns/08012.html","text":"p: JOY, Mightiest Indra, known and marked, sprung most from Soma-draughts, where thou smitest down the greedy fiend, for that we long.\n\np: Wherewith thou bolpest Adhrigu, the great Dasagva, and the Deva.Who stirs the sunlight, and the sea, for that we long.\n\np: Wherewith thou dravest forth like cars Sindhu and all the mighty floods To go the way ordained by Law, for that we long.\n\np: Accept this laud for aid, made pure like oil, thou Caster of the Stone, Whereby even in a moment thou hast waxen great.\n\np: Be pleased, Song-lover, with this song it flows abundant like the sea. Indra, with all thy assists thou hast waxen great.\n\np: The Deva who from afar hath sent gifts to maintain our friendship's bond, Thou. spreading them like rain from heaven, hast waxen great.\n\np: The beams that mark him have grown strong, the thunder rests between his arms, when, like the Sun, he hath increased both Heaven and Earth.\n\np: When, Mighty Lord of Heroes, thou didst cat a thousand buffaloes, then grew and waxed exceeding great thine Indra-power.\n\np: Indra consumeth with the rays of Surya the malicious man: Like Agni conquering the woods, he hath grown strong.\n\np: This newest thought of ours that suits the time approaches unto thee: Serving, beloved in many a place it metes and marks.\n\np: The pious germ of offering directly purifies the soul. By Indra's lauds it waxes great, it metes and marks.\n\np: Indra who wins the friend hath spread himself to drink the Soma-draught: Like worshipper's dilating praise; it metes and marks.\n\np: He whom the sages, living men, have gladdened, offering up their hymns, Hath swelled like oil of offering in Agni's mouth.\n\np: Aditi also hath brought forth a hymn for Indra, Sovran Lord: The work of offering for help is glorified.\n\np: The ministering monks have sung their songs for aid and eulogy: Deva, thy Bays turn not from the rite which Law ordains.\n\np: If, indra, thou drink Soma by Visnu's or Trta Aptya's side, or with the Maruts take delight in flowing drops;\n\np: Or, Sakra, if thou gladden thee afar or in the sea of air, Rejoice thee in this juice of ours, in flowing drops.\n\np: Or, Lord of Heroes if thou aid the worshipper who shed; the. or him whose laud delights thee, and his flowing drops.\n\np: To magnify the Deva, the Deva, indra, yea, indra for your help, and promptly end  'the offering-this have they gained.\n\np: With worship, him whom men adore, with Soma, him who drinks it most, indra with lauds have they increasedthis have they gained.\n\np: His leadings are with power and might and his instructions manifold: He gives the worshipper all wealth: this have they gained.\n\np: For subduing Vrtra have the Devas set Indra in the foremost place. Indra the choral bands have sung, for vigorous strength.\n\np: We to the Mighty with our might, with lauds to him who hears our call, with holy hymns have sung aloud, for vigorous strength.\n\np: Not earth, nor heaven, nor firmaments contain the Thunder-wielding Deva. They shake before his violent rush and vigorous strength.\n\np: What time the Devas, O Indra, get thee foremost in the furious fight, then thy two beautiful Bay Steeds carried thee on.\n\np: When Vrtra, stayer of the floods, thou si\"est, Thundeicr with might, then thy two beautiful Bay Steeds carried thee on.\n\np: When Visnu, through thine energy, strode wide those three great steps of his, then thy two beautiful Bay Steeds carried thee on.\n\np: When thy two beautiful Bay Steeds grew great and greater day by day, Even then all creatures that had life bowed down to thee.\n\np: When, indra, all the Marut folk humbly submitted them to thee, Even then all creatures that had life bowed down to thee.\n\np: When yonder Sun, that brilliant light, thou settest in the heaven above, Even then all creatures that had life bowed down to thee.\n\np: To thee, O Indra, with this thought the sage lifts up this eulogy, Akin and leading as on foot to offerings.\n\np: When in thine own dear dwelling all gathered have lifted up the voice Milk-streams at worship's central spot, for offering,\n\np: As Monk, O Indra, give us wealth in brave men and good steeds ana kine That we may first remember thee for offering.","people":["Indra","Soma","Vrtra","Agni","Visnu","Sakra","Deva","Surya","Aditi","Trta","Aptya","Sindhu"],"places":["Earth","Heaven"],"things":["Worship","Milk","Steeds","Work","Lord","Soma","Offering","Light","Air","Sun","Wealth","Men","Streams","Might","Juice","Rain","Song","Joy","Help","Strong","Mighty","Praise","Voice","Brave","Worshipper","Delight","Hymn","Heroes","Offerings","Songs","Drops","Friend","Sage","call","Cars","Life","Gifts"],"groups":["Devas","Maruts","Marut","Man","Monks"],"concepts":["Good","Life","Friendship","Beautiful","Cars","Holy","Strength","Offering","Offerings","Pleased"],"hash":"md5-7rLgwjvg5Ykz0es97vMnhA==","created":"Monday, April 8, 2024 - 10:51:52 PM"},{"id":"6ebcd846-661d-4005-b3b3-f7c74b163c8e","key":"08013","book":"08","title":"HYMN XIII. Indra.","link":"https://indra.ai/rigveda/hymns/08013.html","text":"p: INDRA, when Soma juices flow, makes his mind pure and meet for lauds. He gains the power that brings success, for great is he.\n\np: In heaven's first region, in the seat of Devas, is he who brings success, most glorious, prompt to save, who wins the water-floods.\n\np: Him, to win strength, have I invoked, even Indra mighty for the fray. Be thou most near to us for bliss, a friend to aid.\n\np: Indra, Song -lover, here for thee the worshipper's libation flows. Rejoicing in this sacred grass thou shinest forth.\n\np: Even now, O Indra, give us that which, pressing juice, we crave of thee. Bring us wealth manifold which finds the light of heaven.\n\np: What time the zealous worshipper hath boldly sung his songs to theelike branches of a tree up-grows what they desire.\n\np: Generate songs even as of old, give car unto the singer's call. Thou for the pious hast grown great at each carouse.\n\np: Sweet strains that glorify him play like waters speeding down a slope, Yea, him who in this song is called the Lord of Heaven;\n\np: Yea, who alone is called the Lord, the single Ruler of the folk, by worshippers seeking aid. May he joy in the draught.\n\np: Praise him, the Glorious, skilled in song, Lord of the two victorious Bays: They seek the worshipper's abode who bows in meditation.\n\np: Put forth thy strength: with dappled Steeds come, thou of mighty intellect, with swift Steeds to  'the offering, for ’tis thy joy.\n\np: Grant wealth to those who praise thee, Lord of Heroes, Mightiest Indra: give Our princes everlasting fame and opulence.\n\np: I call thee when the Sun is risen, I call thee at the noon of day: With thy car-horses, indra, come wellpleased to us.\n\np: Speed forward hither, come to us, rejoice thee in the milky draught: Spin out the thread of ancient time, as well is known.\n\np: If, Sakra, Vrtra conquerer, thou be far away or near to us. Or in the sea, thou art the guard of Soma juice.\n\np: Let songs we sing and Soma-drops expressed by us make Indra strong: The tribes who bring oblations find delight in him.\n\np: Him sages longing for his aid, with offerings brought in eager hastehim. even as branches, all mankind have made to grow.\n\np: At the Trkadrukas the Devas span offering that stirred the mind: May our songs strengthen him who still hath strengthened us.\n\np: When, true to duty, at due times the worshipper offers lauds to thee, they call him Purifier, pure, and Wonderful.\n\np: That mind of Rudra, fresh and strong, moves conscious in the ancient ways, with reference whereto the wise have ordered this.\n\np: If thou elect to be my Friend drink of this offerings juice, by help whereof we may subdue all enemies.\n\np: O Indra, Lover of the song, when shall thy praiser be most blest? When wilt thou grant us wealth in herds of kine and steeds?\n\np: And thy two highIy-lauded Bays, strong stallions, draw thy car who art Untouched by age, most gladdening car for which we pray.\n\np: With ancient offerings we implore the Young and Strong whom many praise. He from of old hath sat upon dear sacred grass.\n\np: Wax miglity, thou whom many laud for aids which Rsis have extolled. Pour down for us abundant food and guard us well.\n\np: O Indra, Caster of the Stone, thou helpest him who praises thee: From offering I send to thee a mindyoked hymn.\n\np: Here, yoking for the Soma-draught these Horses, sharers of thy feast, Thy Bay Steeds, indra, fraught with weal tb, consent to come.\n\np: Attendants on thy glory, let the Rudras roar assent to thee, and all the Marut companies come tothe feast.\n\np: These his victorious followers bold in the heavens the place they love, Leagued in the heart of offering, as well we know.\n\np: That we may long behold the light, what time the ordered rite proceeds. He duly measures, as he views,  'the offering.\n\np: O Indra, strong is this thy car, and strong are these Bay Steeds of thine: O Satakratu, thou art strong, strong is our call.\n\np: Strong is the press-stone, strong thy joy, strong is the flowing Soma juice: Strong is the rite thou furtherest, strong is our call.\n\np: As strong I call on thee the Strong, O Thunderer with thy thousand aids: For thou hast won the hymn of praise. Strong is our call.","people":["Indra","Soma","Vrtra","Satakratu","Sakra","Attendants"],"places":["Heaven"],"things":["Mankind","Steeds","Lord","Meditation","Soma","Waters","Water","Glory","Glorious","Singer","Offering","Light","Sun","Wealth","Food","Flow","Juice","Song","Joy","Help","Wise","Strong","Mighty","Grass","Car","Praise","Worshipper","Delight","Hymn","Heroes","Offers","Offerings","Bliss","Songs","Drops","Friend","Horses","call"],"groups":["Devas","Marut","Rudras","Worshippers","Rsis"],"concepts":["Love","Sacred","Strength","Offering","Offerings","Glorious","Swift"],"hash":"md5-v/aDqooTedHgfg/53LDZmA==","created":"Monday, April 8, 2024 - 10:51:52 PM"},{"id":"47df824d-67f7-4e15-a7fc-34258d21df5e","key":"08014","book":"08","title":"HYMN XIV. Indra.","link":"https://indra.ai/rigveda/hymns/08014.html","text":"p: IF I, O Indra, were, like thee, the single Sovran of all wealth, My worshipper should be rich in kine.\n\np: I should be fain, O Lord of Power, to strengthen and enrich the sage, Were I the Lord of herds of kine.\n\np: To worshippers who press the juice thy goodness, indra, is a cow Yielding in plenty kine and steeds.\n\np: None is there, indra, Deva.or man, to hinder thy munificence, the wealth which, lauded, thou wilt give.\n\np: The offering made Indra strong when he unrolled the earth, and made Himself a diadem in heaven.\n\np: Thine aid we claim, O Indra, thine who after thou hast waxen great Hast won all treasure.s for thine own.\n\np: In Soma's ecstasy Indra spread the firmament and realms of light, when he cleft Vala limb from limb.\n\np: Showing the hidden he drave forth the cows for the Angirases, and Vala he cast headlong down.\n\np: By Indra were the lumirious realms of heaven established and secured, Firm and immovable from their place.\n\np: Indra, thy laud moves quickly like a joyous wave of water-floods: Bright shine the drops that gladden thee.\n\np: For thou, O Indra, art the Deva whom hymns and praises magnify: Thou blessest those who worship thee.\n\np: Let the two long-maned Bay Steeds bring Indra to drink the Soma juice, the Bountiful to  'our offering.\n\np: With waters' foam thou torest off, indra, the head of Namuci, Subduing all contending hosts.\n\np: The Dasyus, when they fain would climb by magic arts and mount to heaven, Thou, indra, castest down to earth.\n\np: As Soma-drinker conquering all, thou scatteredst to every side Their settlement who poured no gifts.","people":["Indra","Soma","Deva","Namuci"],"places":["Earth","Heaven","Firmament"],"things":["Worship","Steeds","Lord","Soma","Waters","Water","Offering","Shine","Light","Treasure","Wealth","Juice","Strong","Worshipper","Drops","Sage","Cow","Gifts"],"groups":["Dasyus","Worshippers","Angirases","Man"],"concepts":["Offering"],"hash":"md5-fPjglJf2L50eJs/llkW34Q==","created":"Monday, April 8, 2024 - 10:51:52 PM"},{"id":"fe7fa79d-d9ca-4428-95cf-21ed27bcd203","key":"08015","book":"08","title":"HYMN XV. Indra.","link":"https://indra.ai/rigveda/hymns/08015.html","text":"p: SING forth to him whom many men invoke, to him whom many laud. Invite the powerful Indra with your songs of praise.\n\np: Whose lofty might-for doubly strong is he-supports the heavens and earth, and hills and plains and floods and light with manly power.\n\np: Such, praised by many! thou art King alone thou smitest Vrtras dead, to gain, O Indra, spoils of war and high renown.\n\np: We sing this strong and wild delight of thine which conquers in the fray, Which, Caster of the Stone! gives room and shines like gold.\n\np: Wherewith thou also foundest lights for Ayu and for Manu's sake: Now joying in this sacred grass thou beamest forth.\n\np: This day too singers of the hymn praise, as of old, this might of thine: Win thou the waters day by day, thralls of the strong.\n\np: That lofty Indra-power of thine, thy strength and thine intelligence, Thy thunderbolt for which we long, the wish makes keen.\n\np: O Indra. Heaven and Earth augment thy manly power and thy renown; The waters and thy mountains stir and urge thee on.\n\np: Visnu the lofty ruling Power, Varuna, Mitra sing thy praise: In thee the Marut3' company have great delight.\n\np: O Indra, thou wast born the Lord of men, most liberal of thy gifts: Excellent deeds forevermore are all thine own.\n\np: Ever, alone, O highly-praised, thou sendest Vrtras to their rest: Non else than Indra executes the mighty deed.\n\np: Though here and there, in varied hymns, indra, men call on thee for aid, Still with our heroes fight and win the light of heaven.\n\np: Already have all forms of him entered our spacious dwelling-place: For victory stir thou Indra, up, the Lord of Might.","people":["Indra","Visnu","Mitra","Varuna","Ayu"],"places":["Earth","Heaven"],"things":["Victory","Lord","Born","Mountains","Waters","Light","Men","Might","Gold","Strong","Mighty","Grass","Praise","Delight","Hymn","Heroes","Excellent","Songs","King","call","Gifts"],"groups":["Vrtras"],"concepts":["Sacred","Strength","Powerful","Intelligence"],"hash":"md5-tB5irGfQDLafeIwxbybpVw==","created":"Monday, April 8, 2024 - 10:51:52 PM"},{"id":"fbfdbf07-cec4-4832-bf94-8dde0c8f2966","key":"08016","book":"08","title":"HYMN XVI. Indra.","link":"https://indra.ai/rigveda/hymns/08016.html","text":"p: PRAISE Indra whom our songs must laud, sole Sovran of mankind, the Chief Most liberal who controlleth men.\n\np: In whom the hymns of praise delight, and all the glory-giving songs. Like the floods' longing for the sea.\n\np: Him I invite with eulogy, best King, effective in the fight, Strong for the gain of mighty spoil.\n\np: Whose perfect ecstasies are wide, profound, victorious, and give joy in the field where heroes win.\n\np: Him, when the spoils of war are staked, men call to be their advocate: They who have Indra win the day.\n\np: Men honour him with stirring songs and magnify with solemn rites: Indra is he who giveth case.\n\np: Indra is priest and Rsi, he is much invoked by many men, and mighty by his mighty powers.\n\np: Meet to be lauded and invoked, true Hero with his deeds of might, Victorious even when alone.\n\np: The men, the people magnify that Indra with their Slina. songs, with hymns and sacred eulogies\n\np: Him who advances them to wealth, sends light to lead them in the war, and quells their foemen in the fray.\n\np: May he, the saviour much-invoked. May Indra bear us in a ship Safely beyond all enemies.\n\np: As such, O Indra, honour us with gifts of booty, further us, and lead us to felicity.","people":["Indra"],"places":[],"things":["Mankind","Glory","Light","Wealth","Men","Might","Joy","Strong","Mighty","Chief","Praise","Delight","Heroes","People","Powers","Songs","Hero","King","call","spoil","Gifts"],"groups":[],"concepts":["Sacred"],"hash":"md5-2MZ8pXy6k2DQFGh9/cV5Rg==","created":"Monday, April 8, 2024 - 10:51:52 PM"},{"id":"44f6d4f5-de29-48e7-af0c-4b947c8b9cb0","key":"08017","book":"08","title":"HYMN XVII Indra.","link":"https://indra.ai/rigveda/hymns/08017.html","text":"p: COME, we have pressed the juice for thee; O Indra, drink this Soma here Sit thou on this my sacred grass.\n\np: O Indra, let thy long-maned Bays, yoked by prayer, bring thee hitherward Give car and listen to our meditations.\n\np: We Soma-bearing Brahmans call thee Soma-drinker with thy friend, We, indra, bringing Soma juice.\n\np: Come unto us who bring the juice, come unto this our eulogy, Fair-visored! drink thou of the juice.\n\np: I pour it down within thee, so through all thy members let it spread: Take with. thy tongue the pleasant drink.\n\np: Sweet to thy body let it be, delicious be the savoury juice: Sweet be the Soma to thine heart.\n\np: Like women, let this Soma-draught, invested with its robe, approach, O active Indra, close to thee.\n\np: Indra, transported with the juice, vast in his bulk, strong in his neck And stout arms, smites the Vrtras down.\n\np: O Indra, go thou forward, thou who rulest over all by might: Thou Vrtra conquerer subdue the fiends,\n\np: Long be thy grasping-hook wherewith thou givest ample wealth to him Who sheds the juice and worships thee.\n\np: Here, indra, is thy Soma-draught, made pure upon the sacred grass: Run hither, come and drink thereof.\n\np: Famed for thy radiance, worshipped well this juice is shed for thy delight Thou art invoked, Akhandala!\n\np: To Kundapayya, grandson's son, grandson of Srngavrs! to thee, to him have I addressed my thought.\n\np: Strong pillar thou, Lord of the home armour of Soma-offerers: The drop of Soma breaketh all the strongholds down, and Indra is the Rsis’ Friend.\n\np: Holy Prdikusanu, winner of the spoil, on eminent o’er many men, Lead on the wild horse Indra with his vigorous grasp forward to drink the Soma juice.","people":["Indra","Soma","Vrtra"],"places":[],"things":["Lord","Soma","Wealth","Men","Might","Juice","Home","Strong","Grass","Car","Delight","Friend","Horse","call","spoil"],"groups":["Brahmans","Son","Rsis","Vrtras"],"concepts":["Holy","Sacred","Worshipped","Winner"],"hash":"md5-0IsIzyrZmWC3dMjxwblK7w==","created":"Monday, April 8, 2024 - 10:51:52 PM"},{"id":"c082ef78-bed9-4fab-a5c9-9b60119f578e","key":"08018","book":"08","title":"HYMN XVIII. Adityas.","link":"https://indra.ai/rigveda/hymns/08018.html","text":"p: Now let the mortal offer prayer to win the unexampled grace of these Adityas and their aid to cherish life.\n\np: For not an enemy molests the paths which these Adityas tread: Infallible guards, they strengthen us in happiness.\n\np: Now soo. May Bhaga, Savitar, Varuna, Mitra, Aryaman Give us the shelter widely spread which we implore.\n\np: With Devas come thou whose fostering care none checks, O Devas Aditi: Come, dear to many, with the Lords who guard us well.\n\np: For well these Sons of Aditi know to keep enmities aloof, Unrivalled, giving ample room, they save from woe.\n\np: Aditi guard our herd by day, Aditi, free from guile, by night, Aditi, ever strengthening, save us from grief!\n\np: And in the day our hymn is this: May Aditi come nigh to help, with loving-kindness bring us weal and chase our foes.\n\np: An. May the Asvins, the divine Pair of Physicians, send us health: May they remove iniquity and chase our foes.\n\np: May Agni bless us with his fires, and Surya warm us pleasantly: May the pure Wind breathe sweet on us, and chase our foes.\n\np: Drive ye disease and strife away, drive ye away malignity: Adityas, keep us ever far from sore distress.\n\np: Remove from us the arrow, keep famine, Adityas! far away: Keep enmities afar from us, Lords of all wealth!\n\np: Now, O Adityas, grant to us the shelter that lets man go free, Yea, even the sinner from his sin, ye Bounteous Devas 1\n\np: Whatever mortal with the powe r of demons fain would injure us, may he, impetuous, suffer harm by his own deeds.\n\np: May sin o’ertake our human foe, the man who speaketh evil thinghim who would cause our misery, whose heart is false.\n\np: Devas, ye are with the simple ones, ye know each mortal in your hearts; Ye, Vasus, well discriminate the false and true.\n\np: Fain would we have the sheltering aid of mountains and of water-floods: Keep far from us iniquity, O Heaven and Earth.\n\np: So with auspicious sheltering aid do ye, O Vasus, carry us Beyond all trouble and distress, borne in your ship.\n\np: Adityas, ye Most MightyOnes, grant to our children and their seed Extended term of life that the, may live long days.\n\np: Offering, O Adityas, is your inward monitor: be kind, for in the bond of kindred we are bound to you.\n\np: The Maruts’ high protecting aid, the Asvins, and the Deva who saves, Mitra and Varuna for weal we supplicate.\n\np: Grant us a home with triple guard, Aryaman, Mitra, Varuna! Unthreatened, Maruts! meet for praise, and filled with men.\n\np: And as we human beings, O Adityas, are akin to death, Graciously lengthen ye our lives that we may live.","people":["Agni","Mitra","Varuna","Asvins","Savitar","Bhaga","Deva","Surya","Aditi","Aryaman"],"places":["Earth","Heaven"],"things":["Mountains","Water","Offering","Wealth","Men","Help","Home","Praise","Hymn","Life","Death"],"groups":["Devas","Maruts","Sons","Human","MightyOnes","Man","Vasus","Adityas"],"concepts":["Evil","Death","Life","Divine","Offering","Auspicious"],"hash":"md5-RcRKmpnSO7vjNz8An4yz+A==","created":"Monday, April 8, 2024 - 10:51:53 PM"},{"id":"49409ba1-b6fb-4c20-ac72-f6a2790f07ab","key":"08019","book":"08","title":"HYMN XIX. Agni.","link":"https://indra.ai/rigveda/hymns/08019.html","text":"p: SING praise to hiin, the Lord of Light. The Devas have made the Deva.to be their messenger, and sent oblation to Devas.\n\np: Agni, the Bounteous Giver, bright with varied flames, laud thou, O singer Sobhari- Him who controls this sacred food with Soma blent, who hath first claim to offering.\n\np: Thee have we chosen skilftillest in offering, Immortal Monk among the Devas, Wise finisher of this holy rite:\n\np: The Son of Strength, the blessed, brightly shining One, Agni whose light is excellent. May be by offering win us in heaven the grace of Mitra, Varuna, and the Floods.\n\np: The mortal who hath ministered to Agni with oblation, fuel, ritual lore, and reverence, skilled in offering.\n\np: Verily swift to run are his fleet-footed steeds, and most resplendent fame is his. No trouble caused by Devas or wrought by mortal man from any side o’ertaketh him.\n\np: May we by thine own fires be well supplied with fire, O Son of Strength, O Lord of Might: Thou as our Friend hast worthy men.\n\np: Agni, who praises like a guest of friendly mind, is as a car that brings us gear. Also in thee is found perfect security thou art the Sovran Lord of wealth.\n\np: That man, moreover, merits praise who brings, auspicious Agni, offerings gifts May he win riches by his thoughts.\n\np: He for whose offering thou standest up erect is prosperous and rules o’er men. He wins with coursers and with singers killed in song: with heroes he obtains the prize.\n\np: He in whose dwelling Agni is chief ornament, and, all-desired, loves his laud well, and zealously tends his offerings-\n\np: His, or the lauding sage's word, his, Son of Strength! who Is most prompt with sacred gifts, Set thou beneath the Devas, Vasu, above mankind, the speech of the intelligent.\n\np: He who with offerings gifts or homage bringeth very skilful Agni nigh, or him who flashes fast with song,\n\np: The mortal who with blazing fuel, as his laws command, adores the Perfect Deva, Blest with his thoughts in splendour shall exceed all men, as though he overpassed the floods.\n\np: Give us the splendour, Agni, whic. May overcome each greedy fiend in our abode, the wrath of evil-hearted folk.\n\np: That, wherewith Mitra, Varuna, and Aryaman, the Asvins, Bhaga give us light, tha. May we, by thy power finding best furtherance, worship, O Indra, helped by thee.\n\np: O Agni, most devout are they, the sages who have set thee Sage exceeding wise, O Deva, for men to look upon:\n\np: Who have arranged thine altar Blessed Deva, at morn brought thine oblation, pressed the juice. They by their deeds of strength have won diem, mighty wealth, who have set all their hope in thee.\n\np: -May Agni worshipped bring us bliss. May the gift, Blessed One, and offering bring bliss; Yea. May our praises bring us bliss.\n\np: Show forth the mind that brings success in war with fiends, wherewith thou conquerest in fight. Bring down the many firm hopes of our enemies, and let us vanquish with thine aid.\n\np: I praise with song the Friend of man, whom Devas sent down to be herald and messenger, best worshipper, bearer of our gifts.\n\np: Thou unto sharp-toothed Agni, Young and Radiant Deva, proclaimest with thy song the feast- Agni, who for our sweet strains moulds heroic strength when sacred oil is offered him,\n\np: While, served with offerings oil, now upward and now downward Agni moves his sword, as doth the Asura his robe.\n\np: The Deva, the Friend of man, who bears our gifts to heaven, the Deva with his sweet-smelling mouth, Distributes, skilled in offering, his precious things, invoking Monk, Immortal Deva.\n\np: Son of Strength, Agni, if thou wert the mortal, bright as Mitra, I worshipped with our gifts! And I were the Immortal God\n\np: I would not give thee up, Vasu, to calumny, or misery, O Bounteous One. My worshipper should feel no hunger or distress, nor, Agni, should he live in sin.\n\np: Like a son cherished in his father's houi§e, let our oblation rise unto the Devas.\n\np: With thine immediate ai. May I, excellent Agni, ever gain my wish A mortal with a Deva.to help.\n\np: O Agni, by thy wisdom, by thy bounties, by thy leadin. May I gather wealth. Excellent Agni, thou art called my Providence: delight thou to be liberal.\n\np: Agni, he conquers by thine aid that brings him store of noble heroes and great strength, whose bond of friendship is thy choice.\n\np: Thy spark is black and crackling, kindled in due time, O Bounteous, it is taken up. Thou art the dear Friend of the mighty Mornings: thou shinest in glimmerings of the night.\n\np: We Sobharis have come to him, for assist, who is good to help with thousand powers, the Sovran, Trasadasyu's Friend.\n\np: O Agni, thou on whom all other fires depend, as branches on the parent stem, I make the treasure.s of the folk, like songs, mine own, while I exalt thy sovran might.\n\np: The mortal whom, Adityas, ye, Guilelew, lead to the farther bank Of all the princes, Bounteous Ones\n\np: Whoe’er he be, Man-ruling Kings! the Regent of the race of men- May we, O Mitra, Varuna, and Aryaman, like him be furtherers of your law.\n\np: A gift of fifty female slaves hath Trasadasyu given me, purukutsa's son, most liberal, kind, lord of the brave.\n\np: And Syava too for me led forth a strong steed at Suvastu's ford: A herd of three times seventy kine, good lord of gifts, he gave to me.","people":["Indra","Soma","Agni","Mitra","Varuna","Asvins","Bhaga","Deva","Aryaman","Vasu"],"places":["Heaven"],"things":["Worship","Mankind","Steeds","Lord","Reverence","Soma","Singer","Offering","Light","Treasure","Wealth","Food","Men","Might","Juice","Song","Help","Wise","Strong","Mighty","Car","Chief","Praise","Brave","Worshipper","Delight","Heroes","Gift","Splendour","Excellent","Powers","Offerings","Bliss","Songs","Friend","Sage","Riches","Security","Gifts"],"groups":["Devas","Asura","Kings","Father","Son","Immortal","Man","Adityas"],"concepts":["Good","Evil","Friendship","Heroic","Immortal","Holy","Sacred","Strength","Wisdom","Devout","Offering","Offerings","Worshipped","Giver","Auspicious","Swift","Noble","Speech"],"hash":"md5-AjlPy7VdTi99YsTPZdTZpw==","created":"Monday, April 8, 2024 - 10:51:53 PM"},{"id":"a9b94b96-8bdb-41a2-91fe-7ca5b9c84ea5","key":"08020","book":"08","title":"HYMN XX Maruts.","link":"https://indra.ai/rigveda/hymns/08020.html","text":"p: LET none, Swift Travellers! check you: come hither, like-spirited, stay not far away, Ye benders even of what is firm.\n\np: Maruts, Rbhuksans, Rudras come ye with your cars strong-fellied and exceeding bright. Come, ye for whom we long, with food, to offering, come ye with love to Sobbari.\n\np: For well we know the vigorous might of Rudra's Sons, the Martits, who are passing strong, Swift Visnu's band, who send the rain.,\n\np: Islands are bursting forth and misery is stayed: the heaven and earth are joined in one. Decked with bright rings, ye spread the broad expanses out, when ye, Self. luminous, stirred yourselves.\n\np: Even things immovable shake and reel, the mountains and the forest trees at your approach, and the earth trembles as ye come.\n\np: To lend free course, O Maruts, to your furious rush, heaven high and higher still gives way, Where they, the Heroes mighty with their arms, display their gleaming omaments on their forms.\n\np: After their Deva like nature they, the bull. like Heroes, dazzling and impetuous, wear Great splendour as they show erect.\n\np: The pivot of the Sobharis' chariot within the golden box is balmed with milk. May they the Well-born, Mighty, kindred of the Cow, aid us to food and to delight.\n\np: Bring, ye who sprinkle balmy drops. oblations to your vigorous Marut company, to those whose leader is the Bull.\n\np: Come hither, O ye Mares, on your stronghorsed car, solid in look, with solid naves. Lightly like winged falcons, O ye Heroes, come, come to enjoy our ofrerings.\n\np: Their decoration is the same: their omaments of gold are bright upon their arms; Their lances glitter splendidly.\n\np: They toil not to defend their bodies from attack, strong Heroes with their mighty arms. Strong are your bows and strong the weapons in your cars, and glory sits on every face.\n\np: Whose name extendeth like a sea, alone, resplendent, so that all have joy in it, and life-power like ancestral might.\n\np: Pay honour to these Maruts and sing praise to them, for of the wheel-spokes of the car Of these loud roarers none is last: this is their power, this moves them to give mighty gifts.\n\np: Blest by your favouring help was he, O Maruts, at the earlier flushings of the morn, and even now shall he be blest.\n\np: The strong man to whose offering, O Heroes, ye approach that y. May taste thereof, with glories and with war that winneth spoil shall gain great bliss, ye Shakers of the world.\n\np: Even as Rudra's Sons, the brood of the Creator Dyaus, the Asura, desire, O Youthful Ones, so shall it be:\n\np: And these the bounteous, worthy of the Maruts who move onward pouring down the rain- Even for their sake, O Youthful Ones, with kindest heart take us to you to be your own.\n\np: O Sobhari, with newest song sing out unto the youthful purifying Bulls, Even as a plougher to his steers.\n\np: Who, like a celebrated boxer, overcome the challengers in every fight: They who, like shining bulls, are most illustrious-honour those Maruts with thy song.\n\np: Allied by common ancestry, ye Maruts, even the Cows, alike in energy, Lick, all by turns, each other's head.\n\np: Even mortal man, ye Dancers breast adorned with gold, attains to brotherhood with you. Mark ye and notice us, O Maruts; evermore your friendship is secured to us.\n\np: O Maruts, rich in noble gifts, bring us a portion of the Maruts’ medicine, Ye Coursers who are Friends to us.\n\np: Haters of those who serve you not, bliss-bringers, bring us bliss with those auspicious aids Wherewith ye are victorious and guard Sindhu well, and assist Krvi in his need.\n\np: Maruts, who rest on fair trimmed grass, what balm soever Sindhu or Asikni hath, or mountains or the seas contain.\n\np: Ye carry on your bodies, ye who see it all: so bless us graciously therewith. Cast, Maruts, to the ground our sick man's malady: replace the dislocated limb.","people":["Visnu","Deva","Sindhu"],"places":["Earth","Heaven"],"things":["Leader","Milk","Born","Mountains","Glory","Offering","Creator","Food","Might","Rain","Song","Joy","Gold","Help","Strong","Mighty","Grass","Car","Praise","Delight","Heroes","Splendour","Friends","Bliss","Drops","Cow","spoil","Cars","Life","Gifts","Wheel"],"groups":["Asura","Dyaus","Maruts","Marut","Rudras","Rbhuksans","Sons","Steers","Brotherhood","Man"],"concepts":["Life","Friendship","Cars","Love","Offering","Auspicious","Swift","Noble","Creator"],"hash":"md5-7dDRNu0cKbI/Mn2CdyJZ0w==","created":"Monday, April 8, 2024 - 10:51:53 PM"},{"id":"3230cc56-9b14-489e-b746-04d634d9a2f4","key":"08021","book":"08","title":"HYMN XXI. Indra.","link":"https://indra.ai/rigveda/hymns/08021.html","text":"p: WE call on thee, O Matchless One! We seeking help, possessing nothing firm ourselves, Call on thee wonderful in fight\n\np: On thee for aid in offering. This youth of ours, the bold, the mighty, hath gonse forth. We therefore, we thy friends, indra, havie chosen thee, free-giver, as our Guardian Deva.\n\np: Come hither, for the drops are here, O Lord of corn-lands. Lord of horses, Lord of kine: Drink thou the Soma, Soma's Lord!\n\np: For we the kinless singers have drawn hither thee, O Indra, who hast numerous kin. With all the forms thou hast, comic thou of bull-like strength, come near to drink the Soma juice.\n\np: Sitting like birds beside thy meath., mingled with milk, that gladdeneth and exalteth thee, indra, to thee we sing aloud.\n\np: We speak to thee with this our reverential prayer. Why art thou pondering yet awhile? Here are our wishes; thou art liberal, Lord of Bays: we and our hymns are present here.\n\np: For not in recent times alone, O Indra, Thunder-armed, have we obtained thine aid. Of old we knew thy plenteous wealth.\n\np: Hero, we knew thy friendship and thy rich rewards: these, Thunderer, now we crave of thee. O Vasu, for all wealth that cometh of the kine, sharpen our powers, fair-visored Deva.\n\np: Him who of old hath brought to us this and that blessing, him I magnify for you, Even Indra, O my friends, for help\n\np: Borne by Bay Steeds, the Lord of heroes, ruling men, for it is he who takes; delight. May Maghavan bestow on us his worshippers hundreds of cattle and of steeds.\n\np: Hero. May we, with thee for Friend, withstand the man who pants against us in his wrath, in fight with people rich in kine.\n\np: May we be victors in the singer's battlesong, and meet the wicked, Much invoked! With heroes smite the foeman and show forth our strength. O Indra, further thou our thoughts.\n\np: O Indra, from all ancient time rivalless ever and companionless art thou: Thou seekest comradeship in war.\n\np: Thou findest not the wealthy man to be thy friend: those scorn thee who are flown with wine. What time thou thunderest and gatherest, then thou, even as a Father, art invoked.\n\np: O Indra, let us not, like fools who waste their lives at home, with friendship such as thine Sit idly by the poured-out juice.\n\np: Giver of kine. May we not miss thy gracious gifts: let us not rob thee of thine own. Strip even the strong places of the foe, and bring: thy gifts can never be made vain.\n\np: Indra or blest Sarasvati alone bestows such wealth, treasure. so great, or thou, O Citra, on the worshipper.\n\np: Citra is King, and only kinglings are the rest who dwell beside Sarasvati. He, like Parjanya with his rain, hath spread himself with thousand, yea, with myriad gifts.","people":["Indra","Soma","Citra","Maghavan","Sarasvati","Deva","Parjanya","Vasu"],"places":[],"things":["Meath","Milk","Steeds","Lord","Soma","Singer","Offering","Treasure","Wealth","Men","Juice","Rain","Help","Home","Strong","Mighty","Blessing","Worshipper","Delight","Heroes","People","Lord of Bays","Powers","Friends","Drops","Friend","Hero","King","Horses","call","Cattle","Gifts"],"groups":["Worshippers","Father","Man"],"concepts":["Friendship","Strength","Offering","Giver"],"hash":"md5-s41cBHcEViUNXZ4bwdmFVA==","created":"Monday, April 8, 2024 - 10:51:53 PM"},{"id":"3642159c-f188-4024-b4b8-e3bcee39e276","key":"08022","book":"08","title":"HYMN XXII. Asvins.","link":"https://indra.ai/rigveda/hymns/08022.html","text":"p: HITHERWARD have I called to-day, for assist, that most wondrous car Which ye ascended, Asvins, ye whose paths are red, swift to give Car, for Surya's sake.\n\np: Car ever young, much longed-for, easily invoked, soon guided, first in deeds of might, Which waits and serves, O Sobhari, with benevolence, without a rival or a foe.\n\np: These Asvins with our homage, these Two Omnipresent Deities Hitherward will we bring for kind help, these who seek the dwelling of the worshipper.\n\np: One of your chariot wheels is moving swiftly round, one speeds for you its onward course. Like a MilchCow, O Lords of splendour, and with haste let your benevolence come to us.\n\np: That chariot of yours which hath a triple seat and reins of gold, the famous car that traverseth the heaven and earth, thereon Nasatyas, Asvins, come.\n\np: Ye with your plough, when favouring Manu with your help, ploughed the first harvest in the sky. As such will we exalt you now, O Asvins, with our meditation and praise.\n\np: Come to us, Lords of ample wealth, by paths of everlasting Law, Whereby to high dominion ye with mighty strength raised Trksi, Trasadasyu's son.\n\np: This Soma pressed with stones is yours, ye Heroes, Lords of plenteous wealth. Approach to drink the Soma, come, drink in the worshipper's abode.\n\np: O Asvins, mount the chariot, mount the golden seat, ye who are Lords of plenteous wealth, and bring to us abundant food.\n\np: The aids wherewith ye helped Paktha and Adhrigt;, and Babhru severed from his friends. With those, O Asvins, come hither with speed and soon, and heal whatever is diseased.\n\np: When we continually invoke the Asvins, the resistless, at this time of day, We lovers of the song, with songs.\n\np: Through these, ye MightyOnes, come hither to my call which brings all blessings, wears all forms. Tlirough which, All-present Heroes, lavishest of food ye strengthened Krvi, come through these.\n\np: I speak to both of these as such, these Asvins whom I reverence at this time of day: With homage we entreat them both.\n\np: Ye who are Lords of splendour, ye whose paths are red, at eve, at mom, at offering, Give us not utterly as prey to mortal foe, ye Rudras, Lords of ample wealth.\n\np: For bliss I call. the blissful car, at morn the inseparable Asvins with their car I call, like Sobhari our sire.\n\np: Rapid as thought, and strong, and speeding to thejoy, bringing.your swiftly-coming help, be to us a protection even from far away Lords of great wealth, with many aids.'\n\np: Come, Wonder-Workers, to our home, our home, O Asvins, rich in wealth, steeds, and gold, Chief drinkers of the Soma's juice\n\np: Choice-worthy strength, heroic, firm and excellent, uninjured by the Raksas foe, At this your coming nigh, ye Lords of ample wealth and all good things. May we obtain.","people":["Soma","Asvins","Nasatyas","Surya"],"places":["Earth","Heaven","Sky"],"things":["Steeds","Reverence","Meditation","Soma","Offering","Wealth","Food","Might","Juice","Song","Gold","Help","Home","Strong","Mighty","Car","Chief","Praise","Worshipper","Heroes","Splendour","Excellent","Friends","Bliss","Songs","call","MilchCow"],"groups":["Rudras","Deities","Son","MightyOnes"],"concepts":["Good","Wonder-Workers","Heroic","Blessings","Strength","Offering","Benevolence","Swift"],"hash":"md5-Xo+ZrBy+62bgSk8jdNTEFg==","created":"Monday, April 8, 2024 - 10:51:53 PM"},{"id":"ca492ad0-015f-4d55-84cb-67b44c79b6db","key":"08023","book":"08","title":"HYMN XXIII. Agni.","link":"https://indra.ai/rigveda/hymns/08023.html","text":"p: WORSHIP thou Jatavedas, pray to him who willingly accepts, whose smoke wanders at will, and non. May grasp his flame.\n\np: Thou, all men's friend, Visvamanas, exaltest Agni with thy song, the Giver, and his flames with which no cars contend.\n\np: Whose resolute assault, to win vigour and food, deserves our praise. Through whose discovering power the Sage obtaineth wealth.\n\np: Up springs the imperishable flame, the flame of the Refulgent One Most bright, with glowing jaws and glory in his train.\n\np: Skilled in fair offering, extolled, arise in Deva like loveliness, Shining with lofty splendour, with effulgent light.\n\np: Called straight to our oblations, come, O Agni, through our eulogies, as thou hast been our envoy bearing up our gifts.\n\np: I call your Agni, from of old Invoking Monk of living men: Him with this song I laud and magnify for you.\n\np: Whom, wondrous wise, they animate with solemn rites and his fair form, Kind as a friend to men who keep the holy Law.\n\np: Him, true to Law, who perfecteth  'the offering. Law-loving ones! Ye with your song have gratified in the place of prayer.\n\np: May all  'our offerings go to him the truest Angiras, who is among mankind the most illustrious Monk.\n\np: Imperishable Agni, thine are all these high enkindled lightslike horses and like stallions showing forth their strength.\n\np: So give us, Lord of Power and Might, riches combined with hero strength, and guard us with our sons and grand. sons in our frays.\n\np: Soon as the eager Lord of men is friendly unto Manti's race, Agni averteth from us all the demon host.\n\np: O Hero Agni, Lord of men, on hearing this new laud of mine, Burn down the Raksasas, enchanters, with thy flame.\n\np: No mortal foe can e’er prevail by arts of magic over him Who serveth Agni well with offerings gifts.\n\np: Vyasva the sage, who sought the Bull, hath won thee, finder of good things: As suc. May we enkindle thee for ample wealth.\n\np: Usana Kavya stablished thee, O Agni, as Invoking Monk: Thee, Jatavedas, Sacrificing Monk for man.\n\np: All Deities of one accord appointed thee their messenger: Thou, Deva, through hearing, hadst first claim to offering.\n\np: Hi. May the mortal hero make his own immortal messenger. Far-spreading, purifier, him whose path is black.\n\np: With lifted ladles let us call him splendid with his brilliant flame, Men's ancient Agni, wasting not, adorable.\n\np: The man who pays the worship due to him with offerings gifts Obtains both plenteous nourishment and hero fame.\n\np: To Jatavedas Agni, chief in offeringss, first of all With homage goes the ladle rich with sacred gifts.\n\np: Even as Vyatya did. May we with these most high and liberal hymns Pay worship unto Agni of the splendid flame.\n\np: Now sing, as Sthurayupa sang, with lands to him who spreadeth far, to Agni of the home, O Rsi, Vyasva's son.\n\np: As welcome guest of human kind, as offspring of the forest kings, the sages worship ancient Agni for his aid.\n\np: For men's oblations brought to him who is the mighty Lord of all, Sit, Agni, mid our homage, on the sacred grass.\n\np: Grant us abundant. treasure.s, grant the opulence which many crave, with store of heroes, progeny, and high renown.\n\np: Agni, most Youthful of the Devas, send evermore the gift of wealth Unto Varosusaman and to all his folk.\n\np: A mighty Conqueror art thou, O Agni, so disclose to us Food in our herds of kine and gain of ample wealth.\n\np: Thou, Agni, art a glorious Deva. bring hither Mitra, Varuna, Imperial Sovrans, holy-minded, true to Law.","people":["Agni","Angiras","Mitra","Varuna","Usana","Deva","Raksasas"],"places":[],"things":["Worship","Mankind","Lord","Glory","Glorious","Offering","Light","Treasure","Wealth","Food","Men","Might","Song","Home","Wise","Offspring","Mighty","Grass","Chief","Praise","Heroes","Gift","Form","Adorable","Splendour","Offerings","Friend","Hero","Sage","Horses","call","Riches","Cars","Gifts"],"groups":["Devas","Jatavedas","Sons","Deities","Kings","Human","Son","Immortal","Progeny","Man","Visvamanas"],"concepts":["Good","Cars","Immortal","Holy","Sacred","Strength","Offering","Offerings","Giver","Glorious"],"hash":"md5-5wPKhmyXbbfbx65A7X0ayw==","created":"Monday, April 8, 2024 - 10:51:53 PM"},{"id":"1c2c96d8-7d91-4d6f-92e9-48311ef2d4e4","key":"08024","book":"08","title":"HYMN XXIV. Indra.","link":"https://indra.ai/rigveda/hymns/08024.html","text":"p: COMPANIONS, let us learn a prayer to Indra. whom the thunder arms, to glorify your bold and most heroic Friend.\n\np: For thou by subduing Vrtra art the Vrtra conquerer, famed for might. Thou. Hero, in rich gifts surpassest wealthy chiefs.\n\np: As such, when glorified, bring us riches of very wondrous fame, Set in the highest rank, Wealth-giver, Lord of Bays!\n\np: Yea, indra, thou disclosest that preeminent dear wealth of men: Boldly, O Bold One, glorified, bring it to us.\n\np: The workers of destruction stay neither thy right hand nor thy left: Nor hosts that press about thee, Lord of Bays, in fight.\n\np: O Thunder-armed, I come with songs to thee as to a stall with kine: Fulfil the wish and thought of him who sings thy praise.\n\np: Chief Vrtra conquerer, through the hymn of Visvamanas think of all, All that concerneth us, Excellent, Mighty Guide.\n\np: May we, O Vrtra conquerer, O Hero, find this thy newest boon, Longed-for, and excellent, thou who art much invoked!\n\np: O Indra, Dancer, Much-invoked! as thy great power is unsurpassed, So be thy bounty to the worshipper unchecked.\n\np: Most Mighty, most heroic One, for mighty bounty fill thee full. Though strong, strengthen thyself to win wealth, Maghavan!\n\np: O Thunderer, never have our meditations gone forth to any Deva.but thee: So help us, Maghavan, with thine assistance now.\n\np: For, Dancer, verily I find non else for bounty, saving thee, for splendid wealth and power, thou Lover of the Song.\n\np: For Indra pour ye out the drops meath blent with Soma let him drink With bounty and with majesty will he further us.\n\np: I spake to the Bay Coursers' Lord, to him who gives ability: Now hear the son of Asva as he praises thee.\n\np: Never was any Hero born before thee mightier than thou: None certairdy like thee in goodness and in wealth.\n\np: O ministering priest, pour out of the sweet juice what gladdens most: So is the Hero praised who ever prospers us.\n\np: Indra, whom Tawny Coursers bear, praise such as thine, preeminent, None by his power or by his goodness hath attained.\n\np: We, seeking glory, have invoked this Master of all power and might Who must be glorified by constant sacri fice.\n\np: Come, sing we praise to Indra, friends, the Hero who deserves the laudhim who with none to aid o’ercomes all tribes of men.\n\np: To him who wins the kine, who keeps no cattle back, Celestial Deva, Speak wondrous speech more sweet than butter and than meath.\n\np: Whose hero powers are measureless, whose bounty ne’e. May be surpassed, whose liberality, like light, is over all.\n\np: As Vyasva did, praise Indra, praise the Strong unfluctuating Guide, who gives the foe's possessions to the worshipper.\n\np: Now, son of Vyasva, praise thou him who to the tenth time still is new, the very Wise, whom living men must glorify\n\np: Thou knowest, indra, Thunder-armed, how to avoid destructive powers, as one secure from pitfalls each returning day.\n\np: O Indra, bring that aid wherewith of old, most Wondrous! thou didst subdue His foes for active Kutsa: send it down to us.\n\np: So now we seek thee fresh in might, most Wonderful in act! for gain: For thou art he who conquers all our foes for us.\n\np: Who will set free from ruinous woe, or Arya on the Seven Streams: O valiant Hero, bend the Dasa's weapon down.\n\np: As to Varosusaman thou broughtest great riches, for their gain, to Vyasva's sons, Blest Lady, rich in ample wealth!\n\np: Let Narya's offerings meed reach Vyasva's Soma-bearing sons: In hundreds and in thousands be the great reward.\n\np: If one should ask thee, Where is he who offered? Whither lookest thou? Like Vala he hath passed away and dwelleth now on Gomati.","people":["Indra","Soma","Vrtra","Maghavan","Kutsa","Deva","Narya"],"places":[],"things":["Meath","Master","Tawny Coursers","Lord","Born","Soma","Glory","Light","Wealth","Boon","Men","Streams","Might","Juice","Song","Help","Wise","Strong","Mighty","Chief","Praise","Worshipper","Hymn","Excellent","Lord of Bays","Powers","Offerings","Friends","Songs","Drops","Friend","Hero","Riches","Cattle","Gifts"],"groups":["Sons","Son","Visvamanas"],"concepts":["Celestial","Heroic","Offerings","Giver","Speech"],"hash":"md5-2PzppSPNesrMXvTdMokSGQ==","created":"Monday, April 8, 2024 - 10:51:53 PM"},{"id":"acf2d765-3c23-481e-92ac-815ea063d45f","key":"08025","book":"08","title":"HYMN XXV. Mitra and Varuna.","link":"https://indra.ai/rigveda/hymns/08025.html","text":"p: I WORSHIP you who guard this All, Devas, holiest among the Devas, You, faithful to the Law, whose power is sanctified.\n\np: So, too, like charioteers are they, Mitra and sapient Varuna, Sons high-born from of old, whose holy laws stand fast.\n\np: These Twain, possessors of all wealth, most glorious, for supremest sway Aditi, Mighty Mother, true to Law, brought forth.\n\np: Great Varuna and Mitra, Devas, Asuras and imperial Lords, True to Eternal Law proclaim the high decree.\n\np: The offspring of a lofty Power, Daksa's Two Son exceeding strong, who, Lords of flowing rain, dwell in the place of food.\n\np: Ye who have gathered up your gifts, celestial and terrestrial food, Let your rain come to us fraught with the mist of heaven.\n\np: The Twain, who from the lofty sky seem to look down on herds below, Holy, imperial Lords, are set to be revered.\n\np: They, true to Law, exceeding strong, have sat them down for savran rule: Princes whose laws stand fast, they have obtained their sway.\n\np: Pathfinders even better than the eye, with unobstructed sight, Even when they close their lids, observant, they perceive.\n\np: May the Deva Aditi. May the Nasatyas guard us well, the Martits guard us well.endowed with mighty strength.\n\np: Do ye, O Bounteous Devas, protect our dwelling lace by day and night: With you for our defender. May we go unharmed.\n\np: May we, unharmed, serve bountiful Visnu, the Deva who slayeth none: Self-moving Sindhu hear and be the first to mark.\n\np: This sure protection we elect, desirable and reaching far, Which Mitra, Varuna, and Aryaman afford.\n\np: An. May the Sindhu of the floods, the Maruts, and the ASvin Pair, Boon Indra, and boon Visnu have one mind with us.\n\np: Because these warring Heroes stay the enmity of every foe, as the fierce water-flood repels the furious ones.\n\np: Here this one Deva, the Lord of men, looks forth exceeding far and wide: And we, for your advantage, keep his holy laws.\n\np: We keep the old accustomed laws, the statutes of supremacy, the Iong-known laws of Mitra and of Varuna.\n\np: He who hath measured with his ray the boundaries of heaven and earth, and with his majesty hath filled the two worlds full,\n\np: Surya hath spread his light aloft up to the region of the skylike Agni all aflame when gifts are offered him.\n\np: With him who sits afar the word is lord of food that comes from kine, Controller of the gift of unempoisoned food.\n\np: So unto Surya. Heaven, and Earth at morning and at eve I speak. Bringing enjoyments ever rise thou up for us.\n\np: From Uksanyayana a bay, from Harayana a white steed, and from Susaman we obtained a hamessed car.\n\np: These two shall bring me further gain of troops of tawny-coloured steeds, the carriers shall they be of active men of war.\n\np: And the two sages have I gained who hold the reins and bear the whip, and the two great strong coursers, with my newest song.","people":["Indra","Agni","Visnu","Mitra","Varuna","Nasatyas","Deva","Surya","Aditi","Sindhu","Daksa","Aryaman"],"places":["Earth","Heaven","Sky"],"things":["Worship","Steeds","Lord","Born","Water","Glorious","Light","Wealth","Boon","Food","Men","Rain","Song","Offspring","Strong","Mighty","Car","Heroes","Gift","Morning","Gifts"],"groups":["Devas","Asuras","Maruts","Sons","Mother","Son"],"concepts":["Celestial","Holy","Strength","Glorious","Eternal Law"],"hash":"md5-LacBsGPOLGRbiejHDMtHsw==","created":"Monday, April 8, 2024 - 10:51:53 PM"},{"id":"94d4df56-1638-4690-aa3a-8d69b58181d0","key":"08026","book":"08","title":"HYMN XXVI. Asvins.","link":"https://indra.ai/rigveda/hymns/08026.html","text":"p: I CALL your chariot to receive united praise mid princely men, Strong Devas who pour down wealth, of never vanquished might!\n\np: Ye to Varosusaman come, Nasatyas, for this glorious rite. With your protecting aid. Strong Devas, who pour down wealth.\n\np: So with oblations we invoke you, rich in ample wealth, to-day, when night hath passed, O ye who send us plenteous food. O Asvins. Heroes, let your car, famed, best to travel, come to us, and, for his glory, mark your zealous servant's lauds.\n\np: Asvins, who send us precious gifts, even when offended, think of him: For ye, O Rudras, lead us safe beyond our foes.\n\np: For, Wonder-Workers, with fleet steeds ye fly completely round this All, Stirring our thoughts, ye Lords of splendour, honey-hued.\n\np: With all-sustaining opulence, Asvins, come hitherward to us, Ye rich and noble Heroes, ne’er to be o’erthrown.\n\np: To welcome this mine offering, O ye Indra-like Nasatyas, come As Devas of best accord this day with other Devas.\n\np: For we, like Vyasva, lifting up our voice like oxen, call on you: With all your loving kindness, Sages, come to us.\n\np: O Rsi, laud the Asvins well. Will they not listen to thy call? Will they not burn the Panis who are nearer them?\n\np: O Heroes, listen to the son of Vyasva, and regard me here, Varuna, Mitra, Aryaman, of one accord.\n\np: Devas whom we yearn for, of your gifts, of what ye bring to us, bestow By princes' hands on me, ye Mighty, day by day.\n\np: Him whom y 'our offerings clothe, even as a woman with her robe, the Asvins help to glory honouring him well.\n\np: Whoso regards your care of men as assist widest in its reach, About his dwelling go, ye Asvins, loving us.\n\np: Come to us ye who pour down wealth, come to the home which men must guard: Like shafts, ye are made meet for offering by song.\n\np: Most fetching of all calls, the laud, as envoy. Heroes, called to you Be it your own, O Asvin Pair.\n\np: Be ye in yonder sea of heaven, or joying in the home of food, Listen to me, Immortal Ones.\n\np: This river with his lucid flow attracts you, more than all the streams. Even Sindhu with his path of gold.\n\np: O Asvins, with that glorious fame come hither, through our brilliant song, Come ye whose ways are marked with light.\n\np: Harness the steeds who draw the car, O Vasu, bring the well-fed pair. O Vayu, drink thou of our meath: come unto our water-offerings.\n\np: Wonderful Vayu, Lord of Right, thou who art Tvastar's son-in-law, Thy saving assist we elect.\n\np: To Tvastar's son-in-law we pray for wealth whereof he hath control: For glory we seek vayu, men with juice effused.\n\np: From heaven, auspicious Vayu, come drive hither with thy noble steeds: Come on thy mighty car with wide-extending seat.\n\np: We call thee to the homes of men, thee wealthiest in noble food, and liberal as a press-stone with a horse's back.\n\np: So, glad and joyful in thine heart, do thou, Deva, Vayu, first of all Vouchsafe us water, strength, and thought.","people":["Indra","Vayu","Mitra","Varuna","Asvins","Nasatyas","Tvastar","Deva","Sindhu","Aryaman","Vasu"],"places":["Heaven"],"things":["Meath","Steeds","Lord","Water","Glory","Glorious","Offering","Light","Wealth","Food","Men","River","Streams","Flow","Might","Juice","Song","Gold","Help","Home","Strong","Mighty","Car","Praise","Voice","Heroes","Splendour","Offerings","Horse","call","Gifts"],"groups":["Devas","Rudras","Son","Immortal","Panis","Woman"],"concepts":["Wonder-Workers","Immortal","Strength","Offering","Offerings","Auspicious","Glorious","Noble"],"hash":"md5-cuNdagcY1r+jbmzjrxNd7Q==","created":"Monday, April 8, 2024 - 10:51:53 PM"},{"id":"ec348687-cfb3-479b-8646-642917d35e7a","key":"08027","book":"08","title":"HYMN XXVII, Devas.","link":"https://indra.ai/rigveda/hymns/08027.html","text":"p: CHEIF Monk is Agni at the laud, as stones and grass at offering: With song I seek the Maruts, Narasamsa, Devas for help much to be desired.\n\np: I sing to cattle and to Earth, to trees, to Dawns, to Night, to plants. O all ye Vasus, ye possessors of all wealth, be ye the furtherers of our thoughts.\n\np: Forth go, with Agni, to the Devas  'our offering of ancient use, to the Adityas, Varuna whose Law stands fast, and the all-lightening Marut troop.\n\np: Lords of all wealth. May they be strengtheners of man, destroyers of his enemies. Lords of all wealth, do ye, with guards which non. May harm, preserve our dwelling free from foes.\n\np: Come to us with one mind to-day, come to us all with one accord, Maruts with holy song, and, Deva Aditi, Mighty One, to our house and home.\n\np: Send us delightful things, ye Maruts, on your steeds: come ye, O Mitra, to our gifts. Let Indra, Varuna, and the Adityas sit, swift Heroes, on our sacred grass.\n\np: We who have trimmed the grass for you, and set the banquet in array, and pressed the Soma, call you, Varuina, like men, with offerings fires aflame.\n\np: O Maruts, Visinu, Asvins, pusan, haste away with minds turned hitherward to Me. Let the Strong Indra, famed as Vrtra's slayer, come first with the winners of the spoil.\n\np: Ye Guileless Devas, bestow on us a refuge strong on every side, a sure protection, Vasus, unassailable from near at hand or from afar.\n\np: Kinship have I with you, and close alliance O ye Devas, destroyers of our foes. Call us to our prosperity of former days, and soon to new klicity.\n\np: For now have I sent forth to you, that . May win a fair reward, Lords of all wealth, with homage, this my song of praise. like a MilchCow that faileth not.\n\np: Excellent Savitar hath mounted up on high for you, ye sure and careful Guides. Bipeds and quadrupeds, with several hopes and aims, and birds have settled to their tasks.\n\np: Singing their praise with Deva.like thought let us invoke each Deva.for grace, Each Deva.to bring you help, each Deva.to strengthen you.\n\np: For of one spirit are the Devas with mortal man, co-sharers all of gracious gifts. May they increase our strength hereafter and to-day, providing case and ample room.\n\np: I laud you, O ye Guileless Devas, here where we meet to render praise. None, Varuna and Mitra, harins the mortal, man who honours and obeys your laws.\n\np: He makes his house endure, he gathers plenteous food who pays obedience to your will. Born in his sons anew he spreads as Law commands, and prospers every way unharmed.\n\np: E’en without war he gathers wealth, and goes hisway on pleasant paths, whom Mitra, Varuna and Aryaman protect, sharing the gift,of one accord.\n\np: E’en on the plain for him ye make a sloping path, an easy way where road is none: And far away from him the ineffectual shaft must vanish, shot at him in vain.\n\np: If ye appoint the rite to-day, kind Rulers, when the Sun ascends, Lords of all wealth, at sunset or at wakingtime, or be it at the noon of day,\n\np: Or, Asuras, when ye have sheltered the worshipper who goes to offering, at ev. May we, O Vasus, ye possessors of all wealth, come then into the midst of You.\n\np: If ye to-day at sunrise, or at noon, or in the gloom of eve, Lords of all riches, give fair treasure. to the man, the wise man who hath offered,\n\np: Then we, imperial Rulers, claim of you this boon, your wide protection, as a son. May we, Adityas, offering holy gifts, obtain that which shall bring us greater bliss.","people":["Indra","Soma","Vrtra","Agni","Mitra","Varuna","Asvins","Narasamsa","Savitar","Pusan","Deva","Aditi","Aryaman"],"places":["Earth"],"things":["Steeds","Born","Soma","Offering","Sun","Treasure","Wealth","Boon","Food","Men","Song","Help","Home","Wise","Strong","Mighty","Grass","Banquet","Praise","Worshipper","Heroes","Gift","Excellent","Offerings","Bliss","call","spoil","Riches","Cattle","Spirit","MilchCow","Gifts"],"groups":["Devas","Asuras","Maruts","Marut","Sons","Dawns","Son","Man","Vasus","Adityas"],"concepts":["Holy","Sacred","Strength","Offering","Offerings","Swift"],"hash":"md5-MlZZjVY1t/r+P3nvzwVITw==","created":"Monday, April 8, 2024 - 10:51:53 PM"},{"id":"9dbe0b10-221f-424c-b6dc-b07c5da60441","key":"08028","book":"08","title":"HYMN XXVIII, Devas.","link":"https://indra.ai/rigveda/hymns/08028.html","text":"p: THE Thirty Devas and Three besides, whose seat hath been the sacred grass, From time of old have found and gained.\n\np: Varuna, Mitra, Aryaman, Agnis, with Consorts, sending boons, to whom our Vasat! is addressed:\n\np: These are our guardians in the west, and northward here, and in the south, and on the cast, with all the tribe.\n\np: Even as the Devas desire so verily shall it be. None minisheth this power of theirs, No demon, and no mortal\n\np: The Seven carry seven spears; seven are the splendours they possess, and seven the glories they assume.","people":["Mitra","Varuna","Aryaman"],"places":[],"things":["Grass"],"groups":["Devas"],"concepts":["Sacred"],"hash":"md5-XJX768HIWHsjqxl7mp+YwA==","created":"Monday, April 8, 2024 - 10:51:53 PM"},{"id":"1379d87d-808c-4bbb-b866-d94a9ba29170","key":"08029","book":"08","title":"HYMN XXIX Devas.","link":"https://indra.ai/rigveda/hymns/08029.html","text":"p: ONE is a youth brown, active, manifold he decks the golden one with ornament.\n\np: Another, luminous, occupies the place of sacritice, Sage, among the Devas.\n\np: One brandishes in his hand an iron knife, firm, in his seat amid the Deities.\n\np: Another holds the thunderbolt, wherewith he subdues the Vrtras, resting in his hand.\n\np: Another bears a pointed weapon: bright is he, and strong, with healing medicines.\n\np: Another, thief-like, watches well the ways, and knows the places where the treasure.s lie.\n\np: Another with his mighty stride hath made his three steps thither where the Devas rejoice.\n\np: Two with one Dame ride on with winged steeds, and journey forth like travellers on their way.\n\np: Two, highest, in the heavens have set their seat, worshipped with holy oil, imperial Kings.\n\np: Some, singing lauds, conceived the Sama-hymn, great hymn whereby they caused the Sun to shine.","people":[],"places":[],"things":["Journey","Steeds","Shine","Sun","Treasure","Strong","Mighty","Hymn","Sage"],"groups":["Devas","Deities","Kings","Vrtras"],"concepts":["Holy","Worshipped"],"hash":"md5-aBOIYrQRpiI8MXZbHxtFAQ==","created":"Monday, April 8, 2024 - 10:51:53 PM"},{"id":"351dea51-6e30-4c70-bf7a-56cbf6ac7e4f","key":"08030","book":"08","title":"HYMN XXX, Devas.","link":"https://indra.ai/rigveda/hymns/08030.html","text":"p: NOT one of you, ye Devas, is small, none of you is a feeble child: All of you, verily, are great.\n\np: Thus be ye lauded, ye destroyers of the foe, ye Three-and-Thirty Deities, the Devas of man, the Holy Ones.\n\np: As such defend and assist us, with benedictions speak to us: Lead us not from our fathers' and from Manu's path into the distance far away.\n\np: Ye Deities who stay with us, and all ye Devas of all mankind, Give us your wide protection, give shelter for cattle and for steed.","people":[],"places":[],"things":["Mankind","Holy Ones","Cattle"],"groups":["Devas","Fathers","Three-and-Thirty Deities","Deities","Child","Man"],"concepts":["Holy"],"hash":"md5-a7xUIVl5OELqXgT8sjesWA==","created":"Monday, April 8, 2024 - 10:51:53 PM"},{"id":"7f0a48cf-3ce7-4e4a-828f-fafe3aa89c7d","key":"08031","book":"08","title":"HYMN XXXI. Various Deities.","link":"https://indra.ai/rigveda/hymns/08031.html","text":"p: THAT Brahman pleases Indra well, who worships, pours Libation, and prepares the meal.\n\np: Sakra protects from woe the man who gives him offerings cake. And offers Soma blent with milk.\n\np: His chariot shall be glorious, sped by Devas, and mighty shall he be, Subduing all hostilities.\n\np: Each day that passes, in his house flows his libation, rich in milk, Exhaustless, bringing progeny.\n\np: O Devas, with constant draught of milk, husband and wife with one accord Press out and wash the Soma juice.\n\np: They gain sufficient food: they come united to the sacred grass, and never do they fail in strength.\n\np: Never do they deny or seek to hide the favour of the Devas: They win high glory for themselves.\n\np: With sons and daughters by their side they reach their full extent of life, Both decked with ornaments of gold.\n\np: Serving the Immortal One with gifts of offerings meal and wealth, they satisfy the claims of love and pay due honour to the Devas.\n\np: We claim protection from the Hills, we claim protection of the Floods, Of him who stands by Visnu's side.\n\np: May Pusan come, and Bhaga, Lord of wealth, All-bounteous, for our weal Broad be the path that leads to bliss:\n\np: Aramati, and, free from foes, Visva with spirit of a Deva, and the Adityas’ peerless might.\n\np: Seeing that Mitra, Aryaman, and Varuna are guarding us, the paths of Law are fair to tread.\n\np: I glorify with song, for wealth, Agni the Deva, the first of you. We honour as a well-loved Friend the Deva who prospereth our fields.\n\np: As in all frays the hero, so swift moves his car whom Devas attend. The man who, sacrificing, strives to win the heart of Deities will conquer those who worship not.\n\np: Ne’er are ye injured, worshipper, presser of juice, or pious man. The man who, sacrificing, strives to win the heart of Deities will conquer those who worship not.\n\np: None in his action equals him, none holds him far or keeps him off. The man who, sacrificing, strives to win the heart of Deities will conquer those who worship not.\n\np: Such strength of heroes shall be his, such mastery of fleet-foot steeds. The man who, sacrificing, strives to win the heart of Deities will conquer those who worship not.","people":["Indra","Soma","Agni","Visnu","Mitra","Varuna","Sakra","Pusan","Bhaga","Deva","Aryaman"],"places":[],"things":["Worship","Milk","Steeds","Lord","Soma","Glory","Glorious","Wealth","Food","Might","Juice","Song","Gold","Mighty","Grass","Car","Worshipper","Heroes","Offers","Offerings","Bliss","Friend","Hero","Life","Spirit","Gifts"],"groups":["Devas","Sons","Deities","Wife","Husband","Immortal","Progeny","Man","Adityas"],"concepts":["Life","Love","Immortal","Sacred","Strength","Offerings","Glorious","Swift"],"hash":"md5-UZYevuc1xmT5KZGwcGTBdw==","created":"Monday, April 8, 2024 - 10:51:53 PM"},{"id":"e860929d-70a8-43e7-8c7f-d7a063ebddc4","key":"08032","book":"08","title":"HYMN XXXII. Indra.","link":"https://indra.ai/rigveda/hymns/08032.html","text":"p: KANVAS, tell forth with song the deeds of Indra, the Impetuous, Wrought in the Soma's wild delight.\n\np: Strong Deva, he slew Anarsani, Srbinda, pipru, and the fiend, Ahisuva, and loosed the floods.\n\np:  Thou broughtest down the dwelling-place, the height of lofty Arbuda. That exploit, indra, must be famed.\n\np: Bold, to your famous Soma I call the fair-visored Deva.for aid, Down like a torrent from the hill.\n\np: Rejoicing in the Soma-draughts. Hero, burst open, like a fort, the stall of horses and of kine.\n\np: If my libation gladdens, if thou takest pleasure in my laud, Come with thy Deva.ead from afar.\n\np: O Indra, Lover of the Song, the singers of thy praise are we: O Soma-drinker, quicken us.\n\np: And, taking thy delight with us bring us still undiminished food: Great is thy wealth, O Maghavan.\n\np: Make thou us rich in herds of kine, in steeds, in gold: let us exert Our strength in offerings gifts.\n\np: Let us call him to aid whose hands stretch far, to whom high laud is due. Who worketh well to assist us.\n\np: He, Satakratu, even in fight acts as a Vrtra conquerer s,till: He gives his worshippers much wealth.\n\np: May he, this A;akra, strengthen us, Boon Deva who satisfies our needs, indra, with all lhis saving helps.\n\np: To him, the mighty stream of wealth, we's rescuing Friend, to Indra sing your song of praise;\n\np: Who bringeth what is great and firm, who winneth glory in his wars, Lord of vast wealth through power and might.\n\np: There liveth none to cheek or stay his energies and gracious deeds: None who can say. He giveth not.\n\np: No debt is due by Brahmans now, by active men who press the juice: Well hath each Soma-draught been paid.\n\np: Sing ye to him who must be praised, say lauds to him who must be praised, Bring prayer to him who must be praised.\n\np: May be, unchecked, strong, meet for praise, bring hundreds, thousands forth to light, indra who aids the worshipper.\n\np: Go with thy Deva.like nature forth, go where the folk are calling thee: Drink, indra, of the drops we pour.\n\np: Drink milky draughts which are thine own, this too which was with Tugrya once, This is it, indra, that is thine.\n\np: Pass him who psours libations out in angry mood or after sin: Here drink the juice we offer thee.\n\np: Over the three great distances, past the Five Peoples go thy way, O Indra, noticing our voice.\n\np: Send forth thy ray like Surya: let my songs attract thee hitherwardlike waters gathering to the vale.\n\np: Now to the Hero fair of cheek, Adhvaryu, pour the Soma forth: Bring of the juice that h. May drink\n\np: Who cleft the water-cloud in twain, loosed rivers for their downward flow, and set the ripe milk in the kine.\n\np: He, meet for praise, slew Vrtra, slew Ahisuva, Urnavabha's son, and pierced th:rough Arbuda with frost.\n\np: To him your matchless Mighty One, unconquerable Conqueror, Sing forth the prayer which Devas have given:\n\np: Indra, who in the wild delight of Soma juice considers here All holy Laws among the Devas.\n\np: Hither let these thy Bays who share thy banquet, Steeds with golden manes, Convey thee to the feast prepared.\n\np: Hither, O thou whom many laud, the Bays whom Priyamedha praised, Shall bring thee to the Soma-draught.","people":["Indra","Soma","Vrtra","Satakratu","Maghavan","Priyamedha","Kanvas","Deva","Surya","Arbuda"],"places":[],"things":["Milk","Steeds","Lord","Rivers","Soma","Waters","Water","Glory","Light","Wealth","Boon","Food","Men","Stream","Flow","Might","Juice","Song","Gold","Strong","Mighty","Banquet","Praise","Voice","Worshipper","Delight","Offerings","Libations","Songs","Drops","Friend","Hero","Horses","call","Gifts"],"groups":["Devas","Brahmans","Worshippers","Son"],"concepts":["Holy","Strength","Offerings","Libations"],"hash":"md5-eIQKT9YNmCGdbmITE1x7Hw==","created":"Monday, April 8, 2024 - 10:51:53 PM"},{"id":"34efb176-4c86-4c79-ad9e-e632967356b1","key":"08033","book":"08","title":"HYMN XXXIII. Indra.","link":"https://indra.ai/rigveda/hymns/08033.html","text":"p: WE compass thee like waters, we whose grass is trimmed and Soma pressed. Here where the filter pours its stream, thy worshippers round thee, O Vrtra conquerer, sit.\n\np: Men, Vasu! by the Soma, with lauds call thee to the foremost place: When comest thou athirst unto the juice as home, O Indra, like a bellowing bull?\n\np: Boldly, Bold Hero, bring us spoil in thousands for the Kanvas' sake. O active Maghavan, with eager prayer we crave the yellow-hued with store ol kine.\n\np: Medhyatithi, to Indra sing, drink of the juice to make thee glad. Close-knit to his Bay Steeds, bolt-armed, beside the juice is he: his chariot is of gold.\n\np: He Who is praised as strong of hand both right and left, most wise and hold: Indra who, rich in hundreds, gathers thousands up, honoured as breaker-down of forts.\n\np: The bold of heart whom none provokes, who stands in bearded confidence; Much-lauded, very glorious, overthrowing foes, strong Helper, like a bull with might.\n\np: Who knows what vital ower he wins, drinking beside the flowing juice? This is the fair-checked Deva who, joying in the draught, breaks down the castles in his strength.\n\np: As a wild elephant rushes on this way and that way, mad with heat,' Non. May compel thee, yet come hither to the draught: thou movest mighty in thy power.\n\np: When he, the Mighty, ne’er o’erthrown, steadfast, made ready for the fight, when Indra Maghavan lists to his praiser's call, he will not stand aloof, but come.\n\np: Yea, verily, thou art a Bull, with a bull's rush. whom non. May stay: Thou Mighty One, art celebrated as a Bull, famed as a Bull both near and far.\n\np: Thy reins are very bulls in strength, bulls' strength is in thy golden whip. Thy car thy Bays are strong as bulls: thou, Satakratu, art a Bull.\n\np: Let the strong presser press for thee. Bring hither, thou straight-rushing Bull. The mighty makes the mighty run in flowing streams for thee whom thy Bay Horses bear.\n\np: Come, thou most potent Indra, come to drink the savoury Soma juice. Maghavan, very wise, will quickly come to hear the songs, the prayer, the hymns of praise.\n\np: When thou hast mounted on thy car let thy yoked Bay Steeds carry thee, past other men's libations, Lord of Hundred Powers, thee, Vrtra conquerer, thee our Friend.\n\np: O thou Most Lofty One, accept our laud as nearest to thine heart. May our libations be most sweet to make thee glad, O Soma-drinker. Heavenly Lord.\n\np: Neither in thy decree nor mine, but in another's he delights. The man who brought us unto this.\n\np: Indra himself hath said, the mind of woman brooks not discipline. Her intellect hath little weight.\n\np: His pair of horses, rushing on in their wild transport, draw his car: High-lifted is the stallion's yoke.\n\np: Cast down thine eyes and look not up. More closely set thy feet. Let none See what thy garment veils, for thou, a Brahman, hast become a dame.","people":["Indra","Soma","Vrtra","Satakratu","Maghavan","Kanvas","Deva","Vasu"],"places":[],"things":["Steeds","Lord","Soma","Waters","Glorious","Men","Streams","Stream","Might","Juice","Gold","Home","Wise","Strong","Mighty","Grass","Car","Praise","Bay Horses","Powers","Libations","Songs","Friend","Hero","Horses","call","spoil"],"groups":["Worshippers","Man","Woman"],"concepts":["Heavenly","Strength","Glorious","Libations"],"hash":"md5-tdYfD4JGTXcU8cadXQwkcA==","created":"Monday, April 8, 2024 - 10:51:53 PM"},{"id":"7b50a822-9229-4130-892a-4f275543fcd6","key":"08034","book":"08","title":"HYMN XXXIV. Indra.","link":"https://indra.ai/rigveda/hymns/08034.html","text":"p: Come hither, indra, with thy Bays, come thou to Kanva's eulogy. Ye by command of yonder Dyaus, Deva.bright by day! have gone to heaven.\n\np: May the stone draw thee as it speaks, the Soma-stone with ringing voice. Ye by command of yonder Dyaus, Deva.bright by day! have gone to heaven.\n\np: The stones' rim shakes the Soma here like a wolf worrying a sheep. Ye by command of yonder Dyaus, Deva.bright by day! have gone to heaven.\n\np: The Kanvas call thee hitherward for assist and to win the spoil. Ye by command of yonder Dyaus, Deva.bright by day! have gone to heaven.\n\np: I set for thee, as for the Strong, the first draught of the juices shed.\n\np: Come with abundant blessings, come with perfect care to assist us.\n\np: Come, Lord of lofty thought, who hast infinite wealth and countless aids.\n\np: Adorable mid Devas, the Monk good to mankind shall bring thee near.\n\np: As wings the falcon, so thy Bays rushing in joy shall carry thee.\n\np: Come from the enemy to us, to svaha and the Soma-draught.\n\np: Come hither with thine car inclined to hear, take pleasure in our lauds.\n\np: Lord of well-nourished Horses, come with well-fed Steeds alike in hue.\n\np: Come hither from the mountains, come from regions of the sea of air.\n\np: Disclose to us O Hero, wealth in thousands both of kine and steeds.\n\np: Bring riches hitherward to us in hundreds, thousands, myriads. Ye by command of yonder Dyaus, Deva.bright by day! have gone to heaven.\n\np: The thousand steeds, the mightiest troop, which we and Indra have received From Vasurocis as a gift,\n\np: The brown that match the wind in speed, and bright bay coursers fleet of footlike Suns, resplendent are they all.\n\np: Mid the Pargvata's rich gifts, swift steeds whose wheels run rapidly, I seemed to stand amid a wood.","people":["Indra","Soma","KanVa","Svaha","Kanvas","Deva"],"places":["Heaven"],"things":["Mankind","Steeds","Lord","Mountains","Soma","Air","Wealth","Joy","Strong","Car","Voice","Gift","Adorable","Wings","Hero","Horses","call","spoil","Riches","Gifts"],"groups":["Devas","Dyaus"],"concepts":["Good","Blessings","Swift"],"hash":"md5-drJ1kzHua2pqOi6XgWiGVA==","created":"Monday, April 8, 2024 - 10:51:53 PM"},{"id":"baa79022-0e91-46c8-8b4b-44e235edd549","key":"08035","book":"08","title":"HYMN XXXV. Asvins.","link":"https://indra.ai/rigveda/hymns/08035.html","text":"p: WITH Agni and with Indra, Visnu. Varuna, with the Adityas, Rudras, Vasus, closely leagued; Accordant, of one mind with Surya and with Dawn, O Asvins, drink the Soma juice.\n\np: With all the Holy Thoughts, all being MightyOnes! in close alliance wil the Mountains. Heaven, and Earth; Accordant. of one mind with Surya and with Dawn, O Asvins, drink the Soma juice.\n\np: With all the Deities, three times eleven, here, in close alliance with the Maruts, Bhrgus, Floods; Accordant, of one mind with Surya and with Dawn, O Asvins, drink the Soma juice.\n\np: Accept  'the offering, attend to this my call: come nigh, O ye Twain Devas, to all libations here. Accordant, of one mind with Surya and with Dawn, O Asvins, bring us strengthening food.\n\np: Accept our praise-song as a youth accepts a maid. Come nigh, O ye Twain Devas, to all libations here. Accordant, of one mind with Surya and with Dawn, O Asvins, bring us strengthening food.\n\np: Accept the songs we sing, accept the solemn rite. Come nigh, O ye Twain Devas, to all libations here. Accordant, of one mind with Surya and with Dawn, O Asvins, bring us strengthening food.\n\np: Ye fly as starlings fly unto the forest trees; like buffaloes ye seek the Soma we have shed. Accordant, of one mind with Surya and with Dawn, come thrice, O Asvins, to our home.\n\np: Ye fly like swans, like those who travel on their way; like buffaloes ye seek the Soma we have shed. Accordant, of one mind with Surya and with Dawn, come thrice, O Asvins, to our home.\n\np: Ye fly to our oblation like a pair of hawks; like buffaloes ye seek the Soma we have shed. Accordant, of one mind with Surya and with Dawn, come thrice, O Asvins, to our home.\n\np: Come hitherward and drink and satisfy yourselves, bestow upon us progeny and affluence. Accordant, of one mind with Surya and with Dawn, O Asvins, grant us vigorous strength.\n\np: Conquer your foes, protect us, praise your worshippers; bestow upon us progeny and affluence. Accordant, of one mind with Surya and with Dawn, O Asvins, grant us vigorous strength.\n\np: Slay enemies, animate men whom ye befriend; bestow upon us progeny and affluence. Accordant, of one mind with Surya and with Dawn, O Asvins, grant us vigorous strength.\n\np: With Mitra, Varuna, Dharma, and the Maruts in your company approach unto your praiser's call. Accordant, of one mind with Surya and with Dawn, and with the Adityas, Asvins! come.\n\np: With Visnu and the Angirases attending you, and with the Maruts come unto your praiser's call. Accordant, of one mind with Surya and with Dawn, and with the Adityas, Asvins! come.\n\np: With Rbhus and With Vajas. O ye MightyOnes, leagued with the Maruts come ye to your praiser's call. Accordant, of one mind with Surya and with Dawn, and with the Adityas, Asvins! come.\n\np: Give spirit to our meditation and animate our thoughts; subdue ye the Raksasas and drive away disease. Accordant, of One mind with Surya and with Dawn, -the presser's Soma, Asvins drink.\n\np: Strengthen the Ruling Power, strengthen the men of war; subdue ye the Raksasas and drive away disease. Accordant, of one mind with Surya and with Dawn, the presser's Soma, Asvins drink.\n\np: Give strength unto the milch-kine, give the people strength, subdue ye the Raksasas and drive away disease. Accordant, of one mind with Surya and with Dawn, the presser's Soma, Asvins drink.\n\np: As ye heard Atri's earliest eulogy, so hear Syavasva, Soma-presser, ye who reel in joy. Accordant, of one mind with Surya and with Dawn, drink juice, O Asvins, three days old.\n\np: Further like running streams Syavasva's eulogies who presses out the Soma, ye who reel in joy. Accordant, of one mind with Surya and with Dawn, drink juice, O Asvins, three days old.\n\np: Seize, as ye grasp the reins, Syavasva's solemn rites who presses out the Soma, ye who reel in joy. Accordant, of one mind with Surya and with Dawn, drink juice, O Asvins, three days old.\n\np: Drive down your chariot hitherward drink ye the Soma's savoury juice. Approach, ye Asvins, come to us: I call you, eager for your aid. Grant treasure.s to the worshipper.\n\np: When offering which tells our reverence hath begun. Heroes! to drink the gushing juice, Approach, ye Asvins, come to us: I call you, eager for your aid. Grant treasure.s to the worshipper.\n\np: Sate you with consecrated drink, with juice effused, ye Deities. Approach, ye Asvins, come to us: I call you, eager for your aid. Grant treasure.s to the worshipper.","people":["Indra","Soma","Agni","Visnu","Mitra","Varuna","Asvins","Atri","Surya","Raksasas","Dawn"],"places":["Earth","Heaven"],"things":["Mountains","Reverence","Meditation","Soma","Offering","Treasure","Food","Men","Streams","Juice","Song","Joy","Home","Praise","Worshipper","Heroes","People","Libations","Songs","Swans","call","Spirit"],"groups":["Devas","Maruts","Rudras","Deities","Worshippers","Bhrgus","Maid","Progeny","Angirases","MightyOnes","Vasus","Adityas","Rbhus"],"concepts":["Holy","Strength","Offering","Libations"],"hash":"md5-TeaRK+7RDPM8cnnQoMdevg==","created":"Monday, April 8, 2024 - 10:51:53 PM"},{"id":"6df18606-de0c-413a-8cca-b0364f186bcf","key":"08036","book":"08","title":"HYMN XXXVI. Indra.","link":"https://indra.ai/rigveda/hymns/08036.html","text":"p: THOU helpest him whose grass is trimmed, who sheds the juice, O Satakratu, drink Soma to make thee glad. The share which they have fixed for thee Indra, Victor o’er all hosts and space, begirt with Maruts, Lord of Heroes, winner of the floods.\n\np: Maghavan, help thy worshipper: let him help thee. O Satakratu, drink Soma to make thee glad. The share which they have fixed for thee, etc.\n\np: Thou aidest Devas with food, and that with might aids thee, O Satakratu, drink Soma to make thee glad.\n\np: Creator of the heaven, creator of the earth, O Satakratu, drink Soma to make thee glad.\n\np: Father of cattle, father of all steeds art thou. O Satakratu, drink Soma to make thee glad.\n\np: Stone-hurler, glorify the Atris' hymn of praise. O Satakratu, drink Soma to make thee glad.\n\np: Hear thou Syavasva while he pours to thee, as erst thou heardest Atri when he wrought his holy rites. Indra, thou only gavest Trasadasyu aid in the fierce fight with heroes, strengthening his prayers.","people":["Indra","Soma","Satakratu","Maghavan","Atri"],"places":["Earth","Heaven"],"things":["Steeds","Lord","Soma","Creator","Food","Might","Juice","Help","Grass","Praise","Worshipper","Hymn","Heroes","Cattle"],"groups":["Devas","Maruts","Atris","Father"],"concepts":["Holy","Winner","Creator"],"hash":"md5-FoSWWTrJLBXV0vOwrcBmNw==","created":"Monday, April 8, 2024 - 10:51:53 PM"},{"id":"1eb72db5-6382-449e-a129-1a26dc063e12","key":"08037","book":"08","title":"HYMN XXXVII. Indra.","link":"https://indra.ai/rigveda/hymns/08037.html","text":"p: THIS prayer, and those who shed the juice, in wars with Vrtra thou holpest, indra, Lord of Strength, with all thy assists. O Vrtra conquerer, from libation poured at noon, drink of the Soma juice, thou blameless Thunderer.\n\np: Thou mighty Conqueror of hostile armaments, O Indra, Lord of Strength, with all thy saving help.\n\np: Sole Ruler, thou art Sovran of this world of life, O Indra, Lord of Strength, with all thy saving help.\n\np: Thou only sunderest these two consistent worlds, O Indra, Lord of Strength, with all thy saving help.\n\np: Thou art the Lord supreme o’er rest and energy, O Indra, Lord of Strength, with all thy saving help.\n\np: Thou helpest one to power, and one thou hast not helped, O Indra, Lord of Strength, with all thy saving aid.\n\np: Hear thou Syavasva while he sings to thee, as erst thou heardest Atri when he wrought his holy rites. Indra, thou only gavest Trasadasyu aid in the fierce fight with heroes, strengthening his powers.","people":["Indra","Soma","Vrtra","Atri"],"places":[],"things":["Lord","Soma","Juice","Help","Mighty","Heroes","Powers","Life"],"groups":[],"concepts":["Life","Holy","Strength"],"hash":"md5-UxFSRDuSKwE7oU6vHy/bxg==","created":"Monday, April 8, 2024 - 10:51:53 PM"},{"id":"af00cc54-bd34-4a5d-9587-76a75dbd78ba","key":"08038","book":"08","title":"HYMN XXXVIII. Indra and Agni.","link":"https://indra.ai/rigveda/hymns/08038.html","text":"p: YE Twain are Monks of offering, winners in war and holy works: Indra and Agni, mark this well.\n\np: Ye bounteous riders on the car, ye Vrtra conquerers unsubdued: Indra and Agni, mark this well.\n\np: The men with pressing-stones have pressed this meath of yours which gives delight: Indra, and Agni, mark this well.\n\np: Accept  'our offering for weal, sharers of praise! the Soma shed: Indra and Agni. Heroes, come.\n\np: Be pleased with these libations which attract you to our sacred gifts Indra and Agni. Heroes, come.\n\np: Accept this eulogy of mine whose model is the Gayatri: Indra and Agni. Heroes, Come.\n\np: Come with the early-faring Devas, ye who are Lords of genuine wealth: Indra and Agni, to the Soma-draught\n\np: Hear ye the call of Atris, hear Syavasva as he sheds the juice: Indra and Agni to the Soma-draught\n\np: Thus have I called you to our aid as sages called on you of old: Indra and AgniH!\n\np: Indra's and Agni's grace I claim, Sarasvati's associates To whom this psalm of praise is sung.","people":["Indra","Soma","Vrtra","Agni","Sarasvati"],"places":[],"things":["Meath","Soma","Offering","Wealth","Men","Juice","Car","Praise","Delight","Heroes","Pressing-Stones","Libations","call","Gifts"],"groups":["Devas","Atris","Monks"],"concepts":["Holy","Sacred","Offering","Libations","Pleased"],"hash":"md5-D3BBOykwdh9Z0FL8c59zXA==","created":"Monday, April 8, 2024 - 10:51:53 PM"},{"id":"b1e9b65c-4288-470a-bf4c-e38c03ffb3f5","key":"08039","book":"08","title":"HYMN XXXIX. Agni.","link":"https://indra.ai/rigveda/hymns/08039.html","text":"p: THE glorious Agni have I praised, and worshipped with. the sacred food. May Agni deck the Devas for us. Between both gathering-places he goes on his embassy, the Sage. May all the others die away.\n\np: Agni, burn down the word within their bodies through our newest speech, All hatreds of the godless, all the wicked man's malignities. Away let the destroyers go. May all the others die away.\n\np: Agni, I offer hymns to thee, like holy oil within thy mouth. Acknowledge them. among the Devas, for thou art the most excellent, the worshipper's blissful messenger. Let all the others die away.\n\np: Agni bestows all vital power even as each man supplicates. He brings the Vasus strengthening gifts, and grants delight, in rest and stir, forevery calling on the Devas. Let all the others die away.\n\np: Agni hath made himself renowned by wonderful victorious act. He is the Monk of all the tribes, chosen with offerings meeds. He urges Deities to receive. Let all the others die away.\n\np: Agni knows all that springs from Devas, he knows the mystery of men. Giver of wealth is Agni, he uncloses both the doors to us when worshipped with our newest gift. Let all the others die away.\n\np: Agni inhabiteth with Devas and men who offer offering. He cherisheth with great delight much wisdom, as all things that be, Deva.among Devas adorable. May all the others die away.\n\np: Agni who liveth in all streams, Lord of the Sevenfold Race of menhim dweller in three homes we seek, best slayer of the Dasyus for Mandhatar, first in offering. Let all the others die away.\n\np: Agni the Wise inhabiteth three gathering-places, triply formed. Decked as our envoy let the Sage bring hither and conciliate the Thrice Eleven Deities. Let all the others die away.\n\np: Our Agni, thou art first among the Devas, and first mid living men. Thou only rulest over wealth. Round about thee, as natural dams, circumfluous the waters run. Let all the others die away.","people":["Agni","Deva"],"places":[],"things":["Lord","Waters","Glorious","Offering","Wealth","Food","Men","Streams","Wise","Worshipper","Delight","Gift","Adorable","Excellent","Offerings","Sage","Gifts"],"groups":["Devas","Dasyus","Deities","Man","Vasus"],"concepts":["Holy","Sacred","Wisdom","Offering","Offerings","Worshipped","Giver","Glorious","Speech"],"hash":"md5-1PkOxw3bOOnS1OR3yTOGZA==","created":"Monday, April 8, 2024 - 10:51:54 PM"},{"id":"ac62e8cf-f4e9-4c80-ae37-432a7dd132a7","key":"08040","book":"08","title":"HYMN XL. Indra and Agni.","link":"https://indra.ai/rigveda/hymns/08040.html","text":"p: INDRA and Agni, surely ye as Conquerors will give us wealth, Whereby in fight we may o’ercome that which is strong and firmly fixed, as Agni burns the woods with wind. Let all the others die away.\n\np: We set no snares to tangle you; Indra we worship and adore. Hero of heroes mightiest. Onc. May he come unto us with his Steed, come unto us to win us strength, and to complete  'the offering.\n\np: For, famous Indra and Agni, ye are dwellers in the midst of frays. Sages in wisdom, ye are knit to him who seeketh you as friends. Heroes, bestow on him his wish.\n\np: Nabhaka-like, with sacred song Indra's and Agni's praise I sing, theirs to whom all this world belongs, this heaven and this mighty earth which bear rich treasure. in their lap.\n\np: To Indra and to Agni send your meditations, as was Nabhaka's wont. Who oped with sideway opening the sea with its foundations seven—Indra all powerful in his might.\n\np: Tear thou asunder, as of old, like tangles of a creeping plant, Demolish thou the Dasa's might. May we with Indra's help divide the treasure. he hath gathered up.\n\np: What time with this same song these men call Indra and Agni sundry ways, may we with our own heroes quell those who provoke us to the fight, and conquer those who strive with us.\n\np: The Two refulgent with their beams rise and come downward from the sky. By Indra's and by Agni's hest, flowing away, the rivers, run which they released from their restraint.\n\np: O Indra, many are thine aids, many thy ways of guiding us, Lord of the Bay Steeds, Hinva's Son. To a Good Hero come our meditations, which soon shall have accomplishment.\n\np: Inspire him with your holy hymns, the Hero bright and glorioushim who with might demolisheth even the brood of Susna, and winneth for us the heavenly streams.\n\np: Inspire him worshipped with fair rites, the glorious Hero truly brave. He brake in pieces Susna's brood who still expected not the stroke, and won for us the heavenly streams. Let all the others die away.\n\np: Thus have we sung anew to Indra and Agni, as sang our sires, Angirases, and Mandhatar. Guard us with triple shelter and preserve us. May we be masters of a store of riches.","people":["Indra","Agni","Susna"],"places":["Earth","Heaven","Sky"],"things":["Worship","Masters","Steeds","Lord","Rivers","Glorious","Offering","Treasure","Wealth","Men","Streams","Might","Song","Help","Strong","Mighty","Praise","Brave","Heroes","Friends","Hero","call","Riches"],"groups":["Son","Angirases"],"concepts":["Good","Heavenly","Holy","Sacred","Strength","Wisdom","Offering","Worshipped","Glorious","Powerful"],"hash":"md5-R7B8RbQEEJuaoHXKmKpHCA==","created":"Monday, April 8, 2024 - 10:51:54 PM"},{"id":"5dd5b56d-1a81-4617-bfdf-f415dcdf641e","key":"08041","book":"08","title":"HYMN XLI. Varuna.","link":"https://indra.ai/rigveda/hymns/08041.html","text":"p: To make this Varuna come forth sing thou a song unto the band of Maruts wiser than thyself. This Varuna who guardeth well the thoughts of men like herds of kine. Let all the others die away.\n\np: Him altogether praise I with the song and hymns our fathers sang, and with Nabhaka's eulogies. Him dwelling at the rivers’ source, surrounded by his Sisters Seven.\n\np: The nights he hath encompassed, and stablished the morns with magic art visible over all is he. His dear Ones, following his Law, have prospered the Three Dawns for him.\n\np: He, visible o’er all the earth, stablished the quarters of the sky: He measured out the eastern place, that is the fold of Varuna: like a strong herdsman is the Deva.\n\np: He who supports the worlds of life, he who well knows the hidden names mysterious of the morning beams. He cherishes much wisdom, Sage, as heaven brings forth each varied form.\n\np: In whom all wisdom centres, as the nave is set within the wheel. Haste ye to honour Trita, as kine haste to gather in the fold, even as they muster steeds to yoke.\n\np: He wraps these regions as a robe; he contemplates the tribes of Devas and all the works of mortal men. Before the home of Varuna all the Devas follow his decree.\n\np: He is an Ocean far-removed, yet through the heaven to him ascends the worship which these realms possess. With his bright foot he overthrew their magic, and went up to heaven.\n\np: Ruler, whose bright far-seeing rays, pervading all three earths, have filled the three superior realms of heaven. Firm is the seat of Varuna: over the Seven he rules as King.\n\np: Who, after his decree, o’erspread the Dark Ones with a robe of light. Who measured out the ancient seat, who pillared both the worlds apart as the Unborn supported heaven. Let all the others die away.","people":["Varuna","Trita","Deva"],"places":["Ocean","Earth","Heaven","Sky"],"things":["Worship","Steeds","Rivers","Light","Men","Song","Home","Strong","Praise","Form","King","Sage","Morning","Life","Wheel"],"groups":["Devas","Maruts","Fathers","Dawns"],"concepts":["Life","Wisdom"],"hash":"md5-Q7igCScZ21slpHG7M03feA==","created":"Monday, April 8, 2024 - 10:51:54 PM"},{"id":"12e37470-0a5a-4a79-b1ff-321218b90b30","key":"08042","book":"08","title":"HYMN XLII Varuna.","link":"https://indra.ai/rigveda/hymns/08042.html","text":"p: LORD of all wealth, the Asura propped the heavens, and measured out the broad earth's wide expanses. He, King supreme, approached all living creatures. All these are Varuna's holy operations.\n\np: So humbly worship Varuna the Mighty revere the wise Guard of World Immortal. May he vouchsafe us triply-barred protection. O Earth and Heaven, within your lap preserve us.\n\np: Sharpen this song of him who strives his utmost, sharpen, Deva.Varuna, his strength and insight; May we ascend the ship that bears us safely, whereby we may pass over all misfortune.\n\np: Asvins, with songs the singer stones have made you hasten hitherward, Nasatyas, to the Soma-draught. Let all the others die away.\n\np: As the sage Atri with his hymns, O Asvins, called you eagerly, Nasatyas, to the Soma-draught. Let all the others die away.\n\np: So have I called you to our aid, even as the wise have called of old, Nasatyas, to the Soma-draught. Let all the others die away.","people":["Soma","Varuna","Asvins","Nasatyas","Atri","Deva"],"places":["Earth","Heaven"],"things":["Worship","Lord","Soma","Singer","Wealth","Song","Wise","Mighty","Ascend","Songs","King","Sage"],"groups":["Asura","Immortal"],"concepts":["Immortal","Holy","Strength"],"hash":"md5-kh2oEQcuIRkZ66grtg6Tdg==","created":"Monday, April 8, 2024 - 10:51:54 PM"},{"id":"8893a2cd-5823-43ae-8f09-23f5fd03e4ec","key":"08043","book":"08","title":"HYMN XLIII. Agni.","link":"https://indra.ai/rigveda/hymns/08043.html","text":"p: THESE songs of mine go forth as lauds of Agni, the disposing Sage, whose worshipper is ne’er o’erthrown.\n\np: Wise Agni Jatavedas, I beget a song of praise for thee. Who willingly receivest it.\n\np: Thy sharpened flames, O Agni, like the gleams of light that glitter through, Devour the forests with their teeth.\n\np: Gold-coloured, bannered with the smoke, urged by the wind, aloft to heaven Rise, lightly borne, the flames of fire.\n\np: These lightly kindled fiery flames are all around made visible, Even as the gleanings of the Dawns.\n\np: As Jatavedas speeds along, the dust is black beneath his feet, when Agni spreads upon the earth.\n\np: Making the plants his nourishment, Agni devours and wearies not, Seeking the tender shrubs again.\n\np: Bending him down with all his tongues, he flickers with his fiery glow Splendid is Agni in the woods.\n\np: Agni, thine home is in the floods: into the plants thou forcest way, and as their Child art born anew.\n\np: Worshipped with offerings shines thy flame, O Agni, from the sacred oil, with kisses on the ladle's mouth.\n\np: Let us serve Agni with our hymns, Disposer, fed on ox and cow, who bears the Soma on his back.\n\np: Yea, thee, O Agni, do we seek with homage and with fuel, Monk Whose wisdom is most excellent.\n\np: O worshipped with oblations, pure Agni, we call on thee as erst, Did Bhrgu, Manus, Angiras.\n\np: For thou, O Agni, by the fire, Sage by the Sage, Good by the Good, Friend by the Friend, art lighted up.\n\np: So wealth in thousands, food with store of heroes give thou to the sage, O Agni, to the worshipper.\n\np: O Agni, Brother, made by strength, Lord of red steeds and brilliant sway, Take pleasure in this laud of mine.\n\np: My praises, Agni, go to thee, as the cows seek the stall to meet, the lowing calf that longs for milk.\n\np: Agni, best Angiras, to thee all people who have pleasant homes, Apart, have turned as to their wish.\n\np: The sages skilled in holy song and thinkers with their thoughts have urged Agni to share the sacred feast.\n\np: So, Agni, unto thee the Monk, invoker, strong in forays, pray Those who spin out  'the offering.\n\np: In many a place, the same in look art thou, a Prince o’er all the tribes In battles we invoke thine aid.\n\np: Pray thou to Agni, pray to him who blazes served with sacred oil: Let him give ear to this our call.\n\np: We call on thee as such, as one who hears, as Jatavedas, one, Agni! who beats away our foes.\n\np: I pray to Agni, King of men, the Wonderful, the President Of holy Laws. May he give ear.\n\np: Him like a bridegroom, him who stirs all people, like a noble horselike a fleet steed, we instigate.\n\np: Slaying things deadly, burning up foes, Raksasas, on every side, Shine, Agni, with thy sharpened flame.\n\np: Thou whom the people kindle even as Manus did, best Angiras! O Agni, mark thou this my speech.\n\np: O Agni, made by strength! be thou born in the heavens or born in floods, as such we call on thee with songs.\n\np: Yea, all the people, all the folk who have good dwellings, each apart, Send food for thee to eat thereof.\n\np: O Agni, s. May we, devout, gazed at by men, throughout our days, pass lightly over all distress.\n\np: We venerate with cheerful hearts the cheerful Agni, dear to all, Burning, with purifying flame.\n\np: So thou, O Agni rich in light, beaming like Surya with thy rays Boldly demolishest the gloom,\n\np: We meditate to thee for this thy gift, Victor the gift that faileth not, O Agni, choicest wealth from thee.","people":["Soma","Agni","Angiras","Surya","Raksasas"],"places":["Earth","Heaven"],"things":["Milk","Steeds","Lord","Born","Soma","Offering","Shine","Light","Wealth","Food","Men","Song","Gold","Home","Wise","Strong","Praise","Worshipper","Heroes","Gift","Excellent","People","Offerings","Songs","Friend","King","Sage","Cow","call"],"groups":["Jatavedas","Dawns","Child","Brother"],"concepts":["Good","Holy","Sacred","Strength","Wisdom","Devout","Offering","Offerings","Worshipped","Noble","Speech"],"hash":"md5-DJLCE5zjzJpY91AnTeswKg==","created":"Monday, April 8, 2024 - 10:51:54 PM"},{"id":"8c581e2b-0cce-4106-ae58-139515179c4f","key":"08044","book":"08","title":"HYMN XLIV. Agni.","link":"https://indra.ai/rigveda/hymns/08044.html","text":"p: PAY service unto Agni with your fuel, rouse your Guest with oil: In him present your offerings.\n\np: Agni, do thou accept my laud, be magnified by this my song: Welcome my sweetly-spoken words.\n\np: Agni, envoy, I place in front; the oblation-bearer I address: Here let him seat the Deities.\n\np: Agni, the lofty flames of thee enkindled have gone up on high, Thy bright flames, thou Refulgent One.\n\np: Beloved! let my ladles full of sacred oil come near to thee: Agni, accept our offerings.\n\np: I worship Agni—may he hear!—the cheerful, the Invoker, Monk, Of varied splendour, rich in light.\n\np: Ancient Invoker, meet for praise, beloved Agni, wise and strong, the visitant of solemn rites.\n\np: Agni, best Angiras, accept straightway these offerings, and guide The seasonable offering.\n\np: Excellent Deva, with brilliant flames, enkindled bring thou hitherward, knowing the way, the Heavenly Host.\n\np: Him, Sage and Herald, void of guile, ensign of offers, him Smoke-bannered, rich in light, we seek.\n\np: O Agni, be our Guardian thou, Deva, against those who injure us: Destroy our foes, thou Son of Strength.\n\np: Making his body beautiful, Agni the Sage hath waxen by The singer and his ancient hymn.\n\np: I invocate the Child of Strength, Agni with purifying flame, At this well-ordered offering.\n\np: So Agni, rich in many friends, with fiery splendour, seat thyself With Devas upon our sacred grass.\n\np: The mortal man who serves the Deva.Agni within his own abode, for him he causes wealth to shine.\n\np: Agni is head and height of heaven, the Master of the earth is he: He quickeneth the waters’ seed.\n\np: Upward, O Agni, rise thy flames, pure and resplendent, blazing high, Thy lustres, fair effulgences.\n\np: For, Agni, thou as Lord of Light rulest o’er choicest gifts. May I, Thy singer, find defence in thee.\n\np: O Agni, they who understand stir thee to action with their thoughts: So let our songs enhance thy might.\n\np: We ever claim the friendship of Agni, the singing messenger, Of Deva.like nature, void of guile.\n\np: Agni who bears most holy sway, the holy Singer, holy Sage. Shines holy when we worship him.\n\np: Yea, let my meditations, let my songs exalt thee evermore. Think, Agni, of our friendly bond,\n\np: If I were thou and thou wert I, O Agni, every prayer of thine Should have its due fulfilment here.\n\np: For Excellent and Lord of wealth. art thou O Agni, rich in light: May we enjoy thy favouring grace.\n\np: Agni, to thee whose laws stand fast our resonant songs of praise speed forth, as rivers hasten to the sea.\n\np: Agni, the Youthful Lord of men, who stirreth much and eateth all, the Sage, I glorify with hymns.\n\np: To Agni let us haste with lauds, the Guide of offerings rites, Armed with sharp teeth, the Mighty One.\n\np: And let this man, good Agni, be with thee the singer of thy praise: Be gracious, Holy One, to him.\n\np: For thou art sharer of our feast, wise, ever watchful as a Sage: Agni, thou shinest in the sky.\n\np: O Agni, Sage, before our foes, before misfortunes fall on us, Excellent Lord, prolong our lives.","people":["Agni","Angiras","Deva"],"places":["Earth","Heaven","Sky"],"things":["Worship","Master","Lord","Rivers","Waters","Singer","Offering","Shine","Light","Wealth","Men","Might","Song","Wise","Strong","Mighty","Grass","Praise","Hymn","Splendour","Offers","Excellent","Offerings","Friends","Songs","Sage","Gifts"],"groups":["Devas","Deities","Son","Child","Man"],"concepts":["Good","Heavenly","Friendship","Beautiful","Holy","Sacred","Strength","Offering","Offerings"],"hash":"md5-mibYto2/GScxoQZyZRDi5g==","created":"Monday, April 8, 2024 - 10:51:54 PM"},{"id":"94c423a8-33c1-4c3b-908e-381b2cc6c38e","key":"08045","book":"08","title":"HYMN XLV. Indra","link":"https://indra.ai/rigveda/hymns/08045.html","text":"p: HITHERWARD! they who light flame and straightway trim the sacred grass. Whose Friend is Indra ever young.\n\np: High is their fuel, great their laud, wide is their splinter from the stake, whose Friend is Indra ever young.\n\np: Unequalled in fight the hero leads his army with the warrior chiefs. Whose Friend is Indra ever young.\n\np: The new-born Vrtra conquerer asked his Mother, as he seized his shaft, who are the fierce? Who are renowned?\n\np: Savasi answered. He who seeks thine enmity will battle like a stately elephant on a hill.\n\np: And hear, O Maghavan; to him who craves of thee thou grantest all Whate’er thou makest firm is firm.\n\np: What time the Warrior Indra goes to battle, borne by noble steeds, best of all charioteers is he.\n\np: Repel, O Thunder-armed, in all directions all attacks on us: And be our own most glorious Deva.\n\np: May Indra set our car in front, in foremost Place to win the spoil. He whom the wicked injure not.\n\np: Thine enmit. May we escape, and, Sakra, for thy bounty, rich In kine. May we come near to thee\n\np: Softly approaching, Thunder-armed wealthy by hundreds, rich in steeds, Unrivalled, ready with our gifts.\n\np: For thine exalted excellence gives to thy worshippers each day Hundreds and thousands of thy boons.\n\np: Indra, we know thee breaker-down even of strong forts, winner of spoil, as one who conquers wealth for us.\n\np: Though thou art highest, Sage and Bold! let the drops cheer thee when we come To thee as to a trafficker.\n\np: Bring unto us the treasure. of the opulent man who, loth to give, Hath slighted thee for gain of wealth.\n\np: Indra, these friends of ours, supplied with Soma, wait and look to thee, as men with fodder to the herd.\n\np: And thee who art not deaf, whose cars are quick to listen, for our aid, We call to us from far away.\n\np: When thou hast listened, make our call one which thou never wilt forget, and be our very nearest Friend.\n\np: When even now, when we have been in trouble, we have thought of thee, O Indra, give us gifts of kine.\n\np: O Lord of Strength, we rest on thee, as old men rest upon a staff: We long to have. thee dwell with us.\n\np: To Indra sing a song of praise. Hero of mighty valour, him Whom no one challenges to war.\n\np: Hero, the Soma being shed, I pour the juice for thee to drink: Sate thee and finish thy carouse.\n\np: Let not the fools, or those who mock beguile thee when they seek thine aid Love not the enemies of prayer.\n\np: Here let them with rich milky draught cheer thee to great munificence: Drink as the wild-bull drinks the lake.\n\np: Proclaim in our assemblies what deeds, new and ancient, far away, the Vrtra conquerer hath achieved.\n\np: In battle of a thousand arms Indra drank Kadru's Soma juice: There he displayed his manly might.\n\np: True undeniable strength he found in Yadu and in Turvasa, and conquered through  'the offering.\n\np: Him have I magnified, our Lord in, common, Guardian of your folk, Discloser of great wealth in kine;\n\np: Rbhuksan, not to be restrained, who strengthened Tugra's son in lauds, indra beside the flowing juice;\n\np: Who for Trisoka clave the hill that formed a wide receptacle, So that the cows might issue forth.\n\np: Whate’er thy plan or purpose be, whate’er, in transport, thou wouldst do, Do it not, indra, but be kind.\n\np: But little hath been heard of done upon the earth by one like thee i Let thine heart, indra, turn to us.\n\np: Thine then shall be this high renown, thine shall these lofty praises be, when, indra, thou art kind to us.\n\np: Not for one trespass, not for two, O Hero, subdue us, nor for three, Nor yet for many trespasses.\n\np: I fear one powerful like thee, the crusher-down of enemies, Mighty, repelling all attacks.\n\np: O wealthy Deva, ne’e. May I live to see my friend or son in need: Hitherward let thy heart be turned.\n\np: What friend, O people, unprovoked, hath ever said unto a friend. He turns and leaves us in distress?\n\np: Hero, insatiate enjoy this Soma juice so near to thee, Even as a hunter rushing down.\n\np: Hither I draw those Bays of thine yoked by our hymn, with splendid car, that tho. Mayst give unto the monks.\n\np: Drive all our enemies away, smite down the foes who press around, and bring the wealth for which we long:\n\np: O Indra, that which is concealed in strong firm place precipitous: Bring us the wealth for which we long\n\np: Great riches which the world of men shall recognize as sent by thee: Bring us the wealth for which we long.","people":["Indra","Soma","Vrtra","Yadu","Turvasa","Sakra","Maghavan","Tugra","Deva","Rbhuksan"],"places":["Earth"],"things":["Cheer","Steeds","Lord","Born","Soma","Glorious","Offering","Light","Treasure","Wealth","Men","Might","Juice","Song","Strong","Mighty","Grass","Car","Praise","Hymn","Lake","People","Friends","Drops","Warrior","Friend","Hero","Sage","call","spoil","Riches","Cars","Gifts"],"groups":["Worshippers","Mother","Son","Man","Monks"],"concepts":["Cars","Love","Splendid Car","Sacred","Strength","Offering","Glorious","Powerful","Winner","Noble"],"hash":"md5-ieO0XrmCdLanYF4pB5WMIQ==","created":"Monday, April 8, 2024 - 10:51:54 PM"},{"id":"1fb16fe3-a714-4417-a16b-98a946e8c2ac","key":"08046","book":"08","title":"HYMN XLVI. Indra.","link":"https://indra.ai/rigveda/hymns/08046.html","text":"p: WE, indra, Lord of ample wealth, our Guide, depend on one like thee, Thou driver of the Tawny Steeds.\n\np: For, Hurler of the Bolt, we know thee true, the giver of our food, We know the giver of our wealth.\n\np: O thou whose majesty the bards celebrate with their songs, thou Lord, Of hundred powers and hundred aids.\n\np: Fair guidance hath the mortal man whom Aryaman, the Marut host, and Mitra, void of guile, protect.\n\np: Kine, steeds, and hero strength he gains, and prospers, by the Adityas sped, Ever in wealth which all desire.\n\np: We meditate to Indra for his gift, to him the Fearless and the Strong, We meditate to him the Lord of wealth.\n\np: For verily combined in him are all the fearless powers of aid. Him, rich in wealth, let swift Steeds bring to us, his Bays, to Soma juice for his carouse:\n\np: Yea, that most excellent carouse, indra, which subdues most enemies, with Heroes wins the light of heaven, and is invincible in war:\n\np: Which merits fame, all-bountiful! and, unsubdued, hath victory in deeds of might. So come to our libations, Strongest! Excellent! May we obtain a stall of kine.\n\np: Responding to our wish for cows, for steeds, and chariots, as of old, be gracious, Greatest of the Great\n\np: For. Hero, nowhere can I find the bounds of thy munificence. Still do thou favour us, O Bolt-armed Maghavan: with strength hast thou rewarded hymns.\n\np: High, glorifier of his friend, he knows all generations, he whom many praise. All races of mankind with ladies lifted up invoke that Mighty Indra's aid.\n\np: Be he our Champion and Protector in great deeds, rich in all wealth, the Vrtra conquerer, Maghavan.\n\np: In the juice sing to your Hero with high laud, to him the Wise, to Indra, glorious in his name, the Mighty One, even as the hymn alloweth it.\n\np: Thou givest wealth to me myself, thou givest treasure., Excellent! and the strong steed, O Much-invoked, in deeds of might, yea, even now.\n\np: Him, Sovran Ruler of all precious things, who even hath power o’er this fair form of his, as now it taketh shape, and afterward,\n\np: We praise, so that the Mighty On. May speed to you, pourer of bounties, Traveller, prepared to go. Thou favourest the Maruts known to all, by song and offering. With song and praise I sing to thee.\n\np: We in  'the offering perform their will whose voice is lifted high, the worship of those Thundering Ones who o’er the ridges of these mountains fly in troops.\n\np: O Indra, Mightiest, bring us that which crushes men of evil minds, Wealth suited to our needs, O Stirrer of the thought, best wealth, O thou who stirrest thought.\n\np: O Winner, noble winner, strong, wondrous, most splendid, excellent, Sole Lord of victory, bring all-overpowering wealth, joy-giving, chief in deeds of might.\n\np: Now let the godless man approach who hath received reward so great As Vasa, Asvya, when this light of morning dawned, received from Prthusravas, from Kanita's son.\n\np: Steeds sixty thousand and ten thousand kine, and twenty hundred camels I obtained; Ten hundred brown in hue, and other ten red in three spots: in all, ten thousand kine.\n\np: Ten browns that make my wealth increase, fleet steeds whose tails are long and fair, Turn with swift whirl my chariot wheel;\n\np: The gifts which Prthusravas gave, Kanita's son munificent. He gave a chariot wrought of gold: the prince was passing bountiful, and won himself most lofty fame.\n\np: Come thou to this great rite of ours, Vayu! to give us vigorous light. We have served thee that thou mightest give much to us, yea, mightest quickly give great wealth.\n\np: Who with thrice seven times seventy horses comes to us, invested with the rays of morn, Through these our Soma-draughts and those who press, to give, drinker of pure bright Soma Juice.\n\np: Who hath inclined this glorious one, bounteous himself, to give us gifts. Borne on firm chariot with the prosperous Nahusa, wise, to a man yet more devout.\n\np: Sole Lord in beauty meet for praise, O Vayu, dropping fatness down, Hurried along by steeds, by camels, and by hounds, spreads forth thy train: even this it is.\n\np: So, as a prize dear to the strong, the sixty thousand have I gained, Bulls that resemble vigorous steeds.\n\np: To me come oxen like a herd, yea, unto me the oxen come.\n\np: And in the grazing herd he made a hundred camels bleat for me, and twenty hundred mid the white.\n\np: A hundred has the sage received, Dasa Balbutha's and Taruksa's gifts. These are thy people, Vayu, who rejoice with Indra for their guard, rejoice with Devas for guards.\n\np: And now to Vasa Asvya here this stately woman is led forth, Adorned with ornaments of gold.","people":["Indra","Soma","Vrtra","Vayu","Mitra","Maghavan","Aryaman"],"places":["Heaven"],"things":["Worship","Mankind","Victory","Steeds","Lord","Mountains","Soma","Chariots","Glorious","Offering","Light","Treasure","Wealth","Food","Men","Might","Juice","Song","Joy","Beauty","Gold","Wise","Strong","Mighty","Chief","Praise","Voice","Hymn","Heroes","Gift","Form","Excellent","People","Powers","Libations","Songs","Friend","Hero","Sage","Horses","Morning","Gifts","Wheel","Sovran Ruler"],"groups":["Devas","Maruts","Marut","Son","Man","Woman","Adityas"],"concepts":["Evil","Strength","Devout","Offering","Giver","Glorious","Libations","Swift","Winner","Noble"],"hash":"md5-QW6euRzoej+rK4V8ihW7tw==","created":"Monday, April 8, 2024 - 10:51:54 PM"},{"id":"f43e7055-8889-4354-9785-f7ec1aadd428","key":"08047","book":"08","title":"HYMN XLVII. Adityas.","link":"https://indra.ai/rigveda/hymns/08047.html","text":"p: GREAT help ye give the worshipper, Varuna, Mitra, MightyOnes! No sorrow ever reaches him whom ye, Adityas, keep from harm. Yours are incomparable aids, and good the assist they afford.\n\np: O Devas, Adityas, well ye know the way to keep all woes afar. As the birds spread their sheltering wings, spread your protection over us.\n\np: As the birds spread their sheltering wings let your protection cover us. We mean all shelter and defence, ye who have all things for your own.\n\np: To whomsoever they, most Wise, have given a home and means of life, O'er the whole riches of this man they, the Adityas, have control.\n\np: As drivers of the car avoid ill roads, let sorrows pass us by. May we be under Indra's guard, in the Adityas’ favouring grace.\n\np: For verily men sink and faint through loss of wealth which ye have given. Much hath he gained from you, O Devas, whom ye, Adityas, have approached.\n\np: On him shall no fierce anger fall, no sore distress shall visit him, to whom, Adityas, ye have lent your shelter that extendeth far.\n\np: Resting in you, O Devas, we are like men who fight in coats of mail. Ye guard us from each great offence, ye guard us from each lighter fault.\n\np: May Aditi defend us. May Aditi guard and shelter us, Mother of wealthy Mitra and of Aryaman and Varuna.\n\np: The shelter, Devas, that is secure, auspicious, free from malady, a sure protection, triply strong, even that do ye extend to us.\n\np: Look down on us, Adityas, as a guide exploring from the bank. Lead us to pleasant ways as men lead horses to an easy ford.\n\np: Ill be it for the demons' friend to find us or come near to us. But for the MilchCow be it well, and for the man who strives for fame.\n\np: Each evil deed made manifest, and that which is concealed, O Devas, the whole thereof remove from us to Trita Aptya far away.\n\np: Daughter of Heaven, the dream that bodes evil to us or to our kine, Remove, O Lady of the Light, to Trita Aptya far away.\n\np: Even if, O Child of Heaven, it make a garland or a chain of gold, the whole bad dream, whate’er it be, to Trita Aptya we consign.\n\np: To him whose food and work is this, who comes to take his share therein, to Trita, and to Dvita, Dawn! bear thou the evil dream away.\n\np: As we collect the utmost debt, even the eighth and sixteenth part, So unto Aptya we transfer together all the evil dream.\n\np: Now have we conquered and obtained, and from our trespasses are free. Shine thou away the evil dream, O Dawn, whereof we are afraid. Yours are incomparable aids, and good the assist they afford.","people":["Indra","Mitra","Varuna","Trita","Dawn","Aditi","Aptya","Aryaman"],"places":["Heaven"],"things":["Work","Shine","Light","Wealth","Food","Men","Gold","Help","Home","Wise","Strong","Car","Worshipper","Wings","Friend","Horses","Riches","Life","MilchCow"],"groups":["Devas","Mother","Child","MightyOnes","Man","Adityas"],"concepts":["Good","Evil","Life","Auspicious"],"hash":"md5-6jVmPqvTBR4s0rTcNcMkFQ==","created":"Monday, April 8, 2024 - 10:51:54 PM"},{"id":"00ec653d-5156-44fe-9180-0d18b485db03","key":"08048","book":"08","title":"HYMN XLVIII. Soma.","link":"https://indra.ai/rigveda/hymns/08048.html","text":"p: WISELY have I enjoyed the savoury viand, religious-thoughted, best to find out treasure., the food to which all Deities and mortals, calling it meath, gather themselves together.\n\np: Tlou shalt be Aditi as thou hast entered within, appeaser of celestial anger. Indu, enjoying Indra's friendship, bring us—as a swift steed the car—forward to riches.\n\np: We have drunk Soma and become immortal; we have attained the light, the Devas discovered. Now wha. May foeman's malice do to harm us? What, O Immortal, mortal man's deception?\n\np: Absorbed into the heart, be sweet, O Indu, as a kind father to his son, O Soma, as a wise Friend to friend: do thou, wide-ruler, O Soma, lengthen out our days for living.\n\np: These glorious drops that give me freedom have I drunk. Closely they knit my joints as straps secure a car. Let them protect my foot from slipping on the way: yea, let the drops I drink preserve me from disease.\n\np: Make me shine bright like fire produced by friction: give us a clearer sight and make us better. For in carouse I think of thee, O Soma, Shall I, as a rich man, attain to comfort?\n\np: May we enjoy with an enlivened spirit the juice thou givest, like ancestral riches. O Soma, King, prolong thou our existence as Surya makes the shining days grow longer.\n\np: King Soma, favour us and make us prosper: we are thy devotees; of this be mindful. Spirit and power are fresh in us, O Indu give us not up unto our foeman's pleasure.\n\np: For thou hast settled in each joint, O Soma, aim of men's eyes and guardian of our bodies. When we offend against thine holy statutes, as a kind Friend, Deva, best of all, be gracious.\n\np: May I be with the Friend whose heart is tender, who, Lord of Bays! When quaffed will never harm me- This Soma now deposited within me. For this, I pray for longer life to Indra.\n\np: Our maladies have lost their strength and vanished: they feared, and passed away into the darkness. Soma hath risen in us, exceeding mighty, and we are come where men prolon existence.\n\np: , Fathers, that Indu which our hearts have drunken, Immortal in himself, hath entered mortals. So let us serve this Soma with oblation, and rest securely in his grace and favour.\n\np: Associate with the Fathers thou, O Soma, hast spread thyself abroad through earth and heaven. So with oblation let us serve thee, Indu, and so let us become the lords of riches,\n\np: Give us your blessing, O ye Devas’ preservers. Neve. May sleep or idle talk control us. But evermor. May we, as friends of Soma, speak to the synod with brave sons around us.\n\np: On all sides. Soma, thou art our life-giver: aim of all eyes, light-finder, come within us. Indu, of one accord with thy protections both from behind and from before preserve us.","people":["Indu","Indra","Soma","King Soma","Deva","Surya","Aditi"],"places":["Earth","Heaven"],"things":["Meath","Lord","Soma","Glorious","Shine","Light","Treasure","Food","Men","Juice","Wise","Mighty","Car","Blessing","Brave","Lord of Bays","Friends","Drops","Friend","King","Riches","Life","Spirit"],"groups":["Devas","Fathers","Sons","Deities","Father","Son","Immortal","Man"],"concepts":["Celestial","Life","Friendship","Immortal","Holy","Strength","Giver","Glorious","Swift"],"hash":"md5-1xBuvV2l0mtqfYWEWWap4A==","created":"Monday, April 8, 2024 - 10:51:54 PM"},{"id":"7d4b62cc-8b20-4fe6-96ee-ee905dbdc905","key":"08049","book":"08","title":"HYMN XLIX. Agni.","link":"https://indra.ai/rigveda/hymns/08049.html","text":"p: AGNI, come hither with thy fires; we choose thee as Invoking Monk. Let the extended ladle full of oil balm thee, best Monk, to sit on sacred grass.\n\np: For unto thee, O Angiras, O Son of Strength, move ladles in  'the offering. To Agni, Child of Force, whose locks drop oil, we seek, foremost in offerings rites.\n\np: Agni, thou art Disposer, Sage. Herald, bright Deva. and worshipful, best offerer, cheerful, to be praised in holy rites, pure Lord! by singers with their hymns.\n\np: Most Youthful and Eternal, bring the longing Devas to me, the guileless, for the feast. Come, Vasu, to the banquet that is well-prepared: rejoice thee, gracious, with our songs.\n\np: Famed art thou, Agni, far and wide, preserver, righteous, and a Sage. The holy singers, O refulgent kindled Deva. arrangers, call on thee to come.\n\np: Shine, most Resplendent! blaze, send bliss unto the folk, and to thy worshipper Great art thou. May my princes, with good fires, subduing foes, rest in the keeping of the Devas.\n\np: O Agni, as thou burnest down to earth even high-grown underwood, So, bright as Mitra is, burn him who injures us, him who plots ill against thy friend.\n\np: Give us not as a prey to mortal enemy, nor to the wicked friend of fiends. With conquering guards, auspicious, unassailable, protect us, O Most Youthful Deva.\n\np: Protect us, Agni, through the first, protect us through the second hymn, protect us through three hymns, O Lord of Power and Might, through four hymns, Vasu, guard thou us.\n\np: Preserve us from each fiend who brings the Devas no gift, preserve thou us in deeds of strength: For we possess in thee the nearest Friend of all, for service of the Devas and weal.\n\np: O Holy Agni, give us wealth renowned with men and strengthening life. Bestow on us, O Helper, that which many crave, more glorious still by righteousness;\n\np: Wherewith we may o’ercome our rivals in the war, o’erpowering the foe's designs. So wax thou by our food, O Excellent in strength. Quicken our thoughts that find out wealth.\n\np: Agni is even as a bull who whets and brandishes his horns. Well-sharpened are his jaws whic. May not be withstood: the Child of Strength hath powerful teeth.\n\np: Not to be stayed, O Bull, O Agni, are thy teeth when thou art spreading far and wide. Make our oblations duly offered up, O Monk, and give us store of precious things.\n\np: Thou liest in the wood: from both thy Mothers mortals kindle thee. Unweariedly thou bearest up the offerer's gifts, then shinest bright among the Devas.\n\np: And so the seven monks, O Agni, worship thee, free-giver, Everlasting One. Thou cleavest through the rock with heat and fervent glow. Agni, rise up above the men.\n\np: For you let us whose grass is trimmed call Agni, Agni, restless Deva. Let us whose food is offered call to all the tribes Agni the Invoking Monk of men.\n\np: Agni, with noble psalm that tells his wish he dwells, thinking on thee who guardest him. Speedily bring us strength of many varied sorts to be most near to assist us.\n\np: Agni, praise-singer! Lord of men, Deva.burner-up of Raksasas, Mighty art thou, the ever-present Household-Lord, Home-friend and Guardian from the sky.\n\np: Let no fiend come among us, O thou rich in light, no spell of those who deal in spells. To distant pastures drive faint hunger: far away, O Agni, chase the demons’ friends.","people":["Agni","Angiras","Mitra","Deva","Raksasas","Vasu"],"places":["Earth","Sky"],"things":["Worship","Lord","Glorious","Singer","Offering","Shine","Light","Wealth","Food","Men","Might","Home","Mighty","Grass","Banquet","Praise","Worshipper","Hymn","Gift","Excellent","Offerings","Friends","Bliss","Songs","Friend","Sage","call","Life","Gifts"],"groups":["Devas","Son","Child","Monks"],"concepts":["Good","Life","Holy","Sacred","Strength","Offering","Offerings","Giver","Auspicious","Glorious","Powerful","Noble"],"hash":"md5-6XtI2OUsRCJjK07Xv8h1VA==","created":"Monday, April 8, 2024 - 10:51:54 PM"},{"id":"ccb61062-3d1e-4bf0-9a3a-82ebf10f767e","key":"08050","book":"08","title":"HYMN L. Indra.","link":"https://indra.ai/rigveda/hymns/08050.html","text":"p: BOTH boons.may Indra, hitherward turned, listen to this prayer of ours, and mightiest Maghavan with thought inclined to us come near to drink the Soma juice.\n\np: For him, strong, independent Ruler. Heaven and Earth have fashioned forth for power and might. Thou seatest thee as first among thy peers in place, for thy soul longs for Soma juice.\n\np: Fill thyself full, O Lord of wealth, O Indra, with the juice we shed. We know thee, Lord of Bay Steeds victor in the fight, vanquishing e’en the invincible.\n\np: Changeless in truth, O Maghavan Indra, let it be as thou in wisdom willest it. May we, O fair of check, win booty with thine aid, O Thunderer, swiftly seeking it.\n\np: Indra, with all thy saving helps give us assistance, Lord of power. For after thee we follow even as glorious bliss, thee. Hero, finder-out of wealth.\n\np: Increaser of our steeds and multiplying kine, a golden well, O Deva, art thou, for no on. May impair the gifts laid up in thee. Bring me whatever thing I ask.\n\np: For thou.come to the worshipper!—wilt find great wealth to make us rich. Fill thyself full for gain of kine, full, indra, for the gain of steeds.\n\np: Thou as thy gift bestowest many hundred herds, yea, many thousands dost thou give. With singers' hymns have we brought the Fort-render near, singing to Indra for his grace.\n\np: Whether the simple or the sage, indra, have offered praise to thee. He Satakratu! by his love hath gladdened thee, ambitious! ever pressing on!\n\np: If he the Strong of arm, the breaker-down of forts, the great Destroyer, hear my call, We, seeking riches cry to Indra, Lord of wealth, to Satakratu with our lauds.\n\np: We count not then as sinners, nor as niggardly or foolish men, when with the Soma juice which we have shed we make Indra, the Mighty One, our Friend.\n\np: Him have we yoked in fight, the powerful Conqueror, debt-claimer, not to be deceived. Best charioteer, the Victor marks each fault, he knows the strong to whom he will come near.\n\np: Indra, give us security from that whereof we are afraid. Help us let thy assist give us this: drive away foes and enemies.\n\np: For thou, O liberal Lord of bounty, strengthenest his ample home who worships thee. So Indra, Maghavan, thou Lover of the Song, we with pressed Soma call on thee,\n\np: Indra is Vrtra conquerer, guard, our best defender from the foe. May he preserve our last and middlemost, and keep watch from behind us and before.\n\np: Defend us from behind, below, above, in front, on all sides, indra, shield us well. Keep far away from us the terror sent from heaven: keep impious weapons far away.\n\np: Protect us, indra, each to-day, each morrow, and each following day. Our singers, through all days, shalt thou, Lord of the brave, keep safely both by day and night.\n\np: A crushing Warrior, passing rich is Maghavan, endowed with all heroic might. Thine arms, O Satakratu, are exceeding strong, arms which have grasped the thunderbolt.","people":["Indra","Soma","Vrtra","Satakratu","Maghavan","Deva"],"places":["Earth","Heaven"],"things":["Steeds","Lord","Soma","Glorious","Wealth","Men","Might","Juice","Song","Help","Home","Strong","Mighty","Praise","Brave","Worshipper","Gift","Bliss","Warrior","Friend","Hero","Sage","call","Riches","Security","Gifts"],"groups":[],"concepts":["Heroic","Love","Wisdom","Truth","Glorious","Powerful"],"hash":"md5-bAObpYmwSp9U/m4RWufd0Q==","created":"Monday, April 8, 2024 - 10:51:54 PM"},{"id":"c5a81527-38bc-4017-be6a-116e068a1141","key":"08051","book":"08","title":"HYMN LI. Indra.","link":"https://indra.ai/rigveda/hymns/08051.html","text":"p: OFFER ye up as praise to him that wherein Indra takes delight. The Soma-bringers magnify Indra's great energy with hymns. Good are the gifts that Indra gives.\n\np: Sole among chiefs, companionless, impetuous, and peerless, he Hath waxen great o’er many folk, yea., over all things born, in might.\n\np: Lord of swift bounty, he will win e’en with a steed of worthless sort. This, indra, must be told of thee who wilt perform heroic deeds.\n\np: Come to us hither: let us pay devotions that enhance thy might, for which, most Potent! thou wouldst fain bless the man here who strives for fame.\n\np: For thou, O Indra, makest yet more bold the spirit of the bold Who with strong Soma serveth thee, still ready with his reverent prayers.\n\np: Worthy of song, he looketh down as a man looketh into wells. Pleased with the Soma-bringer's skill he maketh him his mate and friend.\n\np: In strength and wisdom all the Devas, indra, have yielded unto thee. Be thou the Guard of all, O thou whom many praise.\n\np: Praised, indra, is this might of thine, best for the service of the Devas, that thou with power dost subdue Vrtra, O Lord of Strength.\n\np: He makes the races of mankind like synods of the Beauteous One. Indra knows this his manifest deed, and is renowned.\n\np: Thy might, O Indra, at its birth, thee also, and thy mental power, in thy care, Maghavan rich in kine! they have increased exceedingly.\n\np: O Vrtra conquerer, thou and I will both combine for winning spoil. Even malignity will consent, O Bolt-armed Hero, unto us.\n\np: Let us extol this Indra as truthful and never as untrue. Dire is his death who pours no gifts great light hath he who offers them. Good are the gifts that Indra gives.","people":["Indra","Soma","Vrtra","Maghavan"],"places":[],"things":["Mankind","Lord","Born","Soma","Light","Might","Song","Strong","Praise","Delight","Offers","Friend","Hero","Winning","spoil","Death","Spirit","Gifts"],"groups":["Devas","Man"],"concepts":["Good","Birth","Death","Heroic","Strength","Wisdom","Truthful","Swift","Pleased"],"hash":"md5-t3Cw8EwT3HUW4eVYUPDfKw==","created":"Monday, April 8, 2024 - 10:51:54 PM"},{"id":"f52e8814-a95f-4b32-8fb1-dcda349765e3","key":"08052","book":"08","title":"HYMN LII. Indra.","link":"https://indra.ai/rigveda/hymns/08052.html","text":"p: WITH powers of MightyOnes hath he, Ancient, beloved, been equipped, Through whom the Father Manu made prayers efficacious with the Devas.\n\np: Him, maker of the sky, let stones wet with the Soma ne’er forsake, Nor hymns and prayer that must be said.\n\np: Indra who knew full well disclosed the kine to the Angirases. This his great deed must be extolled.\n\np: Indra, promoter of the song, the sage's Strengthener as of old, Shall come to bless and assist us at presentation of this laud.\n\np: Now after their desire's intent the pious singers with the cry Of Hail! have sung loud hymns to thee, indra, to gain a stall of kine.\n\np: With Indra rest all deeds of might, deeds done and yet to be performed, whom singers know devoid of guile.\n\np: When the Five Tribes with all their men to Indra have sent out their voice, and when the Sage hath strewn much grass, this is the Friend's own dwelling-place.\n\np: This praise is verily thine own: thou hast performed these manly deeds, and sped the wheel upon its way.\n\np: At the o’erflowing of this Steer, boldly he strode for life, and took Soma as cattle take their corn.\n\np: Receiving this and craving help, we, who with you are Daksa's sons, Would fain exalt the Maruts’ Lord.\n\np: Yea. Hero, with the singers we sing to the duly-coming Band. Allied with the, may we prevail.\n\np: With us are raining Rudras, clouds accordant in call to battle, at the death of Vrtra,","people":["Indra","Soma","Vrtra","Daksa"],"places":["Sky"],"things":["Lord","Soma","Men","Might","Song","Help","Grass","Praise","Voice","Powers","Friend","Hero","Sage","call","Cattle","Life","Death","Wheel"],"groups":["Devas","Maruts","Rudras","Sons","Father","Angirases","MightyOnes"],"concepts":["Death","Life"],"hash":"md5-FzNmcXkiSgZeNBNky3VHUQ==","created":"Monday, April 8, 2024 - 10:51:54 PM"},{"id":"5f097f8d-f61a-4818-bf22-b81929cb50d0","key":"08053","book":"08","title":"HYMN LIII. Indra.","link":"https://indra.ai/rigveda/hymns/08053.html","text":"p: MAY our hymns give thee great delight. Display thy bounty, Thunderer. Drive off the enemies of prayer.\n\np: Crush with thy foot the niggard churls who bring no gifts. Mighty art thou There is not one to equal thee.\n\np: Thou art the Lord of Soma pressed, Soma impressed is also thine. Thou art the Sovran of the folk.\n\np: Come, go thou forth, dwelling in heaven and listening to the prayers of men: Thou fillest both the heavens and earth.\n\np: Even that hill with rocky heights, with hundreds, thousands, held within. Thou for thy worshippers brakest through.\n\np: We call on thee both night and day to taste the flowing Soma juice: Do thou fulfil our heart's desire.\n\np: Where is that ever-youthful Steer, strong. necked and never yet bent down? What Brahman ministers to him?\n\np: To whose libation doth the Steer, betake him with delight therein? Who takes delight in Indra now?\n\np: Whom, Vrtra conquerer, have thy gift and hero powers accompanied? Who is thy dearest in the laud?\n\np: For thee among mankind, among the Purus is this Soma shed. Hasten thou hither: drink thereof.\n\np: This, growing by Soma and by Saryanavan, dear to thee, in Arjikiya, cheers thee best.\n\np: Hasten thou hitherward, and drink this for munificence to-day, Delightful for thine eager draught.","people":["Indra","Soma","Vrtra"],"places":["Earth","Heaven"],"things":["Mankind","Lord","Soma","Men","Juice","Strong","Mighty","Delight","Gift","Powers","Hero","call","Gifts"],"groups":["Worshippers"],"concepts":[],"hash":"md5-lQ0nuC8MTexjt3C6F1azUQ==","created":"Monday, April 8, 2024 - 10:51:54 PM"},{"id":"b4442062-9190-4f7b-bbac-05ecdd126960","key":"08054","book":"08","title":"HYMN LIV. Indra.","link":"https://indra.ai/rigveda/hymns/08054.html","text":"p: THOUGH, indra, thou art called by men from east and west, from north and south, Come hither quickly with fleet steeds\n\np: If in the effluence of heaven, rich in its light, thou takest joy, or in the sea in Soma juice.\n\np: With songs I call thee, Great and Wide, even as a cow to profit us, indra, to drink the Soma-draught.\n\np: Hither, O Indra, let thy Bays bear up and, bring upon thy car Thy glory, Deva. and majesty.\n\np: Thou, indra, wouldst be sung and praised as great, strong, lordly in thy deeds Come hither, drink our Soma juice.\n\np: We who have shed the Soma and prepared the feast are calling thee. To sit on this our sacred grass.\n\np: As, indra, thou art evermore the common Lord of all alike, as such we invocate thee now.\n\np: The men with stones have milked for thee this nectar of the Soma juice: Indra, be pleased with it, and drink.\n\np: Neglect all pious men with skill in sacred song: come hitherward, with speed, and give us high renown.\n\np: Devas. May the mighty rest unharmed, the King who gives me spotted kine, Kine decked with golden ornaments.\n\np: Beside a thousand spotted kine I have received a gift of gold, pure, brilliant, and exceeding great.\n\np: Durgaha's grandsons, giving me a thousand kine, munificent, have won renown among the Devas.","people":["Indra","Soma","Deva"],"places":["Heaven"],"things":["Steeds","Lord","Soma","Glory","Light","Men","Juice","Song","Joy","Gold","Strong","Mighty","Grass","Car","Gift","Songs","King","Cow","call"],"groups":["Devas"],"concepts":["Sacred","Pleased"],"hash":"md5-cLoW3hcrGcR9gR/a27CnMg==","created":"Monday, April 8, 2024 - 10:51:54 PM"},{"id":"ce553755-c406-46af-bb49-3065466ff1f7","key":"08055","book":"08","title":"HYMN LV. Indra.","link":"https://indra.ai/rigveda/hymns/08055.html","text":"p: LOUD singing at the sacred rite where Soma flows we monks invoke With haste, that h. May help, as the bard's Cherisher, indra who findeth wealth for you.\n\np:  Whom with fair helm, in rapture of the juice, the firm resistless slayers hinder not: Giver of glorious wealth to him who sing a his praise, honouring him who toils and pours:\n\np: Sakra, who like a curry-comb for horses or a golden goad, indra, the Vrtra conquerer, urges eagerly the opening of the stall of kine:\n\np: Who for the worshipper scatters forth ample wealth, even though buried, piled in heaps: May Indra, Lord of Bay Steeds, fair-helmed Thunderer, act at his pleasure, as he lists.\n\np: Hero whom many praise, what thou hast longed for, oven of old, from men. All that we offer unto thee, O Indra, now, offering, laud, effectual speech.\n\np: To Soma, Much-invoked, Bolt-armed! for thy carouse, Celestial, Soma-drinker come. Thou to the man who- prays and pours the juice hast been best giver of delightful wealth.\n\np: Here, verily, yesterday we let the Thunder-wielder drink his fill. So in like manner offer him the juice today. Now range you by the Glorious One.\n\np: Even the wolf, the savage beast that rends the sheep, follows the path of his decrees. So graciously accepting, indra, this our praise, with wondrous thought come forth to us.\n\np: What manly deed of vigour now remains that Indra hath not done? Who hath not heard his glorious title and his fame, the Vrtra conquerer from his birth?\n\np: 'How great his power resistless! how invincible the Vrtra conquerer's matchless might! Indra excels all usurers who see the day, excels all traffickers in strength.\n\np: O Indra, Vrtra conquerer, we, thy very constant worshippers, Bring prayers ne’er heard before to thee, O Much-invoked, O Thunder-armed, to be thy meed.\n\np: O thou of mighty acts, the aids that are in thee call forward many an eager hope. Past the water-offerings, Vasu, even of the good, hear my call, Strongest Deva, and come.\n\np: Verily, indra, we are thine, we worshippers depend on thee. For there is none but only thou to show us race thou much invoked.\n\np: From this our misery and famine set us free, from this dire curse deliver us. Succour us with thine help and with thy wondrous thought. Most Mighty, finder of the way.\n\np: Now let your Soma juice be poured; be not afraid, O Kali's sons. This darkening sorrow goes away; yea, of itself it vanishes.","people":["Indra","Soma","Vrtra","Sakra","Deva","Vasu"],"places":[],"things":["Steeds","Lord","Soma","Water","Glorious","Offering","Wealth","Men","Might","Juice","Help","Mighty","Praise","Worshipper","Offerings","Hero","Horses","call"],"groups":["Sons","Worshippers","Man","Monks"],"concepts":["Celestial","Good","Birth","Sacred","Strength","Offering","Offerings","Giver","Glorious","Speech"],"hash":"md5-r+Rn8K/Ci5Ls/Cr8lQhy5A==","created":"Monday, April 8, 2024 - 10:51:54 PM"},{"id":"898c011f-3792-404b-92c8-44676196c118","key":"08056","book":"08","title":"HYMN LVI. Adityas.","link":"https://indra.ai/rigveda/hymns/08056.html","text":"p: Now pray we to these Ksatriyas, to the Adityas for their aid, these who are gracious to assist.\n\np: May Mitra bear us o’er distress, and Varuna and Aryaman, Yea, the Adityas, as they know.\n\np: For wonderful and meet for praise is these Adityas’ saving help To him who offers and prepares.\n\np: The mighty aid of you, the Great, Varuna, Mitra, Aryaman, We claim to be our sure defence.\n\np: Guard us, Adityas, still alive, before the deadly weapon strike: Are yc not they who hear our call?\n\np: What sheltering defence ye have for him who toils in pouring gifts, Graciously bless ye us therewith.\n\np: Adityas, Devas, from sorrow there is freedom; for the sinless, wealth, O ye in whom no fault is seen.\n\np: Let not this fetter bind us fast. May he release us for success; For strong is Indra and renowned.\n\np: O Devas who fain would lend your aid, destroy not us as ye destroy Your enemies who go astray.\n\np: And thee too, O Great Aditi, thee also, Deva, I address, thee very gracious to assist.\n\np: Save us in depth and shallow from the foe, thou Mother of Strong Sons Let no one of our seed be harmed.\n\np: Far-spread! wide-ruling! grant that we, unharmed by envy. May expand Grant that our progen. May live.\n\np: Those who, the Princes of the folk, in native glory, ne’er deceived, Maintain their statutes, void of guile—\n\np: As such, from mouth of ravening wolves, O ye Adityas, rescue uslike a bound thief, O Aditi.\n\np: Adityas, let this arrow, yea, let this malignity depart From us or e’er it strike us dead.\n\np: For, Bountiful Adityas, we have evermore enjoyed your help, Both now and in die days of old.\n\np: To every one, O ye Most Wise, who turneth even from sin to you, Ye Devas vouchsafe that h. May live.\n\np: May this new mercy profit us, which, ye Adityas, frees like one, Bound from his bonds, O Aditi.\n\np: O ye Adityas, this your might is not to be despised by us: So be ye graciously inclined.\n\np: Let not Vivasvan's weapon nor the shaft, Adityas, wrought with skill, Destroy us ere old age be nigh.\n\np: On every side dispel all sin, Adityas, all hostility, indigence, and combined attack.","people":["Indra","Mitra","Varuna","Vivasvan","Deva","Aditi","Aryaman"],"places":[],"things":["Glory","Wealth","Might","Help","Wise","Strong","Mighty","Praise","Offers","call","Gifts"],"groups":["Devas","Sons","Mother","Adityas"],"concepts":[],"hash":"md5-W3CY3MrCH8yLOn1qcYfhrA==","created":"Monday, April 8, 2024 - 10:51:54 PM"},{"id":"ebca7a61-143d-4ec8-a5f1-3eec26947160","key":"08057","book":"08","title":"HYMN LVII. Indra.","link":"https://indra.ai/rigveda/hymns/08057.html","text":"p: EVEN as a car to give us aid, we draw thee hither for our bliss, Strong in thy deeds, checking assault, Lord, Mightiest Indra, of the brave!\n\np: Great in thy power and wisdom, Strong, with thought that comprehendeth all Thou hast filled full with majesty.\n\np: Thou very Mighty One, whose hands by virtue of thy greatness grasp, the golden bolt that breaks its way.\n\np: Your Lord of might that ne’er hath bent, that ruleth over all mankind, I call, that he, as he is wont. May aid the chariots and the men.\n\np: Whom, ever furthering, in frays that win the light, in both the hosts Men call to assist and to help.\n\np: Indra, the Strong, the measureless, worthy of praise, most Bountiful, Sole Ruler even over wealth.\n\np: Him, for his ample bounty, him, this Indra do I urge to drink, who, as his praise was sung of old, the Dancer, is the Lord of men.\n\np: Thou Mighty One, whose friendship none of mortals ever hath obtained None will attain unto thy might.\n\np: Aided by thee, with thee allied, in frays for water and for sun, Bolt-armed. May we win ample spoil.\n\np: So seek we thee with offering and songs, chief Lover of the Song, As, in our battles Indra, thou to Purumayya gavest help.\n\np: O Thunderer, thou whose friendship and whose onward guidance both are sweet, Thy offering must be prepared.\n\np: To us, ourselves, give ample room, give for our dwelling ample room Give ample room to us to live.\n\np: We count the banquet of the Devas a spacious pathway for the men, and for the cattle, and the car.\n\np: Six men, yea, two and two, made glad with Soma juice, come near to me With offerings pleasant to the taste.\n\np: Two brown-hued steeds, indrota's gift, two bays from Rksa's son were mine, From Asvamedha's son two red.\n\np: From Atithigva good car-steeds; from Arksa rein-obeying steeds, From Asvamedha beauteous ones.\n\np: Indrota, Atithigva's son, gave me six horses matched with mares And Patakratu gave besides.\n\np: Marked above all, amid the brown, is the red mare Vrsanvati, Obedient to the rein and whip.\n\np: O bound to me by deeds of might, not even the man who loves to blame. Hath found a single fault in you.","people":["Indra","Soma","Atithigva"],"places":[],"things":["Mankind","Steeds","Lord","Soma","Water","Chariots","Offering","Light","Sun","Wealth","Men","Might","Juice","Song","Help","Strong","Mighty","Car","Banquet","Chief","Praise","Brave","Gift","Offerings","Bliss","Songs","Horses","call","spoil","Cattle"],"groups":["Devas","Son","Man"],"concepts":["Good","Friendship","Wisdom","Offering","Offerings"],"hash":"md5-IhIITI1GA7/lnubViy+MIg==","created":"Monday, April 8, 2024 - 10:51:54 PM"},{"id":"b9e9fba3-1241-4264-a766-79591c4b7652","key":"08058","book":"08","title":"HYMN LVIII. Indra.","link":"https://indra.ai/rigveda/hymns/08058.html","text":"p: I SEND you forth the song of praise for Indu, hero-gladdener. With hymn and plenty he invites you to complete  'the offering.\n\np: Thou wishest for thy kine a bull, for those who long for his approach, for those who turn away from him, lord of thy cows whom non. May kill.\n\np: The dappled kine who stream with milk prepare his draught of Soma juice: Clans in the birth-place of the Devas, in the three luminous realms of heaven.\n\np: Praise, even as he is known, with song Indra the guardian of the kine, the Son of Truth, Lord of the brave.\n\np: Hither his Bay Steeds have been sent, red Steeds are on the sacred grass, Where we in concert sing our songs.\n\np: For Indra Thunder-armed the kine have yielded mingled milk and meath, what time he found them in the vault.\n\np: When I and Indra mount on high up to the Bright One's place and home, We, having drunk of meath, will reach his seat whose Friends are three times seven.\n\np: Sing, sing ye forth your songs of praise, ye Briyamedhas, sing your songs: Yea, let young children sing their lauds as a strong castle praise ye him.\n\np: Now loudly let the viol sound, the lute send out its voice with might, Shrill be, the music of the string. To Indra. is the hymn up-raised.\n\np: When hither speed the dappled cows, unflinching, easy to be milked, Seize quickly, as it bursts away, the Soma juice for Indra's drink.\n\np: Indra hath drunk, Agni hath drunk. all Deities have drunk their fill. Here Varuna shall have his home, to whom the floods have sung aloud as mother-kine unto their calves.\n\np: Thou, Varuna, to whom belong Seven Rivers, art a glorious Deva. The waters flow into thy throat as ’twere a pipe with ample mouth.\n\np: He who hath made the fleet steeds spring, well-harnessed, to the worshipper. He, the swift Guide, is that fair form that loosed the horses near at hand.\n\np: Indra, the very Mighty, holds his enemies in utter scorn. He, far away, and yet a child, cleft the cloud smitten by his voice.\n\np: He, yet a boy exceeding small, mounted his newly-fashioned car. He for his Mother and his Sire cooked the wild mighty buffalo.\n\np: Lord of the home, fair-helmeted, ascend thy chariot wrought of gold. We will attend the Heavenly One, the thousand-footed, red of hue, matchless, who blesses where he goes.\n\np: With reverence they come hitherward to him as to. a Sovran lord, that the, may bring him near for this man's good success, to prosper and bestow his gifts.\n\np: The Priyamedhas have observed the offering of the men of old, Of ancient custom, while they strewed the sacred grass, and spread their sacred food.","people":["Indu","Indra","Soma","Agni","Varuna","Deva"],"places":["Heaven"],"things":["Meath","Milk","Steeds","Lord","Rivers","Reverence","Soma","Waters","Glorious","Offering","Food","Men","Stream","Flow","Might","Juice","Song","Gold","Home","Strong","Mighty","Grass","Car","Praise","Voice","Brave","Worshipper","Hymn","Form","Ascend","Friends","Songs","Hero","Horses","Gifts"],"groups":["Devas","Deities","Mother","Son","Child","Man"],"concepts":["Good","Birth","Heavenly","Sacred","Offering","Truth","Glorious","Swift"],"hash":"md5-7wHw8wYaSzGRpyS5xpiQgg==","created":"Monday, April 8, 2024 - 10:51:54 PM"},{"id":"abd83e56-6e95-4628-91f0-ef9f1c58b560","key":"08059","book":"08","title":"HYMN LIX. Indra.","link":"https://indra.ai/rigveda/hymns/08059.html","text":"p: HE who, as Sovran Lord of men, moves with his chariots unrestrained, the Vrtra conquerer vanquisher, of fighting hosts, preeminent, is praised with song.\n\np: Honour that Indra, puruhanman! for his aid, in whose sustaining hand of old, the splendid bolt of thunder was deposited, as the great Sun was set in heaven.\n\np: No one by deed attains to him who works and strengthens evermore: No, not by offering, to Indra. praised o all, resistless, daring, bold in might.\n\np: The potent Conqueror, invincible in war, him at whose birth the MightyOnes, the Kine who spread afar, sent their loud voices out, heavens, earths seat their loud voices out,\n\np: O Indra, if a hundred heavens and if a hundred earths were thine— No, not a thousand Suns could match thee at thy birth, not both the worlds, O Thunderer.\n\np: Thou. Hero, hast performed thy hero deeds with might, yea, all with strength, O Strongest One. Maghavan, help us to a stable full of kine, O Thunderer, with wondrous aids.\n\np: Let not a godless mortal gain this food, O thou whose life is long! But one who yokes the bright-hued steeds, the Etasas, even Indra yoker of the Bays.\n\np: Urge ye the Conqueror to give, your Indra greatly to be praised, to be invoked in shallow waters and in depths, to be invoked in deeds of might.\n\np: O Vasu, O thou Hero, raise us up to ample opulence. Raise us to gain of mighty wealth O Indra, to sublime renown.\n\np: Indra, thou justifiest us, and tramplest down thy slanderers. Guard thyself, valiant Hero, in thy vital parts: strike down the Dasa with thy blows.\n\np: The man who brings no offering, inhuman, godless, infidelhim let his friend the mountain cast to rapid death, the mountain cast the Dasyu down.\n\np: O Mightiest Indra, loving us, gather thou up, as grains of corn, within thine hand, of these their kine, to give away, yea, gather twice as loving us.\n\np: O my companions, wish for power. Ho. May we perfect Sara's praise, the liberal princely patron, never to be harmed?\n\np: By many a sage whose grass is trimmed thou art continually praised, that thou, O Sara, hast bestowed here one and here another calf.\n\np: The noble, Suradeva's son, hath brought a calf, led by the car to three of us. As a chief brings a goat to milk.","people":["Indra","Vrtra","Maghavan","Vasu"],"places":["Heaven"],"things":["Milk","Steeds","Lord","Waters","Chariots","Offering","Sun","Wealth","Food","Men","Might","Song","Help","Mighty","Grass","Car","Chief","Praise","Friend","Hero","Sage","Life","Death"],"groups":["Dasyu","Son","MightyOnes","Man"],"concepts":["Birth","Death","Life","Strength","Offering","Noble"],"hash":"md5-jGh+TjPdRp5o90Hgh99Few==","created":"Monday, April 8, 2024 - 10:51:54 PM"},{"id":"140d0c3f-606c-48b5-9bec-d26af5ba58e3","key":"08060","book":"08","title":"HYMN LX. Agni.","link":"https://indra.ai/rigveda/hymns/08060.html","text":"p: O AGNI, with thy mighty wealth guard us from all malignity, Yea, from all hate of mortal man.\n\np: For over thee, O Friend from birth, the wrath of man hath no control: Nay, Guardian of the earth art thou.\n\np: As such, with all the Devas, O Son of Strength, auspicious in thy flame. Give us wealth bringing all things good.\n\np: Malignities stay not from wealth the mortal man whom, Agni, thou Protectest while he offers gifts.\n\np: Sage Agni, be whom thou dost urge, in worship of the Devas, to wealth, with thine assistance winneth kine.\n\np: Riches with many heroes thou hast for the man who offers gifts: Lead thou us on to higher bliss.\n\np: Save us, O Jatavedas, nor abandon us to him who sins, Unto the evil-hearted man.\n\np: O Agni, let no godless man avert thy bounty as a Deva. Over all treasure.s thou art Lord.\n\np: So, Son of Strength, thou aidest us to what is great and excellent. Those, Vasu! Friend! who sing thy praise.\n\np: Let our songs come anear to him beauteous and bright with piercing flame Our offerings, with our homage, to the Lord of wealth, to him whom many praise, for help:\n\np: To Agni Jatavedas, to the Son of Strength, that h. May give us precious gifts, Immortal, from of old Monk among mortal men, the most delightful in the house.\n\np: Agni, made yours by offering, Agni, while holy rites advance; Agni, the first in songs, first with the warrior steed; Agni to win the land for us.\n\np: May Agni who is Lord of wealth vouchsafe us food for friendship sake. Agni we ever seek for seed and progeny, the Vasu who protects our lives.\n\np: Solicit with your chants, for help, Agni the Deva with piercing flame, for riches famous Agni, purumilha and ye men! Agni to light our dwelling well.\n\np: Agni we laud that h. May keep our foes afar, Agni to give us health and strength. Let him as Guardian be invoked in all the tribes, the lighter-up of glowing brands.","people":["Agni","Deva","Vasu"],"places":["Earth"],"things":["Worship","Lord","Offering","Light","Treasure","Wealth","Food","Men","Help","Mighty","Praise","Heroes","Offers","Excellent","Offerings","Bliss","Songs","Warrior","Friend","Sage","Riches","Gifts"],"groups":["Devas","Jatavedas","Son","Immortal","Progeny","Man"],"concepts":["Good","Evil","Birth","Friendship","Immortal","Holy","Strength","Offering","Offerings","Auspicious"],"hash":"md5-5IIQURZ3UDtK7yV1zD5i7A==","created":"Monday, April 8, 2024 - 10:51:54 PM"},{"id":"9c4fc07d-431d-48e4-93a0-e4470c4451f7","key":"08061","book":"08","title":"HYMN LXI. Agni.","link":"https://indra.ai/rigveda/hymns/08061.html","text":"p: PREPARE oblation: let him come; and let the minister serve again Who knows the ordering thereof,\n\np: Rejoicing in his friendship, let the Sage be seated over man, beside the shoot of active power.\n\np: Him, glowing bright beyond all thought, they seek among the race of man; With him for tongue they seize the food.\n\np: He hath inflamed the twofold plain: life-giving, he hath climbed the wood, and with his tongue hath struck the rock.\n\np: Wandering here the radiant Calf finds none to fetter him, and seeks The Mother to declare his praise.\n\np: And now that great and mighty team, the team of horses that are his, and traces of his car, are seen.\n\np: The seven milk a single cow; the two set other five to work, On the stream's loud-resounding bank.\n\np: Entreated by Vivasvan's ten, indra cast down the water-jar With threefold hammer from the sky.\n\np: Three times the newly-kindled flame proceeds around  'the offering: The Monks anoint it with the meath.\n\np: With reverence they drain the fount that circles with its wheel above, Exhaustless, with the mouth below.\n\np: The pressing-stones are set at work: the meath is poured into the tank, At the out-shedding of the fount.\n\np: Ye cows, protect the fount: the two MightyOnes bless  'the offering. The handles twain are wrought of gold.\n\np: Pour on the juice the ornament which reaches both the heaven and earth Supply the liquid to the Bull.\n\np: These know their own abiding-place: like calves beside the mother cows They meet together with their kin.\n\np: Devouring in their greedy jaws, they make sustaining food in heaven, to Indra, Agni light and prayer.\n\np: The Pious One milked out rich food, sustenance dealt in portions seven, together with the Sun's seven rays.\n\np: I took some Soma when the Sun rose up, O Mitra, Varuna. That is the sick man's medicine.\n\np: From where oblations must be laid, which is the Well-beloved's home. He with his tongue hath compassed heaven.","people":["Indra","Soma","Agni","Mitra","Varuna","Vivasvan"],"places":["Earth","Heaven","Sky"],"things":["Meath","Milk","Work","Reverence","Soma","Water","Offering","Light","Sun","Food","Stream","Juice","Gold","Home","Mighty","Car","Praise","Pressing-Stones","Sage","Cow","Horses","Life","Wheel"],"groups":["Mother","MightyOnes","Man","Monks"],"concepts":["Life","Friendship","Offering"],"hash":"md5-RfHXFIZNS6LK6PgR0gum5Q==","created":"Monday, April 8, 2024 - 10:51:54 PM"},{"id":"9e14a307-ed16-41d7-a3c4-2167d8c1eb81","key":"08062","book":"08","title":"HYMN LXII. Asvins.","link":"https://indra.ai/rigveda/hymns/08062.html","text":"p: ROUSE ye for him who keeps the Law, yoke your steeds, Asvins, to your car Let your protecting help be near.\n\np: Come, Asvins, with your car more swift than is the twinkling of an eye Let your protecting help be near.\n\np: Asvins, ye overlaid with cold the fiery pit for Atri's sake: Let your protecting help be near.\n\np: Where are ye? whither are ye gone? whither, like falcons, have ye flown? Let your protecting help be near.\n\np: If ye at any time this day are listening to this my call, Let your protecting help be near.\n\np: The Asvins, first to hear our meditation, for closest kinship I approach: Let your protecting help be near.\n\np: For Atri ye, O Asvins, made a dwelling-place to shield him well, Let your protecting help be near.\n\np: Ye warded off the fervent heat for Atri when he sweetly spake: Let your protecting help be near.\n\np: Erst Saptavadhri by his prayer obtained the trenchant edge of fire: Let your protecting help be near.\n\np: Come hither, O ye Lords of wealth, and listen to this call of mine: Let your protecting help be near.\n\np: What is this praise told forth of you as Elders in the ancient way? Let your protecting help be near.\n\np: One common brotherhood is yours, Asvins your kindred is the same: Let your protecting help be near.\n\np: This is your chariot, Asvins, which speeds through the regions, earth and heaven Let your protecting aid be near.\n\np: Approach ye hitherward to us with thousands both of steeds and kine: Let your protecting help be near.\n\np: Pass us not by, remember us with thousands both of kine and steeds: Let your protecting help be near.\n\np: The purple-tinted Dawn hath risen, and true to Law hath made the light Let your protecting help be near.\n\np: He looked upon the Asvins, as an axe-armed man upon a tree: Let your protecting help be near.\n\np: By the black band encompassed round, break it down, bold one, like a fort. Let your protecting help be near.","people":["Asvins","Atri","Dawn"],"places":["Earth","Heaven"],"things":["Steeds","Meditation","Light","Wealth","Help","Car","Praise","call"],"groups":["Brotherhood","Man"],"concepts":["Swift"],"hash":"md5-EVCBWJk+n4lwTuDFYJ2S+w==","created":"Monday, April 8, 2024 - 10:51:55 PM"},{"id":"8afd3502-ef3f-430b-a3cc-3e78d625c7a3","key":"08063","book":"08","title":"HYMN LXIII. Agni.","link":"https://indra.ai/rigveda/hymns/08063.html","text":"p: EXERTING all our strength with thoughts of power we glorify in speech Agni your dear familiar Friend, the darling Guest in every home.\n\np: Whom, served with offerings oil like Mitra, men presenting gifts Eulogize with their songs of praise\n\np: Much-lauded Jatavedas, him who bears oblations up to heaven Prepared in service of the Devas.\n\np: To noblest Agni, Friend of man, best Vrtra conquerer, are we comehim in whose presence Rksa's son, mighty Srutarvan, waxes great;\n\np: To deathless Jatavedas, meet for praise, adored, with sacred oil, Visible through the gloom of night\n\np: Even Agni whom these priestly men worship with offerings gifts, with lifted ladles offering them.\n\np: O Agni, this our newest hymn hath been addressed from us to thee, O cheerful Guest, well-born, most wise, worker of wonders, ne’er deceived.\n\np: Agni. May it be dear to thee, most grateful, and exceeding sweet: Grow mightier, eulogized therewith.\n\np: Splendid with splendour. May it be, and in the battle with the foe Add loftier glory to thy fame.\n\np: Steed, cow, a lord of heroes, bright like Indra, who shall fill the car. Whose high renown ye celebrate, and people praise each glorious deed.\n\np: Thou whom Gopavana made glad with song, O Agni Angiras. Hear this my call, thou Holy One.\n\np: Thou whom the priestly folk implore to aid the gathering of the spoil, Such be thou in the fight with foes.\n\np: I, called to him who reels with joy, Srutarvan, Rksa's son, shall stroke The heads of four presented steeds, like the long wool of fleecy rams.\n\np: Four coursers with a splendid car, Savistha's horses, fleet of foot, Shall bring me to the sacred feast, as flying steeds brought Tugra's son.\n\np: The very truth do I declare to thee, parusni, mighty flood. Waters! no man is there who gives more horses than Savistha gives.","people":["Indra","Vrtra","Agni","Angiras","Mitra","Tugra"],"places":["Heaven"],"things":["Worship","Steeds","Lord","Born","Waters","Glory","Glorious","Offering","Men","Song","Joy","Home","Wise","Mighty","Car","Praise","Hymn","Heroes","Splendour","People","Offerings","Songs","Friend","Cow","Horses","call","spoil","Gifts"],"groups":["Devas","Jatavedas","Son","Man"],"concepts":["Splendid Car","Holy","Sacred","Strength","Offering","Offerings","Truth","Glorious","Speech"],"hash":"md5-ZSJnxxa3W7dqw5rTrMuNsQ==","created":"Monday, April 8, 2024 - 10:51:55 PM"},{"id":"6417c799-6070-43fd-95c8-cd3f1c02bb7a","key":"08064","book":"08","title":"HYMN LXIV. Agni.","link":"https://indra.ai/rigveda/hymns/08064.html","text":"p: YOKE, Agni, as a charioteer, thy steeds who best invite the Devas: As ancient Herald seat thyself.\n\np: And, Deva, as skilfullest of all, call for us hitherward the Devas: Give all our wishes sure effect.\n\np: For thou, most Youthful, Son of Strength, thou to whom offering is paid, Art holy, faithful to the Law.\n\np: This Agni, Lord of wealth and spoil hundredfold, thousandfold, is head And chief of riches and a Sage.\n\np: As craftsmen bend the felly, so bend at our general call: come nigh, Angiras, to  'the offering.\n\np: Now, O Virupa, rouse for him, Strong Deva who shines at early morn, Fair praise with voice that ceases not.\n\np: With missile of this Agni, his who looks afar, will we lay low The thief in combat for the kine.\n\np: Let not the Companies of Devas fail us, like Dawns that float awaylike cows who leave the niggardly.\n\np: Let not the sinful tyranny of any fiercely hating foe Smite us, as billows smite a ship.\n\np: O Agni, Deva, the people sing reverent praise to thee for strength: With terrors trouble thou the foe.\n\np: Wilt thou not, Agni, lend us aid in winning cattle, winning wealth? Maker of room, make room for us.\n\np: In this great battle cast us not aside as one who bears a load: Snatch up the wealth and win it all.\n\np: O Agni, let this plague pursue and fright another and not us: Make our impetuous strength more strong.\n\np: The reverent or unwearied man whose holy labour he acceptshim Agni favours with success.\n\np: Abandoning the foeman's host pass hither to this company: Assist the men with whom I stand.\n\np: As we have known thy gracious help, as of a Father, long ago, So now we pray to thee for bliss.","people":["Agni","Angiras","Virupa","Deva"],"places":[],"things":["Steeds","Lord","Offering","Wealth","Men","Help","Strong","Chief","Praise","Voice","People","Bliss","Sage","Winning","call","spoil","Riches","Cattle"],"groups":["Devas","Dawns","Father","Son","Man"],"concepts":["Holy","Strength","Offering"],"hash":"md5-1Th4+SscBH245Ph+NW/7dw==","created":"Monday, April 8, 2024 - 10:51:55 PM"},{"id":"72e3af37-411c-49e3-a3a4-5ae5df04d539","key":"08065","book":"08","title":"HYMN LXV. Indra.","link":"https://indra.ai/rigveda/hymns/08065.html","text":"p: NOT to forsake me, I invoke this Indra girt by Maruts, Lord Of magic power who rules with might.\n\np: This Indra with his Marut Friends clave into pieces Vrtra's bead With hundred-knotted thunderbolt.\n\np: Indra, with Marut Friends grown strong, hath rent asunder Vrtra, and Released the waters of the sea.\n\np: This is that Indra who, begirt by Maruts, won the light of heaven That he might drink the Soma juice.\n\np: Mighty, impetuous, begirt by Maruts, him who loudly roars, indra we invocate with songs.\n\np: Indra begirt by Maruts we invoke after the ancient plan, that h. May drink the Soma juice.\n\np: O liberal Indra, Marut-girt, much-lauded Satakratu, drink The Soma at this offering.\n\np: To thee, O Indra, Marut-girt, these Soma juices, Thunderer! Are offered from the heart with lauds.\n\np: Drink, indra, with thy Marut Friends, pressed Soma at the morning rites, Whetting thy thunderbolt with strength.\n\np: Arising in thy might, thy jaws thou shookest, indra, having quaffed The Soma which the mortar pressed.\n\np: Indra, both worlds complained to thee when uttering thy fearful roar, what time thou smotest Dasyus dead.\n\np: From Indra have I measured out a son eight-footed with nine parts, Delicate, faithful. to the Law.","people":["Indra","Soma","Vrtra","Satakratu"],"places":["Heaven"],"things":["Lord","Soma","Waters","Offering","Light","Might","Juice","Strong","Mighty","Friends","Songs","Morning"],"groups":["Dasyus","Maruts","Marut","Son"],"concepts":["Strength","Offering"],"hash":"md5-7zP4u1pk07CvtavsIF7LhQ==","created":"Monday, April 8, 2024 - 10:51:55 PM"},{"id":"9bf2fb8a-bbb3-43df-bc97-ebcb03053017","key":"08066","book":"08","title":"HYMN LXVI. Indra.","link":"https://indra.ai/rigveda/hymns/08066.html","text":"p: SCARCELY was Satakratu, born when of his Mother he inquired, who are the mighty? Who are famed?\n\np:  Then Savasi declared to him Aurnavabha, Ahisuva: Son, these be they thou must o’erthrow\n\np: The Vrtra conquerer smote them all as spokes are hammered into naves: The Dasyu-killer waxed in might.\n\np: Then Indra at a single draught drank the contents of thirty pails, pails that were filled with Soma juice.\n\np: Indra in groundless realms of space pierced the Gandharva through, that he Might make Brahmans' strength increase.\n\np: Down from the mountains Indra shot hither his well-directed shaft: He gained the ready brew of rice.\n\np: One only is that shaft of thine, with thousand feathers, hundred barbs, Which, indra, thou hast made thy friend.\n\np: Strong as the Rbhus at thy birth, therewith to those who praise thee, men, and women, bring thou food to eat.\n\np: By thee these exploits were achieved, the mightiest deeds, abundantly: Firm in thy heart thou settest them.\n\np: All these things Visnu brought, the Lord of ample stride whom thou hadst sent- A hundred buffaloes, a brew of rice and milk: and Indra, slew the ravening boar\n\np: Most deadly is thy bow, successful, fashioned well: good is thine arrow, decked with gold. Warlike and well equipped thine arms are, which increase sweetness for him who drinks the sweet.","people":["Indra","Soma","Vrtra","Visnu","Satakratu"],"places":[],"things":["Milk","Lord","Born","Mountains","Soma","Food","Men","Might","Juice","Gold","Strong","Mighty","Praise","Friend"],"groups":["Dasyu","Brahmans","Gandharva","Mother","Son","Rbhus"],"concepts":["Good","Birth","Strength"],"hash":"md5-NnVygmdcbZasaBZ0cQjiTA==","created":"Monday, April 8, 2024 - 10:51:55 PM"},{"id":"3f00344e-1298-4e78-b776-d2a0318077df","key":"08067","book":"08","title":"HYMN LXVII. Indra.","link":"https://indra.ai/rigveda/hymns/08067.html","text":"p: BRING us a thousand, indra, as our guerdon for the Soma juice: Hundreds of kine, O Hero, bring.\n\np: Bring cattle, bring us ornament, bring us embellishment and steeds, Give us, besides, two rings of gold.\n\np: And, Bold One, bring in ample store rich jewels to adorn the ear, for thou, Good Lord, art far renowned.\n\np: None other is there for the priest. Hero! but thou, to give him gifts, to win much spoil and prosper him.\n\np: Indra can never be brought low, Sakra can never be subdued: He heareth and beholdeth all.\n\np: He spieth out the wrath of man, he who can never be deceived: Ere blame can come he marketh it.\n\np: He hath his stomach full of might, the Vrtra conquerer, Conqueror, Soma, ordering all.\n\np: In thee all treasure.s are combined, Soma all blessed things in thee, Uninjured, easy to bestow.\n\np: To thee speeds forth my hope that craves the gift of corn, and kine and gold, Yea, craving horses, speeds to thee.\n\np: Indra, through hope in thee alon even this sickle do I grasp. Fill my hand, Maghavan, with all that it can hold of barley cut or gathered up.","people":["Indra","Soma","Vrtra","Sakra","Maghavan"],"places":[],"things":["Steeds","Lord","Soma","Treasure","Might","Juice","Gold","Gift","Hero","Horses","spoil","Cattle","Gifts"],"groups":["Man"],"concepts":["Good"],"hash":"md5-Lt68XbHpkkEnNKXtQAkY/A==","created":"Monday, April 8, 2024 - 10:51:55 PM"},{"id":"789c02cf-6d96-4b6f-88cc-75d6ba31a536","key":"08068","book":"08","title":"HYMN LXVIII. Soma.","link":"https://indra.ai/rigveda/hymns/08068.html","text":"p: THIS here is Soma, ne’er restrained, active, all-conquering bursting forth, Rsi and Sage by sapience,\n\np: All that is bare he covers o’er, all that is sick he medicines; The blind man sees, the cripple walks.\n\np: Thou, Soma, givest wide defence against the hate of alien men, Hatreds that waste and weaken us.\n\np: Thou by thine insight and thy skill, Impetuous One, from heaven and earth Drivest the sinner's enmity.\n\np: When to their task they come with zeal. May they obtain the Giver's grace, and satisfy his wish who thirsts.\n\np: May he find what erst was lost, s. May be speed the pious man, and lengthen his remaining life.\n\np: Gracious, displaying tender love, unconquered, gentle in thy thoughts, be sweet, O Soma, to our heart.\n\np: O Soma, terrify us not; strike us not with alarm, O King: Wound not our heart with dazzling flame.\n\np: When in my dwelling-place I see the wicked enemies of Devas, King, chase their hatred far away, thou Bounteous One, dispel our foes.","people":["Soma"],"places":["Earth","Heaven"],"things":["Soma","Men","King","Sage","Life"],"groups":["Devas","Man"],"concepts":["Life","Love","Giver"],"hash":"md5-DvdNG20ztZ5gAePoMp8nng==","created":"Monday, April 8, 2024 - 10:51:55 PM"},{"id":"84fb87bc-f894-43c9-88da-bd4d4f01b752","key":"08069","book":"08","title":"HYMN LXIX. Indra","link":"https://indra.ai/rigveda/hymns/08069.html","text":"p: O Sarakratu! truely I have made non else my Comforter. Indra; be gracious unto us.\n\np: Thou who hast ever aided us kindly of old to win the spoil, as such, O Indra, favour us.\n\np: What now? As prompter of the poor thou helpest him who sheds the juice. Wilt thou not, indra, strengthen us?\n\np: O Indra, help our chariot on, yea, Thunderer, though it lag behind: Give this my car the foremost place.\n\np: Ho there! why sittest thou at case? Make thou my chariot to be first And bring the fame of victory near.\n\np: Assist our car that seeks the prize. What can be easier for thee? So make thou us victorious.\n\np: Indra, be firm: a fort art thou. To thine appointed place proceeds The auspicious hymn in season due.\n\np: Let not our portion be disgrace. Broad is the course, the prize is set, the barriers are opened wide.\n\np: This thing we wish. that tho. Mayst take thy fourth, thy offerings name. So art thou held to be our Lord.\n\np: Ekadyu hath exalted you, Immortals: both Devas and Devas hath he delighted. Bestow upon him bounty meet for praises. May he, enriched with meditation, come soon and early.","people":["Indra"],"places":[],"things":["Victory","Lord","Meditation","Juice","Help","Car","Hymn","Offerings","spoil"],"groups":["Devas"],"concepts":["Offerings","Auspicious"],"hash":"md5-Ya3lFTztewJ2orXJ3sx2CA==","created":"Monday, April 8, 2024 - 10:51:55 PM"},{"id":"e0baaa83-a904-4f33-93da-48890fe7f0e4","key":"08070","book":"08","title":"HYMN LXX. Indra.","link":"https://indra.ai/rigveda/hymns/08070.html","text":"p: INDRA, Deva.of the mighty arm, gather for us with thy right hand Manifold and nutritious spoil.\n\np: We know thee mighty in thy deeds, of mighty bounty, mighty wealth, Mighty in measure, prompt to aid.\n\np: Hero, when thou art fain to give, neithe, may Devas nor mortal men Restrain thee like a fearful Bull.\n\np: Come, let us glorify Indra, Lord supreme of wealth, Self-ruling King: In bount. May he harm us not.\n\np: Let prelude sound and following chant so let him hear the Saman sung, and with his bounty answer us.\n\np: O Indra, with thy right hand bring, and with thy left remember us. Let us not lose our share of wealth.\n\np: Come nigh, O Bold One, boldly bring hither the riches of the churl Who giveth least of all the folk.\n\np: Indra, the booty which thou hast with holy singers to receive, Even that booty win with us.\n\np: Indra, thy swiftly-coming spoil, the booty which rejoices all, Sounds quick in concert with our hopes.","people":["Indra","Deva"],"places":[],"things":["Lord","Wealth","Men","Mighty","Hero","King","spoil","Riches"],"groups":["Devas"],"concepts":["Holy"],"hash":"md5-bJsMVH39oexqwhT9wqcyqg==","created":"Monday, April 8, 2024 - 10:51:55 PM"},{"id":"2b348076-7a02-4c3f-93f9-0e974ca55e69","key":"08071","book":"08","title":"HYMN LXXI. Indra.","link":"https://indra.ai/rigveda/hymns/08071.html","text":"p: HASTE forward to us from afar, or, Vrtra conquerer, from anear, to meet the offering to the meath.\n\np: Strong are the Soma-draughts; come nigh: the juices fill thee with delight: Drink boldly even as thou art wont'.\n\np: Joy, indra, in the strengthening food et it content thy wish and thought, and be delightful to thine heart.\n\np: Come to us thou who hast no foe: we call thee down to hymns of praise, in heaven's sublimest realm of light.\n\np: This Soma here expressed with stones and dressed with milk for thy carouse, indra, is offered up to thee.\n\np: Graciously, indra, hear my call. Come and obtain the draught, and sate Thyself with juices blent with milk.\n\np: The Soma, indra, which is shed in chalices and vats for thee, Drink thou, for thou art Lord thereof.\n\np: The Soma seen within the vats, as in the flood the Moon is seen, Drink thou, for thou art Lord thereof.\n\np: That which the Hawk brought in his claw, inviolate, through the air to thee, Drink thou, for thou art Lord thereof.","people":["Indra","Soma","Vrtra"],"places":["Heaven"],"things":["Meath","Milk","Lord","Soma","Offering","Light","Air","Moon","Food","Joy","Strong","Praise","Delight","call"],"groups":[],"concepts":["Offering"],"hash":"md5-eko/EbDMOmLg8khUrRLSig==","created":"Monday, April 8, 2024 - 10:51:55 PM"},{"id":"dfe48808-0bd7-4e9a-a68b-f69008b9e78c","key":"08072","book":"08","title":"HYMN LXXII, Devas.","link":"https://indra.ai/rigveda/hymns/08072.html","text":"p: WE choose unto ourselves that high protection of the Mighty Devas That i. May help and assist us.\n\np: May they be ever our allies, Varuna, Mitra, Aryaman, Far-seeing Devas who prosper us.\n\np: Ye furtherers of holy Law, transport us safe o’er many woes, as over water-floods in ships.\n\np: Dear wealth be Aryaman to us, Varuna dear wealth meet for praise: Dear wealth we choose unto ourselves.\n\np: For Sovrans of dear wealth are ye, Adityas, not of sinner's wealth, Ye sapient Devas who subdue the foe.\n\np: We in our homes, ye Bounteous Ones, and while we journey on the road, invoke you, Devas, to prosper us.\n\np: Regard us, indra, Visnu, here, ye Asvins and the Marut host, Us who are kith and kin to you.\n\np: Ye Bounteous Ones, from time of old we here set forth our brotherhood, Our kinship in. the Mother's womb.\n\np: Then come with Indra for your chief, as early day, ye Bounteous Devas Yea, 1 address you now for this.","people":["Indra","Visnu","Mitra","Varuna","Asvins","Aryaman"],"places":[],"things":["Journey","Water","Wealth","Help","Mighty","Chief","Praise"],"groups":["Devas","Marut","Mother","Brotherhood","Adityas"],"concepts":["Holy"],"hash":"md5-jL9PbNS5kWxz/jbZHDqoHg==","created":"Monday, April 8, 2024 - 10:51:55 PM"},{"id":"021e0c9d-bbd3-413c-bd6c-7a7e106b3868","key":"08073","book":"08","title":"HYMN LXXIII. Agni.","link":"https://indra.ai/rigveda/hymns/08073.html","text":"p: AGNI, your dearest Guest, I laud, him who is loving as a friend, who brings us riches like a car.\n\np: Whom as a far-foreseeing Sage the Devas have, from the olden time, Established among mortal men.\n\np: Do thou, most Youthful Deva, protect the men who offer, hear their songs, and of thyself preserve their seed.\n\np: What is the praise wherewith, O Deva, Angiras, Agni, Son of Strength, We, after thine own wish and thought,\n\np: May serve thee, O thou Child of Power, and with what offering's plan? What prayer shall I now speak to thee?\n\np: Our Deva, make all of us to dwell in happy habitations, and Reward our songs with spoil and wealth.\n\np: Lord of the house, what plenty fills the songs which thou inspirest now, Thou whose hymn helps to win the kine?\n\np: Hirn Wise and Strong they glorify, the foremost Champion in the fray, and mighty in his dwelling-place.\n\np: Agni, he dwells in rest and peace who smites and no one smites again: With hero sons he prospers well","people":["Agni","Angiras","Deva"],"places":[],"things":["Lord","Offering","Wealth","Men","Wise","Strong","Mighty","Car","Praise","Hymn","Songs","Friend","Hero","Sage","spoil","Riches"],"groups":["Devas","Sons","Son","Child"],"concepts":["Strength","Offering"],"hash":"md5-0j2W7AhMCB6Qgtk/L2sjaA==","created":"Monday, April 8, 2024 - 10:51:55 PM"},{"id":"2caf4dee-d0dd-4e27-a02a-d8735b827ad3","key":"08074","book":"08","title":"HYMN LXXIV. Asvins.","link":"https://indra.ai/rigveda/hymns/08074.html","text":"p: To this mine invocation, O ye Asvins, ye Nasatyas, come, to drink the savoury Soma juice.\n\np: This laud of mine, ye Asvins Twain, and this mine invitation hear, to drink the savoury Soma juice.\n\np: Here Krsna is invoking you, O Asvins, Lords of ample wealth. To drink the savoury Soma juice.\n\np: List. Heroes, to the singer's call, the call of Krsna lauding you, to drink the savoury Soma juice.\n\np: Chiefs, to the sage who sings your praise grant an inviolable home, to drink the savoury Soma juice.\n\np: Come to the worshipper's abode, Asvins, who here is lauding you, to drink the savoury Soma juice.\n\np: Yoke to the firmly jointed car the ass which draws you, Lords of wealth. To drink the savoury Soma juice.\n\np: Come hither, Asvins, on your car of triple form with triple seat, to drink the savoury Soma juice.\n\np: O Asvins, O Nasatyas, now accept with favouring grace my songs, to drink the savoury Soma juice.","people":["Soma","Asvins","Nasatyas"],"places":[],"things":["Soma","Singer","Wealth","Juice","Home","Car","Praise","Worshipper","Heroes","Form","Songs","Sage","call"],"groups":[],"concepts":[],"hash":"md5-UESogpbKlvf86KNsKnccLQ==","created":"Monday, April 8, 2024 - 10:51:55 PM"},{"id":"4d9d83e0-f5bc-4f76-8554-e2f031885768","key":"08075","book":"08","title":"HYMN LXXV. Asvins.","link":"https://indra.ai/rigveda/hymns/08075.html","text":"p: YE Twain are wondrous strong, well-skilled in arts that heal, both bringers of delight, ye both won Daksa's praise. Visvaka calls on you as such to save his life. Break ye not off our friendship, come and set me free.\n\np: How shall he praise you now who is distraught in mind? Ye Twain give wisdom for the gainof what is good. Visvaka calls on you as such to save his life. Break ye not off our friendship, come and set me free.\n\np: Already have ye Twain, possessors of great wealth, prospered Visnapu thus for gain of what is good. Visvaka calls on you as such to save his life. Break ye not off our friendship, come and set me free.\n\np: And that Impetuous Hero, winner of the spoil, though he is far away, we call to assist us, whose gracious favour, like a father's, is most sweet. Break ye not off our friendship, come and set me free.\n\np: About the holy Law toils Savitar the Deva.the horn of holy Law hath he spread far and wide. The holy Law hath quelled even mighty men of war. Break ye not off our ftiendship, come and act me free.","people":["Savitar","Deva","Daksa"],"places":[],"things":["Wealth","Men","Strong","Mighty","Praise","Delight","Hero","call","spoil","Life"],"groups":["Father"],"concepts":["Good","Life","Friendship","Holy","Wisdom","Winner"],"hash":"md5-kt9qfqmf7FXpwguR1rGCMQ==","created":"Monday, April 8, 2024 - 10:51:55 PM"},{"id":"3d7761d2-6956-4179-9e62-aaab2b2eba77","key":"08076","book":"08","title":"HYMN LXXVI. Asvins.","link":"https://indra.ai/rigveda/hymns/08076.html","text":"p: SPLENDID, O Asvins, is your praise. Come fountain-like, to pour the stream. Of the sweet juice effused-dear is it, Chiefs, in heaven-drink like two wild bulls at a pool.\n\np: Drink the libation rich in sweets, O Asvins Twain: sit. Heroes, on the sacred grass. Do ye with joyful heart in the abode of man preserve his life by means of wealth.\n\np: The Priyamedhas bid you come with all the assists that are yours. Come to his house whose holy grass is trimmed, to dear offering at the morning rites.\n\np: Drink ye the Soma rich in meath, ye Asvins Twain: sit gladly on the sacred grass. So, waxen mighty, to our eulogy from heaven come ye as wild-bulls to the pool.\n\np: Come to us, O ye Asvins, now with steeds of many a varied hue, Ye Lords of splendour, wondrous, borne on paths of gold, drink Soma, ye who strengthen Law.\n\np: For we the priestly singers, fain tohymn your praise, invoke you for the gain of strength. So, wondrous, fair, and famed for great deeds come to us, through our hymn, Asvins, when ye hear.","people":["Soma","Asvins"],"places":["Heaven"],"things":["Meath","Steeds","Soma","Offering","Wealth","Stream","Juice","Gold","Mighty","Grass","Praise","Hymn","Heroes","Splendour","Morning","Life"],"groups":["Man"],"concepts":["Life","Holy","Sacred","Strength","Offering"],"hash":"md5-C+uDO5TuWVS0p4aqBxx6rg==","created":"Monday, April 8, 2024 - 10:51:55 PM"},{"id":"8f0a369a-83eb-457c-b81f-d191c5e65c44","key":"08077","book":"08","title":"HYMN LXXVII. Indra.","link":"https://indra.ai/rigveda/hymns/08077.html","text":"p: As cows low to their calves in stalls, so with our songs we glorify This Indra, even your Wondrous Deva who checks attack, who joys in the delicious juice.\n\np: Celestial, bounteous Giver, girt about with might, rich, mountain-like, in precious thingshim swift we seek. for foodful booty rich in kine, brought hundredfold and thousandfold.\n\np: Indra, the strong and lofty hills are powerless to bar thy way. None stay that act of thine when thou wouldst fain give wealth to one like me who sings thy praise.\n\np: A Warrior thou by strength, wisdom, and wondrous deed, in might excellest all that is. Hithe, may this our hymn attract thee to our help, the hymn which Gotamas have made.\n\np: For in thy might thou stretchest out beyond the boundaries of heaven. The earthly region, indra, comprehends thee not. After thy Deva.ead hast thou waxed.\n\np: When, Maghavan, thou honourest the worshipper, no one is there to stay thy wealth. Most liberal Giver thou, do thou inspire our song of praise, that we may win the spoil.","people":["Indra","Maghavan","Deva"],"places":["Heaven"],"things":["Wealth","Might","Juice","Song","Help","Strong","Praise","Worshipper","Hymn","Songs","Warrior","spoil"],"groups":["Gotamas"],"concepts":["Celestial","Strength","Wisdom","Giver","Swift"],"hash":"md5-06m0RXo9x1l8tN1NlF1GIw==","created":"Monday, April 8, 2024 - 10:51:55 PM"},{"id":"9e756c1a-def7-4799-ae4c-31bf7fec2180","key":"08078","book":"08","title":"HYMN LXXVIII. Indra.","link":"https://indra.ai/rigveda/hymns/08078.html","text":"p: To Indra sing the lofty hymn, Maruts that subdues the Vrtras best. Whereby the Holy Ones created for the Deva.the light divine that ever wakes.\n\np: Indra who quells the curse blew curses far away, and then in splendour came to us. Indra, refulgent with thy Marut host! the Devas strove eagerly to win thy love.\n\np: Sing to your lofty Indra, sing, Maruts, a holy hymn of praise. Let Satakratu, Vrtra conquerer, kill the foe with hundred-knotted thunderbolt.\n\np: Aim and fetch boldly forth, O thou whose heart is bold: great glory will be thine thereby. In rapid torrent let the mother waters spread. Slay Vrtra, win the light of heaven.\n\np: When thou, unequalled Maghavan, wast born to smite the Vrtras dead, Thou spreadest out the spacious earth and didst support and prop the heavens.\n\np: Theri was  'the offering produced for thee, the laud, and song of joy, Thou in thy might surpassest all, all that now is and yet shall be.\n\np: Raw kine thou filledst with ripe milk. Thou madest Surya rise to heaven.. Heat him as milk is heated with pure Sama hymns, great joy to him who loves the song.","people":["Indra","Vrtra","Satakratu","Maghavan","Deva","Surya"],"places":["Earth","Heaven"],"things":["Holy Ones","Milk","Born","Waters","Glory","Offering","Light","Might","Song","Joy","Praise","Hymn","Splendour"],"groups":["Devas","Maruts","Marut","Mother","Vrtras"],"concepts":["Divine","Love","Holy","Offering"],"hash":"md5-sX94swNyXjFt/D88F/3aXQ==","created":"Monday, April 8, 2024 - 10:51:55 PM"},{"id":"bd447906-80b3-4647-b7cb-32c2f6dae0ae","key":"08079","book":"08","title":"HYMN LXXIX. Indra.","link":"https://indra.ai/rigveda/hymns/08079.html","text":"p: MAY Indra, who in every fight must be invoked, be near to us. May the most mighty Vrtra conquerer, meet for praise, come to libations and to hymns.\n\np: Thou art the best of all in sending bounteous gifts, true art thou, lordly in thine act. We claim alliance with the very Glorious One, yea, with the Mighty Son of Strength.\n\np: Prayers unsurpassed are offered up to thee the Lover of the Song. Indra, Lord of Bay Steeds, accept these fitting hymns, hymns which we have thought out for thee.\n\np: For thou art truthful, ne’er subdued and bringest many a Vrtra low. As such, O Mightiest Lord, Wielder of Thunder, send wealth hither to the worshipper.\n\np: O Indra, thou art far-renowned, impetuous, O Lord of Strength. Alone thou slayest with the guardian of mankind resistless never-conquered foes.\n\np: As such we seek thee now, O Asura, thee most wise, craving thy bounty as our share. Thy sheltering defence is like a mighty cloak. May thy glories reach to us.","people":["Indra","Vrtra"],"places":[],"things":["Mankind","Steeds","Lord","Glorious","Wealth","Song","Wise","Mighty","Praise","Worshipper","Libations","Gifts"],"groups":["Asura","Son"],"concepts":["Strength","Truthful","Glorious","Libations"],"hash":"md5-C72Z+5uMqjCk+G/n4P2DIg==","created":"Monday, April 8, 2024 - 10:51:55 PM"},{"id":"71edbfcc-dc58-4e55-8f0c-d3c3cee1eb51","key":"08080","book":"08","title":"HYMN LXXX. Indra.","link":"https://indra.ai/rigveda/hymns/08080.html","text":"p: DOWN to the stream a maiden came, and found the Soma by the way. Bearing it to her home she said, for Indra will I press thee out, for Sakra will I press thee out.\n\np: Thou roaming yonder, little man, beholding every house in turn, Drink thou this Soma pressed with teeth, accompanied with grain and curds, with cake of meal and song of praise.\n\np: Fain would we learn to know thee well, nor yet can we attain to thee. Still slowly and in gradual drops, O Indu, unto Indra flow.\n\np: Will he not help and work for us? Will he not make us wealthier? Shall we not, hostile to our lord, unite ourselves to Indra now?\n\np: O Indra, cause to sprout again three places, these which I declare. My father's head, his cultured field, and this the part below my waist.\n\np: Make all of these grow crops of hair, you cultivated field of ours, My body, and my father's head.\n\np: Cleansing Apala, indra! thrice, thou gavest sunlike skin to her, Drawn, Satakratu! through the hole of car, of wagon, and of yoke.","people":["Indu","Indra","Soma","Satakratu","Sakra"],"places":[],"things":["Work","Lord","Soma","Stream","Flow","Song","Help","Home","Car","Praise","Drops"],"groups":["Father","Man"],"concepts":[],"hash":"md5-1KkLqXEo7zyA3JI81RDlIA==","created":"Monday, April 8, 2024 - 10:51:55 PM"},{"id":"c0894013-a8dc-40b0-bc9e-34257c077b92","key":"08081","book":"08","title":"HYMN LXXXI. Indra","link":"https://indra.ai/rigveda/hymns/08081.html","text":"p: INVITE ye Indra with a song to drink your draught of Soma juice, All-conquering Satakratu, most munificent of all who live.\n\np: Lauded by many, much-invoked, leader of song, renowned of old: His name is Indra, tell it forth.\n\np: Indra the Dancer be to us the giver of abundant strength: May he, the mighty, bring it near.\n\np: Indra whose jaws are strong hath drunk of worshipping Sudaksa's draught, the Soma juice with barley mixt.\n\np: Call Indra loudly with your songs of praise to drink the Soma juice. For this is what augments his stiength.\n\np: When he hath drqnk its gladdening drops, the Deva with vigour of a Deva.Hath far surpassed all things that are.\n\np: Thou speedest down to assist us this ever-conquering Deva.of yourshim who is drawn to all our songs\n\np: The Warrior not to he restrained, Soma ne’er o’erthrown, the Chieftain of resistless might.\n\np: O Indra, send us riches, thou Omniscient, worthy of our praise: Help us in the decisive fray.\n\np: Even thence, O Indra, come to us with food that gives a hundred powers, with food that gives a thousand powers.\n\np: We sought the wisdom of the wise. Sakra, Kine-giver, Thunder-armed! May we with steeds o’ercome in fight.\n\np: We make thee, Satakratu, find enjoyment in the songs we sing. Like cattle in the pasture lands.\n\np: For, Satakratu, Thunder-armed, all that we craved, as men are wont, All that we hoped, have we attained.\n\np: Those, Son of Strength, are come to thee who cherish wishes in their hearts O Indra, non excelleth thee.\n\np: So. Hero, guard us with thy care, with thy most liberal providence, Speedy, and terrible to foes.\n\np: O Satakratu Indra, now rejoice with that carouse of thine Which is most splendid of them all\n\np: Even, indra, that carouse which subdues the Vrtras best, most widely famed, best giver of thy power and might.\n\np: For that which is thy gift we know, true Soma-drinker, Thunder-armed, Mighty One, amid all the folk.\n\np: For Indra, Lover of Carouse, loud be our songs about the juice: Let poets sing the song of praise.\n\np: We summon Indra to the draught, irl whom all glories rest, in whom The seven communities rejoice.\n\np: At the Trikadrukas the Devas span offering that stirs the mind: Let our songs aid and prosper it.\n\np: Let the drops pass within thee as the rivers flow into the sea: O fndra, naught excelleth thee.\n\np: Thou, wakeful Hero, by thy might hast taken food of Soma juice, Which, indra, is within thee now.\n\np: O Indra, Vrtra conquerer, let Soma be ready for thy maw, the drops be ready for thy forms.\n\np: Now Srutakaksa sings his song that cattle and the stee. May come, that Indra's very sel. May come.\n\np: Here, indra, thou art ready by our Soma juices shed for thee, Sakra, at hand that tho. Mayst give.\n\np: Even from far away our songs reach thee, O Caster of the Stone: May we come very close to thee.\n\np: For so thou art the hero's Friend, a Hero, too, art thou, and strong: May thine heart be won to us.\n\np: So hath the offering, wealthiest Lord, been paid by all the worshippers: So dwell thou, indra, even with me.\n\np: Be not thou like a slothfid priest, O Lord of spoil and wealth: rejoice In the pressed Soma blent with milk.\n\np: O Indra, let not ill designs surround us in the sunbeams' light: Thi. May we gain with thee for Friend.\n\np: With thee to help us, indra, let us answer all our enemies: For thou art ours and we are thine.\n\np: Indra, the poets and thy friends, faithful to thee, shall loudly sing Thy praises as they follow thee.","people":["Indra","Soma","Vrtra","Satakratu","Sakra","Deva"],"places":[],"things":["Leader","Milk","Steeds","Lord","Rivers","Soma","Offering","Light","Wealth","Food","Men","Flow","Might","Juice","Song","Help","Wise","Strong","Mighty","Praise","Gift","Powers","Friends","Songs","Drops","Warrior","Friend","Hero","call","spoil","Riches","Cattle"],"groups":["Devas","Worshippers","Son","Vrtras"],"concepts":["Strength","Wisdom","Offering","Giver"],"hash":"md5-maUnI90cTUSBs9tZHREFyA==","created":"Monday, April 8, 2024 - 10:51:55 PM"},{"id":"013753aa-68e0-4ae3-a38c-ac741e851002","key":"08082","book":"08","title":"HYMN LXXXII. Indra.","link":"https://indra.ai/rigveda/hymns/08082.html","text":"p: SURYA, thou mountest up to meet the Hero famous for his wealth, who hurls the bolt and works for man\n\np: Him who with might of both his arms brake nine-and-ninety castles down, Slew Vrtra and smote Ahi dead.\n\np: This Indra is our gracious Friend. He sends us in a full broad stream Riches in horses, kine, and corn.\n\np: Whatever, Vrtra conquerer! thou, Surya, hast risen upon to-day, Tbat, indra, all is in thy power.\n\np: When, Mighty One, Lord of the brave, thou thinkest thus, I shall not die, that thought of thine is true indeed.\n\np: Thou, indra, goest unto all Soma libations shed for thee, Both far away and near at hand.\n\np: We make this Indra very strong to strike the mighty Vrtra dead: A vigorous Hero shall he be.\n\np: Indra was made for giving, set, most mighty, o’er the joyous draught. Bright, meet for Soma, famed in song.\n\np: By song as ’twere, the powerful bolt which non. May parry was prepared Lofty, invincible he grew.\n\np: Indra, Song-lover, lauded, make even in the wilds fair ways for us, whenever, Maghavan, thou wilt.\n\np: Thou whose commandment and behest of sovran sway none disregards, Neither audacious man nor Deva.\n\np: And both these Devas, Earth. Heaven, Lord of the beauteous helm! revere Thy might which no on. May resist.\n\np: Thou in the black cows and the red and in the cows with spotted skin This white milk hast deposited.\n\np: When in their terror all the Devas shrank from the Dragon's furious might, Fear of the monster fell on them.\n\np: Then he was my Defender, then, invincible, whose foe is not, the Vrtra conquerer showed his might.\n\np: Him your best Vrtra conquerer, him the famous Champion of mankind I urge to great munificence,\n\np: To come, Much-lauded! Many-named with this same thought that longs for milk, whene’er the Soma juice is shed.\n\np: Much-honoured by libations. May the Vrtra conquerer wake for us: May Sakra listen to our meditations.\n\np: O Hero, with that aid dost thou delight us, with what assist bring Riches to those who worship thee?\n\np: With whose libation joys the Strong, the Hero with his team who quells The foe, to drink the Soma juice?\n\np: Rejoicing in thy spirit bring thousandfold opulence to us: Enrich thy votary with gifts.\n\np: These juices with their wedded wives flow to enjoyment lovingly: To waters speeds the restless one.\n\np: Presented strengthening gifts have sent Indra away at offering, with might, onto the cleansing bath.\n\np: These two who share his feast, Bay Steeds with golden manes, shall bring him to The banquet that is laid for him.\n\np: For thee, O Lord of Light, are shed these Soma-drops, and grass is strewn Bring Indra to his worshippers.\n\np: May Indra give thee skill, and lights of heaven, wealth to his votary And monks who praise him: laud ye him.\n\np: O Satakratu, wondrous strength and all our lauds I bring to thee: Be gracious to thy worshippers.\n\np: Bring to us all things excellent, O Satakratu, food and strength: For, indra, thou art kind to us.\n\np: § O Satakratu, bring to us all blessings, all felicity: Fbr, indra, thou art kind to us.\n\np: Bearing the Soma juice we call, best Vrtra conquerer, unto thee: For, indra, thou art kind to us.\n\np: Come, Lord of rapturous, joys, to our libation with thy Bay Steeds, come To our libation with thy Steeds.\n\np: Known as best Vrtra conquerer erst, as Indra Satakratu, come With Bay Steeds to the juice we shed.\n\np: O Vrtra conquerer, thou art he who drinks these drops of Soma: come With Bay Steeds to the juice we shed.\n\np: May Indra give, to aid us, wealth handy that rules the Skilful Ones: Yea. May the Strong give potent wealth.","people":["Indra","Soma","Vrtra","Satakratu","Sakra","Maghavan","Deva","Surya","Ahi"],"places":["Earth","Heaven"],"things":["Worship","Mankind","Milk","Steeds","Lord","Soma","Waters","Offering","Light","Wealth","Food","Stream","Flow","Might","Juice","Song","Strong","Mighty","Grass","Banquet","Praise","Brave","Delight","Excellent","Libations","Drops","Friend","Hero","Horses","call","Riches","Spirit","Gifts"],"groups":["Devas","Worshippers","Man","Monks"],"concepts":["Blessings","Strength","Offering","Libations","Powerful"],"hash":"md5-RU63imWuw8Xd1TPkuexAGA==","created":"Monday, April 8, 2024 - 10:51:55 PM"},{"id":"943ea4c6-cb63-4722-990f-63c64347ed5d","key":"08083","book":"08","title":"HYMN LXXXIII. Maruts.","link":"https://indra.ai/rigveda/hymns/08083.html","text":"p: THE Cow, the famous Mother of the wealthy Maruts, pours her milk: Both horses of the cars are yoked.\n\np: She in whose bosom all the Devas, and Sun and Moon for men to see, Maintain their everlasting Laws.\n\np: This all the pious sing to us, and sacred poets evermore: The Maruts to the Soma-draught\n\np: Here is the Soma ready pressed of this the Maruts drink, of this Self-luminous the Asvins drink.\n\np: Of this, moreover, purified, set in three places, procreant, Drink Varuna, Mitra, Aryaman.\n\np: And Indra, like the Herald Monk, desirous of the milky juice, At early morn will quaff thereof.\n\np: When have the Princes gleamed and shone through waters as through troops of foes'? When hasten they whose might ispure?\n\np: What favour do I claim this day of you great Deities, you who are Wondrously splendid in yourselves?\n\np: 1 call, to drink the Soma, those Maruts who spread all realms of earth And luminous regions of the sky.\n\np: You, even such, pure in your might, you, O ye Maruts, I invoke From heaven to drink this Somajuice.\n\np: The Maruts, those who have sustained and propped the heavens and earth apart, I call to drink this Soma juice.\n\np: That vigorous band of Maruts that abidetb in the mountains, I Invoke to drink this Soma juice.","people":["Indra","Soma","Mitra","Varuna","Asvins","Aryaman"],"places":["Earth","Heaven","Sky"],"things":["Milk","Mountains","Soma","Waters","Sun","Moon","Men","Might","Juice","Cow","Horses","call","Cars"],"groups":["Devas","Maruts","Deities","Mother"],"concepts":["Cars","Sacred"],"hash":"md5-F/9WStra6RLQCc/G2T7JaQ==","created":"Monday, April 8, 2024 - 10:51:55 PM"},{"id":"7147c4fd-e0a4-4b21-bc14-4f9618b952b0","key":"08084","book":"08","title":"HYMN LXXXIV. Indra.","link":"https://indra.ai/rigveda/hymns/08084.html","text":"p: SONG-LOVER! like a charioteer come songs to thee when Soma flows. O Indra, they have called to thee as mother-kine unto their calves.\n\np: Bright juices bitherward have sped thee, indra, Lover of the Song. Drink, indra, of this flowing sap: in every house ’tis set for thee.\n\np: Drink Soma to inspirit thee. Indra, which the Falcon brought: For thou art King and Sovran Lord of all the families of men.\n\np: O Indra, hear Tirasci's call, the call of him who serveth thee. Satisfy him with wealth of kine and valiant offspring: Great art thou.\n\np: For he, O Indra, hath produced for thee the newest gladdening song, a hymn that springs from careful thought, ancient, and full of sacred truth.\n\np: That Indra will we laud whom songs and hymns of praise have magnified. Striving to win, we celebrate his many deeds of hero might.\n\np: Come now and let us glorify pure Indra with pure Sama hymns. Let the pure milky draught delight him strengthened by pure songs of praise.\n\np: O Indra, come thou pure to us, with pure assistance, pure thyself. Pure, send thou riches down to us, and, meet for Soma, pure, be glad.\n\np: O Indra, pure, vouchsafe us wealth, and, pure, enrich the worshipper. Pure, thou dost strike the Vrtras dead, and strivest, pure, to win the spoil.","people":["Indra","Soma"],"places":[],"things":["Lord","Soma","Wealth","Men","Might","Song","Offspring","Praise","Worshipper","Delight","Hymn","Songs","Hero","King","call","spoil","Riches"],"groups":["Families","Mother","Vrtras"],"concepts":["Sacred","Truth"],"hash":"md5-8P0A0vPSFreHld7Ih21h3w==","created":"Monday, April 8, 2024 - 10:51:55 PM"},{"id":"1e735de7-8fce-460f-9a31-ab22879369e4","key":"08085","book":"08","title":"HYMN LXXXV. Indra.","link":"https://indra.ai/rigveda/hymns/08085.html","text":"p: FOR him the Mornings made their courses longer, and Nights with pleasant voices spake to Indra. For him the Floods stood still, the Seven Mothers, Streams easy for the heroes to pass over.\n\np: The Darter penetrated, though in trouble, thrice-seven close-pressed ridges of the mountains. Neither might Deva.nor mortal man accomplish what the Strong Hero wrought in full-grown vigour.\n\np: The mightiest force is Indra's bolt of iron when firmly grasped in both the arms of Indra. His head and mouth have powers that pass all others, and all his people hasten near to listen.\n\np: 1 count thee as the Holiest of the Holy, the caster-down of what hath ne’er been shaken. I count thee as the Banner of the heroes, I count thee as the Chief of all men living.\n\np: What time, O Indra, in thine arms thou tookest thy wildly rushing bolt to Slay the Dragon, the mountains roared, the cattle loudly bellowed, the Brahmans with their hymns drew nigh to Indra.\n\np: Let us praise him who made these worlds and creatures, all things that after him sprang into being. May we win Mitra with our songs, and Indra, and. wait upon our Lord with adoration.\n\np: Flying in terror from the snort of Vrtra, all Deities who were thy friends forsook thee. So, indra, be thy friendship with the Maruts: in all these battles thou shalt be the victor.\n\np: Thrice-sixty Maruts, waxing strong, were with thee, like piles of beaming light, worthy of worship. We come to thee: grant us a happy portion. Let us adore thy might with this oblation.\n\np: A sharpened weapon is the host of Maruts. Who, indra, dares withstand thy bolt of thunder? Weaponless are the Asuras, the godless: scatter them with thy wheel, Impetuous Hero.\n\np: To him the Strong and Mighty, most auspicious, send up the beAuteous hymn for sake of cattle. Lay oa his body many songs for Indra invoked with song, for will not he regard. them?\n\np: To him, the Mighty, who accepts laudation, send forth thy thought as by a boat o’er rivers, Stir with thy hymn the body of the Famous and Dearest One, for will not he regard it?\n\np: Serve him with gifts of thine which Indra welcomes: praise with fair praise, invite him with thine homage. Draw near, O singer, and refrain from outcry. Make thy voice heard, for will not he regard it?\n\np: The Black Drop sank in Amsumati's bosom, advancing with ten thousand round about it. Indra with might longed for it as it panted: the hero-hearted laid aside his weapons.\n\np: 1 s w the Drop in the far distance moving, on the slope bank of Amsumati's riverlike a black cloud that sank into the water. Heroes, I send you forth. Go, fight in battle.\n\np: And then the Drop in Amsumati's bosom, splendid with light, assumed its proper body; And Indra, with Narasamsa to aid him, conquered the godless tribes that came against him.\n\np: Then, at thy birth, thou wast the foeman, indra, of those the seven who ne’er had met a rival. The hidden Pair, the Heaven and Earth, thou foundest, and to the mighty worlds thou gavest pleasure.\n\np: So, Thunder-armed! thou with thy bolt of thunder didst boldly smite that power which none might equal; With weapons broughtest low the migbt of Susna, and, indra, foundest by thy strength the cattle.\n\np: Then wast thou, Chieftain of all living mortals, the very mighty slayer of the Vrtras. Then didst thou set the obstructed rivers flowing, and win the floods that were enthralled by Dasas.\n\np: Most wise is he, rejoicing in libations, splendid as day, resistless in his anger. He only doth great deeds, the only Hero, sole Vrtra conquerer he, with none beside him.\n\np: Indra is Vrtra's slayer, man's sustainer: he must be called; with fair praise let us call him. Maghavan is our Helper, our Protector, giver of spoil and wealth to make us famous.\n\np: This Indra, Vrtra conquerer, this Rbhuksan, even at his birth, was meet for invocation. Doer of many deeds for man's advantage, like Soma quaffed, for friends we must invoke him.","people":["Indra","Soma","Vrtra","Mitra","Maghavan","Susna","Narasamsa","Deva","Rbhuksan"],"places":["Earth","Heaven"],"things":["Worship","Lord","Mountains","Rivers","Soma","Water","Singer","Light","Wealth","Men","Streams","Might","Song","Wise","Strong","Mighty","Chief","Praise","Voice","Hymn","Heroes","People","Powers","Libations","Friends","Songs","Hero","call","spoil","Cattle","Gifts","Wheel"],"groups":["Asuras","Maruts","Deities","Brahmans","Man","Vrtras"],"concepts":["Birth","Friendship","Holy","Strength","Giver","Auspicious","Libations"],"hash":"md5-JjdyXXyJZW0UyJDsXzifZw==","created":"Monday, April 8, 2024 - 10:51:55 PM"},{"id":"1d20f667-e7c0-45ba-9c04-aa700ef8e1af","key":"08086","book":"08","title":"HYMN LXXXVI. Indra.","link":"https://indra.ai/rigveda/hymns/08086.html","text":"p: O INDRA, Lord of Light, what joys thou broughtest from the Asuras, prosper therewith him who lauds that deed, and those whose grass is trimmed for thee.\n\np: The unwasting share of steeds and kine which, indra, thou hast fast secured, Grant to the worshipper who presses Soma and gives guerdon, not unto the churl.\n\np: The riteless, godless man who sleeps, O Indra, his unbroken steep. May he by following his own devices die. Hide from him wealth that nourishes.\n\np: Whether, O Sakra, thou be far, or, Vrtra conquerer, near at hand, thence by heaven-reaching songs he who hath pressed the juice invites thee with thy long-maned Steeds.\n\np: Whether thou art in heaven's bright sphere, or in the basin of the sea; Whether, chief Vrtra conquerer, in some place on earth, or in the firmament, approach.\n\np: Thou Soma-drinker, Lord of Strength, beside our flowing Soma juice Delight us with thy bounty rich in pleasantness, O Indra, with abundant wealth.\n\np: O Indra, turn us not away: be the companion of our feast. For thou art our protection, yea, thou art our kin: O Indra, turn us not away.\n\np: Sit down with us, O Indra, sit beside the juice to drink the meath. Show forth great favour to the Singer, Maghavan; Indra, with us, beside the juice.\n\np: O Indra, nor Devas nor mortals have attained to thee. Thou in thy might surpassest all that hath been made: the Devas have not attained to thee.\n\np: Of one accord they made and formed for kingship Indra, the Hero who in all encounters overcometh, most eminent for power, destroyer in the conflict, fierce and exceeding strong, stalwart and full of vigour.\n\np: Bards joined in song to Indra so that he might drink the Soma juice, the Lord of Light, that he whose laws stand fast might aid with power and with the help he gives.\n\np: Tle holy sages form a ring, looking and singing to the Ram. Inciters, full of vigour, not to he deceived, are with the chanters, nigh to bear.\n\np: Loudly I call that Indra, Maghavan the Mighty, who evermore possesses power, ever resistless. Holy, most liberal. May he lead us on to riches, and, Thunder-armed, make all our pathways pleasant for us.\n\np: Thou knowest well, O Sakra, thou Most Potent, with thy strength, indra, to destroy these castles. Before thee, Thunder-armed! all beings tremble: the heavens and earth before thee shake with terror,\n\np: May thy truth, indra, Wondrous Hero be my guard: bear me o’er much woe, Thunderer! as over floods. When, indra, wilt thou honour us with opulence, all-nourishing and much-to-be. desired, O King?","people":["Indra","Soma","Vrtra","Sakra","Maghavan"],"places":["Earth","Heaven","Firmament"],"things":["Meath","Steeds","Lord","Soma","Singer","Light","Wealth","Might","Juice","Song","Help","Strong","Mighty","Grass","Chief","Worshipper","Delight","Form","Songs","Hero","King","call","Riches"],"groups":["Devas","Asuras","Man"],"concepts":["Holy","Strength","Truth"],"hash":"md5-0dvmajH/MCsv7J2lWc3XMQ==","created":"Monday, April 8, 2024 - 10:51:55 PM"},{"id":"c8e9d286-eb2e-4a38-ba20-9038383976bc","key":"08087","book":"08","title":"HYMN LXXXVII. Indra.","link":"https://indra.ai/rigveda/hymns/08087.html","text":"p: To Indra sing a Sama hymn, a lofty song to Lofty Sage, to him who guards the Law, inspired, and fain for praise.\n\np: Thou, indra, art the Conqueror: thou gavest splendour to the Sun. Maker of all things, thou art Mighty and All-Deva.\n\np: Radiant with light thou wentest to the sky, the luminous realm of heaven. ne Deities, indra strove to win thee for their Friend.\n\np: Come unto us, O Indra, dear, still conquering, unconcealable, Vast as a mountain spread on all sides, Lord of Heaven.\n\np: O truthful Soma-drinker, thou art mightier than both the worlds. Thou strengthenest him who pours libation, Lord of Heaven.\n\np: For thou art he, O Indra, wiio stormeth all castles of the foe, Slayer of Dasyus, man's Supporter, Lord of Heaven.\n\np: Now have we, indra, Friend of Song, sent our great wishes forth to thee, Coming like floods that follow floods.\n\np: As rivers swell the ocean, so. Hero, our meditations increase thy might, Though of thyself, O Thunderer, waxing day by day.\n\np: With holy song mey bind to the broad wide-yoked car the Bay Steeds of the rapid Deva, bearers of Indra, yoked by word.\n\np: O Indra, bring great strength to us, bring valour, Satakratu, thou most active, bring A hero conquering in war.\n\np: For, gracious Satakratu, thou hast ever been a Mother and a Sire to us, So now for bliss we pray to thee.\n\np: To thee, Strong, Much-invoked, who showest forth thy strength, O Satakratu, do I speak: So grant thou us heroic strength.","people":["Indra","Soma","Satakratu","Deva"],"places":["Ocean","Heaven","Sky"],"things":["Steeds","Lord","Rivers","Soma","Light","Sun","Might","Song","Strong","Mighty","Car","Praise","Hymn","Splendour","Bliss","Friend","Hero","Sage"],"groups":["Dasyus","Deities","Mother","Man"],"concepts":["Heroic","Holy","Strength","Truthful"],"hash":"md5-D73+HoCWfnPphLdu3GNhUg==","created":"Monday, April 8, 2024 - 10:51:55 PM"},{"id":"9727facd-97e7-4aea-9c72-ab811c4bd081","key":"08088","book":"08","title":"HYMN LXXXVIII. Indra.","link":"https://indra.ai/rigveda/hymns/08088.html","text":"p: O THUNDERER, zealous worshippers gave thee drink this time yesterday. So, indra, listen here to those who bring the laud: come near unto our dwellingplace.\n\np: Lord of Bay Steeds, fair-helmed, rejoice thee: this we crave. Here the disposers wait on thee. Thy loftiest glories claim our lauds beside the juice, O Indra, Lover of the Song.\n\np: Turning, as ’twere, to meet the Sun, enjoy from Indra all good things. When he who will be born is born with power we look to treasure.s as our heritage.\n\np: Praise him who sends us wealth, whose bounties injure none: good are the gifts which Indra. grants. He is not worth with one who satisfies his wish: he turns his mind to giving boons.\n\np: Thou in thy battles, indra, art subduer of all hostile bands. Father art thou, aIl-conquering, cancelling the curse, thou victor of the vanquisher.\n\np: The Earth and Heaven clung close to thy victorious might as to their calf two mother-cows. When thou attackest Vrtra all the hostile bands shrink and faint, indra, at thy wrath.\n\np: Bring to your aid the Eternal One, who shoots and non. May shoot at him, inciter, swift, victorious, best of Charioteers. Tugrya's unvanquished Strengthener;\n\np: Arranger of things unarranged, e’en Satakratu, source of might, indra, the Friend of all, for assist we invoke, Guardian of treasure., sendjng wealth.","people":["Indra","Vrtra","Satakratu"],"places":["Earth","Heaven"],"things":["Steeds","Lord","Born","Sun","Treasure","Wealth","Might","Juice","Song","Praise","Friend","Gifts"],"groups":["Worshippers","Father","Mother"],"concepts":["Good","Swift"],"hash":"md5-vSzeLy8MfrVe5ise4Evijw==","created":"Monday, April 8, 2024 - 10:51:55 PM"},{"id":"145d0685-44b4-400f-a27c-d202e096d125","key":"08089","book":"08","title":"HYMN LXXXIX Indra. Vak.","link":"https://indra.ai/rigveda/hymns/08089.html","text":"p: I MOVE before thee here present in person, and all the Deities follow behind me. When, indra, thou securest me my portion, with me thou shalt perform heroic actions.\n\np: The food of meath in foremost place I give thee, thy Soma shall be pressed, thy share appointed. Thou on my right shalt be my friend and comrade: then shall we two smite dead full many a foeman.\n\np: Striving for strength bring forth a laud to Indra, a truthful hymn if he in truth existeth. One and another say, there is no Indra. Who hath beheld him? Whom then shall we honour?\n\np: Here am I, look upon me here, O singer. All that existeth 1 surpass in greatness. The Holy Law's commandments make me mighty. Rending with strength I rend the worlds asunder.\n\np: When the Law's lovers mounted and ap. proached me as 1 sate lone upon the dear sky's summit. Then spake my spirit to the heart within me, My friends have cried unto me with their children.\n\np: All these thy deeds must be declared at Soma-feasts, wrought, indra, Bounteous Lord, for him who sheds the juice, when thou didst open wealth heaped up by many, brought from far away to Sarablia, the Rsi's kin.\n\np: Now run ye forth your several ways: he is not here who kept you back. For hath not Indra sunk his bolt deep down in Vrtra's vital part?\n\np: On-rushing with the speed of thought within the iron fort he pressed: The Falcon went to heaven and brought the Soma to the Thunderer.\n\np: Deep in the ocean lies the bolt with waters compassed round about, and in continuous onward flow the floods their tribute bring to it.\n\np: When, uttering words which no one comprehended, Vak, Queen of Devas, the Gladdener, was seated, the heaven's four regions drew forth drink and vigour: now whither hath her noblest portion vanished?\n\np: The Deities generated Vak the Deva, and animals of every figure speak her. May she, the Gladdener, yielding food and vigour, the Milch-cow Vak, approach us meetly lauded.\n\np: Step forth with wider stride, my comrade Visnu; make room, Dyaus, for the leaping of the lightning. Let us subdue Vrtra, let us free the rivers let them flow loosed at the command of Indra.","people":["Indra","Soma","Vrtra","Visnu","Deva","Vak"],"places":["Ocean","Heaven","Sky"],"things":["Meath","Lord","Rivers","Soma","Waters","Singer","Wealth","Food","Flow","Juice","Mighty","Hymn","Tribute","Friends","Friend","Cow","Spirit"],"groups":["Devas","Dyaus","Deities"],"concepts":["Heroic","Holy","Strength","Truthful","Truth"],"hash":"md5-WRs04PToeMLNHv9sq0+Uwg==","created":"Monday, April 8, 2024 - 10:51:55 PM"},{"id":"4387d241-ba57-472f-a484-f764797a352c","key":"08090","book":"08","title":"HYMN XC. Various.","link":"https://indra.ai/rigveda/hymns/08090.html","text":"p: YEA, specially that mortal man hath toiled for service of the Devas, who quickly hath brought near Mitra and Varuna. to share his offerings gifts.\n\np: Supreme in sovran power, far-sighted, Chiefs and Kings, most swift to hear from far away, Both, wondrously, set them in motion as with arms, in company with Surya's beams.\n\np: The rapid messenger who runs before you, Mitra and Varuna, with iron head, swift to the draught,\n\np: He whom no ma. May question, non. May summon back, who stands not still for colloquy. From hostile clash with him keep ye us safe this day: keep us in safety with your arms.\n\np: To Aryaman and Mitra sing a reverent song, O pious one, a pleasant hymn that shall protect to Varuna: sing forth a laud unto the Kings.\n\np: The true, Red Treasure they have sent, one only Son born of the Three. They, the Immortal Ones, never deceived, survey the families of mortal men.\n\np: My songs are lifted up, and acts most splendid are to be performed. Come hither, ye Nasatyas, with accordant mind, to meet and to enjoy my gifts.\n\np: Lords of great wealth, when we invoke your bounty which no demon checks, Both of you, furthering our eas ward-offcred praise, come, Chiefs whom Jamadagni lauds!\n\np: Come, Vayu, drawn by fair hymns, to  'our offering that reaches heaven. Poured on the middle of the strainingcloth, and cooked, this bright drink hath been offered ilice.\n\np: He comes by straightest paths, as ministering Monk, to taste the offerings gifts. Then, Lord of harnessed teams I drink of the twofold draught, bright Soma mingled with the milk.\n\np: Verily, Surya, thou art great; truly, Aditya, thou art great. As thou art great indeed, thy greatness is admired: yea, verily Deva, art great.\n\np: Yea, Surya, thou art great in fame thou evermore, O Deva, art great. Thou by thy greatness art the Devas’ High Monk, divine, far-spread unconquerable light.\n\np: She yonder, bending lowly down, clothed in red hues and rich in rays, is seen, advancing as it were with various tints, amid the ten surrounding arms.\n\np: Past and gone are three mortal generations: the fourth and last into the Sun hath entered. He mid the worlds his lofty place hath taken. Into green plants is gone the Purifying.\n\np: The Rudras' Mother, Daughter of the Vasus, centre of nectar, the Adityas’ Sister- To folk who understand will 1 proclaim it-injure not Aditi, the Cow, the sinless.\n\np: Weak-minded men have as a cow adopted me who came hither from the Devas, a Deva, who, skilled in eloquence, her voice uplifteth, who standeth near at hand with all devotions.","people":["Soma","Vayu","Mitra","Varuna","Nasatyas","Aditya","Deva","Surya","Aditi","Aryaman"],"places":["Heaven"],"things":["Milk","Lord","Born","Soma","Offering","Light","Sun","Treasure","Wealth","Men","Song","Praise","Voice","Hymn","Offerings","Songs","Cow","Gifts"],"groups":["Devas","Rudras","Families","Kings","Mother","Son","Sister","Immortal","Man","Vasus","Adityas"],"concepts":["Divine","Immortal","Offering","Offerings","Swift"],"hash":"md5-vDw6W8M4VFaIcZDju8HwGQ==","created":"Monday, April 8, 2024 - 10:51:55 PM"},{"id":"e1294d96-9f2f-46bb-b6ed-2f5d086f1e75","key":"08091","book":"08","title":"HYMN XCI. Agni.","link":"https://indra.ai/rigveda/hymns/08091.html","text":"p: LORD of the house, Sage, ever young, high power of life, O Agni, Deva, Thou givest to thy worshipper.\n\np: So with our song that prays and serves, attentive, Lord of spreading light, Agni, bring hitherward the Devas.\n\np: For, Ever-Youthful One, with thee, best Furtherer, as our ally, We overcome, to win the spoil.\n\np: As Aurva Bhrgu used, as Apnavana used, I call the pure Agni who clothes him with the sea.\n\np: 1 call the Sage who sounds like wind, the Might that like Parjanya roars, Agni who clothes him with the sea.\n\np: As Savitar's productive Power, as him who sends down bliss, I call Agni who clothes him with the sea.\n\np: Hither, for powerful kirship, I call Agni, him Who prospers you, most frequent at our solemn rites\n\np: That through this famed One's power, h. May stand by us even as Tvastar comes Unto the forms that must he shaped.\n\np: This Agni is the Lord supreme above all glories mid the Devas: May he come nigh to us with strength.\n\np: Here praise ye him the most renowned of all the ministering Monks, Agni, the Chief at offering;\n\np: Piercing, with purifying flame, enkindled in our homes, most high, Swiftest to hear from far away.\n\np: Sage, laud the Mighty One who wins the spoil of victory like a steed, and, Mitra like, unites the folk.\n\np: Still turning to their aim in thee, the oblation-bearer's sister hymns Have come to thee before the wind.\n\np: The waters find their place in him, for whom the threefold sacred grass Is spread unbound, unlimited.\n\np: The station of the Bounteous Deva.hath, through his aid which none impair, a pleasant aspect like the Sun.\n\np: Blazing with splendour, Agni, Deva, through pious gifts of sacred oil. Bring thou the Devas and worship them.\n\np: The Devas as mothers brought thee forth, the Immortal Sage, O Angiras, the bearer of our gifts to heaven.\n\np: Wise Agni, Devas established thee, the Seer, noblest messenger, as bearer of our sacred gifts.\n\np: No cow have I to call mine own, no axe at hand wherewith to work, Yet what is here I bring to thee.\n\np: O Agni, whatsoever be the fuel that we lay for thee, be pleased therewith, most Youthful God\n\np: That which the white-ant cats away, that over which the emmet crawls- May all of this be oil to thee.\n\np: When he enkindles Agni, man should with his heart attend the song: I with the monks have kindled him.","people":["Agni","Angiras","Mitra","Tvastar","Savitar","Deva","Parjanya"],"places":["Heaven"],"things":["Worship","Victory","Work","Lord","Waters","Offering","Light","Sun","Might","Song","Wise","Mighty","Grass","Chief","Praise","Worshipper","Splendour","Bliss","Sage","Cow","call","spoil","Life","Gifts"],"groups":["Devas","Sister","Immortal","Man","Monks"],"concepts":["Life","Immortal","Sacred","Strength","Offering","Powerful","Pleased"],"hash":"md5-99brjG9XNqXTq3clo7pfrA==","created":"Monday, April 8, 2024 - 10:51:55 PM"},{"id":"a2719800-9b47-44e2-9cdc-369439766012","key":"08092","book":"08","title":"HYMN XCII. Agni","link":"https://indra.ai/rigveda/hymns/08092.html","text":"p: THAT noblest Furtherer hath appeared, to whom men bring their holy works. Our songs of praise have risen aloft to Agni who was barn to give the Arya strength.\n\np: Agni of Divodasa turned, as ’twere in majesty, to the Devas. Onward he sped along the mother earth, and took his station in the height of heaven.\n\np: Him before whom the people shrink when he performs his glorious deedshim who wins thousands at the worship of the Devas, himself, that Agni, serve with son s.\n\np: The mortal man whom thou wouldst lead to opulence, O Vasu, he who brings thee gifts. He, Agni, wins himself a hero singing lauds, yea, one who feeds a thousand men.\n\np: He with the steed wins spoil even in the fenced fort, and gains imperishable fame. In thee, O Lord of wealth, continually we lay all precious offerings to the Devas.\n\np: To him who dealeth out all wealth, who is the cheerful Monk of men, to him, like the first vessels filled with savoury juice, to Agni go the songs of praise.\n\np: Votaries, richly-gifted, deck him with their songs, even as the steed who draws the car. On both, Strong Lord of men! on child and grandson pour the bounties which our nobles give.\n\np: Sing forth to him, the Holy, most munificent, sublime with his refulgent glow, to Agni, ye Upastutas.\n\np: Worshipped with gifts, enkindled, splendid, Maghavan shall win himself heroic fame. And will not his most newly shown benevolence come to us with abundant strength?\n\np: Monk, presser of the juice! praise now the dearest Guest of all our friends, Agni, the driver of the cars.\n\np: Who, finder-out of treasure.s open and concealed, bringeth them hither, Holy One. Whose waves, as in a cataract, are hard to pass, when he, through song, would win him strength.\n\np: Let not the noble Guest, Agni, be wroth with us: by many a man his praise is sung, Good Herald, skilled in offering.\n\np: O Vasu, Agni, let not them be harmed who come in any way with lauds to thee. Even the lowly, skilled in rites, with offered gifts, seeketh thee for the envoy's task.\n\np: Friend of the Maruts, Agni, come with Rudras to the Soma-draught, to Sobhar's fair song of praise, and be thou joyful in the light. VALAKHILYA","people":["Soma","Agni","Maghavan","Vasu"],"places":["Earth","Heaven"],"things":["Worship","Lord","Soma","Glorious","Offering","Light","Treasure","Wealth","Men","Juice","Song","Strong","Car","Praise","People","Offerings","Friends","Songs","Friend","Hero","spoil","Cars","Gifts"],"groups":["Devas","Maruts","Rudras","Mother","Son","Child","Man"],"concepts":["Good","Heroic","Cars","Holy","Strength","Offering","Offerings","Worshipped","Benevolence","Glorious","Noble"],"hash":"md5-oB8JIsPBT6B86REXxDsGYg==","created":"Monday, April 8, 2024 - 10:51:55 PM"},{"id":"b5b5fb94-63a9-4175-811f-55ed832afdda","key":"08093","book":"08","title":"HYMN I. Indra.","link":"https://indra.ai/rigveda/hymns/08093.html","text":"p: TO you will I sing Indra's praise who gives good gifts as well we know; The praise of Maghavan who, rich in treasure., aids his singers with wealth thousandfold.\n\np: As with a hundred hosts, he rushes boldly on, and for the offerer subdues his foes. As from a mountain flow the water-brooks, thus flow his gifts who feedeth many a one.\n\np: The drops effused, the gladdening draughts, O Indra, Lover of the Son As waters seek the lake where they are wont to rest, fill thee, for bounty, Thunderer.\n\np: The matchless draught that strengthens and gives eloquence, the sweetest of the meath drink thou, that in thy joy tho. Maysi scatter thy gifts o’er us, plenteously, even as the dust.\n\np: Come quickly to our laud, urged on by Soma-pressers like a horse- Laud, Deva like Indra, which milch-kine make sweet for thee: with Kanva's sons are gifts for thee.\n\np: With homage have we sought thee as a Hero, strong, preeminent, with unfailing wealth. O Thunderer, as a plenteous spring pours forth its stream, so, indra, flow our songs to thee.\n\np: If now thou art at offering, or if thou art upon the earth, Come thence, high-thoughted! to  'our offering with the Swift, come, Mighty with the MightyOnes.\n\np: The active, fleet-foot, tawny Coursers that are thine are swift to victory, like the Wind, Wherewith thou goest round to visit Manus' seed, wherewith all heaven is visible.\n\np: Indra, from thee so great we crave prosperity in wealth of kine, As, Maghavan, thou favouredst Medhyatithi, and, in the fight, Nipatithi.\n\np: As, Maghavan, to Kanva, Trasadasyu, and to Paktha and Dasavraja; As, indra, to Gosarya and Rjisvan, thou vouchsafedst wealth in kine and gold.","people":["Indra","Soma","KanVa","Maghavan","Deva","Rjisvan"],"places":["Earth","Heaven"],"things":["Meath","Victory","Tawny Coursers","Soma","Waters","Water","Offering","Treasure","Wealth","Stream","Flow","Joy","Gold","Strong","Mighty","Praise","Lake","Songs","Drops","Hero","Horse","Gifts"],"groups":["Sons","Son","MightyOnes"],"concepts":["Good","Offering","Swift"],"hash":"md5-od4kdrXe6Pe3wvh54WetaA==","created":"Monday, April 8, 2024 - 10:51:55 PM"},{"id":"03643fa9-6f07-4033-972f-6de6c64bc463","key":"08094","book":"08","title":"HYMN II. Indra.","link":"https://indra.ai/rigveda/hymns/08094.html","text":"p: SAKRA I praise, to win his aid, far-famed, exceeding bountiful, who gives, as ’twere in thousands, precious wealth to him who sheds the juice and worships him.\n\np: Arrows with hundred points, unconquerable, are this Indra's n-dghty arms in war. He streams on liberal worshippers like a hill with springs, when juices poured have gladdened him.\n\np: What time the flowing Soma-drops have gladdened with their taste the Friendlike water, gracious Lord! were my libations made, like milch-kine to the worshipper.\n\np: To him the peerless, who is calling you to give you aid, forth flow the drops of pleasant meath. The Soloa-drops which call on thee, O gracious Lord, have brought thee to our hymn of praise.\n\np: He rushes hurrying like a steed to Soma that adorns our rite, Which hymns make sweet to thee, lover of pleasant food. The call to Paura thou dost love.\n\np: Praise the strong, grasping Hero, winner of the spoil, ruling supreme oer mighty wealth. Like a full spring, O Thunderer, from thy store hast thou poured on the worshipper evermore.\n\np: Now whether thou be far away, or in the heavens, or on the earth, O Indra, mighty- thoughted, harnessing thy Bays, come Lofty with the Lofty Ones.\n\np: The Bays who draw thy chariot, Steeds who injure none, surpass the wind's impetuous strength- With whom thou silencest the enemy of man, with whon; thou goest round the sky.\n\np: O gracious Hero. May we learn anew to know thee as thou art: As in decisive fight thou holpest Etasa, or Vasa 'gainst Dasavraja,\n\np: As, Maghavan, to Kanva at the sacred feast, to Dirghanitha thine home-friend, as to Gosarya thou, Stone-darter, gavest wealth, give me a gold-bright stall of kine.","people":["Indra","Soma","KanVa","Sakra","Maghavan","Etasa"],"places":["Earth","Sky"],"things":["Meath","Steeds","Lord","Soma","Water","Wealth","Food","Streams","Flow","Juice","Gold","Home","Strong","Mighty","Praise","Worshipper","Hymn","Libations","Drops","Friend","Hero","call","spoil"],"groups":["Worshippers","Man"],"concepts":["Love","Sacred","Strength","Libations","Winner"],"hash":"md5-Lo3D+CHonELXGDy91jiK1Q==","created":"Monday, April 8, 2024 - 10:51:55 PM"},{"id":"2c059b04-79cc-4345-8647-c0cebf9b11dd","key":"08095","book":"08","title":"HYMN III. Indra.","link":"https://indra.ai/rigveda/hymns/08095.html","text":"p: As with Manu Samvarani, indra, thou drankest Soma juice, and, Maghavan, with Nipatithi, Medbyatithi, with Pustigu and Srustigu.\n\np: T'he son of Prsadvana was Praskaniva's host, who lay decrepit and forlorn. Aided by thee the Rsi Dasyave-vrka strove to obtain thousands of kine.\n\np: Call hither with thy newest song Indra who lacks not hymns of praisehim who observes and knows, inspirer of the sage, him who seems eager to enjoy.\n\np: He unto whom they sang the seven-headed hymn, three-parted, in the loftiest place. He sent his thunder down on all these living things, and so displayed heroic might.\n\np: We invocate that Indra who bestoweth precious things on us. Now do we know his newest favour. May we gain a stable that is full of kine.\n\np: He whom thou aidest, gracious Lord, to give again, obtains great wealth to nourish him. We with our Soma ready, Lover of the Song! call, indra Maghavan, on thee.\n\np: Ne’er art thou fruitless, indra ne’er dost thou desert the worshipper But now thy bounty as a Indu is poured forth ever more and more.\n\np: He who hath. overtaken Krvi with his might, and silenced Susna with deathbolts. When he supported yonder heaven and spread it out, then first the son of earth was born.\n\np: Good Lord of wealth is he to whom all Aryas, Dasas here belong. Directly unto thee, the pious Rusama Paviru, is that wealth brought nigh.\n\np: In zealous haste the singers have sung forth a song distilling oil and rich in sweets. Riches have spread among us and heroic strength, with us are flowing Soma-drops.","people":["Indu","Indra","Soma","Maghavan","Susna"],"places":["Earth","Heaven"],"things":["Lord","Born","Soma","Wealth","Might","Juice","Song","Worshipper","Hymn","Drops","Sage","call","Riches"],"groups":["Son","Aryas"],"concepts":["Good","Heroic","Strength"],"hash":"md5-Wwph6GUbWn/oyC2c/yeAwA==","created":"Monday, April 8, 2024 - 10:51:55 PM"},{"id":"d50c61ca-e215-46b7-bd51-b485ba81698d","key":"08096","book":"08","title":"HYMN IV. Indra.","link":"https://indra.ai/rigveda/hymns/08096.html","text":"p: As, Sakra, thou with Manu called Vivasvan drankest Soma juice, As, indra, thou didst love the hymn by Trita's side, so dost thou joy with Ayu now.\n\np: As thou with Matarisvan, Medhya, prsadhra, hast cheered thee Indra, with pressed juice, Drunk Soma with Rjunas, Syumarasmi, by Dasonya's Dasasipra's side.\n\np: ’Tis he who made the lauds his own and boldly drank the Soma juice. He to whom Visnu came striding his three wide steps, as Mitra's statutes ordered it.\n\np: In whose laud thou didst joy, indra, at the great deed, O Satakratu, Mighty One! Seeking renown we call thee as the milkers call the cow who yields abundant milk.\n\np: He is our Sire who gives to us, Great, Mighty, ruling as he wills. Unsought. May he the Strong, Rich, Lord of ample wealth, give us of horses and of kine.\n\np: He to whom thou, Good Lord, givest that h. May give increases wealth that nourishes. Eager for wealth we call on Indra, Lord of wealth, on Satakratu with our lauds.\n\np: Never art thou neglectful: thou guardest both races with thy care. The call on Indra, fourth Aditya! is thine own. Amrta is stablished in the heavens.\n\np: The offercr whom thou, indra, Lover of the Song, liberal Maghavan, favourest. As at the call of Kanva so, O gracious Lord, hear, thou our songs and eulogy.\n\np: Sung is the song of ancient time: to Indra have ye said the prayer. They have sung many a Brhati of offering, poured forth the worshipper's many thoughts.\n\np: Indra hath tossed together mighty stores of wealth, and both the worlds, yea, and the Sun. Pure, brightly-shining, mingled with the milk, the draughts of Soma have made Indra glad.","people":["Indra","Soma","Visnu","KanVa","Mitra","Satakratu","Sakra","Maghavan","Aditya","Vivasvan","Trita","Ayu","Matarisvan"],"places":[],"things":["Milk","Lord","Soma","Offering","Sun","Wealth","Juice","Song","Joy","Strong","Mighty","Worshipper","Hymn","Songs","Cow","Horses","call","Amrta"],"groups":[],"concepts":["Good","Love","Offering"],"hash":"md5-Kmo/ASBF183Xndke6UKHgw==","created":"Monday, April 8, 2024 - 10:51:55 PM"},{"id":"198896aa-4a09-4c01-8735-875d9424f41e","key":"08097","book":"08","title":"HYMN V. Indra.","link":"https://indra.ai/rigveda/hymns/08097.html","text":"p: As highest of the Maghavans, preeminent among the Bulls, best breaker-down of forts, kine-winner, Lord of wealth, we seek thee, indra Maghavan.\n\np: Thou who subduedst Ayu, Kutsa, Atithigva, waxing daily in thy might, as such, rousing thy power, we invocate thee now, thee Satakratu, Lord of Bays.\n\np: The pressing-stones shall pour for us the essence of the meath of all, Drops that have been pressed out afar among the folk, and those that have been pressed near us.\n\np: Repel all enmities and keep thern far away: let all win treasure. for their own. Even among Sistas are the stalks that make thee glad, where thou with Soma satest thee.\n\np: Come, indra, very near to us with aids of firmly-based resolve; Come, most auspicious, with thy most auspicious help, good Kinsman, with good kinsmen, come!\n\np: Bless thou with progeny the chief of men, the lord of heroes, victor in the fray. Aid with thy powers the men who sing thee lauds and keep their spirits ever pure and bright.\n\np: May we be such in battle as are surest to obtain thy grace: With holy offerings and invocations of the Devas, we mean, that we may win the spoil.\n\np: Thine, Lord of Bays, am I. Prayer longeth for the spoil. Still with thy help I seek the fight. So, at the raiders' head, I, craving steeds and kine, unite myself with thee alone.","people":["Indra","Soma","Satakratu","Maghavan","Kutsa","Atithigva","Ayu"],"places":[],"things":["Meath","Steeds","Lord","Soma","Treasure","Wealth","Men","Might","Help","Chief","Heroes","Pressing-Stones","Lord of Bays","Powers","Offerings","Drops","spoil"],"groups":["Devas","Progeny"],"concepts":["Good","Holy","Offerings","Auspicious","Winner"],"hash":"md5-5hKhbd51Apg8XR7LjRlOnA==","created":"Monday, April 8, 2024 - 10:51:55 PM"},{"id":"ba992226-b1c4-4a91-a3a7-157aa4b0addf","key":"08098","book":"08","title":"HYMN VI. Indra.","link":"https://indra.ai/rigveda/hymns/08098.html","text":"p: INDRA, the poets with. their hymns extol this hero might of thine: They strengthened, loud in song, thy power that droppeth oil. With hymns the Pauras came to thee.\n\np: Through piety they came to Indra for his aid, they whose libations give theejoy. As thou with, Krsa and Samvarta hast rejoiced, so, indra, be thou glad with us.\n\np: Agreeing in your spirit, all ye Deities, come nigh to us. Vasus and Rudras shall come near to give us aid, and Maruts listen to our call.\n\np: May Pusan, Visnu, and Sarasvati befriend, and the Seven Streams, this call of mine: May Waters, Wind, the Mountains, and the Forest-Lord, and Earth give ear unto my cry.\n\np: Indra, with thine own bounteous gift, most liberal of the MightyOnes, be our boon benefactor, Vrtra conquerer, be our feast-companion for our weal.\n\np: Leader of heroes, Lord of battle, lead thou us to combat, thou Most Sapient One. High fame is theirs who win by invocations, feasts and entertainment of the Devas.\n\np: Our hopes rest on the Faithful One: in Indra is the people's life. O Maghavan, come nigh that tho. Mayst give us aid: make plenteous food stream forth for us.\n\np: Thee would we worship, indra, with our songs of praise: O Satakratu, be thou ours. Pour down upon Praskanva bounty vast and firm, exuberant, that shall never fail.","people":["Indra","Vrtra","Visnu","Satakratu","Maghavan","Pusan","Sarasvati","Praskanva"],"places":["Earth"],"things":["Worship","Leader","Lord","Mountains","Waters","Boon","Food","Streams","Stream","Might","Song","Praise","Heroes","Gift","People","Libations","Songs","Hero","call","Life","Spirit"],"groups":["Devas","Maruts","Rudras","Deities","MightyOnes","Vasus"],"concepts":["Life","Libations"],"hash":"md5-6hcgI2gQzFoU43sMr/8P+w==","created":"Monday, April 8, 2024 - 10:51:56 PM"},{"id":"a990ea1e-68d0-4eec-b2f1-31f9811359ac","key":"08099","book":"08","title":"HYMN VII. Praskanva's Gift.","link":"https://indra.ai/rigveda/hymns/08099.html","text":"p: GREAT, verily, is Indra's might. I have beheld, and hither comes Thy bounty, Dasyave-vrka!\n\np: A hundred oxen white of hue are shining like the stars in heaven, So tall, they seem to prop the sky.\n\np: Bamboos a hundred, a hundred dogs, a hundred skins of beasts well-tanned, a hundred tufts of Balbaja, four hundred red-hued mares are mine.\n\np: Blest by the Devas, Kinvayanas! be ye who spread through life on life: Like horses have ye stridden forth.\n\np: Then men extolled the team of seven not yet full-grown, its fame is great. The dark mares rushed along the paths, so that no eye could follow them.","people":["Indra"],"places":["Heaven","Sky"],"things":["Men","Might","Horses","Life"],"groups":["Devas"],"concepts":["Life"],"hash":"md5-7k6/HjlGuVcnqf/A41AnIQ==","created":"Monday, April 8, 2024 - 10:51:56 PM"},{"id":"b9990fd1-be9a-49a1-9cff-ac64d5216b6e","key":"08100","book":"08","title":"HYMN VIII Praskanva's Go.","link":"https://indra.ai/rigveda/hymns/08100.html","text":"p: THY bounty, Dasyave-vrka, exhaustless hath displayed itself: Its fulness is as broad as heaven.\n\np: Ten thousand Dasyave-vrka, the son of Putakrata, hath From his own wealth bestowed on me.\n\np: A hundred asses hath he given, a hundred head of fleecy sheep, a hundred slaves, and wreaths besides.\n\np: There also was a mare led forth, picked out for Putakrata's sake, Not of the horses of the herd.\n\np: Observant Agni hath appeared, oblation-bearer with his car. Agni with his resplendent flame hath shone on high as shines the Sun, hath shone like Surya in theheavens.","people":["Agni","Surya"],"places":["Heaven"],"things":["Sun","Wealth","Car","Horses"],"groups":["Son"],"concepts":[],"hash":"md5-iv6MCiHwkeBY9IB43C5yNg==","created":"Monday, April 8, 2024 - 10:51:56 PM"},{"id":"7cdd90dc-ca76-497b-9c21-15db74da67aa","key":"08101","book":"08","title":"HYMN IX. Asvins.","link":"https://indra.ai/rigveda/hymns/08101.html","text":"p: ENDOWED, O Devas, with your primeval wisdom, come quickly with your chariot, O ye Holy. Come with your mighty powers, O ye Nasatyas; come hither, drink ye this the third libation.\n\np: The truthful Deities, the Three-and-Thirty, s w you approach before the Ever-Truthful. Accepting this our worship and libation, O Asvins bright with fire, drink ye the Soma.\n\np: Asvins, that work of yours deserves our wonder.the Bull of heaven and earth and air's mid region; Yea, and your thousand promises in battle, -to all of these come near and drink beside us.\n\np: Here is your portion laid for you, ye Holy: come to these songs of ours, O ye Nasatyas. Drink among us the Soma full of sweetness, and with your powers assist the man who worships.","people":["Soma","Asvins","Nasatyas"],"places":["Earth","Heaven"],"things":["Worship","Work","Soma","Air","Mighty","Powers","Songs"],"groups":["Devas","Deities","Man"],"concepts":["Holy","Wisdom","Truthful"],"hash":"md5-VD7eNf9qAmTBl3gmatlhqg==","created":"Monday, April 8, 2024 - 10:51:56 PM"},{"id":"f8f77d28-6123-49dc-86b4-540dba323691","key":"08102","book":"08","title":"HYMN X, Devas.","link":"https://indra.ai/rigveda/hymns/08102.html","text":"p: HE whom the monks in sundry ways arranging  'the offering, of one accord, bring hither, who was appointed as a learned Brahman, -what is  'theofferings knowledge of him?\n\np: Kindled in many a spot, still One is Agni; Silrya is One though high o’er all he shineth. Illumining this All, still One is usas. That which is One hath into All developed.\n\np: The chariot bright and radiant, treasure.-laden, three-wheeled, with easy seat, and lightly rolling, Which She of Wondrous Wealth was born to harness.this car of yours I call. Drink what remaineth.","people":["Agni","Usas"],"places":[],"things":["Born","Offering","Treasure","Wealth","Car","call"],"groups":["Monks"],"concepts":["Offering"],"hash":"md5-G3MQYCZxuyjugePeDmLyOg==","created":"Monday, April 8, 2024 - 10:51:56 PM"},{"id":"fa451a7b-ed31-4432-957b-ac517238735b","key":"08103","book":"08","title":"HYMN XI. Indra-Varuna.","link":"https://indra.ai/rigveda/hymns/08103.html","text":"p: IN offerings poured to you, O Indra-Varuna, these shares of yours stream forth to glorify your state. Ye haste to the libations at each offering when ye assist the worshipper who sheds the juice.\n\np: The waters and the plants, O Indra-Varuna, had efficacious vigour, and attained to might: Ye who have gone beyond the path of middle air.no godless man is worthy to be called your foe.\n\np: True is your Krsa's word, indra and Varuna: The seven holy voices pour a wave of meath. For their sake, Lords of splendour! aid the pious man who, unbewildered, keeps you ever in his thoughts.\n\np: Dropping oil, sweet with Soma, pouring forth their stream, are the Seven Sisters in the seat of offering. These, dropping oil, are yours, O Indra-Varuna: with these enrich with gifts and help the worshipper.\n\np: To our great happiness have we ascribed to these Two Bright Ones truthfulness, great strength, and majesty. O Lords of splendour, aid us through the Three-times-Seven, as we pour holy oil, O Indra-Varuna.\n\np: What ye in time of old Indra and Varuna, gave Rsis revelation, thought, and power of song, and places which the wise made, weaving offering.these through my spirit's fervid glow have I beheld.,\n\np: O Indra-Varuna, grant to the worshippers cheerfulness void of pride, and wealth to nourish them.","people":["Indra","Soma","Varuna"],"places":[],"things":["Meath","Soma","Waters","Offering","Air","Wealth","Stream","Might","Juice","Song","Help","Wise","Worshipper","Splendour","Offerings","Libations","Truthfulness","Spirit","Gifts"],"groups":["Worshippers","Rsis","Man"],"concepts":["Holy","Strength","Offering","Offerings","Libations"],"hash":"md5-x1nBsDyYtxjEd+JiYZuPJQ==","created":"Monday, April 8, 2024 - 10:51:56 PM"}],"copyright":"©2023 Quinn Michaels (indra.ai). All rights reserved.","created":"Monday, April 8, 2024 - 10:51:52 PM"}