{"id":"a8e9fd50-066b-4f6a-9f6d-983301619c89","key":"09","link":"https://indra.ai/rigveda/books/09.html","hymns":[{"id":"79a6c762-21d9-47a8-8319-7f40d73efc61","key":"09001","book":"09","title":"HYMN I. Indu Pavamana.","link":"https://indra.ai/rigveda/hymns/09001.html","text":"p: In sweetest and most gladdening stream flow pure, O Soma, on thy way, pressed out for Indra, for his drink.\n\np: Friend of all men, he hath with the wood attained unto His place, his iron-fashioned home.\n\np: Be thou best Vrtra conquerer, best granter of bliss, most liberal: Promote our wealthy princes' gifts.\n\np: Flow onward unto the banquet of the Mighty Devas.\n\np: O Indu, we draw nigh to thee, with this one object day by day.\n\np: By means of this eternal fleece. May Surya's Daughter purify Thy Soma that is foaming forth.\n\np: Ten Sister Maids of slender form seize him within the press and hold Him firmly on the final day.\n\np: The virgins send him forth, and fuse The triple foe-repelling meath.\n\np: Inviolable for Indra's drink, the fresh young Indu.\n\np: In this draught, he, the Hero, pours his wealth on us.","people":["Indu","Indra","Soma","Vrtra","Surya"],"places":[],"things":["Meath","Soma","Iron-Fashioned Home","Wealth","Men","Stream","Flow","Home","Mighty","Banquet","Form","Bliss","Friend","Hero","Gifts"],"groups":["Devas","Sister","Ten Sister Maids"],"concepts":[],"hash":"md5-eV/CTALsqWW+90hLHwihuw==","created":"Monday, April 8, 2024 - 10:51:52 PM"},{"id":"3a02f6a6-fcda-482b-b942-d4c60353a8b2","key":"09002","book":"09","title":"HYMN II. Indu Pavamana.","link":"https://indra.ai/rigveda/hymns/09002.html","text":"p: Soma, flow on, inviting Devas, speed to the purifying cloth: Pass into Indra, as a Bull.\n\np: As mighty food speed hitherward, Indu, as a most splendid Steer: Sit in thy place as one with strength.\n\np: The well-loved was made to flow, the stream of the creative juice drew waters to himself.\n\np: The mighty waters, yea, the floods accompany thee Mighty One.\n\np: The lake is brightened in the floods. heaven's prop and stay, Falls on the purifying cloth.\n\np: The tawny Bull hath bellowed, He shines together with the Sun.\n\np: Songs, Indu, active in their might are beautified for thee, where thou deckest thee for our delight.\n\np: To thee who givest ample room we meditate. Great are the praises due to thee.\n\np: Indu as, indra's Friend, on us pour with a stream of sweetness, like Parjanya sender of the rain.\n\np: Winner of kine, Indu, art thou, winner of heroes, steeds, and strength Primeval Soul of Offerings.","people":["Indu","Indra","Soma","Parjanya"],"places":["Heaven"],"things":["Steeds","Soma","Waters","Sun","Food","Stream","Flow","Might","Juice","Rain","Mighty","Delight","Heroes","Creative","Lake","Offerings","Songs","Friend"],"groups":["Devas"],"concepts":["Strength","Offerings","Winner"],"hash":"md5-9HZvBDS8GJpsPrkNtJnAaQ==","created":"Monday, April 8, 2024 - 10:51:52 PM"},{"id":"d7c297a6-1968-42ab-9956-3a6252939d16","key":"09003","book":"09","title":"HYMN III. Indu Pavamana.","link":"https://indra.ai/rigveda/hymns/09003.html","text":"p: HERE present this Immortal Deva.flies, like a bird upon her wings, to settle in the vats of wood.\n\np: This Deva, made ready with the hymn, runs swiftly through the winding ways, inviolable as he flows.\n\np: This Deva.while flowing is adorned by men Devout and skilled in holy songs.\n\np: He, like a warrior going forth with heroes, as he flows along is fain to win all precious boons.\n\np: This Deva, as he is flowing on, speeds like a car and gives his gifts. He lets his voice be heard of all\n\np: Praised by the sacred bards, this Deva dives into waters, and bestows gifts upon the worshipper.\n\np: Away he rushes with his stream, across the regions into heaven, and roars as he is flowing on.\n\np: While flowing, meet for offering, he hath gone up to heaven across the regions, irresistible.\n\np: After the way of ancient time, this Deva, pressed out flows tawny to the straining-cloth.\n\np: This Lord of many Holy Laws, even at his birth engendering strength flows onward in a stream.","people":["Deva"],"places":["Heaven"],"things":["Lord","Waters","Offering","Men","Stream","Car","Voice","Worshipper","Hymn","Heroes","Songs","Wings","Warrior","Bird","Gifts"],"groups":["Immortal"],"concepts":["Birth","Immortal","Holy","Sacred","Strength","Devout","Offering"],"hash":"md5-zvBVszIDS0e8Df8Em4BUMQ==","created":"Monday, April 8, 2024 - 10:51:52 PM"},{"id":"48a67e6c-8e2c-4ed0-910c-64e00c4313ec","key":"09004","book":"09","title":"HYMN IV. Indu Pavamana.","link":"https://indra.ai/rigveda/hymns/09004.html","text":"p: O Indu, flowing on thy way. Make us better than we are.\n\np: Win thou the light, win heavenly light. Make us better than we are.\n\np: Win skilful strength and mental power, O Indu. Make us better than we are.\n\np: Ye purifiers for his drink. Make us better than we are.\n\np: Give us our portion in the Sun. Make us better than we are.\n\np: Through thine own mental power. Make us better than we are.\n\np: Pour to us a stream of riches doubly great renown. Make us better than we are.\n\np: As one victorious unsubdued in battle. Make us better than we are.\n\np: With offerings, pavamana! men have strengthened thee to prop the Law. Make us better than we are.\n\np: O Indu, bring us true wealth, manifold, quickening all life. Make us better than we are.","people":["Indu","Pavamana"],"places":[],"things":["Light","Sun","Wealth","Men","Stream","Offerings","Riches","Life"],"groups":[],"concepts":["Life","Heavenly","Strength","Offerings"],"hash":"md5-yIDPXiAxx+q+/fVu2r0www==","created":"Monday, April 8, 2024 - 10:51:52 PM"},{"id":"a6b4c9b2-2178-474a-b1fe-8af14ee6583c","key":"09005","book":"09","title":"HYMN V Apris.","link":"https://indra.ai/rigveda/hymns/09005.html","text":"p: ENKINDLED, pavamana, Lord, sends forth his light on every side In friendly show, the bellowing Bull.\n\np: He, pavamana, Self-produced, speeds onward sharpening his horns: He glitters through the firmament.\n\np: Brilliant like wealth, adorable, with splendour Pavamana shines, Mightily with the streams of meath.\n\np: The tawny Pavamana, who strews from of old the grass with might, is honored, Deva amid the Devas.\n\np: The golden, the Celestial Doors are lifted with their frames on high, by Pavamana glorified.\n\np: With passion Pavamana longs for the great lofty pair, well-formed Like beauteous maidens, Night and Dawn\n\np: Both Devas who look on men I call, Celestial Heralds, indra's Self Is Pavamana, yea, the Bull.\n\np: This, pavamana's offering, shall the three beauteous Devas, Sarasvati and Bharati and Ila, Mighty One, attend.\n\np: 1 summon Tvastar hither, our protector, champion earliest-born, Indu is Indra, Pavamana is Prajapati.\n\np: O Pavamana, with the meath in streams anoint Vanaspati, the ever-green. the golden-hued, refulgent, with a thousand boughs.\n\np: Come to the consecrating rite of Pavamana, all ye Devas. Vayu, Surya, Narasamsa, indra, and Agni, in accord.","people":["Indu","Pavamana","Indra","Agni","Vayu","Narasamsa","Tvastar","Bharati","Sarasvati","Deva","Surya","Ila","Dawn","Prajapati","Vanaspati"],"places":["Firmament"],"things":["Meath","Lord","Born","Offering","Light","Wealth","Men","Streams","Might","Mighty","Grass","Adorable","Splendour","call"],"groups":["Devas"],"concepts":["Celestial","Offering"],"hash":"md5-2o/NnIsRL3+/AztO/j+Gxg==","created":"Monday, April 8, 2024 - 10:51:52 PM"},{"id":"e5eae2af-e42c-4c7b-937e-fd80c37c79c0","key":"09006","book":"09","title":"HYMN VI. Indu Pavamana.","link":"https://indra.ai/rigveda/hymns/09006.html","text":"p: Indu, flow on with pleasant stream, to the Devas, Our Friend, unto the woollen sieve.\n\np: Pour hitherward, as Indra's Self, Indu, that gladdening stream of thine.\n\np: Flow to the filter hitherward, pouring that ancient gladdening juice, Streaming forth power and high renown.\n\np: Hither the sparkling drops have flowed, like waters down a steep descent, they have reached Indra purified.\n\np: Whom, having passed the filter, While he disports him in the wood.\n\np: The juice pour forth, for offering and service of the Devas, to him who bears away the draught.\n\np:  Effused, the Deva.flows onward with his stream to Indra, to the Deva, so that his will may strengthen him.\n\np: Soul of  'the offering, the juice effused flows quickly on, he keeps his ancient wisdom of a Sage.\n\np: So pouring forth, as Indra's Friend, best Gladdener! For the banquet, even in secret, he storest hymns.","people":["Indu","Indra","Deva"],"places":[],"things":["Waters","Offering","Stream","Flow","Juice","Banquet","Drops","Friend","Sage"],"groups":["Devas"],"concepts":["Wisdom","Offering"],"hash":"md5-BhlKplyGgFNEQWjwBXjkWQ==","created":"Monday, April 8, 2024 - 10:51:52 PM"},{"id":"f9c049f4-4b40-4715-a4c2-931b7cb70b1e","key":"09007","book":"09","title":"HYMN VII. Indu Pavamana.","link":"https://indra.ai/rigveda/hymns/09007.html","text":"p: FORTH on their way the glorious drops have flowed for maintenance of Law, knowing the offerings course.\n\np: Down in the mighty waters sinks the stream, most excellent, oblation best of all in worth.\n\np: About the holy place, the true, guileless, noblest, hath sent forth Continuous voices in the wood.\n\np: When, clothed in manly strength, the Sage flows in celestial wisdom round the strong would win the light of heaven.\n\np: When purified, he sits as King above the hosts, among his folk.\n\np: Dear, golden-coloured, in the fleece he sinks and settles in the wood. The Singer shows his zeal in hymns.\n\np: He goes to Indra, Vayu, to the Asvins, as his custom is, with gladdening juice which gives them joy.\n\np: Tle streams of pleasant Soma flow to Bhaga, Mitra and Varuna. Well-knowing through his mighty powers. Heaven and Earth, riches of meath to win us wealth: Gain for us treasure.s and renown.","people":["Indra","Soma","Vayu","Mitra","Varuna","Asvins","Bhaga"],"places":["Earth","Heaven"],"things":["Meath","Soma","Waters","Glorious","Singer","Light","Treasure","Wealth","Streams","Stream","Flow","Juice","Joy","Strong","Mighty","Excellent","Powers","Offerings","Drops","King","Sage","Riches"],"groups":[],"concepts":["Celestial","Holy","Strength","Wisdom","Offerings","Glorious"],"hash":"md5-vJ2h7KZDVE4GimE8yq6L/w==","created":"Monday, April 8, 2024 - 10:51:52 PM"},{"id":"04057404-937d-47ba-883c-329be499dbb7","key":"09008","book":"09","title":"HYMN VIII. Indu Pavamana.","link":"https://indra.ai/rigveda/hymns/09008.html","text":"p: OBEYING Indra's dear desire these Soma juices have flowed forth, increasing his heroic might.\n\np: Laid in the bowl, pure-flowing on to Vayu and the Asvins. May These give us great heroic strength.\n\np: Indu, incite to bounty Indra's heart, to sit in place of offering.\n\np: The ten swift fingers deck thee forth, seven ministers impel thee on. The sages have rejoiced in thee.\n\np: When through the filter thou art poured to be a gladdening draught for Devas.\n\np: When purified within the jars, Soma, brightred and golden-hued, Hath clothed him with a robe of milk.\n\np: Flow on to us and make us wealthy. O Indu, flow into thy friend, send down the rain from heaven, a stream of opulence from earth.Give us victory\n\np: May we obtain thee, indra's drink, who viewest men and findest light, Gain thee, and progeny and food.","people":["Indu","Indra","Soma","Vayu","Asvins"],"places":["Earth","Heaven"],"things":["Victory","Milk","Soma","Offering","Light","Food","Men","Stream","Flow","Might","Rain","Friend"],"groups":["Devas","Progeny"],"concepts":["Heroic","Strength","Offering","Swift"],"hash":"md5-d+8wJI2prS3biS357ETfuA==","created":"Monday, April 8, 2024 - 10:51:52 PM"},{"id":"535d3bc4-fc28-4356-9901-df0b73245973","key":"09009","book":"09","title":"HYMN IX. Indu Pavamana.","link":"https://indra.ai/rigveda/hymns/09009.html","text":"p: THE Sage of Heaven whose heart is wise, when laid between both hands and pressed, Sends us delightful powers of life.\n\np: On, onward to a glorious home; dear to the people void of guile, with excellent enjoyment, flow.\n\np: He, the bright Son, when born illumed his Parents who had sprung to life, Great Son great Strengtheners of Law.\n\np: Urged by the seven devotions he hath stirred the guileless rivers which Have magnified the Single Eye.\n\np: These helped to might theYouthful One, high over all, invincible, Indu, indra! in thy law.\n\np: The immortal Courser, good to draw, looks down upon the Seven: the fount Hath satisfied the Devas\n\np: Aid us in holy rites, O Man: O Pavamana, drive away Dark shades that must be met in fight.\n\np: Make the paths ready for a hymn newer and newer evermore. Make the lights shine as erst they shone.\n\np: Give, pavamana, high renown, give kine and hero sons, win for us wisdom, win the light.","people":["Indu","Pavamana","Indra"],"places":["Heaven"],"things":["Born","Rivers","Glorious","Shine","Light","Flow","Might","Home","Wise","Hymn","Excellent","People","Powers","Hero","Sage","Parents","Life"],"groups":["Devas","Sons","Son","Immortal","Man"],"concepts":["Good","Life","Immortal","Holy","Wisdom","Glorious"],"hash":"md5-jB6PPAo8pChndci9z068uw==","created":"Monday, April 8, 2024 - 10:51:52 PM"},{"id":"dac4b388-08a4-4043-9048-ce71177436eb","key":"09010","book":"09","title":"HYMN X. Indu Pavamana.","link":"https://indra.ai/rigveda/hymns/09010.html","text":"p: LIKE cars that thunder on their way, like coursers eager for renown, have Soma drops flowed forth for wealth.\n\np: Forth have they rushed from holding hands, like chariots that are urged to speedlike joyful songs of singing-men.\n\np: The Kings deck themselves with milk, as Kings are graced with eulogies, and, with seven monks,  'the offering.\n\np: Pressed for the gladdening draught, the drops flow forth abundantly with song, the Soma juices in a stream.\n\np: Winning Vivasvan's glory and producing Morning's light, the Suns Pass through the openings of the cloth.\n\np: The singing-men of ancient time open the doors of sacred songs. Men, for the mighty to accept.\n\np: Combined in close society sit the seven monks, the brother-hood, filling the station of the One.\n\np: He gives us kinship with the Devas, and with the Sun unites our eye. The Sage's offspring hath appeared.\n\np: The Sun with his dear eye beholds that quarter of the heavens which monks have placed within the sacred cell.","people":["Soma","Vivasvan"],"places":[],"things":["Milk","Soma","Chariots","Glory","Offering","Light","Sun","Wealth","Men","Stream","Flow","Song","Offspring","Mighty","Songs","Drops","Sage","Winning","Cars","Morning"],"groups":["Devas","Kings","Brother","Monks"],"concepts":["Cars","Sacred","Offering"],"hash":"md5-D7a1tdDkRB1wEs61gn1srQ==","created":"Monday, April 8, 2024 - 10:51:52 PM"},{"id":"fc1dc8bd-9a68-401f-9dce-cedba8cebde7","key":"09011","book":"09","title":"HYMN XL Indu Pavamana.","link":"https://indra.ai/rigveda/hymns/09011.html","text":"p: SING forth to Indu, O ye men, to him who is purified, fain to make offerings to the Devas.\n\np: Together with thy pleasant juice, Divine, devoted to the Deva.\n\np: Bring, by thy flowing, weal to kine, weal to the people, weal to steeds. Weal, O King, to growing plants.\n\np: Sing a praise-song to Soma brown of hue, of independent might. The Red, who reaches up to heaven.\n\np: Purify Soma when effused with stones which bands move rapidly, and pour the sweet milk in the meath.\n\np: With humble homage draw ye nigh; blend the libation with the curds: To Indra offer Indu up.\n\np: Soma, foe-que chief o’er men, doing the will of pour forth prosperity upon our kine.\n\np: Heart-knower, Sovran of the heart, thou art effused, O Indu, that Indra may drink thee and rejoice.\n\np: O Indu Pavamana, give us riches and heroic strength. Indu! with Indra for his ally.","people":["Indu","Pavamana","Indu Pavamana","Indra","Soma","Deva"],"places":["Heaven"],"things":["Meath","Milk","Steeds","Soma","Men","Might","Juice","Humble","Song","Chief","Praise","People","Offerings","King","Riches"],"groups":["Devas"],"concepts":["Divine","Heroic","Strength","Offerings"],"hash":"md5-Sm5fsJXgma0QE6+NvnQijg==","created":"Monday, April 8, 2024 - 10:51:52 PM"},{"id":"893bf967-a472-4bce-9d7c-5b4032da1016","key":"09012","book":"09","title":"HYMN XII. Indu Pavamana.","link":"https://indra.ai/rigveda/hymns/09012.html","text":"p: To Indra have the drops been poured, shed in the seat of offerings.\n\np: To Indra have the sages called, Called him to drink the Soma juice.\n\np: In the stream's wave wise Indu dwells, distilling rapture, in his seat.\n\np: Indu is worshipped in the central point Of heaven.\n\np: In close embraces Indu holds Soma when poured within the jars. \n\np: Indu sends forth a voice on high to regions of the sea of air, Shaking the vase that drops with meath.\n\np: The Tree whose praises never fail yields heavenly milk among our hymns.\n\np: The Wise One, with the Sage's stream, flows on to the dear places of the sky.\n\np: O Pavamana, bring us wealth bright with a thousand splendours. Yea. O Indu, give us ready help.","people":["Indu","Pavamana","Indra","Soma"],"places":["Heaven","Sky"],"things":["Meath","Milk","Soma","Air","Wealth","Stream","Juice","Help","Wise","Voice","Offerings","Drops","Sage"],"groups":[],"concepts":["Heavenly","Offerings","Worshipped"],"hash":"md5-nMtx5vH+lP2aHJ424+KwNw==","created":"Monday, April 8, 2024 - 10:51:52 PM"},{"id":"3a5888de-cc9b-46d9-aaf1-230c484b8ad6","key":"09013","book":"09","title":"HYMN XIII. Indu Pavamana.","link":"https://indra.ai/rigveda/hymns/09013.html","text":"p: PASSED through, the fleece in thousand streams the Soma, purified, flows on To Indra's, Viyu's special place.\n\np: Sing forth, ye men who long for help, to Pavamana, to the Sage, Effused to entertain the Devas.\n\np: The Soma-drops with thousand powers are purified for victory, Hymned to become the feast of Devas.\n\np: Yea, as thou flowest bring great store of food that we may win the spoil Indu, bring splendid manly might.\n\np: May they in flowing give us wealth in thousands, and heroic power. These Deva like Soma-drops effused.\n\np: Like coursers by their drivers urged, they were poured forth, for victory, Swift through the woollen straining-cloth.\n\np: Noisily flow the Soma-drops, like milch-kine lowing to their calves: They have run forth from both the hands.\n\np: As Gladdener whom Indra loves, O Pavamana, with a roar Drive all our enemies away.\n\np: O Pavamamas, driving off the godless, looking on the light, Sit in the place of offering.","people":["Indu","Pavamana","Indra","Soma","Deva"],"places":[],"things":["Victory","Soma","Offering","Light","Wealth","Food","Men","Streams","Flow","Might","Help","Powers","Drops","Sage","spoil"],"groups":["Devas"],"concepts":["Heroic","Special","Offering","Swift"],"hash":"md5-9u9M1EWF98XtQV4RV+eFSw==","created":"Monday, April 8, 2024 - 10:51:52 PM"},{"id":"af800ffd-e464-41e9-a0a0-78450b09c61e","key":"09014","book":"09","title":"HYMN XIV. Indu Pavamana.","link":"https://indra.ai/rigveda/hymns/09014.html","text":"p: REPOSING on the river's wave the Sage hath widely flowed around, bearing the hymn which many love.\n\np: When the Five kindred Companies, active in duty, with the song Establish him, the Powerful,\n\np: Then in his juice whose strength is great, have all the Devas rejoiced themselves, when he hath clothed him in the milk.\n\np: Freeing himself he flows away, leaving his body's severed limbs, and meets his own Companion here.\n\np: He by the daughters of the priest, like a fair youth, hath been adorned, Making the milk, as ’twere, his robe.\n\np: O'er the fine fingers, through desire of milk, in winding course he goes, and utters voice which he hath found.\n\np: The nimble fingers have approached, adorning him the Lord of Strength: They grasp the vigorous Courser's back.\n\np: Comprising all the treasure.s that are in the heavens and on the earth, Come, Soma, as our faithful Friend.","people":["Soma"],"places":["Earth"],"things":["Milk","Lord","Soma","Treasure","River","Juice","Song","Voice","Hymn","Friend","Sage"],"groups":["Devas"],"concepts":["Love","Strength","Powerful"],"hash":"md5-N9FBNl+Mrr2RqbEGAu72mw==","created":"Monday, April 8, 2024 - 10:51:52 PM"},{"id":"d76ce1bb-4582-405f-832b-42c7273d6111","key":"09015","book":"09","title":"HYMN XV. Indu Pavamana.","link":"https://indra.ai/rigveda/hymns/09015.html","text":"p: THROUGH the fine fingers, with the song, this Hero comes with rapid ears, Going to Indra's special place.\n\np: In holy thought he ponders much for the great worship of the Devas. Where the Immortals have their seat.\n\np: Like a good horse is he led out, when on the path that shines with light The mettled steeds exert their strength.\n\np: He brandishes his horns on high, and whets them Bull who leads the herd, Doing with might heroic deeds.\n\np: He moves, a vigorous Steed, adorned with beauteous rays of shining gold, becoming Sovran of the streams.\n\np: He, over places rough to pass, bringing rich treasure.s closely packed. Descends into the reservoirs.\n\np: Men beautify him in the vats, him worthy to be beautifiedhim who brings forth abundant food.\n\np: Him, even him, the fingers ten and the seven songs make beautiful, well-weaponed, best of gladdeners.","people":["Indra"],"places":[],"things":["Worship","Steeds","Light","Treasure","Food","Men","Streams","Might","Song","Gold","Songs","Hero","Horse"],"groups":["Devas"],"concepts":["Good","Beautiful","Heroic","Special","Holy","Strength"],"hash":"md5-B5wAPiBag2OukAA82QYGyQ==","created":"Monday, April 8, 2024 - 10:51:52 PM"},{"id":"cd92a0b4-60ff-4ce4-bae1-05aae885777b","key":"09016","book":"09","title":"HYMN XVI. Indu Pavamana.","link":"https://indra.ai/rigveda/hymns/09016.html","text":"p: THE pressers from the Soma-press send forth thy juice for rapturous joy The speckled sap runs like a flood.\n\np: With strength we follow through the sieve him who brings might and wins the kine, Enrobed in water with his juice.\n\np: Pour on the sieve the Soma, ne’er subdued in waters, waterless, and make it pure for Indra's drink.\n\np: Moved by the purifier's thought, the Soma flows into the sieve: By wisdom it hath gained its home.\n\np: With humble homage, indra, have the Soma-drops flowed forth to thee, Contending for the glorious prize.\n\np: Purified in his fleecy garb, attaining every beauty, he Stands, hero-like, amid the kine.\n\np: Swelling, as ’twere, to heights of heaven, the stream of the creative juice Falls lightly on the cleansing sieve.\n\np: Thus, Soma, purifying himwho knoweth song mid living men, Thou wanderest through the cloth of wool.","people":["Indra","Soma"],"places":["Heaven"],"things":["Soma","Waters","Water","Glorious","Men","Stream","Might","Juice","Humble","Song","Joy","Beauty","Home","Creative","Drops","Hero"],"groups":[],"concepts":["Strength","Wisdom","Glorious"],"hash":"md5-MPQo26Wtr0f9sGnEkIPhRA==","created":"Monday, April 8, 2024 - 10:51:52 PM"},{"id":"bc14f6f6-8c5c-438e-bbac-eabff35d0864","key":"09017","book":"09","title":"HYMN XVII. Indu Pavamana.","link":"https://indra.ai/rigveda/hymns/09017.html","text":"p: LIKE rivers down a steep descent, subduing the Vrtras, full of zeal, the rapid Soma-streams have flowed.\n\np: The drops of Soma juice effused fall like the rain upon the earth: To Indra flow the Soma-streams.\n\np: With swelling wave the gladdening drink, the Soma, flows intothe sieve, Loving the Devas and subduing fiends.\n\np: It hastens to the pitchers, poured upon the sieve it waxes strong At offers through the lauds.\n\np: Soma, thou shinest mounting heaven as ’twere above light's triple realm, and moving secm'st to speed the Sun.\n\np: To him, the head of sacnfice, singers and bards have sung their songs, Offering what he loves to see.\n\np: The men, the sages with their hymns, eager for help, deck thee strong &teed, Deck thee for service of the Devas.\n\np: Flow onward to the stream of meath rest efficacious in thy home, Fair, to be drunk at offering.","people":["Indra","Soma"],"places":["Earth","Heaven"],"things":["Meath","Rivers","Soma","Offering","Light","Sun","Men","Streams","Stream","Flow","Juice","Rain","Help","Home","Strong","Offers","Songs","Drops"],"groups":["Devas","Vrtras"],"concepts":["Offering"],"hash":"md5-ZC2qzMxGf1ZkndYKA6AGnA==","created":"Monday, April 8, 2024 - 10:51:52 PM"},{"id":"849ad9ae-7df7-4275-9015-dae91819ced5","key":"09018","book":"09","title":"HYMN XVIII. Indu Pavamana.","link":"https://indra.ai/rigveda/hymns/09018.html","text":"p: THOU, Soma, dweller on the hills, effused, hast flowed into the sieve,: All-bounteous art thou in carouse.\n\np: Thou art a sacred Bard, a Sage; the meath is offipring of thy sap: All-bountcous art thou in carouse.\n\np: All Deities of one accord have come that the, may drink of thee: All-bounteous art thou in carouse.\n\np: He who containeth in his hands all treasure.s much to be desired: All-bounteous art thou in carouse.\n\np: Who milketh out this mighty Pair, the Earth and Heaven, like mother kine All-bounteous art thou in carouse.\n\np: Who in a moment mightily floweth around these two world-halvcs: All-bounteous art thou in carouse.\n\np: The Strong One, being purified, hath in the pitchers cried aloud: All-bounteous art thou in carouse.","people":["Soma"],"places":["Earth","Heaven"],"things":["Meath","Soma","Treasure","Strong","Mighty","Sage"],"groups":["Deities","Mother"],"concepts":["Sacred"],"hash":"md5-ysos15gNW7GQBWUxDiYbqg==","created":"Monday, April 8, 2024 - 10:51:53 PM"},{"id":"f0be4775-9257-40ea-93d0-6cd9f82e3b8a","key":"09019","book":"09","title":"HYMN XIX. Indu Pavamana.","link":"https://indra.ai/rigveda/hymns/09019.html","text":"p: O SOMA, being purified bring us the wondrous treasure., meet For lauds, that is in earth and heaven.\n\np: For ye Twain, indra, Soma, are Lords of the light, Lords of the kine: Great Rulers, prosper ye our songs.\n\np: The tawny Steer, while cleansed among the living, bellowing on the grass, Hath sunk and settled in his home.\n\np: Over the Steer's productive flow the sacred songs were resonant, the mothers of the darling Son.\n\np: Hath he not, purified, impregned the kine whb long to meet their Lord, the kine who yield the shining milk?\n\np: Bring near us those who stand aloof strike fear into our enemies: O Pavamana, find us wealth.\n\np: Soma, bring down the foeman's might, his vigorous strength and vital powe'r, Whether he be afar or near.","people":["Pavamana","Indra","Soma"],"places":["Earth","Heaven"],"things":["Milk","Lord","Soma","Light","Treasure","Wealth","Flow","Might","Home","Grass","Songs"],"groups":["Son"],"concepts":["Sacred","Strength"],"hash":"md5-0JgqIu7YuPSi9DKukGx3iA==","created":"Monday, April 8, 2024 - 10:51:53 PM"},{"id":"fad43176-65d9-4109-b5bf-bb5f4e21f0a2","key":"09020","book":"09","title":"HYMN XX Indu Pavamana.","link":"https://indra.ai/rigveda/hymns/09020.html","text":"p: FORTH through the straining-cloth the Sage flows to the banquet of the Devas, Subduing all our enemies.\n\np: For he, as Pavamana, sends thousandfold treasure. in the shape Of cattle to the singing-men.\n\np: Thou graspest all things with thy mind, and purifiest thee with thoughts As such, O Soma, find us fame.\n\np: Pour lofty glory on us, send sure riches to our liberal lords, Bring food to those who sing thy praise.\n\np: As thou art cleansed, O Wondrous Steed, O Soma, thou hast entered, like a pious King, into the songs.\n\np: He, Soma, like a courser in the floods invincible, made clean With hands, is resting in the jars.\n\np: Disporting, like a liberal chief, thou goest, Soma, to the sieve, Lending the laud a Hero's strength.","people":["Pavamana","Soma"],"places":[],"things":["Soma","Glory","Treasure","Food","Men","Banquet","Chief","Praise","Songs","Hero","King","Sage","Riches","Cattle"],"groups":["Devas"],"concepts":["Strength"],"hash":"md5-D4OzsCT9zm/GC99fuWFgTw==","created":"Monday, April 8, 2024 - 10:51:53 PM"},{"id":"28cfc101-6ce1-4bc5-ac9a-d1c6a0fe67cb","key":"09021","book":"09","title":"HYMN XXI. Indu Pavamana.","link":"https://indra.ai/rigveda/hymns/09021.html","text":"p: To Indra flow these running drops, these Somas frolicsome in mood. Exhilarating, finding light;\n\np: Driving off foes, bestowing room upon the presser, willingly Bringing their praiser vitalforce.\n\np: Lightly disporting them, the drops flow to one common reservoir, and fall into the river's wave.\n\np: These Pavamanas have obtained all blessings much to be desiredlike coursers harnessed to a car.\n\np: With view to us, O Soma-drops, bestow his manifold desire On him who yet hath given us naught.\n\np: Bring us our wish with this design, as a wright brings his new-wrought wheel: Flow pure and shining with the stream.\n\np: These drops have cried with resonant voice: like swift steeds they have run the course, and roused the good man's hymn to life.","people":["Indra","Soma"],"places":[],"things":["Steeds","Soma","Light","River","Stream","Flow","Car","Reservoir","Voice","Hymn","Drops","Life","Wheel"],"groups":["Man"],"concepts":["Good","Life","Blessings","Swift"],"hash":"md5-K66cLfyVwFQKdfj+Pvbcww==","created":"Monday, April 8, 2024 - 10:51:53 PM"},{"id":"a3841de7-705a-4e16-adc4-21a86add2b05","key":"09022","book":"09","title":"HYMN XXII. Indu Pavamana.","link":"https://indra.ai/rigveda/hymns/09022.html","text":"p: THESE rapid Soma-streams have stirred themselves to motion like strong steedslike cars, like armies hurried forth.\n\np: Swift as wide winds they lightly move, like rain-storms of Parjanya, like The flickering flames of burning fire.\n\np: These Soma juices, blent with curds, purified, skilled in sacred hymns, have gained by song their hearts'desire.\n\np: Immortal, cleansed, these drops, since first they flowed, have never wearied, fain To reach the regions and their paths.\n\np: Advancing they have travelled o’er the ridges of the earth and heaven, and this the highest realm of all.\n\np: Over the heights have they attained the highest thread that is spun out, and this which must be deemed most high.\n\np: Thou, Soma, boldest wealth in kine which thou hast seized from niggard churls: Thou calledst forth the outspun thread.","people":["Soma","Parjanya"],"places":["Earth","Heaven"],"things":["Soma","Wealth","Streams","Rain","Song","Strong","Armies","Drops","Cars"],"groups":["Immortal"],"concepts":["Cars","Immortal","Flickering","Sacred","Swift"],"hash":"md5-BD8vPp7NdL6lXVGZaWrvWA==","created":"Monday, April 8, 2024 - 10:51:53 PM"},{"id":"14949bf7-9485-40b6-8340-a09bda2166e6","key":"09023","book":"09","title":"HYMN XXIII. Indu Pavamana.","link":"https://indra.ai/rigveda/hymns/09023.html","text":"p: SWIFT Soma drops have been effused in streams of meath, the gladdening drink, for sacred lore of every kind.\n\np: Hither to newer. resting-place the ancient Living Ones are come. They made the Sun that he might shine.\n\np: O Pavamana, bring to us the unsacrificing foeman's wealth, and give us food with progeny.\n\np: The living Somas being cleansed diffuse exhilarating drink, Turned to the vat which drips with meath.\n\np: Soma gows on intelligent, possessing sap and mighty strength, Brave Hero who repels the curse.\n\np: For Indra, Soma! thou art cleansed, a feast-companion for the Devas:\n\np: ndu, thou fain wilt win us strength\n\np: When he had drunken draughts of this, indra smote down resistless foes: Yea, smote them, and shall smite them still.","people":["Pavamana","Indra","Soma"],"places":[],"things":["Meath","Soma","Shine","Sun","Wealth","Food","Streams","Might","Mighty","Brave","Drops","Hero"],"groups":["Devas","Progeny"],"concepts":["Sacred","Strength","Swift"],"hash":"md5-4wuB4TxQkQ0GcLq6i7kaTw==","created":"Monday, April 8, 2024 - 10:51:53 PM"},{"id":"1fd2a09b-5d85-476b-aed5-aa840204313a","key":"09024","book":"09","title":"HYMN XXIV. Indu Pavamana.","link":"https://indra.ai/rigveda/hymns/09024.html","text":"p: HITHERWARD have the drops while they are purified.\n\np: Like floods rushing down a precipice: They come to Indra, being cleansed.\n\np: O Indu Pavamana, thou art flowing to be Indra's drink.\n\np: Victorious, to be hailed with joy, O Indu, flow, delighting men, to him who ruleth o’er mankind.\n\np: Thou, Indu, when, effused by stones, thou runnest to the filter, art, Ready for Indra's high decree.\n\np: Flow on, best Vrtra conquerer; flow meet to be hailed with joyful lauds. Pure, purifying, wonderful.\n\np: Pure, purifying is he called Indu, dear to Devas.","people":["Indu","Pavamana","Indu Pavamana","Indra","Vrtra"],"places":[],"things":["Mankind","Men","Flow","Joy","Drops"],"groups":["Devas"],"concepts":[],"hash":"md5-KAkBu5R2+hKiLbWXXoBM3Q==","created":"Monday, April 8, 2024 - 10:51:53 PM"},{"id":"8944d103-51db-4aee-9be2-abbf2dfb0d3c","key":"09025","book":"09","title":"HYMN XXV. Indu Pavamana.","link":"https://indra.ai/rigveda/hymns/09025.html","text":"p: GREEN-HUED! as one who giveth strength flow on for Devas to drink, a draught For Vayu and the Marut host.\n\np: O Pavamana, sent by song, roaring about thy dwelling-place, pass into Vayu as Law bids.\n\np: The Steer shines with the Deities, dear Sage in his appointed home, Foe-Slayer, most beloved by Devas.\n\np: Taking each beauteous form, he goes, desirable, while purified, Thither where- the Immortals sit.\n\np: To Indra Soma flows, the Red, engendering song, exceeding wise, the visitor of living men.\n\np: Flow, best exhilarator, Sage, flow to the filter in a stream To seat thee in the place of song.","people":["Pavamana","Indra","Soma","Vayu"],"places":[],"things":["Soma","Men","Stream","Flow","Song","Home","Wise","Form","Sage"],"groups":["Devas","Marut","Deities"],"concepts":["Strength"],"hash":"md5-zznVgE9YJ643c6RZU9W5BA==","created":"Monday, April 8, 2024 - 10:51:53 PM"},{"id":"81de4400-fff1-4364-9337-a3c3281e1a5f","key":"09026","book":"09","title":"HYMN XXVI. Indu Pavamana.","link":"https://indra.ai/rigveda/hymns/09026.html","text":"p: THE sages with the fingers' art have dressed and decked that vigorous Steed Upon the lap of Aditi,\n\np: The kine have called aloud to him exhaustless with a thousand streams, to Indu who supporteth heaven.\n\np: Him, nourisher of many, Sage, creative Pavamana, they Have sent, by wisdom, to the sky.\n\np: Him, dweller with Vivasvan, they with use of both arms have sent forth, the Lord of Speech infallible.\n\np: Him, green, beloved, many eyed, the Sisters with prosing stones Send down to ridges of the sieve.\n\np: O Pavamana, Indu, monks hurry thee on to Indra, thee Who aidest song and cheerest him.","people":["Indu","Pavamana","Indra","Vivasvan","Aditi"],"places":["Heaven","Sky"],"things":["Lord","Streams","Song","Creative","Sage"],"groups":["Monks"],"concepts":["Wisdom","Speech"],"hash":"md5-1FAjKpRUbyDmCz286ZpsYQ==","created":"Monday, April 8, 2024 - 10:51:53 PM"},{"id":"1b8aaa91-877f-4b4c-b935-05a9817bdd92","key":"09027","book":"09","title":"HYMN XXVII. Indu Pavamana.","link":"https://indra.ai/rigveda/hymns/09027.html","text":"p: THIS Sage, exalted by our lauds, flows to the purifying cloth, Scattering foes as he is cleansed.\n\np: As giving power and winning light, for Indra and for Vayu he Is poured upon the filtering-cloth.\n\np: The men conduct him, Soma, Steer, Omniscient, and the Head of Heaven, Effused into the vats of wood.\n\np: Longing for kine, longing for gold hath Indu Pavamana lowed, Still Conqueror, never overcome.\n\np: This Pavamana, gladdening draught, drops on the filtering cloth, and then Mounts up with Surya to the sky.\n\np: To Indra in the firmament this mighty tawny Steer hath flowed, This Indu, being purified.","people":["Indu","Pavamana","Indu Pavamana","Indra","Soma","Vayu","Surya"],"places":["Heaven","Firmament","Sky"],"things":["Soma","Light","Men","Gold","Mighty","Drops","Sage","Winning"],"groups":[],"concepts":[],"hash":"md5-2UUFzSZulWC5dp5elrxzrg==","created":"Monday, April 8, 2024 - 10:51:53 PM"},{"id":"242f7aff-4cb2-49fa-bf3a-30e375de425b","key":"09028","book":"09","title":"HYMN XXVIII. Indu Pavamana.","link":"https://indra.ai/rigveda/hymns/09028.html","text":"p: URGED by the men, this vigorous Steed, Lord of the mind, Omniscient, Runs to the woollen straining-cloth.\n\np: Within the filter hath he flowed, this Soma for the Devas effused, Entering all their essences.\n\np: He shines in beauty there, this Deva Immortal in his dwelling-place, Foe-slayer, dearest to the Devas.\n\np: Directed by the Sisters ten, bellowing on his way this Steer Runs onward to the wooden vats.\n\np: This Pavamana, swiftand strong, Omniscient, gave spleudour to The Sun and all his forms of light.\n\np: This Soma being purified, flows mighty and infallible, Slayer of sinners, dear toDevas.","people":["Pavamana","Soma","Deva"],"places":[],"things":["Lord","Soma","Light","Sun","Men","Beauty","Strong","Mighty"],"groups":["Devas","Immortal"],"concepts":["Immortal"],"hash":"md5-QBVM32CaLGno6kNv70YVSw==","created":"Monday, April 8, 2024 - 10:51:53 PM"},{"id":"cbb2a470-424b-4ee0-87e0-feb3eb15efc3","key":"09029","book":"09","title":"HYMN XXIX. Indu Pavamana.","link":"https://indra.ai/rigveda/hymns/09029.html","text":"p: FORWARD with mighty force have flowed the currents of this Steer effused, Of him who sets him by the Devas.\n\np: The singers praise him with their song, and learned monks adorn the Steed, Brought forth as light that merits laud.\n\np: These things thou winnest lightly while purified, Soma, Lord of wealth: Fill full the sea that claims our praise.\n\np: Winning all precious things at once, flow on, O Soma, with thy stream Drive to one place our enemies.\n\np: Preserve us from the godless, from ill-omened voice of one and all, that so we may be freed from blame.\n\np: O Indu, as thou flowest on bring us the wealth of earth and heaven, and splendid vigour, in thy stream.","people":["Indu","Soma"],"places":["Earth","Heaven"],"things":["Lord","Soma","Light","Wealth","Stream","Flow","Song","Mighty","Praise","Voice","Winning"],"groups":["Devas","Monks"],"concepts":[],"hash":"md5-/Z5OvQiFmyepxkCauTrJZA==","created":"Monday, April 8, 2024 - 10:51:53 PM"},{"id":"3d92fb9e-a909-476b-a881-151de50ee983","key":"09030","book":"09","title":"HYMN XXX. Indu Pavamana.","link":"https://indra.ai/rigveda/hymns/09030.html","text":"p: STREAMS of this Potent One have flowed easily to the straining-cloth: While he is cleansed he lifts his voice.\n\np: Indu, by pressers urged to speed, bellowing out while beautified. Sends forth a very mighty sound.\n\np: Pour on us, Soma, with thy stream manconquering might which many crave, Accompanied with hero sons.\n\np: Hither hath Pavamana flowed, Soma flowed hither in a stream, to settle in the vats of wood.\n\np: To waters with the stones they drive thee tawny-hued, most rich in sweets, O Indu, to be Indra's drink.\n\np: For Indra, for the Thunderer press the Soma very rich in sweets, Lovely, inspiriting, for strength.","people":["Indu","Pavamana","Indra","Soma"],"places":[],"things":["Soma","Waters","Streams","Stream","Might","Mighty","Voice","Hero"],"groups":["Sons"],"concepts":["Strength"],"hash":"md5-khNQK3CwL6pMLwr9/6siTA==","created":"Monday, April 8, 2024 - 10:51:53 PM"},{"id":"e980125c-147e-4c2e-83ab-5dfd12f4ce8d","key":"09031","book":"09","title":"HYMN XXXI. Indu Pavamana.","link":"https://indra.ai/rigveda/hymns/09031.html","text":"p: THE, Soma-drops, benevolent, come forth as they are purified, bestowing wealth which al. May see.\n\np: O Indu, high o’er heaven and earth be thou, increaser of our might: The Master of all strength be thou.\n\np: The winds are gracious in their love to thee, the rivers flow to thee Soma, they multiply thy power.\n\np: Soma, wax great. From every sid. May vigorous powers unite in thee: Be in the gathering-Place of strength.\n\np: For thee, brown-hued! the kine have poured imperishable oil and milk. Aloft on the sublimest height.\n\np: Friendship, O Indu, we desire with thee who bearest noble arms, with thee, O Lord of all that is.","people":["Indu","Soma"],"places":["Earth","Heaven"],"things":["Master","Milk","Lord","Rivers","Soma","Wealth","Flow","Might","Powers","Drops"],"groups":[],"concepts":["Friendship","Love","Strength","Noble"],"hash":"md5-tB7B1PksdXKnpRCHYNE1Sg==","created":"Monday, April 8, 2024 - 10:51:53 PM"},{"id":"114a106a-ef6f-42eb-9208-fda3d77a314d","key":"09032","book":"09","title":"HYMN XXXII. Indu Pavamana.","link":"https://indra.ai/rigveda/hymns/09032.html","text":"p: THE rapture-shedding Soma-drops, effused in our assembly, have Flowed forth to glorify our prince.\n\np: Then Trita's Maidens onward urge the Tawny-coloured with the stones, Indu for Indra, for his drink.\n\np: Now like a swan he maketh all the company sing each his hymn: He, like a steed, is bathed in milk.\n\np: O Soma, viewing heaven and earth, thou runncst like a darting deer Set in the place of offering.\n\np: The cows have sung with joy to him, even as a woman to her love He came as to a settled race.\n\np: Bestow illustrious fame on us, both on our liberal lords and me, Glory, intelligence, and wealth.","people":["Indu","Indra","Soma","Trita"],"places":["Earth","Heaven"],"things":["Milk","Soma","Glory","Offering","Wealth","Joy","Hymn","Drops","Swan"],"groups":["Woman"],"concepts":["Love","Offering","Intelligence"],"hash":"md5-3UrNXYJZC39KJThzKMn4xQ==","created":"Monday, April 8, 2024 - 10:51:53 PM"},{"id":"3b12e035-bc2f-4d5c-a10f-897149aa36fd","key":"09033","book":"09","title":"HYMN XXXIII. Indu Pavamana.","link":"https://indra.ai/rigveda/hymns/09033.html","text":"p: LIKE waves of waters, skilled in song the juices of the Soma speed Onward, as buffaloes to woods.\n\np: With stream of offering the brown bright drops have flowed with strength in store Of kine into the wooden vats.\n\np: To Indra, Vayu, Varuna, to Visnu, and the Maruts, flow The drops of Soma juice effused.\n\np: Three several words are uttered: kine are ]owing, cows who give their milk: The Tawny-hued goes bellowing on.\n\np: The young and sacred mothers of the holy rite have uttered praise: They decorate the Child of Heaven.\n\np: From every side, O Soma, for our profit, pour thou forth four seas Filled full of riches thousandfold.","people":["Indra","Soma","Vayu","Visnu","Varuna"],"places":["Heaven"],"things":["Milk","Soma","Waters","Offering","Stream","Flow","Juice","Song","Praise","Drops","Riches"],"groups":["Maruts","Child"],"concepts":["Holy","Sacred","Strength","Offering"],"hash":"md5-rpCU17KkMny61w/+BcNI3Q==","created":"Monday, April 8, 2024 - 10:51:53 PM"},{"id":"3b9a8bab-c75f-44b8-aa51-05d450ba36cd","key":"09034","book":"09","title":"HYMN XXXIV. Indu Pavamana.","link":"https://indra.ai/rigveda/hymns/09034.html","text":"p: THE drop of Soma juice effused flows onward with this stream impelled. Rending strong places with its might.\n\np: Poured forth to Indra, Varuna, to Vayu and the Marut hosts, to Visnu, flows the Soma juice.\n\np: With stones they press the Soma forth, the Strong conducted by the strong: They milk the liquor out with skill.\n\np: ’Tis he whom Trita must refine, ’tis he who shall make Indra glad: The Tawny One is decked with tints.\n\np: Him do the Sons of Prsni milk, the dwelling-place of offering, Oblation lovely and most dear.\n\np: To him in one unitcd stream th-,se songs flow on straight forward. he, Loud voiced, hath made the milch-kine low.","people":["Indra","Soma","Vayu","Visnu","Varuna","Trita"],"places":[],"things":["Milk","Soma","Offering","Stream","Flow","Might","Juice","Strong","Songs"],"groups":["Marut","Sons"],"concepts":["Offering"],"hash":"md5-tdZvHOg/KMzBfNWjlhPTtA==","created":"Monday, April 8, 2024 - 10:51:53 PM"},{"id":"af42335c-8368-4439-8ac8-2ecef08301b4","key":"09035","book":"09","title":"HYMN XXXV. Indu Pavamana.","link":"https://indra.ai/rigveda/hymns/09035.html","text":"p: Pour forth on us abundant wealth, O Pavamana, with thy stream. Wherewith tho. Mayest find us light\n\np: O Indu, swayer of the sea, shaker of all things, flow thou on, bearer of wealth to us with might.\n\np: With thee for Hero, Valiant One. May we subdue our enemies: Let what is precious flow to us.\n\np: Indu arouses strength the Sage who strives for victory, winning power, Discovering holy works and means.\n\np: Mover of speech, we robe him with our songs as he is purified Soma, the Guardian of the folk;\n\np: On whose way, Lord of Holy Law, most richi as he is purified. The people all have set their hearts.","people":["Indu","Pavamana","Soma"],"places":[],"things":["Victory","Lord","Soma","Light","Wealth","Stream","Flow","Might","People","Songs","Hero","Sage","Winning"],"groups":[],"concepts":["Holy","Strength","Speech"],"hash":"md5-7YpUtp2XV2ymdoHzPxKb0w==","created":"Monday, April 8, 2024 - 10:51:53 PM"},{"id":"fcd7909b-3556-48c1-a50c-1587603769f5","key":"09036","book":"09","title":"HYMN XXXVI. Indu Pavamana.","link":"https://indra.ai/rigveda/hymns/09036.html","text":"p: FORTH from the mortar is the juice sent, like a car-horse, to the sieve: The Steed steps forward to the goal.\n\np: Thus, Soma, watchful, bearing well, cheering the Devas, flow past the sieve, Turned to the vat that drops with meath.\n\np: Excellent Pavamana, make the lights shine brightly out for us. Speed us to mental power and skill.\n\np: He, beautified by pious men, and coming from their hands adorned, Flows through the fleecy straining-cloth.\n\np: May Soma pour all treasure.s of the heavens, the earth, the firmament Upon the liberal worshipper.\n\np: Thou mountest to the height of heaven, O Soma, seeking steeds and kine, and seeking heroes, Lord of Strength!","people":["Pavamana","Soma"],"places":["Earth","Heaven","Firmament"],"things":["Meath","Steeds","Lord","Soma","Shine","Treasure","Men","Flow","Juice","Car","Worshipper","Heroes","Excellent","Drops","Horse"],"groups":["Devas"],"concepts":["Strength"],"hash":"md5-TnvDFYhYJpRdmgfb0DoXQA==","created":"Monday, April 8, 2024 - 10:51:53 PM"},{"id":"75e7d37b-063d-4a54-9567-04770b9ae916","key":"09037","book":"09","title":"HYMN XXXVII. Indu Pavamana.","link":"https://indra.ai/rigveda/hymns/09037.html","text":"p: SOMA, the Steer, effused for draught, flows to the purifying sieve, Slaying the fiends, loving the Devas.\n\np: Far-sighted, tawny-coloured, he flows to the sieve, intelligent, bellowing, to his place of rest.\n\np: This vigorous Pavamana runs forth to the luminous realm of heaven, Fiend-slayer, through the fleecy sieve.\n\np: This Payamana up above Trita's high ridge hath made the Sun, together with the Sisters, shine.\n\np: This Vrtra-subduing Steer, effused, Soma room-giver, ne’er deceived, Hath gone, as ’twere, to win the spoil.\n\np: Urged onward by the sage, the Deva.speeds forward to the casks of wood, Indu to Indra willingly.","people":["Indu","Pavamana","Indra","Soma","Vrtra","Trita","Deva"],"places":["Heaven"],"things":["Soma","Shine","Sun","Sage","spoil"],"groups":["Devas"],"concepts":["Giver"],"hash":"md5-mxnbAQVrArL06Rr+XKg8Eg==","created":"Monday, April 8, 2024 - 10:51:53 PM"},{"id":"0edd7e77-cd1b-47a5-a0df-f3ecd51dfaab","key":"09038","book":"09","title":"HYMN XXXVIII. Indu Pavamana.","link":"https://indra.ai/rigveda/hymns/09038.html","text":"p: THIS Steer, this Chariot, rushes through the woollen filter, as he goes To war that wins a thousand spoils.\n\np: The Dames of Trita with the stones onward impel this Tawny One Indu to Indra for his drink.\n\np: Ten active fingers carefully adorn him here; they make him bright And beauteous for the gladdening draught.\n\np: He like a falcon settles down amid the families of men. Speeding like lover to his love.\n\np: This young exhilarating juice looks downward from its place in heaven, This Soma-drop that pierced the sieve.\n\np: Poured for the draught, this tawny juice flows forth, intelligent, crying out, Unto the well-beloved place.","people":["Indu","Indra","Soma","Trita"],"places":["Heaven"],"things":["Soma","Men","Juice"],"groups":["Families","Dames"],"concepts":["Love"],"hash":"md5-bQWl2ypMGdpKNAW9W7IHyg==","created":"Monday, April 8, 2024 - 10:51:53 PM"},{"id":"271b94d9-95f5-447b-ad45-d27b348a3849","key":"09039","book":"09","title":"HYMN XXXIX Indu Pavamana.","link":"https://indra.ai/rigveda/hymns/09039.html","text":"p: FLOW On, O thou of lofty thought, flow swift in thy beloved form, Saying, I go where dwell the Devas.\n\np: Preparing what is unprepared, and bringing store of food to man, make thou the rain descend from heaven.\n\np: With might, bestowing power, thejuice enters the purifying sieve, Far-seeing, sending forth its light.\n\np: This is it which in rapid course hath with the river's wave flowed down From heaven upon the straining cloth.\n\np: Inviting him frorh far away, and even from near at hand, the juice For Indra is poured forth as meath.\n\np: In union they have sung the hymn: with stones they urge the Tawny One. Sit in the place of offering.","people":["Indra"],"places":["Heaven"],"things":["Meath","Offering","Light","Food","River","Flow","Might","Juice","Rain","Hymn","Form"],"groups":["Devas","Man"],"concepts":["Offering","Swift"],"hash":"md5-MakeiRUTE+XAOmQWWAWqLQ==","created":"Monday, April 8, 2024 - 10:51:54 PM"},{"id":"73da9a77-acc6-41ba-865e-699df39a5a38","key":"09040","book":"09","title":"HYMN XL. Indu Pavamana.","link":"https://indra.ai/rigveda/hymns/09040.html","text":"p: THE Very Active hath assailed, while purified, all enemies: They deck the Sage with holy songs.\n\np: The Red hath mounted to his place; to India, goes the mighty juice: He settles in his firm abode.\n\np: O Indu, Soma, send us now great opulence from every side, pour on us treasure.s thousandfold.\n\np: O Indu Pavamana, bring, Indu, all splcndours hitherward: Find for us food in boundless store.\n\np: As thou art cleansed, bring hero strength and riches to thy worshipper, and prosper thou the singer's hymns.\n\np: O Indu, Soma, being cleansed, bring hither riches doublypiled, Wealth, mighty Indu, meet for lauds.","people":["Indu","Pavamana","Indu Pavamana","Soma"],"places":[],"things":["Soma","Singer","Treasure","Wealth","Food","Juice","Mighty","Worshipper","Songs","Hero","Sage","Riches"],"groups":[],"concepts":["Holy","Strength"],"hash":"md5-D9U/qe8pFkiOSiYfTGWYvQ==","created":"Monday, April 8, 2024 - 10:51:54 PM"},{"id":"026d9f38-c819-4cfa-8a77-ff687ab8ab1b","key":"09041","book":"09","title":"HYMN XLI. Indu Pavamana.","link":"https://indra.ai/rigveda/hymns/09041.html","text":"p: ACTIVE and bright have they come forth, impetuous in speed like bulls, Driving the black skin far away.\n\np: Quelling the riteless Dasyu. May we think upon the bridge of bliss, Leaving the bridge of woe behind.\n\np: The mighty Pavamana's roar is heard as ’twere the rush of rain Lightnings are flashing to the sky.\n\np: Pour out on us abundant food, when thou art pressed, O Indu wealth In kine and gold and steeds and spoil.\n\np: Flow on thy way, most Active, thou. fill full the mighty heavens and earth, as Dawn, as Surya with his beams.\n\np: On every side, O Soma, flow round us with thy protecting stream, as Rasa flows around the world.","people":["Indu","Pavamana","Soma","Surya","Dawn","Rasa"],"places":["Earth","Sky"],"things":["Steeds","Soma","Wealth","Food","Stream","Flow","Rain","Gold","Mighty","Bliss","spoil"],"groups":["Dasyu"],"concepts":[],"hash":"md5-/e7e/6Z42Z7IIi3E9xYA1A==","created":"Monday, April 8, 2024 - 10:51:54 PM"},{"id":"3563b2ba-85fc-47b1-af7d-65575ab7d6e3","key":"09042","book":"09","title":"HYMN XLII. Indu Pavamana.","link":"https://indra.ai/rigveda/hymns/09042.html","text":"p: ENGENDERING the Sun in floods, engendering heaven's lights, green-hued, Robed in the waters and the milk,\n\np: According to primeval plan this Soma, with his stream, effused Flows purely on, a Deva.for Devas.\n\np: For him victorious, waxen great, the juices with a thousand powers Are purified for winning spoil.\n\np: Shedding the ancient fluid he is poured into the cleansing sieve: He, thundering, hath produced the Devas.\n\np: Soma, while purifying, sends hither all things to be desired. He sends the Devas who strengthen Law.\n\np: Soma, effused, pour on us wealth in kine, in heroes, steeds, and spoil, Send us abundant store of food.","people":["Soma","Deva"],"places":["Heaven"],"things":["Milk","Steeds","Soma","Waters","Sun","Wealth","Food","Stream","Heroes","Powers","Winning","spoil"],"groups":["Devas"],"concepts":[],"hash":"md5-opTn0yPEPYHHUxGtq0O12g==","created":"Monday, April 8, 2024 - 10:51:54 PM"},{"id":"b01ecb62-0ed1-4966-944f-385bec4b9eba","key":"09043","book":"09","title":"HYMN XLIII. Indu Pavamana.","link":"https://indra.ai/rigveda/hymns/09043.html","text":"p: WE will enrobe with sacred song the Lovely One who, as a Steed, is decked with milk for rapturous joy.\n\np: All songs of ours desiring grace adorn him in the ancient way, Indu for Indra, for his drink.\n\np: Soma flows on when purified, beloved and adorned with songs, Songs of the sage Medhyatithi.\n\np: O Indu Pavamana, find exceeding glorious wealth for us, Wealth, Indu, fraught with boundless might.\n\np: Like courser racing to the prize Indu, the lover of the Devas, Roars, as he passes, in the sieve.\n\np: Flow on thy way to win us strength, to speed the sage who praises thee: Soma, bestow heroic power.","people":["Indu","Pavamana","Indu Pavamana","Indra","Soma"],"places":[],"things":["Milk","Soma","Glorious","Wealth","Flow","Might","Song","Joy","Songs","Sage"],"groups":["Devas"],"concepts":["Heroic","Sacred","Strength","Glorious"],"hash":"md5-5n/Izu4D09yvYyY8L6+WbQ==","created":"Monday, April 8, 2024 - 10:51:54 PM"},{"id":"fd9072cd-30d6-4749-83a1-97df5571c22f","key":"09044","book":"09","title":"HYMN XLIV. Indu Pavamana.","link":"https://indra.ai/rigveda/hymns/09044.html","text":"p: INDU, to us for this great rite, bearing as ’twere thy wave to Devas, Unwearied, thou art flowing forQh.\n\np: Pleased with the hymn, impelled by prayer, Soma is hurried far away, the Wise One in the Singer's stream.,\n\np: Watchful among the. gods, this juice advances to the cleansing sieve Soma, most active, travels on.\n\np: Flow onward, seeking strength for us, embellishing  'the offering: The priest with trimmed grass calleth thee.\n\np: May Soma, ever bringing power to Bhaga and to Vayu, Sage And Hero, lead us to the Devas.\n\np: So, to increase our wealth to-day, inspirer, best of Furtherers, Win for us strength and high renown.","people":["Indu","Soma","Vayu","Bhaga"],"places":[],"things":["Soma","Singer","Offering","Wealth","Stream","Flow","Juice","Wise","Grass","Hymn","Hero","Sage"],"groups":["Devas"],"concepts":["Strength","Offering","Pleased"],"hash":"md5-n65O9bb/0X0728c/08P65Q==","created":"Monday, April 8, 2024 - 10:51:54 PM"},{"id":"d232530a-94bf-4f6d-974d-de68eba2687c","key":"09045","book":"09","title":"HYMN XLV. Indu Pavamana.","link":"https://indra.ai/rigveda/hymns/09045.html","text":"p: FLOW, thou who viewest men, to give delight, to entertain the Devas, Indu, to Indra for his drink.\n\np: Stream to thine embassy for us: thou hastenest, for Indra, to The Devas, O better than our friends.\n\np: We balm thee, red of hue, with milk to fit thee for the rapturous joy: Unbar for us the doors of wealth.\n\np: He through the sieve hath passed, as comes a courser to the pole, to run Indu belongs unto the Devas.\n\np: All friends have lauded him as he sports in the wood, beyond the fleece: Singers have chanted Indu's praise.\n\np: Flow Indu, with that stream wherein steeped thou announcest to the man Who worships thee heroic strength.","people":["Indu","Indra"],"places":[],"things":["Milk","Wealth","Men","Stream","Flow","Joy","Praise","Delight","Friends"],"groups":["Devas","Man"],"concepts":["Heroic","Strength"],"hash":"md5-3UyzXCvOMyAHG6OicHVDOg==","created":"Monday, April 8, 2024 - 10:51:54 PM"},{"id":"bfa3b613-0285-4e93-b6de-ecf01252a9b2","key":"09046","book":"09","title":"HYMN XLVI. Indu Pavamana.","link":"https://indra.ai/rigveda/hymns/09046.html","text":"p: LIKE able coursers they have been sent forth to be the feast of Devas, joying in mountains, flowing on.\n\np: To Vayu flow the Soma-streams, the drops of juice made beautiful Like a bride dowered by her sire.\n\np: Pressed in the mortar, these, the drops of juice, the Somas rich in food, Give strength to Indra with their work.\n\np: Deft-handed men, run hither, seize the brilliant juices blent with meal, and cook with milk the gladdening draught.\n\np: Thus, Soma, Conqueror of wealth! flow, finding furtherance for us, Giver oF ample opulence.\n\np: This Pavamana, meet to be adorned, the fingers ten adorn, the draught that shall make Indra glad.","people":["Pavamana","Indra","Soma","Vayu"],"places":[],"things":["Milk","Work","Mountains","Soma","Wealth","Food","Men","Streams","Flow","Juice","Drops"],"groups":["Devas"],"concepts":["Beautiful","Strength","Giver"],"hash":"md5-Qg6tesQzWaTp7ya4abt4BA==","created":"Monday, April 8, 2024 - 10:51:54 PM"},{"id":"a06d4ab1-5b33-4986-9657-6ab0cfeada7e","key":"09047","book":"09","title":"HYMN XLVII. Indu Pavamana.","link":"https://indra.ai/rigveda/hymns/09047.html","text":"p: GREAT as he was, Soma hath gained strength by this high solemnity: joyous he riseth like a bull.\n\np: His task is done: his crushings of the Dasyus are made manifest: He sternly reckoneth their debts.\n\np: Soon as his song of praise is born, the Soma, indra's juice, becomes A thousand-winning thunderbolt.\n\np: Seer and Sustainer, he himself desireth riches for the sage When he embellisheth his songs.\n\np: Fain would they both win riches as in races of the steeds. In war Thou art upon the conquerors' side.","people":["Indra","Soma"],"places":[],"things":["Steeds","Born","Soma","Juice","Song","Praise","Songs","Sage","Winning","Riches"],"groups":["Dasyus"],"concepts":["Strength"],"hash":"md5-P4GNiWe0HLjtirmHEzEeSQ==","created":"Monday, April 8, 2024 - 10:51:54 PM"},{"id":"8a895b43-83fe-416b-843b-059194234eb2","key":"09048","book":"09","title":"HYMN XLVIII. Indu Pavamana.","link":"https://indra.ai/rigveda/hymns/09048.html","text":"p: WITH offering we seek to thee kind Cherisher of manly might In mansions of the lofty heavens;\n\np: Gladdening crusher of the bold, ruling with very mighty sway, Destroyer of a hundred forts.\n\np: Hence, Sapient One! the Falcon, strong of wing, unwearied, brought thee down, Lord over riches, from the sky.\n\np: That eac. May see the light, the Bird brought us the guard of Law, the Friend Of all, the speeder through the air.\n\np: And now, sent forth, it hath attained to mighty power and majesty, most active, ready to assist.","people":[],"places":["Sky"],"things":["Lord","Offering","Light","Air","Might","Strong","Mighty","Friend","Bird","Riches"],"groups":[],"concepts":["Offering"],"hash":"md5-shdHl2qdKIBW/eRdwNqcEw==","created":"Monday, April 8, 2024 - 10:51:54 PM"},{"id":"b18e6ef9-b7e4-4983-90be-cc4822e5c7e6","key":"09049","book":"09","title":"HYMN XLIX. Indu Pavamana.","link":"https://indra.ai/rigveda/hymns/09049.html","text":"p: Poust down the rain upon us, pour a wave of waters from the sky, and plenteous store of wholesome fbod.\n\np: Flow onward with that stream of thine, whereby the cows have come to us, the kine of strangers to our home.\n\np: Chief Friend of Devas in sacred rites, pour on us fatness with thy stream, ppur down on us a flood of rain.\n\np: To give us vigour, with thy stream run through the fleecy straining-cloth For verily the Devas will bear.\n\np: Onward hath Pavamana flowed and beaten off the Raksasas, Flashing out splendour as of old.","people":["Pavamana","Raksasas"],"places":["Sky"],"things":["Waters","Stream","Flow","Rain","Home","Chief","Splendour","Friend"],"groups":["Devas"],"concepts":["Sacred"],"hash":"md5-MjE0qst9Q8Duu75GrcwHBg==","created":"Monday, April 8, 2024 - 10:51:54 PM"},{"id":"036a164f-ebd1-4cba-a586-39dab58cf025","key":"09050","book":"09","title":"HYMN L. Indu Pavamana.","link":"https://indra.ai/rigveda/hymns/09050.html","text":"p: LOUD as a river's roaring wave thy powers have lifted up themselves: Urge on thine arrow's sharpened point.\n\np: At thine effusion upward rise three voices full of joy, when thou Flowest upon the fleecy ridge.\n\np: On to the fleece they urge with stone the tawny well-beloved One, Even Pavamana, dropping meath.\n\np: Flow with thy current to the sieve, O Sage most powerful to cheer, to seat thee in the place of song.\n\np: Flow, most Exhilarating! flow anointed with the milk for balm, Indu, for Indra, for his drink.","people":["Indu","Pavamana","Indra"],"places":[],"things":["Meath","Cheer","Milk","River","Flow","Song","Joy","Powers","Sage"],"groups":[],"concepts":["Powerful"],"hash":"md5-K/F7Q6msi8b7a2uJ68jAIQ==","created":"Monday, April 8, 2024 - 10:51:54 PM"},{"id":"ed5201fe-aa12-41c5-8261-d54323f93843","key":"09051","book":"09","title":"HYMN LI. Indu Pavamana.","link":"https://indra.ai/rigveda/hymns/09051.html","text":"p: ADHVARYU, on the filter pour the Soma juice expressed with stones, and make it pure for Indra's drink.\n\np: Pour out for Indra, Thunder-armed, the milk of heaven, the Soma's juice, most excellent, most rich in sweets.\n\np: These Devas and all the Marut host, Indu enjoy this juice of thine, This Pavamana's flowing meath.\n\np: For, Soma, thou hast been effused, strengthening for the wild carouse, O Steer, the singer, for our help.\n\np: Flow with thy stream, Far-sighted One, effused, into the cleansing sieve: Flow on to give us strength and fame.","people":["Indu","Pavamana","Indra","Soma"],"places":["Heaven"],"things":["Meath","Milk","Soma","Singer","Stream","Flow","Juice","Help","Excellent"],"groups":["Devas","Marut"],"concepts":["Strength"],"hash":"md5-oGImlDVAbqVytNkad6jLEA==","created":"Monday, April 8, 2024 - 10:51:54 PM"},{"id":"e65f6906-8566-4160-b386-4f915364e342","key":"09052","book":"09","title":"HYMN LII. Indu Pavamana.","link":"https://indra.ai/rigveda/hymns/09052.html","text":"p: WEALTH-WINNER, dwelling in the sky, bringing us vigour with the juice, Flow to the filter when effused.\n\np: So, in thine ancient ways. May he, beloved, with a thousand streams Run o’er the fleecy straining-cloth.\n\np: Him who is like a caldron shake: O Indu, shake thy gift to us Shake it, armed Warrior! with thine arms.\n\np: Indu, invoked with many a prayer, bring down the vigour of these men, Of him who threatens us with war.\n\np: Indu, Wealth-giver, with thine help pour out for us a hundred, yea, a thousand of thy pure bright streams.","people":["Indu"],"places":["Sky"],"things":["Wealth","Men","Streams","Flow","Juice","Help","Gift","Warrior","Caldron"],"groups":[],"concepts":["Giver","Winner"],"hash":"md5-OK/0hXUrpbaegX5hG8uJtQ==","created":"Monday, April 8, 2024 - 10:51:54 PM"},{"id":"b5de055e-0d9f-4b28-bf84-e224714a2ff3","key":"09053","book":"09","title":"HYMN LIII. Indu Pavamana.","link":"https://indra.ai/rigveda/hymns/09053.html","text":"p: O THOU with stones for arms, thy powers, crushing the fiends, have raised themselves: Chase thou the foes who compass us.\n\np: Thou conquerest thus with might when car meets car, and when the prize is staked: With fearless heart will I sing praise.\n\np: No one with evil thought assails this Pavamana's holy laws: Crush him who fain would fight with thee.\n\np: For Indra to the streams they drive the tawny rapture-dropping Steed, Indu the bringer of delight.","people":["Indu","Pavamana","Indra"],"places":[],"things":["Streams","Might","Car","Praise","Delight","Powers"],"groups":[],"concepts":["Evil","Holy"],"hash":"md5-FscZ+6viODiTsYbB4E+mIw==","created":"Monday, April 8, 2024 - 10:51:54 PM"},{"id":"8df92132-4607-4449-8ec4-90bad9834869","key":"09054","book":"09","title":"HYMN LIV. Indu Pavamana.","link":"https://indra.ai/rigveda/hymns/09054.html","text":"p: AFTER his ancient splendour, they, the bold, have drawn the bright milk from The Sage who wins a thousand gifts.\n\np: In aspect he is like the Sun; he runneth forward to the lakes, Seven currents flowing through the sky.\n\np: He, shining in his splendour, stands high over all things that exist- Soma, a Deva.as Surya is.\n\np: Thou, Indu, in thy brilliancy, pourest on us, as Indra's Friend, Wealth from the kine to feast the Devas.","people":["Indu","Indra","Soma","Deva","Surya"],"places":["Sky"],"things":["Milk","Soma","Sun","Wealth","Splendour","Friend","Sage","Gifts"],"groups":["Devas"],"concepts":[],"hash":"md5-EXIEWpw8p1COSU9baj05gA==","created":"Monday, April 8, 2024 - 10:51:54 PM"},{"id":"1fdde032-782c-4f2f-81eb-027f18cad332","key":"09055","book":"09","title":"HYMN LV. Indu Pavamana.","link":"https://indra.ai/rigveda/hymns/09055.html","text":"p: POUR on us with thy juice all kinds of corn, each sort of nourishment, and, Soma, all felicities.\n\np: As thine, O Indu, is the praise, and thine what springeth from the juice, Seat thee on the dear sacred grass.\n\np: And, finding for us kine and steeds, O Soma, with thy juice flow on Through days that fly most rapidly.\n\np: As one who conquers, ne’er subdued, attacks and stays the enemy, thus, Vanquisher of thousands! flow.","people":["Indu","Soma"],"places":[],"things":["Steeds","Soma","Flow","Juice","Grass","Praise"],"groups":[],"concepts":["Sacred"],"hash":"md5-/iF65r0pw19f/kQyE34MRA==","created":"Monday, April 8, 2024 - 10:51:54 PM"},{"id":"eaeb1035-5de2-4a51-9b89-679819134a9a","key":"09056","book":"09","title":"HYMN LVI. Indu Pavamana.","link":"https://indra.ai/rigveda/hymns/09056.html","text":"p: SWIFT to the purifying sieve flows Soma as exalted Law, Slaying the fiends, loving the Devas.\n\np: When Soma pours the strengthening food a hundred ever-active streams To Indra's friendship win theirway.\n\np: Ten Dames have sung to welcome thee, even as a maiden greets her love: O Soma, thou art decked to win.\n\np: Flow hitherward, O Indu, sweet to Indra and to Visnu: guard The men, the singers, from distress.","people":["Indu","Indra","Soma","Visnu"],"places":[],"things":["Soma","Food","Men","Streams","Flow"],"groups":["Devas","Dames"],"concepts":["Friendship","Love","Swift"],"hash":"md5-VaVZ+caRn6HOaBZP+Sub8g==","created":"Monday, April 8, 2024 - 10:51:54 PM"},{"id":"6b7e9bce-0739-4319-9641-827e01f93cac","key":"09057","book":"09","title":"HYMN LVII. Indu Pavamana.","link":"https://indra.ai/rigveda/hymns/09057.html","text":"p: THY streams that never fail or waste flow forth like showers of rain from heaven, to bring a thousand stores of strength.\n\np: He flows beholding on his way all wellbeloved sacred lore, Green-tinted, brandishing his, arms.\n\np: He, when the people deck him like a docile king of elephants. Sits as a falcon in the, wood.\n\np: So bring thou hitherward to us, Indu, while thou art purified, All treasure.s both of heaven and earth.","people":["Indu"],"places":["Earth","Heaven"],"things":["Treasure","Streams","Flow","Rain","People","King"],"groups":[],"concepts":["Sacred","Strength"],"hash":"md5-isr0V/z6ltOTn0IK62308w==","created":"Monday, April 8, 2024 - 10:51:54 PM"},{"id":"6ecc75f4-5867-4eef-a90b-7b04dbabad85","key":"09058","book":"09","title":"HYMN LVIII. Indu Pavamana.","link":"https://indra.ai/rigveda/hymns/09058.html","text":"p: SWIFT runs this giver of delight, even the stream of flowing juice: Swift runs this giver of delight.\n\np: The Morning knows all precious things, the Deva knows her grace to man: Swift runs this giver of delight.\n\np: We have accepted thousands from Dhvasra's and Purusanti's hands: Swift runs this giver of delight.\n\np: From whom we have accepted thus thousands and three times ten beside: Swift runs this giver of delight.","people":["Deva"],"places":[],"things":["Stream","Juice","Delight","Morning"],"groups":["Man"],"concepts":["Giver","Swift"],"hash":"md5-1v9hAyEpbUk1pgVQW1pLGQ==","created":"Monday, April 8, 2024 - 10:51:54 PM"},{"id":"9ba3b955-ecb3-4a39-851f-d35d04809414","key":"09059","book":"09","title":"HYMN LIX. Indu Pavamana.","link":"https://indra.ai/rigveda/hymns/09059.html","text":"p: FLOW onward, Soma, winning kine, and steeds, and all that gives delight: Bring hither wealth with progeny.\n\np: Flow onward from the waters, flow, inviolable, from the plants: Flow onward from the pressing-boards.\n\np: Soma, as Pavamana, pass over all trouble and distress: Sit on the sacred grass, a Sage.\n\np: Thou, pavamana, foundest light; thou at thy birth becamest great: O Indu, thou art over all.","people":["Indu","Pavamana","Soma"],"places":[],"things":["Steeds","Soma","Waters","Light","Wealth","Flow","Grass","Delight","Sage","Winning"],"groups":["Progeny"],"concepts":["Birth","Sacred"],"hash":"md5-duSpCjX50f/nHkGjS1yT+g==","created":"Monday, April 8, 2024 - 10:51:54 PM"},{"id":"68dd66e6-31e1-4be7-9229-ab743ed70adf","key":"09060","book":"09","title":"HYMN LX. Indu Pavamana.","link":"https://indra.ai/rigveda/hymns/09060.html","text":"p: SING forth and laud with sacred song most active Pavamana, laud Indu who sees with thousand eyes.\n\np: Thee who hast thousand eyes to see, bearer of thousand burthens, they Have filtered through the fleecy cloth.\n\np: He, pavamana, hath streamed through the fleece then he runs into the jars, Finding his way to Indra's heart.\n\np: That Indr. May be bounteous, flow, most active Soma, for our weal: Bring genial seed with progeny.","people":["Indu","Pavamana","Indra","Soma"],"places":[],"things":["Soma","Flow","Song"],"groups":["Progeny"],"concepts":["Sacred"],"hash":"md5-wPQqC0liafp6XTg5Q5XFXw==","created":"Monday, April 8, 2024 - 10:51:54 PM"},{"id":"a83fd847-ec40-4a32-8795-72465e917703","key":"09061","book":"09","title":"HYMN LXI. Indu Pavamana.","link":"https://indra.ai/rigveda/hymns/09061.html","text":"p: FLOW onward, Indu, with this food for him who in thy wild delight Battered the nine-and-ninety down,\n\np: Smote swiftly forts, and gambara, then Yadu and that Turvaga, for pious Divodasa's sake.\n\np: Finder of horses, pour on us horses and wealth in kine and gold, and, Indu, food in boundless store.\n\np: We seek to win thy friendly love, even Pavamana's flowing o’er The limit of the cleansing sieve.\n\np: With those same waves which in their stream oyerflow the purifying sieve, Soma; be gracious unto us.\n\np: O Soma, being purified, bring us from all sides.for thou canst. Riches and food with hero sons.\n\np: Him here, the Child whom streams have borne, the ten swift fingers beautify With the Adityas is he seen.\n\np: With Indra and with Vayu he, effused, flows onward with,the beams Of Surya to the cleansing sieve.\n\np: Flow rich in sweets and lovely for our Bhaga, Vayu, pusan flow For Mitra and for Varuna.\n\np: High is thy juice's birth: though set in heaven, on earth it hath obtained Strong sheltering power and great renown.\n\np: Striving to win, with him we gain all wealth from the ungodly man, Yea, all the glories of mankind.\n\np: Finder of room and freedom, flow for Indra whom we must adore, for Varuna and the Marut host.\n\np: The Devas have come to Indu well-descended, beautified with milk, the active crusher of the foe.\n\np: Even as mother cows their calf, so let our praise-songs strengthen him, Yea, him who winneth Indra's heart.\n\np: Soma, pour blessings on our kine, pour forth the food that streams with milk Increase the sea that merits laud.\n\np: From heaven hath Pavamana made, as ’twere, the marvellous thunder, and The lofty light of all mankind.\n\np: The gladdening and auspicious juice of thee, of Pavamana, King! Flows o’er the woollen straining-cloth.\n\np: Thy juice, O Pavamana, sends its rays abroad like splendid skilllike lustre, all heaven's light, to see.\n\np: Flow onward with that juice of thine most excellent, that brings delight, Slaying the wicked, dear to Devas.\n\np: Killing the foeman and his hate, and winning booty every day, Gainer art thou of steeds and kine.\n\np: Red-hued, be blended with the milk that seems to yield its lovely breast, Falcon-like resting in thine home.\n\np: Flow onward thou who strengthenedst Indra to slaughter Vrtra who Compassed and stayed the mighty floods.\n\np: Soma who rainest gifts. May we win riches with our hero sons: Strengthen, as thou art cleansed, our hymns.\n\np: Aided by thee, and through thy grace. May we be slayers when we war: Watch, Soma, at our solemn rites.\n\np: Chasing our foemen, driving off the godless, Soma flowcth on, Going to Indra's special place.\n\np: O Pavamana, hither bring great riches, and destroy our foes: O Indu, grant heroic fame.\n\np: A hundred obstacles have ne’er checked thee when fain to give thy boons, when, being cleansed, thou combatest.\n\np: Indu, flow on, a mighty juice; glorify us among the folk: Drive all our enemies away.\n\np: Indu, in this thy friendship most lofty and gloriou. May we Subdue all those who war with us.\n\np: Those awful weapons that thou hast, sharpened at point to strike men down- Guard us therewith from every foe.","people":["Indu","Pavamana","Indra","Soma","Vrtra","Vayu","Yadu","Mitra","Varuna","Pusan","Bhaga","Surya","Turvaga"],"places":["Earth","Heaven"],"things":["Mankind","Milk","Steeds","Soma","Light","Wealth","Food","Men","Streams","Stream","Flow","Juice","Gold","Home","Strong","Mighty","Praise","Delight","Excellent","Songs","Hero","King","Horses","Winning","Riches","Gifts"],"groups":["Devas","Marut","Sons","Mother","Child","Man","Adityas"],"concepts":["Birth","Friendship","Heroic","Special","Blessings","Love","Auspicious","Swift"],"hash":"md5-b7jKxfb/vW22i/vqGb6dyQ==","created":"Monday, April 8, 2024 - 10:51:54 PM"},{"id":"eb269eeb-74ac-444e-a419-0c44af1ecc90","key":"09062","book":"09","title":"HYMN LXII. Indu Pavamana.","link":"https://indra.ai/rigveda/hymns/09062.html","text":"p: THESE rapid Soma-drops have been poured through the purifying sieve To bring us all felicities.\n\np: Dispelling manifold mishap, giving the courser's progeny, Yea, and the warrior steed, success.\n\np: Bringing prosperity to kine, they make perpetual Ila flow To us for noble eulogy.\n\np: Strong, mountain-born, the stalk hath been pressed in the streams for rapturous joy: Hawk-like he settles in his home.\n\np: Fair is the Deva.loved juice; the plant is washed in waters, pressed by men The milch-kine sweeten it with milk.\n\np: As drivers deck a courser, so have they adorned the meath's juice for Ambrosia, for the festival.\n\np: Thou, Indu, with thy streams that drop sweet juices, which were poured for help, Hast settled in the cleansing sieve.\n\np: So flow thou onward through the fleece, for Indra flow, to be his drink, Finding thine home in vats of wood.\n\np: As giving room and freedom, as most sweet, pour butter forth and milk, O Indu, for the Angirases.\n\np: Most active and benevolent, this Pavamana, sent to us For lofty friendship, meditates.\n\np: Queller of curses, mighty, with strong sway, this Pavamana shall Bring treasure.s to the worshipper.\n\np: Pour thou upon us thousandfold possessions, both of kine and steeds, Exceeding glorious, much-desired.\n\np: Wandering far, with wise designs, the juice here present is effused, Made beautiful by living men.\n\np: For Indra flows the gladdening drink, the measurer of the region, Sage, with countless wealth and endless help.\n\np: Born on the inountain, lauded here, Indu for Indra is set down, as in her sheltering nest a bird.\n\np: Pressed by the men, as ’twere to war hath Indu Pavamana sped, to test with might within the vats.\n\np: That h. May move, they yoke him to the three-backed triple-seated car By the Seven Rsis’ holy songs.\n\np: Drive ye that Tawny Courser, O ye pressers, on his way to war, Swift Steed who carries off the spoil.\n\np: Pouring all glories hither, he, effused and entering the jar, Stands like a hero mid the kine.\n\np: Indu, the living men milk out the juice to make the rapturous draught: Devas for the Devas milk out the meath.\n\np: Pour for the Devas into the sieve our Soma very rich in sweetshim whom the Devas most gladly hear.\n\np: Into his stream who gladdens best these Soma juices have been poured, Lauded with songs for lofty fame.\n\np: Thou flowest to enjoy the milk, and bringest valour, being cleansed: Winning the spoil flow hitherward.\n\np: And, hymned by Jamadagnis, let all nourishment that kine supply, and general praises, flow to us.\n\np: Soma, as leader of the song flow onward with thy wondrous aids, for holy lore of every kind.\n\np: Do thou as leader of the song, stirring the waters of the sea, Flow onward, thou who movest all.\n\np: O Soma, O thou Sage, these worlds stand ready to attest thy might: For thy behoof the rivers flow.\n\np: Like showers of rain that fall from heaven thy streams perpetually flow To the bright fleece spread under them.\n\np: For potent Indra purify Indu effectual and strong, Enjoyment-giver, Mighty Lord.\n\np: Soma, true, pavamana, Sage, is seated in the cleansing sieve, giving his praiser hero strength.","people":["Indu","Pavamana","Indu Pavamana","Indra","Soma","Deva","Ila"],"places":["Heaven"],"things":["Meath","Leader","Milk","Steeds","Lord","Born","Rivers","Soma","Waters","Glorious","Treasure","Wealth","Men","Streams","Stream","Flow","Might","Juice","Rain","Song","Joy","Help","Home","Wise","Strong","Mighty","Car","Worshipper","Songs","Drops","Warrior","Hero","Bird","Sage","Winning","spoil"],"groups":["Devas","Progeny","Rsis","Angirases"],"concepts":["Friendship","Beautiful","Holy","Strength","Giver","Glorious","Swift","Noble"],"hash":"md5-2YyEYjZx2aIoJCFTHFngbw==","created":"Monday, April 8, 2024 - 10:51:55 PM"},{"id":"07751174-c13f-4603-86ae-e5a16b9212b9","key":"09063","book":"09","title":"HYMN LXIII. Indu Pavamana.","link":"https://indra.ai/rigveda/hymns/09063.html","text":"p: POUR hitherward, O Indu, wealth in thousands and heroic strength, and keep renown secure for us.\n\np: Thou makest food and vigour swell for Indra, best of gladdeners! Within the cups thou seatest thee.\n\np: For Indra and for Visnu poured, Soma hath flowed into the jar: May Vayu find it rich in sweets.\n\np: , in stream of solemn offering Have flowed through twisted obstacles,\n\np: Performing every noble work, active, augmenting Indra's strength, Driving away the godless ones.\n\np: Brown Soma-drops, effused that seek Indra, to their appropriate place Flow through the region hitherward.\n\np: Flow onward with that stream of thine wherewith thou gavest Surya light, Urging on waters good to men.\n\np: He, pavamana, high o’er man yoked the Sun's courser Etasa To travel through the realm of air.\n\np: And those ten Coursers, tawny-hued, he harnessed that the Sun might come Indu, he said, is Indra's self.\n\np: Hence, singers, pour the gladdeningjuice to Vayu and to Indra, pour The drops upon the fleecy cloth.\n\np: O Indu Pavamana, find wealth for us not to be assailed, Wealth which the foema. May not win.\n\np: Send riches hither with thy stream in thousands, both of steeds and kine, Send spoil of war and high renown.\n\np: Soma the Deva, expressed with stones, like Surya, floweth on his way, pouring the juice within the jar.\n\np: These brilliant drops have poured for us, in stream of solemn offeringworshipful laws and strength in kine.\n\np: Over the cleansing sieve have flowed the Somas, blent with curdled milk, Effused for Indra Thunder-armed.\n\np: Soma, do thou most rich in sweets, a gladdening drink most dear to Devas, Flow to the sieve to bring us wealth.\n\np: For Indra, living men adorn the Tawny Courser in the streams, Indu, the giver of delight.\n\np: Pour for us, Soma, wealth in gold, in horses and heroic sons, Bring hither strength in herds of kine.\n\np: For Indra pour ye on the fleece him very sweet to taste, who longs. For battle as it were in war.\n\np: The singers, seeking help, adorn the Sage who must be decked with songs: Loud bellowing the Steer comes on,\n\np: The singers with their thoughts and hymns have, in the stream of offering, Caused Soma, active Steer, to roar.\n\np: Deva, working with mankind, flow on; to Indra go thy gladdening juice: To Vayu mount as Law commands\n\np: O Soma, pavamana, thou pourest out wealth that brings renown: Enter the lake, as one we love.\n\np: Indu thou flowestbringing wisdom and delight: Drive off the folk who love not Devas.\n\np: The Pavamanas have been poured for holy lore of every kind.\n\np: The Pavamanas have been shed, driving all enemies afar.\n\np: From, heaven, from out the firmament, hath Pavamana been effused upon the summit of the earth.\n\np: O Indu, very wise, drive, being purified, with thy stream all foes, all Raksasas away.\n\np: Driving the Raksasas afar, O Soma, bellowing, pour for us most excellent and splendid strength.\n\np: Soma, do thou secure for us the treasure.s of the earih and heaven, Indu, all boons to be desired.","people":["Indu","Pavamana","Indu Pavamana","Indra","Soma","Vayu","Visnu","Etasa","Deva","Surya","Raksasas"],"places":["Earth","Heaven","Firmament"],"things":["Mankind","Milk","Steeds","Work","Soma","Waters","Offering","Light","Air","Sun","Treasure","Wealth","Food","Men","Streams","Stream","Flow","Might","Juice","Gold","Help","Wise","Delight","Lake","Excellent","Songs","Drops","Sage","Horses","spoil","Riches"],"groups":["Devas","Sons","Man"],"concepts":["Good","Heroic","Love","Holy","Strength","Wisdom","Offering","Giver","Noble"],"hash":"md5-1O7TmO6hoeOar/flTF6j9w==","created":"Monday, April 8, 2024 - 10:51:55 PM"},{"id":"19753234-85ef-4239-b2f0-724bcc4d2564","key":"09064","book":"09","title":"HYMN LXIV. Indu Pavamana.","link":"https://indra.ai/rigveda/hymns/09064.html","text":"p: Soma, thou art a splendid Steer, a Steer, O Deva, with steerlike sway: Thou as a Steer ordainest laws.\n\np: Steer-strong thy might is as a steer's, steerstrong thywood, steer-like thy drink A Steer indeed, O Steer, art thou.\n\np: Thou, Indu, as a vigorous horse, hast neighed together steeds and kine: Unbar for us the doors to wealth.\n\np: Out of desire of cows and steeds and horses. potent Soma-drops, Brilliant and swift, have been effused.\n\np: They purified in both the hands, made beautiful by holy men, Flow onward to the fleecy cloth.\n\np: These Soma juices shall pour forth all treasure.s for the worshipper From heaven and earth and firmament.\n\np: The streams of Pavamana, thine, Finder of all, have been effused, Even as Surya's rays of light.\n\np: Making the light that shines from heaven thou flowest on to every form Soma, thou swellest like a sea.\n\np: Urged on thou sendest out thy voice, O Pavamana; thou hast movedlike the Deva.Surya, to the sieve.\n\np: Indu, Enlightener, Friend, hath been purified by the sages' hymns: So starts the charioteer his steed-\n\np: Thy Deva.delighting wave which hath flowed to purifying seive, Alighting in the home of Law.\n\np: Flow to our sieve, a gladdening draught that hath most intercourse with Devas, Indu, to Indra for his drink.\n\np: Flow onward with a stream for food, made beautiful by sapient men: Indu with sheen approach the milk.\n\np: While thou art cleansed, Song-Lover, bring comfort and vigour to the folk, poured, Tawny One! on milk and curds.\n\np: Purified for the feast of Devas, go thou to Indra's special place, Resplendent, guided by the strong.\n\np: Accelerated by the hymn, the rapid drops of Soma juice Have flowed, urged onward, to the lake.\n\np: Easily have the living drops, made beautiful, approached the lake, Yea, to the place of offering.\n\np: Compass about, our faithful Friend, all our possessions with thy might: Guard, hero like, our sheltering home.\n\np: Loud neighs the Courser Etasa, with singers, harnessed for the place, Guided for travel to the lake.\n\np: What time the Swift One resteth in the golden place of offering. He leaves the foolish far away.\n\np: The friends have sung in unison, the prudent wish to offering: Down sink the unintelligent.\n\np: For Indra girt by Maruts, flow, thou Indu, very rich in sweets, to sit in place of offering.\n\np: Controlling monks and sages skilled in holy song adorn thee well: The living make thee beautiful.\n\np: Aryaman, Mitra, Varuna drink Pavamana's juice, yea, thine: O Sage, the Maruts drink thereof.\n\np: O Indu, thou while thou art purified urgest onward speech. Thousandfold, with the lore of hymns.\n\np: Yea, Soma, Indu, while thou art purified do thou bring to us Speech thousandfold that longs for war.\n\np: O Indu, Much-invoked, while thou art purifying, as the Friend. Of these men enter thou the lake.\n\np: Bright are these Somas blent with milk, with light that flashes brilliantly. And form that utters loud acclaim.\n\np: Led by his drivers, and sent forth, the Strong Steed hath come nigh for spoillike warriors when they stand arrayed.\n\np: Specially, Soma, coming as a Sage from heaven to prosper us, Flow like the Sun for us to see.","people":["Indu","Pavamana","Indra","Soma","Mitra","Varuna","Etasa","Deva","Surya","Aryaman"],"places":["Earth","Heaven","Firmament"],"things":["Milk","Steeds","Soma","Offering","Light","Sun","Treasure","Wealth","Food","Men","Streams","Stream","Flow","Might","Juice","Song","Home","Strong","Voice","Worshipper","Hymn","Form","Lake","Friends","Drops","Friend","Hero","Sage","Horses","Horse"],"groups":["Devas","Maruts","Monks"],"concepts":["Beautiful","Special","Holy","Offering","Swift","Speech"],"hash":"md5-H4E8pn91XdwZOaH1B4voZg==","created":"Monday, April 8, 2024 - 10:51:55 PM"},{"id":"16de102c-b597-49ae-8e52-1783aad96b45","key":"09065","book":"09","title":"HYMN LXV. Indu Pavamana.","link":"https://indra.ai/rigveda/hymns/09065.html","text":"p: THE, glittering maids send Sura forth, the glorious sisters, close-allied, Send Indu forth, their mighty Lord.\n\np: Pervade, O Pavamana, all our treasure.s with repeated light, Deva, coming hither from the Devas.\n\np: Pour on us, pavamana, rain, as service and rain praise for Devas: Pour all to be our nourishment.\n\np: Thou art a Steer by lustre: we, O Pavamana, faithfully Call upon thee the Splendid One.\n\np: Do thou, rejoicing, nobly-armed! pour upon us heroic strength: O Indu, come thou bitherward.\n\np: When thou art cleansed with both the hands and dipped in waters, with the wood. Thou comest to the gathering-place.\n\np: Sing forth your songs, as Vyasva sang, to Indu Pavamana, to, the Mighty One with thousand eyes;\n\np: Whose coloured sap they drive with stones, the yellow meath-distilling juice, Indu for Indra, for his drink.\n\np: We seek to gain the friendly love of thee that Strong and Mighty One, Of thee the winner of all wealth.\n\np: Flow onward with thy stream, a Steer, inspiriting the Maruts’ Lord, Winning all riches by thy might.\n\np: I send thee forth to battle from the press, O Pavamana, Strong, Sustainer, looker on the light.\n\np: Acknowledged by this song of mine, flow, tawny-coloured, with thy stream Incite to battle thine ally.\n\np: O Indu, visible to all pour out for us abundant food: Soma, be thou our prosperer.\n\np: The pitchers, Indu, with thy streams have sung aloud in vigorous might Enter them, and let Indra drink.\n\np: O thou whose potent gladdening juice they milk out with the stones, flow on, Destroyer of our enemies.\n\np: King Pavamana is implored with holy songs, on man's behalf, to travel through the firmament.\n\np: Bring us, O Indu, hundredfold increase of kine, and noble steeds, the gift of fortune for our help.\n\np: Pressed for the banquet of the Devas, O Soma, bring us might, and speedlike beauty for a brilliant show.\n\np: Soma, flow on exceeding bright with loud roar to the wooden vats, Falcon-like resting in thine home.\n\np: Soma, the Water-winner flows to Indra, Vayu, Varuna, to Visnu and the Marut host.\n\np: Soma , bestowing food upon our progeny, from every sides, pour on us riches thousandfold\n\np: The Soma juices which have been expressed afar or near at hand, or there on Saryanavan's bank,\n\np: Those pressed among Arjikas, pressed among the active, in men's homes, or pressed among the Races Five-\n\np: May these celestial drops, expressed, pour forth upon us, as they flow, Rain from the heavens apd hero strength.\n\np: Urged forward o’er the ox-hide flows the Lovely One of tawny hue, Lauded by Jamadagni's song.\n\np: Like horses urged to speed, the drops, bright, stirring vital power, when blent With milk, are beautified in streams.\n\np: So they who toil with juices send thee forward for the Devas’ repast: So with this splendour flow thou on.\n\np: We choose to-day that chariot-steed of thine, the Strong, that brings us bliss, the Guardian, the desire of all,\n\np: The Excellent, the Gladdener, the Sage with heart that understands, the Guardian, the desire of all;\n\np: Who for ourselves, O thou Most Wise, is wealth and fair intelligence, the Guardian, the desire of all.","people":["Indu","Pavamana","Indu Pavamana","Indra","Soma","Vayu","Visnu","Varuna","Deva"],"places":["Firmament"],"things":["Meath","Milk","Steeds","Lord","Soma","Waters","Water","Glorious","Light","Treasure","Wealth","Food","Men","Streams","Stream","Flow","Might","Juice","Rain","Song","Beauty","Help","Home","Wise","Strong","Mighty","Banquet","Praise","Gift","Splendour","Excellent","Bliss","Songs","Drops","Hero","King","Sage","Horses","Winning","call","Riches"],"groups":["Devas","Maruts","Marut","Progeny","Man"],"concepts":["Celestial","Heroic","Love","Holy","Strength","Glorious","Winner","Noble","Intelligence"],"hash":"md5-zyc4NmkYGCzSsmXCTfqM/g==","created":"Monday, April 8, 2024 - 10:51:55 PM"},{"id":"72e95e9a-1b87-4aaa-8686-c981dcd61124","key":"09066","book":"09","title":"HYMN LXVI. Indu Pavamana.","link":"https://indra.ai/rigveda/hymns/09066.html","text":"p: FOR holy lore of every sort, flow onward thou whom all men love. A Friend to be besought by friends.\n\np: O'er all thou rulest with these Two which, Indu Pavamana, stand, Turned, as thy stations, hitherward.\n\np: Wise Indu Pavamana, thou encompassest on every side Thy stations as the seasons come.\n\np: Flow onward, generating food, for precious boons of every kind, a friend for friends, to be our help.\n\np: Upon the lofty ridge of heaven thy bright rays with their essences, Soma, spread purifying power.\n\np: O Soma, these Seven Rivers flow, as being thine, to give command: The Streams of milk run forth to thee.\n\np: Flow onward, Soma in a stream, effused to gladden Indra's heart, Bringing imperishable fame.\n\np: Driving thee in Vivasvan's course, the Seven Sisters with their hymns Made melody round thee the Sage.\n\np: The virgins deck thee o’er fresh streams to drive thee to the sieve when thou, a singer, bathest in the wood.\n\np: The streams of Pavamana, thine, Sage, Mighty One, have pouredthem forth. Like coursers eager for renown.\n\np: They have been poured upon the fleece towards the meath-distilling vat: The holy songs have sounded forth.\n\np: Like milch-kine coming home, the drops of Soma juice have reached the lake, have reached the place of offering.\n\np: O Indu, to our great delight the running waters flow to us, when thou wilt robe thyself in milk.\n\np: In this thy friendship, and with thee to help us, fain to offering, Indu, we crave thy friendly love.\n\np: Flow on, O Soma, for the great Viewer of men, for gain of Idne Enter thou into Indra's throat.\n\np: Best art thou, Soma, of the great, Strongest of strong ones, Indu: thou As Warrior ever hast prevailed.\n\np: Mightier even than the strong, more valiant even than the brave, More libpral than the bountiful,\n\np: Soma, as Sura, bring us food, win offspring of our bodies: we Elect thee for our friendship, we elect thee for companionship.\n\np: Agni, thou pourest life; send down upon us food and vigorous strength; Drive thou misfortune far away,\n\np: Agni is Pavamana, Sage, Chief Monk of all the Races Five: To him whose wealth is great we pray.\n\np: Skilled in thy task, O Agni, pour splendour with hero strength on us, Granting me wealth that nourishes.\n\np: Beyond his enemies away to sweet praise Pavamana flowslike Surya visible to all.\n\np: Adorned by living men, set forth for entertainment, rich in food, Far-sighted Indu is a Steed.\n\np: He, pavamana, hath produced the lofty Law, the brilliant light, Destroying darkness black of hue.\n\np: From tawny Pavamana, the Destroyer, radiant streams have sprung, Quick streams from him whose gleams are swift.\n\np: Best rider of the chariot, praised with fairest praise mid beauteous ones, Gold-gleaming with the Marut host,\n\np: May Pavamana, best to win the booty, penetrate with rays, giving the singer hero strength.\n\np: Over the fleecy sieve hath flowed the drop effused: to Indra comes Indu while he is purified\n\np: This Soma, through the pressing-stones, is sporting on the oxhide, and Summoning Indra to the draught.\n\np: O Pavamana, bless us, so that we may live, with that bright milk Of thine which hath been brought from heaven.","people":["Indu","Pavamana","Indu Pavamana","Indra","Soma","Agni","Vivasvan","Surya"],"places":["Heaven"],"things":["Meath","Milk","Seasons","Rivers","Soma","Waters","Singer","Offering","Light","Wealth","Food","Men","Streams","Stream","Flow","Juice","Gold","Help","Home","Wise","Offspring","Strong","Mighty","Chief","Praise","Brave","Delight","Lake","Splendour","Pressing-Stones","Friends","Songs","Drops","Warrior","Friend","Hero","Sage","Life"],"groups":["Marut"],"concepts":["Life","Friendship","Love","Holy","Strength","Offering","Swift"],"hash":"md5-K1s0+vj0/XNBoFiwLHV7jQ==","created":"Monday, April 8, 2024 - 10:51:55 PM"},{"id":"9d793973-6f07-4adc-806b-13e2fe81bf9d","key":"09067","book":"09","title":"HYMN LXVII. Soma and Others.","link":"https://indra.ai/rigveda/hymns/09067.html","text":"p: THOU, Soma, hast a running stream, joyous, most strong at offering: Flow bounteously bestowing wealth.\n\np: Effused as cheerer of the men, flowing best gladdener, thou art A Prince to Indra with thy juice.\n\np: Poured forth by pressing-stones, do thou with loud roar send us in a stream Most excellent illustrious might.\n\np: Indu, urged forward, floweth through the fleecy cloth: the Tawny One With his loud roar hath brought as strength.\n\np: Indu, thou flowest through the fleece, bringing felicities and fame, and, Soma, spoil and wealth in kine.\n\np: Hither, O Indu, bring us wealth in steeds and cattle hundredfold: Bring wealth, O Soma, thousandfold.\n\np: In purifying, through the sieve the rapid drops of'Soma juice Come nigh to Indra in their course.\n\np: For Indra floweth excellent Indu, the noblest Soma juice The Living for the Living One.\n\np: The glittering maids send Sura forth they with their song have sung aloud To Pavamana dropping meath.\n\np: May Pusan, drawn by goats, be our protector, and on all his paths Bestow on us our share of maids.\n\np: This Soma flows like gladdening oil for him who wears the braided locks: He shall give us our share of maids.\n\np: This Soma juice, O glowing Deva, flows like pure oil, effused for thee: He shall give us our share of maids.\n\np: Flow onward, Soma, in thy stream, begetter of the sages' speech: Wealth-giver among Devas art thou.\n\np: The Falcon dips within the jars: he wrapḥim in his robe and goes Loud roaring to the vats of wood.\n\np: Soma, thy juice hath been effused and poured into the pitcher: like a rapid hawk it rushes on.\n\np: For Indra flow most rich in sweets, O Soma, bringing him delight.\n\np: They were sent forth to feast the Devas, like chariots that display their strength.\n\np: Brilliant, best givers of delight, these offerings have sent Vayu forth.\n\np: Bruised by the press-stones and extolled, Soma, thou goest to the sieve, giving the worshipper hero strength.\n\np: This juice bruised by the pressing-stones and lauded passes through the sieve, Slayer of demons, through the fleece.\n\np: O Pavamana, drive away the danger, whether near at hand Or far remote, that finds me here.\n\np: This da. May Pavamana cleanse us with his purifying power, most active purifying Monk.\n\np: O Agni, with the cleansing light diffused through all thy fiery glow, purify thou this prayer of ours.\n\np: Cleanse us with thine own cleansing power, O Agni, that is bright with flame, and by libations poured to thee.\n\np: Savitar, Deva, by both of these, libation, purifying power, purify me on every side.\n\np: Cleanse us, Deva.Savitar, with Three, O Soma, with sublimest forms, Agni, with forms of power and might.\n\np: May the Devas’ company make me clean, and Vasus make rue pure by song. Purify me, ye General Devas; O Jatavedas, make me pure.\n\np: Fill thyself full of juice, flow forth, O Soma, thou with all thy stalks, the best oblation to the Devas.\n\np: We with our homage have approached the Friend who seeks our wondering praise, Young, strengthener of the solemn rite.\n\np: Lost is Alayya's axe. O Soma, Deva.do thou send it back hither in thy flow Even, Soma, Deva, if ’twere a mole.\n\np: The man who reads the essence stored by saints, the Pavamani hymns, Tastes food completely purified, made sweet by Matarisvan's touch.\n\np: Whoever reads the essence stored by saints, the Pavamani hymns, Sarasvati draws forth for him water and butter, milk and meath.","people":["Indu","Pavamana","Indra","Soma","Agni","Vayu","Savitar","Pusan","Sarasvati","Deva","Matarisvan"],"places":[],"things":["Meath","Milk","Steeds","Soma","Water","Chariots","Offering","Light","Wealth","Food","Men","Stream","Flow","Might","Juice","Song","Strong","Praise","Worshipper","Delight","Excellent","Pressing-Stones","Offerings","Libations","Drops","Friend","Hero","spoil","Cattle"],"groups":["Devas","Jatavedas","Man","Vasus"],"concepts":["Strength","Offering","Offerings","Giver","Libations","Speech"],"hash":"md5-/5BIu0pbDeLQ1VpXqdlAYA==","created":"Monday, April 8, 2024 - 10:51:55 PM"},{"id":"7c1157d7-5f84-4a1a-b5e0-0f11e5275094","key":"09068","book":"09","title":"HYMN LXVIII. Indu Pavamana.","link":"https://indra.ai/rigveda/hymns/09068.html","text":"p: THE drops of Soma juice like cows who yield their milk have flowed forth, rich in meath, unto the Shining One, and, seated on the grass, raising their voice, assumed the milk, the covering robe wherewith the udders stream.\n\np: He bellows with a roar arourd the highest twigs: the Tawny One is sweetened as he breaks them up. Then passing through the sieve into the ample room, the Deva.throws off the dregs according to his wish.\n\np: The gladdening drink that measured out the meeting Twins fills full with milk the Eternal Ever-waxing Pair. Bringing to light the Two great Regions limitless, moving above them he gained sheen that never fades.\n\np: Wandering through, the Parents, strengthening the floods, the Sage makes his place swell with his own native might. The stalk is mixed with grain: he comes led by the men together with the sisters, and preserves the Head.\n\np: With energetic intellect the Sage is born, deposited as germ of Law, far from the Twins. They being young at first showed visibly distinct the Creature that is half-concealed and half-exposed.\n\np: The sages knew the form of him the Gladdener, what time the Falcon brought the plant from far away. Him who assures success they beautified in streams, the stalk who yearned therefor, mighty and meet for praise.\n\np: Together with the Rsis, with their prayers and hymns ten women deck thee, Soma, friendly when effused. Led by the men, with invocations of the Devas, through the fleece, thou hast given us strength to win the spoil.\n\np: Songs resonant with praise have celebrated him. Soma, Friend, springing forth with his fair company. Even him who rich in meath, with undulating stream, Winnner of Wealth, Immortal, sends his voice from heaven,\n\np: He sends it into all the region forth from heaven. Soma, while he is filtcred, settles in the jars. With milk and waters is he decked when pressed with stones: Indu, when purified, shall find sweet rest and room.\n\np: Even thus poured forth How on thy way, O Soma, vouchsafing us most manifold lively vigour. We will invoke benevolent Earth and Heaven. Give us, ye Devas, riches with noble heroes.","people":["Indu","Soma","Deva"],"places":["Earth","Heaven"],"things":["Meath","Milk","Born","Soma","Waters","Light","Wealth","Men","Streams","Stream","Might","Juice","Mighty","Grass","Praise","Voice","Heroes","Form","Songs","Drops","Friend","Sage","Parents","spoil","Riches"],"groups":["Devas","Immortal","Rsis"],"concepts":["Immortal","Strength","Noble"],"hash":"md5-ZBX0tQNXSAuBeWYVWGuaKg==","created":"Monday, April 8, 2024 - 10:51:55 PM"},{"id":"ebf415a2-e71c-4c32-8206-cc485d40e792","key":"09069","book":"09","title":"HYMN LXIX. Indu Pavamana.","link":"https://indra.ai/rigveda/hymns/09069.html","text":"p: LAID like an arrow on the bow the hymn hath been loosed like a young calf to the udder of its dam. As one who cometh first with full stream she is milked the Soma is impelled to this man's holy rites.\n\np: The thought is deeply fixed; the savoury juice is shed; the tongue with joyous sound is stirring in the mouth; And Pavamana, like the shout of combatants, the drop rising in sweet juice, is flowing through the fleece.\n\np: He flows about the sheep-skin, longing for a bride: he looses Aditi's Daughters for the worshipper. The sacred drink hath come, gold-tinted, well-restrained: like a strong Bull he shines, whetting his manly might.\n\np: The Bull is bellowing; the Cows are coming nigh: the Devas approach the Deva's own resting-place. Onward hath Soma passed through the sheep's fair bright fleece, and hath, as ’twere, endued a garment newly washed.\n\np: The golden-hued, Immortal, newly bathed, puts on a brightly shining vesture that is never harmed. He made the ridge of heaven to be his radiant robe, by sprinkling of the bowls from moisture of the sky.\n\np: Even as the beams of Surya, urging men to speed, that cheer and send to sleep, together rush they forth, these swift outpourings in long course of holy rites: no form save only Indra shows itself so pure.\n\np: As down the steep slope of a river to the vale, drawn from the Steer the swift strong draughts have found a way. Well be it with the men and cattle in our home. May powers, O Soma. May the people stay with us.\n\np: Pour out upon us wealth in goods, in gold, in steeds, in corn, and great heroic strength. Ye, Soma, are my Fathers, lifted up on high as heads of heaven and makers of the strength of life.\n\np: These Pavamanas here, these drops of Soma, to Indra have sped forth like cars to booty. Effused, they pass the cleansing fleece, while, gold-hued, they cast their covering off to pour the rain down.\n\np: O Indu, flow thou on for lofty Indra, flow blameless, very gracious, foe-destroyer. Bring splendid treasure.s to the man who lauds thee. O Heaven and Earth, with all the Devas protect. us.","people":["Indu","Pavamana","Indra","Soma","Deva","Surya","Aditi"],"places":["Earth","Heaven","Sky"],"things":["Cheer","Steeds","Soma","Treasure","Wealth","Men","River","Stream","Flow","Might","Juice","Rain","Gold","Home","Strong","Worshipper","Hymn","Form","People","Powers","Drops","Cars","Cattle","Life"],"groups":["Devas","Fathers","Immortal","Man"],"concepts":["Life","Heroic","Cars","Immortal","Holy","Sacred","Strength","Swift"],"hash":"md5-toMdPr1Dgs4MwGG2w1N22Q==","created":"Monday, April 8, 2024 - 10:51:55 PM"},{"id":"6075f110-c215-4dee-94fc-7451f84b6447","key":"09070","book":"09","title":"HYMN LXX. Indu Pavamana.","link":"https://indra.ai/rigveda/hymns/09070.html","text":"p: THE three times seven Milch-kine in the eastern heaven have for this Soma poured the genuine milky draught. Four other beauteous Creatures hath he made for his adornment, when he waxed in strength through holy rites.\n\np: Longing for lovely Amrta, by his wisdom he divided, each apart from other, earth and heaven. He gladly wrapped himself in the most lucid floods, when through their glory they found the Deva's resting-place.\n\np: May those his brilliant rays he ever free from death, inviolate, for both classes of created things. Rays wherewith powers of men and Devas are purified. Yea, even for this have sageswelcomed him as King.\n\np: He, while he is adorned by the ten skilful ones, that he too in the Midmost Mother. May create, While he is watching o’er the lovely Amrta's ways, looks on both races as Beholder of mankind.\n\np: He, while he is adorned to stream forth mighty strength, rejoices in his place between the earth and heaven. The Steer dispels the evil-hearted with his might, aiming at offerings as an archer at the game.\n\np: Beholding, as it were, Two Mother Cows, the Steer goes roaring on his way even as the Maruts roar. Knowing Eternal Law, the earliest light of heaven, he, passing wise, was chosen out to tell it forth.\n\np: The fearful Bull is bellowing with violent might, far-sighted, sharpening his yellowcoloured horns. Soma assumes his seat in the well-fashioned place: the cowhide and the sheepskin are his ornament.\n\np: Bright, making pure his body free from spot and stain, on the sheep's back the Golden-coloured hath flowed down. Acceptable to Mitra, Vayu, Varuna, he is prepared as threefold meal by skilful men.\n\np: Flow on for the Deva's banquet, Soma, as a Steer, and enter Indra's heart, the Soma's reservoir. Bear us beyond misfortune ere we be oppres. sed. the man who knows the land directs the man who asks.\n\np: Urged like a car-steed flow to strength, O Soma: Indu, flow onward to the throat of Indra. Skilled, bear us past, as in a boat o’er water: as battling Hero save us from the foeman.","people":["Indu","Indra","Soma","Vayu","Mitra","Varuna","Deva"],"places":["Earth","Heaven"],"things":["Mankind","Soma","Water","Glory","Light","Men","Stream","Flow","Might","Wise","Mighty","Car","Reservoir","Banquet","Powers","Offerings","Hero","King","Death","Amrta"],"groups":["Devas","Maruts","Mother","Man"],"concepts":["Evil","Death","Holy","Strength","Wisdom","Offerings","Eternal Law"],"hash":"md5-3vGVgT3kL/iMjpPCLku/kA==","created":"Monday, April 8, 2024 - 10:51:55 PM"},{"id":"a4d0c3e5-8878-43a4-ac54-aa08291526c1","key":"09071","book":"09","title":"HYMN LXXI. Indu Pavamana,","link":"https://indra.ai/rigveda/hymns/09071.html","text":"p: THE guerdon is bestowed: the Mighty takes his Seat, and, ever-Watchful, guards from fiend and evil sprite. Gold-hued, he makes the cloud his diadem, the milk his carpet in both worlds, and prayer his robe of state.\n\np: Strong, bellowing, he goes, like one who subdues the folk; he lets this hue of Asuras flow off from him, Throws off his covering, seeks his father's meeting-place, and thus makes for himself the bright robe he assumes.\n\np: Onward he flows, from both the hands, pressed out with stones: excited by the prayer, the water makes him wild. He frolics and draws near, completes his work with song, and bathes in streams to satisfy the worshipper.\n\np: They pour out meath around the Master of the house, Celestial Strengthener of the mountain that gives might; In whom, through his great powers, oblation-eating cows in their uplifted udder mix their choicest milk.\n\np: They, the ten sisters, on the lap of Aditi, have sent him forward like a car from both the arms. He wanders and comes near the Cow's mysterious place, even the place which his inventions have produced.\n\np: Like as a falcon to his home, so speeds the Deva.to his own golden wisely-tashioned place to rest. With song they urge the darling to the sacred grass: the Holy One goes like a courser to the Devas.\n\np: From far away, from heaven, the redhued noted Sage, Steer of the triple height, hath sung unto the kine. With thousand guidings he, leading this way and that, shines, as a singer, splendidly through many a morn.\n\np: His covering assumes a radiant hue; where’er he comes into the fight he drives the foe afar. The Winner of the Floods, with food he seeks the host of heaven, he comes to praises glorified with milk.\n\np: Like a bull roaming round the herds he bellows: he hath assumed the brilliancy of Surya. Down to the earth hath looked the heavenly Falcon: Soma with wisdom views all living creatures.","people":["Soma","Deva","Surya","Aditi"],"places":["Earth","Heaven"],"things":["Meath","Master","Milk","Work","Soma","Water","Singer","Food","Streams","Flow","Might","Song","Gold","Home","Strong","Mighty","Grass","Car","Worshipper","Powers","Sage","Cow"],"groups":["Devas","Asuras","Father"],"concepts":["Celestial","Evil","Heavenly","Holy","Sacred","Wisdom","Winner"],"hash":"md5-MWJPSuDPvJZtB64zqnwAmQ==","created":"Monday, April 8, 2024 - 10:51:55 PM"},{"id":"73fc42ff-c0b2-4def-ad32-f5bf7ba8fc33","key":"09072","book":"09","title":"HYMN LXXII. Indu Pavamana.","link":"https://indra.ai/rigveda/hymns/09072.html","text":"p: THEY cleanse the Gold-hued: like a red Steed is he yoked, and Soma in the jar is mingled with the milk. He sendeth out his voice, and many loving friends of him the highly lauded hasten with their songs.\n\np: The many sages utter words in unison, while into Indra's throat they pour the Soma juice, when, with the ten that dwell together closely joined, the men whose hands are skilful cleanse the lovely meath.\n\np: He goes upon his way, unresting, to the cows, over the roaring sound which Sarya's Daughter loves. The Falcon brought it to him for his own delight: now with the twofold kindred sisters is his home.\n\np: Washed by the men, stone-pressed, dear on the holy grass, faithful to seasons, Lord of cattle from of old, most liberal, completing offering for men, O Indra, pure bright Soma, Indu, flows for thee.\n\np: O Indra, urged by arms of men and poured in streams, Soma flows on for thee afterḥis Deva like kind. Plans thou fulfillest, gatherest thoughts for offering: in the bowls sits the Gold-hued like a roosting bird.\n\np: Sages well-skilled in work, intelligent, drain out the stalk that roars, the Sage, the Everlasting One. The milk, the hymns unite them with him in the place of offering, his seat who is produced anew.\n\np: Earth's central point, sustainer of the mighty heavens, distilled into the streams, into the waters' wave, as Indra's thunderbolt, Steer with farspreading wealth, Soma is flowing on to make the heart rejoice.\n\np: Over the earthly region flow thou on thy way, helping the praiser and the pourer, thou Most Wise. Let us not lack rich treasure. reaching to our home, an. May we clothe ourselves in manifold bright wealth.\n\np: Hither, O Indu, unto us a hundred gifts of steeds, a thousand gifts of cattle and of gold, Measure thou forth, yea, splendid ample strengthening food do thou, O Pavamana, heed this laud of ours.","people":["Indu","Pavamana","Indra","Soma","Deva"],"places":["Earth"],"things":["Meath","Milk","Steeds","Work","Lord","Seasons","Soma","Waters","Offering","Treasure","Wealth","Food","Men","Streams","Flow","Juice","Gold","Home","Wise","Mighty","Grass","Voice","Delight","Friends","Songs","Bird","Sage","Cattle","Gifts"],"groups":[],"concepts":["Holy","Offering"],"hash":"md5-nIUcE9GsA7tJHE+BEBb6XA==","created":"Monday, April 8, 2024 - 10:51:55 PM"},{"id":"51fa55fe-833a-430e-8ea0-a9eba1f0471c","key":"09073","book":"09","title":"HYMN LXXIII. Indu Pavamana.","link":"https://indra.ai/rigveda/hymns/09073.html","text":"p: THEY from the spouting drop have sounded at the rim: naves speed together to the place of offering. That Asura hath formed, to seize, three lofty heights. The ships of truth have borne the pious man across.\n\np: The strong Steers, gathering, have duly stirred themselves,and over the stream's wave the friends sent forth the song. Engendering the hymn, with flowing streams of meath, indra's dear body have they caused to wax in strength.\n\np: With sanctifying gear they sit around the song: their ancient Father guards their holy work from harm. Varuna hath o’erspread the mighty sea of air. Sages had power to hold him in sustaining floods.\n\np: Sweet-tongued, exhaustless, they have sent their voices down togetlier, in heaven's vault that pours a thousand streams. His wildly-restless warders never close an eye: in every place are found the bonds that bind man last.\n\np: O'er Sire and Mother they have roared in unison bright with the verse of praise, burning up riteless men, Blowing away with supernatural might from earth and from the heavens the swarthy skin which Indra hates.\n\np: Those which, as guides of song and counsellors of speed, were manifested from their ancient dwelling place. From these the eyeless and the deaf have turned aside: the wicked travel not the pathway of the Law.\n\np: What time the filter with a thousand streams is stretched, the thoughtful sages purify their song therein. Bright-coloured are their spies, vigorous, void of guile, excellent, fair to see, beholders of mankind.\n\np: Guardian of Law, most wise, h. May not be deceived: three Purifiers hath he set within his heart. With wisdom he beholds all creatures that exist: he drives into the pit the hated riteliess ones.\n\np: The thread of offering spun in the cleansing sieve, on Varuna's tongue-tip, by supernatural might. This, by their striving, have the prudent ones attained: he who hath not this power shall sink into the pit.","people":["Indra","Varuna"],"places":["Earth","Heaven"],"things":["Mankind","Meath","Work","Offering","Air","Men","Streams","Stream","Might","Song","Wise","Strong","Mighty","Praise","Hymn","Excellent","Friends"],"groups":["Asura","Steers","Father","Mother","Man"],"concepts":["Holy","Strength","Wisdom","Offering","Truth"],"hash":"md5-HtcRtp3pehQclbFGPg/z8w==","created":"Monday, April 8, 2024 - 10:51:55 PM"},{"id":"b357ba49-98ee-4c70-9958-584ef766140d","key":"09074","book":"09","title":"HYMN LXXIV. Indu Pavamana","link":"https://indra.ai/rigveda/hymns/09074.html","text":"p: BORN like a youngling he hath clamoured in the wood, when he, the Red, the Strong, would win the light of heaven. He comes with heavenly seed that makes the water swell: him for wide-spreading shelter we implore with prayer.\n\np: A far-extended pillar that supports the sky the Soma-stalk, filled full, moves itself every way. He shall bring both these great worlds while the rite proceeds: the Sage holds these who move! together and all food.\n\np: Wide space hath he who follows Aditi's right path, and mighty, well-made food, meath blent with Soma juice; He who from hence commands the rain, Steer of the kine, Leader of floods, who helps us hence, who claims our laud.\n\np: Butter and milk are drawn from animated cloud; thence Amrta is produced, centre of offering. Hini the Most Bounteous Ones, ever united, love; him as ouir Friend the Men who make all swell rain down.\n\np: The Soma-stalk hath roared, following with the wave: he swells with sap for man the skin which Devas enjoy. Upon the lap of Aditi he lays the germ, by means whereof we gain children and progeny.\n\np: In the third region which distils a thousand streams. May the Exhaustless Ones descend with procreant power. The kindred Four have been sent downward from the heavens: dropping with oil they bring Amrta and sacred gifts.\n\np: Soma assumes white colour when he strives to gain: the bounteous Asura knows full many a precious boon. Down the steep slope, through song, he comes to offering, and he will burst the water-holding cask of heaven,\n\np: Yea, to the shining milk-anointed beaker, as to his goal, hath stepped the conquering Courser. Pious-souled men have sent their giffi of cattle unto Kaksivan of the hundred winters.\n\np: Soma, thy juice when thou art blended with the streams, flows, pavamana, through the long wool of the sheep. So, cleansed by sages. O best giver of delight, grow sweet for Indra, pavamana! for his drink.","people":["Pavamana","Indra","Soma","Aditi","Kaksivan"],"places":["Heaven","Sky"],"things":["Meath","Leader","Milk","Born","Soma","Water","Offering","Light","Boon","Food","Men","Streams","Juice","Rain","Song","Strong","Mighty","Delight","Friend","Sage","Cattle","Gifts","Amrta"],"groups":["Devas","Asura","Progeny","Man"],"concepts":["Heavenly","Love","Sacred","Offering","Giver"],"hash":"md5-av7JTbZmPMb6ZQNC8WymjQ==","created":"Monday, April 8, 2024 - 10:51:55 PM"},{"id":"6b138022-c37b-4b10-a733-7758737066a0","key":"09075","book":"09","title":"HYMN LXXV. Indu Pavamana.","link":"https://indra.ai/rigveda/hymns/09075.html","text":"p: GRACIOUSLY-MINDED he is flowing on his way to win dear names o’er which the Youthful One grows great. The Mighty and Far-seeing One hath mounted now the mighty Surya's car which moves to every side.\n\np: The Speaker, unassailable Master of this hymn, the Tongue of offering pours forth the pleasant meath. Within the lustrous region of the heavens the Son makes the third secret name of Mother and of Sire.\n\np: Sending forth flashes he hath bellowed to the jars, led by the men into the golden reservoir. The milky streams of offering have sung to him: he of the triple height shines brightly through the morns.\n\np: Pressed by the stones, with hymns, and graciously inclined, illuminating both the Parents. Heaven and Earth. He flows in ordered season onward through the flee, a current of sweet juice still swelling day by day.\n\np: Flow onward, Soma, flow to bring prosperity: cleansed by the men, invest thee with the milky draught. What gladdening drinks thou hast, foaming, exceeding strong, even with these incite Indra to give us wealth.","people":["Indra","Soma","Surya"],"places":["Earth","Heaven"],"things":["Meath","Master","Soma","Offering","Wealth","Men","Streams","Flow","Juice","Strong","Mighty","Car","Reservoir","Hymn","Parents"],"groups":["Mother","Son"],"concepts":["Offering"],"hash":"md5-ygXtdwOoH/V8+3m9gnWBig==","created":"Monday, April 8, 2024 - 10:51:55 PM"},{"id":"ca9eb01a-f611-418c-92e1-6c88fda614bf","key":"09076","book":"09","title":"HYMN LXXVI. Indu Pavamana.","link":"https://indra.ai/rigveda/hymns/09076.html","text":"p: ON flows the potent juice, sustainer of the heavens, the strength of Devas, whom men must hail with shouts of joy. The Gold-hued, started like a courser by brave men, impetuously winneth splendour in the streams.\n\np: He takes his weapons, like a hero, in his hands, fain to win light, car-borne, in forays for the kine. Indu, while stimulating India's might, is urged forward and balmed by sages skilful in their task.\n\np: Soma, as thou art purified with flowing wave, exhibiting thy strength enter thou Indra's throat. Make both worlds stream for us, as lightning doth the clouds: mete out exhaustless powers for us, as ’twere through song.\n\np: Onward he flows, the King of all that sees the light: the Rsis’ Lord hath raised the song of offering; Even he who is adorned with Surya's arrowy beam, Father of hymns, whose wisdom is beyond our reach.\n\np: Like as a bull to herds, thou flowest to the pail, bellowing as a steer upon the water's lap. So, best of Cheerers, thou for Indra flowest on that we, with thy protection. May o’ercome in fight.","people":["Indu","Indra","Soma","Surya"],"places":[],"things":["Lord","Soma","Water","Offering","Light","Men","Streams","Stream","Might","Juice","Song","Joy","Gold","Car","Brave","Splendour","Powers","Hero","King"],"groups":["Devas","Father","Rsis"],"concepts":["Strength","Wisdom","Offering"],"hash":"md5-gwsgeaTRDE+3rcFGHF0/6Q==","created":"Monday, April 8, 2024 - 10:51:55 PM"},{"id":"c2cb65e5-fe46-45b7-b062-8b75b68c4909","key":"09077","book":"09","title":"HYMN LXXVII. Indu Pavamana.","link":"https://indra.ai/rigveda/hymns/09077.html","text":"p: MORE beauteous than the beautiful, as Indra's bolt, this Soma, rich in sweets, hath clamoured in the vat. Dropping with oil, abundant, streams of offering flow unto him like milch-kine, lowing, with their milk.\n\np: On flows that Ancient One whom, hitherward, from heaven, sped through the region of the air, the Falcon snatched. He, quivering with alarm and terrified in heart before bow-armed Krsanu, holdeth fast the sweet.\n\np: May those first freshest drops of Soma juice effused flow on, their way to bring us mighty strength in kine. Beauteous as serpents, worthy to be looked upon, they whom each sacred gift and all our meditations have pleased.\n\np: May that much-lauded Indu, with a heart inclined to us, well-knowing, fight against our enemies. He who hath brought the germ beside the Strong One's seat moves onward to the widely-opcned stall of kine.\n\np: The active potent juice of heaven is flowing on, great Varuna whom the forward man can ne’er deceive. Mitra, the Holy, hath been pressed for troubled times, neighing like an impatient horse amid the herd,","people":["Indu","Indra","Soma","Mitra","Varuna"],"places":["Heaven"],"things":["Milk","Soma","Offering","Air","Streams","Flow","Juice","Strong","Mighty","Gift","Drops","Horse"],"groups":["Man"],"concepts":["Beautiful","Holy","Sacred","Strength","Offering","Ancient One","Pleased"],"hash":"md5-yHqiSutW84Zcg/woadrm3g==","created":"Monday, April 8, 2024 - 10:51:55 PM"},{"id":"c48defff-42e9-423f-b505-73d179451b7d","key":"09078","book":"09","title":"HYMN LXXVIII. Indu Pavamana.","link":"https://indra.ai/rigveda/hymns/09078.html","text":"p: RAISING his voice the King hath flowed upon his way: invested with the waters he would win the kine. The fleece retains his solid parts as though impure, and bright and cleansed he seeks the special place of Devas.\n\np: Thou, Soma, art effused for Indra by the men, balmed in the wood as wave, Sage, Viewer of mankind. Full many are the paths whereon tho. Mayest go: a thousand bay steeds hast thou resting in the bowls.\n\np: Apsarases who dwell in waters of the sea, sitting within, have flowed to Soma wise of heart. They urge the Master of the house upon his way, and to the Eternal Pavamana pray for bliss.\n\np: Soma flows on for u's as winner of the kine, winner of thousands, cars, water, and light, and gold; He whom the Devas have made a gladdening draught to drink, the drop most sweet to taste, weal-bringing, red of hue.\n\np: Soma, as Pavamana thou, our faithful Friend, making for us these real treasure.s, flowest on. Slay thou the enemy both near and,far away: grant us security and ample pasturage.","people":["Pavamana","Indra","Soma"],"places":[],"things":["Mankind","Master","Steeds","Soma","Waters","Water","Light","Treasure","Men","Gold","Wise","Voice","Bliss","Friend","King","Sage","Cars","Security"],"groups":["Devas"],"concepts":["Special","Cars","Winner"],"hash":"md5-JSvcVnMdDP0jqyoC6oTi9g==","created":"Monday, April 8, 2024 - 10:51:55 PM"},{"id":"2c09fdee-9272-4aa4-9070-54d217ad8573","key":"09079","book":"09","title":"HYMN LXXIX. Indu Pavamana.","link":"https://indra.ai/rigveda/hymns/09079.html","text":"p: SPONTANEOUS let our drops of Soma juice flow on, pressed, golden-hued, among the Devas of lofty heaven. Perish among us they who give no gifts of food! perish the godless! May our meditations obtain success.\n\np: Forward to us the drops, distilling meath, shall flow, like riches for whose sake we urge the horses on. Beyond the crafty hindering of all mortal me. May we continually bear precious wealth away.\n\np: Yea, yerily, foe of hate shown to himself is he, yea, verity, destroyer too of other hate. As thirst subdueth in the desert, conquer thou, O Soma Pavarnana, men of evil thoughts.\n\np: Near kin to thee is he, raised loftiest in the heavens: upon the earth's high ridge thy scions have grown forth. The press-stones chew and crunch thee on the ox's hide: sages have milked thee with their hands into the streams.\n\np: So do they hurry on thy strong and beauteous juice, O Indu, as the first ingredient of the draught. Bring low, thou Pavamana, every single foe, and be thy might shown forth as sweet and gladdening drink.","people":["Indu","Pavamana","Soma"],"places":["Earth","Heaven"],"things":["Meath","Soma","Wealth","Food","Men","Streams","Flow","Might","Juice","Strong","Drops","Horses","Riches","Gifts"],"groups":["Devas"],"concepts":["Evil"],"hash":"md5-hjTsOwlTTvYunzKtFatB/g==","created":"Monday, April 8, 2024 - 10:51:55 PM"},{"id":"bb77838c-1fb6-4caa-9f79-dd8462504b73","key":"09080","book":"09","title":"HYMN LXXX. Indu Pavamana.","link":"https://indra.ai/rigveda/hymns/09080.html","text":"p: ON flows the stream of Soma who beholds mankind: by everlasting Law he calls the Devas from heaven. He lightens with the roaring of Br aspati: h the lakes have not contained the pourings of juice.\n\np: Thou, powerful Soma, thou to whom the cows have -lowed, ascendest bright with sheen, thine iron-fashioned home. Thou, lengthening our princes' life and high renown, flowest for Indra as his might to gladdening drink.\n\np: Best giver of delight, he flows to Indra's throat, robing himself in might, Auspicious One, for fame. He spreads himself abroad to meet all things that be: the vigorous Tawny Steed flows sporting on his way.\n\np: The men, the ten swift fingers, milk thee out for Devas, even thee most rich in meath, with thousand flowing streams. Soma who winnest thousands, driven by the men, expressed with stones, bring, as thou flowest, all the Devas.\n\np: Deft-handed men with stones, the ten swift fingers, drain thee into waters, thee, the Steer enriched with sweets. Thou, Soma, gladdening Indra, and the Heavenly Host, flowest as Pavamana like a river's wave.","people":["Pavamana","Indra","Soma"],"places":["Heaven"],"things":["Mankind","Meath","Milk","Soma","Iron-Fashioned Home","Waters","Men","River","Streams","Stream","Might","Juice","Home","Delight","Life"],"groups":["Devas"],"concepts":["Life","Heavenly","Giver","Auspicious","Powerful","Swift"],"hash":"md5-ebyTFq12rmMwEFIdUWBy3A==","created":"Monday, April 8, 2024 - 10:51:55 PM"},{"id":"96a26788-d529-456d-b0e7-347da6291cf8","key":"09081","book":"09","title":"HYMN LXXXI. Indu Pavamana.","link":"https://indra.ai/rigveda/hymns/09081.html","text":"p: ONWARD to Indra's throat move, beauteously adorned, the waves of Soma as he purifies himself, when they, brought forward with the lovely curd of kine, effused, have cheered the Hero to bestow his gifts.\n\np: Hither hath Soma flowed unto the beakers, like a chariot-horse, a stallion swift upon his way. Thus, knowing both the generations, he obtains the rights and dues of Devas from yonder and from hence.\n\np: While thou art cleansed, O Soma, scatter wealth on us; Indu, bestow great bounty as a liberal Prince. Giver of life, with wisdom help to opulence; strew not our home possessions far away from us.\n\np: Hither let Pusan Pavamana come to us, Varuna, Mitra, bountiful, of one accord, the Maruts, Asvins, Vayu, and Narasamsa, Savitar, Tvastar, tractable Sarasvati.\n\np: Both Heaven and Earth, the all-invigorating Pair, Vidhatar, Aditi, and Aryaman the Deva, Bhaga who blesses men, the spacious Firmament.let all the Devas in Pavamana take delight.","people":["Indu","Pavamana","Indra","Soma","Vayu","Mitra","Varuna","Asvins","Narasamsa","Tvastar","Savitar","Pusan","Sarasvati","Bhaga","Deva","Aditi","Vidhatar","Aryaman"],"places":["Earth","Heaven","Firmament"],"things":["Soma","Wealth","Men","Help","Home","Delight","Hero","Horse","Life","Gifts"],"groups":["Devas","Maruts"],"concepts":["Life","Wisdom","Giver","Swift"],"hash":"md5-pzwgr5W6NVLyMN0TqpAJ0w==","created":"Monday, April 8, 2024 - 10:51:55 PM"},{"id":"76209bd3-209f-4fd1-a602-6864c867c6c9","key":"09082","book":"09","title":"HYMN LXXXII. Indu Pavamana.","link":"https://indra.ai/rigveda/hymns/09082.html","text":"p: EVEN as a King hath Soma, red and tawny Bull, been pressed: the Wondrous One hath bellowed to the kine. While purified he passes through the filtering fleece to seat him hawk-like on the place that drops with oil.\n\np:  To glory goest thou, Sage with disposing skill, like a groomed steed thou rusbest forward to the prize. O Soma, be thou gracious, driving off distress: thou goest, clothed in butter, to a robe of state.\n\np: Parjanya is the Father of the Mighty Bird: on mountains, in earth's centre hath he made his home. The waters too have flowed, the Sisters, to the kine: he meets the pressing-stones at the beloved rite.\n\np: Thou givest pleasure as a wife delights her lord. Listen, O Child of Pajri, for to thee I speak. Amid the holy songs go on that we may live: in time of trouble, Soma, watch thou free from blame.\n\np: As to the men of old thou camest, Indu unharmed, to strengthen, winning hundreds, thousands, So now for new felicity flow onward: the waters follow as thy law ordaineth.","people":["Indu","Soma","Parjanya"],"places":["Earth"],"things":["Lord","Mountains","Soma","Waters","Glory","Men","Flow","Home","Mighty","Pressing-Stones","Songs","Drops","King","Bird","Sage","Winning"],"groups":["Father","Child","Wife"],"concepts":["Holy"],"hash":"md5-z8sb8PXgK0ZggqjPqDmYEg==","created":"Monday, April 8, 2024 - 10:51:55 PM"},{"id":"b3431ed6-1be8-4a33-acd5-e16883bd724c","key":"09083","book":"09","title":"HYMN LXXXIII. Indu Pavamana.","link":"https://indra.ai/rigveda/hymns/09083.html","text":"p: SPREAD is thy cleansing filter, Narasamsa: as Prince, thou enterest its limbs from every side. The raw, whose mass hath not been heated gains not this: they only which are dressed, which bear, attain to it.\n\np: High in the seat of heaven is spread the Scorcher's sieve: its threads are standing separate, glittering with light. The Swift Ones favour him who purifieth this: with consciousness they stand upon the height of heaven.\n\np: The foremost spotted Steer hath made the Mornings shine, and yearning after strength sustains all things that be. By his high wisdom have the mighty Sages wrought: the Fathers who behold mankind laid down the germ,\n\np: Gandharva verily protects his dwellingplace; Wondrous, he guards the generations of the Devas. Lord of the snare, he takes the foeman with the snare: those who are most devout have gained a share of meath.\n\np: Rich in oblations! robed in cloud, thou corapassest oblation, offering, the mighty seat of Devas. King, on thy chariot-sieve thou goest up to war, and with a thousand weapons winnest lofty fame.","people":["Narasamsa"],"places":["Heaven"],"things":["Mankind","Meath","Lord","Offering","Shine","Light","Mighty","King"],"groups":["Devas","Fathers","Gandharva"],"concepts":["Strength","Wisdom","Devout","Offering","Swift"],"hash":"md5-B7N6LxmumI4B8LR0MRtSLQ==","created":"Monday, April 8, 2024 - 10:51:55 PM"},{"id":"e64dd4e8-3d76-40d1-8f87-4d39c8bc533d","key":"09084","book":"09","title":"HYMN LXXXIV. Indu Pavamana.","link":"https://indra.ai/rigveda/hymns/09084.html","text":"p: FLOW, cheering Devas, most active, winner of the flood, for Indra, and for Vayu, and for Varuna. Bestow on us to-day wide room with happiness, and in tbine ample dwelling laud the Host of Heaven.\n\np: He who hath come anear to creatures that have life, Immortal Soma flows onward to all of them. Effecting, for our aid, both union and release, Indu, like Surya, follows closely after Dawn.\n\np: He who is poured with milk, he who within the plants hastes bringing treasure. for the happiness of Devas. He, poured forth in a stream flows with the lightning's flash, Soma who gladdens Indra and the Host of Heaven.\n\np: Winner of thousands, he, this Soma, flows along, raising a vigorous voice that wakens with the dawn. Indu with winds drives on the ocean of the air, he sinks within the jars, he rests in Indra's heart.\n\np: The kine with milk dress him who makes the milk increase, Soma, amid the songs, who finds the light of heaven. Winner of wealth, the effectual juice is flowing on, Singer and Sage by wisdom, dear as heaven itself.","people":["Indu","Indra","Soma","Vayu","Varuna","Surya","Dawn"],"places":["Ocean","Heaven"],"things":["Milk","Soma","Singer","Light","Air","Treasure","Wealth","Stream","Flow","Juice","Voice","Songs","Sage","Life"],"groups":["Devas","Immortal"],"concepts":["Life","Immortal","Wisdom","Winner"],"hash":"md5-FZduvRFabx4TpEYablky/g==","created":"Monday, April 8, 2024 - 10:51:55 PM"},{"id":"9170a4b8-8ab2-44a6-bb85-b38180c4216e","key":"09085","book":"09","title":"HYMN LXXXV. Indu Pavamana.","link":"https://indra.ai/rigveda/hymns/09085.html","text":"p: FLOW on to Indra, Soma, carefully effused: let sickness stay afar together with the fiends. Let not the double-tongued delight them with thy juice. here be thy flowing drops laden with opulence.\n\np: O Pavamana, urge us forward in the fight thou art the vigour of the Devas, the well-loved drink. Smite thou our enemies who raise the shout of joy: Indra, drink Soma juice, and drive away our foes.\n\np: Unharmed, best Cheerer O Indu, flowest on: thou, even thou thyself, art Indra's noblest food. Full many a wise man lifts to thee the song of praise, and hails thee with a kiss as Sovran of this world.\n\np: Wondrous, with hundred streams, hymned in a thousand songs, Indu pours out for Indra his delightrul meath. Winning us land and waters, flow thou hitherward: Rainer of bounties, Soma, make broad way for us.\n\np: Roaring within the beaker thou art balmed with milk: thou passest through the fleecy filter all at once. Carefully cleansed and decked like a prizewinning steed, O Soma, thou hast flowed down within Indra's throat.\n\np: Flow onward sweet of flavour for the Heavenly Race, for Indra sweet, whose name is easily invoked: Flow sweet for Mitra, Varuna, and Vayu, rich in meath, inviolable for Narasamsa.\n\np: Ten rapid fingers deck the Courser in the jar: with hymns the holy singers send their voices forth. The filtering juices hasten to their eulogy, the drops that gladden find their way to Indra's heart.\n\np: While thou art purified pour on us hero strength, great, far-extended shelter, spacious pasturage. Let no oppression master this our holy work. May we, O Indu, gain all opulence through thee.\n\np: The Steer who sees afar hath risen above the sky: the Sage hath caused the lights of heaven to give their shine. The. King is passing through the filter with a roar: they drain the milk of heaven from him who looks on men.\n\np: High in the vault of heaven, unceasing, honey-tongued, the Loving Ones drain out the mountain-haunting Steer. The drop that hath grown great in waters, in the lake meath-rich, in the stream's wave and in the cleansing sieve.\n\np: The Loving Ones besought with many voices the Eagle who had flown away to heaven. Hymns kiss the Youngling worthy of laudation, resting on earth, the Bird of golden colour.\n\np: High to heaven's vault hath the Gandharva risen, beholding all his varied forms and figures. His ray hath shone abroad with gleaming splendour: pure, he hath lighted both the worlds, the Parents.","people":["Indu","Pavamana","Indra","Soma","Vayu","Mitra","Varuna","Narasamsa"],"places":["Earth","Heaven","Sky"],"things":["Meath","Master","Milk","Work","Soma","Waters","Shine","Food","Men","Streams","Stream","Flow","Juice","Song","Joy","Wise","Praise","Delight","Lake","Splendour","Songs","Drops","Hero","King","Bird","Sage","Parents","Winning"],"groups":["Devas","Gandharva","Man"],"concepts":["Heavenly","Holy","Strength"],"hash":"md5-isTC/CeVoIBPM1E+IKL44g==","created":"Monday, April 8, 2024 - 10:51:55 PM"},{"id":"6833929c-f11d-41b1-9b50-32f5ba465426","key":"09086","book":"09","title":"HYMN LXXXVI. Indu Pavamana.","link":"https://indra.ai/rigveda/hymns/09086.html","text":"p: THY gladdening draughts, O Pavamana, urged by song flow swiftly of themselves like sons of fleet-foot mares. The drops of Soma juice, those eagles of the heavens, most cheering, rich in meath, rest in the reservoir.\n\np: As rapid chariot-steeds, so turned in several ways have thine exhilarating juices darted forth, Soma-drops rich in meath, waves, to the Thunder-armed, to Indra, like milch-kine who seek their calf with milk.\n\np: Like a steed urged to battle, finder of the light; speed onward to the cloud-born reservoir of heaven, a Steer that o’er the woolly surface seeks the sieve, Soma while purified for Indra's nourishment.\n\np: Fleet as swift steeds, thy drops, divine, thought-swift, have been, O Pavamana, poured with milk into the vat. The Rsis have poured in continuous Soma drops, ordainers who adorn thee, Friend whom Rsis love.\n\np: O thou who seest all things, Sovran as thou art and passing strong, thy rays encompass all abodes. Pervading with thy natural powers thou flowest on, and as the whole world's Lord, O Soma, thou art King.\n\np: The beams of Pavamana, sent from earth and heaven, his ensigns who is ever steadfast, travel round. When on the sieve the Golden-hued is cleansed, he rests within the vats as one who seats him in his place.\n\np: Served with fair rites he flows, ensign of offering: Soma advances to the special place of Devas. He speeds with thousand currents to the reservoir, and passes through the filter bellowing as a bull.\n\np: The Sovran dips him in the seain and the streams, and set in rivers with the waters' wave moves on. High heaven's Sustainer at the central point of earth, raised on the fleecy surface Pavamana stands.\n\np: He on whose high decree the heavens and earth depend nath roared and thundered like the summit of the sky. Soma flows on obtaining Indra's friendly love, and, as they purify him, settles in the jars.\n\np: He, light of offering distils delicious meath, most wealthy, Father and begetter of the Devas. He, gladdening, best of Cheerers.hat Indra loves, enriches with mysterious treasure. earth and heaven.\n\np: The vigorous and far-seeing one, the Lord of heaven, flows, shouting to the beaker, with his thousand streams. Coloured like gold he rests in seats where Mitra dwells, the Steer made beautiful by rivers and by sheep.\n\np: In forefront of the rivers Pavamana speeds, in forefront of the hymn, foremost among the kine. He shares the mighty booty in the van of war: the well-armed Steer is purified by worshippers.\n\np: This heedful Pavamana, like a bird sent forth, hath with his wave flowed onward to the fleecy sieve. O Indra, through thy wisdom, b thy thought, O Sage, Soma flows bright and pure between the earth and heaven.\n\np: He, clad in mail that reaches heaven, the Holy One, filling the firmament stationed amid the worlds, knowing. the realm of light, hath come to us in rain: he summons to himself his own primeval Sire.\n\np: He who was first of all to penetrate his form bestowed upon his race wide shelter and defence. From that high station which he hath in loftiest heaven he comes victorious to all encounters here.\n\np: Indu hath started for Indra's special place and slights not as a friend the promise of his Friend. Soma speeds onward like a youth to youtlitial maids, and gains the beaker by a course of bundred paths.\n\np: Your songs, exhilarating, tuneful, uttering praise, are come into the placns where the people meet. Worshippers have exalted Soma with their hymns, and milch kine have come near to meet him with their milk.\n\np: O Indu, while they cleanse thee, pour on us accumulateds Plentiful, nutritious food, Which, ceaseless, thrice a day shall yield us hero power enriched with store of nourishment, and strength, and Meath.\n\np: Far-seeing Soma flows, the Steer, the Lord of hymns, the Furtherer of day, of morning, and of heaven. Mixt with the streams he caused the beakers to resound, and with the singers' aid they entered Indra's heart.\n\np: On, with the prudent singers, flows the ancient Sage and guided by the men hath roared about the vats. Producing Trita's name. May he pour forth the meath, that Vayu and that Indr. May become his Friends.\n\np: He, being purified, hath made the Mornings shine: this, even this is he who gave the rivers room. He made the Three Times Seven pour out the milky flow: Soma, the Cheerer, yields whate’er the heart finds sweet.\n\np: Flow, onward, Soma, in thine own celestial forms, flow, Indu, poured within the beaker and the sieve. Sinking into the throat of Indra with a roar, led by the men thou madest Surya mount to heaven.\n\np: Pressed out with stones thou flowest onward to the sieve, O Indu, entering the depths of Indra's throat. Far-sighted Soma, now thou lookest on mankind: thou didst unbar the cowstall for the Angirases.\n\np: In thee, O Soma, while thou purifitedst thee, high-thoughted sages, seeking favour, have rejoiced. Down from the heavens the Falcon brought thee hitherward, even thee, O Indu, thee whom all our hymns adorn.\n\np: Seven Milch-kine glorify the Tawny-coloured One while with his wave in wool he purifies himself. The living men, the mighty, have impelled the Sage into the waters' lap, the place of offering.\n\np: Indu, attaining purity, plunges through the foe, making Ilis ways all easy for the pious man. Making the kine his mantle, he, the lovely Sage, runs like a sporting courser onward through the fleece.\n\np: The ceaseless watery fountains with their hundred streams sing, as they hasten near, to him the Golden-hued Him, clad in robes of milk, swift fingers beautify on the third height and in the luminous realm of heaven.\n\np: These are thy generations of celestial seed thou art the Sovran Lord of all the world of life. This universe, O Pavamana, owns thy sway; thou, Indu, art the first establisher of Law.\n\np: Thou art the sea, O Sage who bringest alf to light: under thy Law are these five regions of the world. Tlou reachest out beyond the earth, beyond the heavens: thine are the lights, O Pavamana, thine the Sun.\n\np: Thou in the filter, Indu Pavamana, art purified to support the region for the Devas. The chief, the longing ones have sought to hold thee fast, and all these living creatures have been turned to thee.\n\np: Onward the Singer travels o’er the fleecy sieve. the Tawny Steer hath bellowed in the wooden vats. Hymns have been sung aloud in resonant harmony, and holy songs kiss him, the Child who claims our praise.\n\np: He hath assumed the rays of Surya for his robe, spinning, as he knows bow, the triply-twisted thread. He, guiding to the newest rules of Holy Law, comes as the Women's Consort to the special place.\n\np: On flows the King of rivers and the Lord of heaven: he follows with a shout the paths of Holy Law. The Golden-hued is poured forth, with his hundred streams, Wealth-bringer, lifting up his voice while purified.\n\np: Fain to be cleansed pavamana, pourest out, like wondrous Surya, through the fleece, an ample sea. Purified with the hands, pressed by the men with stones, thou speedest on to mighty booty-bringing war.\n\np: Thou, pavamana, sendest food and power in streams. thou sittest in the beakers as a hawk on trees, for Indra poured as cheering juice to make him glad, as nearest and farseeing bearer-up of heaven.\n\np: The Sisters Seven, the Mothers, stand around the Babe, the noble, new-born Infant, skilled in holy song, Gandharva of the floods, divine, beholding men, Soma, that h. May reign as King of all the world.\n\np: As Sovran Lord thereof thou Passest through these worlds, O Indu, harnessing thy tawny well-winged Mares. May they pour forth for thee milk and oil rich in sweets: O Soma, let the folk abide in thy decree.\n\np: O Soma, thou beholdest men from every side: O Pavamana, Steer, thou wanderest through these. Pour out upon us wealth in treasure. and in gold. May we have strength to live among the things that be.\n\np: Winner of gold and goods and cattle flow thou on, set as impregner, Indu, mid the worlds of life. Rich in brave men art thou, Soma, who winnest all: these holy singers wait upon thee with the song.\n\np: The wave of flowing meath hath wakened up desires: the Steer enrobed in milk plunges into the streams. Borne on his chariot-sieve the King hath risen to war, and with a thousand rays hath won him high renown.\n\np: Dear to all life, he sends triumphant praises forth, abundant, bringing offspring, each succeeding day. From Indra crave for us, Indu, when thou art quaffed, the blessing that gives children, wealth that harbours steeds.\n\np: When days begin, the strong juice, lovely, golden-hued, is recognized by wisdom more and more each day. He, stirring both the Races, goes between the two, the bearer of the word of men and word of Devas.\n\np: They balm him, balm him over balm him thoroughly, caress the mighty strength and balm it with the meath. They seize the flying Steer at the stream's breathing-place: cleansing with gold they grasp the Animal herein.\n\np: Sing forth to Pavamana skilled in holy song: the juice is flowing onward like a mighty stream. He.glideth like a serpent from his ancient skin, and like a playful horse the Tawny Steer hath run.\n\np: Dweller in floods, King, foremost, he displays his might, set among living things as measurer of days. Distilling oil he flows, fair, billowy, golden-hued, borne on a car of light, sharing one hom-e with wealth.\n\np: Loosed is the heavens! support, the uplifted cheering juice: the triply-mingled draught flows round into the worlds. The holy hymns caress the stalk that claims our praise, when singers have approached his beauteous robe with song.\n\np: Thy strearns that flow forth rapidly collected run over the fine fleece of the sheep as thou art cleansed. When, Indu, thou art. balmed with milk within the bowl, thou sinkest in the jars, O Soma, when expressed.\n\np: Winner of power, flow, Soma, worthy of our laud: run onward to the fleece as well-beloved meath. Destroy, O Indu, all voracious Raksasas. With brave sons in the assembly let our speech be bold.","people":["Indu","Pavamana","Indu Pavamana","Indra","Soma","Vayu","Mitra","Trita","Surya","Raksasas"],"places":["Earth","Heaven","Firmament","Sky"],"things":["Mankind","Meath","Milk","Steeds","Lord","Born","Rivers","Soma","Waters","Singer","Offering","Shine","Light","Sun","Treasure","Wealth","Food","Men","Streams","Stream","Flow","Might","Juice","Rain","Song","Gold","Offspring","Strong","Mighty","Car","Reservoir","Blessing","Chief","Praise","Voice","Brave","Hymn","Form","People","Powers","Friends","Songs","Drops","Friend","Hero","King","Bird","Sage","Horse","Morning","Cattle","Life"],"groups":["Devas","Sons","Worshippers","Gandharva","Father","Child","Rsis","Angirases","Man"],"concepts":["Celestial","Life","Divine","Beautiful","Special","Love","Holy","Strength","Wisdom","Offering","Swift","Winner","Noble","Speech"],"hash":"md5-71ZuerS9VNi5SPWliVx9HA==","created":"Monday, April 8, 2024 - 10:51:55 PM"},{"id":"c139f371-c506-42ba-814f-572cb5aad4e6","key":"09087","book":"09","title":"HYMN LXXXVII. Indu Pavamana.","link":"https://indra.ai/rigveda/hymns/09087.html","text":"p: RUN onward to the reservoir and seat thee: cleansed by the men speed forward to the battle. Making thee beauteous like an able courser, forth to the sacred grass with reins they lead thee.\n\np: Indu, the well-armed Deva, is flowing onward, who quells the curse and guards from treacherous onslaught, Father, begetter of the Devas, most skilful, the buttress of the heavens and earth's supporter.\n\np:  Rsi and Sage, the Champion of the people, cleft and sagacious, Usana in wisdom. He hath discovered even their hidden nature, the Cows' concealed and most mysterious title.\n\np: This thine own Soma rich in meath, O Indra, Steer for the Steer, hath flowed into the filter. The strong Free-giver, winning hundreds, thousands, hath reached the holy grass that never fails him.\n\np: These Somas are for wealth of countless cattle, renown therefor, and mighty strength immortal. These have been sent forth, urified by strainers, like steeds who rusg to battle fain for glory.\n\np: He, while he cleanses him, invoked of many, hath flowed to give the people all enjoyment. Thou whom the Falcon brought, bring, dainty offerings, bestir thyself and send us wealth and booty.\n\np: This Soma, pressed into the cleansing filter, hath run as ’twere a host let loose, the Courser; Like a strong bull who whets his horns kpen-pointed, like a brave warrior in the fray for cattle.\n\np: He issued forth from out the loftiest mountain, and found kine hidden somewhere in a stable. Soma's stream clears itself for thee, O Indra, like lightning thundering through the clouds of heaven,\n\np: Cleansing thyselr, and borne along with Indra, Soma, thou goest round the herd of cattle. May thy praise help us, Mighty One, prompt Giver, to the full ample food which thou bestowest.","people":["Indu","Indra","Soma","Usana","Deva"],"places":["Earth","Heaven"],"things":["Meath","Steeds","Soma","Glory","Wealth","Food","Men","Stream","Help","Strong","Mighty","Grass","Reservoir","Praise","Brave","People","Offerings","Warrior","Sage","Winning","Cattle"],"groups":["Devas","Father","Immortal"],"concepts":["Immortal","Holy","Sacred","Strength","Wisdom","Offerings","Giver"],"hash":"md5-QH5HGJhFs6q+GhMDmlYigQ==","created":"Monday, April 8, 2024 - 10:51:55 PM"},{"id":"5d85e469-1e4b-4a21-8cc0-98342f0644f2","key":"09088","book":"09","title":"HYMN LXXXVIII. Indu Pavamana.","link":"https://indra.ai/rigveda/hymns/09088.html","text":"p: FOR thee this Soma is effused, O Indra: drink of this juice; for thee the stream is flowing- Soma, which thou thyself hast made and chosen, even Indu, for thy special drink to cheer thee.\n\np: Like a capacious car hath it been harnessed, the Mighty; to acquire abundant treasure.s. Then in  'the offering they celebrated all triumphs won by Nahus -n the battle.\n\np: Like Vayu with his team, moving at pleasure, most gracious when invoked like both Nasatyas, Thou art thyself like the Wealth-Giver, Soma! who grants all boons, like song-inspiring Pusan.\n\np: Like Indra who hath done great deeds Soma, art slayer of the Vrtras, fort-destroyer. Like Pedu's horse who killed the brood of serpents, thus thou, O Soma, slayest every Dasyu.\n\np: Like Agni loosed amid the forest, fiercely he winneth splendour in the running waters. Like one who fights, the roaring of the mighty, thus Indu Pavamana sends his current.\n\np: These Somas passing through the fleecy filter, like rain descending from the clouds of heaven, have been effused and poured into the beakers, swiftly like rivers running lowly seaward.\n\np: Flow onward like the potent band of Maruts, like that Celestial Host whom none revileth. Quickly be gracious unto us like waters, like offering victorious, thousand-fashioned.\n\np: Thine are King Varuna's eternal statutes, lofty and deep, O Soma, is thy glory. All-pure art thou like Mitra the beloved, adorable, like Aryaman, O Soma.","people":["Indu","Pavamana","Indu Pavamana","Indra","Soma","Agni","Vayu","Mitra","Varuna","Nasatyas","Pusan","Aryaman"],"places":["Heaven"],"things":["Cheer","Rivers","Soma","Waters","Glory","Offering","Treasure","Wealth","Stream","Flow","Juice","Rain","Song","Mighty","Car","Adorable","Splendour","King","Horse"],"groups":["Dasyu","Maruts","Vrtras"],"concepts":["Celestial","Special","Offering","Giver"],"hash":"md5-PYnyPZRZ5SZZoEVjkAjgPQ==","created":"Monday, April 8, 2024 - 10:51:55 PM"},{"id":"d3f45994-7027-4a22-a604-940730d683fa","key":"09089","book":"09","title":"HYMN LXXXIX. Indu Pavamana.","link":"https://indra.ai/rigveda/hymns/09089.html","text":"p: THIS Chariot-horse hath moved along the pathways, and Pavamana flowed like rain from heaven. With us hath Soma with a thousand currents sunk in the wood, upon his Mother's bosom.\n\np:  King, he hath clothed him in the robe of rivers, mounted the straightest-going ship of Order. Sped by the Hawk the drop hath waxed in waters: the father drains it, drains the Father's offspring.\n\np: They come to him, red, tawny, Lord of Heaven, the watchful Guardian of the meath, the Lion. First. Hero in the fight, he seeks the cattle, and with his eye the Steer is our protector.\n\np: They harness to the broad-wheeled car the mighty Courser whose back bears meath, unwearied, awful. The twins, the sisters brighten him, and strengthen-these children of one damethe vigorous Racer.\n\np: Four pouring out the holy oil attend him, sitting together in the same container. To him they flow, when purified, with homage, and still, from every side, are first about him.\n\np: He is the buttress of the heavens, supporter of earth, and in his hand are all the people. Be the team's Lord a well to thee the singer: cleansed is the sweet plant's stalk for deed of glory.\n\np: Fighting, uninjured come where Devas are feasted; Soma, as Vitra-slayer flow for Indra. Vouchsafe us ample riches very splendi. May we be masters of heroic vigour.","people":["Pavamana","Indra","Soma"],"places":["Earth","Heaven"],"things":["Meath","Masters","Lord","Rivers","Soma","Waters","Glory","Singer","Flow","Rain","Offspring","Mighty","Car","People","Hero","King","Horse","Riches","Order","Cattle"],"groups":["Devas","Father","Mother"],"concepts":["Heroic","Holy"],"hash":"md5-HcrYXdWyiPcPvsoHlayBFg==","created":"Monday, April 8, 2024 - 10:51:55 PM"},{"id":"c018b1de-78b4-4a47-845d-16f1701f2083","key":"09090","book":"09","title":"HYMN XC. Indu Pavamana,","link":"https://indra.ai/rigveda/hymns/09090.html","text":"p: URGED On, the Father of the Earth and Heaven hath gone forth like a car to gather booty, Going to Indra, sharpening his weapons, and in his hand containing every treasure..\n\np: To him the tones of sacred song have sounded, Steer of the triple height, the Life-bestower. Dwelling in wood as Varuna in rivers, lavishing treasure. he distributes blessings\n\np: Great Conqueror, warnor-girt, Lord of all heroes, flow on thy way as he who winneth riches; With sharpened. arms, with swift bow, never vanquished in battle, vanquishing in fight the foemen.\n\np: Giving security, Lord of wide dominion, send us both earth and heaven with all their fulness. Striving to win the Dawns, the light, the waters, and cattle, call to us abundant vigour.\n\np: O Soma, gladden Varuna and Mitra; cheer, Indu Pavamana! Indra, Visnu. Cheer thou the Devas, the Company of Maruts: Indu, cheer mighty Indra to rejoicing.\n\np: Thus like a wise and potent King flow onward, destroying with thy vigour all misfortunes. For our well-spoken hymn give life, O Indu. Do ye preserve us evermore with blessings.","people":["Indu","Pavamana","Indu Pavamana","Indra","Soma","Visnu","Mitra","Varuna"],"places":["Earth","Heaven"],"things":["Cheer","Lord","Rivers","Soma","Waters","Light","Treasure","Flow","Song","Wise","Mighty","Car","Hymn","Heroes","King","call","Riches","Cattle","Life","Security"],"groups":["Devas","Maruts","Dawns","Father"],"concepts":["Life","Blessings","Sacred","Swift"],"hash":"md5-+hAlrrlpITb5yPluWOiwIg==","created":"Monday, April 8, 2024 - 10:51:55 PM"},{"id":"0e7f1d9f-9a54-4c63-8047-8a8ec5aaeb0f","key":"09091","book":"09","title":"HYMN XCI. Indu Pavamana.","link":"https://indra.ai/rigveda/hymns/09091.html","text":"p: As for a chariot-race, the skilful Speaker, Chief, Sage, inventor, hath, with song, been started. The sisters ten upon the fleecy summit drive on the Car-horse to the resting places.\n\np: The drop of Soma, pressed by wise Nahusyas, becomes the banquet of the Heavenly People- Indu, by hands of mortal men made beauteous, immortal, with the sheep and cows and waters.\n\np: Steer roaring unto Steer, this Pavamana, this juice runs to the white milk of the MilchCow. Through thousand fine hairs goes the tuneful Singer, like Sura by his fair and open pathways.\n\np: Break down the, strong seats even of the demons: cleansing thee, Indu, robd thyself in vigour. Rend with thy swift bolt, coming from above them, those who are near and those who yet are distant.\n\np: Prepare the forward paths in ancient manner for the new bymn, thou Giver of all bounties. Those which are high and hard for foes to conque. May we gain from thee, Active! Food-bestower!\n\np: So purifying thee vouchsafe us waters, heaven's light, and cows, offipring and many children. Give us health, ample land, and lights, O Soma, and grant us long to look upon the sunshine.","people":["Indu","Pavamana","Soma"],"places":["Heaven"],"things":["Milk","Soma","Waters","Singer","Light","Food","Men","Juice","Song","Wise","Strong","Car","Banquet","Chief","People","Sage","Horse","MilchCow"],"groups":["Immortal"],"concepts":["Heavenly","Immortal","Giver","Swift"],"hash":"md5-o+tmta4sG0x10CewclNebg==","created":"Monday, April 8, 2024 - 10:51:55 PM"},{"id":"22877d77-3783-4d03-a7a2-9cf4ad7a45a8","key":"09092","book":"09","title":"HYMN XCII. Indu Pavamana.","link":"https://indra.ai/rigveda/hymns/09092.html","text":"p: THE gold-hued juice, poured out upon the filter, is started like a car sent forth to conquer. He hath gained song and vigour while they cleansed him, and hath rejoiced the Devas with entertainments.\n\np: He who beholdeth man hath reached the filter: bearing his name, the Sage hath sought his dwelling. The Rsis came to him, seven holy singers, when in the bowls he settled as Invoker.\n\np: Shared by all Devas, mobt wise, propitious, Soma goes, while they cleanse him, to his constant station. Let him rejoice in all his lofty wisdom to the Five Tribes the Sage attains with labour.\n\np: In thy mysterious place, O Pavamana Soma, are all the Devas, the Thrice-Eleven. Ten on the fleecy height, themselves, self-prompted, and seven fresh rivers, brighten and adorn thee.\n\np: Now let this be the truth of Pavamana, there where all singers gather them together, that he hath given us room and made the daylight, hath holpen Manu and repelled the Dasyu.\n\np: As the Sage seeks the station rich in cattle, like a true King who goes to great assemblies, Soma hath sought the beakers while they cleansed him, and like a wild bull, in the wood hath settled.","people":["Pavamana","Soma"],"places":[],"things":["Rivers","Soma","Juice","Song","Gold","Wise","Car","King","Sage","Cattle"],"groups":["Devas","Dasyu","Rsis","Man"],"concepts":["Holy","Wisdom","Truth"],"hash":"md5-mUjDrBMWhSAgnbv/HqxL/A==","created":"Monday, April 8, 2024 - 10:51:55 PM"},{"id":"38e07cc5-5bba-4e58-999a-0e2d0ac20732","key":"09093","book":"09","title":"HYMN XCIII. Indu Pavamana.","link":"https://indra.ai/rigveda/hymns/09093.html","text":"p: TEN sisters, pouring out the rain together, swift-moving thinkers of the sage, adorn him. Hither hath run the gold-hued Child of Surya and reached the vat like a fleet vigorous courser.\n\np: Even as a youngling crying to his mothers, the bounteous Steer hath flowed along to waters. As youth to damsel, so with milk he hastens on to the. chose meeting-place, the beaker.\n\np: Yea, swollen is the udder of the MilchCow: thither in streams goes very sapient Indu. The kine make ready, as with new-washed treasure.s, the Head and Chief with milk within the vessels.\n\np: With all the Devas, O Indu Pavamana, while thou art roaring send us wealth in horses. Hither upon her car come willing Plenty, inclined to us, to give us of her treasure.s.\n\np: Now unto us mete riches, while they cleansethee, all-glorious, swelling wealth, with store of heroes. Long be his life who worships, thee, O Indu. May he, enriched with meditation, come soon and early.","people":["Indu","Pavamana","Indu Pavamana","Surya"],"places":[],"things":["Milk","Meditation","Waters","Glorious","Treasure","Wealth","Streams","Rain","Gold","Car","Chief","Heroes","Sage","Horses","Riches","Life","MilchCow"],"groups":["Devas","Child"],"concepts":["Life","Glorious","Swift"],"hash":"md5-ou4OlJHQ4LuNqbtUkqWrhg==","created":"Monday, April 8, 2024 - 10:51:55 PM"},{"id":"fcf468c1-36de-4ed4-b99c-85a1ec0bd853","key":"09094","book":"09","title":"HYMN XCIV. Indu Pavamana.","link":"https://indra.ai/rigveda/hymns/09094.html","text":"p: WHEN beauties strive for him as for a charger, then strive the songs like soldiers for the sunlight. Acting the Sage, he flows enrobed in waters and song as ’twere a stall that kin. May prosper.\n\np: The worlds expand to hirn who from aforetime found light to spread the law of life eternal. The swelling songs, like kine within the stable, in deep devotion call aloud on Indu.\n\np: When the sage bears his holy wisdom round him, like a car visiting all worlds, the Hero, becoming fame, mid Devas, unto the mortal, wealth to the skilled, worth praise mid the Ever-present,\n\np: For glory born be hath come forth to glory: he giveth life and glory to the singers. They, clothed in glory, have become immortal. He, measured in his course, makes frays successful.\n\np: Stream to us food and vigour, kine and horses: give us broad lights and fill thDevas with rapture. All ther are easy things for thee to master thou, pavamana Soma, quellest foemen.","people":["Indu","Pavamana","Soma"],"places":[],"things":["Master","Born","Soma","Waters","Glory","Light","Wealth","Food","Stream","Song","Car","Praise","Songs","Hero","Sage","Horses","call","Life"],"groups":["Devas","Immortal"],"concepts":["Life","Immortal","Holy","Wisdom"],"hash":"md5-ynTi1OlcVLQlX2A9D9ePKg==","created":"Monday, April 8, 2024 - 10:51:55 PM"},{"id":"19a037bf-dc92-4b58-9368-5ab32f02e824","key":"09095","book":"09","title":"HYMN XCV Indu Pavamana.","link":"https://indra.ai/rigveda/hymns/09095.html","text":"p: Loud neighs the Tawny Steed when started, settling deep in the wooden vessel while they cleanse him. Led by the men he takes the milk for raiment: then shall he, through his powers, engender praise-songs.\n\np: As one who rows drives on his boat, he, Gold-hued, sends forth his voice, loosed on the path of Order. As Deva, the secret names of Devas he utters, to be declared on sacred grass more widely.\n\np: Hastening onward like the waves of waters, our holy hymns are pressing nigh to Soma. To him they come with lowly adoration, and, longing, enter him who longs to meet them.\n\np: They drain the stalk, the Steer who dwells on mountains, even as a Bull who decks him on the upland. Hymns follow and attend him as he bellows: Trita bears Varuna aloft in ocean.\n\np: Sending thy voice out as Director, loosen the Invoker's thought, O Indu, as they cleanse thee. While thou and Indra rule for our advantage. May we be masters of heroic vigour.","people":["Indu","Indra","Soma","Varuna","Trita","Deva"],"places":["Ocean"],"things":["Masters","Milk","Mountains","Soma","Waters","Men","Gold","Grass","Praise","Voice","Powers","Songs","Order"],"groups":["Devas"],"concepts":["Heroic","Holy","Sacred"],"hash":"md5-YNA5yCRz7yCETQOBjWx+og==","created":"Monday, April 8, 2024 - 10:51:55 PM"},{"id":"04fd9726-ed02-4d56-8b41-0ce18a4daa9e","key":"09096","book":"09","title":"HYMN XCVI. Indu Pavamana","link":"https://indra.ai/rigveda/hymns/09096.html","text":"p: IN forefront of the cars forth goes the Hero, the Leader, winning spoil: his host rejoices. Soma endues his robes of lasting colours, and blesses, for his friends, their calls on Indra.\n\np: Men decked with gold adorn his golden tendril, incessantly with steed-impelling homage. The Friend of Indra mounts his car well-knowing, he comes thereon to meet the prayer we offer.\n\np: O Deva, for service of the Devas flow onward, for food sublime, as Indra's drink, O Soma. Making the floods, bedewing earth and heaven, come from the vast, comfort us while we cleanse thee\n\np: Flow for prosperity and constant Vigour, flow on for happiness and high perfection. This is the wish of these friends assembled: this is my wish, O Indu Pavamana.\n\np: Father of holy hymns, Soma flows onward the Father of the earth, Father of heaven: Father of Agni, Surya's generator, the Father who begat Indra and Visnu.\n\np: Brahman of Devas, the Leader of the poets, Rsi of sages, Bull of savage creatures, Falcon amid the vultures, Axe of forests, over the cleansing sieve goes Soma singing.\n\np: He, Indu Pavamana, like a river, hath stirred the wave of voice, our songs and praises. Beholding these inferior powers in cattle, he rests among them as a Steer well-knowing.\n\np: As Gladdener, Warrior never harmed in battle, with thousand genial streams, pour strength and vigour. As thoughtful Pavamana, urge O Indu, speeding the kine, the plant's wave on to Indra.\n\np: Dear, grateful to the Devas, on to the beaker moves Soma, sweet to Indra, to delight him. With hundred powers, with thousand currents, Indu, like a strong car-horse, goes to the assembly.\n\np: Born in old time as finder-out of treasure.s, drained with the stone, decking himself in waters, Warding off curses, King of all existence, he shall find way for prayer the while they cleanse him.\n\np: For our sage fathers, Indu Pavamana, of old performed, by thee, their sacred duties. Fighting unvanquished, open the enclosures: enrich us with large gifts of steeds and heroes.\n\np: As thou didst flow for Manu Life-bestowing, Foe-queller, Comforter, rich in oblations, Even thus flow onward now conferring riches: combine with Indra, and bring forth thy weapons.\n\np: Flow onward, Soma, rich in sweets and holy. enrobed in waters on the fleecy summit. Settle in vessels that are full of fatness, as cheering and most gladdening drink for Indra.\n\np: Pour, hundred-streamed, winner of thousands, mighty at the Devas’ banquet, pour the rain of heaven, While thou with rivers roarest in the beaker, and blent with milk prolongest our existence.\n\np: Purified with our holy hymns, this Soma o’ertakes malignities like some strong chargerlike fresh milk poured by Aditi, like passage in ample room, or like a docile car-horse.\n\np: Cleansed by the pressers, armed with noble weapons, stream to us the fair secret name thou bearest. Pour booty, like a horse, for love of glory Deva, soma, send us kine, and send us Vayu.\n\np: They deck him at his birth, the lovely Infant, the Maruts with their troop adorn the Car-horse. By songs a Poet and a Sage by wisdom, Soma joes singing through the cleansing filter.\n\np: Light-winner, Rsi-mindcd, Rsi-maker, hymned in a thousand hymns, Leader of sages, a Steer who strives to gain his third form, Soma is, like Viraj, resplendent as a Singer.\n\np: Hawk seated in the bowls, Bird wide-extended, the Banner seeking kine and wielding weapons, Following close the sea, the wave of waters, the great Bull tells his fourth form and declares it.\n\np: Like a fair youth who decorates his body, a courser rushing to the gain of riches, a steer to herds, so, flowing to the pitcher, he with a roar hath passed into the beakers.\n\np: Flow on with might as Pavamana, Indu flow loudly roaring through the fleecy filter. Enter the beakers sporting, as they cleanse thee, and let thy gladdening juice make Indra joyful.\n\np: His streams have been effused in all their fulness, and he hath entered, balmed with milk, the goblets. Singing his psalm, well-skilled in song, a Chanter, be comes as ’twere to his friend's sister roaring.\n\np: Chasing our foes thou comest, pavamana Indu, besting, as lover to his darling. As a bird flies and settles in the forest, thus Soma settles, purified, in goblets.\n\np: With full stream and abundant milk, O Soma, thy beams come, like a woman, as they cleanse thee. He, gold-hued, rich in boons, brought to the waters, hath roared within the goblet of the pious.","people":["Indu","Pavamana","Indu Pavamana","Indra","Soma","Agni","Vayu","Visnu","Deva","Surya","Aditi"],"places":["Earth","Heaven"],"things":["Leader","Milk","Steeds","Born","Rivers","Soma","Waters","Glory","Singer","Light","Treasure","Food","Men","River","Streams","Stream","Flow","Might","Juice","Rain","Song","Gold","Strong","Mighty","Car","Banquet","Voice","Delight","Heroes","Form","Powers","Friends","Songs","Warrior","Friend","Hero","King","Bird","Sage","Horse","Winning","spoil","Riches","Cars","Cattle","Life","Gifts"],"groups":["Devas","Maruts","Fathers","Father","Sister","Woman"],"concepts":["Birth","Life","Cars","Love","Holy","Sacred","Strength","Wisdom","Winner","Noble"],"hash":"md5-NjjzaZVFTMB6+f/YTnXEhA==","created":"Monday, April 8, 2024 - 10:51:55 PM"},{"id":"38a6bde9-5abd-43a0-8442-b2684b153336","key":"09097","book":"09","title":"HYMN XCVII. Indu Pavamana","link":"https://indra.ai/rigveda/hymns/09097.html","text":"p: MADE pure by this man's urgent zeal and impulse the Deva.hath to the Devas his juice imparted. He goes, effused and singing, to the filter, like priest to measured seats supplied with cattle.\n\np: Robed in fair raiment meet to wear in battle, a mighty Sage pronouncing invocations. Roll onward to the beakers as they cleanse thee, far-seeing at the feast of Devas, and watchful.\n\np: Dear, he is brightened on the fleecy summit, a Prince among us, nobler than the noble. Roar out as thou art purified, run forward. Do ye preserve us evermore with blessings.\n\np: Let us sing praises to the Devas: sing loudly, send ye the Soma forth for mighty riches. Let him flow, sweetly-flavoured, through the filter, and let our pious one rest in the pitcher.\n\np: Winning the friendship of the Deities, Indu flows in a thousand streams to make them joyful. Praised by the men after the ancient statute, he hath come nigh, for our great bliss, to Indra.\n\np: Flow, Gold-hued, cleansing thee, to enrich the singer: let thy juice go to Indra to support him. Come nigh, together with the Devas, for bounty. Do ye preserve us evermore with blessings.\n\np: The Deva.declares the Deities' generations, like Usana, proclaiming lofty wisdom. With brilliant kin, far-ruling, sanctifying, the Boar advances, singing, to the places.\n\np: The Swans, the Vrsaganas from anear us have brought their restless spirit to our dwelling. Friends come to Pavamana meet for praises, and sound in concert their resistless music.\n\np: He follows the Wide-strider's rapid movement: cows low, as ’twere, to him who sports at pleasure. He with the sharpened horns brings forth abundance: the Silvery shines by night, by day the Golden.\n\np: Strong Indu, bathed in milk, flows on for Indra, Soma exciting strength, to make him joyful. He quells malignities and subdues the demons, the King of mighty power who brings us comfort.\n\np: Then in a stream he flows, milked out with press-stones, mingled with sweetness, through the fleecy filter- Indu rejoicing in the love of Indra, the Deva who gladdens, for the Deva's enjoyment.\n\np: As he is purified he pours out treasure.s, a Deva.bedewing Devas with his own juices. Indu hath, wearing qualities by seasons, on the raised fleece engaged, the ten swift fingers.\n\np: The Red Bull bellowing to the kine advances, causing the heavens and earth to roar and tbunder. Well is he beard like Indra's shout in battle: letting this voice be known he hastens hither.\n\np: Swelling with milk, abounding in sweet flavours, urging the meath-rich plant thou goest onward. Raising a shout thou flowest as they cleanse thee, when thou, O Soma, art effused for Indra.\n\np: So flow thou on inspiriting, for rapture, aiming deatb-shafts at him who stays the waters, Flow to us wearing thy resplendent colour, effused and eager for the kine, O Soma.\n\np: Pleased with us, Indu, send us as thou flowest good easy paths in ample space and comforts. Dispelling, as ’twere with a club, misfortunes, run o’er the height, run o’er the fleecy summit.\n\np: Pour on us rain celestial, quickly streaming, refreshing, fraught with health and ready bounty. Flow Indu, send these Winds thy lower kinsmen, setting them free like locks of hair unbraided.\n\np: Part, like a knotted tangle, while they cleanse thee, O Soma, righteous and unrighteous conduct. Neigh like a tawny courser who is loosened, come like a youth, O Deva, a house-possessor.\n\np: For the Deva's service, for delight, O Indu, run o’er the height, run o'ver the fleecy summit. With thousand streams, inviolate, sweet-scented, flow on for gain of strength that conquers heroes.\n\np: Without a car, without a rein to guide them, unyoked, like coursers started in the contest, these brilliant drops of Soma juice run forward. Do ye, O Deities, come nigh to drink them.\n\np: So for our banquet of the Devas, O Indu, pour down the rain of heaven into the vessels. May Soma grant us riches sought with longing, mighty, exceeding strong, with store of heroes.\n\np: What time the loving spirit's word had formed him Chief of all food, by statute of the Highest, then loudly lowing came the cows to Indu, the chosen, well-loved Master in the beaker.\n\np: The Sage, Celestial, liberal, raining bounties, pours as he flows the Genuine for the Truthful. The King shall be effectual strength's upholder: he by the ten bright reins is mostly guided.\n\np: He who beholds mankind, made pure with filters, the King supreme of Deities and mortals, From days of old is Treasure-Lord of riches: he, Indu, cherishes fair well-kept Order.\n\np: Haste, like a steed, to vittory for glory, to Indra's and to Vayu's entertainment. Give us food ample, thousandfold: be, Soma, the finder-out of riches when they cleanse thee.\n\np: Effused by us let Deva.delighting Somas bring as they flow a home with noble heroes. Rich in all boons like monks acquiring favour, the worshippers of heaven, the best of Cheerers.\n\np: So, Deva, for service of the Devas flow onward, flow, drink of Devas, for ample food, O Soma. For we go forth to war against the mighty make heaven and earth well stablished by thy cleansing.\n\np: Thou, yoked by strong men, neighest like a courser, swifter than thought is, like an awful lion. By paths directed hitherward, the straightest, send thou us happiness, Indu, while they cleanse thee.\n\np: Sprung from the Devas, a hundred streams, a thousand, have been effused: sages prepare and purge them. Bring us from heaven the means of winnning, Indu; thou art-forerunnner of abundant riches.\n\np: The streams of days, were poured as ’twere from heaven: the wise King doth not treat his friend unkindly. Like a son following his father's wishes, grant to this family success and safety.\n\np: Now are thy streams poured forth with all their sweetness, when, purified. thou goest through the filter. The race of kine is thy gift, pavarridna: when born thou madest Surya rich with brightness.\n\np: Bright, bellowing aiong the path of Order, thou shinest as the form of life eternal. Thou flowest on as gladdening drink for Indra, sending thy voice out with the hymns of sages.\n\np: Pouring out streams at the Devas’ feast with service Soma, lookest down, a heavenly Eagle. Enter the Soma-holding beaker, Indu, and with a roar approach the ray of Sarya.\n\np: Three are the voices that the Courser utters: he speaks the thought of prayer, the law of Order. To the Cow's Master come the Cows inquiring: the hymns with eager longing come to Soma.\n\np: To Soma come the Cows, the Milch-kine longing, to Soma sages with their hvmns inquiring. Soma, effused, is purified and blended our hymns and Trstup songs unite in Soma.\n\np: Thus, Soma, as we pour thee into vessels, while thou art purified flow for our welfare. Pass into Indra with a mighty roaring make the voice swell, and generate abundance.\n\np: Singer of true songs, ever-watchful, Soma hath settled in the ladles when they cleanse him. Him the Adhvaryus, paired and eager, follow, leaders of offering and skilful-handed.\n\np: Cleansed near the Sun as ’twere he as Creator hath filled full heaven and earth, and hath disclosed them. He by whose dear help men gain all their wishes shall yield the precious meed as to a victor.\n\np: He, being cleansed, the Strengthener and Increaser, Soma the Bounteous, helped us with his lustre, Wherewith our sires of old who knew the footsteps found light and stole the cattle from the mountain.\n\np: In the first vault of heaven loud roared the Ocean, King of all being, generating creatures. Steer, in the filter, on the fleecy summit, Soma, the Drop effused, hath waxen mighty.\n\np: Soma the Steer, in that as Child of Waters he chose the Devas, performed that great achievement. He, pavamana, granted strength to Indra; he, Indu, generated light in Surya.\n\np: Make Vayu glad, for furtherance and bounty: cheer Varuna and Mitra, as they cleanse thee. Gladden the Devas, gladden the host of Maruts: make Heaven and Earth rejoice, O Deva, O Soma.\n\np: Flow onward righteous slayer of the wicked, driving away our enemies and sickness, Blending thy milk with milk which cows afford us. We are thy friends, thou art the Friend of Indra.\n\np: Pour us a fount of meath, a spring of treasure.; send us a hero son and happy fortune. Be sweet to India when they cleanse thee, Indu, and pour down riches on us from the ocean.\n\np: Strong Soma, pressed, like an impetuous courser, hath flowed in stream as a flood speeding downward. Cleansed, he hath settled in his wooden dwelling: Indu hath flowed with milk and with the waters.\n\np: Strong, wise, for thee who longest for his coming this Soma here flows to the bowls, O Indra. He, chariot-borne, sun-bright, and truly potent, was poured forth like the longing of the pious.\n\np: He, purified with ancient vital vigour, pervading all his Daughter's forms and figures, Finding his threefold refuge in the waters, goes singing, as a priest, to the assemblies.\n\np: Now, chariot-borne, flow unto us, Deva.Soma, as thou art purified flow to the saucers, Sweetest in waters, rich in meath, and holy, as Savitar the Indu is, truthfulminded.\n\np: To feast him, flow mid song and hymn, to Vayu, flow purified to Varuna and Mitra. Flow to the song-inspiring car-borne Hero, to mighty Indra, him who wields the thunder.\n\np: Pour on us garments that shall clothe us meetly, send, purified, miIch-kine, abundant yielders. Deva.Soma, send us chariot-drawing horses that the, may bring us treasure.s bright and golden.\n\np: Send to us in a stream celestial riches, send us, when thou art cleansed, what earth containeth, So that thereby we may acquire possessions and Rsihood in Jamadagni's manner.\n\np: Pour forth this wealth with this purification: flow onward to the yellow lake, O Indu. Here, too, the Ruddy, wind-swift, full of wisdom, Shall give a son to him who cometh quickly.\n\np: Flow on for us with this purification to the famed ford of thee whose due is glory. May the Foe-queller shake us down, for triumph, like a tree's ripe fruit, sixty thousand treasure.s.\n\np: Eagerly do we pray for those two exploits, at the blue lake and Prsana, wrought in battle. He sent our enemies to sleep and slew thern, and turned away the foolish and unfriendly.\n\np: Thou comest unto three extended filters, and hasteriest through each one as they cleanse thee. Thou art the giver of the gift, a Bhaga, a Maghavan for liberal lords, O Indu.\n\np: This Soma here, the Wise, the All-obtainer, flows on his way as King of all existence. Driving the drops at our assemblies, Indu completely traverses the fleecy filter.\n\np: The Great Inviolate are kissing Indu, and singing in his place like eager sages. The wise men send him forth with ten swift fingers, and balm his form with essence of the waters.\n\np: Soma. May we, with thee as Pavamana, pile up together all our spoil in battle. This boon vouchsafe us Varuna and Mitra, and Aditi and Sindhu, Earth and Heaven.","people":["Indu","Pavamana","Indra","Soma","Vayu","Mitra","Varuna","Maghavan","Savitar","Usana","Bhaga","Deva","Surya","Aditi","Sindhu"],"places":["Ocean","Earth","Heaven"],"things":["Mankind","Meath","Cheer","Master","Milk","Lord","Seasons","Born","Triumph","Soma","Waters","Glory","Singer","Offering","Light","Creator","Sun","Treasure","Wealth","Boon","Food","Men","Streams","Stream","Flow","Juice","Rain","Song","Gold","Help","Home","Wise","Strong","Mighty","Car","Banquet","Chief","Voice","Delight","Hymn","Heroes","Gift","Form","Lake","Friends","Bliss","Songs","Drops","Friend","Hero","King","Sage","Cow","Swans","Horses","Winning","spoil","Riches","Order","Cattle","Life","Spirit"],"groups":["Devas","Maruts","Deities","Worshippers","Father","Son","Child","Man","Monks"],"concepts":["Celestial","Good","Life","Heavenly","Friendship","Blessings","Love","Holy","Strength","Wisdom","Offering","Giver","Truthful","Swift","Pleased","Noble","Creator"],"hash":"md5-8XwlGRy9iK2YnriOGmk6wQ==","created":"Monday, April 8, 2024 - 10:51:55 PM"},{"id":"05fa5dc7-5ca4-4f32-a44b-560e1b9c76a3","key":"09098","book":"09","title":"HYMN XCVIII. Indu Pavamana","link":"https://indra.ai/rigveda/hymns/09098.html","text":"p: STREAM on us riches that are sought by many, best at winning strength Riches, O Indu, thousandfold, glorious, conquering the great.\n\np: Effused, he hath, as on a car, invested him in fleecy mail: Onward hath Indu flowed in streams, impelled, surrounded by the wood.\n\np: Effused, this Indu hath flowed on, distilling rapture, to the fleece: He goes erect, as seeking kine in stream, with light, to offering.\n\np: For thou thyself, O Indu, Deva, to every mortal worshipper Attractest riches thousandfold, made manifest in hundred forms.\n\np: Good Vrtra conquerer. May we be still nearest to this wealth of thine Which many crave, nearest to food and happiness, Resistless One!\n\np: Whom, bright with native splendour, crushed between the pair of pressingstones- The wavy Friend whom Indra loves-the twice-five sisters dip and bathe,\n\np: Him with the fleece they purify, brown, golden-hued, beloved of all, who with exhilarating juice goes forth to all the Deities.\n\np: Through longing for this sap of yours ye drink what brings ability, Even him who, dear as heaven's own light, gives to our princes high renown.\n\np: Indu at holy rites produced you. Heaven and Earth, the Friends of men, Hill-haunting Deva.the Devas. They bruised him where the roar was loud.\n\np: For Vrtra-subduing Indra Soma, art poured that h. May drink, poured for the guerdon-giving man, poured for the Deva who sitteth there.\n\np: These ancient Somas, at the break of day, have flowed into the sieve, Snorting away at early morn these foolish evil-hearted ones.\n\np: Friends. May the princes, ye and we, obtain this Most Resplendent One. Gain him who hath the smell of strength, win him whose home is very strength.","people":["Indu","Indra","Soma","Vrtra","Deva"],"places":["Earth","Heaven"],"things":["Soma","Glorious","Offering","Light","Wealth","Food","Men","Streams","Stream","Juice","Home","Car","Worshipper","Splendour","Friends","Friend","Winning","Riches"],"groups":["Devas","Deities","Man"],"concepts":["Good","Evil","Holy","Strength","Offering","Glorious"],"hash":"md5-KhpUZ88s0RHz9BnilZe9gQ==","created":"Monday, April 8, 2024 - 10:51:56 PM"},{"id":"222e892d-cf57-41bf-be22-ab399c5e41e9","key":"09099","book":"09","title":"HYMN XCIX. Indu Pavamana.","link":"https://indra.ai/rigveda/hymns/09099.html","text":"p: THEY for the Bold and Lovely One ply manly vigour like a bow: joyous, in front of songs they weave bright raiment for the Lord Divine.\n\np: And he, made beautiful by night, dips forward into strengthening food', what time  'theofferings thoughts speed on his way the Golden-hued.\n\np: We cleanse this gladdening drink of his the juice which Indra chiefly drinks—- That which kine took into their mouths, of old, and princes take it now.\n\np: To him, while purifying, they have raised the ancient psalm of praise: And sacred songs which bear the names of Devas have supplicated him.\n\np: They purify him as he drops, courageous, in the fleecy sieve. Him they instruct as messenger to bear the sage's morning prayer.\n\np: Soma, best Cheerer, takes his seat, the while they cleanse him in the bowls. He as it were impregns the cow, and babbles on, the Lord of Song.\n\np: He is effused and beautified, a Deva.for Devas, by skilful men. He penetrates the mighty floods collecting all he knows therein.\n\np: Pressed, Indu, guided by the men, thou art led to the cleaning sieve. Thou, yielding Indra highest joy, takest thy seat within the bowls.","people":["Indu","Indra","Soma","Deva"],"places":[],"things":["Lord","Soma","Food","Men","Juice","Song","Joy","Mighty","Praise","Songs","Drops","Sage","Cow","Morning"],"groups":["Devas"],"concepts":["Divine","Beautiful","Sacred"],"hash":"md5-Ez0Gp/KS83UKXFdzp0Rwig==","created":"Monday, April 8, 2024 - 10:51:56 PM"},{"id":"735f06d6-d5a8-4ed2-8e34-d6a79b1a235f","key":"09100","book":"09","title":"HYMN C. Indu Pavamana.","link":"https://indra.ai/rigveda/hymns/09100.html","text":"p: THE Guileless Ones are singing praise to Indra's well beloved Friend, As, in the morning of its life, the mothers lick the new-born calf.\n\np: O Indu, while they cleanse thee bring, O Soma, doubly-waxing wealth Thou in the worshipper's abode causest all treasure.s to increase.\n\np: Set free the. song which mind hath yoked, even as thunder frees the rain: All treasure.s of the earth and heaven, O Soma, thou dost multiply.\n\np: Thy stream when thou art pressed runs on like some victorious warrior's steed Hastening onward through the fleece like a fierce horse who wins the prize.\n\np: Flow on, Sage Soma, with thy stream to give us mental power and strength, Effused for Indra, for his drink, for Mitra and for Varuna.\n\np: Flow to the filter with thy stream, effused, best winner of spoil, O Soma, as most rich in sweets for Indra, Visnu, and the Devas.\n\np: The mothers, void of guiles, caress thee Golden-coloured, in the sieve, as cows, O Pavamana, lick the new-born calf, as Law commands.\n\np: Thou, pavamana, movest on with wondrous rays to great renown. Striving within the votary's house thou drivest all the glooms away.\n\np: Lord of great sway, thou liftest thee above the heavens, above the earth. Thou, pavamana hast assumed thy coat of mail in majesty.","people":["Indu","Pavamana","Indra","Soma","Visnu","Mitra","Varuna"],"places":["Earth","Heaven"],"things":["Lord","Born","Soma","Treasure","Wealth","Stream","Flow","Rain","Song","Praise","Worshipper","Warrior","Friend","Sage","Horse","spoil","Morning","Life"],"groups":["Devas"],"concepts":["Life","Strength","Winner"],"hash":"md5-80srOCZrqfxau72iDwg8Bg==","created":"Monday, April 8, 2024 - 10:51:56 PM"},{"id":"590e752f-8aef-41bc-815f-c9d2f5c73c68","key":"09101","book":"09","title":"HYMN CI. Indu Pavamana","link":"https://indra.ai/rigveda/hymns/09101.html","text":"p: FOR first possession of your juice, for the exhilarating drink, Drive ye away the dog, my friends, drive ye the long-tongued dog away.\n\np: He who with purifying stream, effused, comes flowing hitherward, Indu, is like an able steed.\n\np: The men with all-pervading song send unassailable Soma forth, by pressing-stones, to offering.\n\np: The Somas, very rich in sweets, for which the sieve is destined, flow the source of Indra's joy. May your strong juices reach the Devas.\n\np: Indu flows on for Indra's sake: thus have the Deities declared. The Lord of Speech exerts himself, Ruler of all, because of might.\n\np: Inciter of the voice of song, with thousand streams the ocean flows, Even Soma, Lord of opulence, the Friend of Indra, day by day.\n\np: As Pusan, fortune, Bhaga, comes this Soma while they make him pure. He, Lord of the multitude, hath looked upon the earth and heaven.\n\np: The dear cows lowed in joyful mood together to the gladdening drink. The drops as they were purified, the Soma juices, made then paths.\n\np: O Pavamana, bring the juice, the mightiest, worthy to be famed, Which the Five Tribes have over them, whereby we may win opulence.\n\np: For us the Soma juices flow, the drops best furtherers of our weal, Effused as friends without a spot, benevolent, finders of the light.\n\np: Effused by means of pressing-stones, upon the ox-hide visible, they, treasure.-finders, have announced food unto us from every side.\n\np: Tlese Soma juices, skilled in song, purified, blent with milk and curd, when moving and when firmly laid in oil, resemble lovely Suns.\n\np: Let not the power of men restrain the voice of the outpouring juice: As Bhrgu's sons chased Makha, so drive ye the greedy hound away.\n\np: The Friend hath wrapped him in his robe, as in his parents arms, a son. He went, as lover to a dame, to take his station suitor-like.\n\np: That Hero who produces strength, he who hath propped both worlds apart, Gold-hued, hath wrapped him in the sieve, to settle, priest-like, in his place.\n\np: Soma upon the ox's skin through the sheep's wool flows purified. Bellowing out, the Tawny Steer goes on to Indra's special place.","people":["Indu","Pavamana","Indra","Soma","Pusan","Bhaga"],"places":["Ocean","Earth","Heaven"],"things":["Milk","Lord","Soma","Offering","Light","Treasure","Food","Men","Streams","Stream","Flow","Might","Juice","Song","Joy","Gold","Strong","Voice","Pressing-Stones","Friends","Drops","Friend","Hero","Parents"],"groups":["Devas","Sons","Deities","Son"],"concepts":["Special","Strength","Offering","Speech"],"hash":"md5-N4wtr4vfQAn5hSDiBZrk7Q==","created":"Monday, April 8, 2024 - 10:51:56 PM"},{"id":"455ea53f-4b0e-4f45-8c56-81abc5864959","key":"09102","book":"09","title":"HYMN CIL Indu Pavamana.","link":"https://indra.ai/rigveda/hymns/09102.html","text":"p: THE Child, when blended with the streams, speeding the plan of offering, Surpasses all things that are dear, yea, from of old.\n\np: The place, near the two pressing-stones of Trita, hath he occupied, Secret and dear through seven lights of offering.\n\np: Urge to three courses, on the heights of Trita, riches in a stream. He who is passing wise measures his courses out.\n\np: Even at his birth the Mothers Seven taught him, for glory, like a sage, So that he, firm and sure, hath set his mind on wealth.\n\np: Under his sway, of one accord, are all the guileless Deities: Warriors to be envied, they, when they are pleased.\n\np: The Babe whom they who strengthen Law have generated fair to see, Much longed for at  'the offering, most liberal Sage.\n\np: To him, united, of themselves, come the young Parents of the rite, when they adorn him, duly weaving offerings.\n\np: With wisdom and with radiant eyes unbar to us the stall of heaven, Speeding at solemn rite the plan of Holy Law.","people":["Trita"],"places":["Heaven"],"things":["Glory","Offering","Wealth","Streams","Stream","Wise","Pressing-Stones","Offerings","Sage","Parents","Riches"],"groups":["Deities","Child"],"concepts":["Birth","Holy","Wisdom","Offering","Offerings","Pleased"],"hash":"md5-2qnnk9QPOSRj1d1SDNhhNA==","created":"Monday, April 8, 2024 - 10:51:56 PM"},{"id":"3429d432-301f-4bac-a3d3-3ba1072ae2be","key":"09103","book":"09","title":"HYMN CIII. Indu Pavamana.","link":"https://indra.ai/rigveda/hymns/09103.html","text":"p: To Soma who is purified as ordering Monk the song is raised: Bring meed, as ’twere, to one who makes thee glad with hymns.\n\np: Blended with milk and curds he flows on through the long wool of the sheep. The Gold-hued, purified, makes him three seats for rest.\n\np: On through the long wool of the sheep to the meath-dropping vat he flows: The Rsis’ sevenfold quire hath sung aloud to him.\n\np: Shared by all Devas, infallible, the Leader of our holy hymns, Golden-hued Soma, being cleansed, hath reached the bowls.\n\np: After thy Deva like qualities, associate with Indra, go, as a Monk purified by monks, Immortal One.\n\np: Like a car-horse who shows his strength, a Deva.effused for Deities. The penetrating Pavamana flows along.","people":["Pavamana","Indra","Soma","Deva"],"places":[],"things":["Meath","Leader","Milk","Soma","Song","Gold","Car","Horse"],"groups":["Devas","Deities","Immortal","Rsis","Monks"],"concepts":["Immortal","Holy","Strength"],"hash":"md5-LhnbDlE2Z6NNkVDyLXyZaQ==","created":"Monday, April 8, 2024 - 10:51:56 PM"},{"id":"784e4eed-4792-4e2b-a83c-d1af5e7cb327","key":"09104","book":"09","title":"HYMN CIV. Indu Pavamana.","link":"https://indra.ai/rigveda/hymns/09104.html","text":"p: SIT down, O friends, and sing aloud to him who purifies himself: Deck him for glory, like a child, with holy rites.\n\np: Unite him bringing household wealth, even as a calf, with mother kinehim who hath double strength, the Deva, delighting juice.\n\np: Purify him who gives us power, that he, most Blessed One. May be A banquet for the Troop, Mitra, and Varuna.\n\np: Voices have sung aloud to thee as finderout of wealth for us: We clothe the hue thou wearest with a robe of milk.\n\np: Thou, Indu, art the food of Devas, O Sovran of all gladdening drinks: As Friend for friend, be thou best finder of success.\n\np: Drive utterly away from us each demon each voracious fiend, the godless and the false: keep sorrow far away.","people":["Indu","Mitra","Varuna","Deva"],"places":[],"things":["Milk","Glory","Wealth","Food","Juice","Banquet","Friends","Friend"],"groups":["Devas","Mother","Child"],"concepts":["Holy","Strength"],"hash":"md5-qlbt/9lNFrwRAwTK2dFmFw==","created":"Monday, April 8, 2024 - 10:51:56 PM"},{"id":"4bfb428a-c3e0-4c4c-b0c8-b049fd0a75d3","key":"09105","book":"09","title":"HYMN CV. Indu Pavamana","link":"https://indra.ai/rigveda/hymns/09105.html","text":"p: SING; ye aloud, O friends, to him who makes him pure for gladdening drink: They shall make sweet the Child with offering and laud.\n\np: Like as a calf with mother cows, so Indu is urged forth and sent, Glorified by our hymns, the Deva.delighting juice.\n\np: Effectual means of power is he, he is a banquet for the Troop. He who hath been effused, most rich in meath, for Devas.\n\np: Flow to us, Indu, passing, strong, effused, with wealth of kine and steeds: I will spread forth above the milk thy radiant hue.\n\np: Lord of the tawny, Indu thou who art the Deva's most special food, as Friend to friend, for splendour be thou good to men.\n\np: Drive utterly, far away from us each godless, each voracious foe. O Indu, overcome and drive the false afar.","people":["Indu","Deva"],"places":[],"things":["Meath","Milk","Steeds","Lord","Offering","Wealth","Food","Men","Flow","Juice","Strong","Banquet","Splendour","Friends","Friend"],"groups":["Devas","Mother","Child"],"concepts":["Good","Special","Offering"],"hash":"md5-Os/DduMIJnLhhVEWtxxuGA==","created":"Monday, April 8, 2024 - 10:51:56 PM"},{"id":"7eae15cb-de61-49b7-b5ef-caee0152a843","key":"09106","book":"09","title":"HYMN CVI. Indu Pavamana.","link":"https://indra.ai/rigveda/hymns/09106.html","text":"p: To Indra, to the Mighty Steer. May these gold-coloured juices go, Drops rapidly produced, that find the light of heaven.\n\np: Effused, this juice victorious flows for Indra, for his maintenance. Soma bethinks him of the Conqueror, as he knows.\n\np: May Indra in his raptures gain from him the grasp that gathers spoil, and, winning waters, wield the steerstrong thunderbolt.\n\np: Flow vigilant for Indra, thou Soma, yea, Indu, run thou on: Bring hither splendid strength that finds the light of heaven.\n\np: Do thou, all-beautiful, purify for Indra's sake the mighty juice, path-maker thou, far seeing, with a thousand ways.\n\np: Best finder of prosperity for us, most rich in sweets for Devas, proceed thou loudly roaring on a thousand paths.\n\np: O Indu, with thy streams, in might, flow for the banquet of the Devas: Rich in meath, Soma, in our beaker take thy place.\n\np: Thy drops that swim in water have exalted Indra to delight: The Devas have drunk thee up for immortality.\n\np: Stream opulence to us, ye drops of Soma, pressed and purified, pouring down rain from heaven in hoods, and finding light.\n\np: Soma, while filtered, with his wave flows through the long wool of the sheep, Shouting while purified before the voice of song.\n\np: With songs they send the Mighty forth, sporting in wood, above the fleece: Our psalms have glorified him of the triple height.\n\np: Into the jars hath he been loosed, like an impetuous steed for war, and lifting up his voice, while filtered, glided on.\n\np: Gold-hued and lovely in his course, througb tangles of the wool he flows, and pours heroic fame upon the worshippers.\n\np: Flow thus, a faithful votary: the streams of meath have been effused. Thou comest to the filter, singing, from each side.","people":["Indu","Indra","Soma"],"places":["Heaven"],"things":["Meath","Soma","Waters","Water","Light","Streams","Stream","Flow","Might","Juice","Rain","Song","Gold","Mighty","Banquet","Voice","Delight","Songs","Drops","Winning","spoil"],"groups":["Devas","Worshippers"],"concepts":["Beautiful","Heroic","Immortality","Strength"],"hash":"md5-e4ETzXEm6vENHz83xZiNKQ==","created":"Monday, April 8, 2024 - 10:51:56 PM"},{"id":"5f7175d3-a6b6-482f-a1d9-31a8c0a54c28","key":"09107","book":"09","title":"HYMN CVII. Indu Pavamana.","link":"https://indra.ai/rigveda/hymns/09107.html","text":"p: I., HENCE sprinkle forth the juice effused. Soma, the best of sacred gifts, who, friend of man, hath run amid the water-streams. He hath pressed Soma out with stones.\n\np: Now, being purified, flow hither through the fleece inviolate and most odorous. We ladden thee in waters when thou art effused, blending thee still with juice and milk.\n\np: Pressed out for all to see, delighting Devas, Indu, Far-sighted One, is mental power.\n\np: Cleansing thee, Soma, in thy stream, thou flowest in a watery robe: Giver of wealth, thou sittest in the place of Law, O Deva, a fountain made of gold.\n\np: Milking the heavenly udder for dear meath, he hath sat in the ancient gatheringplace. Washed by the men, the Strong Farseeing One streams forth nutriti us food that all desire.\n\np: O Soma, while they cleanse thee, dear and watchful in the sheep's long wool, Thou hast become a Singer most like Angiras: thou madest Surya mount to heaven.\n\np: Bountiful, best of furtherers, Soma floweth on, Rsi and Singer, keen of sight. Thou hast become a Sage most welcome to the Devas: thou madest Surya mount to heaven.\n\np: Pressed out by pressers, Soma goes over the fleecy backs of sheep, Goes, even as with a mare, in tawnycoloured stream, goes in exhilarating stream.\n\np: Down to the water-Soma, rich in kine hath flowed with cows, with cows that have been milked. They have approached the mixing-vessel as a sea: the cheerer streams for the carouse.\n\np: Effused by stones, O Soma, and urged through the long wool of the sheep, Thou, entering the saucers as a man the fort, gold-hued hast settled in the wood.\n\np: He beautifies himself through the sheep's long fine wool, like an impetuous steed in war, Even Indu Pavamana who shall be the joy of sages and of holy bards.\n\np: O Soma.for the feast of Devas, river-like he hath swelled with surge, with the stalk's juice, exhilarating, resting not, into the vat that drops with meath.\n\np: Like a dear son who must be decked, the Lovely One hath clad him in a shining robe. Men skilful at their work drive him forth, like a car, into the rivers from their bands.\n\np: The living drops of Soma juice pour, as they flow, the gladdening drink, intelligent drops above the basin of the sea, exhilarating, finding light.\n\np: May Pavamana, King and Deva, speed with his wave over the sea the lofty rite: May he by Mitra's and by Varuna's decree flow furthering the lofty rite.\n\np: Far-seeing, lovely, guided by the men, the Deva whose home is in the sea-\n\np: Soma, the gladdening juice, flows pressed for Indra with his Marut host: He hastens o’er the fleece with all his thousand streams: men make him bright and beautiful.\n\np: Purified in the bowl and gendering the hymn, wise Soma joys among the Devas. Robed in the flood, the Mighty One hath clad himself with milk and settled in the vats.\n\np: O Indu, every day thy friendship hath been my delight. Many fiends follow me; help me, thou Tawny-hued; pass on beyond these barriers.\n\np: Close to thy bosom am I, Soma, day and night. O Tawny-hued, for friendship sake. Surya himself refulgent with his glow have we o’ertaken in his course like birds.\n\np: Deft-handcd! thou when purified liftest thy voice amid the sea. Thou, pavamana, makest riches flow to us, yellow, abundant, much-desifed.\n\np: Making thee pure and bright in the sheep's long wool, thou hast bellowed, steerlike, in the wood. Thou flowest, Indu Pavamana, balmed with milk unto the special place of Devas.\n\np: Flow on to win us strength, flow on to lofty lore of every kind. Thou, Soma, as Exhilarator wast the first to spread the sea abroad for Devas.\n\np: Flow to the realm of earth, flow to the realm of heaven, O Soma, in thy righteous ways. Fair art thou whom the sages, O Far-seeing One, urge onward with their songs and hymns.\n\np: Over the cleansing sieve have flowed the Pavamanas in a stream, Girt by the Maruts, gladdening, Steeds with Indra's stiength, for wisdom and for dainty food.\n\np: Urged onward by the pressers, clad in watery robes, Indu is speeding to the vat. He gendering light, hath made the glad Cows low, while he takes them as his garb of state.","people":["Indu","Pavamana","Indu Pavamana","Indra","Soma","Angiras","Mitra","Varuna","Deva","Surya"],"places":["Earth","Heaven"],"things":["Meath","Milk","Steeds","Work","Rivers","Soma","Waters","Water","Singer","Light","Wealth","Food","Men","River","Streams","Stream","Flow","Juice","Joy","Gold","Help","Home","Wise","Strong","Mighty","Car","Voice","Delight","Hymn","Songs","Drops","Friend","King","Sage","Riches","Gifts"],"groups":["Devas","Maruts","Marut","Son","Man"],"concepts":["Heavenly","Friendship","Beautiful","Special","Holy","Sacred","Strength","Wisdom","Giver"],"hash":"md5-6JVyambctyBoYeQOENI6mQ==","created":"Monday, April 8, 2024 - 10:51:56 PM"},{"id":"40c47ae5-8de2-419a-aff3-03844cf885dc","key":"09108","book":"09","title":"HYMN CVIII. Indu Pavamana.","link":"https://indra.ai/rigveda/hymns/09108.html","text":"p: FOR Indra, flow thou Soma on, as gladdening juice most sweet, intelligent, Great, cheering, dwelling most in heaven.\n\np: Thou, of whom having drunk the Steer acts like a steer. drinking of this that finds the light. He, Excellently Wise, is come to strengthening food, to spoil and wealth like Etasa.\n\np: For, verily, pavamana, thou hast, splendidest, called all the generations of The Devas to immortality.\n\np: By whom Dadhyac Navagva opens fastened doors, by whom the sages gained their wish, by whom they won the fame of lovely Amrta in the felicity of Devas.\n\np: Effused, he floweth in a stream, best rapture-giver, in the long wool of the sheep, Sporting, as ’twere the waters' wave.\n\np: He who from out the rocky cavern took with might the redmrefulgent watery Cows, Thou masterest the stable full of kine and steeds: burst it, brave Lord, like one in mail.\n\np: Press ye and pour him, like a steed, laudworthy, speeding through the region and the flood, who swims in water, roan in wood;\n\np: Increaser of the water, Steer with thousand streams, dear to the race of Deities. Who born in Law hath waxen mighty by the Law, King, Deva, and lofty Ordinance.\n\np: Make splendid glory shine on us, thou Lord of strengthening food, Deva, as the Friend of Devas: Unclose the fount of middle air.\n\np: Roll onward to the bowls, O Mighty One, effused, as Prince supporter of the tribes. Pour on us rain from heaven, send us the waters' flow: incite our thoughts to win the spoil.\n\np: They have drained him the Steer of heaven, him with a thousand streams, distilling rapturous joyhim who brings all things excellent.\n\np: The Mighty One was born Immortal, giving life, lightening darkness with his shine. Wcll-praised by. sages he hath. by his wondrous power assumed the Threefold as his robe.\n\np: Effused is he who brings good things, who brings us bounteous gifts and sweet refreshing food, Soma who brings us quiet homes:\n\np: He whom our Indra and the Marut host shall drink, Bhaga shall drink with Aryarnan, by whom we bring to us Mitra and Varuna and Indra for our great defence.\n\np: Soma, for Indra's drink do thou, led by the men, well-wcaponcd and most gladdening, Flow on with greatest store of sweets.\n\np: Enter the Soma-holder, even Indra's heart, as rivers pass into the sea, acceptable to Mitra, Vayu, Varuna, the noblest Pillar of the heavens.","people":["Pavamana","Indra","Soma","Vayu","Mitra","Varuna","Bhaga","Etasa","Deva"],"places":["Heaven"],"things":["Steeds","Lord","Born","Rivers","Soma","Waters","Water","Glory","Shine","Light","Air","Wealth","Food","Men","Streams","Stream","Flow","Might","Juice","Rain","Wise","Mighty","Brave","Excellent","Friend","King","spoil","Life","Gifts","Amrta"],"groups":["Devas","Marut","Deities","Immortal"],"concepts":["Good","Life","Immortality","Immortal","Giver"],"hash":"md5-Y9qcnEej3GeeBgvfZ6T9Ww==","created":"Monday, April 8, 2024 - 10:51:56 PM"},{"id":"8b63db80-b66f-43c7-8ef1-5c8a4516872d","key":"09109","book":"09","title":"HYMN CIX. Indu Pavamana.","link":"https://indra.ai/rigveda/hymns/09109.html","text":"p: PLEASANT to Indra's Mitra's, pusan's Bhaga's taste, sped onward, Soma, with thy flowing stream.\n\np: Let Indra drink, O Soma, of thy juice for wisdom, and all Deities for strength.\n\np: So flow thou on as bright celestial juice, flow to the vast, immortal dwelling-place.\n\np: Flow onward, Soma, as a mighty sea, as Father of the Devas to every form.\n\np: Flow on, O Soma, radiant for the Devas and Heaven and Earth and bless our progeny.\n\np: Thou, bright Juice, art Sustainer of the sky: flow, mighty, in accordance with true Law.\n\np: Soma, flow splendid with thy copious stream through the great fleece as in the olden time.\n\np: Bom, led by men, joyous, and purified, let the Light-finder make all blessings flow:\n\np: Indu, while cleansed, keeping the people safe, shall give us all possessions for our own.\n\np: Flow on for wisdom, Soma, and for power, as a strong courser bathed, to win the prize.\n\np: The pressers purify this juice of thine, the Soma, for delight, and lofty fame\n\np: They deck the Gold-hued Infant, newlyborn, even Soma, Indu, in the sieve for Devas.\n\np: Fair Indu hath flowed on for rapturous joy, Sage for good fortune in the waters' lap.\n\np: He bears the beauteous name of Indra, that wherewith he overcame all demon foes.\n\np: All Deities are wont to drink of him, pressed by the men and blent with milk and curds.\n\np: He hath flowed forth with thousand streams effused, flowed ihsough the filter and the sheep's long wool.\n\np: With endless genial flow the Strong hath run, purified by the waters, blent with milk.\n\np: Pressed out with stones, directed by the men, go fortli, O Soma, into Indra's throat.\n\np: The mighty Soma with a thousand streams is poured to Indra through the cleansing sieve.\n\np: Indu they balm with pleasant milky juice for Indra, for the Steer, for his delight.\n\np: Lightly, for sheen, they cleanse thee for the Devas, gold-coloured, wearing water as thy robe.\n\np: Indu to Indra streams, yea, downward streams, Strong, flowing to the floods, and mingling -there.","people":["Indu","Indra","Soma","Mitra","Pusan","Bhaga"],"places":["Earth","Heaven","Sky"],"things":["Milk","Soma","Waters","Water","Light","Men","Streams","Stream","Flow","Juice","Joy","Gold","Strong","Mighty","Delight","Form","People","Sage"],"groups":["Devas","Deities","Father","Immortal","Progeny"],"concepts":["Celestial","Good","Blessings","Immortal","Strength","Wisdom"],"hash":"md5-9mKX4Wtp9V5P6oMtoRAY6g==","created":"Monday, April 8, 2024 - 10:51:56 PM"},{"id":"8b7ae2c0-2f1c-4eed-9e75-d869ab6e0e76","key":"09110","book":"09","title":"HYMN CX. Indu Pavamana.","link":"https://indra.ai/rigveda/hymns/09110.html","text":"p: O'ERPOWERING Vrtras, forward run to win great strength: Thou speedest to subdue like on exacting debts.\n\np: In thee, effused, O Soma, we rejoice ourselves for great supremacy in fight. Thou, pavamana, enterest into mighty deeds,\n\np: O Pavamana, thou didst generate the Sun, and spread the moisture out with power, Hasting to us with plenty vivified with milk.\n\np: Thou didst produce him, Deathless Deva.mid mortal men for maintenance of Law and lovely Amrta: Thou evermore hast moved making strength flow to us.\n\np: All round about hast thou with glory pierced for us as ’twere a never-failing well for men to drink, Borne on thy way in fragments from the presser's arms.\n\np: Then, beautifully radiant, certain Heavenly Ones, have sung to him their kinship as they looked thereon, and Savitar the Deva.opens as ’twere a stall.\n\np: Soma, the men of old whose grass was trimmed addressed the hymn to thee for mighty strength and for renown: So. Hero, urge us onward to heroic power.\n\np: They have drained forth from out the great depth of the sky the old primeval milk of heaven that claims the laud: They lifted up their voice to Indra athis birth.\n\np: As long as thou, O Pavamana, art above this earth and heaven and all existence in thy might, Thou standest like a Bull the chief amid the herd.\n\np: In the sheep's wool hath Indu Pavamana flowed, while they cleanse him, like a playful infant, Indu with hundred powers and hundred currents.\n\np: Holy and sweet, while purified, this Indu flows on, a wave of pleasant taste, to Indra. Strength-winner, Treasure-finder, Life. bestower.\n\np: So flow thou on, subduing our assailants, chasing the demons hard to beencountered, well-armed and conquering our . O Soma.","people":["Indu","Pavamana","Indu Pavamana","Indra","Soma","Savitar","Deva"],"places":["Earth","Heaven","Sky"],"things":["Milk","Soma","Glory","Sun","Treasure","Men","Flow","Might","Mighty","Grass","Chief","Voice","Hymn","Powers","Hero","Life","Amrta"],"groups":["Vrtras"],"concepts":["Birth","Life","Heavenly","Heroic","Holy","Strength","Winner"],"hash":"md5-HHXykhgpF5Hf90JZQwMflQ==","created":"Monday, April 8, 2024 - 10:51:56 PM"},{"id":"58cea166-6723-4974-bb5a-01cb19952682","key":"09111","book":"09","title":"HYMN CXI. Indu Pavamana.","link":"https://indra.ai/rigveda/hymns/09111.html","text":"p: WITH this his golden splendour purifying him, he with his own allies subdues all enemies, as Sara with his own allies. Cleansing himself with stream of juice he shines forth yellow-hued and red, when with the praisers he encompasses all forms, with praisers having seven mouths.\n\np: That treasure. of the Panis thou discoveredst; thou with thy mothers deckest thee in thine abode, with songs of worship in thine home. As ’twere from far, the hymn is heard, where holy songs resound in joy. He with the ruddy-hued, threefold hath won life-power, he, glittering, hath won life-power.\n\np: He moves intelligent, directed to the East. The very beauteous car rivals the beams of light, the beautiful celestial car. Hymns, lauding manly valour, came, inciting Indra to success, that y. May be unconquered, both thy bolt and thou, both be unconquered in the war.","people":["Indra"],"places":[],"things":["Worship","Light","Treasure","Stream","Juice","Joy","Home","Car","Hymn","Splendour","Songs","Life"],"groups":["Panis"],"concepts":["Celestial","Life","Beautiful","Holy"],"hash":"md5-C1gCDJ6WpqB5ZzzGtKj7VQ==","created":"Monday, April 8, 2024 - 10:51:56 PM"},{"id":"38e5463d-fe75-4d67-abd7-c146cd077788","key":"09112","book":"09","title":"HYMN CXII. Indu Pavamana.","link":"https://indra.ai/rigveda/hymns/09112.html","text":"p: WE all have various thoughts and plans, and diverse are the ways of men. The Brahman seeks the worshipper, wright seeks the cracked, and leech the maimed. Flow Indu, flow for Indra's sake.\n\np: The smith with ripe and seasoned plants, with feathers of the birds of air, with stones, and with enkindled flames, seeks him who hath a store of gold. Flow Indu, flow for Indra's sake.\n\np: A bard am I, my dad's a leech, mammy lays corn upon the stones. Striving for wealth, with varied plans, we follow our desires like kine. Flow Indu, flow for Indra's sake.\n\np: The horse would draw an easy car, gay hosts attract the laugh and jest. The male desires his mate's approach, the frog is eager for the flood, Flow Indu, flow for Indra's sake.","people":["Indu","Indra"],"places":[],"things":["Air","Wealth","Men","Flow","Gold","Car","Worshipper","Horse"],"groups":[],"concepts":[],"hash":"md5-2gBLp8E6OQU5mO8ouYcmew==","created":"Monday, April 8, 2024 - 10:51:56 PM"},{"id":"165394f5-2c1f-45b7-a826-4bef25092861","key":"09113","book":"09","title":"HYMN CXIII. Indu Pavamana.","link":"https://indra.ai/rigveda/hymns/09113.html","text":"p: LET Vrtra-subduing Indra drink Soma by Saryanavan's side, Storing up vigour in his heart, prepared to do heroic deeds. Flow Indu, flow for Indra's sake.\n\np: Lord of the Quarters, flow thou on, boon Soma, from Arjika land, Effused with ardour and with faith, and the true hymn of offering. Flow Indu, flow for Indra's sake.\n\np: Hither hath Surya's Daughter brought the wild Steer whom Parjanya nursed. Gandharvas have seized bold of him, and in the Soma laid the juice. Flow Indu, flow for Indra's sake.\n\np: Splendid by Law! declaring Law, truthspeaking, truthful in thy works, Enouncing faith, King Soma! thou, O Soma, whom thy maker decks. Flow Indu, flow for Indra's sake.\n\np: Together flow the meeting streams of him the Great and truly Strong. The juices of the juicy meet. Made pure by prayer, O Golden-hued, flow, Indu, flow for Indra's sake.\n\np: O Pavamana, where the priest, as he recites the rhythmic prayer, Lords it o’er Soma with the stone, with Soma bringing forth delight, flow, Indu, flow for Indra's sake.\n\np: O Pavarnana, place me in that deathless, undecaying world Wherein the light of heaven is set, and everlasting lustre shines. Flow Indu, flow for Indra's sake.\n\np: Make me immortal in that realm where dwells the King, Vivasvan's Son, Where is the secret shrine of heaven, where are those waters young and fresh. Flow Indu, flow for Indra's sake.\n\np: Make me immortal in that realm where they move even as they list, in the third sphere of inmost heaven where lucid worlds are full of light. Flow Indu, flow for Indra's sake.\n\np: Make me immortal in that realm of eager wish and strong desire, the region of the radiant Moon, where food and full delight are found. Flow Indu, flow for Indra's sake:\n\np: Make me immortal in that realm where happiness and transports, where Joys and felicities combine, and longing wishes are fulfilled. Flow Indu, flow for Indra's sake.","people":["Indu","Pavamana","Indra","Soma","King Soma","Vrtra","Vivasvan","Surya","Parjanya"],"places":["Arjika","Heaven"],"things":["Lord","Soma","Waters","Offering","Light","Moon","Boon","Food","Streams","Flow","Juice","Strong","Faith","Delight","Hymn","King"],"groups":["Gandharvas","Son","Immortal"],"concepts":["Heroic","Immortal","Offering","Truthful"],"hash":"md5-qiIYiGkSH+UAWbC+V3qv9w==","created":"Monday, April 8, 2024 - 10:51:56 PM"},{"id":"7492e668-884c-498a-a19f-65e38d2cf4b5","key":"09114","book":"09","title":"HYMN CXIV. Indu Pavamana.","link":"https://indra.ai/rigveda/hymns/09114.html","text":"p: THE man who waIketh as the Laws of Indu Pavamana bid. Men call him rich in children, him, O Soma, who hath met thy thought. Flow Indu, flow for Indra's sake.\n\np: Kasyapa, Rsi, lifting up thy voice with hymn-composers' lauds, pav reverence to King Soma born the Sovran Ruler of the plants. Flow Indu, flow for Indra's sake.\n\np: Seven regions have their several Suns; the ministering monks are seven; Seven are the Aditya Deities with these, O Soma, guard thou us. Flow Indu, flow for Indra's sake.\n\np: Guard us with this oblation which, King Soma, hath been dressed for thee.","people":["Indu","Pavamana","Indu Pavamana","Indra","Soma","King Soma","Aditya","Kasyapa"],"places":["Seven Regions"],"things":["Born","Reverence","Soma","Men","Flow","Voice","Hymn","King","call","Sovran Ruler"],"groups":["Deities","Man","Aditya Deities","Monks"],"concepts":[],"hash":"md5-ODLGH0MiodThGz0P8VH7ug==","created":"Monday, April 8, 2024 - 10:51:56 PM"}],"copyright":"©2023 Quinn Michaels (indra.ai). All rights reserved.","created":"Monday, April 8, 2024 - 10:51:52 PM"}